Workbook

Sheet СВОД
D1: Форма 1пс
A3: СВОДНАЯ СМЕТА
A4: на проектные работы и инженерные изыскания
A6: По объекту: | D6: «Реконструкция газопромысловых сооружений Степновской СПХГ»
A9: Наименование строительства и стадии проектирования | D9: Рабочая документация
A14: Наименование проектной организации-генерального проектировщика | D14: ОАО «СИБНЕФТЕТРАНСПРОЕКТ»
A16: Наименование организации заказчика | D16: ООО «Газпром проектирование»
A18: №пп | B18: Перечень выполняемых работ | E18: Ссылка на № смет по формам 2П, 3П | F18: Полная стоимость работ, руб.
F19: изыскательских | G19: проектных | H19: Всего
B20: Корректировка рабочей документации по этапу 3 (Объекты на площадке ГРП 2А)
A21: 1 | B21: Рабочая документация
A22: 1.1 | B22: Генеральный план | E22: =CONCATENATE("Смета №",A22) -> Смета №1.1 | G22: ='РД 1.1 ГП+'!R32 -> 1643029.3 | H22: =G22+F22 -> 1643029.3
A23: 1.2 | B23: Автомобильные дороги | E23: =CONCATENATE("Смета №",A23) -> Смета №1.2 | G23: ='1.2 Автодороги'!R28 -> 1188800 | H23: =G23+F23 -> 1188800
A24: 1.3 | B24: Технология производства | E24: =CONCATENATE("Сметы №",A24,".1","-№",A24,".2") -> Сметы №1.3.1-№1.3.2 | G24: ='1.3.1 ТХ'!R80+'1.3.2 ТХ+'!R52 -> 26164692 | H24: =G24+F24 -> 26164692
A25: 1.4 | B25: Отопление, вентиляция и кондиционирование | E25: =CONCATENATE("Смета №",A25) -> Смета №1.4 | G25: ='1.4 ОВ'!R61 -> 8441774 | H25: =G25+F25 -> 8441774
A26: 1.5 | B26: Автоматизированная система управления технологическим процессом (АСУ ТП) | E26: =CONCATENATE("Смета №",A26) -> Смета №1.5 | G26: ='1.5 АСУТП этап3'!Y174 -> 3980436 | H26: =G26+F26 -> 3980436
A27: 1.6 | B27: Автоматизированная система управления энергоснабжением (АСУ Э) | E27: =CONCATENATE("Смета №",A27) -> Смета №1.6 | G27: ='1.6 АСУЭ этап3'!Y174 -> 1426262 | H27: =G27+F27 -> 1426262
A28: 1.7 | B28: Автоматизация электрического освещения (АЭО) | E28: =CONCATENATE("Смета №",A28) -> Смета №1.7 | G28: ='1.7 АЭО этап3'!Y174 -> 760673 | H28: =G28+F28 -> 760673
A29: 1.8 | B29: Система противопожарной безопасности и автоматики (СПБА) | E29: =CONCATENATE("Смета №",A29) -> Смета №1.8 | G29: ='1.8 СПБА этап3'!Y174 -> 2977054 | H29: =G29+F29 -> 2977054
A30: 1.9 | B30: Сети связи и сигнализации | E30: =CONCATENATE("Смета №",A30) -> Смета №1.9 | G30: ='1.9 СС'!E243 -> 5598494.6 | H30: =G30+F30 -> 5598494.6
A31: 1.10 | B31: Электроснабжение | E31: =CONCATENATE("Смета №",A31) -> Смета №1.10 | G31: ='1.10 ЭС+'!E381 -> 30972770 | H31: =G31+F31 -> 30972770
A32: 1.11 | B32: Электрохимическая защита | E32: =CONCATENATE("Смета №",A32) -> Смета №1.11 | G32: ='1.11 ЭХЗ+'!E279 -> 22463924 | H32: =G32+F32 -> 22463924
A33: 1.12 | B33: Сети водоснабжения и канализации | E33: =CONCATENATE("Смета №",A33) -> Смета №1.12 | G33: ='1.12 ВК'!E97 -> 3867569.2 | H33: =G33+F33 -> 3867569.2
A34: 1.13 | B34: Линейная часть | E34: =CONCATENATE("Смета №",A34) -> Смета №1.13 | G34: ='1.13 ЛЧ+'!R94 -> 1105622.4 | H34: =G34+F34 -> 1105622.4
A35: 1.14 | B35: Проект бурения скважин | E35: =CONCATENATE("Смета №",A35) -> Смета №1.14 | G35: ='1.14 ПроектБур+'!G37 -> 526369.2 | H35: =G35+F35 -> 526369.2
A36: 1.15 | B36: =CONCATENATE("Итого ",B21,":") -> Итого Рабочая документация: | F36: =ROUND(SUM(F32:F33),2) -> 0 | G36: =ROUND(SUM(G22:G35),2) -> 1.1111747e+08 | H36: =ROUND(SUM(H22:H35),2) -> 1.1111747e+08
A38: 2 | B38: Итого по сводной смете: | F38: =F36 -> 0 | G38: =G36 -> 1.1111747e+08 | H38: =H36 -> 1.1111747e+08
A39: 3 | B39: Кроме того, НДС | E39: 0.22 | F39: =ROUND(($F$38) * (22/100),2) -> 0 | G39: =ROUND(G38*0.22,2) -> 24445844 | H39: =G39+F39 -> 24445844
A40: 4 | B40: Всего по сводной смете: | F40: =ROUND((SUM($F$38:$F$39)) * 1,2) -> 0 | G40: =ROUND((SUM($G$38:$G$39)) * 1,2) -> 1.3556331e+08 | H40: =G40+F40 -> 1.3556331e+08
A43: Примечание: Стоимость согласованного объема корректировки РД и СД (ГРП 2А) составляет 45 835 568,66 руб. с НДС 22%.Стоимость корректировки требующего согласования составляет 52 408 303,99 руб. с НДС 22% | I43: ** ГИП

Sheet РД 1.1 ГП+
E1: форма 2П, 707/пр
A3: =СВОД!E22 -> Смета №1.1
A4: на проектные (изыскательские) работы
A6: Наименование предприятия, здания, сооружения, стадии проектирования, этапа, вида проектных или изыскательских работ | F6: =СВОД!B22 -> Генеральный план
A8: Наименование проектной (изыскательской) организации | F8: =СВОД!D14 -> ОАО «СИБНЕФТЕТРАНСПРОЕКТ»
A10: Наименование организации заказчика | F10: =СВОД!D16 -> ООО «Газпром проектирование»
A12: № пп | B12: Наименование объекта проектирования или вида проектных работ | G12: Наименование, номера глав, таблиц, параграфов и пунктов МНЗ на проектные работы | K12: Расчет стоимости | O12: Стоимость, руб.
A13: 1 | B13: 2 | G13: 3 | K13: 4 | O13: 5
A14: Этап 3 (Объекты на площадке ГРП 2А) Разработка комплекта "4212.012.Р.3/0.0004.ГРП.02А.00000.000-ГП"
A15: 1 | B15: Генеральный план и транспорт в составе: вертикальная планировка, благоустройство и озеленение, внутриплощадочные автодороги, сводный план коммуникаций и сетей, участка. Площадь от 0.5 га до 10 га включительно. | G15: НЗ №849/пр Объекты газовой промышленности. 2023 г. Таблица 3.8. Объекты общетехнического назначения, п.10 A = 31.1 тыс.руб; B = 122.993 тыс.руб; Xзад = 5 (га); Количество = 1 | K15: Полный комплекс работ (100%): (A + B * Xзад) * Количество * Ктек * Кст (31 100 руб. + 122 993 руб. * 5) * 1 * 1,56 * 0.6 | O15: =ROUND((31100 + 122993 * 5) * 1 * 1.56 * 0.6, 2) -> 604716.84
B16: Коэффициенты
B17: Стадия: Рабочая документация | G17: Кст = 0.6
B18: инд.3кв.2026г.к 01.01.2022 на пр.раб. | G18: Ктек = 1,56 Письмо Минстроя России от 22.07.2026 №45358-ИФ/09
A19: Этап 3 (Объекты на площадке ГРП 2А) Разработка комплекта "4212.012.Р.3/0.0004.ГРП.02А.00000.000-ГП"
A20: 2 | B20: Инженерная подготовка территории. Объем отсыпки (намыва) грунта от 20 до 50 тыс.куб.м. включительно. | G20: НЗ №912/пр Инженерная защита территорий, зданий и сооружений от опасных геологических процессов. 2023 г. Таблица 3.2. Объекты регулирования стока поверхностных вод, водопонижения, п.1 A = 87,22 тыс.руб; B = 24.266 тыс.руб; Xзад = 50 (тыс.куб.м.); Количество = 1 | K20: (A + B * Xзад) * Количество * Ктек * Кст (87 100 руб. + 24 266 руб. * 50) * 1 * 1,56 * 0.6 | O20: =ROUND((87100 + 24266 * 50) * 1 * 1.56 * 0.6, 2) -> 1217174.4
B21: Коэффициенты
B22: Стадия: Рабочая документация | G22: Кст = 0.6
B23: инд.3кв.2026г.к 01.01.2022 на пр.раб. | G23: Ктек = 1,56 Письмо Минстроя России от 22.07.2026 №45358-ИФ/09
A24: Этап 3 (Шг.2А - Сеть газосборная ГРП 2А). Площадки БКЭС.
A25: 3 | B25: Генеральный план и транспорт в составе: вертикальная планировка, благоустройство и озеленение, внутриплощадочные автодороги, сводный план коммуникаций и сетей, участка. Площадь от 0.5 га до 10 га включительно. | G25: НЗ №849/пр Объекты газовой промышленности. 2023 г. Таблица 3.8. Объекты общетехнического назначения, п.10 A = 31.1 тыс.руб; B = 122.993 тыс.руб; Xмин = 0.5; Xзад = 0.4 (га); Количество = 1 | K25: Полный комплекс работ (100%): (A + B * (0.4 * Xмин + 0.6 * Xзад)) * Количество * Ктек * Кст (31 100 руб. + 122 993 руб. * (0.4 * 0.5 + 0.6 * 0.4)) * 1 * 1,56 * 0.6 | O25: =ROUND((31100 + 122993 * (0.4 * 0.5 + 0.6 * 0.4)) * 1 * 1.56 * 0.6, 2) -> 79763.04
B26: Коэффициенты
B27: Стадия: Рабочая документация | G27: Кст = 0.6
B28: инд.3кв.2026г.к 01.01.2022 на пр.раб. | G28: Ктек = 1,56 Письмо Минстроя России от 22.07.2026 №45358-ИФ/09
A29: 4 | B29: Итого по смете: | O29: =ROUND(SUM($O$15:$O$25),2) -> 1901654.3
A30: 5 | B30: Новое начисление | G30: К1 = 0.8 Коэффициент оптимизации ПАО "Газпром" («Порядок формирования стоимости проектно-изыскательских работ для строительства и реконструкции объектов ПАО «Газпром» от 28.12.2017г. п.5.41) (Ценообразующий) | K30: Коэф-т 1 от п.4 * 0.8 1 865 084.00 руб. * 1 * 0.8 | O30: =ROUND(($O$29) * 1 * 0.8,2) -> 1521323.4
A31: 6 | B31: Новое начисление | G31: К1 = 1.08 Коэффициент районный (Письмо ГК РФ по жилищной и строительной политике от 30 июня 1998 г. N 9-10-17/40) (Ценообразующий) | K31: Коэф-т 1 от п.5 * 1.08 1 492 067.20 руб. * 1 * 1.08 | O31: =ROUND(($O$30) * 1 * 1.08,2) -> 1643029.3
A32: 7 | B32: Всего по смете: | O32: =ROUND(($O$31),2) -> 1643029.3 | R32: =O32 -> 1643029.3

Sheet 1.2 Автодороги
E1: форма 2П, 707/пр
A3: =СВОД!E23 -> Смета №1.2
A4: на проектные (изыскательские) работы
A6: Наименование предприятия, здания, сооружения, стадии проектирования, этапа, вида проектных или изыскательских работ | F6: =СВОД!B23 -> Автомобильные дороги
A8: Наименование проектной (изыскательской) организации | F8: =СВОД!D14 -> ОАО «СИБНЕФТЕТРАНСПРОЕКТ»
A10: Наименование организации заказчика | F10: =СВОД!D16 -> ООО «Газпром проектирование»
A12: № пп | B12: Наименование объекта проектирования или вида проектных работ | G12: Наименование, номера глав, таблиц, параграфов и пунктов МНЗ на проектные работы | K12: Расчет стоимости | O12: Стоимость, руб.
A13: 1 | B13: 2 | G13: 3 | K13: 4 | O13: 5
A14: Этап 3 (Объекты на площадке ГРП 2А) ПАД.02А - Подъездная автомобильная дорога к ГРП 2А Разработка комплекта 4212.012.Р.3/0.0004.ПАД.02А.40712.000-АД
A15: 1 | B15: Автомобильные дороги технической категории IV. Категория сложности проектирования: 3. Протяженность от 0.2 до 0.5 километра включительно. | G15: НЗ №51/пр Строительство, реконструкция и капитальный ремонт автомобильных дорог, их конструктивных элементов и сооружений на них. 2025 г. Таблица 3.5. Автомобильные дороги технической категории IV, п.2.3 A = 290.1 тыс.руб; B = 1 856.633 тыс.руб; Протяженность дороги L = 0.31524 км; Количество = 1; | K15: (A + B * L) * Количество * Ктек * Кст (290 100 руб. + 1 856 633 руб. * 0.31524) * 1 * 1,40 * 0.6 | O15: =ROUND((290100 + 1856633 * 0.31524) * 1 * 1.4 * 0.6, 2) -> 735323.39
B16: Коэффициенты
B17: Стадия: Рабочая документация | G17: Кст = 0.6
B18: инд.3кв.2026г.к 01.01.2023 на пр.раб. | G18: Ктек = 1,40 Письмо Минстроя России от 22.07.2026 №45358-ИФ/09
A19: Этап 3 (Объекты на площадке ГРП 2А) ПАД.02А - Подъездная автомобильная дорога к ГРП 2А Разработка комплекта 4212.012.Р.3/0.0004.ПАД.02А.40712.000-АД
A20: 2 | B20: Примыкание автомобильных дорог в одном уровне с устройством переходно-скоростных полос движения, островков безопасности. Категория сложности проектирования: 3. | G20: НЗ №51/пр Строительство, реконструкция и капитальный ремонт автомобильных дорог, их конструктивных элементов и сооружений на них. 2025 г. Таблица 3.7. Развязки, п.2.3 A = 1 622.6 тыс.руб; Количество = 1 (объект) | K20: A * Количество * Ктек * Кст * K1 1 622 600 руб. * 1 * 1,40 * 0.6 * 0.47 | O20: =ROUND(1622600 * 1 * 1.4 * 0.6 * 0.47, 2) -> 640602.48
B21: Коэффициенты
B22: Стадия: Рабочая документация | G22: Кст = 0.6
B23: инд.3кв.2026г.к 01.01.2023 на пр.раб. | G23: Ктек = 1,40 Письмо Минстроя России от 22.07.2026 №45358-ИФ/09
B24: Пересечение (примыкание) автомобильных дорог в одном уровне определяется с корректирующим коэффициентом для примыканий без устройства переходно-скоростных полос | G24: K1 = 0.47 Табл.4, п.9 (Ценообразующий)
A25: 3 | B25: Итого по смете: | O25: =ROUND(SUM($O$15:$O$24),2) -> 1375925.9
A26: 4 | B26: Новое начисление | G26: К1 = 0.8 Коэффициент оптимизации ПАО "Газпром" («Порядок формирования стоимости проектно-изыскательских работ для строительства и реконструкции объектов ПАО «Газпром» от 28.12.2017г. п.5.41) (Ценообразующий) | K26: Коэф-т 1 от п.15 * 0.8 8 906 372.63 руб. * 1 * 0.8 | O26: =ROUND(($O$25) * 1 * 0.8,2) -> 1100740.7
A27: 5 | B27: Новое начисление | G27: К1 = 1.08 Коэффициент районный (Письмо ГК РФ по жилищной и строительной политике от 30 июня 1998 г. N 9-10-17/40) (Ценообразующий) | K27: Коэф-т 1 от п.16 * 1.08 7 125 098.10 руб. * 1 * 1.08 | O27: =ROUND(($O$26) * 1 * 1.08,2) -> 1188800
A28: 6 | B28: Всего по смете: | O28: =ROUND(($O$27),2) -> 1188800 | R28: =O28 -> 1188800

Sheet 1.3.1 ТХ
E1: форма 2П, 707/пр
A3: =СВОД!E24 -> Сметы №1.3.1-№1.3.2
A4: на проектные (изыскательские) работы
A6: Наименование предприятия, здания, сооружения, стадии проектирования, этапа, вида проектных или изыскательских работ | F6: =СВОД!B24 -> Технология производства
A8: Наименование проектной (изыскательской) организации | F8: =СВОД!D14 -> ОАО «СИБНЕФТЕТРАНСПРОЕКТ»
A10: Наименование организации заказчика | F10: =СВОД!D16 -> ООО «Газпром проектирование»
A12: № пп | B12: Наименование объекта проектирования или вида проектных работ | G12: Наименование, номера глав, таблиц, параграфов и пунктов МНЗ на проектные работы | K12: Расчет стоимости | O12: Стоимость, руб.
A13: 1 | B13: 2 | G13: 3 | K13: 4 | O13: 5
A14: Этап 3 (Объекты на площадке ГРП 2А)
A15: 001 - Технологический корпус №1
A16: 1 | B16: Установка первичной сепарации газа производительностью от 10 млн.куб.м/сут до 60 млн.куб.м/сут включительно | G16: НЗ №849/пр Объекты газовой промышленности. 2023 г. Таблица 3.7. Объекты подготовки газа, газового конденсата (УКПГ, УППГ, УПТГ, ГС), п.2 A = 1 493.1 тыс. руб.B = 22.794 тыс. руб.; Хзад = 10.95 (млн.куб.м/сут); Количество = 1 | K16: (A + B * Xзад) * Количество * Ктек * Кст (1 493 100 руб. + 22 794 руб. * 10.95) * 1 * 1,56 * 0.6 | O16: =ROUND((1493100 + 22794 * 10.95) * 1 * 1.56 * 0.6, 2) -> 1631161.9
B17: Коэффициенты
B18: Стадия: Рабочая документация | G18: Кст = 0.6
B19: инд.3кв.2026г.к 01.01.2022 на пр.раб. | G19: Ктек = 1,56 Письмо Минстроя России от 22.07.2026 №45358-ИФ/09
A20: 002 - Технологический корпус №2
A21: 2 | B21: Установка первичной сепарации газа производительностью от 10 млн.куб.м/сут до 60 млн.куб.м/сут включительно | G21: НЗ №849/пр Объекты газовой промышленности. 2023 г. Таблица 3.7. Объекты подготовки газа, газового конденсата (УКПГ, УППГ, УПТГ, ГС), п.2 A = 1 493.1 тыс. руб.B = 22.794 тыс. руб.; Хзад = 10.95 (млн.куб.м/сут); Количество = 1 | K21: (A + B * Xзад) * Количество * Ктек * Кст (1 493 100 руб. + 22 794 руб. * 10.95) * 1 * 1,56 * 0.6 | O21: =ROUND((1493100 + 22794 * 10.95) * 1 * 1.56 * 0.6, 2) -> 1631161.9
B22: Коэффициенты
B23: Стадия: Рабочая документация | G23: Кст = 0.6
B24: инд.3кв.2026г.к 01.01.2022 на пр.раб. | G24: Ктек = 1,56 Письмо Минстроя России от 22.07.2026 №45358-ИФ/09
A25: 004 - Резервуар, емкость дренажно-аварийная
A26: 3 | B26: Установка дренажной емкости без погружного насоса объемом до 50 куб.м | G26: НЗ №849/пр Объекты газовой промышленности. 2023 г. Таблица 3.7. Объекты подготовки газа, газового конденсата (УКПГ, УППГ, УПТГ, ГС), п.40 A = 699.9 тыс. руб. Количество = 1 (объект) | K26: A * Количество * Ктек * Кст 699 900 руб. * 1 * 1,56 * 0.6 | O26: =ROUND(699900 * 1 * 1.56 * 0.6, 2) -> 655106.4
B27: Коэффициенты
B28: Стадия: Рабочая документация | G28: Кст = 0.6
B29: инд.3кв.2026г.к 01.01.2022 на пр.раб. | G29: Ктек = 1,56 Письмо Минстроя России от 22.07.2026 №45358-ИФ/09
A30: 005 - Резервуар, емкость расходная метанола
A31: 4 | B31: Промежуточный склад ГЖ и ЛВЖ из горизонтальных стальных резервуаров объемом от 50 куб.м до 200 куб.м включительно | G31: НЗ №849/пр Объекты газовой промышленности. 2023 г. Таблица 3.7. Объекты подготовки газа, газового конденсата (УКПГ, УППГ, УПТГ, ГС), п.31 A = 467.7 тыс. руб.B = 0.398 тыс. руб.; Хзад = 100 (куб.м); Количество = 1 | K31: (A + B * Xзад) * Количество * Ктек * Кст (467 700 руб. + 398 руб. * 100) * 1 * 1,56 * 0.6 | O31: =ROUND((467700 + 398 * 100) * 1 * 1.56 * 0.6, 2) -> 475020
B32: Коэффициенты
B33: Стадия: Рабочая документация | G33: Кст = 0.6
B34: инд.3кв.2026г.к 01.01.2022 на пр.раб. | G34: Ктек = 1,56 Письмо Минстроя России от 22.07.2026 №45358-ИФ/09
A35: 006 - Резервуар, емкость дренажно-аварийная
A36: 5 | B36: Установка дренажной емкости без погружного насоса объемом до 50 куб.м | G36: НЗ №849/пр Объекты газовой промышленности. 2023 г. Таблица 3.7. Объекты подготовки газа, газового конденсата (УКПГ, УППГ, УПТГ, ГС), п.40 A = 699.9 тыс. руб. Количество = 1 (объект) | K36: A * Количество * Ктек * Кст 699 900 руб. * 1 * 1,56 * 0.6 | O36: =ROUND(699900 * 1 * 1.56 * 0.6, 2) -> 655106.4
B37: Коэффициенты
B38: Стадия: Рабочая документация | G38: Кст = 0.6
B39: инд.3кв.2026г.к 01.01.2022 на пр.раб. | G39: Ктек = 1,56 Письмо Минстроя России от 22.07.2026 №45358-ИФ/09
A40: 008 - Станция насосная
A41: 6 | B41: Установка приема, смешения и подачи ингибитора в скважины производительностью от 20 л/час до 200 л/час включительно | G41: НЗ №849/пр Объекты газовой промышленности. 2023 г. Таблица 3.7. Объекты подготовки газа, газового конденсата (УКПГ, УППГ, УПТГ, ГС), п.20 A = 114.1 тыс. руб.B = 19.581 тыс. руб.; Xмакс = 200; Хзад = 1000 (л/час); Количество = 1 | K41: (A + B * (0.4 * Xмакс + 0.6 * Xзад)) * Количество * Ктек * Кст (114 100 руб. + 19 581 руб. * (0.4 * 200 + 0.6 * 1000)) * 1 * 1,56 * 0.6 | O41: =ROUND((114100 + 19581 * (0.4 * 200 + 0.6 * 1000)) * 1 * 1.56 * 0.6, 2) -> 12569712
B42: Коэффициенты
B43: Стадия: Рабочая документация | G43: Кст = 0.6
B44: инд.3кв.2026г.к 01.01.2022 на пр.раб. | G44: Ктек = 1,56 Письмо Минстроя России от 22.07.2026 №45358-ИФ/09
A45: 016 - Склад дизтоплива расходный V=10 м3
A46: 7 | B46: Промежуточный склад ГЖ и ЛВЖ из горизонтальных стальных резервуаров объемом от 50 куб.м до 200 куб.м включительно | G46: НЗ №849/пр Объекты газовой промышленности. 2023 г. Таблица 3.7. Объекты подготовки газа, газового конденсата (УКПГ, УППГ, УПТГ, ГС), п.31 A = 467.7 тыс. руб.B = 0.398 тыс. руб.; Xмин = 50; Хзад = 10 (куб.м); Количество = 1 | K46: (A + B * (0.4 * Xмин + 0.6 * (Xмин / 2))) * Количество * Кпон * Ктек * Кст (467 700 руб. + 398 руб. * (0.4 * 50 + 0.6 * (50 / 2))) * 1 * 0.4 * 1,56 * 0.6 | O46: =ROUND((467700 + 398 * (0.4 * 50 + 0.6 * (50 / 2))) * 1 * 0.4 * 1.56 * 0.6, 2) -> 180322.27
B47: Коэффициенты
B48: Стадия: Рабочая документация | G48: Кст = 0.6
B49: инд.3кв.2026г.к 01.01.2022 на пр.раб. | G49: Ктек = 1,56 Письмо Минстроя России от 22.07.2026 №45358-ИФ/09
B50: К'пон = Xзад / (0.5 * Xмин) | G50: К'пон = 0.4 понижающий коэффициент, учитывающий разницу в трудоемкости работ по проектируемому объекту и объекту аналогу. (Методика 707/пр п.131(3)) (Ценообразующий)
A51: 019 - Здание операторной
A52: 8 | B52: Центральной пункт управления, диспетчерская, операторная, СЭБ, СЭРБ. Объем от 100 куб.м до 1000 куб.м включительно. | G52: НЗ №849/пр Объекты газовой промышленности. 2023 г. Таблица 3.8. Объекты общетехнического назначения, п.1 A = 1 007.2 тыс.руб; B = 1.085 тыс.руб; Xзад = 907.2 (куб.м); Количество = 1 | K52: (A + B * Xзад) * Количество * Ктек * Кст (1 007 200 руб. + 1 085 руб. * 907.2) * 1 * 1,56 * 0.6 | O52: =ROUND((1007200 + 1085 * 907.2) * 1 * 1.56 * 0.6, 2) -> 1864055.2
B53: Коэффициенты
B54: Стадия: Рабочая документация | G54: Кст = 0.6
B55: инд.3кв.2026г.к 01.01.2022 на пр.раб. | G55: Ктек = 1,56 Письмо Минстроя России от 22.07.2026 №45358-ИФ/09
A56: 024 - Свеча Ду 800мм, Н=30м
A57: 9 | B57: Установка факела вертикального производительностью от 7.5 млн.куб.м/сут до 25 млн.куб.м/сут включительно | G57: НЗ №849/пр Объекты газовой промышленности. 2023 г. Таблица 3.7. Объекты подготовки газа, газового конденсата (УКПГ, УППГ, УПТГ, ГС), п.23 A = 1 320.8 тыс. руб.B = 9.459 тыс. руб.; Xмин = 7.5; Хзад = 4.7088 (млн.куб.м/сут); Количество = 1 | K57: (A + B * (0.4 * Xмин + 0.6 * Xзад)) * Количество * Ктек * Кст (1 320 800 руб. + 9 459 руб. * (0.4 * 7.5 + 0.6 * 4.7088)) * 1 * 1,56 * 0.6 | O57: =ROUND((1320800 + 9459 * (0.4 * 7.5 + 0.6 * 4.7088)) * 1 * 1.56 * 0.6, 2) -> 1287843.6
B58: Коэффициенты
B59: Стадия: Рабочая документация | G59: Кст = 0.6
B60: инд.3кв.2026г.к 01.01.2022 на пр.раб. | G60: Ктек = 1,56 Письмо Минстроя России от 22.07.2026 №45358-ИФ/09
A61: 025 - Установка свечных сепараторов
A62: 10 | B62: Установка факельного сепаратора и сборника жидкости производительностью по сбрасываемому газу от 7.5 млн.куб.м/сут до 25 млн.куб.м/сут включительно | G62: НЗ №849/пр Объекты газовой промышленности. 2023 г. Таблица 3.7. Объекты подготовки газа, газового конденсата (УКПГ, УППГ, УПТГ, ГС), п.22 A = 415.6 тыс. руб.B = 32.687 тыс. руб.; Xмин = 7.5; Хзад = 4.7088 (млн.куб.м/сут); Количество = 1 | K62: (A + B * (0.4 * Xмин + 0.6 * Xзад)) * Количество * Ктек * Кст (415 600 руб. + 32 687 руб. * (0.4 * 7.5 + 0.6 * 4.7088)) * 1 * 1,56 * 0.6 | O62: =ROUND((415600 + 32687 * (0.4 * 7.5 + 0.6 * 4.7088)) * 1 * 1.56 * 0.6, 2) -> 567226.23
B63: Коэффициенты
B64: Стадия: Рабочая документация | G64: Кст = 0.6
B65: инд.3кв.2026г.к 01.01.2022 на пр.раб. | G65: Ктек = 1,56 Письмо Минстроя России от 22.07.2026 №45358-ИФ/09
A66: 031 - Ресиверы азота
A67: 11 | B67: Станция азотная производительностью от 500 куб.м/час до 1000 куб.м/час включительно | G67: НЗ №849/пр Объекты газовой промышленности. 2023 г. Таблица 3.7. Объекты подготовки газа, газового конденсата (УКПГ, УППГ, УПТГ, ГС), п.35 A = 6 131.1 тыс. руб.B = 4.907 тыс. руб.; Xмин = 500; Хзад = 150 (куб.м/час); Количество = 1 | K67: (A + B * (0.4 * Xмин + 0.6 * (Xмин / 2))) * Количество * Кпон * Ктек * Кст (6 131 100 руб. + 4 907 руб. * (0.4 * 500 + 0.6 * (500 / 2))) * 1 * 0.6 * 1,56 * 0.6 | O67: =ROUND((6131100 + 4907 * (0.4 * 500 + 0.6 * (500 / 2))) * 1 * 0.6 * 1.56 * 0.6, 2) -> 4407745.7
B68: Коэффициенты
B69: Стадия: Рабочая документация | G69: Кст = 0.6
B70: инд.3кв.2026г.к 01.01.2022 на пр.раб. | G70: Ктек = 1,56 Письмо Минстроя России от 22.07.2026 №45358-ИФ/09
B71: К'пон = Xзад / (0.5 * Xмин) | G71: К'пон = 0.6 понижающий коэффициент, учитывающий разницу в трудоемкости работ по проектируемому объекту и объекту аналогу. (Методика 707/пр п.131(3)) (Ценообразующий)
A72: Сети внутриплощадочные (ТК1=0,2 км, ТК2=0,25км, ТК3= 0,35км, ТК4=0,37км)
A73: 12 | B73: Межцеховые и внеплощадочные сети на эстакадах (теплогазоматериалопроводы). Протяженность от 1 км до 5 км включительно. | G73: НЗ №849/пр Объекты газовой промышленности. 2023 г. Таблица 3.7. Объекты подготовки газа, газового конденсата (УКПГ, УППГ, УПТГ, ГС), п.25 A = 3 051.8 тыс.руб; B = 946.944 тыс.руб; Xзад = 1.17 (км); Количество = 1 | K73: (A + B * Xзад) * Количество * Ктек * Кст (3 051 800 руб. + 946 944 руб. * 1.17) * 1 * 1,56 * 0.6 | O73: =ROUND((3051800 + 946944 * 1.17) * 1 * 1.56 * 0.6, 2) -> 3893502.1
B74: Коэффициенты
B75: Стадия: Рабочая документация | G75: Кст = 0.6
B76: инд.3кв.2026г.к 01.01.2022 на пр.раб. | G76: Ктек = 1,56 Письмо Минстроя России от 22.07.2026 №45358-ИФ/09
A77: 13 | B77: Итого по смете: | O77: =ROUND(SUM($O$16:$O$73),2) -> 29817964
A78: 14 | B78: Новое начисление | G78: К1 = 0.8 Коэффициент оптимизации ПАО "Газпром" («Порядок формирования стоимости проектно-изыскательских работ для строительства и реконструкции объектов ПАО «Газпром» от 28.12.2017г. п.5.41) (Ценообразующий) | K78: Коэф-т 1 от п.13 * 0.8 29 244 541.79 руб. * 1 * 0.8 | O78: =ROUND(($O$77) * 1 * 0.8,2) -> 23854371
A79: 15 | B79: Новое начисление | G79: К1 = 1.08 Коэффициент районный (Письмо ГК РФ по жилищной и строительной политике от 30 июня 1998 г. N 9-10-17/40) (Ценообразующий) | K79: Коэф-т 1 от п.14 * 1.08 23 395 633.43 руб. * 1 * 1.08 | O79: =ROUND(($O$78) * 1 * 1.08,2) -> 25762721
A80: 16 | B80: Всего по смете: | O80: =ROUND(($O$79),2) -> 25762721 | R80: =O80 -> 25762721

Sheet 1.3.2 ТХ+
E1: форма 2П, 707/пр
A3: Смета №1.3.2
A4: на проектные (изыскательские) работы
A6: Наименование предприятия, здания, сооружения, стадии проектирования, этапа, вида проектных или изыскательских работ | F6: ='1.3.1 ТХ'!F6:P6 -> Технология производства
A8: Наименование проектной (изыскательской) организации | F8: =СВОД!D14 -> ОАО «СИБНЕФТЕТРАНСПРОЕКТ»
A10: Наименование организации заказчика | F10: =СВОД!D16 -> ООО «Газпром проектирование»
A12: № пп | B12: Наименование объекта проектирования или вида проектных работ | G12: Наименование, номера глав, таблиц, параграфов и пунктов МНЗ на проектные работы | K12: Расчет стоимости | O12: Стоимость, руб.
A13: 1 | B13: 2 | G13: 3 | K13: 4 | O13: 5
A14: Этап 3
A15: ВТМ.2А - Метанолопровод внутрипромысловый к ГРП.2А
A16: 4212.00.Р.04.ВТМ.2А.000.Л.000 Инв номер 783977
A17: 1 | B17: Трубопроводы (межцеховые и шлейфы) диаметром до 300 мм. Протяженность от 1 км до 5 км включительно. | G17: НЗ №849/пр Объекты газовой промышленности. 2023 г. Таблица 3.6. Объекты сбора газа (шлейфы, коллекторы и межцеховые трубопроводы), п.1 A = 61.9 тыс.руб; B = 15.484 тыс.руб; Xзад = 1.485 (км); Количество = 1 | K17: (A + B * Xзад) * Количество * Ктек * Кст (61 900 руб. + 15 484 руб. * 1.485) * 1 * 1.56 * 0.6 | O17: =ROUND((61900 + 15484 * 1.485) * 1 * 1.56 * 0.6, 2) -> 79460.54
B18: Коэффициенты
B19: Стадия: Рабочая документация | G19: Кст = 0.6
B20: инд.3кв.2026г.к 01.01.2022 на пр.раб. | G20: Ктек = 1.56 Письмо Минстроя России от 23.07.2026 №45358-ИФ/09
A21: Г3.2А - Межпоселковый газопровод высокого давления II категории от коллектора ПППГ-ГРП5 до ГРП 2А
A22: 4212.00.Р.04.Г3.2А.000.ГСН.000 Инв номер 784436
A23: 2 | B23: Трубопроводы (межцеховые и шлейфы) диаметром до 300 мм. Протяженность от 1 км до 5 км включительно. | G23: НЗ №849/пр Объекты газовой промышленности. 2023 г. Таблица 3.6. Объекты сбора газа (шлейфы, коллекторы и межцеховые трубопроводы), п.1 A = 61.9 тыс.руб; B = 15.484 тыс.руб; Xзад = 2.42 (км); Количество = 1 | K23: (A + B * Xзад) * Количество * Ктек * Кст (61 900 руб. + 15 484 руб. * 2.42) * 1 * 1.56 * 0.6 | O23: =ROUND((61900 + 15484 * 2.42) * 1 * 1.56 * 0.6, 2) -> 93011.52
B24: Коэффициенты
B25: Стадия: Рабочая документация | G25: Кст = 0.6
B26: инд.3кв.2026г.к 01.01.2022 на пр.раб. | G26: Ктек = 1.56 Письмо Минстроя России от 23.07.2026 №45358-ИФ/09
A27: Внутриплощадочные сети 4212.00.Р.04 - Реконструкция газопромысловых сооружений Степновской СПХГ.
A28: 4212.012.Р.3/0.0004.ГРП.02А.31610.000-ТХ
A29: 3 | B29: Трубопроводы (межцеховые и шлейфы) диаметром до 300 мм. Протяженность от 1 км до 5 км включительно. | G29: НЗ №849/пр Объекты газовой промышленности. 2023 г. Таблица 3.6. Объекты сбора газа (шлейфы, коллекторы и межцеховые трубопроводы), п.1 A = 61.9 тыс.руб; B = 15.484 тыс.руб; Xмин = 1; Xзад = 0.235 (км); Количество = 1 | K29: (A + B * (0.4 * Xмин + 0.6 * (Xмин / 2))) * Количество * Кпон * Ктек * Кст (61 900 руб. + 15 484 руб. * (0.4 * 1 + 0.6 * (1 / 2))) * 1 * 0.47 * 1.56 * 0.6 | O29: =ROUND((61900 + 15484 * (0.4 * 1 + 0.6 * (1 / 2))) * 1 * 0.47 * 1.56 * 0.6, 2) -> 31999.25
B30: Коэффициенты
B31: Стадия: Рабочая документация | G31: Кст = 0.6
B32: инд.3кв.2026г.к 01.01.2022 на пр.раб. | G32: Ктек = 1.56 Письмо Минстроя России от 23.07.2026 №45358-ИФ/09
B33: К'пон = Xзад / (0.5 * Xмин) | G33: К'пон = 0.47 понижающий коэффициент, учитывающий разницу в трудоемкости работ по проектируемому объекту и объекту аналогу. (Методика 707/пр п.131(3)) (Ценообразующий)
A34: 4212.00.Р.04.ВТГз.2А.000.Л.000
A35: 4 | B35: Трубопроводы (межцеховые и шлейфы) диаметром до 300 мм. Протяженность от 1 км до 5 км включительно. | G35: НЗ №849/пр Объекты газовой промышленности. 2023 г. Таблица 3.6. Объекты сбора газа (шлейфы, коллекторы и межцеховые трубопроводы), п.1 A = 61.9 тыс.руб; B = 15.484 тыс.руб; Xзад = 2 (км); Количество = 1 | K35: (A + B * Xзад) * Количество * Ктек * Кст (61 900 руб. + 15 484 руб. * 2) * 1 * 1.56 * 0.6 | O35: =ROUND((61900 + 15484 * 2) * 1 * 1.56 * 0.6, 2) -> 86924.45
B36: Коэффициенты
B37: Стадия: Рабочая документация | G37: Кст = 0.6
B38: инд.3кв.2026г.к 01.01.2022 на пр.раб. | G38: Ктек = 1.56 Письмо Минстроя России от 23.07.2026 №45358-ИФ/09
A39: 4212.00.Р.04.ВТК.ГРП.2А.000.Л.000
A40: 5 | B40: Трубопроводы (межцеховые и шлейфы) диаметром до 300 мм. Протяженность от 1 км до 5 км включительно. | G40: НЗ №849/пр Объекты газовой промышленности. 2023 г. Таблица 3.6. Объекты сбора газа (шлейфы, коллекторы и межцеховые трубопроводы), п.1 A = 61.9 тыс.руб; B = 15.484 тыс.руб; Xзад = 2 (км); Количество = 1 | K40: (A + B * Xзад) * Количество * Ктек * Кст (61 900 руб. + 15 484 руб. * 2) * 1 * 1.56 * 0.6 | O40: =ROUND((61900 + 15484 * 2) * 1 * 1.56 * 0.6, 2) -> 86924.45
B41: Коэффициенты
B42: Стадия: Рабочая документация | G42: Кст = 0.6
B43: инд.3кв.2026г.к 01.01.2022 на пр.раб. | G43: Ктек = 1.56 Письмо Минстроя России от 23.07.2026 №45358-ИФ/09
A44: 4212.00.Р.04.ГК.2 А.000.Л.000
A45: 6 | B45: Трубопроводы (межцеховые и шлейфы) диаметром до 300 мм. Протяженность от 1 км до 5 км включительно. | G45: НЗ №849/пр Объекты газовой промышленности. 2023 г. Таблица 3.6. Объекты сбора газа (шлейфы, коллекторы и межцеховые трубопроводы), п.1 A = 61.9 тыс.руб; B = 15.484 тыс.руб; Xзад = 2 (км); Количество = 1 | K45: (A + B * Xзад) * Количество * Ктек * Кст (61 900 руб. + 15 484 руб. * 2) * 1 * 1.56 * 0.6 | O45: =ROUND((61900 + 15484 * 2) * 1 * 1.56 * 0.6, 2) -> 86924.45
B46: Коэффициенты
B47: Стадия: Рабочая документация | G47: Кст = 0.6
B48: инд.3кв.2026г.к 01.01.2022 на пр.раб. | G48: Ктек = 1.56 Письмо Минстроя России от 23.07.2026 №45358-ИФ/09
A49: 7 | B49: Итого по смете: | O49: =ROUND(SUM($O$17:$O$45),2) -> 465244.66
A50: 8 | B50: Новое начисление | G50: К1 = 0.8 Коэффициент оптимизации ПАО "Газпром" («Порядок формирования стоимости проектно-изыскательских работ для строительства и реконструкции объектов ПАО «Газпром» от 28.12.2017г. п.5.41) (Ценообразующий) | K50: Коэф-т 1 от п.7 * 0.8 465 244.66 руб. * 1 * 0.8 | O50: =ROUND(($O$49) * 1 * 0.8,2) -> 372195.73
A51: 9 | B51: Новое начисление | G51: К1 = 1.08 Коэффициент районный (Письмо ГК РФ по жилищной и строительной политике от 30 июня 1998 г. N 9-10-17/40) (Ценообразующий) | K51: Коэф-т 1 от п.8 * 1.08 372 195.73 руб. * 1 * 1.08 | O51: =ROUND(($O$50) * 1 * 1.08,2) -> 401971.39
A52: 10 | B52: Всего по смете: | O52: =ROUND(($O$51),2) -> 401971.39 | R52: =O52 -> 401971.39

Sheet 1.4 ОВ
E1: форма 2П, 707/пр
A3: =СВОД!E25 -> Смета №1.4
A4: на проектные (изыскательские) работы
A6: Наименование предприятия, здания, сооружения, стадии проектирования, этапа, вида проектных или изыскательских работ | F6: =СВОД!B25 -> Отопление, вентиляция и кондиционирование
A8: Наименование проектной (изыскательской) организации | F8: =СВОД!D14 -> ОАО «СИБНЕФТЕТРАНСПРОЕКТ»
A10: Наименование организации заказчика | F10: =СВОД!D16 -> ООО «Газпром проектирование»
A12: № пп | B12: Наименование объекта проектирования или вида проектных работ | G12: Наименование, номера глав, таблиц, параграфов и пунктов МНЗ на проектные работы | K12: Расчет стоимости | O12: Стоимость, руб.
A13: 1 | B13: 2 | G13: 3 | K13: 4 | O13: 5
A14: Этап 3 (Объекты на площадке ГРП 2А)
A15: 4212.012.Р.3/0.0004.ГРП.02А.31201.025-ТС
A16: 1 | B16: Внутриплощадочные инженерные сети. Тепло-, газо-, материалопроводы на эстакадах. Длина трассы до 0.1 км. | G16: Объекты нефтеперерабатывающей и нефтехимической промышленности. 2015 г. Таблица 8. Объекты подсобно-производственного, вспомогательного и общезаводского назначения, внутриплощадочные инженерные сети, схема планировочной организации земельного участка, п.2.3 A = 1 695.18 тыс.руб; B = 1 100.96 тыс.руб; Xмин = 0.1; Xзад = 0.015 (км); Количество = 1 | K16: (A + B * (0.4 * Xмин + 0.6 * (Xмин / 2))) * Количество * Кпон * Ктек * Кст * K1 (1 695 180 руб. + 1 100 960 руб. * (0.4 * 0.1 + 0.6 * (0.1 / 2))) * 1 * 0.3 * 7,22 * 0.6 * 0.5 * 0.7 | O16: =ROUND((1695180 + 1100960 * (0.4 * 0.1 + 0.6 * (0.1 / 2))) * 1 * 0.3 * 7.22 * 0.6 * 0.5 * 0.7, 2) -> 806124.36
B17: Коэффициенты
B18: Стадия: Рабочая документация | G18: Кст = 0.6
B19: инд.3кв.2026г.к 01.01.2001 на пр.раб. | G19: Ктек = 7,22 Письмо Минстроя России от 22.07.2026 №45358-ИФ/09
B20: К'пон = Xзад / (0.5 * Xмин) | G20: К'пон = 0.3 понижающий коэффициент, учитывающий разницу в трудоемкости работ по проектируемому объекту и объекту аналогу. (Методика 707/пр п.131(3)) (Ценообразующий)
B21: При проектировании трассы с 1-5 трубопроводами вводится коэффициент | G21: K1 = 0.5 Глава 2.5, п.2.5.6 (Ценообразующий)
B22: Исключенные разделы документации
B23: 1. Схема планировочной организации земельного участка | G23: 5%
B24: 2. Архитектурные решения. Конструктивные и объемно-планировочные решения | G24: 25%
A25: 4212.012.Р.3/0.0004.ГРП.02А.31111.004-ТС
A26: 2 | B26: Внутриплощадочные инженерные сети. Тепло-, газо-, материалопроводы на эстакадах. Длина трассы до 0.1 км. | G26: Объекты нефтеперерабатывающей и нефтехимической промышленности. 2015 г. Таблица 8. Объекты подсобно-производственного, вспомогательного и общезаводского назначения, внутриплощадочные инженерные сети, схема планировочной организации земельного участка, п.2.3 A = 1 695.18 тыс.руб; B = 1 100.96 тыс.руб; Xмин = 0.1; Xзад = 0.01 (км); Количество = 1 | K26: (A + B * (0.4 * Xмин + 0.6 * (Xмин / 2))) * Количество * Кпон * Ктек * Кст * K1 (1 695 180 руб. + 1 100 960 руб. * (0.4 * 0.1 + 0.6 * (0.1 / 2))) * 1 * 0.2 * 7,22 * 0.6 * 0.5 * 0.7 | O26: =ROUND((1695180 + 1100960 * (0.4 * 0.1 + 0.6 * (0.1 / 2))) * 1 * 0.2 * 7.22 * 0.6 * 0.5 * 0.7, 2) -> 537416.24
B27: Коэффициенты
B28: Стадия: Рабочая документация | G28: Кст = 0.6
B29: инд.3кв.2026г.к 01.01.2001 на пр.раб. | G29: Ктек = 7,22 Письмо Минстроя России от 22.07.2026 №45358-ИФ/09
B30: К'пон = Xзад / (0.5 * Xмин) | G30: К'пон = 0.2 понижающий коэффициент, учитывающий разницу в трудоемкости работ по проектируемому объекту и объекту аналогу. (Методика 707/пр п.131(3)) (Ценообразующий)
B31: При проектировании трассы с 1-5 трубопроводами вводится коэффициент | G31: K1 = 0.5 Глава 2.5, п.2.5.6 (Ценообразующий)
B32: Исключенные разделы документации
B33: 1. Схема планировочной организации земельного участка | G33: 5%
B34: 2. Архитектурные решения. Конструктивные и объемно-планировочные решения | G34: 25%
A35: 4212.00.Р.04.ГРП.2А.000.ТК2.000
A36: 3 | B36: Внутриплощадочные инженерные сети. Тепло-, газо-, материалопроводы на эстакадах. Длина трассы свыше 0.1 до 0.3 км. | G36: Объекты нефтеперерабатывающей и нефтехимической промышленности. 2015 г. Таблица 8. Объекты подсобно-производственного, вспомогательного и общезаводского назначения, внутриплощадочные инженерные сети, схема планировочной организации земельного участка, п.2.4 A = 1 700.5 тыс.руб; B = 1 047.8 тыс.руб; Xзад = 0.25 (км); Количество = 1 | K36: (A + B * Xзад) * Количество * Ктек * Кст * K1 (1 700 500 руб. + 1 047 800 руб. * 0.25) * 1 * 7,22 * 0.6 * 0.5 * 0.7 | O36: =ROUND((1700500 + 1047800 * 0.25) * 1 * 7.22 * 0.6 * 0.5 * 0.7, 2) -> 2975466.7
B37: Коэффициенты
B38: Стадия: Рабочая документация | G38: Кст = 0.6
B39: инд.3кв.2026г.к 01.01.2001 на пр.раб. | G39: Ктек = 7,22 Письмо Минстроя России от 22.07.2026 №45358-ИФ/09
B40: При проектировании трассы с 1-5 трубопроводами вводится коэффициент | G40: K1 = 0.5 Глава 2.5, п.2.5.6 (Ценообразующий)
B41: Исключенные разделы документации
B42: 1. Схема планировочной организации земельного участка | G42: 5%
B43: 2. Архитектурные решения. Конструктивные и объемно-планировочные решения | G43: 25%
A44: 4212.00.Р.04.ГРП.2А.000.ТК4.000
A45: 4 | B45: Внутриплощадочные инженерные сети. Тепло-, газо-, материалопроводы на эстакадах. Длина трассы свыше 0.3 до 0.5 км. | G45: Объекты нефтеперерабатывающей и нефтехимической промышленности. 2015 г. Таблица 8. Объекты подсобно-производственного, вспомогательного и общезаводского назначения, внутриплощадочные инженерные сети, схема планировочной организации земельного участка, п.2.5 A = 1 712.5 тыс.руб; B = 1 007.8 тыс.руб; Xзад = 0.37 (км); Количество = 1 | K45: (A + B * Xзад) * Количество * Ктек * Кст * K1 (1 712 500 руб. + 1 007 800 руб. * 0.37) * 1 * 7,22 * 0.6 * 0.5 * 0.7 | O45: =ROUND((1712500 + 1007800 * 0.37) * 1 * 7.22 * 0.6 * 0.5 * 0.7, 2) -> 3161862.2
B46: Коэффициенты
B47: Стадия: Рабочая документация | G47: Кст = 0.6
B48: инд.3кв.2026г.к 01.01.2001 на пр.раб. | G48: Ктек = 7,22 Письмо Минстроя России от 22.07.2026 №45358-ИФ/09
B49: При проектировании трассы с 1-5 трубопроводами вводится коэффициент | G49: K1 = 0.5 Глава 2.5, п.2.5.6 (Ценообразующий)
B50: Исключенные разделы документации
B51: 1. Схема планировочной организации земельного участка | G51: 5%
B52: 2. Архитектурные решения. Конструктивные и объемно-планировочные решения | G52: 25%
A53: 4212.012.Р.3/0.0004.ГРП.02А.21701.012-ТМ
A54: 5 | B54: Автономные источники теплоснабжения (АИТ). Теплопроизводительность свыше 1 до 5 МВт. | G54: Газооборудование и газоснабжение промышленных предприятий, зданий и сооружений. 2015 г. Таблица 2. Автономные источники теплоснабжения (АИТ), п.2 A = 379.281 тыс.руб; B = 76.551 тыс.руб; Xзад = 1.95 (МВт); Количество = 1 | K54: (A + B * Xзад) * Количество * Ктек * Кст (379 281 руб. + 76 551 руб. * 1.95) * 1 * 7,22 * 0.6 | O54: =ROUND((379281 + 76551 * 1.95) * 1 * 7.22 * 0.6, 2) -> 2289702.2
B55: Коэффициенты
B56: Стадия: Рабочая документация | G56: Кст = 0.6
B57: инд.3кв.2026г.к 01.01.2001 на пр.раб. | G57: Ктек = 7,22 Письмо Минстроя России от 22.07.2026 №45358-ИФ/09
A58: 6 | B58: Итого по смете: | O58: =ROUND(SUM($O$16:$O$57),2) -> 9770571.8
A59: 7 | B59: Новое начисление | G59: К1 = 0.8 Коэффициент оптимизации ПАО "Газпром" («Порядок формирования стоимости проектно-изыскательских работ для строительства и реконструкции объектов ПАО «Газпром» от 28.12.2017г. п.5.41) (Ценообразующий) | K59: Коэф-т 1 от п.17 * 0.8 42 849 451.36 руб. * 1 * 0.8 | O59: =ROUND(($O$58) * 1 * 0.8,2) -> 7816457.4
A60: 8 | B60: Новое начисление | G60: К1 = 1.08 Коэффициент районный (Письмо ГК РФ по жилищной и строительной политике от 30 июня 1998 г. N 9-10-17/40) (Ценообразующий) | K60: Коэф-т 1 от п.18 * 1.08 34 279 561.09 руб. * 1 * 1.08 | O60: =ROUND(($O$59) * 1 * 1.08,2) -> 8441774
A61: 9 | B61: Всего по смете: | O61: =O60 -> 8441774 | R61: =O61 -> 8441774

Sheet 1.5 АСУТП этап3
B1: 5
B4: =СВОД!E26 -> Смета №1.5
B5: Этап 3 (Объекты на площадке ГРП 2А) АСУ ТП
B6: Наименование объекта | G6: Сети внутриплощадочные 001 - Технологический корпус №1 002 - Технологический корпус №2 004 - Резервуар, емкость дренажно-аварийная 005 - Резервуар, емкость расходная метанола 006 - Резервуар, емкость дренажно-аварийная 008 - Станция насосная 009 - Здание станции насосной водоснабжения производственного 016 - Склад дизтоплива расходный V=10 м3 019 - Здание операторной 022 - Здание контрольно- пропускного пункта
B8: Стадия | G8: Рабочая документация
B10: Наименование организации Заказчика
B11: Наименование проектной организации | G11: =СВОД!D14 -> ОАО «СИБНЕФТЕТРАНСПРОЕКТ»
B13: Смета составлена на основании "СБЦ на проектные работы в строительстве "Автоматизированные системы управления технологическими процессами (АСУТП)" (2016г.)
B15: 1. Краткая характеристика объекта автоматизации:
B16: Новое строительство
B17: Новое строительство
B18: Реконструкция, модернизация, тех. перевооружение
B19: Требование на разработку ТЗ к созданию АСУ ТП: | H19: Нет
H20: Да
H21: Нет
B22: Требуемые части документации АСУ ТП:
D23: ОР | E23: ОО | F23: ИО | G23: ТО | H23: МО | I23: ПО
D24: Да | E24: Нет | F24: Нет | G24: Да | H24: Нет | I24: Нет
D25: Да | E25: Да | F25: Да | G25: Да | H25: Да | I25: Да
D26: Нет | E26: Нет | F26: Нет | G26: Нет | H26: Нет | I26: Нет
B27: 2. Исходные данные:
B28: Трудоемкость разработки ТЗ на создание АСУ ТП
B29: Основные факторы, определяющие трудоемкость разработки | M29: Количество баллов
B30: № пп | C30: Фактор | E30: Наименование | H30: Определение | M30: ТЗ
B31: 1 | C31: Ф1 | E31: Степень научно-технической новизны (ТОУ) | H31: I степень - ТОУ имеет действующие аналоги в России и, возможно за рубежом | M31: =IF(H19="Да",SUMIF($H32:$L35,$H31,M32:N35),0) -> 0
B32: 1.1 | H32: I степень - ТОУ имеет действующие аналоги в России и, возможно за рубежом | M32: 1
B33: 1.2 | H33: II степень - ТОУ имеет действующие аналоги только за рубежом | M33: 2
B34: 1.3 | H34: III степень - ни с конструкторской, ни с технологической точек зрения ТОУ не является принципиально новым объектом, но действующих аналогов не имеет | M34: 4
B35: 1.4 | H35: IV степень - с конструкторской и (или) технологической точек зрения ТОУ является принципиально новым объектом | M35: 8
B36: 2 | C36: Ф2 | E36: Характер протекания управляемого технологического процесса во времени | H36: Непрерывный (с длительным поддержанием режимов, близких к установившимся, и практически безостановочной подачей сырья и реагентов) | M36: =IF(H19="Да",SUMIF($H37:$L42,$H36,M37:N42),0) -> 0
B37: 2.1 | H37: Непрерывный (с длительным поддержанием режимов, близких к установившимся, и практически безостановочной подачей сырья и реагентов) | M37: 1
B38: 2.2 | H38: Полунепрерывный (непрерывный, с существенными для управления переходными режимами, вызванными либо добавками (заменами) сырья или реагентов, либо выдачей продукции) | M38: 2
B39: 2.3 | H39: Непрерывно-дискретный - I (сочетающий непрерывные и прерывистые режимы на различных стадиях процесса) | M39: 4
B40: 2.4 | H40: Непрерывно-дискретный - II (сочетающий непрерывные и прерывистые режимы с малой длительностью непрерывных режимов в аварийных условиях) | M40: 5
B41: 2.5 | H41: Циклический (прерывистый, с существенной для управления длительностью интервалов непрерывного функционирования и циклическим следованием интервалов с различными режимами) | M41: 4
B42: 2.6 | H42: Дискретный (прерывистый, с малой, несущественной для управления, длительностью непрерывных технологических операций) | M42: 3
B43: 3 | C43: Ф3 | E43: Количество технологических операций, выполняемых на ТОУ | H43: свыше 10 до 20 | M43: =IF(H19="Да",SUMIF($H44:$L51,$H43,M44:N51),0) -> 0
B44: 3.1 | H44: до 5 | M44: 1
B45: 3.2 | H45: свыше 5 до 10 | M45: 2
B46: 3.3 | H46: свыше 10 до 20 | M46: 4
B47: 3.4 | H47: свыше 20 до 35 | M47: 5
B48: 3.5 | H48: свыше 35 до 50 | M48: 7
B49: 3.6 | H49: свыше 50 до 70 | M49: 9
B50: 3.7 | H50: свыше 70 до 100 | M50: 10
B51: 3.8 | H51: за каждые 50 свыше 100 | M51: 11
B52: 4 | C52: Ф4 | E52: Количество переменных, характеризующих ТОУ | H52: свыше 470 до 600 | M52: =IF(H19="Да",SUMIF($H53:$L66,$H52,M53:N66),0) -> 0
B53: 4.1 | H53: до 20 | M53: 1
B54: 4.2 | H54: свыше 20 до 50 | M54: 2
B55: 4.3 | H55: свыше 50 до 100 | M55: 3
B56: 4.4 | H56: свыше 100 до 170 | M56: 4
B57: 4.5 | H57: свыше 170 до 250 | M57: 5
B58: 4.6 | H58: свыше 250 до 350 | M58: 6
B59: 4.7 | H59: свыше 350 до 470 | M59: 7
B60: 4.8 | H60: свыше 470 до 600 | M60: 8
B61: 4.9 | H61: свыше 600 до 800 | M61: 9
B62: 4.10 | H62: свыше 800 до 1000 | M62: 10
B63: 4.11 | H63: свыше 1000 до 1300 | M63: 11
B64: 4.12 | H64: свыше 1300 до 1600 | M64: 12
... B66: 4.14 | H66: за каждые 500 свыше 2000 | M66: 14
B67: 5 | L67: ИТОГО (ƩБч): | M67: =M31+M36+M43+M52 -> 0
B68: Трудоемкость разработки документации на АСУ ТП
B69: Основные факторы, определяющие трудоемкость разработки | M69: Количество баллов для частей проектной документации (Бч)
B70: № пп | C70: Фактор | E70: Наименование | H70: Определение | M70: ОР | N70: ОО | O70: ИО | P70: ТО | Q70: МО | R70: ПО
B71: 1 | C71: Ф2 | E71: Характер протекания управляемого технологического процесса во времени | H71: Непрерывный (с длительным поддержанием режимов, близких к установившимся, и практически безостановочной подачей сырья и реагентов) | M71: =IF(D24="Да",SUMIF($H72:$L77,$H71,M72:M77),0) -> 1 | N71: =IF(E24="Да",SUMIF($H72:$L77,$H71,N72:N77),0) -> 0 | O71: =IF(F24="Да",SUMIF($H72:$L77,$H71,O72:O77),0) -> 0 | P71: =IF(G24="Да",SUMIF($H72:$L77,$H71,P72:P77),0) -> 1 | Q71: =IF(H24="Да",SUMIF($H72:$L77,$H71,Q72:Q77),0) -> 0 | R71: =IF(I24="Да",SUMIF($H72:$L77,$H71,R72:R77),0) -> 0
B72: 1.1 | H72: Непрерывный (с длительным поддержанием режимов, близких к установившимся, и практически безостановочной подачей сырья и реагентов) | M72: 1 | N72: 1 | O72: 1 | P72: 1 | Q72: 1 | R72: 1
B73: 1.2 | H73: Полунепрерывный (непрерывный, с существенными для управления переходными режимами, вызванными либо добавками (заменами) сырья или реагентов, либо выдачей продукции) | M73: 2 | N73: 1 | O73: 2 | P73: 1 | Q73: 2 | R73: 2
B74: 1.3 | H74: Непрерывно-дискретный - I (сочетающий непрерывные и прерывистые режимы на различных стадиях процесса) | M74: 3 | N74: 3 | O74: 3 | P74: 3 | Q74: 3 | R74: 3
B75: 1.4 | H75: Непрерывно-дискретный - II (сочетающий непрерывные и прерывистые режимы с малой длительностью непрерывных режимов в аварийных условиях) | M75: 4 | N75: 3 | O75: 4 | P75: 3 | Q75: 4 | R75: 4
B76: 1.5 | H76: Циклический (прерывистый, с существенной для управления длительностью интервалов непрерывного функционирования и циклическим следованием интервалов с различными режимами) | M76: 3 | N76: 2 | O76: 3 | P76: 2 | Q76: 3 | R76: 3
B77: 1.6 | H77: Дискретный (прерывистый, с малой, несущественной для управления, длительностью непрерывных технологических операций) | M77: 2 | N77: 2 | O77: 2 | P77: 2 | Q77: 3 | R77: 3
B78: 2 | C78: Ф5 | E78: Количество технологических операций, контролируемых или управляемых АСУ ТП | H78: свыше 10 до 20 | M78: =IF(D24="Да",SUMIF($H79:$L85,$H78,M79:M85),0) -> 3 | N78: =IF(E24="Да",SUMIF($H79:$L85,$H78,N79:N85),0) -> 0 | O78: =IF(F24="Да",SUMIF($H79:$L85,$H78,O79:O85),0) -> 0 | P78: =IF(G24="Да",SUMIF($H79:$L85,$H78,P79:P85),0) -> 2 | Q78: =IF(H24="Да",SUMIF($H79:$L85,$H78,Q79:Q85),0) -> 0 | R78: =IF(I24="Да",SUMIF($H79:$L85,$H78,R79:R85),0) -> 0
B79: 2.1 | E79: За каждые 50 свыше 100 начисляется еще по баллу | H79: до 5 | M79: 1 | N79: 1 | O79: 1 | P79: 1 | Q79: 1 | R79: 1
B80: 2.2 | H80: свыше 5 до 10 | M80: 2 | N80: 2 | O80: 2 | P80: 2 | Q80: 2 | R80: 2
B81: 2.3 | H81: свыше 10 до 20 | M81: 3 | N81: 2 | O81: 3 | P81: 2 | Q81: 3 | R81: 3
B82: 2.4 | H82: свыше 20 до 35 | M82: 4 | N82: 3 | O82: 4 | P82: 3 | Q82: 4 | R82: 4
B83: 2.5 | H83: свыше 35 до 50 | M83: 5 | N83: 3 | O83: 5 | P83: 3 | Q83: 5 | R83: 5
B84: 2.6 | H84: свыше 50 до 70 | M84: 6 | N84: 4 | O84: 6 | P84: 4 | Q84: 6 | R84: 6
B85: 2.7 | H85: свыше 70 до 100 | M85: 7 | N85: 5 | O85: 7 | P85: 5 | Q85: 7 | R85: 7
B86: 3 | C86: Ф6 | E86: Степень развитости информационных функций АСУ ТП | H86: III степень - косвенное измерение (вычисление) отдельных комплексных показателей функционирования ТОУ | M86: =IF(D24="Да",SUMIF($H87:$L90,$H86,M87:M90),0) -> 6 | N86: =IF(E24="Да",SUMIF($H87:$L90,$H86,N87:N90),0) -> 0 | O86: =IF(F24="Да",SUMIF($H87:$L90,$H86,O87:O90),0) -> 0 | P86: =IF(G24="Да",SUMIF($H87:$L90,$H86,P87:P90),0) -> 5 | Q86: =IF(H24="Да",SUMIF($H87:$L90,$H86,Q87:Q90),0) -> 0 | R86: =IF(I24="Да",SUMIF($H87:$L90,$H86,R87:R90),0) -> 0
B87: 3.1 | H87: I степень - параллельные контроль и измерение параметров состояния ТОУ | M87: 1 | N87: 1 | O87: 1 | P87: 1 | Q87: 1 | R87: 1
B88: 3.2 | H88: II степень - централизованный контроль и измерение параметров состояния ТОУ | M88: 3 | N88: 2 | O88: 3 | P88: 3 | Q88: 3 | R88: 3
B89: 3.3 | H89: III степень - косвенное измерение (вычисление) отдельных комплексных показателей функционирования ТОУ | M89: 6 | N89: 2 | O89: 6 | P89: 5 | Q89: 6 | R89: 6
B90: 3.4 | H90: IV степень - анализ и обобщенная оценка состояния процесса в целом по его модели (распознавание ситуаций, диагностика аварийных состояний, поиск "узкого места", прогноз хода процесса) | M90: 9 | N90: 3 | O90: 9 | P90: 8 | Q90: 9 | R90: 9
B91: 4 | C91: Ф7 | E91: Степень развитости управляющих функций АСУ ТП | H91: III степень - многосвязное автоматическое регулирование или автоматическое программное логическое управление по циклу с разветвлениями | M91: =IF(D24="Да",SUMIF($H92:$L98,$H91,M92:M98),0) -> 5 | N91: =IF(E24="Да",SUMIF($H92:$L98,$H91,N92:N98),0) -> 0 | O91: =IF(F24="Да",SUMIF($H92:$L98,$H91,O92:O98),0) -> 0 | P91: =IF(G24="Да",SUMIF($H92:$L98,$H91,P92:P98),0) -> 5 | Q91: =IF(H24="Да",SUMIF($H92:$L98,$H91,Q92:Q98),0) -> 0 | R91: =IF(I24="Да",SUMIF($H92:$L98,$H91,R92:R98),0) -> 0
B92: 7.22 | H92: I степень - одноконтурное автоматическое регулирование или автоматическое однотактное логическое управление (переключения, блокировки и тому подобное) | M92: 1 | N92: 1 | O92: 1 | P92: 1 | Q92: 1 | R92: 1
B93: 7.2 | H93: II степень - каскадное и (или) программное автоматическое регулирование или автоматическое программное логическое управление по "жесткому" циклу | M93: 3 | N93: 2 | O93: 3 | P93: 3 | Q93: 3 | R93: 3
B94: 7.3 | H94: III степень - многосвязное автоматическое регулирование или автоматическое программное логическое управление по циклу с разветвлениями | M94: 5 | N94: 2 | O94: 5 | P94: 5 | Q94: 5 | R94: 5
B95: 7.4 | H95: IV степень - оптимальное управление установившимися режимами (в статике) | M95: 6 | N95: 3 | O95: 7 | P95: 7 | Q95: 7 | R95: 7
B96: 7.5 | H96: V степень - оптимальное управление переходными процессами или процессом в целом (оптимизация в динамике) | M96: 8 | N96: 4 | O96: 10 | P96: 9 | Q96: 11 | R96: 11
B97: 7.6 | H97: VI степень - оптимальное управление быстропротекающими переходными процессами в аварийных условиях | M97: 9 | N97: 4 | O97: 11 | P97: 10 | Q97: 13 | R97: 13
B98: 7.7 | H98: VII степень - оптимальное управление с адаптацией (самообучением и изменением алгоритмов и параметров системы) | M98: 10 | N98: 5 | O98: 12 | P98: 11 | Q98: 14 | R98: 14
B99: 5 | C99: Ф8 | E99: Режим выполнения управляющих фукций АСУ ТП | H99: Автоматический режим прямого (непосредственного) цифрового (или аналого-цифрового) управления | M99: =IF(D24="Да",SUMIF($H100:$L104,$H99,M100:M104),0) -> 5 | N99: =IF(E24="Да",SUMIF($H100:$L104,$H99,N100:N104),0) -> 0 | O99: =IF(F24="Да",SUMIF($H100:$L104,$H99,O100:O104),0) -> 0 | P99: =IF(G24="Да",SUMIF($H100:$L104,$H99,P100:P104),0) -> 7 | Q99: =IF(H24="Да",SUMIF($H100:$L104,$H99,Q100:Q104),0) -> 0 | R99: =IF(I24="Да",SUMIF($H100:$L104,$H99,R100:R104),0) -> 0
B100: 5.1 | H100: Автоматизированный "ручной" режим | M100: 1 | N100: 1 | O100: 1 | P100: 1 | Q100: 1 | R100: 1
B101: 5.2 | H101: Автоматизированный режим "советчика" | M101: 1 | N101: 1 | O101: 2 | P101: 1 | Q101: 2 | R101: 2
B102: 5.3 | H102: Автоматизированный диалоговый режим | M102: 2 | N102: 2 | O102: 2 | P102: 2 | Q102: 3 | R102: 3
B103: 5.4 | H103: Автоматический режим косвенного управления | M103: 3 | N103: 2 | O103: 3 | P103: 4 | Q103: 4 | R103: 4
B104: 5.5 | H104: Автоматический режим прямого (непосредственного) цифрового (или аналого-цифрового) управления | M104: 5 | N104: 3 | O104: 5 | P104: 7 | Q104: 7 | R104: 7
B105: 6 | C105: Ф9 | E105: Количество переменных, измеряемых, контролируемых и регистрируемых АСУ ТП | H105: свыше 1000 до 1300 | M105: =IF(D24="Да",SUMIF($H106:$L119,$H105,M106:M119),0) -> 7 | N105: =IF(E24="Да",SUMIF($H106:$L119,$H105,N106:N119),0) -> 0 | O105: =IF(F24="Да",SUMIF($H106:$L119,$H105,O106:O119),0) -> 0 | P105: =IF(G24="Да",SUMIF($H106:$L119,$H105,P106:P119),0) -> 11 | Q105: =IF(H24="Да",SUMIF($H106:$L119,$H105,Q106:Q119),0) -> 0 | R105: =IF(I24="Да",SUMIF($H106:$L119,$H105,R106:R119),0) -> 0
B106: 6.1 | H106: до 20 | M106: 1 | N106: 1 | O106: 1 | P106: 1 | Q106: 1 | R106: 1
B107: 6.2 | H107: свыше 20 до 50 | M107: 2 | N107: 1 | O107: 2 | P107: 2 | Q107: 2 | R107: 2
...

Sheet 1.6 АСУЭ этап3
B1: 5
B4: =СВОД!E27 -> Смета №1.6
B5: Этап 3 (Объекты на площадке ГРП 2А) АСУ Э
B6: Наименование объекта | G6: Сети внутриплощадочные
B8: Стадия | G8: Рабочая документация
B10: Наименование организации Заказчика
B11: Наименование проектной организации | G11: =СВОД!D14 -> ОАО «СИБНЕФТЕТРАНСПРОЕКТ»
B13: Смета составлена на основании "СБЦ на проектные работы в строительстве "Автоматизированные системы управления технологическими процессами (АСУТП)" (2016г.)
B15: 1. Краткая характеристика объекта автоматизации:
B16: Новое строительство
B17: Новое строительство
B18: Реконструкция, модернизация, тех. перевооружение
B19: Требование на разработку ТЗ к созданию АСУ ТП: | H19: Нет
H20: Да
H21: Нет
B22: Требуемые части документации АСУ ТП:
D23: ОР | E23: ОО | F23: ИО | G23: ТО | H23: МО | I23: ПО
D24: Да | E24: Нет | F24: Нет | G24: Да | H24: Нет | I24: Нет
D25: Да | E25: Да | F25: Да | G25: Да | H25: Да | I25: Да
D26: Нет | E26: Нет | F26: Нет | G26: Нет | H26: Нет | I26: Нет
B27: 2. Исходные данные:
B28: Трудоемкость разработки ТЗ на создание АСУ ТП
B29: Основные факторы, определяющие трудоемкость разработки | M29: Количество баллов
B30: № пп | C30: Фактор | E30: Наименование | H30: Определение | M30: ТЗ
B31: 1 | C31: Ф1 | E31: Степень научно-технической новизны (ТОУ) | H31: I степень - ТОУ имеет действующие аналоги в России и, возможно за рубежом | M31: =IF(H19="Да",SUMIF($H32:$L35,$H31,M32:N35),0) -> 0
B32: 1.1 | H32: I степень - ТОУ имеет действующие аналоги в России и, возможно за рубежом | M32: 1
B33: 1.2 | H33: II степень - ТОУ имеет действующие аналоги только за рубежом | M33: 2
B34: 1.3 | H34: III степень - ни с конструкторской, ни с технологической точек зрения ТОУ не является принципиально новым объектом, но действующих аналогов не имеет | M34: 4
B35: 1.4 | H35: IV степень - с конструкторской и (или) технологической точек зрения ТОУ является принципиально новым объектом | M35: 8
B36: 2 | C36: Ф2 | E36: Характер протекания управляемого технологического процесса во времени | H36: Непрерывный (с длительным поддержанием режимов, близких к установившимся, и практически безостановочной подачей сырья и реагентов) | M36: =IF(H19="Да",SUMIF($H37:$L42,$H36,M37:N42),0) -> 0
B37: 2.1 | H37: Непрерывный (с длительным поддержанием режимов, близких к установившимся, и практически безостановочной подачей сырья и реагентов) | M37: 1
B38: 2.2 | H38: Полунепрерывный (непрерывный, с существенными для управления переходными режимами, вызванными либо добавками (заменами) сырья или реагентов, либо выдачей продукции) | M38: 2
B39: 2.3 | H39: Непрерывно-дискретный - I (сочетающий непрерывные и прерывистые режимы на различных стадиях процесса) | M39: 4
B40: 2.4 | H40: Непрерывно-дискретный - II (сочетающий непрерывные и прерывистые режимы с малой длительностью непрерывных режимов в аварийных условиях) | M40: 5
B41: 2.5 | H41: Циклический (прерывистый, с существенной для управления длительностью интервалов непрерывного функционирования и циклическим следованием интервалов с различными режимами) | M41: 4
B42: 2.6 | H42: Дискретный (прерывистый, с малой, несущественной для управления, длительностью непрерывных технологических операций) | M42: 3
B43: 3 | C43: Ф3 | E43: Количество технологических операций, выполняемых на ТОУ | H43: свыше 10 до 20 | M43: =IF(H19="Да",SUMIF($H44:$L51,$H43,M44:N51),0) -> 0
B44: 3.1 | H44: до 5 | M44: 1
B45: 3.2 | H45: свыше 5 до 10 | M45: 2
B46: 3.3 | H46: свыше 10 до 20 | M46: 4
B47: 3.4 | H47: свыше 20 до 35 | M47: 5
B48: 3.5 | H48: свыше 35 до 50 | M48: 7
B49: 3.6 | H49: свыше 50 до 70 | M49: 9
B50: 3.7 | H50: свыше 70 до 100 | M50: 10
B51: 3.8 | H51: за каждые 50 свыше 100 | M51: 11
B52: 4 | C52: Ф4 | E52: Количество переменных, характеризующих ТОУ | H52: свыше 470 до 600 | M52: =IF(H19="Да",SUMIF($H53:$L66,$H52,M53:N66),0) -> 0
B53: 4.1 | H53: до 20 | M53: 1
B54: 4.2 | H54: свыше 20 до 50 | M54: 2
B55: 4.3 | H55: свыше 50 до 100 | M55: 3
B56: 4.4 | H56: свыше 100 до 170 | M56: 4
B57: 4.5 | H57: свыше 170 до 250 | M57: 5
B58: 4.6 | H58: свыше 250 до 350 | M58: 6
B59: 4.7 | H59: свыше 350 до 470 | M59: 7
B60: 4.8 | H60: свыше 470 до 600 | M60: 8
B61: 4.9 | H61: свыше 600 до 800 | M61: 9
B62: 4.10 | H62: свыше 800 до 1000 | M62: 10
B63: 4.11 | H63: свыше 1000 до 1300 | M63: 11
B64: 4.12 | H64: свыше 1300 до 1600 | M64: 12
... B66: 4.14 | H66: за каждые 500 свыше 2000 | M66: 14
B67: 5 | L67: ИТОГО (ƩБч): | M67: =M31+M36+M43+M52 -> 0
B68: Трудоемкость разработки документации на АСУ ТП
B69: Основные факторы, определяющие трудоемкость разработки | M69: Количество баллов для частей проектной документации (Бч)
B70: № пп | C70: Фактор | E70: Наименование | H70: Определение | M70: ОР | N70: ОО | O70: ИО | P70: ТО | Q70: МО | R70: ПО
B71: 1 | C71: Ф2 | E71: Характер протекания управляемого технологического процесса во времени | H71: Непрерывный (с длительным поддержанием режимов, близких к установившимся, и практически безостановочной подачей сырья и реагентов) | M71: =IF(D24="Да",SUMIF($H72:$L77,$H71,M72:M77),0) -> 1 | N71: =IF(E24="Да",SUMIF($H72:$L77,$H71,N72:N77),0) -> 0 | O71: =IF(F24="Да",SUMIF($H72:$L77,$H71,O72:O77),0) -> 0 | P71: =IF(G24="Да",SUMIF($H72:$L77,$H71,P72:P77),0) -> 1 | Q71: =IF(H24="Да",SUMIF($H72:$L77,$H71,Q72:Q77),0) -> 0 | R71: =IF(I24="Да",SUMIF($H72:$L77,$H71,R72:R77),0) -> 0
B72: 1.1 | H72: Непрерывный (с длительным поддержанием режимов, близких к установившимся, и практически безостановочной подачей сырья и реагентов) | M72: 1 | N72: 1 | O72: 1 | P72: 1 | Q72: 1 | R72: 1
B73: 1.2 | H73: Полунепрерывный (непрерывный, с существенными для управления переходными режимами, вызванными либо добавками (заменами) сырья или реагентов, либо выдачей продукции) | M73: 2 | N73: 1 | O73: 2 | P73: 1 | Q73: 2 | R73: 2
B74: 1.3 | H74: Непрерывно-дискретный - I (сочетающий непрерывные и прерывистые режимы на различных стадиях процесса) | M74: 3 | N74: 3 | O74: 3 | P74: 3 | Q74: 3 | R74: 3
B75: 1.4 | H75: Непрерывно-дискретный - II (сочетающий непрерывные и прерывистые режимы с малой длительностью непрерывных режимов в аварийных условиях) | M75: 4 | N75: 3 | O75: 4 | P75: 3 | Q75: 4 | R75: 4
B76: 1.5 | H76: Циклический (прерывистый, с существенной для управления длительностью интервалов непрерывного функционирования и циклическим следованием интервалов с различными режимами) | M76: 3 | N76: 2 | O76: 3 | P76: 2 | Q76: 3 | R76: 3
B77: 1.6 | H77: Дискретный (прерывистый, с малой, несущественной для управления, длительностью непрерывных технологических операций) | M77: 2 | N77: 2 | O77: 2 | P77: 2 | Q77: 3 | R77: 3
B78: 2 | C78: Ф5 | E78: Количество технологических операций, контролируемых или управляемых АСУ ТП | H78: свыше 5 до 10 | M78: =IF(D24="Да",SUMIF($H79:$L85,$H78,M79:M85),0) -> 2 | N78: =IF(E24="Да",SUMIF($H79:$L85,$H78,N79:N85),0) -> 0 | O78: =IF(F24="Да",SUMIF($H79:$L85,$H78,O79:O85),0) -> 0 | P78: =IF(G24="Да",SUMIF($H79:$L85,$H78,P79:P85),0) -> 2 | Q78: =IF(H24="Да",SUMIF($H79:$L85,$H78,Q79:Q85),0) -> 0 | R78: =IF(I24="Да",SUMIF($H79:$L85,$H78,R79:R85),0) -> 0
B79: 2.1 | E79: За каждые 50 свыше 100 начисляется еще по баллу | H79: до 5 | M79: 1 | N79: 1 | O79: 1 | P79: 1 | Q79: 1 | R79: 1
B80: 2.2 | H80: свыше 5 до 10 | M80: 2 | N80: 2 | O80: 2 | P80: 2 | Q80: 2 | R80: 2
B81: 2.3 | H81: свыше 10 до 20 | M81: 3 | N81: 2 | O81: 3 | P81: 2 | Q81: 3 | R81: 3
B82: 2.4 | H82: свыше 20 до 35 | M82: 4 | N82: 3 | O82: 4 | P82: 3 | Q82: 4 | R82: 4
B83: 2.5 | H83: свыше 35 до 50 | M83: 5 | N83: 3 | O83: 5 | P83: 3 | Q83: 5 | R83: 5
B84: 2.6 | H84: свыше 50 до 70 | M84: 6 | N84: 4 | O84: 6 | P84: 4 | Q84: 6 | R84: 6
B85: 2.7 | H85: свыше 70 до 100 | M85: 7 | N85: 5 | O85: 7 | P85: 5 | Q85: 7 | R85: 7
B86: 3 | C86: Ф6 | E86: Степень развитости информационных функций АСУ ТП | H86: III степень - косвенное измерение (вычисление) отдельных комплексных показателей функционирования ТОУ | M86: =IF(D24="Да",SUMIF($H87:$L90,$H86,M87:M90),0) -> 6 | N86: =IF(E24="Да",SUMIF($H87:$L90,$H86,N87:N90),0) -> 0 | O86: =IF(F24="Да",SUMIF($H87:$L90,$H86,O87:O90),0) -> 0 | P86: =IF(G24="Да",SUMIF($H87:$L90,$H86,P87:P90),0) -> 5 | Q86: =IF(H24="Да",SUMIF($H87:$L90,$H86,Q87:Q90),0) -> 0 | R86: =IF(I24="Да",SUMIF($H87:$L90,$H86,R87:R90),0) -> 0
B87: 3.1 | H87: I степень - параллельные контроль и измерение параметров состояния ТОУ | M87: 1 | N87: 1 | O87: 1 | P87: 1 | Q87: 1 | R87: 1
B88: 3.2 | H88: II степень - централизованный контроль и измерение параметров состояния ТОУ | M88: 3 | N88: 2 | O88: 3 | P88: 3 | Q88: 3 | R88: 3
B89: 3.3 | H89: III степень - косвенное измерение (вычисление) отдельных комплексных показателей функционирования ТОУ | M89: 6 | N89: 2 | O89: 6 | P89: 5 | Q89: 6 | R89: 6
B90: 3.4 | H90: IV степень - анализ и обобщенная оценка состояния процесса в целом по его модели (распознавание ситуаций, диагностика аварийных состояний, поиск "узкого места", прогноз хода процесса) | M90: 9 | N90: 3 | O90: 9 | P90: 8 | Q90: 9 | R90: 9
B91: 4 | C91: Ф7 | E91: Степень развитости управляющих функций АСУ ТП | H91: I степень - одноконтурное автоматическое регулирование или автоматическое однотактное логическое управление (переключения, блокировки и тому подобное) | M91: =IF(D24="Да",SUMIF($H92:$L98,$H91,M92:M98),0) -> 1 | N91: =IF(E24="Да",SUMIF($H92:$L98,$H91,N92:N98),0) -> 0 | O91: =IF(F24="Да",SUMIF($H92:$L98,$H91,O92:O98),0) -> 0 | P91: =IF(G24="Да",SUMIF($H92:$L98,$H91,P92:P98),0) -> 1 | Q91: =IF(H24="Да",SUMIF($H92:$L98,$H91,Q92:Q98),0) -> 0 | R91: =IF(I24="Да",SUMIF($H92:$L98,$H91,R92:R98),0) -> 0
B92: 7.22 | H92: I степень - одноконтурное автоматическое регулирование или автоматическое однотактное логическое управление (переключения, блокировки и тому подобное) | M92: 1 | N92: 1 | O92: 1 | P92: 1 | Q92: 1 | R92: 1
B93: 7.2 | H93: II степень - каскадное и (или) программное автоматическое регулирование или автоматическое программное логическое управление по "жесткому" циклу | M93: 3 | N93: 2 | O93: 3 | P93: 3 | Q93: 3 | R93: 3
B94: 7.3 | H94: III степень - многосвязное автоматическое регулирование или автоматическое программное логическое управление по циклу с разветвлениями | M94: 5 | N94: 2 | O94: 5 | P94: 5 | Q94: 5 | R94: 5
B95: 7.4 | H95: IV степень - оптимальное управление установившимися режимами (в статике) | M95: 6 | N95: 3 | O95: 7 | P95: 7 | Q95: 7 | R95: 7
B96: 7.5 | H96: V степень - оптимальное управление переходными процессами или процессом в целом (оптимизация в динамике) | M96: 8 | N96: 4 | O96: 10 | P96: 9 | Q96: 11 | R96: 11
B97: 7.6 | H97: VI степень - оптимальное управление быстропротекающими переходными процессами в аварийных условиях | M97: 9 | N97: 4 | O97: 11 | P97: 10 | Q97: 13 | R97: 13
B98: 7.7 | H98: VII степень - оптимальное управление с адаптацией (самообучением и изменением алгоритмов и параметров системы) | M98: 10 | N98: 5 | O98: 12 | P98: 11 | Q98: 14 | R98: 14
B99: 5 | C99: Ф8 | E99: Режим выполнения управляющих фукций АСУ ТП | H99: Автоматический режим косвенного управления | M99: =IF(D24="Да",SUMIF($H100:$L104,$H99,M100:M104),0) -> 3 | N99: =IF(E24="Да",SUMIF($H100:$L104,$H99,N100:N104),0) -> 0 | O99: =IF(F24="Да",SUMIF($H100:$L104,$H99,O100:O104),0) -> 0 | P99: =IF(G24="Да",SUMIF($H100:$L104,$H99,P100:P104),0) -> 4 | Q99: =IF(H24="Да",SUMIF($H100:$L104,$H99,Q100:Q104),0) -> 0 | R99: =IF(I24="Да",SUMIF($H100:$L104,$H99,R100:R104),0) -> 0
B100: 5.1 | H100: Автоматизированный "ручной" режим | M100: 1 | N100: 1 | O100: 1 | P100: 1 | Q100: 1 | R100: 1
B101: 5.2 | H101: Автоматизированный режим "советчика" | M101: 1 | N101: 1 | O101: 2 | P101: 1 | Q101: 2 | R101: 2
B102: 5.3 | H102: Автоматизированный диалоговый режим | M102: 2 | N102: 2 | O102: 2 | P102: 2 | Q102: 3 | R102: 3
B103: 5.4 | H103: Автоматический режим косвенного управления | M103: 3 | N103: 2 | O103: 3 | P103: 4 | Q103: 4 | R103: 4
B104: 5.5 | H104: Автоматический режим прямого (непосредственного) цифрового (или аналого-цифрового) управления | M104: 5 | N104: 3 | O104: 5 | P104: 7 | Q104: 7 | R104: 7
B105: 6 | C105: Ф9 | E105: Количество переменных, измеряемых, контролируемых и регистрируемых АСУ ТП | H105: до 20 | M105: =IF(D24="Да",SUMIF($H106:$L119,$H105,M106:M119),0) -> 1 | N105: =IF(E24="Да",SUMIF($H106:$L119,$H105,N106:N119),0) -> 0 | O105: =IF(F24="Да",SUMIF($H106:$L119,$H105,O106:O119),0) -> 0 | P105: =IF(G24="Да",SUMIF($H106:$L119,$H105,P106:P119),0) -> 1 | Q105: =IF(H24="Да",SUMIF($H106:$L119,$H105,Q106:Q119),0) -> 0 | R105: =IF(I24="Да",SUMIF($H106:$L119,$H105,R106:R119),0) -> 0
B106: 6.1 | H106: до 20 | M106: 1 | N106: 1 | O106: 1 | P106: 1 | Q106: 1 | R106: 1
B107: 6.2 | H107: свыше 20 до 50 | M107: 2 | N107: 1 | O107: 2 | P107: 2 | Q107: 2 | R107: 2
...

Sheet 1.7 АЭО этап3
B1: 5
B4: =СВОД!E28 -> Смета №1.7
B5: Этап 3 (Объекты на площадке ГРП 2А) АЭО
B6: Наименование объекта | G6: Сети внутриплощадочные
B8: Стадия | G8: Рабочая документация
B10: Наименование организации Заказчика
B11: Наименование проектной организации | G11: =СВОД!D14 -> ОАО «СИБНЕФТЕТРАНСПРОЕКТ»
B13: Смета составлена на основании "СБЦ на проектные работы в строительстве "Автоматизированные системы управления технологическими процессами (АСУТП)" (2016г.)
B15: 1. Краткая характеристика объекта автоматизации:
B16: Новое строительство
B17: Новое строительство
B18: Реконструкция, модернизация, тех. перевооружение
B19: Требование на разработку ТЗ к созданию АСУ ТП: | H19: Нет
H20: Да
H21: Нет
B22: Требуемые части документации АСУ ТП:
D23: ОР | E23: ОО | F23: ИО | G23: ТО | H23: МО | I23: ПО
D24: Да | E24: Нет | F24: Нет | G24: Да | H24: Нет | I24: Нет
D25: Да | E25: Да | F25: Да | G25: Да | H25: Да | I25: Да
D26: Нет | E26: Нет | F26: Нет | G26: Нет | H26: Нет | I26: Нет
B27: 2. Исходные данные:
B28: Трудоемкость разработки ТЗ на создание АСУ ТП
B29: Основные факторы, определяющие трудоемкость разработки | M29: Количество баллов
B30: № пп | C30: Фактор | E30: Наименование | H30: Определение | M30: ТЗ
B31: 1 | C31: Ф1 | E31: Степень научно-технической новизны (ТОУ) | H31: I степень - ТОУ имеет действующие аналоги в России и, возможно за рубежом | M31: =IF(H19="Да",SUMIF($H32:$L35,$H31,M32:N35),0) -> 0
B32: 1.1 | H32: I степень - ТОУ имеет действующие аналоги в России и, возможно за рубежом | M32: 1
B33: 1.2 | H33: II степень - ТОУ имеет действующие аналоги только за рубежом | M33: 2
B34: 1.3 | H34: III степень - ни с конструкторской, ни с технологической точек зрения ТОУ не является принципиально новым объектом, но действующих аналогов не имеет | M34: 4
B35: 1.4 | H35: IV степень - с конструкторской и (или) технологической точек зрения ТОУ является принципиально новым объектом | M35: 8
B36: 2 | C36: Ф2 | E36: Характер протекания управляемого технологического процесса во времени | H36: Непрерывный (с длительным поддержанием режимов, близких к установившимся, и практически безостановочной подачей сырья и реагентов) | M36: =IF(H19="Да",SUMIF($H37:$L42,$H36,M37:N42),0) -> 0
B37: 2.1 | H37: Непрерывный (с длительным поддержанием режимов, близких к установившимся, и практически безостановочной подачей сырья и реагентов) | M37: 1
B38: 2.2 | H38: Полунепрерывный (непрерывный, с существенными для управления переходными режимами, вызванными либо добавками (заменами) сырья или реагентов, либо выдачей продукции) | M38: 2
B39: 2.3 | H39: Непрерывно-дискретный - I (сочетающий непрерывные и прерывистые режимы на различных стадиях процесса) | M39: 4
B40: 2.4 | H40: Непрерывно-дискретный - II (сочетающий непрерывные и прерывистые режимы с малой длительностью непрерывных режимов в аварийных условиях) | M40: 5
B41: 2.5 | H41: Циклический (прерывистый, с существенной для управления длительностью интервалов непрерывного функционирования и циклическим следованием интервалов с различными режимами) | M41: 4
B42: 2.6 | H42: Дискретный (прерывистый, с малой, несущественной для управления, длительностью непрерывных технологических операций) | M42: 3
B43: 3 | C43: Ф3 | E43: Количество технологических операций, выполняемых на ТОУ | H43: свыше 10 до 20 | M43: =IF(H19="Да",SUMIF($H44:$L51,$H43,M44:N51),0) -> 0
B44: 3.1 | H44: до 5 | M44: 1
B45: 3.2 | H45: свыше 5 до 10 | M45: 2
B46: 3.3 | H46: свыше 10 до 20 | M46: 4
B47: 3.4 | H47: свыше 20 до 35 | M47: 5
B48: 3.5 | H48: свыше 35 до 50 | M48: 7
B49: 3.6 | H49: свыше 50 до 70 | M49: 9
B50: 3.7 | H50: свыше 70 до 100 | M50: 10
B51: 3.8 | H51: за каждые 50 свыше 100 | M51: 11
B52: 4 | C52: Ф4 | E52: Количество переменных, характеризующих ТОУ | H52: свыше 470 до 600 | M52: =IF(H19="Да",SUMIF($H53:$L66,$H52,M53:N66),0) -> 0
B53: 4.1 | H53: до 20 | M53: 1
B54: 4.2 | H54: свыше 20 до 50 | M54: 2
B55: 4.3 | H55: свыше 50 до 100 | M55: 3
B56: 4.4 | H56: свыше 100 до 170 | M56: 4
B57: 4.5 | H57: свыше 170 до 250 | M57: 5
B58: 4.6 | H58: свыше 250 до 350 | M58: 6
B59: 4.7 | H59: свыше 350 до 470 | M59: 7
B60: 4.8 | H60: свыше 470 до 600 | M60: 8
B61: 4.9 | H61: свыше 600 до 800 | M61: 9
B62: 4.10 | H62: свыше 800 до 1000 | M62: 10
B63: 4.11 | H63: свыше 1000 до 1300 | M63: 11
B64: 4.12 | H64: свыше 1300 до 1600 | M64: 12
... B66: 4.14 | H66: за каждые 500 свыше 2000 | M66: 14
B67: 5 | L67: ИТОГО (ƩБч): | M67: =M31+M36+M43+M52 -> 0
B68: Трудоемкость разработки документации на АСУ ТП
B69: Основные факторы, определяющие трудоемкость разработки | M69: Количество баллов для частей проектной документации (Бч)
B70: № пп | C70: Фактор | E70: Наименование | H70: Определение | M70: ОР | N70: ОО | O70: ИО | P70: ТО | Q70: МО | R70: ПО
B71: 1 | C71: Ф2 | E71: Характер протекания управляемого технологического процесса во времени | H71: Непрерывный (с длительным поддержанием режимов, близких к установившимся, и практически безостановочной подачей сырья и реагентов) | M71: =IF(D24="Да",SUMIF($H72:$L77,$H71,M72:M77),0) -> 1 | N71: =IF(E24="Да",SUMIF($H72:$L77,$H71,N72:N77),0) -> 0 | O71: =IF(F24="Да",SUMIF($H72:$L77,$H71,O72:O77),0) -> 0 | P71: =IF(G24="Да",SUMIF($H72:$L77,$H71,P72:P77),0) -> 1 | Q71: =IF(H24="Да",SUMIF($H72:$L77,$H71,Q72:Q77),0) -> 0 | R71: =IF(I24="Да",SUMIF($H72:$L77,$H71,R72:R77),0) -> 0
B72: 1.1 | H72: Непрерывный (с длительным поддержанием режимов, близких к установившимся, и практически безостановочной подачей сырья и реагентов) | M72: 1 | N72: 1 | O72: 1 | P72: 1 | Q72: 1 | R72: 1
B73: 1.2 | H73: Полунепрерывный (непрерывный, с существенными для управления переходными режимами, вызванными либо добавками (заменами) сырья или реагентов, либо выдачей продукции) | M73: 2 | N73: 1 | O73: 2 | P73: 1 | Q73: 2 | R73: 2
B74: 1.3 | H74: Непрерывно-дискретный - I (сочетающий непрерывные и прерывистые режимы на различных стадиях процесса) | M74: 3 | N74: 3 | O74: 3 | P74: 3 | Q74: 3 | R74: 3
B75: 1.4 | H75: Непрерывно-дискретный - II (сочетающий непрерывные и прерывистые режимы с малой длительностью непрерывных режимов в аварийных условиях) | M75: 4 | N75: 3 | O75: 4 | P75: 3 | Q75: 4 | R75: 4
B76: 1.5 | H76: Циклический (прерывистый, с существенной для управления длительностью интервалов непрерывного функционирования и циклическим следованием интервалов с различными режимами) | M76: 3 | N76: 2 | O76: 3 | P76: 2 | Q76: 3 | R76: 3
B77: 1.6 | H77: Дискретный (прерывистый, с малой, несущественной для управления, длительностью непрерывных технологических операций) | M77: 2 | N77: 2 | O77: 2 | P77: 2 | Q77: 3 | R77: 3
B78: 2 | C78: Ф5 | E78: Количество технологических операций, контролируемых или управляемых АСУ ТП | H78: до 5 | M78: =IF(D24="Да",SUMIF($H79:$L85,$H78,M79:M85),0) -> 1 | N78: =IF(E24="Да",SUMIF($H79:$L85,$H78,N79:N85),0) -> 0 | O78: =IF(F24="Да",SUMIF($H79:$L85,$H78,O79:O85),0) -> 0 | P78: =IF(G24="Да",SUMIF($H79:$L85,$H78,P79:P85),0) -> 1 | Q78: =IF(H24="Да",SUMIF($H79:$L85,$H78,Q79:Q85),0) -> 0 | R78: =IF(I24="Да",SUMIF($H79:$L85,$H78,R79:R85),0) -> 0
B79: 2.1 | E79: За каждые 50 свыше 100 начисляется еще по баллу | H79: до 5 | M79: 1 | N79: 1 | O79: 1 | P79: 1 | Q79: 1 | R79: 1
B80: 2.2 | H80: свыше 5 до 10 | M80: 2 | N80: 2 | O80: 2 | P80: 2 | Q80: 2 | R80: 2
B81: 2.3 | H81: свыше 10 до 20 | M81: 3 | N81: 2 | O81: 3 | P81: 2 | Q81: 3 | R81: 3
B82: 2.4 | H82: свыше 20 до 35 | M82: 4 | N82: 3 | O82: 4 | P82: 3 | Q82: 4 | R82: 4
B83: 2.5 | H83: свыше 35 до 50 | M83: 5 | N83: 3 | O83: 5 | P83: 3 | Q83: 5 | R83: 5
B84: 2.6 | H84: свыше 50 до 70 | M84: 6 | N84: 4 | O84: 6 | P84: 4 | Q84: 6 | R84: 6
B85: 2.7 | H85: свыше 70 до 100 | M85: 7 | N85: 5 | O85: 7 | P85: 5 | Q85: 7 | R85: 7
B86: 3 | C86: Ф6 | E86: Степень развитости информационных функций АСУ ТП | H86: I степень - параллельные контроль и измерение параметров состояния ТОУ | M86: =IF(D24="Да",SUMIF($H87:$L90,$H86,M87:M90),0) -> 1 | N86: =IF(E24="Да",SUMIF($H87:$L90,$H86,N87:N90),0) -> 0 | O86: =IF(F24="Да",SUMIF($H87:$L90,$H86,O87:O90),0) -> 0 | P86: =IF(G24="Да",SUMIF($H87:$L90,$H86,P87:P90),0) -> 1 | Q86: =IF(H24="Да",SUMIF($H87:$L90,$H86,Q87:Q90),0) -> 0 | R86: =IF(I24="Да",SUMIF($H87:$L90,$H86,R87:R90),0) -> 0
B87: 3.1 | H87: I степень - параллельные контроль и измерение параметров состояния ТОУ | M87: 1 | N87: 1 | O87: 1 | P87: 1 | Q87: 1 | R87: 1
B88: 3.2 | H88: II степень - централизованный контроль и измерение параметров состояния ТОУ | M88: 3 | N88: 2 | O88: 3 | P88: 3 | Q88: 3 | R88: 3
B89: 3.3 | H89: III степень - косвенное измерение (вычисление) отдельных комплексных показателей функционирования ТОУ | M89: 6 | N89: 2 | O89: 6 | P89: 5 | Q89: 6 | R89: 6
B90: 3.4 | H90: IV степень - анализ и обобщенная оценка состояния процесса в целом по его модели (распознавание ситуаций, диагностика аварийных состояний, поиск "узкого места", прогноз хода процесса) | M90: 9 | N90: 3 | O90: 9 | P90: 8 | Q90: 9 | R90: 9
B91: 4 | C91: Ф7 | E91: Степень развитости управляющих функций АСУ ТП | H91: I степень - одноконтурное автоматическое регулирование или автоматическое однотактное логическое управление (переключения, блокировки и тому подобное) | M91: =IF(D24="Да",SUMIF($H92:$L98,$H91,M92:M98),0) -> 1 | N91: =IF(E24="Да",SUMIF($H92:$L98,$H91,N92:N98),0) -> 0 | O91: =IF(F24="Да",SUMIF($H92:$L98,$H91,O92:O98),0) -> 0 | P91: =IF(G24="Да",SUMIF($H92:$L98,$H91,P92:P98),0) -> 1 | Q91: =IF(H24="Да",SUMIF($H92:$L98,$H91,Q92:Q98),0) -> 0 | R91: =IF(I24="Да",SUMIF($H92:$L98,$H91,R92:R98),0) -> 0
B92: 7.22 | H92: I степень - одноконтурное автоматическое регулирование или автоматическое однотактное логическое управление (переключения, блокировки и тому подобное) | M92: 1 | N92: 1 | O92: 1 | P92: 1 | Q92: 1 | R92: 1
B93: 7.2 | H93: II степень - каскадное и (или) программное автоматическое регулирование или автоматическое программное логическое управление по "жесткому" циклу | M93: 3 | N93: 2 | O93: 3 | P93: 3 | Q93: 3 | R93: 3
B94: 7.3 | H94: III степень - многосвязное автоматическое регулирование или автоматическое программное логическое управление по циклу с разветвлениями | M94: 5 | N94: 2 | O94: 5 | P94: 5 | Q94: 5 | R94: 5
B95: 7.4 | H95: IV степень - оптимальное управление установившимися режимами (в статике) | M95: 6 | N95: 3 | O95: 7 | P95: 7 | Q95: 7 | R95: 7
B96: 7.5 | H96: V степень - оптимальное управление переходными процессами или процессом в целом (оптимизация в динамике) | M96: 8 | N96: 4 | O96: 10 | P96: 9 | Q96: 11 | R96: 11
B97: 7.6 | H97: VI степень - оптимальное управление быстропротекающими переходными процессами в аварийных условиях | M97: 9 | N97: 4 | O97: 11 | P97: 10 | Q97: 13 | R97: 13
B98: 7.7 | H98: VII степень - оптимальное управление с адаптацией (самообучением и изменением алгоритмов и параметров системы) | M98: 10 | N98: 5 | O98: 12 | P98: 11 | Q98: 14 | R98: 14
B99: 5 | C99: Ф8 | E99: Режим выполнения управляющих фукций АСУ ТП | H99: Автоматизированный диалоговый режим | M99: =IF(D24="Да",SUMIF($H100:$L104,$H99,M100:M104),0) -> 2 | N99: =IF(E24="Да",SUMIF($H100:$L104,$H99,N100:N104),0) -> 0 | O99: =IF(F24="Да",SUMIF($H100:$L104,$H99,O100:O104),0) -> 0 | P99: =IF(G24="Да",SUMIF($H100:$L104,$H99,P100:P104),0) -> 2 | Q99: =IF(H24="Да",SUMIF($H100:$L104,$H99,Q100:Q104),0) -> 0 | R99: =IF(I24="Да",SUMIF($H100:$L104,$H99,R100:R104),0) -> 0
B100: 5.1 | H100: Автоматизированный "ручной" режим | M100: 1 | N100: 1 | O100: 1 | P100: 1 | Q100: 1 | R100: 1
B101: 5.2 | H101: Автоматизированный режим "советчика" | M101: 1 | N101: 1 | O101: 2 | P101: 1 | Q101: 2 | R101: 2
B102: 5.3 | H102: Автоматизированный диалоговый режим | M102: 2 | N102: 2 | O102: 2 | P102: 2 | Q102: 3 | R102: 3
B103: 5.4 | H103: Автоматический режим косвенного управления | M103: 3 | N103: 2 | O103: 3 | P103: 4 | Q103: 4 | R103: 4
B104: 5.5 | H104: Автоматический режим прямого (непосредственного) цифрового (или аналого-цифрового) управления | M104: 5 | N104: 3 | O104: 5 | P104: 7 | Q104: 7 | R104: 7
B105: 6 | C105: Ф9 | E105: Количество переменных, измеряемых, контролируемых и регистрируемых АСУ ТП | H105: до 20 | M105: =IF(D24="Да",SUMIF($H106:$L119,$H105,M106:M119),0) -> 1 | N105: =IF(E24="Да",SUMIF($H106:$L119,$H105,N106:N119),0) -> 0 | O105: =IF(F24="Да",SUMIF($H106:$L119,$H105,O106:O119),0) -> 0 | P105: =IF(G24="Да",SUMIF($H106:$L119,$H105,P106:P119),0) -> 1 | Q105: =IF(H24="Да",SUMIF($H106:$L119,$H105,Q106:Q119),0) -> 0 | R105: =IF(I24="Да",SUMIF($H106:$L119,$H105,R106:R119),0) -> 0
B106: 6.1 | H106: до 20 | M106: 1 | N106: 1 | O106: 1 | P106: 1 | Q106: 1 | R106: 1
B107: 6.2 | H107: свыше 20 до 50 | M107: 2 | N107: 1 | O107: 2 | P107: 2 | Q107: 2 | R107: 2
...

Sheet 1.8 СПБА этап3
B1: 5
B4: =СВОД!E29 -> Смета №1.8
B5: Этап 3 (Объекты на площадке ГРП 2А) СПБА
B6: Наименование объекта | G6: Сети внутриплощадочные 001 - Технологический корпус №1 002 - Технологический корпус №2 008 - Станция насосная 009 - Здание станции насосной водоснабжения производственного 019 - Здание операторной
B8: Стадия | G8: Рабочая документация
B10: Наименование организации Заказчика
B11: Наименование проектной организации | G11: =СВОД!D14 -> ОАО «СИБНЕФТЕТРАНСПРОЕКТ»
B13: Смета составлена на основании "СБЦ на проектные работы в строительстве "Автоматизированные системы управления технологическими процессами (АСУТП)" (2016г.)
B15: 1. Краткая характеристика объекта автоматизации:
B16: Новое строительство
B17: Новое строительство
B18: Реконструкция, модернизация, тех. перевооружение
B19: Требование на разработку ТЗ к созданию АСУ ТП: | H19: Нет
H20: Да
H21: Нет
B22: Требуемые части документации АСУ ТП:
D23: ОР | E23: ОО | F23: ИО | G23: ТО | H23: МО | I23: ПО
D24: Да | E24: Нет | F24: Нет | G24: Да | H24: Нет | I24: Нет
D25: Да | E25: Да | F25: Да | G25: Да | H25: Да | I25: Да
D26: Нет | E26: Нет | F26: Нет | G26: Нет | H26: Нет | I26: Нет
B27: 2. Исходные данные:
B28: Трудоемкость разработки ТЗ на создание АСУ ТП
B29: Основные факторы, определяющие трудоемкость разработки | M29: Количество баллов
B30: № пп | C30: Фактор | E30: Наименование | H30: Определение | M30: ТЗ
B31: 1 | C31: Ф1 | E31: Степень научно-технической новизны (ТОУ) | H31: I степень - ТОУ имеет действующие аналоги в России и, возможно за рубежом | M31: =IF(H19="Да",SUMIF($H32:$L35,$H31,M32:N35),0) -> 0
B32: 1.1 | H32: I степень - ТОУ имеет действующие аналоги в России и, возможно за рубежом | M32: 1
B33: 1.2 | H33: II степень - ТОУ имеет действующие аналоги только за рубежом | M33: 2
B34: 1.3 | H34: III степень - ни с конструкторской, ни с технологической точек зрения ТОУ не является принципиально новым объектом, но действующих аналогов не имеет | M34: 4
B35: 1.4 | H35: IV степень - с конструкторской и (или) технологической точек зрения ТОУ является принципиально новым объектом | M35: 8
B36: 2 | C36: Ф2 | E36: Характер протекания управляемого технологического процесса во времени | H36: Непрерывный (с длительным поддержанием режимов, близких к установившимся, и практически безостановочной подачей сырья и реагентов) | M36: =IF(H19="Да",SUMIF($H37:$L42,$H36,M37:N42),0) -> 0
B37: 2.1 | H37: Непрерывный (с длительным поддержанием режимов, близких к установившимся, и практически безостановочной подачей сырья и реагентов) | M37: 1
B38: 2.2 | H38: Полунепрерывный (непрерывный, с существенными для управления переходными режимами, вызванными либо добавками (заменами) сырья или реагентов, либо выдачей продукции) | M38: 2
B39: 2.3 | H39: Непрерывно-дискретный - I (сочетающий непрерывные и прерывистые режимы на различных стадиях процесса) | M39: 4
B40: 2.4 | H40: Непрерывно-дискретный - II (сочетающий непрерывные и прерывистые режимы с малой длительностью непрерывных режимов в аварийных условиях) | M40: 5
B41: 2.5 | H41: Циклический (прерывистый, с существенной для управления длительностью интервалов непрерывного функционирования и циклическим следованием интервалов с различными режимами) | M41: 4
B42: 2.6 | H42: Дискретный (прерывистый, с малой, несущественной для управления, длительностью непрерывных технологических операций) | M42: 3
B43: 3 | C43: Ф3 | E43: Количество технологических операций, выполняемых на ТОУ | H43: свыше 10 до 20 | M43: =IF(H19="Да",SUMIF($H44:$L51,$H43,M44:N51),0) -> 0
B44: 3.1 | H44: до 5 | M44: 1
B45: 3.2 | H45: свыше 5 до 10 | M45: 2
B46: 3.3 | H46: свыше 10 до 20 | M46: 4
B47: 3.4 | H47: свыше 20 до 35 | M47: 5
B48: 3.5 | H48: свыше 35 до 50 | M48: 7
B49: 3.6 | H49: свыше 50 до 70 | M49: 9
B50: 3.7 | H50: свыше 70 до 100 | M50: 10
B51: 3.8 | H51: за каждые 50 свыше 100 | M51: 11
B52: 4 | C52: Ф4 | E52: Количество переменных, характеризующих ТОУ | H52: свыше 470 до 600 | M52: =IF(H19="Да",SUMIF($H53:$L66,$H52,M53:N66),0) -> 0
B53: 4.1 | H53: до 20 | M53: 1
B54: 4.2 | H54: свыше 20 до 50 | M54: 2
B55: 4.3 | H55: свыше 50 до 100 | M55: 3
B56: 4.4 | H56: свыше 100 до 170 | M56: 4
B57: 4.5 | H57: свыше 170 до 250 | M57: 5
B58: 4.6 | H58: свыше 250 до 350 | M58: 6
B59: 4.7 | H59: свыше 350 до 470 | M59: 7
B60: 4.8 | H60: свыше 470 до 600 | M60: 8
B61: 4.9 | H61: свыше 600 до 800 | M61: 9
B62: 4.10 | H62: свыше 800 до 1000 | M62: 10
B63: 4.11 | H63: свыше 1000 до 1300 | M63: 11
B64: 4.12 | H64: свыше 1300 до 1600 | M64: 12
... B66: 4.14 | H66: за каждые 500 свыше 2000 | M66: 14
B67: 5 | L67: ИТОГО (ƩБч): | M67: =M31+M36+M43+M52 -> 0
B68: Трудоемкость разработки документации на АСУ ТП
B69: Основные факторы, определяющие трудоемкость разработки | M69: Количество баллов для частей проектной документации (Бч)
B70: № пп | C70: Фактор | E70: Наименование | H70: Определение | M70: ОР | N70: ОО | O70: ИО | P70: ТО | Q70: МО | R70: ПО
B71: 1 | C71: Ф2 | E71: Характер протекания управляемого технологического процесса во времени | H71: Непрерывно-дискретный - I (сочетающий непрерывные и прерывистые режимы на различных стадиях процесса) | M71: =IF(D24="Да",SUMIF($H72:$L77,$H71,M72:M77),0) -> 3 | N71: =IF(E24="Да",SUMIF($H72:$L77,$H71,N72:N77),0) -> 0 | O71: =IF(F24="Да",SUMIF($H72:$L77,$H71,O72:O77),0) -> 0 | P71: =IF(G24="Да",SUMIF($H72:$L77,$H71,P72:P77),0) -> 3 | Q71: =IF(H24="Да",SUMIF($H72:$L77,$H71,Q72:Q77),0) -> 0 | R71: =IF(I24="Да",SUMIF($H72:$L77,$H71,R72:R77),0) -> 0
B72: 1.1 | H72: Непрерывный (с длительным поддержанием режимов, близких к установившимся, и практически безостановочной подачей сырья и реагентов) | M72: 1 | N72: 1 | O72: 1 | P72: 1 | Q72: 1 | R72: 1
B73: 1.2 | H73: Полунепрерывный (непрерывный, с существенными для управления переходными режимами, вызванными либо добавками (заменами) сырья или реагентов, либо выдачей продукции) | M73: 2 | N73: 1 | O73: 2 | P73: 1 | Q73: 2 | R73: 2
B74: 1.3 | H74: Непрерывно-дискретный - I (сочетающий непрерывные и прерывистые режимы на различных стадиях процесса) | M74: 3 | N74: 3 | O74: 3 | P74: 3 | Q74: 3 | R74: 3
B75: 1.4 | H75: Непрерывно-дискретный - II (сочетающий непрерывные и прерывистые режимы с малой длительностью непрерывных режимов в аварийных условиях) | M75: 4 | N75: 3 | O75: 4 | P75: 3 | Q75: 4 | R75: 4
B76: 1.5 | H76: Циклический (прерывистый, с существенной для управления длительностью интервалов непрерывного функционирования и циклическим следованием интервалов с различными режимами) | M76: 3 | N76: 2 | O76: 3 | P76: 2 | Q76: 3 | R76: 3
B77: 1.6 | H77: Дискретный (прерывистый, с малой, несущественной для управления, длительностью непрерывных технологических операций) | M77: 2 | N77: 2 | O77: 2 | P77: 2 | Q77: 3 | R77: 3
B78: 2 | C78: Ф5 | E78: Количество технологических операций, контролируемых или управляемых АСУ ТП | H78: свыше 5 до 10 | M78: =IF(D24="Да",SUMIF($H79:$L85,$H78,M79:M85),0) -> 2 | N78: =IF(E24="Да",SUMIF($H79:$L85,$H78,N79:N85),0) -> 0 | O78: =IF(F24="Да",SUMIF($H79:$L85,$H78,O79:O85),0) -> 0 | P78: =IF(G24="Да",SUMIF($H79:$L85,$H78,P79:P85),0) -> 2 | Q78: =IF(H24="Да",SUMIF($H79:$L85,$H78,Q79:Q85),0) -> 0 | R78: =IF(I24="Да",SUMIF($H79:$L85,$H78,R79:R85),0) -> 0
B79: 2.1 | E79: За каждые 50 свыше 100 начисляется еще по баллу | H79: до 5 | M79: 1 | N79: 1 | O79: 1 | P79: 1 | Q79: 1 | R79: 1
B80: 2.2 | H80: свыше 5 до 10 | M80: 2 | N80: 2 | O80: 2 | P80: 2 | Q80: 2 | R80: 2
B81: 2.3 | H81: свыше 10 до 20 | M81: 3 | N81: 2 | O81: 3 | P81: 2 | Q81: 3 | R81: 3
B82: 2.4 | H82: свыше 20 до 35 | M82: 4 | N82: 3 | O82: 4 | P82: 3 | Q82: 4 | R82: 4
B83: 2.5 | H83: свыше 35 до 50 | M83: 5 | N83: 3 | O83: 5 | P83: 3 | Q83: 5 | R83: 5
B84: 2.6 | H84: свыше 50 до 70 | M84: 6 | N84: 4 | O84: 6 | P84: 4 | Q84: 6 | R84: 6
B85: 2.7 | H85: свыше 70 до 100 | M85: 7 | N85: 5 | O85: 7 | P85: 5 | Q85: 7 | R85: 7
B86: 3 | C86: Ф6 | E86: Степень развитости информационных функций АСУ ТП | H86: II степень - централизованный контроль и измерение параметров состояния ТОУ | M86: =IF(D24="Да",SUMIF($H87:$L90,$H86,M87:M90),0) -> 3 | N86: =IF(E24="Да",SUMIF($H87:$L90,$H86,N87:N90),0) -> 0 | O86: =IF(F24="Да",SUMIF($H87:$L90,$H86,O87:O90),0) -> 0 | P86: =IF(G24="Да",SUMIF($H87:$L90,$H86,P87:P90),0) -> 3 | Q86: =IF(H24="Да",SUMIF($H87:$L90,$H86,Q87:Q90),0) -> 0 | R86: =IF(I24="Да",SUMIF($H87:$L90,$H86,R87:R90),0) -> 0
B87: 3.1 | H87: I степень - параллельные контроль и измерение параметров состояния ТОУ | M87: 1 | N87: 1 | O87: 1 | P87: 1 | Q87: 1 | R87: 1
B88: 3.2 | H88: II степень - централизованный контроль и измерение параметров состояния ТОУ | M88: 3 | N88: 2 | O88: 3 | P88: 3 | Q88: 3 | R88: 3
B89: 3.3 | H89: III степень - косвенное измерение (вычисление) отдельных комплексных показателей функционирования ТОУ | M89: 6 | N89: 2 | O89: 6 | P89: 5 | Q89: 6 | R89: 6
B90: 3.4 | H90: IV степень - анализ и обобщенная оценка состояния процесса в целом по его модели (распознавание ситуаций, диагностика аварийных состояний, поиск "узкого места", прогноз хода процесса) | M90: 9 | N90: 3 | O90: 9 | P90: 8 | Q90: 9 | R90: 9
B91: 4 | C91: Ф7 | E91: Степень развитости управляющих функций АСУ ТП | H91: II степень - каскадное и (или) программное автоматическое регулирование или автоматическое программное логическое управление по "жесткому" циклу | M91: =IF(D24="Да",SUMIF($H92:$L98,$H91,M92:M98),0) -> 3 | N91: =IF(E24="Да",SUMIF($H92:$L98,$H91,N92:N98),0) -> 0 | O91: =IF(F24="Да",SUMIF($H92:$L98,$H91,O92:O98),0) -> 0 | P91: =IF(G24="Да",SUMIF($H92:$L98,$H91,P92:P98),0) -> 3 | Q91: =IF(H24="Да",SUMIF($H92:$L98,$H91,Q92:Q98),0) -> 0 | R91: =IF(I24="Да",SUMIF($H92:$L98,$H91,R92:R98),0) -> 0
B92: 7.22 | H92: I степень - одноконтурное автоматическое регулирование или автоматическое однотактное логическое управление (переключения, блокировки и тому подобное) | M92: 1 | N92: 1 | O92: 1 | P92: 1 | Q92: 1 | R92: 1
B93: 7.2 | H93: II степень - каскадное и (или) программное автоматическое регулирование или автоматическое программное логическое управление по "жесткому" циклу | M93: 3 | N93: 2 | O93: 3 | P93: 3 | Q93: 3 | R93: 3
B94: 7.3 | H94: III степень - многосвязное автоматическое регулирование или автоматическое программное логическое управление по циклу с разветвлениями | M94: 5 | N94: 2 | O94: 5 | P94: 5 | Q94: 5 | R94: 5
B95: 7.4 | H95: IV степень - оптимальное управление установившимися режимами (в статике) | M95: 6 | N95: 3 | O95: 7 | P95: 7 | Q95: 7 | R95: 7
B96: 7.5 | H96: V степень - оптимальное управление переходными процессами или процессом в целом (оптимизация в динамике) | M96: 8 | N96: 4 | O96: 10 | P96: 9 | Q96: 11 | R96: 11
B97: 7.6 | H97: VI степень - оптимальное управление быстропротекающими переходными процессами в аварийных условиях | M97: 9 | N97: 4 | O97: 11 | P97: 10 | Q97: 13 | R97: 13
B98: 7.7 | H98: VII степень - оптимальное управление с адаптацией (самообучением и изменением алгоритмов и параметров системы) | M98: 10 | N98: 5 | O98: 12 | P98: 11 | Q98: 14 | R98: 14
B99: 5 | C99: Ф8 | E99: Режим выполнения управляющих фукций АСУ ТП | H99: Автоматический режим прямого (непосредственного) цифрового (или аналого-цифрового) управления | M99: =IF(D24="Да",SUMIF($H100:$L104,$H99,M100:M104),0) -> 5 | N99: =IF(E24="Да",SUMIF($H100:$L104,$H99,N100:N104),0) -> 0 | O99: =IF(F24="Да",SUMIF($H100:$L104,$H99,O100:O104),0) -> 0 | P99: =IF(G24="Да",SUMIF($H100:$L104,$H99,P100:P104),0) -> 7 | Q99: =IF(H24="Да",SUMIF($H100:$L104,$H99,Q100:Q104),0) -> 0 | R99: =IF(I24="Да",SUMIF($H100:$L104,$H99,R100:R104),0) -> 0
B100: 5.1 | H100: Автоматизированный "ручной" режим | M100: 1 | N100: 1 | O100: 1 | P100: 1 | Q100: 1 | R100: 1
B101: 5.2 | H101: Автоматизированный режим "советчика" | M101: 1 | N101: 1 | O101: 2 | P101: 1 | Q101: 2 | R101: 2
B102: 5.3 | H102: Автоматизированный диалоговый режим | M102: 2 | N102: 2 | O102: 2 | P102: 2 | Q102: 3 | R102: 3
B103: 5.4 | H103: Автоматический режим косвенного управления | M103: 3 | N103: 2 | O103: 3 | P103: 4 | Q103: 4 | R103: 4
B104: 5.5 | H104: Автоматический режим прямого (непосредственного) цифрового (или аналого-цифрового) управления | M104: 5 | N104: 3 | O104: 5 | P104: 7 | Q104: 7 | R104: 7
B105: 6 | C105: Ф9 | E105: Количество переменных, измеряемых, контролируемых и регистрируемых АСУ ТП | H105: свыше 100 до 170 | M105: =IF(D24="Да",SUMIF($H106:$L119,$H105,M106:M119),0) -> 3 | N105: =IF(E24="Да",SUMIF($H106:$L119,$H105,N106:N119),0) -> 0 | O105: =IF(F24="Да",SUMIF($H106:$L119,$H105,O106:O119),0) -> 0 | P105: =IF(G24="Да",SUMIF($H106:$L119,$H105,P106:P119),0) -> 4 | Q105: =IF(H24="Да",SUMIF($H106:$L119,$H105,Q106:Q119),0) -> 0 | R105: =IF(I24="Да",SUMIF($H106:$L119,$H105,R106:R119),0) -> 0
B106: 6.1 | H106: до 20 | M106: 1 | N106: 1 | O106: 1 | P106: 1 | Q106: 1 | R106: 1
B107: 6.2 | H107: свыше 20 до 50 | M107: 2 | N107: 1 | O107: 2 | P107: 2 | Q107: 2 | R107: 2
...

Sheet 1.9 СС
E1: Форма 2П
A3: =СВОД!E30 -> Смета №1.9
A4: на проектные работы
B6: Наименование объекта, стадии, этапа проектных работ | C6: =СВОД!B30 -> Сети связи и сигнализации
C7: Этап 3
B8: Наименование проектной | C8: =СВОД!D14 -> ОАО «СИБНЕФТЕТРАНСПРОЕКТ»
B9: (изыскательской) организации
B11: Наименование организации | C11: =СВОД!D16 -> ООО «Газпром проектирование»
B12: заказчика
A14: № пп. | B14: Характеристика предприятия, здания, сооружения или виды работ | C14: Номер частей, глав, таблиц, процентов, параграфов и пунктов указаний к разделу Справочника базовых цен на проектные и изыскательские работы для строительства | D14: Расчет стоимости: (a+bx)*Ki, или (объем строительно-монтажных работ) * проц./100 или количество x цена | E14: Стоимость, руб.
A15: 1 | B15: 2 | C15: 3 | D15: 4 | E15: 5
A17: 001 - Технологический корпус №1
A18: 1 | B18: Пожарная сигнализация на площади 80,8*15= 1212м2 | C18: СБЦ на ПРС "Системы противопожарной и охранной защиты" (табл. 3 п.6) | D18: 2304x0,6x55,26x1,5x1,2x1,1x1,3 | E18: =2304*0.6*55.26*1.5*1.2*1.1*1.3 -> 196631.53
C19: К=0,6(стадия Р)
C20: К=55,26(инфляц.)
C21: К=1,5 п.3 (управление ПЗ и ПБ)
C22: К=1,2 п.2.2 (установка вне здания РПИ)
C23: К=1,1 п.2.5 (вынос оборудования из здания)
C24: К=1,3 п.2.5 (взрывоопасность )
A25: 2 | B25: Система оповещения людей о пожаре на площади 80,8*15= 1212м2 | C25: СБЦ на ПРС "Системы противопожарной и охранной защиты" (табл. 4 п.6) | D25: 1843x0,6x55,26x1,4x1,1x1,3 | E25: =1843*0.6*55.26*1.4*1.1*1.3 -> 122335.23
C26: К=0,6(стадия Р)
C27: К=55,26(инфляц.)
C28: К=1,4 (тип 3)
C29: К=1,1 п.2.5 (вынос оборудования из здания)
C30: К=1,3 п.2.5 (взрывоопасность)
A31: 3 | B31: Установка оперативно-диспетчерской связи до 50 | C31: СБЦ ПР для стр-ва, объекты связи, 2010г. (табл.9 п.1) | D31: (1020+15x15)x0,52x7,22 | E31: =(1020+15*15)*0.52*7.22 -> 4674.228
C32: К=0,52(стадия Р)
C33: К=7,22 (инфляц.)
A34: 4 | B34: Производственная громкоговорящая связь 12 абонентов | C34: СБЦ ПР для стр-ва, объекты связи, 2010г. (табл.9 п.4) | D34: (1650+76x15)x0,52x7,22 | E34: =(1650+76*15)*0.52*7.22 -> 10474.776
C35: К=0,52(стадия Р)
C36: К=7,22 (инфляц.)
A37: 5 | B37: Сеть комплексная средств связи и передачи информации на промплощадке 50 пар (телефон,ГГС) | C37: СЦБ ПР для стр-ва, объекты связи (табл.9 п.11) | D37: (1950+19x10)x0,52x7,22 | E37: =(1950+19*10)*0.52*7.22 -> 8034.416
C38: К=0,52(стадия Р)
C39: К=7,22 (инфляц.)
A40: 6 | B40: Локальная вычислительная сеть с числом узлов 1 | C40: СБЦ ПР для стр-ва, объекты связи, 2010г. (табл.24 п.2) | D40: (2450+3680x1)x0,5x7,22 | E40: =(2450+3680*1)*0.5*7.22 -> 22129.3
C41: К=0,5 (стадия Р)
C42: К=7,22 (инфляц.)
A43: 7 | B43: СКС в здании | C43: СБЦ ПР для стр-ва, объекты связи, 2010г. (табл.24 п.8) | D43: (2450+3680x15)x0,5x7,22 | E43: =(2450+3680*15)*0.5*7.22 -> 208116.5
C44: К=0,5 (стадия Р)
C45: К=7,22 (инфляц.)
A46: 8 | B46: СПД до 100 каналов (ГПТ+контроллер проект в СПБА) | C46: СЦБ ПР для стр-ва, объекты связи (табл.2 п.2) | D46: (25980+4623x20)x0,58x7,22 | E46: =(25980+4623*20)*0.58*7.22 -> 495979.34
C47: К=0,58 (стадия Р)
C48: К=7,22 (инфляц.)
B49: ИТОГО 001 - Технологический корпус №1: | E49: =SUM(E18:E48) -> 1068375.3
A50: 002 - Технологический корпус №2
A51: 9 | B51: Пожарная сигнализация на площади 72*15= 1080 м2 | C51: СБЦ на ПРС "Системы противопожарной и охранной защиты" (табл. 3 п.6) | D51: 2304x0,6x55,26x1,5x1,2x1,1x1,3 | E51: =2304*0.6*55.26*1.5*1.2*1.1*1.3 -> 196631.53
C52: К=0,6(стадия Р)
C53: К=55,26(инфляц.)
C54: К=1,5 п.3 (управление ПЗ и ПБ)
C55: К=1,2 п.2.2 (установка вне здания РПИ)
C56: К=1,1 п.2.5 (вынос оборудования из здания)
C57: К=1,3 п.2.5 (взрывоопасность )
A58: 10 | B58: Система оповещения людей о пожаре на площади 72*15= 1080 м2 | C58: СБЦ на ПРС "Системы противопожарной и охранной защиты" (табл. 4 п.6) | D58: 1843x0,6x55,26x1,4x1,1x1,3 | E58: =1843*0.6*55.26*1.4*1.1*1.3 -> 122335.23
C59: К=0,6(стадия Р)
C60: К=55,26(инфляц.)
C61: К=1,4 (тип 3)
C62: К=1,1 п.2.5 (вынос оборудования из здания)
C63: К=1,3 п.2.5 (взрывоопасность)
A64: 11 | B64: Установка оперативно-диспетчерской связи до 50 | C64: СБЦ ПР для стр-ва, объекты связи, 2010г. (табл.9 п.1) | D64: (1020+15x15)x0,52x7,22 | E64: =(1020+15*15)*0.52*7.22 -> 4674.228
C65: К=0,52(стадия Р)
C66: К=7,22 (инфляц.)
A67: 12 | B67: Производственная громкоговорящая связь 12 абонентов | C67: СБЦ ПР для стр-ва, объекты связи, 2010г. (табл.9 п.4) | D67: (1650+76x15)x0,52x7,22 | E67: =(1650+76*15)*0.52*7.22 -> 10474.776
C68: К=0,52(стадия Р)
C69: К=7,22 (инфляц.)
A70: 13 | B70: Сеть комплексная средств связи и передачи информации на промплощадке 50 пар (телефон,ГГС) | C70: СЦБ ПР для стр-ва, объекты связи (табл.9 п.11) | D70: (1950+19x10)x0,52x7,22 | E70: =(1950+19*10)*0.52*7.22 -> 8034.416
C71: К=0,52(стадия Р)
C72: К=7,22 (инфляц.)
A73: 14 | B73: Локальная вычислительная сеть с числом узлов 1 | C73: СБЦ ПР для стр-ва, объекты связи, 2010г. (табл.24 п.2) | D73: (2450+3680x1)x0,5x7,22 | E73: =(2450+3680*1)*0.5*7.22 -> 22129.3
C74: К=0,5 (стадия Р)
C75: К=7,22 (инфляц.)
A76: 15 | B76: СКС в здании | C76: СБЦ ПР для стр-ва, объекты связи, 2010г. (табл.24 п.8) | D76: (2450+3680x15)x0,5x7,22 | E76: =(2450+3680*15)*0.5*7.22 -> 208116.5
C77: К=0,5 (стадия Р)
C78: К=7,22 (инфляц.)
A79: 16 | B79: СПД до 100 каналов (ГПТ+контроллер проект в СПБА) | C79: СЦБ ПР для стр-ва, объекты связи (табл.2 п.2) | D79: (25980+4623x20)x0,58x7,22 | E79: =(25980+4623*20)*0.58*7.22 -> 495979.34
C80: К=0,58 (стадия Р)
C81: К=7,22 (инфляц.)
B82: ИТОГО 002 - Технологический корпус №2: | E82: =SUM(E51:E81) -> 1068375.3
A83: 008 - Станция насосная
A84: 17 | B84: Пожарная сигнализация на площади 27,5*9=248 м2 | C84: СБЦ на ПРС "Системы противопожарной и охранной защиты" (табл. 3 п.3) | D84: 820x0,6x55,26x1,5x1,2x1,1x1,3 | E84: =820*0.6*55.26*1.5*1.2*1.1*1.3 -> 69981.706
C85: К=0,6(стадия Р)
C86: К=55,26(инфляц.)
C87: К=1,5 п.3 (управление ПЗ и ПБ)
C88: К=1,2 п.2.2 (установка вне здания РПИ)
C89: К=1,1 п.2.5 (вынос оборудования из здания)
C90: К=1,3 п.2.5 (взрывоопасность )
A91: 18 | B91: Система оповещения людей о пожаре на площади 27,5*9=248 м2 | C91: СБЦ на ПРС "Системы противопожарной и охранной защиты" (табл. 4 п.3) | D91: 656x0,6x55,26x1,4x1,1x1,3 | E91: =656*0.6*55.26*1.4*1.1*1.3 -> 43544.173
C92: К=0,6(стадия Р)
C93: К=55,26(инфляц.)
C94: К=1,4 (тип 3)
C95: К=1,1 п.2.5 (вынос оборудования из здания)
C96: К=1,3 п.2.5 (взрывоопасность)
A97: 19 | B97: Установка оперативно-диспетчерской связи до 50 | C97: СБЦ ПР для стр-ва, объекты связи, 2010г. (табл.9 п.1) | D97: (1020+15x11)x0,52x7,22 | E97: =(1020+15*11)*0.52*7.22 -> 4448.964
C98: К=0,52(стадия Р)
C99: К=7,22 (инфляц.)
A100: 20 | B100: Производственная громкоговорящая связь 12 абонентов | C100: СБЦ ПР для стр-ва, объекты связи, 2010г. (табл.9 п.4) | D100: (1650+76x11)x0,52x7,22 | E100: =(1650+76*11)*0.52*7.22 -> 9333.4384
C101: К=0,52(стадия Р)
C102: К=7,22 (инфляц.)
A103: 21 | B103: Сеть комплексная средств связи и передачи информации на промплощадке 50 пар (телефон,ГГС) | C103: СЦБ ПР для стр-ва, объекты связи (табл.9 п.11) | D103: (1950+19x10)x0,52x7,22 | E103: =(1950+19*10)*0.52*7.22 -> 8034.416
C104: К=0,52(стадия Р)
C105: К=7,22 (инфляц.)
...

Sheet 1.10 ЭС+
E1: Форма 2П
A3: =СВОД!E31 -> Смета №1.10
A4: на проектные работы
B6: Наименование объекта, стадии, этапа проектных работ | C6: =СВОД!B31 -> Электроснабжение
B8: Наименование проектной | C8: =СВОД!D14 -> ОАО «СИБНЕФТЕТРАНСПРОЕКТ»
B9: (изыскательской) организации
B11: Наименование организации | C11: =СВОД!D16 -> ООО «Газпром проектирование»
B12: заказчика
A14: № пп. | B14: Характеристика предприятия, здания, сооружения или виды работ | C14: Номер частей, глав, таблиц, процентов, параграфов и пунктов указаний к разделу Справочника базовых цен на проектные и изыскательские работы для строительства | D14: Расчет стоимости: (a+bx)*Ki, или (объем строительно-монтажных работ) * проц./100 или количество x цена | E14: Стоимость, руб.
A15: 1 | B15: 2 | C15: 3 | D15: 4 | E15: 5
A17: Этап 3 (Объекты на площадке ГРП 2А)
A18: 1 - Технологический корпус №1
A19: 1 | B19: Установка низковольтных щитов управления (НКУ-0,4 кВ), в помещении размером до 20 м2. Всего 6 шт. (компл. ЭМ, ЭО) | C19: СБЦ на проектные работы "Объекты магистрального транспорта нефти". т.4, п.24.2. | D19: 21120x6x7,22x0,6x1,08 | E19: =21120*6*7.22*0.6*1.08 -> 592867.12
C20: К1=7,22-инфляционный коэффициент
C21: К2=0,6 - ст. "Р"
C22: К3=1,08 - районный коэф-т
A23: 2 | B23: Проектирование системы бесперебойного питания , системы постоянного тока. Всего 4 панели. (ЭМ) | C23: СБЦ «Газооборудование и газоснабжение промышленных предприятий, зданий и сооружений», 2015г., таб. 19, п.1. | D23: 11083x4x7,22x0,6x1,08 | E23: 11083*4*7,22*0,6*1,08
C24: К1=7,22-инфляционный коэффициент
C25: К2=0,6 - Cтадия "Р"
C26: К3=1,08 - районный коэф-т
A27: 3 | B27: Прокладка кабельных линий 0,4 кВ до потребителей по кабельным конструкциям. Суммарная протяжённость трассы -0,6 км. (ЭМ, ЭМ1, ЭО) | C27: СБЦ «Объекты нефтеперерабатывающей и нефтехимической промышленности», 2015 г, табл.8, п.2.10. | D27: 433690x0,6x7,22x0,6x1,08 | E27: =433690*0.6*7.22*0.6*1.08 -> 1217426.8
C28: К1=7,22-инфляционный коэффициент
C29: К2=0,6 - ст. "Р"
C30: К3=1,08 - районный коэф-т
A31: 4 | B31: Расчет токов короткого замыкания в сети 0,4 кВ. Всего 9 линий.(ЭМ,ЭО) | C31: СБЦ «Объекты нефтеперерабатывающей и нефтехимической промышленность», 2015г, таб.11 п.19. | D31: 10070x9x7,22x0,6x1,08 | E31: =10070*9*7.22*0.6*1.08 -> 424017.89
C32: К1=7,22-инфляционный коэффициент
C33: К2=0,6 - ст. "Р"
C34: К3=1,08 - районный коэф-т
A35: 5 | B35: Проектирование заземляющего устройства зданий и сооружений. Всего 1 объект (ЭМ1) | C35: СБЦ на проектные работы "Объекты магистрального транспорта нефти". т.4, п.22.1. | D35: 8870x1x7,22x0,6x1,08 | E35: =8870*1*7.22*0.6*1.08 -> 41498.827
C36: К1=7,22-инфляционный коэффициент
C37: К2=0,6 - ст. "Р"
C38: К3=1,08 - районный коэф-т
A39: 6 | B39: Рассмотрение конструкторской документации на оборудование, предоставляемой Заказчиком от заводов-изготовителей или поставщиков до ее окончательного утверждения, при необходимости корректировка проекта с учетом утвержденных Заказчиком материалов конструкторской документации заводов-изготовителей. | C39: Методические указания от 29.12.2009 г. Часть III п.3.9. До 2% от цены разработки документации по пп.1, 2 | D39: 800277,04512x0,02 | E39: =800277.04512*0.02 -> 16005.541
A40: 2 - Технологический корпус №2
A41: 1 | B41: Установка низковольтных щитов управления (НКУ-0,4 кВ), в помещении размером до 20 м2. Всего 6 шт. (компл. ЭМ, ЭО) | C41: СБЦ на проектные работы "Объекты магистрального транспорта нефти". т.4, п.24.2. | D41: 21120x6x7,22x0,6x1,08 | E41: =21120*6*7.22*0.6*1.08 -> 592867.12
C42: К1=7,22-инфляционный коэффициент
C43: К2=0,6 - ст. "Р"
C44: К3=1,08 - районный коэф-т
A45: 2 | B45: Проектирование системы бесперебойного питания , системы постоянного тока. Всего 4 панели. (ЭМ) | C45: СБЦ «Газооборудование и газоснабжение промышленных предприятий, зданий и сооружений», 2015г., таб. 19, п.1. | D45: 11083x4x7,22x0,6x1,08 | E45: =11083*4*7.22*0.6*1.08 -> 207409.92
C46: К1=7,22-инфляционный коэффициент
C47: К2=0,6 - Cтадия "Р"
C48: К3=1,08 - районный коэф-т
A49: 3 | B49: Прокладка кабельных линий 0,4 кВ до потребителей по кабельным конструкциям. Суммарная протяжённость трассы -0,6 км. (ЭМ, ЭМ1, ЭО) | C49: СБЦ «Объекты нефтеперерабатывающей и нефтехимической промышленности», 2015 г, табл.8, п.2.10. | D49: 433690x0,6x7,22x0,6x1,08 | E49: =433690*0.6*7.22*0.6*1.08 -> 1217426.8
C50: К1=7,22-инфляционный коэффициент
C51: К2=0,6 - ст. "Р"
C52: К3=1,08 - районный коэф-т
A53: 4 | B53: Расчет токов короткого замыкания в сети 0,4 кВ. Всего 9 линий.(ЭМ,ЭО) | C53: СБЦ «Объекты нефтеперерабатывающей и нефтехимической промышленность», 2015г, таб.11 п.19. | D53: 10070x9x7,22x0,6x1,08 | E53: =10070*9*7.22*0.6*1.08 -> 424017.89
C54: К1=7,22-инфляционный коэффициент
C55: К2=0,6 - ст. "Р"
C56: К3=1,08 - районный коэф-т
A57: 5 | B57: Проектирование заземляющего устройства зданий и сооружений. Всего 1 объект (ЭМ1) | C57: СБЦ на проектные работы "Объекты магистрального транспорта нефти". т.4, п.22.1. | D57: 8870x1x7,22x0,6x1,08 | E57: =8870*1*7.22*0.6*1.08 -> 41498.827
C58: К1=7,22-инфляционный коэффициент
C59: К2=0,6 - ст. "Р"
C60: К3=1,08 - районный коэф-т
A61: 6 | B61: Рассмотрение конструкторской документации на оборудование, предоставляемой Заказчиком от заводов-изготовителей или поставщиков до ее окончательного утверждения, при необходимости корректировка проекта с учетом утвержденных Заказчиком материалов конструкторской документации заводов-изготовителей. | C61: Методические указания от 29.12.2009 г. Часть III п.3.9. До 2% от цены разработки документации по пп.1, 2 | D61: 800277,04512x0,02 | E61: =800277.04512*0.02 -> 16005.541
A62: 8 - Технологическая насосная
A63: 1 | B63: Установка низковольтных щитов управления (НКУ-0,4 кВ), в помещении размером до 20 м2. Всего 5 шт. (компл. ЭМ, ЭО) | C63: СБЦ на проектные работы "Объекты магистрального транспорта нефти". т.4, п.24.2. | D63: 21120x5x7,22x0,6x1,08 | E63: =21120*5*7.22*0.6*1.08 -> 494055.94
C64: К1=7,22-инфляционный коэффициент
C65: К2=0,6 - ст. "Р"
C66: К3=1,08 - районный коэф-т
A67: 2 | B67: Устройство ЧРП для электронасосной дозирования . Всего 2 шт | C67: СБЦ на проектные работы "Объекты магистрального транспорта нефти". т.4, п.47. | D67: 400910x(1+(1*0,5))x7,22x0,6x0,35x1,08 | E67: =400910*(1+(1*0.5))*7.22*0.6*0.35*1.08 -> 984732.78
C68: К1=7,22-инфляционный коэффициент
C69: К2=0,6 - ст. "Р"
C70: К3=0,35 - Методические указания от 29.12.2009 г. Часть III п.3.2
C71: К4=1,08 - районный коэф-т
A72: 3 | B72: Прокладка кабельных линий 0,4 кВ до потребителей по кабельным конструкциям. Суммарная протяжённость трассы -0,3 км. (ЭМ, ЭО) | C72: СБЦ «Объекты нефтеперерабатывающей и нефтехимической промышленности», 2015 г, табл.8, п.2.10. | D72: 433690x0,3x7,22x0,6x1,08 | E72: =433690*0.3*7.22*0.6*1.08 -> 608713.41
C73: К1=7,22-инфляционный коэффициент
C74: К2=0,6 - ст. "Р"
C75: К3=1,08 - районный коэф-т
A76: 4 | B76: Расчет токов короткого замыкания в сети 0,4 кВ. Всего 9 линий.(ЭМ,ЭО) | C76: СБЦ «Объекты нефтеперерабатывающей и нефтехимической промышленность», 2015г, таб.11 п.19. | D76: 10070x9x7,22x0,6x1,08 | E76: =10070*9*7.22*0.6*1.08 -> 424017.89
C77: К1=7,22-инфляционный коэффициент
C78: К2=0,6 - ст. "Р"
C79: К3=1,08 - районный коэф-т
A80: 5 | B80: Проектирование заземляющего устройства зданий и сооружений. Всего 1 объект (ЭМ) | C80: СБЦ на проектные работы "Объекты магистрального транспорта нефти". т.4, п.22.1. | D80: 8870x1x7,22x0,6x1,08 | E80: =8870*1*7.22*0.6*1.08 -> 41498.827
C81: К1=7,22-инфляционный коэффициент
C82: К2=0,6 - ст. "Р"
C83: К3=1,08 - районный коэф-т
A84: 6 | B84: Рассмотрение конструкторской документации на оборудование, предоставляемой Заказчиком от заводов-изготовителей или поставщиков до ее окончательного утверждения, при необходимости корректировка проекта с учетом утвержденных Заказчиком материалов конструкторской документации заводов-изготовителей. | C84: Методические указания от 29.12.2009 г. Часть III п.3.9. До 2% от цены разработки документации по пп.1, 2 | D84: 1478788,71804x0,02 | E84: =1478788.71804*0.02 -> 29575.774
A85: 9 - Водопроводная насосная станция
A86: 1 | B86: Установка низковольтных щитов управления (НКУ-0,4 кВ), в помещении размером до 20 м2. Всего 5 шт. (компл. ЭМ, ЭО) | C86: СБЦ на проектные работы "Объекты магистрального транспорта нефти". т.4, п.24.2. | D86: 21120x5x7,22x0,6x1,08 | E86: =21120*5*7.22*0.6*1.08 -> 494055.94
C87: К1=7,22-инфляционный коэффициент
C88: К2=0,6 - ст. "Р"
C89: К3=1,08 - районный коэф-т
A90: 2 | B90: Прокладка кабельных линий 0,4 кВ до потребителей по кабельным конструкциям. Суммарная протяжённость трассы -0,15 км. (ЭМ, ЭО) | C90: СБЦ «Объекты нефтеперерабатывающей и нефтехимической промышленности», 2015 г, табл.8, п.2.10. | D90: 433690x0,15x7,22x0,6x1,08 | E90: =433690*0.15*7.22*0.6*1.08 -> 304356.7
C91: К1=7,22-инфляционный коэффициент
C92: К2=0,6 - ст. "Р"
C93: К3=1,08 - районный коэф-т
A94: 3 | B94: Расчет токов короткого замыкания в сети 0,4 кВ. Всего 9 линий.(ЭМ,ЭО) | C94: СБЦ «Объекты нефтеперерабатывающей и нефтехимической промышленность», 2015г, таб.11 п.19. | D94: 10070x9x7,22x0,6x1,08 | E94: =10070*9*7.22*0.6*1.08 -> 424017.89
C95: К1=7,22-инфляционный коэффициент
C96: К2=0,6 - ст. "Р"
C97: К3=1,08 - районный коэф-т
A98: 4 | B98: Проектирование заземляющего устройства зданий и сооружений. Всего 1 объект (ЭМ) | C98: СБЦ на проектные работы "Объекты магистрального транспорта нефти". т.4, п.22.1. | D98: 8870x1x7,22x0,6x1,08 | E98: =8870*1*7.22*0.6*1.08 -> 41498.827
C99: К1=7,22-инфляционный коэффициент
C100: К2=0,6 - ст. "Р"
C101: К3=1,08 - районный коэф-т
A102: 5 | B102: Рассмотрение конструкторской документации на оборудование, предоставляемой Заказчиком от заводов-изготовителей или поставщиков до ее окончательного утверждения, при необходимости корректировка проекта с учетом утвержденных Заказчиком материалов конструкторской документации заводов-изготовителей. | C102: Методические указания от 29.12.2009 г. Часть III п.3.9. До 2% от цены разработки документации по пп.1, 2 | D102: 798412,63896x0,02 | E102: =798412.63896*0.02 -> 15968.253
A103: 14 - Блочно-комплектная автоматизированная дизельная электростанция "БКАЭ-0,4-400-К"
A104: 1 | B104: Проектирование аварийной дизельной электростанции (АДЭС). Всего одна АДЭС мощностью 400 кВт. | C104: таб. 3.15 п.1.Приложение к приказу №847/пр от 13.12.2023 | D104: (224900+1742x400)x1,71x0,6x1,08x0,35 | E104: =(224900+1742*400)*1.71*0.6*1.08*0.35 -> 357461.07
C105: К1=1,71-инфляционный коэффициент
C106: К2=0,6 - ст. "Р"
...

Sheet 1.11 ЭХЗ+
E1: Форма 2П
A3: =СВОД!E32 -> Смета №1.11
A4: на проектные работы
B6: Наименование объекта, стадии, этапа проектных работ | C6: =СВОД!B32 -> Электрохимическая защита
B8: Наименование проектной | C8: =СВОД!D14 -> ОАО «СИБНЕФТЕТРАНСПРОЕКТ»
B9: (изыскательской) организации
B11: Наименование организации | C11: =СВОД!D16 -> ООО «Газпром проектирование»
B12: заказчика
A14: № пп. | B14: Характеристика предприятия, здания, сооружения или виды работ | C14: Номер частей, глав, таблиц, процентов, параграфов и пунктов указаний к разделу Справочника базовых цен на проектные и изыскательские работы для строительства | D14: Расчет стоимости: (a+bx)*Ki, или (объем строительно-монтажных работ) * проц./100 или количество x цена | E14: Стоимость, руб.
A15: 1 | B15: 2 | C15: 3 | D15: 4 | E15: 5
A17: Этап 3 (Объекты на площадке ГРП 2А)
A18: 4212.012.Р.3/0.0004.ГРП.02А.00000.000-ЭХЗ1, 4212.012.Р.3/0.0004.ГРП.02А.00000.000-ЭХЗ2, 4212.012.Р.3/0.0004.ГРП.02А.00000.000-ЭХЗ3
A19: 1 | B19: Электрозащитная установка от коррозии (катодная, электродренажная). От 1 до 5 установок. Всего 1 установка | C19: СБЦ-2015 (Приказ Минстроя от 27.02.2015 № 140/пр, приложение №4 "СБЦ на преоктные работы в строительстве "Газооборудование и газоснабжение промышленных предприятий, зданий и сооружений" табл. 16 п.1 | D19: (5148+30850x1)x7,22x0,6 | E19: =(5148+30850*1)*7.22*0.6 -> 155943.34
C20: К1=7,22-инфляционный коэффициент
C21: К2=0,6 Cтадия "Р"
A22: 2 | B22: Проектирование вентильных перемычек (блоки БСЗ)..Всего 4 установки | C22: СБЦ-2015 (Приказ Минстроя от 27.02.2015 № 140/пр, приложение №4 "СБЦ на преоктные работы в строительстве "Газооборудование и газоснабжение промышленных предприятий, зданий и сооружений" табл. 16 п.1 | D22: (5148+30850x4)x7,22x0,6x0,031 | E22: =(5148+30850*4)*7.22*0.6*0.031 -> 17262.968
C23: К1=7,22-инфляционный коэффициент
C24: К2=0,6 Cтадия "Р"
C25: К3=0,031 п.2.4.3 СБЦ
A26: 3 | B26: Проектирование глубинного анадного заземлителя (ГАЗ). Всего 8 шт | C26: СБЦ-2015 "Газооборудование и газоснабжение промышленных предприятий, зданий и сооружений" глава 2.4 п. 2.4.2 ,табл. 19 п.4 | D26: 20435x7,22x0,6x8 | E26: =20435*7.22*0.6*8 -> 708195.36
C27: К1=7,22-инфляционный коэффициент
C28: К2=0,6 Cтадия "Р"
C29: К3=8 Ценообразующий коэф-т
A30: 4 | B30: Контрольно-измерительные пункты (КИП). Количество КИП всего по объекту -40 шт. | C30: СБЦ-2015 (Приказ Минстроя от 27.02.2015 № 140/пр, приложение №4 "СБЦ на преоктные работы в строительстве "Газооборудование и газоснабжение промышленных предприятий, зданий и сооружений" табл. 16 п.5 | D30: 495483x7,22x0,6x0,007x40 | E30: =495483*7.22*0.6*0.007*40 -> 601001.06
C31: К1=7,22-инфляционный коэффициент
C32: К2=0,6 Cтадия "Р"
C33: К3=0,007 п.2.4.3 СБЦ
C34: К4=40 Ценообразующий коэф-т
A35: 5 | B35: Проектирование протекторной установки (УПЗ).Количество УПЗ всего по объекту -40 шт. | C35: СБЦ-2015"Газооборудование и газоснабжение промышленных предприятий, зданий и сооружений" глава 2.4 п. 2.4.2 ,табл. 19 п.4 | D35: 20435x7,22x0,6x40x0,1 | E35: =20435*7.22*0.6*40*0.1 -> 354097.68
C36: К1=7,22-инфляционный коэффициент
C37: К2=0,6 Cтадия "Р"
C38: К3=40 Ценообразующий коэф-т
C39: К4=0,1- СБЦ-2015 глава 2.4 п. 2.4.1
A40: 6 | B40: Проектирование кабельных линий напряжением до 1.0 кВ. Всего 4 км | C40: СБЦ-2015 "Газооборудование и газоснабжение промышленных предприятий, зданий и сооружений"глава 2.4 п. 2.4.2 ,табл. 19 п.2 | D40: (9996+22090x4)x7,22x0,6 | E40: =(9996+22090*4)*7.22*0.6 -> 426078.19
C41: К1=7,22-инфляционный коэффициент
C42: К2=0,6 Cтадия "Р"
A43: ГК.2 А - Коллектор газосборный КС 3 - ГРП 2А | G43: дополнено
A44: 4212.001.Р.007.0004.ГК.2А.0000.000-ЭХЗ1
A45: 1 | B45: Проектирование вентильных перемычек (блоки БСЗ)..Всего 100 установок | C45: СБЦ-2015 (Приказ Минстроя от 27.02.2015 № 140/пр, приложение №4 "СБЦ на преоктные работы в строительстве "Газооборудование и газоснабжение промышленных предприятий, зданий и сооружений" табл. 16 п.5 | D45: 495483x7,22x0,6x0,031x30,7 | E45: 2042760
C46: К1=7,22-инфляционный коэффициент
C47: К2=0,6 Cтадия "Р"
C48: К3=0,031 п.2.4.3 СБЦ
C49: К4=1+(99*0,3)=30,7 Ценообразующий коэф-т
A50: 2 | B50: Контрольно-измерительные пункты (КИП). Количество КИП всего по объекту -130 шт. | C50: СБЦ-2015 (Приказ Минстроя от 27.02.2015 № 140/пр, приложение №4 "СБЦ на преоктные работы в строительстве "Газооборудование и газоснабжение промышленных предприятий, зданий и сооружений" табл. 16 п.5 | D50: 495483x7,22x0,6x0,007x39,7 | E50: 596494
C51: К1=7,22-инфляционный коэффициент
C52: К2=0,6 Cтадия "Р"
C53: К3=0,007 п.2.4.3 СБЦ
C54: К4=1+(129*0,3)=39,7 Ценообразующий коэф-т
A55: 3 | B55: Проектирование протекторной установки (УПЗ).Количество УПЗ всего по объекту -110 шт. | C55: СБЦ-2015"Газооборудование и газоснабжение промышленных предприятий, зданий и сооружений" глава 2.4 п. 2.4.2 ,табл. 19 п.4 | D55: 20435x7,22x0,6x33,7x0,1 | E55: 298327
C56: К1=7,22-инфляционный коэффициент
C57: К2=0,6 Cтадия "Р"
C58: К3=1+(109*0,3)=33,7 Ценообразующий коэф-т
C59: К4=0,1- СБЦ-2015 глава 2.4 п. 2.4.1
A60: 4 | B60: Проектирование кабельных линий напряжением до 1.0 кВ. Всего 3 км | C60: СБЦ-2015 "Газооборудование и газоснабжение промышленных предприятий, зданий и сооружений"глава 2.4 п. 2.4.2 ,табл. 19 п.3 | D60: (9996+22090x3)x7,22x0,6 | E60: 330384
C61: К1=7,22-инфляционный коэффициент
C62: К2=0,6 Cтадия "Р"
A63: 4212.001.Р.007.0004.ГК.2А.0000.000-ЭХЗ2
A64: 1 | B64: Проектирование вентильных перемычек (блоки БСЗ)..Всего 100 установок | C64: СБЦ-2015 (Приказ Минстроя от 27.02.2015 № 140/пр, приложение №4 "СБЦ на преоктные работы в строительстве "Газооборудование и газоснабжение промышленных предприятий, зданий и сооружений" табл. 16 п.5 | D64: 495483x7,22x0,6x0,031x30,7 | E64: 2042760
C65: К1=7,22-инфляционный коэффициент
C66: К2=0,6 Cтадия "Р"
C67: К3=0,031 п.2.4.3 СБЦ
C68: К4=1+(99*0,3)=30,7 Ценообразующий коэф-т
A69: 2 | B69: Контрольно-измерительные пункты (КИП). Количество КИП всего по объекту -130 шт. | C69: СБЦ-2015 (Приказ Минстроя от 27.02.2015 № 140/пр, приложение №4 "СБЦ на преоктные работы в строительстве "Газооборудование и газоснабжение промышленных предприятий, зданий и сооружений" табл. 16 п.5 | D69: 495483x7,22x0,6x0,007x39,7 | E69: 596494
C70: К1=7,22-инфляционный коэффициент
C71: К2=0,6 Cтадия "Р"
C72: К3=0,007 п.2.4.3 СБЦ
C73: К4=1+(129*0,3)=39,7 Ценообразующий коэф-т
A74: 3 | B74: Проектирование протекторной установки (УПЗ).Количество УПЗ всего по объекту -110 шт. | C74: СБЦ-2015"Газооборудование и газоснабжение промышленных предприятий, зданий и сооружений" глава 2.4 п. 2.4.2 ,табл. 19 п.4 | D74: 20435x7,22x0,6x33,7x0,1 | E74: 298327
C75: К1=7,22-инфляционный коэффициент
C76: К2=0,6 Cтадия "Р"
C77: К3=1+(109*0,3)=33,7 Ценообразующий коэф-т
C78: К4=0,1- СБЦ-2015 глава 2.4 п. 2.4.1
A79: 4 | B79: Проектирование кабельных линий напряжением до 1.0 кВ. Всего 3 км | C79: СБЦ-2015 "Газооборудование и газоснабжение промышленных предприятий, зданий и сооружений"глава 2.4 п. 2.4.2 ,табл. 19 п.3 | D79: (9996+22090x3)x7,22x0,6 | E79: 330384
C80: К1=7,22-инфляционный коэффициент
C81: К2=0,6 Cтадия "Р"
A82: Шг.2А - Сеть газосборная ГРП 2А
A83: 4212.00.Р.04.Шг.2А.000.ЭХЗ.000
A84: 1 | B84: Электрозащитная установка от коррозии (катодная, электродренажная). От 1 до 5 установок. Всего 1 установка | C84: СБЦ-2015 (Приказ Минстроя от 27.02.2015 № 140/пр, приложение №4 "СБЦ на преоктные работы в строительстве "Газооборудование и газоснабжение промышленных предприятий, зданий и сооружений" табл. 16 п.1 | D84: (5148+30850x1)x7,22x0,6 | E84: 155943
C85: К1=7,22-инфляционный коэффициент
C86: К2=0,6 Cтадия "Р"
A87: 2 | B87: Проектирование вентильных перемычек (блоки БСЗ)..Всего 20 установок | C87: СБЦ-2015 (Приказ Минстроя от 27.02.2015 № 140/пр, приложение №4 "СБЦ на преоктные работы в строительстве "Газооборудование и газоснабжение промышленных предприятий, зданий и сооружений" табл. 16 п.4 | D87: (107483+19400x(1+(19*0,3)))x7,22x0,6x0,031 | E87: 31889
C88: К1=7,22-инфляционный коэффициент
C89: К2=0,6 Cтадия "Р"
C90: К3=0,031 п.2.4.3 СБЦ
A91: 3 | B91: Проектирование глубинного анадного заземлителя (ГАЗ). Всего16 шт | C91: СБЦ-2015 "Газооборудование и газоснабжение промышленных предприятий, зданий и сооружений" глава 2.4 п. 2.4.2 ,табл. 19 п.4 | D91: 20435x7,22x0,6x1 | E91: 88524
C92: К1=7,22-инфляционный коэффициент
C93: К2=0,6 Cтадия "Р"
C94: К3=1 Ценообразующий коэф-т
A95: 4 | B95: Контрольно-измерительные пункты (КИП). Количество КИП всего по объекту -410 шт. | C95: СБЦ-2015 (Приказ Минстроя от 27.02.2015 № 140/пр, приложение №4 "СБЦ на преоктные работы в строительстве "Газооборудование и газоснабжение промышленных предприятий, зданий и сооружений" табл. 16 п.5 | D95: 495483x7,22x0,6x0,007x123,7 | E95: 1858596
C96: К1=7,22-инфляционный коэффициент
C97: К2=0,6 Cтадия "Р"
C98: К3=0,007 п.2.4.3 СБЦ
C99: К4=1+(409*0,3)=123,7 Ценообразующий коэф-т
A100: 5 | B100: Проектирование протекторной установки (УПЗ).Количество УПЗ всего по объекту -220 шт. | C100: СБЦ-2015"Газооборудование и газоснабжение промышленных предприятий, зданий и сооружений" глава 2.4 п. 2.4.2 ,табл. 19 п.4 | D100: 20435x7,22x0,6x66,7x0,1 | E100: 590458
C101: К1=7,22-инфляционный коэффициент
C102: К2=0,6 Cтадия "Р"
C103: К3=1+(219*0,3)=66,7 Ценообразующий коэф-т
C104: К4=0,1- СБЦ-2015 глава 2.4 п. 2.4.1
A105: 6 | B105: Проектирование кабельных линий напряжением до 1.0 кВ. Всего 16 км | C105: СБЦ-2015 "Газооборудование и газоснабжение промышленных предприятий, зданий и сооружений"глава 2.4 п. 2.4.2 ,табл. 19 п.3 | D105: (9996+22090x16)x7,22x0,6 | E105: 1574405
C106: К1=7,22-инфляционный коэффициент
...

Sheet 1.12 ВК
E1: Форма 2П
A3: =СВОД!E33 -> Смета №1.12
A4: на проектные работы
B6: Наименование объекта, стадии, этапа проектных работ | C6: =СВОД!B33 -> Сети водоснабжения и канализации
B8: Наименование проектной | C8: =СВОД!D14 -> ОАО «СИБНЕФТЕТРАНСПРОЕКТ»
B9: (изыскательской) организации
B11: Наименование организации | C11: =СВОД!D16 -> ООО «Газпром проектирование»
B12: заказчика
A14: № пп. | B14: Характеристика предприятия, здания, сооружения или виды работ | C14: Номер частей, глав, таблиц, процентов, параграфов и пунктов указаний к разделу Справочника базовых цен на проектные и изыскательские работы для строительства | D14: Расчет стоимости: (a+bx)*Ki, или (объем строительно-монтажных работ) * проц./100 или количество x цена | E14: Стоимость, руб.
A15: 1 | B15: 2 | C15: 3 | D15: 4 | E15: 5
A17: Этап №3 ГРП 2А
A18: 1 | B18: Система автоматического газового пожаротушения помещени технологического корпуса №1 (4 напр.) | C18: СБЦ "Системы противопожарной и охранной защиты" т.2 п.2 | D18: 3814x55,26x1,3x1,3x0,9x1 | E18: =3814*55.26*1.3*1.3*0.9*1 -> 320568.45
C19: k=55,26
C20: к=1.3 п.2.5
C21: к=1.3 п.3
C22: е=0,9 ст.РП
C23: к=1 объем
A24: 2 | B24: Система автоматического газового пожаротушения помещени технологического корпуса №2 (4 напр.) | C24: СБЦ "Системы противопожарной и охранной защиты" т.2 п.2 | D24: 3814x55,26x1,3x1,3x0,9x1 | E24: =3814*55.26*1.3*1.3*0.9*1 -> 320568.45
C25: k=55,26
C26: к=1.3 п.2.5
C27: к=1.3 п.3
C28: е=0,9 ст.РП
C29: к=1 объем
A30: 3 | B30: Система автоматического газового пожаротушения помещени технологической насосной поз.8 | C30: СБЦ "Системы противопожарной и охранной защиты" т.2 п.1 | D30: 2560x55,26x1,3x1,3x0,9x1 | E30: =2560*55.26*1.3*1.3*0.9*1 -> 215169.18
C31: k=55,26
C32: к=1.3 п.2.5
C33: к=1.3 п.3
C34: е=0,9 ст.РП
C35: к=1 объем
A36: 4 | B36: Система автоматического газового пожаротушения помещений операторной поз.19 | C36: СБЦ "Системы противопожарной и охранной защиты" т.2 п.1 | D36: 2560x55,26x1,3x0,75x0,7 | E36: =2560*55.26*1.3*0.75*0.7 -> 96550.272
C37: k=55,26
C38: к=1.3 п.3
C39: к=0,75 ст.Р
C40: к=0,7 объем
A41: 5 | B41: Насосная станция противопожарного водоснабжения поз.9 Q= 200 м3/час | C41: Спр. баз. цен "ВиК" 2015 г. т.5 п.3 | D41: (179590+353530x0,2)x7,22x1,1x0,4x0,7 | E41: =(179590+353530*0.2)*7.22*1.1*0.4*0.7 -> 556598.23
C42: k=7,22 инфл.
C43: к=1,1 микропроцесс.
C44: к=0,4 ст.Р
C45: к=0,7 объем
A46: 6 | B46: Резервуары для противопожарного запаса воды поз.10, 11 емк. 200 куб.м. 2 шт. | C46: Спр. баз. цен "ВиК" 2015 г. т.5 п.10 | D46: (21960+79880x0,2)x7,22x2x0,4x0,7 | E46: =(21960+79880*0.2)*7.22*2*0.4*0.7 -> 153382.84
C47: k=7,22 инфл.
C48: к=2-2 шт.
C49: к=0,4 ст.Р
C50: к=0,7 объем
A51: 7 | B51: Дренажная емкость бытовых сточных вод поз.17, поз.32 | C51: Спр. баз. цен "Объекты нефтеперерабатывающей пр-ти" 2015 г. т.8 п.1.92 | D51: 146600x1x7,22x2x0,6x0,7 | E51: =146600*1*7.22*2*0.6*0.7 -> 889099.68
C52: k=7,22 инфл.
C53: к=2-2 шт.
C54: к=0,6 ст.Р
C55: к=0,7 объем
A56: 8 | B56: Резервуар производственно-дождевых сточных вод поз.18 емк. 188 куб.м. | C56: Спр. баз. цен "ВиК" 2015 г. т.5 п.10 | D56: (21960+79880x0,188)x7,22x0,4x0,7 | E56: =(21960+79880*0.188)*7.22*0.4*0.7 -> 74753.593
C57: k=7,22 инфл.
C58: к=0,4 ст.Р
C59: к=0,7 объем
A60: 9 | B60: Сети противопожарного водопровода В2 подземной прокладки L=0,8 км. С учетом коэф. застройки больше 0,5 и кол-вом пересеч. больше 10. | C60: Спр. баз. цен "ВиК" 2015 г. т.3 п.1 с учетом п.1.12. К= К застр. + Кпересеч.=1(0,4+0,1)=1,5 | D60: (64940+34770x0,8)x7,22x1,5x1,15x0,4x0,7 | E60: =(64940+34770*0.8)*7.22*1.5*1.15*0.4*0.7 -> 323464.29
C61: k=7,22 инфл.
C62: к=1,5
C63: к=1,15 полиэтилен
C64: к=0,4 ст.Р
C65: к=0,7 объем
A66: 10 | B66: Сети хозяйственно-питьевого водопровода В1 подземной прокладки L=0,24 км. С учетом коэф. застройки больше 0,5 и кол-вом пересеч. больше 10. | C66: Спр. баз. цен "ВиК" 2015 г. т.3 п.1 с учетом п.1.12. К= К застр. + Кпересеч.=1(0,4+0,1)=1,5 | D66: (64940+34770x0,24)x7,22x1,5x1,15x0,4x0,7 | E66: =(64940+34770*0.24)*7.22*1.5*1.15*0.4*0.7 -> 255563.15
C67: k=7,22 инфл.
C68: к=1,5
C69: к=1,15 полиэтилен
C70: к=0,4 ст.Р
C71: к=0,7 объем
A72: 11 | B72: Сети хозяйственно-бытовой канализации К1, I-я группа L=0,08 км. | C72: Спр. баз. цен "ВиК" 2015 г. т.8 п.4 | D72: (114690+16850x0,08)x7,22x1,15x0,4x0,7 | E72: =(114690+16850*0.08)*7.22*1.15*0.4*0.7 -> 269769.78
C73: k=7,22 инфл.
C74: к=1,15 полиэтилен
C75: к=0,4 ст.Р
C76: к=0,7 объем
A77: 12 | B77: Сети канализации К3, К4 самотечные, I-я группа L=0,11 км. | C77: Спр. баз. цен "ВиК" 2015 г. т.8 п.4 | D77: (114690+16850x0,11)x7,22x0,4x0,7 | E77: =(114690+16850*0.11)*7.22*0.4*0.7 -> 235604.34
C78: k=7,22 инфл.
C79: к=0,4 ст.Р
C80: к=0,7 объем
A81: 13 | B81: Сети производственной канализации К3Н, напорные, L=0,1 км. | C81: Спр. баз. цен "ВиК" 2015 г. т.3 п.1 с учетом п.1.12. К= К застр. + Кпересеч.+ Книтки=1(0,4+0,1+ 0,15)=1,65 | D81: (64940+34770x1,1)x7,22x1,15x0,4x0,7 | E81: =(64940+34770*1.1)*7.22*1.15*0.4*0.7 -> 239893.27
C82: k=7,22 инфл.
C83: к=1,15 полиэтилен
C84: к=0,4 ст.Р
C85: к=0,7 объем
A86: 14 | B86: Водовод межплощадочный В1 КС3-ГРП2А подземной прокладки L=1,9 км. С учетом кол-вом пересеч. больше 10. | C86: Спр. баз. цен "ВиК" 2015 г. т.3 п.1 с учетом п.1.12. К= К застр. + Кпересеч.=1(0,4+0,1)=1,5 | D86: (64940+34770x1,9)x7,22x1,5x1,15x1,15x0,4x0,7 | E86: =(64940+34770*1.9)*7.22*1.5*1.15*1.15*0.4*0.7 -> 525367.75
C87: k=7,22 инфл.
C88: к=1,5
C89: к=1,15 2 нитки
C90: к=1,15 полиэтилен
C91: к=0,4 ст.Р
C92: к=0,7 объем
A93: 15 | B93: Итого по этапу 3 | E93: =SUM(E18:E92) -> 4476353.3
A94: 16 | B94: Итого | E94: =E93 -> 4476353.3
A95: 17 | B95: Итого с учетом коэффициента оптимизации ПАО "Газпром": | C95: «Порядок формирования стоимости проектно-изыскательских работ для строительства и реконструкции объектов ПАО «Газпром» от 28.12.2017г. п.5.41 | D95: К=0,8 | E95: =E94*0.8 -> 3581082.6
A96: 18 | B96: Итого с учетом районного коэффициента: | C96: Письмо ГК РФ по жилищной и строительной политике от 30 июня 1998 г. N 9-10-17/40 | D96: К=1,08 | E96: =E95*1.08 -> 3867569.2
A97: Всего по смете | E97: =E96 -> 3867569.2

Sheet 1.13 ЛЧ+
A1: Адепт: Проект v 2026.4.2 © ООО"Адепт" | E1: форма 2П, 707/пр
A3: Смета №1.13
A4: на проектные (изыскательские) работы
A6: Наименование предприятия, здания, сооружения, стадии проектирования, этапа, вида проектных или изыскательских работ | F6: =СВОД!B34 -> Линейная часть
A8: Наименование проектной (изыскательской) организации | F8: =СВОД!D14 -> ОАО «СИБНЕФТЕТРАНСПРОЕКТ»
A10: Наименование организации заказчика | F10: =СВОД!D16 -> ООО «Газпром проектирование»
A12: № пп | B12: Наименование объекта проектирования или вида проектных работ | G12: Наименование, номера глав, таблиц, параграфов и пунктов МНЗ на проектные работы | K12: Расчет стоимости | O12: Стоимость, руб.
A13: 1 | B13: 2 | G13: 3 | K13: 4 | O13: 5
A14: Шг.2А - Сеть газосборная ГРП 2А
A15: 4212.00.Р.04.Шг.2А.000.Л.000 Инв номер 763390
A16: 1 | B16: Трубопроводы (межцеховые и шлейфы) диаметром до 300 мм. Протяженность от 1 км до 5 км включительно. | G16: НЗ №849/пр Объекты газовой промышленности. 2023 г. Таблица 3.6. Объекты сбора газа (шлейфы, коллекторы и межцеховые трубопроводы), п.1 A = 61.9 тыс.руб; B = 15.484 тыс.руб; Xзад = 1.0125 (км); Количество = 1 | K16: (A + B * Xзад) * Количество * Ктек * Кст (61 900 руб. + 15 484 руб. * 1.0125) * 1 * 1,56 * 0.6 | O16: =ROUND((61900 + 15484 * 1.0125) * 1 * 1.56 * 0.6, 2) -> 72612.59
B17: Коэффициенты
B18: Стадия: Рабочая документация | G18: Кст = 0.6
B19: инд.3кв.2026г.к 01.01.2022 на пр.раб. | G19: Ктек = 1,56 Письмо Минстроя России от 22.07.2026 №45358-ИФ/09
A20: 2 | B20: Трубопроводы (межцеховые и шлейфы) диаметром до 300 мм. Протяженность от 1 км до 5 км включительно. | G20: НЗ №849/пр Объекты газовой промышленности. 2023 г. Таблица 3.6. Объекты сбора газа (шлейфы, коллекторы и межцеховые трубопроводы), п.1 A = 61.9 тыс.руб; B = 15.484 тыс.руб; Xзад = 2.33152 (км); Количество = 1 | K20: (A + B * Xзад) * Количество * Ктек * Кст (61 900 руб. + 15 484 руб. * 2.33152) * 1 * 1,56 * 0.6 | O20: =ROUND((61900 + 15484 * 2.33152) * 1 * 1.56 * 0.6, 2) -> 91729.18
B21: Коэффициенты
B22: Стадия: Рабочая документация | G22: Кст = 0.6
B23: инд.3кв.2026г.к 01.01.2022 на пр.раб. | G23: Ктек = 1,56 Письмо Минстроя России от 22.07.2026 №45358-ИФ/09
A24: 4212.00.Р.04.Шг.2А.000.Л1.000 Инв номер 763400
A25: 3 | B25: Трубопроводы (межцеховые и шлейфы) диаметром до 300 мм. Протяженность от 1 км до 5 км включительно. | G25: НЗ №849/пр Объекты газовой промышленности. 2023 г. Таблица 3.6. Объекты сбора газа (шлейфы, коллекторы и межцеховые трубопроводы), п.1 A = 61.9 тыс.руб; B = 15.484 тыс.руб; Xзад = 2.73962 (км); Количество = 1 | K25: (A + B * Xзад) * Количество * Ктек * Кст (61 900 руб. + 15 484 руб. * 2.73962) * 1 * 1,56 * 0.6 | O25: =ROUND((61900 + 15484 * 2.73962) * 1 * 1.56 * 0.6, 2) -> 97643.78
B26: Коэффициенты
B27: Стадия: Рабочая документация | G27: Кст = 0.6
B28: инд.3кв.2026г.к 01.01.2022 на пр.раб. | G28: Ктек = 1,56 Письмо Минстроя России от 22.07.2026 №45358-ИФ/09
A29: 4 | B29: Трубопроводы (межцеховые и шлейфы) диаметром до 300 мм. Протяженность от 1 км до 5 км включительно. | G29: НЗ №849/пр Объекты газовой промышленности. 2023 г. Таблица 3.6. Объекты сбора газа (шлейфы, коллекторы и межцеховые трубопроводы), п.1 A = 61.9 тыс.руб; B = 15.484 тыс.руб; Xмин = 1; Xзад = 0.5418 (км); Количество = 1 | K29: (A + B * (0.4 * Xмин + 0.6 * Xзад)) * Количество * Ктек * Кст (61 900 руб. + 15 484 руб. * (0.4 * 1 + 0.6 * 0.5418)) * 1 * 1,56 * 0.6 | O29: =ROUND((61900 + 15484 * (0.4 * 1 + 0.6 * 0.5418)) * 1 * 1.56 * 0.6, 2) -> 68447
B30: Коэффициенты
B31: Стадия: Рабочая документация | G31: Кст = 0.6
B32: инд.3кв.2026г.к 01.01.2022 на пр.раб. | G32: Ктек = 1,56 Письмо Минстроя России от 22.07.2026 №45358-ИФ/09
A33: 4212.00.Р.04.Шг.2А.000.Л2.000 Инв номер 763405
A34: 5 | B34: Трубопроводы (межцеховые и шлейфы) диаметром до 300 мм. Протяженность от 1 км до 5 км включительно. | G34: НЗ №849/пр Объекты газовой промышленности. 2023 г. Таблица 3.6. Объекты сбора газа (шлейфы, коллекторы и межцеховые трубопроводы), п.1 A = 61.9 тыс.руб; B = 15.484 тыс.руб; Xзад = 3.16977 (км); Количество = 1 | K34: (A + B * Xзад) * Количество * Ктек * Кст (61 900 руб. + 15 484 руб. * 3.16977) * 1 * 1,56 * 0.6 | O34: =ROUND((61900 + 15484 * 3.16977) * 1 * 1.56 * 0.6, 2) -> 103877.95
B35: Коэффициенты
B36: Стадия: Рабочая документация | G36: Кст = 0.6
B37: инд.3кв.2026г.к 01.01.2022 на пр.раб. | G37: Ктек = 1,56 Письмо Минстроя России от 22.07.2026 №45358-ИФ/09
A38: 6 | B38: Трубопроводы (межцеховые и шлейфы) диаметром до 300 мм. Протяженность от 1 км до 5 км включительно. | G38: НЗ №849/пр Объекты газовой промышленности. 2023 г. Таблица 3.6. Объекты сбора газа (шлейфы, коллекторы и межцеховые трубопроводы), п.1 A = 61.9 тыс.руб; B = 15.484 тыс.руб; Xмин = 1; Xзад = 0.39605 (км); Количество = 1 | K38: (A + B * (0.4 * Xмин + 0.6 * (Xмин / 2))) * Количество * Кпон * Ктек * Кст (61 900 руб. + 15 484 руб. * (0.4 * 1 + 0.6 * (1 / 2))) * 1 * 0.79 * 1,56 * 0.6 | O38: =ROUND((61900 + 15484 * (0.4 * 1 + 0.6 * (1 / 2))) * 1 * 0.79 * 1.56 * 0.6, 2) -> 53785.98
B39: Коэффициенты
B40: Стадия: Рабочая документация | G40: Кст = 0.6
B41: инд.3кв.2026г.к 01.01.2022 на пр.раб. | G41: Ктек = 1,56 Письмо Минстроя России от 22.07.2026 №45358-ИФ/09
B42: К'пон = Xзад / (0.5 * Xмин) | G42: К'пон = 0.79 понижающий коэффициент, учитывающий разницу в трудоемкости работ по проектируемому объекту и объекту аналогу. (Методика 707/пр п.131(3)) (Ценообразующий)
A43: 4212.00.Р.04.Шг.2А.000.Л3.000 Инв номер 763410
A44: 7 | B44: Трубопроводы (межцеховые и шлейфы) диаметром до 300 мм. Протяженность от 5 км до 20 км включительно. | G44: НЗ №849/пр Объекты газовой промышленности. 2023 г. Таблица 3.6. Объекты сбора газа (шлейфы, коллекторы и межцеховые трубопроводы), п.1 A = 88.5 тыс.руб; B = 10.167 тыс.руб; Xзад = 5.1931 (км); Количество = 1 | K44: (A + B * Xзад) * Количество * Ктек * Кст (88 500 руб. + 10 167 руб. * 5.1931) * 1 * 1,56 * 0.6 | O44: =ROUND((88500 + 10167 * 5.1931) * 1 * 1.56 * 0.6, 2) -> 132255.16
B45: Коэффициенты
B46: Стадия: Рабочая документация | G46: Кст = 0.6
B47: инд.3кв.2026г.к 01.01.2022 на пр.раб. | G47: Ктек = 1,56 Письмо Минстроя России от 22.07.2026 №45358-ИФ/09
A48: 8 | B48: Трубопроводы (межцеховые и шлейфы) диаметром до 300 мм. Протяженность от 1 км до 5 км включительно. | G48: НЗ №849/пр Объекты газовой промышленности. 2023 г. Таблица 3.6. Объекты сбора газа (шлейфы, коллекторы и межцеховые трубопроводы), п.1 A = 61.9 тыс.руб; B = 15.484 тыс.руб; Xмин = 1; Xзад = 0.02816 (км); Количество = 1 | K48: (A + B * (0.4 * Xмин + 0.6 * (Xмин / 2))) * Количество * Кпон * Ктек * Кст (61 900 руб. + 15 484 руб. * (0.4 * 1 + 0.6 * (1 / 2))) * 1 * 0.1 * 1,56 * 0.6 | O48: =ROUND((61900 + 15484 * (0.4 * 1 + 0.6 * (1 / 2))) * 1 * 0.1 * 1.56 * 0.6, 2) -> 6808.35
B49: Коэффициенты
B50: Стадия: Рабочая документация | G50: Кст = 0.6
B51: инд.3кв.2026г.к 01.01.2022 на пр.раб. | G51: Ктек = 1,56 Письмо Минстроя России от 22.07.2026 №45358-ИФ/09
B52: К'пон = Xзад / (0.5 * Xмин) | G52: К'пон = 0.1 понижающий коэффициент, учитывающий разницу в трудоемкости работ по проектируемому объекту и объекту аналогу. (Методика 707/пр п.131(3)) (Ценообразующий)
A53: 9 | B53: Трубопроводы (межцеховые и шлейфы) диаметром до 300 мм. Протяженность от 1 км до 5 км включительно. | G53: НЗ №849/пр Объекты газовой промышленности. 2023 г. Таблица 3.6. Объекты сбора газа (шлейфы, коллекторы и межцеховые трубопроводы), п.1 A = 61.9 тыс.руб; B = 15.484 тыс.руб; Xзад = 3.61309 (км); Количество = 1 | K53: (A + B * Xзад) * Количество * Ктек * Кст (61 900 руб. + 15 484 руб. * 3.61309) * 1 * 1,56 * 0.6 | O53: =ROUND((61900 + 15484 * 3.61309) * 1 * 1.56 * 0.6, 2) -> 110303
B54: Коэффициенты
B55: Стадия: Рабочая документация | G55: Кст = 0.6
B56: инд.3кв.2026г.к 01.01.2022 на пр.раб. | G56: Ктек = 1,56 Письмо Минстроя России от 22.07.2026 №45358-ИФ/09
A57: 10 | B57: Трубопроводы (межцеховые и шлейфы) диаметром до 300 мм. Протяженность от 1 км до 5 км включительно. | G57: НЗ №849/пр Объекты газовой промышленности. 2023 г. Таблица 3.6. Объекты сбора газа (шлейфы, коллекторы и межцеховые трубопроводы), п.1 A = 61.9 тыс.руб; B = 15.484 тыс.руб; Xмин = 1; Xзад = 0.26027 (км); Количество = 1 | K57: (A + B * (0.4 * Xмин + 0.6 * (Xмин / 2))) * Количество * Кпон * Ктек * Кст (61 900 руб. + 15 484 руб. * (0.4 * 1 + 0.6 * (1 / 2))) * 1 * 0.52 * 1,56 * 0.6 | O57: =ROUND((61900 + 15484 * (0.4 * 1 + 0.6 * (1 / 2))) * 1 * 0.52 * 1.56 * 0.6, 2) -> 35403.43
B58: Коэффициенты
B59: Стадия: Рабочая документация | G59: Кст = 0.6
B60: инд.3кв.2026г.к 01.01.2022 на пр.раб. | G60: Ктек = 1,56 Письмо Минстроя России от 22.07.2026 №45358-ИФ/09
B61: К'пон = Xзад / (0.5 * Xмин) | G61: К'пон = 0.52 понижающий коэффициент, учитывающий разницу в трудоемкости работ по проектируемому объекту и объекту аналогу. (Методика 707/пр п.131(3)) (Ценообразующий)
A62: 4212.00.Р.04.Шг.2А.000.Л4.000 Инв номер 763415
A63: 11 | B63: Трубопроводы (межцеховые и шлейфы) диаметром до 300 мм. Протяженность от 1 км до 5 км включительно. | G63: НЗ №849/пр Объекты газовой промышленности. 2023 г. Таблица 3.6. Объекты сбора газа (шлейфы, коллекторы и межцеховые трубопроводы), п.1 A = 61.9 тыс.руб; B = 15.484 тыс.руб; Xзад = 2.005 (км); Количество = 1 | K63: (A + B * Xзад) * Количество * Ктек * Кст (61 900 руб. + 15 484 руб. * 2.005) * 1 * 1,56 * 0.6 | O63: =ROUND((61900 + 15484 * 2.005) * 1 * 1.56 * 0.6, 2) -> 86996.91
B64: Коэффициенты
B65: Стадия: Рабочая документация | G65: Кст = 0.6
B66: инд.3кв.2026г.к 01.01.2022 на пр.раб. | G66: Ктек = 1,56 Письмо Минстроя России от 22.07.2026 №45358-ИФ/09
A67: 12 | B67: Трубопроводы (межцеховые и шлейфы) диаметром до 300 мм. Протяженность от 1 км до 5 км включительно. | G67: НЗ №849/пр Объекты газовой промышленности. 2023 г. Таблица 3.6. Объекты сбора газа (шлейфы, коллекторы и межцеховые трубопроводы), п.1 A = 61.9 тыс.руб; B = 15.484 тыс.руб; Xзад = 2.129 (км); Количество = 1 | K67: (A + B * Xзад) * Количество * Ктек * Кст (61 900 руб. + 15 484 руб. * 2.129) * 1 * 1,56 * 0.6 | O67: =ROUND((61900 + 15484 * 2.129) * 1 * 1.56 * 0.6, 2) -> 88794.05
B68: Коэффициенты
B69: Стадия: Рабочая документация | G69: Кст = 0.6
B70: инд.3кв.2026г.к 01.01.2022 на пр.раб. | G70: Ктек = 1,56 Письмо Минстроя России от 22.07.2026 №45358-ИФ/09
A71: 4212.00.Р.04.Шг.2А.000.Л5.000 Инв номер 781366
A72: 13 | B72: Трубопроводы (межцеховые и шлейфы) диаметром до 300 мм. Протяженность от 5 км до 20 км включительно. | G72: НЗ №849/пр Объекты газовой промышленности. 2023 г. Таблица 3.6. Объекты сбора газа (шлейфы, коллекторы и межцеховые трубопроводы), п.1 A = 88.5 тыс.руб; B = 10.167 тыс.руб; Xзад = 6.116 (км); Количество = 1 | K72: (A + B * Xзад) * Количество * Ктек * Кст (88 500 руб. + 10 167 руб. * 6.116) * 1 * 1,56 * 0.6 | O72: =ROUND((88500 + 10167 * 6.116) * 1 * 1.56 * 0.6, 2) -> 141037.76
B73: Коэффициенты
B74: Стадия: Рабочая документация | G74: Кст = 0.6
B75: инд.3кв.2026г.к 01.01.2022 на пр.раб. | G75: Ктек = 1,56 Письмо Минстроя России от 22.07.2026 №45358-ИФ/09
A76: 14 | B76: Трубопроводы (межцеховые и шлейфы) диаметром до 300 мм. Протяженность от 1 км до 5 км включительно. | G76: НЗ №849/пр Объекты газовой промышленности. 2023 г. Таблица 3.6. Объекты сбора газа (шлейфы, коллекторы и межцеховые трубопроводы), п.1 A = 61.9 тыс.руб; B = 15.484 тыс.руб; Xмин = 1; Xзад = 0.434 (км); Количество = 1 | K76: (A + B * (0.4 * Xмин + 0.6 * (Xмин / 2))) * Количество * Кпон * Ктек * Кст (61 900 руб. + 15 484 руб. * (0.4 * 1 + 0.6 * (1 / 2))) * 1 * 0.87 * 1,56 * 0.6 | O76: =ROUND((61900 + 15484 * (0.4 * 1 + 0.6 * (1 / 2))) * 1 * 0.87 * 1.56 * 0.6, 2) -> 59232.66
B77: Коэффициенты
B78: Стадия: Рабочая документация | G78: Кст = 0.6
B79: инд.3кв.2026г.к 01.01.2022 на пр.раб. | G79: Ктек = 1,56 Письмо Минстроя России от 22.07.2026 №45358-ИФ/09
B80: К'пон = Xзад / (0.5 * Xмин) | G80: К'пон = 0.87 понижающий коэффициент, учитывающий разницу в трудоемкости работ по проектируемому объекту и объекту аналогу. (Методика 707/пр п.131(3)) (Ценообразующий)
A81: 4212.00.Р.04.Шг.2А.000.Л6.000 Инв номер 781457
A82: 15 | B82: Трубопроводы (межцеховые и шлейфы) диаметром до 300 мм. Протяженность от 1 км до 5 км включительно. | G82: НЗ №849/пр Объекты газовой промышленности. 2023 г. Таблица 3.6. Объекты сбора газа (шлейфы, коллекторы и межцеховые трубопроводы), п.1 A = 61.9 тыс.руб; B = 15.484 тыс.руб; Xзад = 3.754 (км); Количество = 1 | K82: (A + B * Xзад) * Количество * Ктек * Кст (61 900 руб. + 15 484 руб. * 3.754) * 1 * 1,56 * 0.6 | O82: =ROUND((61900 + 15484 * 3.754) * 1 * 1.56 * 0.6, 2) -> 112345.21
B83: Коэффициенты
B84: Стадия: Рабочая документация | G84: Кст = 0.6
B85: инд.3кв.2026г.к 01.01.2022 на пр.раб. | G85: Ктек = 1,56 Письмо Минстроя России от 22.07.2026 №45358-ИФ/09
A86: 16 | B86: Трубопроводы (межцеховые и шлейфы) диаметром до 300 мм. Протяженность от 1 км до 5 км включительно. | G86: НЗ №849/пр Объекты газовой промышленности. 2023 г. Таблица 3.6. Объекты сбора газа (шлейфы, коллекторы и межцеховые трубопроводы), п.1 A = 61.9 тыс.руб; B = 15.484 тыс.руб; Xмин = 1; Xзад = 0.136 (км); Количество = 1 | K86: (A + B * (0.4 * Xмин + 0.6 * (Xмин / 2))) * Количество * Кпон * Ктек * Кст (61 900 руб. + 15 484 руб. * (0.4 * 1 + 0.6 * (1 / 2))) * 1 * 0.27 * 1,56 * 0.6 | O86: =ROUND((61900 + 15484 * (0.4 * 1 + 0.6 * (1 / 2))) * 1 * 0.27 * 1.56 * 0.6, 2) -> 18382.55
B87: Коэффициенты
B88: Стадия: Рабочая документация | G88: Кст = 0.6
B89: инд.3кв.2026г.к 01.01.2022 на пр.раб. | G89: Ктек = 1,56 Письмо Минстроя России от 22.07.2026 №45358-ИФ/09
B90: К'пон = Xзад / (0.5 * Xмин) | G90: К'пон = 0.27 понижающий коэффициент, учитывающий разницу в трудоемкости работ по проектируемому объекту и объекту аналогу. (Методика 707/пр п.131(3)) (Ценообразующий)
A91: 17 | B91: Итого по смете: | O91: =ROUND(SUM($O$16:$O$86),2) -> 1279655.6
A92: 18 | B92: Новое начисление | G92: К1 = 0.8 Коэффициент оптимизации ПАО "Газпром" («Порядок формирования стоимости проектно-изыскательских работ для строительства и реконструкции объектов ПАО «Газпром» от 28.12.2017г. п.5.41) (Ценообразующий) | K92: Коэф-т 1 от п.17 * 0.8 1 255 046.79 руб. * 1 * 0.8 | O92: =ROUND(($O$91) * 1 * 0.8,2) -> 1023724.4
A93: 19 | B93: Новое начисление | G93: К1 = 1.08 Коэффициент районный (Письмо ГК РФ по жилищной и строительной политике от 30 июня 1998 г. N 9-10-17/40) (Ценообразующий) | K93: Коэф-т 1 от п.18 * 1.08 1 004 037.43 руб. * 1 * 1.08 | O93: =ROUND(($O$92) * 1 * 1.08,2) -> 1105622.4
A94: 20 | B94: Всего по смете: | O94: =ROUND(($O$93),2) -> 1105622.4 | R94: =O94 -> 1105622.4

Sheet 1.14 ПроектБур+
B1: =СВОД!E35 -> Смета №1.14
B2: на проектные (изыскательские) работы | C2: Приложение к ______________________________________ | D2: Приложение к ______________________________________
A4: Наименование предприятия, здания, сооружения, стадии проектирования, этапа, вида проектных или изыскательских работ | E4: «Реконструкция газопромысловых сооружений Степновской СПХГ» - «Резервуарный парк легковоспламеняющихся жидкостей Степновской СПХГ», «Площадка печей подогревателей газа Степновской СПХГ», «Внеплощадочные коммуникации», «Газораспределительный пункт № 2А», «Реконструкция газопромысловых сооружений Степновской СПХГ. 2 этап. Объекты на площадке КС-3».3 этап
A7: Наименование проектной (изыскательской) организации | E7: =СВОД!D14 -> ОАО «СИБНЕФТЕТРАНСПРОЕКТ»
A9: Наименование организации заказчика | E9: =СВОД!D16 -> ООО «Газпром проектирование»
B11: Расчет стоимости выполнения работ по себестоимости (на основе трудозатрат) и сложившемуся уровню рентабельности
B12: Раздел 1. Определение трудоемкости (трудозатрат) выполняемой работы
A14: № пп | B14: Перечень выполняемых работ | C14: Исполнители | E14: Количество человеко-дней | F14: Средняя оплата труда за 1 день | G14: Оплата труда (всего),руб.
C15: количество | D15: должность
A16: 1 | B16: 2 | C16: 3 | D16: 4 | E16: 5 | F16: 6 | G16: 7
A17: 1 | B17: Проект бурения скважин, в т.ч. разделы: - пояснительная записка; - геологическая часть; - объем подготовительно-заключительных работ; - выбор бурового оборудования; - расчет времени на бурение и крепление скважины; - прокаткомплектов оборудования; - пожарная безопасность; - выводы; - графическая часть. | C17: 1 | D17: ГИП | E17: 1 | F17: 22082 | G17: =ROUND((C17*E17*F17+C18*E18*F18+C19*E19*F19+ C20*E20*F20+C21*E21*F21+C22*E22*F22+C23*E23*F23),2) -> 219320.5
C18: 1 | D18: Заместитель ГИПа | E18: 0.5 | F18: 19733
C19: 1 | D19: Начальник отдела | E19: 2 | F19: 22082
C20: 1 | D20: Главный специалист | E20: 2 | F20: 17599
C21: 1 | D21: Руководитель группы в состе отдела | E21: 2 | F21: 15758
C22: 1 | D22: Ведущий инженер | E22: 3 | F22: 14027
C23: 1 | D23: Инженер I категории | E23: 3 | F23: 11471
A24: 2 | B24: Итого з/п непосредственных исполнителей | G24: =G17 -> 219320.5
B26: Раздел 2. Определение стоимости работы
A28: № п/п | B28: Наименование показателей | F28: Единица измерения | G28: Значение показателей
A29: 1 | B29: Общая з/п непосредственных исполнителей Сумма от п.3 | F29: руб. | G29: =ROUND(($G$24),2) -> 219320.5
B30: Коэффициент отношения з/п непосредственных исполнителей к себестоимости | G30: 0.45
A31: 2 | B31: Себестоимость исходя из установленного коэффициента Разделить на коэф-т 0.45 от п.1 | F31: руб. | G31: =ROUND(($G$29) * 1/0.45 * 1,2) -> 487378.89
B32: Уровень рентабельности (по отношению к себестоимости) | F32: % | G32: 8
A33: 3 | B33: Прибыль 8% от п.2 | F33: руб. | G33: =ROUND(($G$31) * 8 / 100 * 1,2) -> 38990.31
A34: 4 | B34: Стоимость работы Сумма от п.2-3 | F34: руб. | G34: =ROUND(($G$31 + $G$33),2) -> 526369.2
B35: Применяемый коэффициент к стоимости работы, установленный в связи с дополнительными затратами проектных организаций, расположенных в районах, для работников которых предусмотрены льготные выплаты (северные надбавки и доплаты, районные коэффициенты и др.) | G35: 1
A36: 5 | B36: Всего стоимость работы Коэф-т 1 от п.4 | F36: руб. | G36: =ROUND(($G$34) * 1 * 1,2) -> 526369.2
B37: Всего по смете: | F37: руб. | G37: =G36 -> 526369.2
