Workbook

Sheet Лист1
C1: Форма для заполнения по тендерной процедуре №ТП.....
A2: Разработка проектной и рабочей документации объекта "Перевод установки получения масляных альдегидов методом оксосинтеза на Rh катализатор с наращением мощности по 2-ЭГ и 2-ЭГК на АО «Сибур-Химпром»
A4: № п/п | B4: Наименование показателей | C4: Претендент
A6: Соответствие техническому заданию.
A7: п. 4.10 Смета на строительство объектов капитального строительства
A8: 1. | B8: Разработка сметной документации в 2-х форматах: - ресурсным методом -базисно индексным методом
A9: 2. | B9: Базисно-индексный метод:
A10: 2.1 | B10: По основным (ценообразующим) материалам и вспомогательному оборудованию провести мониторинг рынка поставщиков
A11: 2.2 | B11: Предоставить ведомости объемов работ к каждому расчету за подписью разработчика марки проекта.
A12: 2.3 | B12: Предоставить ведомости материалов с построчной стоимостью ресурсов
A13: 2.4 | B13: Предоставить ведомости оборудования с построчной стоимостью ресурсов
A14: 2.5 | B14: В локальных сметных расчетах учесть разделение ТМЦ поставки Заказчик / Подрядчик.
A15: 2.6 | B15: Базисно-индексным методом: локальные сметные расчеты выполнить в сметно-нормативной базе ФЕР-2001 в ред.2017 (с изм.1-4) в программном комплексе «Гранд-Смета» с применением индексов пересчета по статьям затрат Пермского Регионального Центра Ценообразования (ПРЦЦС).
A16: 2.7 | B16: Сметную документацию (для БИМ) сформировать в составе: - сводный сметный расчет; - объектные сметные расчеты; - локальные сметные расчеты ; - ведомости объемов работ; - ведомости ресурсов; - ведомости оборудования
A17: 3. | B17: Ресурсный метод:
A18: 3.1 | B18: Ресурсные ведомости под каждую единичную расценку (ЕР) и титул
A19: 3.2 | B19: Для определения стоимости ресурсов использовать текущие цены на ресурсы, согласованные с Заказчиком.
... A26: 6. | B26: Предоставить пояснительную записку по формированию стоимости с указанием перечня затрат, возможных к реализации, но не учтенных в стоимости строительства

Sheet КП
G1: Форма для заполнения по тендерной процедуре №…….
A3: Разработка ТЭО, ОТР, FEED, проектной и рабочей документации объекта "Выполнение проектно-изыскательских работ по проектам "Техническое перевооружение сети водопроводов, трубопроводов пенного пожаротушения ООО "Томскнефтехим" » Календарный план
A5: Этапы № п/п | B5: Наименование Этапа | C5: Отчетная документация | D5: Дата начала | E5: Дата окончания* | F5: Перечень пунктов из формы ТКП входящих в этап | G5: Стоимость, руб. без НДС
D6: Перечень пунктов из | E6: Перечень пунктов из | F6: Перечень пунктов из
A7: 1 | B7: Стадия ТЭО (ТЭО_ФО+ЛС+ССР) | G7: =SUM(G8:H22) -> 0
A8: 1.1 | B8: ='ТЭО_ФО+ЛС+ССР'!B67 -> Инженерные Изыскания | C8: Отчеты | F8: 2.1 - 2.9 | G8: ='ТЭО_ФО+ЛС+ССР'!C67 -> 0
A9: =A8+0.1 -> 1.2 | B9: ='ТЭО_ФО+ЛС+ССР'!B131 -> Сбор исходных данных | C9: Отчеты | F9: 3.1 - 3.2 | G9: ='ТЭО_ФО+ЛС+ССР'!C131 -> 0
A10: =A9+0.1 -> 1.3 | B10: ='ТЭО_ФО+ЛС+ССР'!B153 -> Обследование существующих строительных конструкций, трубопроводов, оборудования | C10: Отчеты | F10: 4.1 - 4.2 | G10: ='ТЭО_ФО+ЛС+ССР'!C153 -> 0
A11: =A10+0.1 -> 1.4 | B11: ='ТЭО_ФО+ЛС+ССР'!B168 -> Проектное технологическое обследование объекта | C11: Отчеты | F11: 5.1 - 5.2 | G11: ='ТЭО_ФО+ЛС+ССР'!C168 -> 0
A12: =A11+0.1 -> 1.5 | B12: ='ТЭО_ФО+ЛС+ССР'!B183 -> Разработка разделов ТЭО | C12: Документация | F12: 6.1 - 6.35 | G12: ='ТЭО_ФО+ЛС+ССР'!C183 -> 0
A13: =A12+0.1 -> 1.6 | B13: ='ТЭО_ФО+ЛС+ССР'!B429 -> Сессии VE (Value Engineering) | C13: Отчеты | F13: 7.1. - 7.2 | G13: ='ТЭО_ФО+ЛС+ССР'!C429 -> 0
A14: =A13+0.1 -> 1.7 | B14: ='ТЭО_ФО+ЛС+ССР'!B444 -> 3D модель | C14: Модель | F14: 8.1. | G14: ='ТЭО_ФО+ЛС+ССР'!C444 -> 0
A15: =A14+0.1 -> 1.8 | B15: ='ТЭО_ФО+ЛС+ССР'!B452 -> Смежные работы (при необходимости) | C15: Отчеты | F15: 9.1. - 9.26 | G15: ='ТЭО_ФО+ЛС+ССР'!C452 -> 0
A16: =A15+0.1 -> 1.9 | B16: ='ТЭО_ФО+ЛС+ССР'!B635 -> Электронный документооборот | C16: Акт | F16: 10.1. | G16: ='ТЭО_ФО+ЛС+ССР'!C635 -> 0
A17: =A16+0.1 -> 2 | B17: ='ТЭО_ФО+ЛС+ССР'!B643 -> Отчетная документация по проекту | C17: Отчеты | F17: 11.1. | G17: ='ТЭО_ФО+ЛС+ССР'!C643 -> 0
A18: =A17+0.1 -> 2.1 | B18: ='ТЭО_ФО+ЛС+ССР'!B651 -> Согласование с собственниками существующих сооружений пересечение с проектируемыми сооружениями | C18: Утвержд. Согласования | F18: 12.1. | G18: ='ТЭО_ФО+ЛС+ССР'!C651 -> 0
A19: =A18+0.1 -> 2.2 | B19: ='ТЭО_ФО+ЛС+ССР'!B659 -> Расчет зон поражения аварийных химически опасных веществ | C19: Расчеты | F19: 13.1. | G19: ='ТЭО_ФО+ЛС+ССР'!C659 -> 0
A20: =A19+0.1 -> 2.3 | B20: ='ТЭО_ФО+ЛС+ССР'!B667 -> Разработка СТУ | C20: Сметы | F20: 14.1. - 14.2 | G20: ='ТЭО_ФО+ЛС+ССР'!C667 -> 0
A21: =A20+0.1 -> 2.4 | B21: ='ТЭО_ФО+ЛС+ССР'!B682 -> Выполнение работ связанных с земельным участком под строительство | C21: Сметы | F21: 15.1. - 15.2. | G21: ='ТЭО_ФО+ЛС+ССР'!C682 -> 0
A22: =A21+0.1 -> 2.5 | B22: ='ТЭО_ФО+ЛС+ССР'!B10 -> Смета на строительство объектов капитального строительства | C22: Сметы | F22: 1.1. - 1.8 | G22: ='ТЭО_ФО+ЛС+ССР'!C10 -> 0
A24: 2 | B24: Стадия ОТР (ОТР_BOQ) | G24: =SUM(G25:H31) -> 0
A25: =A24+0.1 -> 2.1 | B25: ='ОТР_BOQ '!B67 -> Документация ОТР | C25: Документация | F25: 2.1 - 2.17 | G25: ='ОТР_BOQ '!C67 -> 0
A26: =A25+0.1 -> 2.2 | B26: ='ОТР_BOQ '!B187 -> Сбор исходных данных. | C26: Отчеты | F26: 3.1 - 3.2 | G26: ='ОТР_BOQ '!C187 -> 0
A27: =A26+0.1 -> 2.3 | B27: ='ОТР_BOQ '!B202 -> Проектное технологическое обследование объекта | C27: Отчеты | F27: 4.1 - 4.2 | G27: ='ОТР_BOQ '!C202 -> 0
A28: =A27+0.1 -> 2.4 | B28: ='ОТР_BOQ '!B217 -> Сессии VE (Value Engineering) | C28: Отчеты | F28: 5.1 - 5.2 | G28: ='ОТР_BOQ '!C217 -> 0
A29: =A28+0.1 -> 2.5 | B29: ='ОТР_BOQ '!B232 -> Смежные работы (при необходимости) | C29: Документация | F29: 6.1 - 6.8 | G29: ='ОТР_BOQ '!C232 -> 0
A30: =A29+0.1 -> 2.6 | B30: ='ОТР_BOQ '!B289 -> Отчетная документация по проекту | C30: Отчеты | F30: 7.1. | G30: ='ОТР_BOQ '!C289 -> 0
A31: =A30+0.1 -> 2.7 | B31: ='ОТР_BOQ '!B10 -> Смета на строительство объектов капитального строительства | C31: Сметы | F31: 1.1. - 1.8 | G31: ='ОТР_BOQ '!C10 -> 0
A33: 3 | B33: Стадия FEED (FEED_BOQ тит1) | G33: =SUM(G34:H36) -> 0
A34: =A33+0.1 -> 3.1 | B34: ='FEED_BOQ тит1'!B60 -> FEED (все разделы) | C34: Документация | F34: 2.1 - 2.22 | G34: ='FEED_BOQ тит1'!C60 -> 0
A35: =A34+0.1 -> 3.2 | B35: ='FEED_BOQ тит1'!B258 -> Смежные работы (при необходимости) | C35: Отчеты | F35: 3.1 - 3.50 | G35: ='FEED_BOQ тит1'!C258 -> 0
A36: =A35+0.1 -> 3.3 | B36: ='FEED_BOQ тит1'!B10 -> Смета на строительство объектов капитального строительства | C36: Отчеты | F36: 1.1 - 1.7 | G36: ='FEED_BOQ тит1'!C10 -> 0
A38: 4 | B38: Стадия FEED (FEED_BOQ тит2) | G38: =SUM(G39:H41) -> 0
A39: =A38+0.1 -> 4.1 | B39: ='FEED_BOQ тит2'!B60 -> FEED (все разделы) | C39: Документация | F39: 2.1 - 2.22 | G39: ='FEED_BOQ тит2'!C60 -> 0
A40: =A39+0.1 -> 4.2 | B40: ='FEED_BOQ тит2'!B258 -> Смежные работы (при необходимости) | C40: Отчеты | F40: 3.1 - 3.50 | G40: ='FEED_BOQ тит2'!C258 -> 0
A41: =A40+0.1 -> 4.3 | B41: ='FEED_BOQ тит2'!B10 -> Смета на строительство объектов капитального строительства | C41: Отчеты | F41: 1.1 - 1.7 | G41: ='FEED_BOQ тит2'!C10 -> 0
A43: 5 | B43: Стадия ПД (ПД_BOQ тит1) | G43: =SUM(G44:H46) -> 0
A44: =A43+0.1 -> 5.1 | B44: ='ПД_BOQ тит1.'!B60 -> Проектная документация (все разделы) | C44: Документация | F44: 2.1 - 2.23 | G44: ='ПД_BOQ тит1.'!C60 -> 0
A45: =A44+0.1 -> 5.2 | B45: ='ПД_BOQ тит1.'!B272 -> Смежные работы (при необходимости) | C45: Отчеты | F45: 3.1 - 3.64 | G45: ='ПД_BOQ тит1.'!C272 -> 0
A46: =A45+0.1 -> 5.3 | B46: ='ПД_BOQ тит1.'!B10 -> Смета на строительство объектов капитального строительства | C46: Отчеты | F46: 1.1 - 1.7 | G46: ='ПД_BOQ тит1.'!C10 -> 0
A48: 6 | B48: Стадия ПД (ПД_BOQ тит2) | G48: =SUM(G49:H51) -> 0
A49: =A48+0.1 -> 6.1 | B49: ='ПД_BOQ тит2'!B60 -> Проектная документация (все разделы) | C49: Документация | F49: 2.1 - 2.23 | G49: ='ПД_BOQ тит2'!C60 -> 0
A50: =A49+0.1 -> 6.2 | B50: ='ПД_BOQ тит2'!B272 -> Смежные работы (при необходимости) | C50: Отчеты | F50: 3.1 - 3.64 | G50: ='ПД_BOQ тит2'!C272 -> 0
A51: =A50+0.1 -> 6.3 | B51: ='ПД_BOQ тит2'!B10 -> Смета на строительство объектов капитального строительства | C51: Отчеты | F51: 1.1 - 1.7 | G51: ='ПД_BOQ тит2'!C10 -> 0
B52: Итого стоимость предложения | G52: =G7+G24+G33 -> 0
B53: * - Датай окончания является дата подписания Заказчиком акта приемки выполненных работ
B55: Наименование организации
B57: Должность подписавшего
B58: Фамилия, Имя, Отчество подписавшего
B59: Дата: | H59: ( подпись, M.П.)
A62: 1.234

Sheet СВОД
C1: Форма для заполнения по тендерной процедуре №…….
A3: Разработка ТЭО, ОТР, FEED, проектной и рабочей документации объекта "Выполнение проектно-изыскательских работ по проектам "Техническое перевооружение сети водопроводов, трубопроводов пенного пожаротушения ООО "Томскнефтехим" »
A5: № п/п | B5: Наименование показателей | C5: Стоимость, руб. без НДС
A7: 1 | B7: Итого стоимость предложения на ТЭО | C7: ='ТЭО_ФО+ЛС+ССР'!C697 -> 0
A8: =A7+1 -> 2 | B8: Итого стоимость предложения на ОТР | C8: ='ОТР_BOQ '!C298 -> 0
A9: =A8+1 -> 3 | B9: Итого стоимость предложения на FEED. титул1 | C9: ='FEED_BOQ тит1'!C618 -> 0
A10: =A9+1 -> 4 | B10: Итого стоимость предложения на FEED. Титул2 | C10: ='FEED_BOQ тит2'!C618 -> 0
A11: =A10+1 -> 5 | B11: Итого стоимость предложения на ПД. титул1 | C11: ='ПД_BOQ тит1.'!C746 -> 0
A12: =A11+1 -> 6 | B12: Итого стоимость предложения на ПД. титул2 | C12: ='ПД_BOQ тит2'!C746 -> 0
A13: =A12+1 -> 7 | B13: Итого стоимость предложения на РД. Титул1 | C13: ='РД_BOQ тит.1'!C1609 -> 0
A14: =A13+1 -> 8 | B14: Итого стоимость предложения на РД. Титул2 | C14: ='РД_BOQ тит.2'!C1609 -> 0
B15: Итого стоимость предложения | C15: =SUM(C7:D14) -> 0
B18: Наименование организации
B20: Должность подписавшего
B21: Фамилия, Имя, Отчество подписавшего
B22: Дата: | D22: ( подпись, M.П.)

Sheet ТЭО_ФО+ЛС+ССР
C1: Форма для заполнения по тендерной процедуре №ТП.....
A2: Разработка ТЭО по объекту "Выполнение проектно-изыскательских работ по проектам "Техническое перевооружение сети водопроводов, трубопроводов пенного пожаротушения ООО "Томскнефтехим" »
C4: (заполняется участником)
A5: № п/п | B5: Наименование показателей | C5: Стоимость, руб. без НДС | D5: Трудозатраты чел.час | E5: Трудозатраты чел.дни | F5: Наименование подрядчика | G5: Обоснование расчета*
G7: Должность | H7: Оценка количества листов документации | J7: чел. | K7: Дней | L7: Часов | M7: Ст-ть чел. часа (руб.) без НДС | N7: Итого Ст-ть (руб.) без НДС | O7: Итого кол. чел.час
H8: (текст.) ф.А4 | I8: (граф.) ф.А1
A9: Соответствие техническому заданию стадии ТЭО
A10: 1. | B10: Смета на строительство объектов капитального строительства | C10: =SUM(C11:C66) -> 0 | D10: =SUM(D12:D66) -> 0 | E10: =SUM(E12:E66) -> 0
A11: 1.1. | B11: Провести мониторинг рынка для определения стоимости ценообразующих материалов | C11: =SUM(N11:N17) -> 0 | D11: =SUM(O11:O17) -> 0 | E11: =D11/8 -> 0 | G11: ГИП | N11: =M11*J11*K11*L11 -> 0 | O11: =J11*K11*L11 -> 0
G12: Нач. отдела | N12: =M12*J12*K12*L12 -> 0 | O12: =J12*K12*L12 -> 0
G13: Гл. специалист | N13: =M13*J13*K13*L13 -> 0 | O13: =J13*K13*L13 -> 0
G14: Рук. Группы | N14: =M14*J14*K14*L14 -> 0 | O14: =J14*K14*L14 -> 0
G15: Вед. инженер | N15: =M15*J15*K15*L15 -> 0 | O15: =J15*K15*L15 -> 0
G16: Старший инженер | N16: =M16*J16*K16*L16 -> 0 | O16: =J16*K16*L16 -> 0
G17: Инженер | N17: =M17*J17*K17*L17 -> 0 | O17: =J17*K17*L17 -> 0
A18: 1.2. | B18: Предоставить ведомости объемов работ в формате BOQ (Описание выполняемых работ/объемы) (с точностью +50% минус 30%) | C18: =SUM(N18:N24) -> 0 | D18: =SUM(O18:O24) -> 0 | E18: =D18/8 -> 0 | G18: ГИП | N18: =M18*J18*K18*L18 -> 0 | O18: =J18*K18*L18 -> 0
G19: Нач. отдела | N19: =M19*J19*K19*L19 -> 0 | O19: =J19*K19*L19 -> 0
G20: Гл. специалист | N20: =M20*J20*K20*L20 -> 0 | O20: =J20*K20*L20 -> 0
G21: Рук. Группы | N21: =M21*J21*K21*L21 -> 0 | O21: =J21*K21*L21 -> 0
G22: Вед. инженер | N22: =M22*J22*K22*L22 -> 0 | O22: =J22*K22*L22 -> 0
G23: Старший инженер | N23: =M23*J23*K23*L23 -> 0 | O23: =J23*K23*L23 -> 0
G24: Инженер | N24: =M24*J24*K24*L24 -> 0 | O24: =J24*K24*L24 -> 0
A25: 1.3. | B25: Предоставить таблицу физических объемов сводную / по титульно (с точностью +50% минус 30%) | C25: =SUM(N25:N31) -> 0 | D25: =SUM(O25:O31) -> 0 | E25: =D25/8 -> 0 | G25: ГИП | N25: =M25*J25*K25*L25 -> 0 | O25: =J25*K25*L25 -> 0
G26: Нач. отдела | N26: =M26*J26*K26*L26 -> 0 | O26: =J26*K26*L26 -> 0
G27: Гл. специалист | N27: =M27*J27*K27*L27 -> 0 | O27: =J27*K27*L27 -> 0
G28: Рук. Группы | N28: =M28*J28*K28*L28 -> 0 | O28: =J28*K28*L28 -> 0
G29: Вед. инженер | N29: =M29*J29*K29*L29 -> 0 | O29: =J29*K29*L29 -> 0
G30: Старший инженер | N30: =M30*J30*K30*L30 -> 0 | O30: =J30*K30*L30 -> 0
G31: Инженер | N31: =M31*J31*K31*L31 -> 0 | O31: =J31*K31*L31 -> 0
A32: 1.4. | B32: Предоставить ведомости материалов с построчной стоимостью ресурсов (BOM) (с точностью +50% минус 30%) | C32: =SUM(N32:N38) -> 0 | D32: =SUM(O32:O38) -> 0 | E32: =D32/8 -> 0 | G32: ГИП | N32: =M32*J32*K32*L32 -> 0 | O32: =J32*K32*L32 -> 0
G33: Нач. отдела | N33: =M33*J33*K33*L33 -> 0 | O33: =J33*K33*L33 -> 0
G34: Гл. специалист | N34: =M34*J34*K34*L34 -> 0 | O34: =J34*K34*L34 -> 0
G35: Рук. Группы | N35: =M35*J35*K35*L35 -> 0 | O35: =J35*K35*L35 -> 0
G36: Вед. инженер | N36: =M36*J36*K36*L36 -> 0 | O36: =J36*K36*L36 -> 0
G37: Старший инженер | N37: =M37*J37*K37*L37 -> 0 | O37: =J37*K37*L37 -> 0
G38: Инженер | N38: =M38*J38*K38*L38 -> 0 | O38: =J38*K38*L38 -> 0
A39: 1.5. | B39: Предоставить ведомости оборудования с построчной стоимостью ресурсов (BOE) (с точностью +50% минус 30%) | C39: =SUM(N39:N45) -> 0 | D39: =SUM(O39:O45) -> 0 | E39: =D39/8 -> 0 | G39: ГИП | N39: =M39*J39*K39*L39 -> 0 | O39: =J39*K39*L39 -> 0
G40: Нач. отдела | N40: =M40*J40*K40*L40 -> 0 | O40: =J40*K40*L40 -> 0
G41: Гл. специалист | N41: =M41*J41*K41*L41 -> 0 | O41: =J41*K41*L41 -> 0
G42: Рук. Группы | N42: =M42*J42*K42*L42 -> 0 | O42: =J42*K42*L42 -> 0
G43: Вед. инженер | N43: =M43*J43*K43*L43 -> 0 | O43: =J43*K43*L43 -> 0
G44: Старший инженер | N44: =M44*J44*K44*L44 -> 0 | O44: =J44*K44*L44 -> 0
G45: Инженер | N45: =M45*J45*K45*L45 -> 0 | O45: =J45*K45*L45 -> 0
A46: 1.6. | B46: Предоставить пусконаладочные работы (ПНР, ППНР) определить расчетом.(с точностью +50% минус 30%) | C46: =SUM(N46:N52) -> 0 | D46: =SUM(O46:O52) -> 0 | E46: =D46/8 -> 0 | G46: ГИП | N46: =M46*J46*K46*L46 -> 0 | O46: =J46*K46*L46 -> 0
G47: Нач. отдела | N47: =M47*J47*K47*L47 -> 0 | O47: =J47*K47*L47 -> 0
G48: Гл. специалист | N48: =M48*J48*K48*L48 -> 0 | O48: =J48*K48*L48 -> 0
G49: Рук. Группы | N49: =M49*J49*K49*L49 -> 0 | O49: =J49*K49*L49 -> 0
G50: Вед. инженер | N50: =M50*J50*K50*L50 -> 0 | O50: =J50*K50*L50 -> 0
G51: Старший инженер | N51: =M51*J51*K51*L51 -> 0 | O51: =J51*K51*L51 -> 0
G52: Инженер | N52: =M52*J52*K52*L52 -> 0 | O52: =J52*K52*L52 -> 0
A53: 1.6. | B53: Выполнение локальных сметных расчётов, объектных смет, сводного сметного расчета стоимости строительства (с точностью +50% минус 30%) | C53: =SUM(N53:N59) -> 0 | D53: =SUM(O53:O59) -> 0 | E53: =D53/8 -> 0 | G53: ГИП | N53: =M53*J53*K53*L53 -> 0 | O53: =J53*K53*L53 -> 0
G54: Нач. отдела | N54: =M54*J54*K54*L54 -> 0 | O54: =J54*K54*L54 -> 0
G55: Гл. специалист | N55: =M55*J55*K55*L55 -> 0 | O55: =J55*K55*L55 -> 0
G56: Рук. Группы | N56: =M56*J56*K56*L56 -> 0 | O56: =J56*K56*L56 -> 0
G57: Вед. инженер | N57: =M57*J57*K57*L57 -> 0 | O57: =J57*K57*L57 -> 0
G58: Старший инженер | N58: =M58*J58*K58*L58 -> 0 | O58: =J58*K58*L58 -> 0
G59: Инженер | N59: =M59*J59*K59*L59 -> 0 | O59: =J59*K59*L59 -> 0
A60: 1.8. | B60: Предоставить пояснительную записку | C60: =SUM(N60:N66) -> 0 | D60: =SUM(O60:O66) -> 0 | E60: =D60/8 -> 0 | G60: ГИП | N60: =M60*J60*K60*L60 -> 0 | O60: =J60*K60*L60 -> 0
G61: Нач. отдела | N61: =M61*J61*K61*L61 -> 0 | O61: =J61*K61*L61 -> 0
G62: Гл. специалист | N62: =M62*J62*K62*L62 -> 0 | O62: =J62*K62*L62 -> 0
G63: Рук. Группы | N63: =M63*J63*K63*L63 -> 0 | O63: =J63*K63*L63 -> 0
G64: Вед. инженер | N64: =M64*J64*K64*L64 -> 0 | O64: =J64*K64*L64 -> 0
G65: Старший инженер | N65: =M65*J65*K65*L65 -> 0 | O65: =J65*K65*L65 -> 0
G66: Инженер | N66: =M66*J66*K66*L66 -> 0 | O66: =J66*K66*L66 -> 0
A67: 2. | B67: Инженерные Изыскания | C67: =SUM(C68:C130) -> 0 | D67: =SUM(D68:D130) -> 0 | E67: =SUM(E68:E130) -> 0
A68: 2.1. | B68: Инженерно-геодезические изыскания. (Миниминально требуемый объем для результатов ТЭО). При отсутствии фондовых материалов. | C68: =SUM(N68:N74) -> 0 | D68: =SUM(O68:O74) -> 0 | E68: =D68/8 -> 0 | G68: ГИП | N68: =M68*J68*K68*L68 -> 0 | O68: =J68*K68*L68 -> 0
G69: Нач. отдела | N69: =M69*J69*K69*L69 -> 0 | O69: =J69*K69*L69 -> 0
G70: Гл. специалист | N70: =M70*J70*K70*L70 -> 0 | O70: =J70*K70*L70 -> 0
G71: Рук. Группы | N71: =M71*J71*K71*L71 -> 0 | O71: =J71*K71*L71 -> 0
G72: Вед. инженер | N72: =M72*J72*K72*L72 -> 0 | O72: =J72*K72*L72 -> 0
G73: Старший инженер | N73: =M73*J73*K73*L73 -> 0 | O73: =J73*K73*L73 -> 0
G74: Инженер | N74: =M74*J74*K74*L74 -> 0 | O74: =J74*K74*L74 -> 0
A75: 2.2. | B75: Инженерно-геологические изыскания. (Миниминально требуемый объем для результатов ТЭО). При отсутствии фондовых материалов. | C75: =SUM(N75:N81) -> 0 | D75: =SUM(O75:O81) -> 0 | E75: =D75/8 -> 0 | G75: ГИП | N75: =M75*J75*K75*L75 -> 0 | O75: =J75*K75*L75 -> 0
G76: Нач. отдела | N76: =M76*J76*K76*L76 -> 0 | O76: =J76*K76*L76 -> 0
G77: Гл. специалист | N77: =M77*J77*K77*L77 -> 0 | O77: =J77*K77*L77 -> 0
G78: Рук. Группы | N78: =M78*J78*K78*L78 -> 0 | O78: =J78*K78*L78 -> 0
G79: Вед. инженер | N79: =M79*J79*K79*L79 -> 0 | O79: =J79*K79*L79 -> 0
G80: Старший инженер | N80: =M80*J80*K80*L80 -> 0 | O80: =J80*K80*L80 -> 0
G81: Инженер | N81: =M81*J81*K81*L81 -> 0 | O81: =J81*K81*L81 -> 0
A82: 2.3. | B82: Инженерно-экологические изыскания. (Миниминально требуемый объем для результатов ТЭО). При отсутствии фондовых материалов. | C82: =SUM(N82:N88) -> 0 | D82: =SUM(O82:O88) -> 0 | E82: =D82/8 -> 0 | G82: ГИП | N82: =M82*J82*K82*L82 -> 0 | O82: =J82*K82*L82 -> 0
G83: Нач. отдела | N83: =M83*J83*K83*L83 -> 0 | O83: =J83*K83*L83 -> 0
G84: Гл. специалист | N84: =M84*J84*K84*L84 -> 0 | O84: =J84*K84*L84 -> 0
G85: Рук. Группы | N85: =M85*J85*K85*L85 -> 0 | O85: =J85*K85*L85 -> 0
G86: Вед. инженер | N86: =M86*J86*K86*L86 -> 0 | O86: =J86*K86*L86 -> 0
G87: Старший инженер | N87: =M87*J87*K87*L87 -> 0 | O87: =J87*K87*L87 -> 0
G88: Инженер | N88: =M88*J88*K88*L88 -> 0 | O88: =J88*K88*L88 -> 0
A89: 2.4. | B89: Инженерно-гидрометеорологические изыскания. (Миниминально требуемый объем для результатов ТЭО). При отсутствии фондовых материалов. | C89: =SUM(N89:N95) -> 0 | D89: =SUM(O89:O95) -> 0 | E89: =D89/8 -> 0 | G89: ГИП | N89: =M89*J89*K89*L89 -> 0 | O89: =J89*K89*L89 -> 0
G90: Нач. отдела | N90: =M90*J90*K90*L90 -> 0 | O90: =J90*K90*L90 -> 0
G91: Гл. специалист | N91: =M91*J91*K91*L91 -> 0 | O91: =J91*K91*L91 -> 0
G92: Рук. Группы | N92: =M92*J92*K92*L92 -> 0 | O92: =J92*K92*L92 -> 0
G93: Вед. инженер | N93: =M93*J93*K93*L93 -> 0 | O93: =J93*K93*L93 -> 0
G94: Старший инженер | N94: =M94*J94*K94*L94 -> 0 | O94: =J94*K94*L94 -> 0
G95: Инженер | N95: =M95*J95*K95*L95 -> 0 | O95: =J95*K95*L95 -> 0
A96: 25. | B96: Инженерно-геофизические исследования. (Миниминально требуемый объем для результатов ТЭО). При отсутствии фондовых материалов. | C96: =SUM(N96:N102) -> 0 | D96: =SUM(O96:O102) -> 0 | E96: =D96/8 -> 0 | G96: ГИП | N96: =M96*J96*K96*L96 -> 0 | O96: =J96*K96*L96 -> 0
G97: Нач. отдела | N97: =M97*J97*K97*L97 -> 0 | O97: =J97*K97*L97 -> 0
G98: Гл. специалист | N98: =M98*J98*K98*L98 -> 0 | O98: =J98*K98*L98 -> 0
G99: Рук. Группы | N99: =M99*J99*K99*L99 -> 0 | O99: =J99*K99*L99 -> 0
G100: Вед. инженер | N100: =M100*J100*K100*L100 -> 0 | O100: =J100*K100*L100 -> 0
G101: Старший инженер | N101: =M101*J101*K101*L101 -> 0 | O101: =J101*K101*L101 -> 0
G102: Инженер | N102: =M102*J102*K102*L102 -> 0 | O102: =J102*K102*L102 -> 0
...

Sheet ОТР_BOQ 
C1: Форма для заполнения по тендерной процедуре №ТП.....
A2: Разработка ОТР (Основные технические решения) по объекту "Выполнение проектно-изыскательских работ по проектам "Техническое перевооружение сети водопроводов, трубопроводов пенного пожаротушения ООО "Томскнефтехим" »
C4: (заполняется участником)
A5: № п/п | B5: Наименование показателей | C5: Стоимость, руб. без НДС | D5: Трудозатраты чел.час | E5: Трудозатраты чел.дни | F5: Наименование подрядчика | G5: Обоснование расчета*
G7: Должность | H7: Оценка количества листов документации | J7: чел. | K7: Дней | L7: Часов | M7: Ст-ть чел. часа (руб.) без НДС | N7: Итого Ст-ть (руб.) без НДС | O7: Итого кол. чел.час
H8: (текст.) ф.А4 | I8: (граф.) ф.А1
A9: Соответствие техническому заданию стадии ПД
A10: 1. | B10: Смета на строительство объектов капитального строительства | C10: =SUM(C11:C66) -> 0 | D10: =SUM(D11:D66) -> 0 | E10: =SUM(E11:E66) -> 0
A11: 1.1. | B11: Выполнить мониторинг рынка поставщиков и предоставить данные с учетом доставки до г. ……….: - по основным (ценообразующим) материалам - по вспомогательному оборудованию | C11: =SUM(N11:N17) -> 0 | D11: =SUM(O11:O17) -> 0 | E11: =D11/8 -> 0 | G11: ГИП | N11: =M11*J11*K11*L11 -> 0 | O11: =J11*K11*L11 -> 0
G12: Нач. отдела | N12: =M12*J12*K12*L12 -> 0 | O12: =J12*K12*L12 -> 0
G13: Гл. специалист | N13: =M13*J13*K13*L13 -> 0 | O13: =J13*K13*L13 -> 0
G14: Рук. Группы | N14: =M14*J14*K14*L14 -> 0 | O14: =J14*K14*L14 -> 0
G15: Вед. инженер | N15: =M15*J15*K15*L15 -> 0 | O15: =J15*K15*L15 -> 0
G16: Старший инженер | N16: =M16*J16*K16*L16 -> 0 | O16: =J16*K16*L16 -> 0
G17: Инженер | N17: =M17*J17*K17*L17 -> 0 | O17: =J17*K17*L17 -> 0
A18: 1.2. | B18: Предоставить ведомости объемов работ в формате BOQ (Описание выполняемых работ/объемы) точность +50% минус 30% | C18: =SUM(N18:N24) -> 0 | D18: =SUM(O18:O24) -> 0 | E18: =D18/8 -> 0 | G18: ГИП | N18: =M18*J18*K18*L18 -> 0 | O18: =J18*K18*L18 -> 0
G19: Нач. отдела | N19: =M19*J19*K19*L19 -> 0 | O19: =J19*K19*L19 -> 0
G20: Гл. специалист | N20: =M20*J20*K20*L20 -> 0 | O20: =J20*K20*L20 -> 0
G21: Рук. Группы | N21: =M21*J21*K21*L21 -> 0 | O21: =J21*K21*L21 -> 0
G22: Вед. инженер | N22: =M22*J22*K22*L22 -> 0 | O22: =J22*K22*L22 -> 0
G23: Старший инженер | N23: =M23*J23*K23*L23 -> 0 | O23: =J23*K23*L23 -> 0
G24: Инженер | N24: =M24*J24*K24*L24 -> 0 | O24: =J24*K24*L24 -> 0
A25: 1.3. | B25: Предоставить таблицу физических объемов сводную / по титульно точность +50% минус 30% | C25: =SUM(N25:N31) -> 0 | D25: =SUM(O25:O31) -> 0 | E25: =D25/8 -> 0 | G25: ГИП | N25: =M25*J25*K25*L25 -> 0 | O25: =J25*K25*L25 -> 0
G26: Нач. отдела | N26: =M26*J26*K26*L26 -> 0 | O26: =J26*K26*L26 -> 0
G27: Гл. специалист | N27: =M27*J27*K27*L27 -> 0 | O27: =J27*K27*L27 -> 0
G28: Рук. Группы | N28: =M28*J28*K28*L28 -> 0 | O28: =J28*K28*L28 -> 0
G29: Вед. инженер | N29: =M29*J29*K29*L29 -> 0 | O29: =J29*K29*L29 -> 0
G30: Старший инженер | N30: =M30*J30*K30*L30 -> 0 | O30: =J30*K30*L30 -> 0
G31: Инженер | N31: =M31*J31*K31*L31 -> 0 | O31: =J31*K31*L31 -> 0
A32: 1.4. | B32: Предоставить ведомости материалов с построчной стоимостью ресурсов (BOM) точность +50% минус 30% | C32: =SUM(N32:N38) -> 0 | D32: =SUM(O32:O38) -> 0 | E32: =D32/8 -> 0 | G32: ГИП | N32: =M32*J32*K32*L32 -> 0 | O32: =J32*K32*L32 -> 0
G33: Нач. отдела | N33: =M33*J33*K33*L33 -> 0 | O33: =J33*K33*L33 -> 0
G34: Гл. специалист | N34: =M34*J34*K34*L34 -> 0 | O34: =J34*K34*L34 -> 0
G35: Рук. Группы | N35: =M35*J35*K35*L35 -> 0 | O35: =J35*K35*L35 -> 0
G36: Вед. инженер | N36: =M36*J36*K36*L36 -> 0 | O36: =J36*K36*L36 -> 0
G37: Старший инженер | N37: =M37*J37*K37*L37 -> 0 | O37: =J37*K37*L37 -> 0
G38: Инженер | N38: =M38*J38*K38*L38 -> 0 | O38: =J38*K38*L38 -> 0
A39: 1.5. | B39: Предоставить ведомости оборудования с построчной стоимостью ресурсов (BOE) точность +50% минус 30% | C39: =SUM(N39:N45) -> 0 | D39: =SUM(O39:O45) -> 0 | E39: =D39/8 -> 0 | G39: ГИП | N39: =M39*J39*K39*L39 -> 0 | O39: =J39*K39*L39 -> 0
G40: Нач. отдела | N40: =M40*J40*K40*L40 -> 0 | O40: =J40*K40*L40 -> 0
G41: Гл. специалист | N41: =M41*J41*K41*L41 -> 0 | O41: =J41*K41*L41 -> 0
G42: Рук. Группы | N42: =M42*J42*K42*L42 -> 0 | O42: =J42*K42*L42 -> 0
G43: Вед. инженер | N43: =M43*J43*K43*L43 -> 0 | O43: =J43*K43*L43 -> 0
G44: Старший инженер | N44: =M44*J44*K44*L44 -> 0 | O44: =J44*K44*L44 -> 0
G45: Инженер | N45: =M45*J45*K45*L45 -> 0 | O45: =J45*K45*L45 -> 0
A46: 1.6. | B46: Расчитать количество стыков / дюйм диаметров по проекту (с приведением методики и пояснения расчетов) точность +50% минус 30% | C46: =SUM(N46:N52) -> 0 | D46: =SUM(O46:O52) -> 0 | E46: =D46/8 -> 0 | G46: ГИП | N46: =M46*J46*K46*L46 -> 0 | O46: =J46*K46*L46 -> 0
G47: Нач. отдела | N47: =M47*J47*K47*L47 -> 0 | O47: =J47*K47*L47 -> 0
G48: Гл. специалист | N48: =M48*J48*K48*L48 -> 0 | O48: =J48*K48*L48 -> 0
G49: Рук. Группы | N49: =M49*J49*K49*L49 -> 0 | O49: =J49*K49*L49 -> 0
G50: Вед. инженер | N50: =M50*J50*K50*L50 -> 0 | O50: =J50*K50*L50 -> 0
G51: Старший инженер | N51: =M51*J51*K51*L51 -> 0 | O51: =J51*K51*L51 -> 0
G52: Инженер | N52: =M52*J52*K52*L52 -> 0 | O52: =J52*K52*L52 -> 0
A53: 1.7. | B53: Предоставить пусконаладочные работы (ПНР, ППНР) определить расчетом.точность +50% минус 30% | C53: =SUM(N53:N59) -> 0 | D53: =SUM(O53:O59) -> 0 | E53: =D53/8 -> 0 | G53: ГИП | N53: =M53*J53*K53*L53 -> 0 | O53: =J53*K53*L53 -> 0
G54: Нач. отдела | N54: =M54*J54*K54*L54 -> 0 | O54: =J54*K54*L54 -> 0
G55: Гл. специалист | N55: =M55*J55*K55*L55 -> 0 | O55: =J55*K55*L55 -> 0
G56: Рук. Группы | N56: =M56*J56*K56*L56 -> 0 | O56: =J56*K56*L56 -> 0
G57: Вед. инженер | N57: =M57*J57*K57*L57 -> 0 | O57: =J57*K57*L57 -> 0
G58: Старший инженер | N58: =M58*J58*K58*L58 -> 0 | O58: =J58*K58*L58 -> 0
G59: Инженер | N59: =M59*J59*K59*L59 -> 0 | O59: =J59*K59*L59 -> 0
A60: 1.8. | B60: Предоставить пояснительную записку | C60: =SUM(N60:N66) -> 0 | D60: =SUM(O60:O66) -> 0 | E60: =D60/8 -> 0 | G60: ГИП | N60: =M60*J60*K60*L60 -> 0 | O60: =J60*K60*L60 -> 0
G61: Нач. отдела | N61: =M61*J61*K61*L61 -> 0 | O61: =J61*K61*L61 -> 0
G62: Гл. специалист | N62: =M62*J62*K62*L62 -> 0 | O62: =J62*K62*L62 -> 0
G63: Рук. Группы | N63: =M63*J63*K63*L63 -> 0 | O63: =J63*K63*L63 -> 0
G64: Вед. инженер | N64: =M64*J64*K64*L64 -> 0 | O64: =J64*K64*L64 -> 0
G65: Старший инженер | N65: =M65*J65*K65*L65 -> 0 | O65: =J65*K65*L65 -> 0
G66: Инженер | N66: =M66*J66*K66*L66 -> 0 | O66: =J66*K66*L66 -> 0
A67: 2. | B67: Документация ОТР | C67: =SUM(C68:C186) -> 0 | D67: =SUM(D68:D186) -> 0 | E67: =SUM(E68:E186) -> 0
A68: 2.1. | B68: Пояснительная записка. | C68: =SUM(N68:N74) -> 0 | D68: =SUM(O68:O74) -> 0 | E68: =D68/8 -> 0 | G68: ГИП | N68: =M68*J68*K68*L68 -> 0 | O68: =J68*K68*L68 -> 0
G69: Нач. отдела | N69: =M69*J69*K69*L69 -> 0 | O69: =J69*K69*L69 -> 0
G70: Гл. специалист | N70: =M70*J70*K70*L70 -> 0 | O70: =J70*K70*L70 -> 0
G71: Рук. Группы | N71: =M71*J71*K71*L71 -> 0 | O71: =J71*K71*L71 -> 0
G72: Вед. инженер | N72: =M72*J72*K72*L72 -> 0 | O72: =J72*K72*L72 -> 0
G73: Старший инженер | N73: =M73*J73*K73*L73 -> 0 | O73: =J73*K73*L73 -> 0
G74: Инженер | N74: =M74*J74*K74*L74 -> 0 | O74: =J74*K74*L74 -> 0
A75: 2.2. | B75: Основные технические решения. Технология производства. | C75: =SUM(N75:N81) -> 0 | D75: =SUM(O75:O81) -> 0 | E75: =D75/8 -> 0 | G75: ГИП | N75: =M75*J75*K75*L75 -> 0 | O75: =J75*K75*L75 -> 0
G76: Нач. отдела | N76: =M76*J76*K76*L76 -> 0 | O76: =J76*K76*L76 -> 0
G77: Гл. специалист | N77: =M77*J77*K77*L77 -> 0 | O77: =J77*K77*L77 -> 0
G78: Рук. Группы | N78: =M78*J78*K78*L78 -> 0 | O78: =J78*K78*L78 -> 0
G79: Вед. инженер | N79: =M79*J79*K79*L79 -> 0 | O79: =J79*K79*L79 -> 0
G80: Старший инженер | N80: =M80*J80*K80*L80 -> 0 | O80: =J80*K80*L80 -> 0
G81: Инженер | N81: =M81*J81*K81*L81 -> 0 | O81: =J81*K81*L81 -> 0
A82: 2.3. | B82: Технологическая схема и схема автоматизации | C82: =SUM(N82:N88) -> 0 | D82: =SUM(O82:O88) -> 0 | E82: =D82/8 -> 0 | G82: ГИП | N82: =M82*J82*K82*L82 -> 0 | O82: =J82*K82*L82 -> 0
G83: Нач. отдела | N83: =M83*J83*K83*L83 -> 0 | O83: =J83*K83*L83 -> 0
G84: Гл. специалист | N84: =M84*J84*K84*L84 -> 0 | O84: =J84*K84*L84 -> 0
G85: Рук. Группы | N85: =M85*J85*K85*L85 -> 0 | O85: =J85*K85*L85 -> 0
G86: Вед. инженер | N86: =M86*J86*K86*L86 -> 0 | O86: =J86*K86*L86 -> 0
G87: Старший инженер | N87: =M87*J87*K87*L87 -> 0 | O87: =J87*K87*L87 -> 0
G88: Инженер | N88: =M88*J88*K88*L88 -> 0 | O88: =J88*K88*L88 -> 0
A89: 2.4. | B89: Экспликация технологического оборудования | C89: =SUM(N89:N95) -> 0 | D89: =SUM(O89:O95) -> 0 | E89: =D89/8 -> 0 | G89: ГИП | N89: =M89*J89*K89*L89 -> 0 | O89: =J89*K89*L89 -> 0
G90: Нач. отдела | N90: =M90*J90*K90*L90 -> 0 | O90: =J90*K90*L90 -> 0
G91: Гл. специалист | N91: =M91*J91*K91*L91 -> 0 | O91: =J91*K91*L91 -> 0
G92: Рук. Группы | N92: =M92*J92*K92*L92 -> 0 | O92: =J92*K92*L92 -> 0
G93: Вед. инженер | N93: =M93*J93*K93*L93 -> 0 | O93: =J93*K93*L93 -> 0
G94: Старший инженер | N94: =M94*J94*K94*L94 -> 0 | O94: =J94*K94*L94 -> 0
G95: Инженер | N95: =M95*J95*K95*L95 -> 0 | O95: =J95*K95*L95 -> 0
A96: 2.5. | B96: Потребление энергоресурсов | C96: =SUM(N96:N102) -> 0 | D96: =SUM(O96:O102) -> 0 | E96: =D96/8 -> 0 | G96: ГИП | N96: =M96*J96*K96*L96 -> 0 | O96: =J96*K96*L96 -> 0
G97: Нач. отдела | N97: =M97*J97*K97*L97 -> 0 | O97: =J97*K97*L97 -> 0
G98: Гл. специалист | N98: =M98*J98*K98*L98 -> 0 | O98: =J98*K98*L98 -> 0
G99: Рук. Группы | N99: =M99*J99*K99*L99 -> 0 | O99: =J99*K99*L99 -> 0
G100: Вед. инженер | N100: =M100*J100*K100*L100 -> 0 | O100: =J100*K100*L100 -> 0
G101: Старший инженер | N101: =M101*J101*K101*L101 -> 0 | O101: =J101*K101*L101 -> 0
G102: Инженер | N102: =M102*J102*K102*L102 -> 0 | O102: =J102*K102*L102 -> 0
...

Sheet FEED_BOQ тит1
C1: Форма для заполнения по тендерной процедуре №ТП.....
A2: Разработка FEED по объекту "Выполнение проектно-изыскательских работ по проектам "Техническое перевооружение сети водопроводов, трубопроводов пенного пожаротушения ООО "Томскнефтехим" »
C4: (заполняется участником)
A5: № п/п | B5: Наименование показателей | C5: Стоимость, руб. без НДС | D5: Трудозатраты чел.час | E5: Трудозатраты чел.день | F5: Наименование подрядчика | G5: Обоснование расчета*
G7: Должность | H7: Оценка количества листов документации | J7: чел. | K7: Дней | L7: Часов | M7: Ст-ть чел. часа (руб.) без НДС | N7: Итого Ст-ть (руб.) без НДС | O7: Итого кол. чел.часов
H8: (текст.) ф.А4 | I8: (граф.) ф.А1
A9: Соответствие техническому заданию стадии ПД
A10: 1. | B10: Смета на строительство объектов капитального строительства | C10: =SUM(C11:C59) -> 0 | D10: =SUM(D11:D59) -> 0 | E10: =SUM(E11:E59) -> 0 | O10: =SUM(O11:O59) -> 0
A11: 1.1. | B11: Выполнить мониторинг рынка поставщиков и предоставить данные с учетом доставки до г. ……….: - по основным (ценообразующим) материалам - по вспомогательному оборудованию | C11: =SUM(N11:N17) -> 0 | D11: =SUM(O11:O17) -> 0 | E11: =D11/8 -> 0 | G11: ГИП | N11: =M11*J11*K11*L11 -> 0 | O11: =J11*K11*L11 -> 0
G12: Нач. отдела | N12: =M12*J12*K12*L12 -> 0 | O12: =J12*K12*L12 -> 0
G13: Гл. специалист | N13: =M13*J13*K13*L13 -> 0 | O13: =J13*K13*L13 -> 0
G14: Рук. Группы | N14: =M14*J14*K14*L14 -> 0 | O14: =J14*K14*L14 -> 0
G15: Вед. инженер | N15: =M15*J15*K15*L15 -> 0 | O15: =J15*K15*L15 -> 0
G16: Старший инженер | N16: =M16*J16*K16*L16 -> 0 | O16: =J16*K16*L16 -> 0
G17: Инженер | N17: =M17*J17*K17*L17 -> 0 | O17: =J17*K17*L17 -> 0
A18: 1.2. | B18: Предоставить ведомости объемов работ в формате BOQ | C18: =SUM(N18:N24) -> 0 | D18: =SUM(O18:O24) -> 0 | E18: =D18/8 -> 0 | G18: ГИП | N18: =M18*J18*K18*L18 -> 0 | O18: =J18*K18*L18 -> 0
G19: Нач. отдела | N19: =M19*J19*K19*L19 -> 0 | O19: =J19*K19*L19 -> 0
G20: Гл. специалист | N20: =M20*J20*K20*L20 -> 0 | O20: =J20*K20*L20 -> 0
G21: Рук. Группы | N21: =M21*J21*K21*L21 -> 0 | O21: =J21*K21*L21 -> 0
G22: Вед. инженер | N22: =M22*J22*K22*L22 -> 0 | O22: =J22*K22*L22 -> 0
G23: Старший инженер | N23: =M23*J23*K23*L23 -> 0 | O23: =J23*K23*L23 -> 0
G24: Инженер | N24: =M24*J24*K24*L24 -> 0 | O24: =J24*K24*L24 -> 0
A25: 1.3. | B25: Предоставить таблицу физических объемов сводную / по титульно | C25: =SUM(N25:N31) -> 0 | D25: =SUM(O25:O31) -> 0 | E25: =D25/8 -> 0 | G25: ГИП | N25: =M25*J25*K25*L25 -> 0 | O25: =J25*K25*L25 -> 0
G26: Нач. отдела | N26: =M26*J26*K26*L26 -> 0 | O26: =J26*K26*L26 -> 0
G27: Гл. специалист | N27: =M27*J27*K27*L27 -> 0 | O27: =J27*K27*L27 -> 0
G28: Рук. Группы | N28: =M28*J28*K28*L28 -> 0 | O28: =J28*K28*L28 -> 0
G29: Вед. инженер | N29: =M29*J29*K29*L29 -> 0 | O29: =J29*K29*L29 -> 0
G30: Старший инженер | N30: =M30*J30*K30*L30 -> 0 | O30: =J30*K30*L30 -> 0
G31: Инженер | N31: =M31*J31*K31*L31 -> 0 | O31: =J31*K31*L31 -> 0
A32: 1.4. | B32: Предоставить ведомости материалов с построчной стоимостью ресурсов (BOM) | C32: =SUM(N32:N38) -> 0 | D32: =SUM(O32:O38) -> 0 | E32: =D32/8 -> 0 | G32: ГИП | N32: =M32*J32*K32*L32 -> 0 | O32: =J32*K32*L32 -> 0
G33: Нач. отдела | N33: =M33*J33*K33*L33 -> 0 | O33: =J33*K33*L33 -> 0
G34: Гл. специалист | N34: =M34*J34*K34*L34 -> 0 | O34: =J34*K34*L34 -> 0
G35: Рук. Группы | N35: =M35*J35*K35*L35 -> 0 | O35: =J35*K35*L35 -> 0
G36: Вед. инженер | N36: =M36*J36*K36*L36 -> 0 | O36: =J36*K36*L36 -> 0
G37: Старший инженер | N37: =M37*J37*K37*L37 -> 0 | O37: =J37*K37*L37 -> 0
G38: Инженер | N38: =M38*J38*K38*L38 -> 0 | O38: =J38*K38*L38 -> 0
A39: 1.5. | B39: Предоставить ведомости оборудования с построчной стоимостью ресурсов (BOE) | C39: =SUM(N39:N45) -> 0 | D39: =SUM(O39:O45) -> 0 | E39: =D39/8 -> 0 | G39: ГИП | N39: =M39*J39*K39*L39 -> 0 | O39: =J39*K39*L39 -> 0
G40: Нач. отдела | N40: =M40*J40*K40*L40 -> 0 | O40: =J40*K40*L40 -> 0
G41: Гл. специалист | N41: =M41*J41*K41*L41 -> 0 | O41: =J41*K41*L41 -> 0
G42: Рук. Группы | N42: =M42*J42*K42*L42 -> 0 | O42: =J42*K42*L42 -> 0
G43: Вед. инженер | N43: =M43*J43*K43*L43 -> 0 | O43: =J43*K43*L43 -> 0
G44: Старший инженер | N44: =M44*J44*K44*L44 -> 0 | O44: =J44*K44*L44 -> 0
G45: Инженер | N45: =M45*J45*K45*L45 -> 0 | O45: =J45*K45*L45 -> 0
A46: 1.6. | B46: Расчитать количество стыков / дюйм диаметров по проекту (с приведением методики и пояснения расчетов) | C46: =SUM(N46:N52) -> 0 | D46: =SUM(O46:O52) -> 0 | E46: =D46/8 -> 0 | G46: ГИП | N46: =M46*J46*K46*L46 -> 0 | O46: =J46*K46*L46 -> 0
G47: Нач. отдела | N47: =M47*J47*K47*L47 -> 0 | O47: =J47*K47*L47 -> 0
G48: Гл. специалист | N48: =M48*J48*K48*L48 -> 0 | O48: =J48*K48*L48 -> 0
G49: Рук. Группы | N49: =M49*J49*K49*L49 -> 0 | O49: =J49*K49*L49 -> 0
G50: Вед. инженер | N50: =M50*J50*K50*L50 -> 0 | O50: =J50*K50*L50 -> 0
G51: Старший инженер | N51: =M51*J51*K51*L51 -> 0 | O51: =J51*K51*L51 -> 0
G52: Инженер | N52: =M52*J52*K52*L52 -> 0 | O52: =J52*K52*L52 -> 0
A53: 1.7. | B53: Предоставить пояснительную записку | C53: =SUM(N53:N59) -> 0 | D53: =SUM(O53:O59) -> 0 | E53: =D53/8 -> 0 | G53: ГИП | N53: =M53*J53*K53*L53 -> 0 | O53: =J53*K53*L53 -> 0
G54: Нач. отдела | N54: =M54*J54*K54*L54 -> 0 | O54: =J54*K54*L54 -> 0
G55: Гл. специалист | N55: =M55*J55*K55*L55 -> 0 | O55: =J55*K55*L55 -> 0
G56: Рук. Группы | N56: =M56*J56*K56*L56 -> 0 | O56: =J56*K56*L56 -> 0
G57: Вед. инженер | N57: =M57*J57*K57*L57 -> 0 | O57: =J57*K57*L57 -> 0
G58: Старший инженер | N58: =M58*J58*K58*L58 -> 0 | O58: =J58*K58*L58 -> 0
G59: Инженер | N59: =M59*J59*K59*L59 -> 0 | O59: =J59*K59*L59 -> 0
A60: 2. | B60: FEED (все разделы) | C60: =C61+C68+C75+C82+C89+C146+C153+C160+C167+C174+C181+C188+C195+C202+C209+C216+C223+C230+C237+C244+C251 -> 0 | D60: =D61+D68+D75+D82+D89+D146+D153+D160+D167+D174+D181+D188+D195+D202+D209+D216+D223+D230+D237+D244+D251 -> 0 | E60: =E61+E68+E75+E82+E89+E146+E153+E160+E167+E174+E181+E188+E195+E202+E209+E216+E223+E230+E237+E244+E251 -> 0 | O60: =SUM(O61:O257) -> 0
A61: 2.1. | B61: Раздел 1. Пояснительная записка. | C61: =SUM(N61:N67) -> 0 | D61: =SUM(O61:O67) -> 0 | E61: 0 | G61: ГИП | N61: =M61*J61*K61*L61 -> 0 | O61: =J61*K61*L61 -> 0
G62: Нач. отдела | N62: =M62*J62*K62*L62 -> 0 | O62: =J62*K62*L62 -> 0
G63: Гл. специалист | N63: =M63*J63*K63*L63 -> 0 | O63: =J63*K63*L63 -> 0
G64: Рук. Группы | N64: =M64*J64*K64*L64 -> 0 | O64: =J64*K64*L64 -> 0
G65: Вед. инженер | N65: =M65*J65*K65*L65 -> 0 | O65: =J65*K65*L65 -> 0
G66: Старший инженер | N66: =M66*J66*K66*L66 -> 0 | O66: =J66*K66*L66 -> 0
G67: Инженер | N67: =M67*J67*K67*L67 -> 0 | O67: =J67*K67*L67 -> 0
A68: 2.2. | B68: Раздел 2. Схема планировочной организации земельного участка. | C68: =SUM(N68:N74) -> 0 | D68: =SUM(O68:O74) -> 0 | E68: =D68/8 -> 0 | G68: ГИП | N68: =M68*J68*K68*L68 -> 0 | O68: =J68*K68*L68 -> 0
G69: Нач. отдела | N69: =M69*J69*K69*L69 -> 0 | O69: =J69*K69*L69 -> 0
G70: Гл. специалист | N70: =M70*J70*K70*L70 -> 0 | O70: =J70*K70*L70 -> 0
G71: Рук. Группы | N71: =M71*J71*K71*L71 -> 0 | O71: =J71*K71*L71 -> 0
G72: Вед. инженер | N72: =M72*J72*K72*L72 -> 0 | O72: =J72*K72*L72 -> 0
G73: Старший инженер | N73: =M73*J73*K73*L73 -> 0 | O73: =J73*K73*L73 -> 0
G74: Инженер | N74: =M74*J74*K74*L74 -> 0 | O74: =J74*K74*L74 -> 0
A75: 2.3. | B75: Раздел 3. Архитектурные решения. | C75: =SUM(N75:N81) -> 0 | D75: =SUM(O75:O81) -> 0 | E75: =D75/8 -> 0 | G75: ГИП | N75: =M75*J75*K75*L75 -> 0 | O75: =J75*K75*L75 -> 0
G76: Нач. отдела | N76: =M76*J76*K76*L76 -> 0 | O76: =J76*K76*L76 -> 0
G77: Гл. специалист | N77: =M77*J77*K77*L77 -> 0 | O77: =J77*K77*L77 -> 0
G78: Рук. Группы | N78: =M78*J78*K78*L78 -> 0 | O78: =J78*K78*L78 -> 0
G79: Вед. инженер | N79: =M79*J79*K79*L79 -> 0 | O79: =J79*K79*L79 -> 0
G80: Старший инженер | N80: =M80*J80*K80*L80 -> 0 | O80: =J80*K80*L80 -> 0
G81: Инженер | N81: =M81*J81*K81*L81 -> 0 | O81: =J81*K81*L81 -> 0
A82: 2.4. | B82: Раздел 4. Конструктивные и объемно-планировочные решения. | C82: =SUM(N82:N88) -> 0 | D82: =SUM(O82:O88) -> 0 | E82: =D82/8 -> 0 | G82: ГИП | N82: =M82*J82*K82*L82 -> 0 | O82: =J82*K82*L82 -> 0
G83: Нач. отдела | N83: =M83*J83*K83*L83 -> 0 | O83: =J83*K83*L83 -> 0
G84: Гл. специалист | N84: =M84*J84*K84*L84 -> 0 | O84: =J84*K84*L84 -> 0
G85: Рук. Группы | N85: =M85*J85*K85*L85 -> 0 | O85: =J85*K85*L85 -> 0
G86: Вед. инженер | N86: =M86*J86*K86*L86 -> 0 | O86: =J86*K86*L86 -> 0
G87: Старший инженер | N87: =M87*J87*K87*L87 -> 0 | O87: =J87*K87*L87 -> 0
G88: Инженер | N88: =M88*J88*K88*L88 -> 0 | O88: =J88*K88*L88 -> 0
A89: 2.5. | B89: Раздел 5. Сведения об инженерном оборудовании, сетях инженерно-технического обеспечения, перечень инженерно-технических мероприятий, содержание технологических решений. | C89: =SUM(C90:C145) -> 0 | D89: =SUM(D90:D145) -> 0 | E89: =SUM(E90:E145) -> 0
A90: 2.5.1. | B90: подраздел 5.1 Система электроснабжения | C90: =SUM(N90:N96) -> 0 | D90: =SUM(O90:O96) -> 0 | E90: =D90/8 -> 0 | G90: ГИП | N90: =M90*J90*K90*L90 -> 0 | O90: =J90*K90*L90 -> 0
G91: Нач. отдела | N91: =M91*J91*K91*L91 -> 0 | O91: =J91*K91*L91 -> 0
G92: Гл. специалист | N92: =M92*J92*K92*L92 -> 0 | O92: =J92*K92*L92 -> 0
G93: Рук. Группы | N93: =M93*J93*K93*L93 -> 0 | O93: =J93*K93*L93 -> 0
G94: Вед. инженер | N94: =M94*J94*K94*L94 -> 0 | O94: =J94*K94*L94 -> 0
G95: Старший инженер | N95: =M95*J95*K95*L95 -> 0 | O95: =J95*K95*L95 -> 0
G96: Инженер | N96: =M96*J96*K96*L96 -> 0 | O96: =J96*K96*L96 -> 0
A97: 2.5.2. | B97: подраздел 5.2 Система водоснабжения | C97: =SUM(N97:N103) -> 0 | D97: =SUM(O97:O103) -> 0 | E97: =D97/8 -> 0 | G97: ГИП | N97: =M97*J97*K97*L97 -> 0 | O97: =J97*K97*L97 -> 0
G98: Нач. отдела | N98: =M98*J98*K98*L98 -> 0 | O98: =J98*K98*L98 -> 0
G99: Гл. специалист | N99: =M99*J99*K99*L99 -> 0 | O99: =J99*K99*L99 -> 0
G100: Рук. Группы | N100: =M100*J100*K100*L100 -> 0 | O100: =J100*K100*L100 -> 0
G101: Вед. инженер | N101: =M101*J101*K101*L101 -> 0 | O101: =J101*K101*L101 -> 0
G102: Старший инженер | N102: =M102*J102*K102*L102 -> 0 | O102: =J102*K102*L102 -> 0
...

Sheet FEED_BOQ тит2
C1: Форма для заполнения по тендерной процедуре №ТП.....
A2: Разработка FEED по объекту "Выполнение проектно-изыскательских работ по проектам "Техническое перевооружение сети водопроводов, трубопроводов пенного пожаротушения ООО "Томскнефтехим" .»
C4: (заполняется участником)
A5: № п/п | B5: Наименование показателей | C5: Стоимость, руб. без НДС | D5: Трудозатраты чел.час | E5: Трудозатраты чел.день | F5: Наименование подрядчика | G5: Обоснование расчета*
G7: Должность | H7: Оценка количества листов документации | J7: чел. | K7: Дней | L7: Часов | M7: Ст-ть чел. часа (руб.) без НДС | N7: Итого Ст-ть (руб.) без НДС | O7: Итого кол. чел.часов
H8: (текст.) ф.А4 | I8: (граф.) ф.А1
A9: Соответствие техническому заданию стадии ПД
A10: 1. | B10: Смета на строительство объектов капитального строительства | C10: =SUM(C11:C59) -> 0 | D10: =SUM(D11:D59) -> 0 | E10: =SUM(E11:E59) -> 0 | O10: =SUM(O11:O59) -> 0
A11: 1.1. | B11: Выполнить мониторинг рынка поставщиков и предоставить данные с учетом доставки до г. ……….: - по основным (ценообразующим) материалам - по вспомогательному оборудованию | C11: =SUM(N11:N17) -> 0 | D11: =SUM(O11:O17) -> 0 | E11: =D11/8 -> 0 | G11: ГИП | N11: =M11*J11*K11*L11 -> 0 | O11: =J11*K11*L11 -> 0
G12: Нач. отдела | N12: =M12*J12*K12*L12 -> 0 | O12: =J12*K12*L12 -> 0
G13: Гл. специалист | N13: =M13*J13*K13*L13 -> 0 | O13: =J13*K13*L13 -> 0
G14: Рук. Группы | N14: =M14*J14*K14*L14 -> 0 | O14: =J14*K14*L14 -> 0
G15: Вед. инженер | N15: =M15*J15*K15*L15 -> 0 | O15: =J15*K15*L15 -> 0
G16: Старший инженер | N16: =M16*J16*K16*L16 -> 0 | O16: =J16*K16*L16 -> 0
G17: Инженер | N17: =M17*J17*K17*L17 -> 0 | O17: =J17*K17*L17 -> 0
A18: 1.2. | B18: Предоставить ведомости объемов работ в формате BOQ | C18: =SUM(N18:N24) -> 0 | D18: =SUM(O18:O24) -> 0 | E18: =D18/8 -> 0 | G18: ГИП | N18: =M18*J18*K18*L18 -> 0 | O18: =J18*K18*L18 -> 0
G19: Нач. отдела | N19: =M19*J19*K19*L19 -> 0 | O19: =J19*K19*L19 -> 0
G20: Гл. специалист | N20: =M20*J20*K20*L20 -> 0 | O20: =J20*K20*L20 -> 0
G21: Рук. Группы | N21: =M21*J21*K21*L21 -> 0 | O21: =J21*K21*L21 -> 0
G22: Вед. инженер | N22: =M22*J22*K22*L22 -> 0 | O22: =J22*K22*L22 -> 0
G23: Старший инженер | N23: =M23*J23*K23*L23 -> 0 | O23: =J23*K23*L23 -> 0
G24: Инженер | N24: =M24*J24*K24*L24 -> 0 | O24: =J24*K24*L24 -> 0
A25: 1.3. | B25: Предоставить таблицу физических объемов сводную / по титульно | C25: =SUM(N25:N31) -> 0 | D25: =SUM(O25:O31) -> 0 | E25: =D25/8 -> 0 | G25: ГИП | N25: =M25*J25*K25*L25 -> 0 | O25: =J25*K25*L25 -> 0
G26: Нач. отдела | N26: =M26*J26*K26*L26 -> 0 | O26: =J26*K26*L26 -> 0
G27: Гл. специалист | N27: =M27*J27*K27*L27 -> 0 | O27: =J27*K27*L27 -> 0
G28: Рук. Группы | N28: =M28*J28*K28*L28 -> 0 | O28: =J28*K28*L28 -> 0
G29: Вед. инженер | N29: =M29*J29*K29*L29 -> 0 | O29: =J29*K29*L29 -> 0
G30: Старший инженер | N30: =M30*J30*K30*L30 -> 0 | O30: =J30*K30*L30 -> 0
G31: Инженер | N31: =M31*J31*K31*L31 -> 0 | O31: =J31*K31*L31 -> 0
A32: 1.4. | B32: Предоставить ведомости материалов с построчной стоимостью ресурсов (BOM) | C32: =SUM(N32:N38) -> 0 | D32: =SUM(O32:O38) -> 0 | E32: =D32/8 -> 0 | G32: ГИП | N32: =M32*J32*K32*L32 -> 0 | O32: =J32*K32*L32 -> 0
G33: Нач. отдела | N33: =M33*J33*K33*L33 -> 0 | O33: =J33*K33*L33 -> 0
G34: Гл. специалист | N34: =M34*J34*K34*L34 -> 0 | O34: =J34*K34*L34 -> 0
G35: Рук. Группы | N35: =M35*J35*K35*L35 -> 0 | O35: =J35*K35*L35 -> 0
G36: Вед. инженер | N36: =M36*J36*K36*L36 -> 0 | O36: =J36*K36*L36 -> 0
G37: Старший инженер | N37: =M37*J37*K37*L37 -> 0 | O37: =J37*K37*L37 -> 0
G38: Инженер | N38: =M38*J38*K38*L38 -> 0 | O38: =J38*K38*L38 -> 0
A39: 1.5. | B39: Предоставить ведомости оборудования с построчной стоимостью ресурсов (BOE) | C39: =SUM(N39:N45) -> 0 | D39: =SUM(O39:O45) -> 0 | E39: =D39/8 -> 0 | G39: ГИП | N39: =M39*J39*K39*L39 -> 0 | O39: =J39*K39*L39 -> 0
G40: Нач. отдела | N40: =M40*J40*K40*L40 -> 0 | O40: =J40*K40*L40 -> 0
G41: Гл. специалист | N41: =M41*J41*K41*L41 -> 0 | O41: =J41*K41*L41 -> 0
G42: Рук. Группы | N42: =M42*J42*K42*L42 -> 0 | O42: =J42*K42*L42 -> 0
G43: Вед. инженер | N43: =M43*J43*K43*L43 -> 0 | O43: =J43*K43*L43 -> 0
G44: Старший инженер | N44: =M44*J44*K44*L44 -> 0 | O44: =J44*K44*L44 -> 0
G45: Инженер | N45: =M45*J45*K45*L45 -> 0 | O45: =J45*K45*L45 -> 0
A46: 1.6. | B46: Расчитать количество стыков / дюйм диаметров по проекту (с приведением методики и пояснения расчетов) | C46: =SUM(N46:N52) -> 0 | D46: =SUM(O46:O52) -> 0 | E46: =D46/8 -> 0 | G46: ГИП | N46: =M46*J46*K46*L46 -> 0 | O46: =J46*K46*L46 -> 0
G47: Нач. отдела | N47: =M47*J47*K47*L47 -> 0 | O47: =J47*K47*L47 -> 0
G48: Гл. специалист | N48: =M48*J48*K48*L48 -> 0 | O48: =J48*K48*L48 -> 0
G49: Рук. Группы | N49: =M49*J49*K49*L49 -> 0 | O49: =J49*K49*L49 -> 0
G50: Вед. инженер | N50: =M50*J50*K50*L50 -> 0 | O50: =J50*K50*L50 -> 0
G51: Старший инженер | N51: =M51*J51*K51*L51 -> 0 | O51: =J51*K51*L51 -> 0
G52: Инженер | N52: =M52*J52*K52*L52 -> 0 | O52: =J52*K52*L52 -> 0
A53: 1.7. | B53: Предоставить пояснительную записку | C53: =SUM(N53:N59) -> 0 | D53: =SUM(O53:O59) -> 0 | E53: =D53/8 -> 0 | G53: ГИП | N53: =M53*J53*K53*L53 -> 0 | O53: =J53*K53*L53 -> 0
G54: Нач. отдела | N54: =M54*J54*K54*L54 -> 0 | O54: =J54*K54*L54 -> 0
G55: Гл. специалист | N55: =M55*J55*K55*L55 -> 0 | O55: =J55*K55*L55 -> 0
G56: Рук. Группы | N56: =M56*J56*K56*L56 -> 0 | O56: =J56*K56*L56 -> 0
G57: Вед. инженер | N57: =M57*J57*K57*L57 -> 0 | O57: =J57*K57*L57 -> 0
G58: Старший инженер | N58: =M58*J58*K58*L58 -> 0 | O58: =J58*K58*L58 -> 0
G59: Инженер | N59: =M59*J59*K59*L59 -> 0 | O59: =J59*K59*L59 -> 0
A60: 2. | B60: FEED (все разделы) | C60: =C61+C68+C75+C82+C89+C146+C153+C160+C167+C174+C181+C188+C195+C202+C209+C216+C223+C230+C237+C244+C251 -> 0 | D60: =D61+D68+D75+D82+D89+D146+D153+D160+D167+D174+D181+D188+D195+D202+D209+D216+D223+D230+D237+D244+D251 -> 0 | E60: =E61+E68+E75+E82+E89+E146+E153+E160+E167+E174+E181+E188+E195+E202+E209+E216+E223+E230+E237+E244+E251 -> 0 | O60: =SUM(O61:O257) -> 0
A61: 2.1. | B61: Раздел 1. Пояснительная записка. | C61: =SUM(N61:N67) -> 0 | D61: =SUM(O61:O67) -> 0 | E61: 0 | G61: ГИП | N61: =M61*J61*K61*L61 -> 0 | O61: =J61*K61*L61 -> 0
G62: Нач. отдела | N62: =M62*J62*K62*L62 -> 0 | O62: =J62*K62*L62 -> 0
G63: Гл. специалист | N63: =M63*J63*K63*L63 -> 0 | O63: =J63*K63*L63 -> 0
G64: Рук. Группы | N64: =M64*J64*K64*L64 -> 0 | O64: =J64*K64*L64 -> 0
G65: Вед. инженер | N65: =M65*J65*K65*L65 -> 0 | O65: =J65*K65*L65 -> 0
G66: Старший инженер | N66: =M66*J66*K66*L66 -> 0 | O66: =J66*K66*L66 -> 0
G67: Инженер | N67: =M67*J67*K67*L67 -> 0 | O67: =J67*K67*L67 -> 0
A68: 2.2. | B68: Раздел 2. Схема планировочной организации земельного участка. | C68: =SUM(N68:N74) -> 0 | D68: =SUM(O68:O74) -> 0 | E68: =D68/8 -> 0 | G68: ГИП | N68: =M68*J68*K68*L68 -> 0 | O68: =J68*K68*L68 -> 0
G69: Нач. отдела | N69: =M69*J69*K69*L69 -> 0 | O69: =J69*K69*L69 -> 0
G70: Гл. специалист | N70: =M70*J70*K70*L70 -> 0 | O70: =J70*K70*L70 -> 0
G71: Рук. Группы | N71: =M71*J71*K71*L71 -> 0 | O71: =J71*K71*L71 -> 0
G72: Вед. инженер | N72: =M72*J72*K72*L72 -> 0 | O72: =J72*K72*L72 -> 0
G73: Старший инженер | N73: =M73*J73*K73*L73 -> 0 | O73: =J73*K73*L73 -> 0
G74: Инженер | N74: =M74*J74*K74*L74 -> 0 | O74: =J74*K74*L74 -> 0
A75: 2.3. | B75: Раздел 3. Архитектурные решения. | C75: =SUM(N75:N81) -> 0 | D75: =SUM(O75:O81) -> 0 | E75: =D75/8 -> 0 | G75: ГИП | N75: =M75*J75*K75*L75 -> 0 | O75: =J75*K75*L75 -> 0
G76: Нач. отдела | N76: =M76*J76*K76*L76 -> 0 | O76: =J76*K76*L76 -> 0
G77: Гл. специалист | N77: =M77*J77*K77*L77 -> 0 | O77: =J77*K77*L77 -> 0
G78: Рук. Группы | N78: =M78*J78*K78*L78 -> 0 | O78: =J78*K78*L78 -> 0
G79: Вед. инженер | N79: =M79*J79*K79*L79 -> 0 | O79: =J79*K79*L79 -> 0
G80: Старший инженер | N80: =M80*J80*K80*L80 -> 0 | O80: =J80*K80*L80 -> 0
G81: Инженер | N81: =M81*J81*K81*L81 -> 0 | O81: =J81*K81*L81 -> 0
A82: 2.4. | B82: Раздел 4. Конструктивные и объемно-планировочные решения. | C82: =SUM(N82:N88) -> 0 | D82: =SUM(O82:O88) -> 0 | E82: =D82/8 -> 0 | G82: ГИП | N82: =M82*J82*K82*L82 -> 0 | O82: =J82*K82*L82 -> 0
G83: Нач. отдела | N83: =M83*J83*K83*L83 -> 0 | O83: =J83*K83*L83 -> 0
G84: Гл. специалист | N84: =M84*J84*K84*L84 -> 0 | O84: =J84*K84*L84 -> 0
G85: Рук. Группы | N85: =M85*J85*K85*L85 -> 0 | O85: =J85*K85*L85 -> 0
G86: Вед. инженер | N86: =M86*J86*K86*L86 -> 0 | O86: =J86*K86*L86 -> 0
G87: Старший инженер | N87: =M87*J87*K87*L87 -> 0 | O87: =J87*K87*L87 -> 0
G88: Инженер | N88: =M88*J88*K88*L88 -> 0 | O88: =J88*K88*L88 -> 0
A89: 2.5. | B89: Раздел 5. Сведения об инженерном оборудовании, сетях инженерно-технического обеспечения, перечень инженерно-технических мероприятий, содержание технологических решений. | C89: =SUM(C90:C145) -> 0 | D89: =SUM(D90:D145) -> 0 | E89: =SUM(E90:E145) -> 0
A90: 2.5.1. | B90: подраздел 5.1 Система электроснабжения | C90: =SUM(N90:N96) -> 0 | D90: =SUM(O90:O96) -> 0 | E90: =D90/8 -> 0 | G90: ГИП | N90: =M90*J90*K90*L90 -> 0 | O90: =J90*K90*L90 -> 0
G91: Нач. отдела | N91: =M91*J91*K91*L91 -> 0 | O91: =J91*K91*L91 -> 0
G92: Гл. специалист | N92: =M92*J92*K92*L92 -> 0 | O92: =J92*K92*L92 -> 0
G93: Рук. Группы | N93: =M93*J93*K93*L93 -> 0 | O93: =J93*K93*L93 -> 0
G94: Вед. инженер | N94: =M94*J94*K94*L94 -> 0 | O94: =J94*K94*L94 -> 0
G95: Старший инженер | N95: =M95*J95*K95*L95 -> 0 | O95: =J95*K95*L95 -> 0
G96: Инженер | N96: =M96*J96*K96*L96 -> 0 | O96: =J96*K96*L96 -> 0
A97: 2.5.2. | B97: подраздел 5.2 Система водоснабжения | C97: =SUM(N97:N103) -> 0 | D97: =SUM(O97:O103) -> 0 | E97: =D97/8 -> 0 | G97: ГИП | N97: =M97*J97*K97*L97 -> 0 | O97: =J97*K97*L97 -> 0
G98: Нач. отдела | N98: =M98*J98*K98*L98 -> 0 | O98: =J98*K98*L98 -> 0
G99: Гл. специалист | N99: =M99*J99*K99*L99 -> 0 | O99: =J99*K99*L99 -> 0
G100: Рук. Группы | N100: =M100*J100*K100*L100 -> 0 | O100: =J100*K100*L100 -> 0
G101: Вед. инженер | N101: =M101*J101*K101*L101 -> 0 | O101: =J101*K101*L101 -> 0
G102: Старший инженер | N102: =M102*J102*K102*L102 -> 0 | O102: =J102*K102*L102 -> 0
...

Sheet ПД_BOQ тит1.
C1: Форма для заполнения по тендерной процедуре №ТП.....
A2: Разработка проектной документации по объекту "Выполнение проектно-изыскательских работ по проектам "Техническое перевооружение сети водопроводов, трубопроводов пенного пожаротушения ООО "Томскнефтехим" »
C4: (заполняется участником)
A5: № п/п | B5: Наименование показателей | C5: Стоимость, руб. без НДС | D5: Трудозатраты чел.час | E5: Трудозатраты чел.день | F5: Наименование подрядчика | G5: Обоснование расчета*
G7: Должность | H7: Оценка количества листов документации | J7: чел. | K7: Дней | L7: Часов | M7: Ст-ть чел. часа (руб.) без НДС | N7: Итого Ст-ть (руб.) без НДС | O7: Итого кол. чел.часов
H8: (текст.) ф.А4 | I8: (граф.) ф.А1
A9: Соответствие техническому заданию стадии ПД
A10: 1. | B10: Смета на строительство объектов капитального строительства | C10: =SUM(C11:C59) -> 0 | D10: =SUM(D11:D59) -> 0 | E10: =SUM(E11:E59) -> 0 | O10: =SUM(O11:O59) -> 0
A11: 1.1. | B11: Выполнить мониторинг рынка поставщиков и предоставить данные с учетом доставки до г. ……….: - по основным (ценообразующим) материалам - по вспомогательному оборудованию | C11: =SUM(N11:N17) -> 0 | D11: =SUM(O11:O17) -> 0 | E11: =D11/8 -> 0 | G11: ГИП | N11: =M11*J11*K11*L11 -> 0 | O11: =J11*K11*L11 -> 0
G12: Нач. отдела | N12: =M12*J12*K12*L12 -> 0 | O12: =J12*K12*L12 -> 0
G13: Гл. специалист | N13: =M13*J13*K13*L13 -> 0 | O13: =J13*K13*L13 -> 0
G14: Рук. Группы | N14: =M14*J14*K14*L14 -> 0 | O14: =J14*K14*L14 -> 0
G15: Вед. инженер | N15: =M15*J15*K15*L15 -> 0 | O15: =J15*K15*L15 -> 0
G16: Старший инженер | N16: =M16*J16*K16*L16 -> 0 | O16: =J16*K16*L16 -> 0
G17: Инженер | N17: =M17*J17*K17*L17 -> 0 | O17: =J17*K17*L17 -> 0
A18: 1.2. | B18: Предоставить ведомости объемов работ в формате BOQ | C18: =SUM(N18:N24) -> 0 | D18: =SUM(O18:O24) -> 0 | E18: =D18/8 -> 0 | G18: ГИП | N18: =M18*J18*K18*L18 -> 0 | O18: =J18*K18*L18 -> 0
G19: Нач. отдела | N19: =M19*J19*K19*L19 -> 0 | O19: =J19*K19*L19 -> 0
G20: Гл. специалист | N20: =M20*J20*K20*L20 -> 0 | O20: =J20*K20*L20 -> 0
G21: Рук. Группы | N21: =M21*J21*K21*L21 -> 0 | O21: =J21*K21*L21 -> 0
G22: Вед. инженер | N22: =M22*J22*K22*L22 -> 0 | O22: =J22*K22*L22 -> 0
G23: Старший инженер | N23: =M23*J23*K23*L23 -> 0 | O23: =J23*K23*L23 -> 0
G24: Инженер | N24: =M24*J24*K24*L24 -> 0 | O24: =J24*K24*L24 -> 0
A25: 1.3. | B25: Предоставить таблицу физических объемов сводную / по титульно | C25: =SUM(N25:N31) -> 0 | D25: =SUM(O25:O31) -> 0 | E25: =D25/8 -> 0 | G25: ГИП | N25: =M25*J25*K25*L25 -> 0 | O25: =J25*K25*L25 -> 0
G26: Нач. отдела | N26: =M26*J26*K26*L26 -> 0 | O26: =J26*K26*L26 -> 0
G27: Гл. специалист | N27: =M27*J27*K27*L27 -> 0 | O27: =J27*K27*L27 -> 0
G28: Рук. Группы | N28: =M28*J28*K28*L28 -> 0 | O28: =J28*K28*L28 -> 0
G29: Вед. инженер | N29: =M29*J29*K29*L29 -> 0 | O29: =J29*K29*L29 -> 0
G30: Старший инженер | N30: =M30*J30*K30*L30 -> 0 | O30: =J30*K30*L30 -> 0
G31: Инженер | N31: =M31*J31*K31*L31 -> 0 | O31: =J31*K31*L31 -> 0
A32: 1.4. | B32: Предоставить ведомости материалов с построчной стоимостью ресурсов (BOM) | C32: =SUM(N32:N38) -> 0 | D32: =SUM(O32:O38) -> 0 | E32: =D32/8 -> 0 | G32: ГИП | N32: =M32*J32*K32*L32 -> 0 | O32: =J32*K32*L32 -> 0
G33: Нач. отдела | N33: =M33*J33*K33*L33 -> 0 | O33: =J33*K33*L33 -> 0
G34: Гл. специалист | N34: =M34*J34*K34*L34 -> 0 | O34: =J34*K34*L34 -> 0
G35: Рук. Группы | N35: =M35*J35*K35*L35 -> 0 | O35: =J35*K35*L35 -> 0
G36: Вед. инженер | N36: =M36*J36*K36*L36 -> 0 | O36: =J36*K36*L36 -> 0
G37: Старший инженер | N37: =M37*J37*K37*L37 -> 0 | O37: =J37*K37*L37 -> 0
G38: Инженер | N38: =M38*J38*K38*L38 -> 0 | O38: =J38*K38*L38 -> 0
A39: 1.5. | B39: Предоставить ведомости оборудования с построчной стоимостью ресурсов (BOE) | C39: =SUM(N39:N45) -> 0 | D39: =SUM(O39:O45) -> 0 | E39: =D39/8 -> 0 | G39: ГИП | N39: =M39*J39*K39*L39 -> 0 | O39: =J39*K39*L39 -> 0
G40: Нач. отдела | N40: =M40*J40*K40*L40 -> 0 | O40: =J40*K40*L40 -> 0
G41: Гл. специалист | N41: =M41*J41*K41*L41 -> 0 | O41: =J41*K41*L41 -> 0
G42: Рук. Группы | N42: =M42*J42*K42*L42 -> 0 | O42: =J42*K42*L42 -> 0
G43: Вед. инженер | N43: =M43*J43*K43*L43 -> 0 | O43: =J43*K43*L43 -> 0
G44: Старший инженер | N44: =M44*J44*K44*L44 -> 0 | O44: =J44*K44*L44 -> 0
G45: Инженер | N45: =M45*J45*K45*L45 -> 0 | O45: =J45*K45*L45 -> 0
A46: 1.6. | B46: Расчитать количество стыков / дюйм диаметров по проекту (с приведением методики и пояснения расчетов) | C46: =SUM(N46:N52) -> 0 | D46: =SUM(O46:O52) -> 0 | E46: =D46/8 -> 0 | G46: ГИП | N46: =M46*J46*K46*L46 -> 0 | O46: =J46*K46*L46 -> 0
G47: Нач. отдела | N47: =M47*J47*K47*L47 -> 0 | O47: =J47*K47*L47 -> 0
G48: Гл. специалист | N48: =M48*J48*K48*L48 -> 0 | O48: =J48*K48*L48 -> 0
G49: Рук. Группы | N49: =M49*J49*K49*L49 -> 0 | O49: =J49*K49*L49 -> 0
G50: Вед. инженер | N50: =M50*J50*K50*L50 -> 0 | O50: =J50*K50*L50 -> 0
G51: Старший инженер | N51: =M51*J51*K51*L51 -> 0 | O51: =J51*K51*L51 -> 0
G52: Инженер | N52: =M52*J52*K52*L52 -> 0 | O52: =J52*K52*L52 -> 0
A53: 1.7. | B53: Предоставить пояснительную записку | C53: =SUM(N53:N59) -> 0 | D53: =SUM(O53:O59) -> 0 | E53: =D53/8 -> 0 | G53: ГИП | N53: =M53*J53*K53*L53 -> 0 | O53: =J53*K53*L53 -> 0
G54: Нач. отдела | N54: =M54*J54*K54*L54 -> 0 | O54: =J54*K54*L54 -> 0
G55: Гл. специалист | N55: =M55*J55*K55*L55 -> 0 | O55: =J55*K55*L55 -> 0
G56: Рук. Группы | N56: =M56*J56*K56*L56 -> 0 | O56: =J56*K56*L56 -> 0
G57: Вед. инженер | N57: =M57*J57*K57*L57 -> 0 | O57: =J57*K57*L57 -> 0
G58: Старший инженер | N58: =M58*J58*K58*L58 -> 0 | O58: =J58*K58*L58 -> 0
G59: Инженер | N59: =M59*J59*K59*L59 -> 0 | O59: =J59*K59*L59 -> 0
A60: 2. | B60: Проектная документация (все разделы) | C60: =C61+C68+C75+C82+C89+C146+C153+C160+C167+C174+C181+C188+C195+C202+C209+C216+C223+C237+C244+C251+C265 -> 0 | D60: =D61+D68+D75+D82+D89+D146+D153+D160+D167+D174+D181+D188+D195+D202+D209+D216+D223+D237+D244+D251+D265 -> 0 | E60: =E61+E68+E75+E82+E89+E146+E153+E160+E167+E174+E181+E188+E195+E202+E209+E216+E223+E237+E244+E251+E265 -> 0 | O60: =SUM(O61:O271) -> 0
A61: 2.1. | B61: Раздел 1. Пояснительная записка. | C61: =SUM(N61:N67) -> 0 | D61: =SUM(O61:O67) -> 0 | E61: 0 | G61: ГИП | N61: =M61*J61*K61*L61 -> 0 | O61: =J61*K61*L61 -> 0
G62: Нач. отдела | N62: =M62*J62*K62*L62 -> 0 | O62: =J62*K62*L62 -> 0
G63: Гл. специалист | N63: =M63*J63*K63*L63 -> 0 | O63: =J63*K63*L63 -> 0
G64: Рук. Группы | N64: =M64*J64*K64*L64 -> 0 | O64: =J64*K64*L64 -> 0
G65: Вед. инженер | N65: =M65*J65*K65*L65 -> 0 | O65: =J65*K65*L65 -> 0
G66: Старший инженер | N66: =M66*J66*K66*L66 -> 0 | O66: =J66*K66*L66 -> 0
G67: Инженер | N67: =M67*J67*K67*L67 -> 0 | O67: =J67*K67*L67 -> 0
A68: 2.2. | B68: Раздел 2. Схема планировочной организации земельного участка. | C68: =SUM(N68:N74) -> 0 | D68: =SUM(O68:O74) -> 0 | E68: =D68/8 -> 0 | G68: ГИП | N68: =M68*J68*K68*L68 -> 0 | O68: =J68*K68*L68 -> 0
G69: Нач. отдела | N69: =M69*J69*K69*L69 -> 0 | O69: =J69*K69*L69 -> 0
G70: Гл. специалист | N70: =M70*J70*K70*L70 -> 0 | O70: =J70*K70*L70 -> 0
G71: Рук. Группы | N71: =M71*J71*K71*L71 -> 0 | O71: =J71*K71*L71 -> 0
G72: Вед. инженер | N72: =M72*J72*K72*L72 -> 0 | O72: =J72*K72*L72 -> 0
G73: Старший инженер | N73: =M73*J73*K73*L73 -> 0 | O73: =J73*K73*L73 -> 0
G74: Инженер | N74: =M74*J74*K74*L74 -> 0 | O74: =J74*K74*L74 -> 0
A75: 2.3. | B75: Раздел 3. Архитектурные решения. | C75: =SUM(N75:N81) -> 0 | D75: =SUM(O75:O81) -> 0 | E75: =D75/8 -> 0 | G75: ГИП | N75: =M75*J75*K75*L75 -> 0 | O75: =J75*K75*L75 -> 0
G76: Нач. отдела | N76: =M76*J76*K76*L76 -> 0 | O76: =J76*K76*L76 -> 0
G77: Гл. специалист | N77: =M77*J77*K77*L77 -> 0 | O77: =J77*K77*L77 -> 0
G78: Рук. Группы | N78: =M78*J78*K78*L78 -> 0 | O78: =J78*K78*L78 -> 0
G79: Вед. инженер | N79: =M79*J79*K79*L79 -> 0 | O79: =J79*K79*L79 -> 0
G80: Старший инженер | N80: =M80*J80*K80*L80 -> 0 | O80: =J80*K80*L80 -> 0
G81: Инженер | N81: =M81*J81*K81*L81 -> 0 | O81: =J81*K81*L81 -> 0
A82: 2.4. | B82: Раздел 4. Конструктивные и объемно-планировочные решения. | C82: =SUM(N82:N88) -> 0 | D82: =SUM(O82:O88) -> 0 | E82: =D82/8 -> 0 | G82: ГИП | N82: =M82*J82*K82*L82 -> 0 | O82: =J82*K82*L82 -> 0
G83: Нач. отдела | N83: =M83*J83*K83*L83 -> 0 | O83: =J83*K83*L83 -> 0
G84: Гл. специалист | N84: =M84*J84*K84*L84 -> 0 | O84: =J84*K84*L84 -> 0
G85: Рук. Группы | N85: =M85*J85*K85*L85 -> 0 | O85: =J85*K85*L85 -> 0
G86: Вед. инженер | N86: =M86*J86*K86*L86 -> 0 | O86: =J86*K86*L86 -> 0
G87: Старший инженер | N87: =M87*J87*K87*L87 -> 0 | O87: =J87*K87*L87 -> 0
G88: Инженер | N88: =M88*J88*K88*L88 -> 0 | O88: =J88*K88*L88 -> 0
A89: 2.5. | B89: Раздел 5. Сведения об инженерном оборудовании, сетях инженерно-технического обеспечения, перечень инженерно-технических мероприятий, содержание технологических решений. | C89: =SUM(C90:C145) -> 0
A90: 2.5.1. | B90: подраздел 5.1 Система электроснабжения | C90: =SUM(N90:N96) -> 0 | D90: =SUM(O90:O96) -> 0 | E90: =D90/8 -> 0 | G90: ГИП | N90: =M90*J90*K90*L90 -> 0 | O90: =J90*K90*L90 -> 0
G91: Нач. отдела | N91: =M91*J91*K91*L91 -> 0 | O91: =J91*K91*L91 -> 0
G92: Гл. специалист | N92: =M92*J92*K92*L92 -> 0 | O92: =J92*K92*L92 -> 0
G93: Рук. Группы | N93: =M93*J93*K93*L93 -> 0 | O93: =J93*K93*L93 -> 0
G94: Вед. инженер | N94: =M94*J94*K94*L94 -> 0 | O94: =J94*K94*L94 -> 0
G95: Старший инженер | N95: =M95*J95*K95*L95 -> 0 | O95: =J95*K95*L95 -> 0
G96: Инженер | N96: =M96*J96*K96*L96 -> 0 | O96: =J96*K96*L96 -> 0
A97: 2.5.2. | B97: подраздел 5.2 Система водоснабжения | C97: =SUM(N97:N103) -> 0 | D97: =SUM(O97:O103) -> 0 | E97: =D97/8 -> 0 | G97: ГИП | N97: =M97*J97*K97*L97 -> 0 | O97: =J97*K97*L97 -> 0
G98: Нач. отдела | N98: =M98*J98*K98*L98 -> 0 | O98: =J98*K98*L98 -> 0
G99: Гл. специалист | N99: =M99*J99*K99*L99 -> 0 | O99: =J99*K99*L99 -> 0
G100: Рук. Группы | N100: =M100*J100*K100*L100 -> 0 | O100: =J100*K100*L100 -> 0
G101: Вед. инженер | N101: =M101*J101*K101*L101 -> 0 | O101: =J101*K101*L101 -> 0
G102: Старший инженер | N102: =M102*J102*K102*L102 -> 0 | O102: =J102*K102*L102 -> 0
...

Sheet ПД_BOQ тит2
C1: Форма для заполнения по тендерной процедуре №ТП.....
A2: Разработка проектной документации по объекту "Выполнение проектно-изыскательских работ по проектам "Техническое перевооружение сети водопроводов, трубопроводов пенного пожаротушения ООО "Томскнефтехим" »
C4: (заполняется участником)
A5: № п/п | B5: Наименование показателей | C5: Стоимость, руб. без НДС | D5: Трудозатраты чел.час | E5: Трудозатраты чел.дни | F5: Наименование подрядчика | G5: Обоснование расчета*
G7: Должность | H7: Оценка количества листов документации | J7: чел. | K7: Дней | L7: Часов | M7: Ст-ть чел. часа (руб.) без НДС | N7: Итого Ст-ть (руб.) без НДС | O7: Итого кол. Чел.час
H8: (текст.) ф.А4 | I8: (граф.) ф.А1
A9: Соответствие техническому заданию стадии ПД
A10: 1. | B10: Смета на строительство объектов капитального строительства | C10: =SUM(C11:C59) -> 0 | D10: =SUM(D11:D59) -> 0 | E10: =SUM(E11:E59) -> 0
A11: 1.1. | B11: Выполнить мониторинг рынка поставщиков и предоставить данные с учетом доставки до г. ……….: - по основным (ценообразующим) материалам - по вспомогательному оборудованию | C11: =SUM(N11:N17) -> 0 | D11: =SUM(O11:O17) -> 0 | E11: =D11/8 -> 0 | G11: ГИП | N11: =M11*J11*K11*L11 -> 0 | O11: =J11*K11*L11 -> 0
G12: Нач. отдела | N12: =M12*J12*K12*L12 -> 0 | O12: =J12*K12*L12 -> 0
G13: Гл. специалист | N13: =M13*J13*K13*L13 -> 0 | O13: =J13*K13*L13 -> 0
G14: Рук. Группы | N14: =M14*J14*K14*L14 -> 0 | O14: =J14*K14*L14 -> 0
G15: Вед. инженер | N15: =M15*J15*K15*L15 -> 0 | O15: =J15*K15*L15 -> 0
G16: Старший инженер | N16: =M16*J16*K16*L16 -> 0 | O16: =J16*K16*L16 -> 0
G17: Инженер | N17: =M17*J17*K17*L17 -> 0 | O17: =J17*K17*L17 -> 0
A18: 1.2. | B18: Предоставить ведомости объемов работ в формате BOQ | C18: =SUM(N18:N24) -> 0 | D18: =SUM(O18:O24) -> 0 | E18: =D18/8 -> 0 | G18: ГИП | N18: =M18*J18*K18*L18 -> 0 | O18: =J18*K18*L18 -> 0
G19: Нач. отдела | N19: =M19*J19*K19*L19 -> 0 | O19: =J19*K19*L19 -> 0
G20: Гл. специалист | N20: =M20*J20*K20*L20 -> 0 | O20: =J20*K20*L20 -> 0
G21: Рук. Группы | N21: =M21*J21*K21*L21 -> 0 | O21: =J21*K21*L21 -> 0
G22: Вед. инженер | N22: =M22*J22*K22*L22 -> 0 | O22: =J22*K22*L22 -> 0
G23: Старший инженер | N23: =M23*J23*K23*L23 -> 0 | O23: =J23*K23*L23 -> 0
G24: Инженер | N24: =M24*J24*K24*L24 -> 0 | O24: =J24*K24*L24 -> 0
A25: 1.3. | B25: Предоставить таблицу физических объемов сводную / по титульно | C25: =SUM(N25:N31) -> 0 | D25: =SUM(O25:O31) -> 0 | E25: =D25/8 -> 0 | G25: ГИП | N25: =M25*J25*K25*L25 -> 0 | O25: =J25*K25*L25 -> 0
G26: Нач. отдела | N26: =M26*J26*K26*L26 -> 0 | O26: =J26*K26*L26 -> 0
G27: Гл. специалист | N27: =M27*J27*K27*L27 -> 0 | O27: =J27*K27*L27 -> 0
G28: Рук. Группы | N28: =M28*J28*K28*L28 -> 0 | O28: =J28*K28*L28 -> 0
G29: Вед. инженер | N29: =M29*J29*K29*L29 -> 0 | O29: =J29*K29*L29 -> 0
G30: Старший инженер | N30: =M30*J30*K30*L30 -> 0 | O30: =J30*K30*L30 -> 0
G31: Инженер | N31: =M31*J31*K31*L31 -> 0 | O31: =J31*K31*L31 -> 0
A32: 1.4. | B32: Предоставить ведомости материалов с построчной стоимостью ресурсов (BOM) | C32: =SUM(N32:N38) -> 0 | D32: =SUM(O32:O38) -> 0 | E32: =D32/8 -> 0 | G32: ГИП | N32: =M32*J32*K32*L32 -> 0 | O32: =J32*K32*L32 -> 0
G33: Нач. отдела | N33: =M33*J33*K33*L33 -> 0 | O33: =J33*K33*L33 -> 0
G34: Гл. специалист | N34: =M34*J34*K34*L34 -> 0 | O34: =J34*K34*L34 -> 0
G35: Рук. Группы | N35: =M35*J35*K35*L35 -> 0 | O35: =J35*K35*L35 -> 0
G36: Вед. инженер | N36: =M36*J36*K36*L36 -> 0 | O36: =J36*K36*L36 -> 0
G37: Старший инженер | N37: =M37*J37*K37*L37 -> 0 | O37: =J37*K37*L37 -> 0
G38: Инженер | N38: =M38*J38*K38*L38 -> 0 | O38: =J38*K38*L38 -> 0
A39: 1.5. | B39: Предоставить ведомости оборудования с построчной стоимостью ресурсов (BOE) | C39: =SUM(N39:N45) -> 0 | D39: =SUM(O39:O45) -> 0 | E39: =D39/8 -> 0 | G39: ГИП | N39: =M39*J39*K39*L39 -> 0 | O39: =J39*K39*L39 -> 0
G40: Нач. отдела | N40: =M40*J40*K40*L40 -> 0 | O40: =J40*K40*L40 -> 0
G41: Гл. специалист | N41: =M41*J41*K41*L41 -> 0 | O41: =J41*K41*L41 -> 0
G42: Рук. Группы | N42: =M42*J42*K42*L42 -> 0 | O42: =J42*K42*L42 -> 0
G43: Вед. инженер | N43: =M43*J43*K43*L43 -> 0 | O43: =J43*K43*L43 -> 0
G44: Старший инженер | N44: =M44*J44*K44*L44 -> 0 | O44: =J44*K44*L44 -> 0
G45: Инженер | N45: =M45*J45*K45*L45 -> 0 | O45: =J45*K45*L45 -> 0
A46: 1.6. | B46: Расчитать количество стыков / дюйм диаметров по проекту (с приведением методики и пояснения расчетов) | C46: =SUM(N46:N52) -> 0 | D46: =SUM(O46:O52) -> 0 | E46: =D46/8 -> 0 | G46: ГИП | N46: =M46*J46*K46*L46 -> 0 | O46: =J46*K46*L46 -> 0
G47: Нач. отдела | N47: =M47*J47*K47*L47 -> 0 | O47: =J47*K47*L47 -> 0
G48: Гл. специалист | N48: =M48*J48*K48*L48 -> 0 | O48: =J48*K48*L48 -> 0
G49: Рук. Группы | N49: =M49*J49*K49*L49 -> 0 | O49: =J49*K49*L49 -> 0
G50: Вед. инженер | N50: =M50*J50*K50*L50 -> 0 | O50: =J50*K50*L50 -> 0
G51: Старший инженер | N51: =M51*J51*K51*L51 -> 0 | O51: =J51*K51*L51 -> 0
G52: Инженер | N52: =M52*J52*K52*L52 -> 0 | O52: =J52*K52*L52 -> 0
A53: 1.7. | B53: Предоставить пояснительную записку | C53: =SUM(N53:N59) -> 0 | D53: =SUM(O53:O59) -> 0 | E53: =D53/8 -> 0 | G53: ГИП | N53: =M53*J53*K53*L53 -> 0 | O53: =J53*K53*L53 -> 0
G54: Нач. отдела | N54: =M54*J54*K54*L54 -> 0 | O54: =J54*K54*L54 -> 0
G55: Гл. специалист | N55: =M55*J55*K55*L55 -> 0 | O55: =J55*K55*L55 -> 0
G56: Рук. Группы | N56: =M56*J56*K56*L56 -> 0 | O56: =J56*K56*L56 -> 0
G57: Вед. инженер | N57: =M57*J57*K57*L57 -> 0 | O57: =J57*K57*L57 -> 0
G58: Старший инженер | N58: =M58*J58*K58*L58 -> 0 | O58: =J58*K58*L58 -> 0
G59: Инженер | N59: =M59*J59*K59*L59 -> 0 | O59: =J59*K59*L59 -> 0
A60: 2. | B60: Проектная документация (все разделы) | C60: =C61+C68+C75+C82+C89+C146+C153+C160+C167+C174+C181+C188+C195+C202+C209+C216+C223+C237+C244+C251+C265 -> 0 | D60: =D61+D68+D75+D82+D89+D146+D153+D160+D167+D174+D181+D188+D195+D202+D209+D216+D223+D237+D244+D251+D265 -> 0 | E60: =E61+E68+E75+E82+E89+E146+E153+E160+E167+E174+E181+E188+E195+E202+E209+E216+E223+E237+E244+E251+E265 -> 0
A61: 2.1. | B61: Раздел 1. Пояснительная записка. | C61: =SUM(N61:N67) -> 0 | D61: =SUM(O61:O67) -> 0 | E61: =D61/8 -> 0 | G61: ГИП | N61: =M61*J61*K61*L61 -> 0 | O61: =J61*K61*L61 -> 0
G62: Нач. отдела | N62: =M62*J62*K62*L62 -> 0 | O62: =J62*K62*L62 -> 0
G63: Гл. специалист | N63: =M63*J63*K63*L63 -> 0 | O63: =J63*K63*L63 -> 0
G64: Рук. Группы | N64: =M64*J64*K64*L64 -> 0 | O64: =J64*K64*L64 -> 0
G65: Вед. инженер | N65: =M65*J65*K65*L65 -> 0 | O65: =J65*K65*L65 -> 0
G66: Старший инженер | N66: =M66*J66*K66*L66 -> 0 | O66: =J66*K66*L66 -> 0
G67: Инженер | N67: =M67*J67*K67*L67 -> 0 | O67: =J67*K67*L67 -> 0
A68: 2.2. | B68: Раздел 2. Схема планировочной организации земельного участка. | C68: =SUM(N68:N74) -> 0 | D68: =SUM(O68:O74) -> 0 | E68: =D68/8 -> 0 | G68: ГИП | N68: =M68*J68*K68*L68 -> 0 | O68: =J68*K68*L68 -> 0
G69: Нач. отдела | N69: =M69*J69*K69*L69 -> 0 | O69: =J69*K69*L69 -> 0
G70: Гл. специалист | N70: =M70*J70*K70*L70 -> 0 | O70: =J70*K70*L70 -> 0
G71: Рук. Группы | N71: =M71*J71*K71*L71 -> 0 | O71: =J71*K71*L71 -> 0
G72: Вед. инженер | N72: =M72*J72*K72*L72 -> 0 | O72: =J72*K72*L72 -> 0
G73: Старший инженер | N73: =M73*J73*K73*L73 -> 0 | O73: =J73*K73*L73 -> 0
G74: Инженер | N74: =M74*J74*K74*L74 -> 0 | O74: =J74*K74*L74 -> 0
A75: 2.3. | B75: Раздел 3. Архитектурные решения. | C75: =SUM(N75:N81) -> 0 | D75: =SUM(O75:O81) -> 0 | E75: =D75/8 -> 0 | G75: ГИП | N75: =M75*J75*K75*L75 -> 0 | O75: =J75*K75*L75 -> 0
G76: Нач. отдела | N76: =M76*J76*K76*L76 -> 0 | O76: =J76*K76*L76 -> 0
G77: Гл. специалист | N77: =M77*J77*K77*L77 -> 0 | O77: =J77*K77*L77 -> 0
G78: Рук. Группы | N78: =M78*J78*K78*L78 -> 0 | O78: =J78*K78*L78 -> 0
G79: Вед. инженер | N79: =M79*J79*K79*L79 -> 0 | O79: =J79*K79*L79 -> 0
G80: Старший инженер | N80: =M80*J80*K80*L80 -> 0 | O80: =J80*K80*L80 -> 0
G81: Инженер | N81: =M81*J81*K81*L81 -> 0 | O81: =J81*K81*L81 -> 0
A82: 2.4. | B82: Раздел 4. Конструктивные и объемно-планировочные решения. | C82: =SUM(N82:N88) -> 0 | D82: =SUM(O82:O88) -> 0 | E82: =D82/8 -> 0 | G82: ГИП | N82: =M82*J82*K82*L82 -> 0 | O82: =J82*K82*L82 -> 0
G83: Нач. отдела | N83: =M83*J83*K83*L83 -> 0 | O83: =J83*K83*L83 -> 0
G84: Гл. специалист | N84: =M84*J84*K84*L84 -> 0 | O84: =J84*K84*L84 -> 0
G85: Рук. Группы | N85: =M85*J85*K85*L85 -> 0 | O85: =J85*K85*L85 -> 0
G86: Вед. инженер | N86: =M86*J86*K86*L86 -> 0 | O86: =J86*K86*L86 -> 0
G87: Старший инженер | N87: =M87*J87*K87*L87 -> 0 | O87: =J87*K87*L87 -> 0
G88: Инженер | N88: =M88*J88*K88*L88 -> 0 | O88: =J88*K88*L88 -> 0
A89: 2.5. | B89: Раздел 5. Сведения об инженерном оборудовании, сетях инженерно-технического обеспечения, перечень инженерно-технических мероприятий, содержание технологических решений. | C89: =SUM(C90:C145) -> 0
A90: 2.5.1. | B90: подраздел 5.1 Система электроснабжения | C90: =SUM(N90:N96) -> 0 | D90: =SUM(O90:O96) -> 0 | E90: =D90/8 -> 0 | G90: ГИП | N90: =M90*J90*K90*L90 -> 0 | O90: =J90*K90*L90 -> 0
G91: Нач. отдела | N91: =M91*J91*K91*L91 -> 0 | O91: =J91*K91*L91 -> 0
G92: Гл. специалист | N92: =M92*J92*K92*L92 -> 0 | O92: =J92*K92*L92 -> 0
G93: Рук. Группы | N93: =M93*J93*K93*L93 -> 0 | O93: =J93*K93*L93 -> 0
G94: Вед. инженер | N94: =M94*J94*K94*L94 -> 0 | O94: =J94*K94*L94 -> 0
G95: Старший инженер | N95: =M95*J95*K95*L95 -> 0 | O95: =J95*K95*L95 -> 0
G96: Инженер | N96: =M96*J96*K96*L96 -> 0 | O96: =J96*K96*L96 -> 0
A97: 2.5.2. | B97: подраздел 5.2 Система водоснабжения | C97: =SUM(N97:N103) -> 0 | D97: =SUM(O97:O103) -> 0 | E97: =D97/8 -> 0 | G97: ГИП | N97: =M97*J97*K97*L97 -> 0 | O97: =J97*K97*L97 -> 0
G98: Нач. отдела | N98: =M98*J98*K98*L98 -> 0 | O98: =J98*K98*L98 -> 0
G99: Гл. специалист | N99: =M99*J99*K99*L99 -> 0 | O99: =J99*K99*L99 -> 0
G100: Рук. Группы | N100: =M100*J100*K100*L100 -> 0 | O100: =J100*K100*L100 -> 0
G101: Вед. инженер | N101: =M101*J101*K101*L101 -> 0 | O101: =J101*K101*L101 -> 0
G102: Старший инженер | N102: =M102*J102*K102*L102 -> 0 | O102: =J102*K102*L102 -> 0
...

Sheet РД_BOQ тит.1
C1: Форма для заполнения по тендерной процедуре №ТП.....
A2: Разработка рабочей документации по объекту "Выполнение проектно-изыскательских работ по проектам "Техническое перевооружение сети водопроводов, трубопроводов пенного пожаротушения ООО "Томскнефтехим" »
C4: (заполняется участником)
A5: № п/п | B5: Наименование показателей | C5: Стоимость, руб. без НДС | D5: Трудозатраты чел.час | E5: Трудозатраты чел.дни | F5: Наименование подрядчика | G5: Обоснование расчета*
G7: Должность | H7: Оценка количества листов документации | J7: чел. | K7: Дней | L7: Дней | M7: Часов | N7: Ст-ть чел. часа (руб.) без НДС | O7: Итого Ст-ть (руб.) без НДС | P7: Итого кол. чел.час
H8: (текст.) ф.А4 | I8: (граф.) ф.А1
A9: Соответствие техническому заданию стадии ПД
A10: 1. | B10: Смета на строительство объектов капитального строительства | C10: =SUM(C11:C73) -> 0 | D10: =SUM(D11:D73) -> 0 | E10: =SUM(E11:E73) -> 0
A11: 1.1. | B11: Выполнить мониторинг рынка поставщиков и предоставить данные с учетом доставки до г. ……….: - по основным (ценообразующим) материалам - по вспомогательному оборудованию | C11: =SUM(O11:O17) -> 0 | D11: =SUM(P11:P17) -> 0 | E11: =D11/8 -> 0 | G11: ГИП | O11: =N11*J11*K11*M11 -> 0 | P11: =J11*K11*M11 -> 0
G12: Нач. отдела | O12: =N12*J12*K12*M12 -> 0 | P12: =J12*K12*M12 -> 0
G13: Гл. специалист | O13: =N13*J13*K13*M13 -> 0 | P13: =J13*K13*M13 -> 0
G14: Рук. Группы | O14: =N14*J14*K14*M14 -> 0 | P14: =J14*K14*M14 -> 0
G15: Вед. инженер | O15: =N15*J15*K15*M15 -> 0 | P15: =J15*K15*M15 -> 0
G16: Старший инженер | O16: =N16*J16*K16*M16 -> 0 | P16: =J16*K16*M16 -> 0
G17: Инженер | O17: =N17*J17*K17*M17 -> 0 | P17: =J17*K17*M17 -> 0
A18: 1.2. | B18: Предоставить ведомости объемов работ в формате BOQ (Описание выполняемых работ/объемы) | C18: =SUM(O18:O24) -> 0 | D18: =SUM(P18:P24) -> 0 | E18: =D18/8 -> 0 | G18: ГИП | O18: =N18*J18*K18*M18 -> 0 | P18: =J18*K18*M18 -> 0
G19: Нач. отдела | O19: =N19*J19*K19*M19 -> 0 | P19: =J19*K19*M19 -> 0
G20: Гл. специалист | O20: =N20*J20*K20*M20 -> 0 | P20: =J20*K20*M20 -> 0
G21: Рук. Группы | O21: =N21*J21*K21*M21 -> 0 | P21: =J21*K21*M21 -> 0
G22: Вед. инженер | O22: =N22*J22*K22*M22 -> 0 | P22: =J22*K22*M22 -> 0
G23: Старший инженер | O23: =N23*J23*K23*M23 -> 0 | P23: =J23*K23*M23 -> 0
G24: Инженер | O24: =N24*J24*K24*M24 -> 0 | P24: =J24*K24*M24 -> 0
A25: 1.3. | B25: Предоставить таблицу физических объемов сводную / по титульно | C25: =SUM(O25:O31) -> 0 | D25: =SUM(P25:P31) -> 0 | E25: =D25/8 -> 0 | G25: ГИП | O25: =N25*J25*K25*M25 -> 0 | P25: =J25*K25*M25 -> 0
G26: Нач. отдела | O26: =N26*J26*K26*M26 -> 0 | P26: =J26*K26*M26 -> 0
G27: Гл. специалист | O27: =N27*J27*K27*M27 -> 0 | P27: =J27*K27*M27 -> 0
G28: Рук. Группы | O28: =N28*J28*K28*M28 -> 0 | P28: =J28*K28*M28 -> 0
G29: Вед. инженер | O29: =N29*J29*K29*M29 -> 0 | P29: =J29*K29*M29 -> 0
G30: Старший инженер | O30: =N30*J30*K30*M30 -> 0 | P30: =J30*K30*M30 -> 0
G31: Инженер | O31: =N31*J31*K31*M31 -> 0 | P31: =J31*K31*M31 -> 0
A32: 1.4. | B32: Предоставить ведомости материалов с построчной стоимостью ресурсов (BOM) | C32: =SUM(O32:O38) -> 0 | D32: =SUM(P32:P38) -> 0 | E32: =D32/8 -> 0 | G32: ГИП | O32: =N32*J32*K32*M32 -> 0 | P32: =J32*K32*M32 -> 0
G33: Нач. отдела | O33: =N33*J33*K33*M33 -> 0 | P33: =J33*K33*M33 -> 0
G34: Гл. специалист | O34: =N34*J34*K34*M34 -> 0 | P34: =J34*K34*M34 -> 0
G35: Рук. Группы | O35: =N35*J35*K35*M35 -> 0 | P35: =J35*K35*M35 -> 0
G36: Вед. инженер | O36: =N36*J36*K36*M36 -> 0 | P36: =J36*K36*M36 -> 0
G37: Старший инженер | O37: =N37*J37*K37*M37 -> 0 | P37: =J37*K37*M37 -> 0
G38: Инженер | O38: =N38*J38*K38*M38 -> 0 | P38: =J38*K38*M38 -> 0
A39: 1.5. | B39: Предоставить ведомости оборудования с построчной стоимостью ресурсов (BOE) | C39: =SUM(O39:O45) -> 0 | D39: =SUM(P39:P45) -> 0 | E39: =D39/8 -> 0 | G39: ГИП | O39: =N39*J39*K39*M39 -> 0 | P39: =J39*K39*M39 -> 0
G40: Нач. отдела | O40: =N40*J40*K40*M40 -> 0 | P40: =J40*K40*M40 -> 0
G41: Гл. специалист | O41: =N41*J41*K41*M41 -> 0 | P41: =J41*K41*M41 -> 0
G42: Рук. Группы | O42: =N42*J42*K42*M42 -> 0 | P42: =J42*K42*M42 -> 0
G43: Вед. инженер | O43: =N43*J43*K43*M43 -> 0 | P43: =J43*K43*M43 -> 0
G44: Старший инженер | O44: =N44*J44*K44*M44 -> 0 | P44: =J44*K44*M44 -> 0
G45: Инженер | O45: =N45*J45*K45*M45 -> 0 | P45: =J45*K45*M45 -> 0
A46: 1.6. | B46: Расчитать количество стыков / дюйм диаметров по проекту (с приведением методики и пояснения расчетов) | C46: =SUM(O46:O52) -> 0 | D46: =SUM(P46:P52) -> 0 | E46: =D46/8 -> 0 | G46: ГИП | O46: =N46*J46*K46*M46 -> 0 | P46: =J46*K46*M46 -> 0
G47: Нач. отдела | O47: =N47*J47*K47*M47 -> 0 | P47: =J47*K47*M47 -> 0
G48: Гл. специалист | O48: =N48*J48*K48*M48 -> 0 | P48: =J48*K48*M48 -> 0
G49: Рук. Группы | O49: =N49*J49*K49*M49 -> 0 | P49: =J49*K49*M49 -> 0
G50: Вед. инженер | O50: =N50*J50*K50*M50 -> 0 | P50: =J50*K50*M50 -> 0
G51: Старший инженер | O51: =N51*J51*K51*M51 -> 0 | P51: =J51*K51*M51 -> 0
G52: Инженер | O52: =N52*J52*K52*M52 -> 0 | P52: =J52*K52*M52 -> 0
A53: 1.7. | B53: Предоставить пусконаладочные работы (ПНР, ППНР) определить расчетом. | C53: =SUM(O53:O59) -> 0 | D53: =SUM(P53:P59) -> 0 | E53: =D53/8 -> 0 | G53: ГИП | O53: =N53*J53*K53*M53 -> 0 | P53: =J53*K53*M53 -> 0
G54: Нач. отдела | O54: =N54*J54*K54*M54 -> 0 | P54: =J54*K54*M54 -> 0
G55: Гл. специалист | O55: =N55*J55*K55*M55 -> 0 | P55: =J55*K55*M55 -> 0
G56: Рук. Группы | O56: =N56*J56*K56*M56 -> 0 | P56: =J56*K56*M56 -> 0
G57: Вед. инженер | O57: =N57*J57*K57*M57 -> 0 | P57: =J57*K57*M57 -> 0
G58: Старший инженер | O58: =N58*J58*K58*M58 -> 0 | P58: =J58*K58*M58 -> 0
G59: Инженер | O59: =N59*J59*K59*M59 -> 0 | P59: =J59*K59*M59 -> 0
A60: 1.8. | B60: Выполнить экспертизу сметной документации | C60: =SUM(O60:O66) -> 0 | D60: =SUM(P60:P66) -> 0 | E60: =D60/8 -> 0 | G60: ГИП | O60: =N60*J60*K60*M60 -> 0 | P60: =J60*K60*M60 -> 0
G61: Нач. отдела | O61: =N61*J61*K61*M61 -> 0 | P61: =J61*K61*M61 -> 0
G62: Гл. специалист | O62: =N62*J62*K62*M62 -> 0 | P62: =J62*K62*M62 -> 0
G63: Рук. Группы | O63: =N63*J63*K63*M63 -> 0 | P63: =J63*K63*M63 -> 0
G64: Вед. инженер | O64: =N64*J64*K64*M64 -> 0 | P64: =J64*K64*M64 -> 0
G65: Старший инженер | O65: =N65*J65*K65*M65 -> 0 | P65: =J65*K65*M65 -> 0
G66: Инженер | O66: =N66*J66*K66*M66 -> 0 | P66: =J66*K66*M66 -> 0
A67: 1.9. | B67: Предоставить пояснительную записку | C67: =SUM(O67:O73) -> 0 | D67: =SUM(P67:P73) -> 0 | E67: =D67/8 -> 0 | G67: ГИП | O67: =N67*J67*K67*M67 -> 0 | P67: =J67*K67*M67 -> 0
G68: Нач. отдела | O68: =N68*J68*K68*M68 -> 0 | P68: =J68*K68*M68 -> 0
G69: Гл. специалист | O69: =N69*J69*K69*M69 -> 0 | P69: =J69*K69*M69 -> 0
G70: Рук. Группы | O70: =N70*J70*K70*M70 -> 0 | P70: =J70*K70*M70 -> 0
G71: Вед. инженер | O71: =N71*J71*K71*M71 -> 0 | P71: =J71*K71*M71 -> 0
G72: Старший инженер | O72: =N72*J72*K72*M72 -> 0 | P72: =J72*K72*M72 -> 0
G73: Инженер | O73: =N73*J73*K73*M73 -> 0 | P73: =J73*K73*M73 -> 0
A74: 2. | B74: Пояснительная записка для ЭПБ на техническое перевооружение | C74: =SUM(C75:C102,C103) -> 0 | D74: =SUM(D75:D102,D103) -> 0 | E74: =SUM(E75:E102,E103) -> 0
A75: 2.1. | B75: Раздел 1. Пояснительная записка. | C75: =SUM(O75:O81) -> 0 | D75: =SUM(P75:P81) -> 0 | E75: =D75/8 -> 0 | G75: ГИП | O75: =N75*J75*K75*M75 -> 0 | P75: =J75*K75*M75 -> 0
G76: Нач. отдела | O76: =N76*J76*K76*M76 -> 0 | P76: =J76*K76*M76 -> 0
G77: Гл. специалист | O77: =N77*J77*K77*M77 -> 0 | P77: =J77*K77*M77 -> 0
G78: Рук. Группы | O78: =N78*J78*K78*M78 -> 0 | P78: =J78*K78*M78 -> 0
G79: Вед. инженер | O79: =N79*J79*K79*M79 -> 0 | P79: =J79*K79*M79 -> 0
G80: Старший инженер | O80: =N80*J80*K80*M80 -> 0 | P80: =J80*K80*M80 -> 0
G81: Инженер | O81: =N81*J81*K81*M81 -> 0 | P81: =J81*K81*M81 -> 0
A82: 2.2. | B82: Раздел 2. Схема планировочной организации земельного участка. | C82: =SUM(O82:O88) -> 0 | D82: =SUM(P82:P88) -> 0 | E82: =D82/8 -> 0 | G82: ГИП | O82: =N82*J82*K82*M82 -> 0 | P82: =J82*K82*M82 -> 0
G83: Нач. отдела | O83: =N83*J83*K83*M83 -> 0 | P83: =J83*K83*M83 -> 0
G84: Гл. специалист | O84: =N84*J84*K84*M84 -> 0 | P84: =J84*K84*M84 -> 0
G85: Рук. Группы | O85: =N85*J85*K85*M85 -> 0 | P85: =J85*K85*M85 -> 0
G86: Вед. инженер | O86: =N86*J86*K86*M86 -> 0 | P86: =J86*K86*M86 -> 0
G87: Старший инженер | O87: =N87*J87*K87*M87 -> 0 | P87: =J87*K87*M87 -> 0
G88: Инженер | O88: =N88*J88*K88*M88 -> 0 | P88: =J88*K88*M88 -> 0
A89: 2.3. | B89: Раздел 3. Архитектурные решения. | C89: =SUM(O89:O95) -> 0 | D89: =SUM(P89:P95) -> 0 | E89: =D89/8 -> 0 | G89: ГИП | O89: =N89*J89*K89*M89 -> 0 | P89: =J89*K89*M89 -> 0
G90: Нач. отдела | O90: =N90*J90*K90*M90 -> 0 | P90: =J90*K90*M90 -> 0
G91: Гл. специалист | O91: =N91*J91*K91*M91 -> 0 | P91: =J91*K91*M91 -> 0
G92: Рук. Группы | O92: =N92*J92*K92*M92 -> 0 | P92: =J92*K92*M92 -> 0
G93: Вед. инженер | O93: =N93*J93*K93*M93 -> 0 | P93: =J93*K93*M93 -> 0
G94: Старший инженер | O94: =N94*J94*K94*M94 -> 0 | P94: =J94*K94*M94 -> 0
G95: Инженер | O95: =N95*J95*K95*M95 -> 0 | P95: =J95*K95*M95 -> 0
A96: 2.4. | B96: Раздел 4. Конструктивные и объемно-планировочные решения. | C96: =SUM(O96:O102) -> 0 | D96: =SUM(P96:P102) -> 0 | E96: =D96/8 -> 0 | G96: ГИП | O96: =N96*J96*K96*M96 -> 0 | P96: =J96*K96*M96 -> 0
G97: Нач. отдела | O97: =N97*J97*K97*M97 -> 0 | P97: =J97*K97*M97 -> 0
G98: Гл. специалист | O98: =N98*J98*K98*M98 -> 0 | P98: =J98*K98*M98 -> 0
G99: Рук. Группы | O99: =N99*J99*K99*M99 -> 0 | P99: =J99*K99*M99 -> 0
G100: Вед. инженер | O100: =N100*J100*K100*M100 -> 0 | P100: =J100*K100*M100 -> 0
G101: Старший инженер | O101: =N101*J101*K101*M101 -> 0 | P101: =J101*K101*M101 -> 0
G102: Инженер | O102: =N102*J102*K102*M102 -> 0 | P102: =J102*K102*M102 -> 0
...

Sheet РД_BOQ тит.2
C1: Форма для заполнения по тендерной процедуре №ТП.....
A2: Разработка рабочей документации по объекту "Выполнение проектно-изыскательских работ по проектам "Техническое перевооружение сети водопроводов, трубопроводов пенного пожаротушения ООО "Томскнефтехим" »
C4: (заполняется участником)
A5: № п/п | B5: Наименование показателей | C5: Стоимость, руб. без НДС | D5: Трудозатраты чел.час | E5: Трудозатраты чел.дни | F5: Наименование подрядчика | G5: Обоснование расчета*
G7: Должность | H7: Оценка количества листов документации | J7: чел. | K7: Дней | L7: Часов | M7: Ст-ть чел. часа (руб.) без НДС | N7: Итого Ст-ть (руб.) без НДС | O7: Итого кол. чел.час
H8: (текст.) ф.А4 | I8: (граф.) ф.А1
A9: Соответствие техническому заданию стадии ПД
A10: 1. | B10: Смета на строительство объектов капитального строительства | C10: =SUM(C11:C73) -> 0 | D10: =SUM(D11:D73) -> 0 | E10: =SUM(E11:E73) -> 0
A11: 1.1. | B11: Выполнить мониторинг рынка поставщиков и предоставить данные с учетом доставки до г. ……….: - по основным (ценообразующим) материалам - по вспомогательному оборудованию | C11: =SUM(N11:N17) -> 0 | D11: =SUM(O11:O17) -> 0 | E11: =D11/8 -> 0 | G11: ГИП | N11: =M11*J11*K11*L11 -> 0 | O11: =J11*K11*L11 -> 0
G12: Нач. отдела | N12: =M12*J12*K12*L12 -> 0 | O12: =J12*K12*L12 -> 0
G13: Гл. специалист | N13: =M13*J13*K13*L13 -> 0 | O13: =J13*K13*L13 -> 0
G14: Рук. Группы | N14: =M14*J14*K14*L14 -> 0 | O14: =J14*K14*L14 -> 0
G15: Вед. инженер | N15: =M15*J15*K15*L15 -> 0 | O15: =J15*K15*L15 -> 0
G16: Старший инженер | N16: =M16*J16*K16*L16 -> 0 | O16: =J16*K16*L16 -> 0
G17: Инженер | N17: =M17*J17*K17*L17 -> 0 | O17: =J17*K17*L17 -> 0
A18: 1.2. | B18: Предоставить ведомости объемов работ в формате BOQ (Описание выполняемых работ/объемы) | C18: =SUM(N18:N24) -> 0 | D18: =SUM(O18:O24) -> 0 | E18: =D18/8 -> 0 | G18: ГИП | N18: =M18*J18*K18*L18 -> 0 | O18: =J18*K18*L18 -> 0
G19: Нач. отдела | N19: =M19*J19*K19*L19 -> 0 | O19: =J19*K19*L19 -> 0
G20: Гл. специалист | N20: =M20*J20*K20*L20 -> 0 | O20: =J20*K20*L20 -> 0
G21: Рук. Группы | N21: =M21*J21*K21*L21 -> 0 | O21: =J21*K21*L21 -> 0
G22: Вед. инженер | N22: =M22*J22*K22*L22 -> 0 | O22: =J22*K22*L22 -> 0
G23: Старший инженер | N23: =M23*J23*K23*L23 -> 0 | O23: =J23*K23*L23 -> 0
G24: Инженер | N24: =M24*J24*K24*L24 -> 0 | O24: =J24*K24*L24 -> 0
A25: 1.3. | B25: Предоставить таблицу физических объемов сводную / по титульно | C25: =SUM(N25:N31) -> 0 | D25: =SUM(O25:O31) -> 0 | E25: =D25/8 -> 0 | G25: ГИП | N25: =M25*J25*K25*L25 -> 0 | O25: =J25*K25*L25 -> 0
G26: Нач. отдела | N26: =M26*J26*K26*L26 -> 0 | O26: =J26*K26*L26 -> 0
G27: Гл. специалист | N27: =M27*J27*K27*L27 -> 0 | O27: =J27*K27*L27 -> 0
G28: Рук. Группы | N28: =M28*J28*K28*L28 -> 0 | O28: =J28*K28*L28 -> 0
G29: Вед. инженер | N29: =M29*J29*K29*L29 -> 0 | O29: =J29*K29*L29 -> 0
G30: Старший инженер | N30: =M30*J30*K30*L30 -> 0 | O30: =J30*K30*L30 -> 0
G31: Инженер | N31: =M31*J31*K31*L31 -> 0 | O31: =J31*K31*L31 -> 0
A32: 1.4. | B32: Предоставить ведомости материалов с построчной стоимостью ресурсов (BOM) | C32: =SUM(N32:N38) -> 0 | D32: =SUM(O32:O38) -> 0 | E32: =D32/8 -> 0 | G32: ГИП | N32: =M32*J32*K32*L32 -> 0 | O32: =J32*K32*L32 -> 0
G33: Нач. отдела | N33: =M33*J33*K33*L33 -> 0 | O33: =J33*K33*L33 -> 0
G34: Гл. специалист | N34: =M34*J34*K34*L34 -> 0 | O34: =J34*K34*L34 -> 0
G35: Рук. Группы | N35: =M35*J35*K35*L35 -> 0 | O35: =J35*K35*L35 -> 0
G36: Вед. инженер | N36: =M36*J36*K36*L36 -> 0 | O36: =J36*K36*L36 -> 0
G37: Старший инженер | N37: =M37*J37*K37*L37 -> 0 | O37: =J37*K37*L37 -> 0
G38: Инженер | N38: =M38*J38*K38*L38 -> 0 | O38: =J38*K38*L38 -> 0
A39: 1.5. | B39: Предоставить ведомости оборудования с построчной стоимостью ресурсов (BOE) | C39: =SUM(N39:N45) -> 0 | D39: =SUM(O39:O45) -> 0 | E39: =D39/8 -> 0 | G39: ГИП | N39: =M39*J39*K39*L39 -> 0 | O39: =J39*K39*L39 -> 0
G40: Нач. отдела | N40: =M40*J40*K40*L40 -> 0 | O40: =J40*K40*L40 -> 0
G41: Гл. специалист | N41: =M41*J41*K41*L41 -> 0 | O41: =J41*K41*L41 -> 0
G42: Рук. Группы | N42: =M42*J42*K42*L42 -> 0 | O42: =J42*K42*L42 -> 0
G43: Вед. инженер | N43: =M43*J43*K43*L43 -> 0 | O43: =J43*K43*L43 -> 0
G44: Старший инженер | N44: =M44*J44*K44*L44 -> 0 | O44: =J44*K44*L44 -> 0
G45: Инженер | N45: =M45*J45*K45*L45 -> 0 | O45: =J45*K45*L45 -> 0
A46: 1.6. | B46: Расчитать количество стыков / дюйм диаметров по проекту (с приведением методики и пояснения расчетов) | C46: =SUM(N46:N52) -> 0 | D46: =SUM(O46:O52) -> 0 | E46: =D46/8 -> 0 | G46: ГИП | N46: =M46*J46*K46*L46 -> 0 | O46: =J46*K46*L46 -> 0
G47: Нач. отдела | N47: =M47*J47*K47*L47 -> 0 | O47: =J47*K47*L47 -> 0
G48: Гл. специалист | N48: =M48*J48*K48*L48 -> 0 | O48: =J48*K48*L48 -> 0
G49: Рук. Группы | N49: =M49*J49*K49*L49 -> 0 | O49: =J49*K49*L49 -> 0
G50: Вед. инженер | N50: =M50*J50*K50*L50 -> 0 | O50: =J50*K50*L50 -> 0
G51: Старший инженер | N51: =M51*J51*K51*L51 -> 0 | O51: =J51*K51*L51 -> 0
G52: Инженер | N52: =M52*J52*K52*L52 -> 0 | O52: =J52*K52*L52 -> 0
A53: 1.7. | B53: Предоставить пусконаладочные работы (ПНР, ППНР) определить расчетом. | C53: =SUM(N53:N59) -> 0 | D53: =SUM(O53:O59) -> 0 | E53: =D53/8 -> 0 | G53: ГИП | N53: =M53*J53*K53*L53 -> 0 | O53: =J53*K53*L53 -> 0
G54: Нач. отдела | N54: =M54*J54*K54*L54 -> 0 | O54: =J54*K54*L54 -> 0
G55: Гл. специалист | N55: =M55*J55*K55*L55 -> 0 | O55: =J55*K55*L55 -> 0
G56: Рук. Группы | N56: =M56*J56*K56*L56 -> 0 | O56: =J56*K56*L56 -> 0
G57: Вед. инженер | N57: =M57*J57*K57*L57 -> 0 | O57: =J57*K57*L57 -> 0
G58: Старший инженер | N58: =M58*J58*K58*L58 -> 0 | O58: =J58*K58*L58 -> 0
G59: Инженер | N59: =M59*J59*K59*L59 -> 0 | O59: =J59*K59*L59 -> 0
A60: 1.8. | B60: Выполнить экспертизу сметной документации | C60: =SUM(N60:N66) -> 0 | D60: =SUM(O60:O66) -> 0 | E60: =D60/8 -> 0 | G60: ГИП | N60: =M60*J60*K60*L60 -> 0 | O60: =J60*K60*L60 -> 0
G61: Нач. отдела | N61: =M61*J61*K61*L61 -> 0 | O61: =J61*K61*L61 -> 0
G62: Гл. специалист | N62: =M62*J62*K62*L62 -> 0 | O62: =J62*K62*L62 -> 0
G63: Рук. Группы | N63: =M63*J63*K63*L63 -> 0 | O63: =J63*K63*L63 -> 0
G64: Вед. инженер | N64: =M64*J64*K64*L64 -> 0 | O64: =J64*K64*L64 -> 0
G65: Старший инженер | N65: =M65*J65*K65*L65 -> 0 | O65: =J65*K65*L65 -> 0
G66: Инженер | N66: =M66*J66*K66*L66 -> 0 | O66: =J66*K66*L66 -> 0
A67: 1.9. | B67: Предоставить пояснительную записку | C67: =SUM(N67:N73) -> 0 | D67: =SUM(O67:O73) -> 0 | E67: =D67/8 -> 0 | G67: ГИП | N67: =M67*J67*K67*L67 -> 0 | O67: =J67*K67*L67 -> 0
G68: Нач. отдела | N68: =M68*J68*K68*L68 -> 0 | O68: =J68*K68*L68 -> 0
G69: Гл. специалист | N69: =M69*J69*K69*L69 -> 0 | O69: =J69*K69*L69 -> 0
G70: Рук. Группы | N70: =M70*J70*K70*L70 -> 0 | O70: =J70*K70*L70 -> 0
G71: Вед. инженер | N71: =M71*J71*K71*L71 -> 0 | O71: =J71*K71*L71 -> 0
G72: Старший инженер | N72: =M72*J72*K72*L72 -> 0 | O72: =J72*K72*L72 -> 0
G73: Инженер | N73: =M73*J73*K73*L73 -> 0 | O73: =J73*K73*L73 -> 0
A74: 2. | B74: Пояснительная записка для ЭПБ на техническое перевооружение | C74: =SUM(C75:C102,C103) -> 0 | D74: =SUM(D75:D102,D103) -> 0 | E74: =SUM(E75:E102,E103) -> 0
A75: 2.1. | B75: Раздел 1. Пояснительная записка. | C75: =SUM(N75:N81) -> 0 | D75: =SUM(O75:O81) -> 0 | E75: =D75/8 -> 0 | G75: ГИП | N75: =M75*J75*K75*L75 -> 0 | O75: =J75*K75*L75 -> 0
G76: Нач. отдела | N76: =M76*J76*K76*L76 -> 0 | O76: =J76*K76*L76 -> 0
G77: Гл. специалист | N77: =M77*J77*K77*L77 -> 0 | O77: =J77*K77*L77 -> 0
G78: Рук. Группы | N78: =M78*J78*K78*L78 -> 0 | O78: =J78*K78*L78 -> 0
G79: Вед. инженер | N79: =M79*J79*K79*L79 -> 0 | O79: =J79*K79*L79 -> 0
G80: Старший инженер | N80: =M80*J80*K80*L80 -> 0 | O80: =J80*K80*L80 -> 0
G81: Инженер | N81: =M81*J81*K81*L81 -> 0 | O81: =J81*K81*L81 -> 0
A82: 2.2. | B82: Раздел 2. Схема планировочной организации земельного участка. | C82: =SUM(N82:N88) -> 0 | D82: =SUM(O82:O88) -> 0 | E82: =D82/8 -> 0 | G82: ГИП | N82: =M82*J82*K82*L82 -> 0 | O82: =J82*K82*L82 -> 0
G83: Нач. отдела | N83: =M83*J83*K83*L83 -> 0 | O83: =J83*K83*L83 -> 0
G84: Гл. специалист | N84: =M84*J84*K84*L84 -> 0 | O84: =J84*K84*L84 -> 0
G85: Рук. Группы | N85: =M85*J85*K85*L85 -> 0 | O85: =J85*K85*L85 -> 0
G86: Вед. инженер | N86: =M86*J86*K86*L86 -> 0 | O86: =J86*K86*L86 -> 0
G87: Старший инженер | N87: =M87*J87*K87*L87 -> 0 | O87: =J87*K87*L87 -> 0
G88: Инженер | N88: =M88*J88*K88*L88 -> 0 | O88: =J88*K88*L88 -> 0
A89: 2.3. | B89: Раздел 3. Архитектурные решения. | C89: =SUM(N89:N95) -> 0 | D89: =SUM(O89:O95) -> 0 | E89: =D89/8 -> 0 | G89: ГИП | N89: =M89*J89*K89*L89 -> 0 | O89: =J89*K89*L89 -> 0
G90: Нач. отдела | N90: =M90*J90*K90*L90 -> 0 | O90: =J90*K90*L90 -> 0
G91: Гл. специалист | N91: =M91*J91*K91*L91 -> 0 | O91: =J91*K91*L91 -> 0
G92: Рук. Группы | N92: =M92*J92*K92*L92 -> 0 | O92: =J92*K92*L92 -> 0
G93: Вед. инженер | N93: =M93*J93*K93*L93 -> 0 | O93: =J93*K93*L93 -> 0
G94: Старший инженер | N94: =M94*J94*K94*L94 -> 0 | O94: =J94*K94*L94 -> 0
G95: Инженер | N95: =M95*J95*K95*L95 -> 0 | O95: =J95*K95*L95 -> 0
A96: 2.4. | B96: Раздел 4. Конструктивные и объемно-планировочные решения. | C96: =SUM(N96:N102) -> 0 | D96: =SUM(O96:O102) -> 0 | E96: =D96/8 -> 0 | G96: ГИП | N96: =M96*J96*K96*L96 -> 0 | O96: =J96*K96*L96 -> 0
G97: Нач. отдела | N97: =M97*J97*K97*L97 -> 0 | O97: =J97*K97*L97 -> 0
G98: Гл. специалист | N98: =M98*J98*K98*L98 -> 0 | O98: =J98*K98*L98 -> 0
G99: Рук. Группы | N99: =M99*J99*K99*L99 -> 0 | O99: =J99*K99*L99 -> 0
G100: Вед. инженер | N100: =M100*J100*K100*L100 -> 0 | O100: =J100*K100*L100 -> 0
G101: Старший инженер | N101: =M101*J101*K101*L101 -> 0 | O101: =J101*K101*L101 -> 0
G102: Инженер | N102: =M102*J102*K102*L102 -> 0 | O102: =J102*K102*L102 -> 0
...

Sheet РД_Ресурс.метод тит.1
C1: Форма для заполнения по тендерной процедуре №ТП.....
A2: Разработка рабочей документации по объекту "Выполнение проектно-изыскательских работ по проектам "Техническое перевооружение сети водопроводов, трубопроводов пенного пожаротушения ООО "Томскнефтехим" »
C4: (заполняется участником)
A5: № п/п | B5: Наименование показателей | C5: Стоимость, руб. без НДС | D5: Трудозатраты чел.час | E5: Трудозатраты чел.дни | F5: Наименование подрядчика | G5: Обоснование расчета*
G7: Должность | H7: Оценка количества листов документации | J7: чел. | K7: Дней | L7: Часов | M7: Ст-ть чел. часа (руб.) без НДС | N7: Итого Ст-ть (руб.) без НДС | O7: Итого кол. чел.час
H8: (текст.) ф.А4 | I8: (граф.) ф.А1
A9: Соответствие техническому заданию стадии ПД
A10: 1. | B10: Смета на строительство объектов капитального строительства | C10: =SUM(C11:C73) -> 0 | D10: =SUM(D11:D73) -> 0 | E10: =SUM(E11:E73) -> 0
A11: 1.1. | B11: Выполнить мониторинг рынка поставщиков и предоставить данные с учетом доставки до г. ……….: - по основным (ценообразующим) материалам - по вспомогательному оборудованию | C11: =SUM(N11:N17) -> 0 | D11: =SUM(O11:O17) -> 0 | E11: =D11/8 -> 0 | G11: ГИП | N11: =M11*J11*K11*L11 -> 0 | O11: =J11*K11*L11 -> 0
G12: Нач. отдела | N12: =M12*J12*K12*L12 -> 0 | O12: =J12*K12*L12 -> 0
G13: Гл. специалист | N13: =M13*J13*K13*L13 -> 0 | O13: =J13*K13*L13 -> 0
G14: Рук. Группы | N14: =M14*J14*K14*L14 -> 0 | O14: =J14*K14*L14 -> 0
G15: Вед. инженер | N15: =M15*J15*K15*L15 -> 0 | O15: =J15*K15*L15 -> 0
G16: Старший инженер | N16: =M16*J16*K16*L16 -> 0 | O16: =J16*K16*L16 -> 0
G17: Инженер | N17: =M17*J17*K17*L17 -> 0 | O17: =J17*K17*L17 -> 0
A18: 1.2. | B18: Предоставить таблицу физических объемов сводная / по титульно | C18: =SUM(N18:N24) -> 0 | D18: =SUM(O18:O24) -> 0 | E18: =D18/8 -> 0 | G18: ГИП | N18: =M18*J18*K18*L18 -> 0 | O18: =J18*K18*L18 -> 0
G19: Нач. отдела | N19: =M19*J19*K19*L19 -> 0 | O19: =J19*K19*L19 -> 0
G20: Гл. специалист | N20: =M20*J20*K20*L20 -> 0 | O20: =J20*K20*L20 -> 0
G21: Рук. Группы | N21: =M21*J21*K21*L21 -> 0 | O21: =J21*K21*L21 -> 0
G22: Вед. инженер | N22: =M22*J22*K22*L22 -> 0 | O22: =J22*K22*L22 -> 0
G23: Старший инженер | N23: =M23*J23*K23*L23 -> 0 | O23: =J23*K23*L23 -> 0
G24: Инженер | N24: =M24*J24*K24*L24 -> 0 | O24: =J24*K24*L24 -> 0
A25: 1.3. | B25: Предоставить ведомости материалов с построчной стоимостью ресурсов | C25: =SUM(N25:N31) -> 0 | D25: =SUM(O25:O31) -> 0 | E25: =D25/8 -> 0 | G25: ГИП | N25: =M25*J25*K25*L25 -> 0 | O25: =J25*K25*L25 -> 0
G26: Нач. отдела | N26: =M26*J26*K26*L26 -> 0 | O26: =J26*K26*L26 -> 0
G27: Гл. специалист | N27: =M27*J27*K27*L27 -> 0 | O27: =J27*K27*L27 -> 0
G28: Рук. Группы | N28: =M28*J28*K28*L28 -> 0 | O28: =J28*K28*L28 -> 0
G29: Вед. инженер | N29: =M29*J29*K29*L29 -> 0 | O29: =J29*K29*L29 -> 0
G30: Старший инженер | N30: =M30*J30*K30*L30 -> 0 | O30: =J30*K30*L30 -> 0
G31: Инженер | N31: =M31*J31*K31*L31 -> 0 | O31: =J31*K31*L31 -> 0
A32: 1.4. | B32: Предоставить ведомости оборудования с построчной стоимостью ресурсов | C32: =SUM(N32:N38) -> 0 | D32: =SUM(O32:O38) -> 0 | E32: =D32/8 -> 0 | G32: ГИП | N32: =M32*J32*K32*L32 -> 0 | O32: =J32*K32*L32 -> 0
G33: Нач. отдела | N33: =M33*J33*K33*L33 -> 0 | O33: =J33*K33*L33 -> 0
G34: Гл. специалист | N34: =M34*J34*K34*L34 -> 0 | O34: =J34*K34*L34 -> 0
G35: Рук. Группы | N35: =M35*J35*K35*L35 -> 0 | O35: =J35*K35*L35 -> 0
G36: Вед. инженер | N36: =M36*J36*K36*L36 -> 0 | O36: =J36*K36*L36 -> 0
G37: Старший инженер | N37: =M37*J37*K37*L37 -> 0 | O37: =J37*K37*L37 -> 0
G38: Инженер | N38: =M38*J38*K38*L38 -> 0 | O38: =J38*K38*L38 -> 0
A39: 1.5. | B39: Расчитать количество стыков / дюйм диаметров по проекту | C39: =SUM(N39:N45) -> 0 | D39: =SUM(O39:O45) -> 0 | E39: =D39/8 -> 0 | G39: ГИП | N39: =M39*J39*K39*L39 -> 0 | O39: =J39*K39*L39 -> 0
G40: Нач. отдела | N40: =M40*J40*K40*L40 -> 0 | O40: =J40*K40*L40 -> 0
G41: Гл. специалист | N41: =M41*J41*K41*L41 -> 0 | O41: =J41*K41*L41 -> 0
G42: Рук. Группы | N42: =M42*J42*K42*L42 -> 0 | O42: =J42*K42*L42 -> 0
G43: Вед. инженер | N43: =M43*J43*K43*L43 -> 0 | O43: =J43*K43*L43 -> 0
G44: Старший инженер | N44: =M44*J44*K44*L44 -> 0 | O44: =J44*K44*L44 -> 0
G45: Инженер | N45: =M45*J45*K45*L45 -> 0 | O45: =J45*K45*L45 -> 0
A46: 1.6. | B46: Разработать сметную документацию ресурсным методом (ГЭСН-2001 в ред.2020 (с изм./доп) | C46: =SUM(N46:N52) -> 0 | D46: =SUM(O46:O52) -> 0 | E46: =D46/8 -> 0 | G46: ГИП | N46: =M46*J46*K46*L46 -> 0 | O46: =J46*K46*L46 -> 0
G47: Нач. отдела | N47: =M47*J47*K47*L47 -> 0 | O47: =J47*K47*L47 -> 0
G48: Гл. специалист | N48: =M48*J48*K48*L48 -> 0 | O48: =J48*K48*L48 -> 0
G49: Рук. Группы | N49: =M49*J49*K49*L49 -> 0 | O49: =J49*K49*L49 -> 0
G50: Вед. инженер | N50: =M50*J50*K50*L50 -> 0 | O50: =J50*K50*L50 -> 0
G51: Старший инженер | N51: =M51*J51*K51*L51 -> 0 | O51: =J51*K51*L51 -> 0
G52: Инженер | N52: =M52*J52*K52*L52 -> 0 | O52: =J52*K52*L52 -> 0
A53: 1.7. | B53: Предоставить BOQ (Описание выполняемых работ/объемы). | C53: =SUM(N53:N59) -> 0 | D53: =SUM(O53:O59) -> 0 | E53: =D53/8 -> 0 | G53: ГИП | N53: =M53*J53*K53*L53 -> 0 | O53: =J53*K53*L53 -> 0
G54: Нач. отдела | N54: =M54*J54*K54*L54 -> 0 | O54: =J54*K54*L54 -> 0
G55: Гл. специалист | N55: =M55*J55*K55*L55 -> 0 | O55: =J55*K55*L55 -> 0
G56: Рук. Группы | N56: =M56*J56*K56*L56 -> 0 | O56: =J56*K56*L56 -> 0
G57: Вед. инженер | N57: =M57*J57*K57*L57 -> 0 | O57: =J57*K57*L57 -> 0
G58: Старший инженер | N58: =M58*J58*K58*L58 -> 0 | O58: =J58*K58*L58 -> 0
G59: Инженер | N59: =M59*J59*K59*L59 -> 0 | O59: =J59*K59*L59 -> 0
A60: 1.8. | B60: Пусконаладочные работы (ПНР, ППНР) определить расчетом. | C60: =SUM(N60:N66) -> 0 | D60: =SUM(O60:O66) -> 0 | E60: =D60/8 -> 0 | G60: ГИП | N60: =M60*J60*K60*L60 -> 0 | O60: =J60*K60*L60 -> 0
G61: Нач. отдела | N61: =M61*J61*K61*L61 -> 0 | O61: =J61*K61*L61 -> 0
G62: Гл. специалист | N62: =M62*J62*K62*L62 -> 0 | O62: =J62*K62*L62 -> 0
G63: Рук. Группы | N63: =M63*J63*K63*L63 -> 0 | O63: =J63*K63*L63 -> 0
G64: Вед. инженер | N64: =M64*J64*K64*L64 -> 0 | O64: =J64*K64*L64 -> 0
G65: Старший инженер | N65: =M65*J65*K65*L65 -> 0 | O65: =J65*K65*L65 -> 0
G66: Инженер | N66: =M66*J66*K66*L66 -> 0 | O66: =J66*K66*L66 -> 0
A67: 1.9. | B67: Выполнить экспертизу сметной документации | C67: =SUM(N67:N73) -> 0 | D67: =SUM(O67:O73) -> 0 | E67: =D67/8 -> 0 | G67: ГИП | N67: =M67*J67*K67*L67 -> 0 | O67: =J67*K67*L67 -> 0
G68: Нач. отдела | N68: =M68*J68*K68*L68 -> 0 | O68: =J68*K68*L68 -> 0
G69: Гл. специалист | N69: =M69*J69*K69*L69 -> 0 | O69: =J69*K69*L69 -> 0
G70: Рук. Группы | N70: =M70*J70*K70*L70 -> 0 | O70: =J70*K70*L70 -> 0
G71: Вед. инженер | N71: =M71*J71*K71*L71 -> 0 | O71: =J71*K71*L71 -> 0
G72: Старший инженер | N72: =M72*J72*K72*L72 -> 0 | O72: =J72*K72*L72 -> 0
G73: Инженер | N73: =M73*J73*K73*L73 -> 0 | O73: =J73*K73*L73 -> 0
A74: 2. | B74: Пояснительная записка для ЭПБ на техническое перевооружение | C74: =SUM(C75:C102,C103) -> 0 | D74: =SUM(D75:D102,D103) -> 0 | E74: =SUM(E75:E102,E103) -> 0
A75: 2.1. | B75: Раздел 1. Пояснительная записка. | C75: =SUM(N75:N81) -> 0 | D75: =SUM(O75:O81) -> 0 | E75: =D75/8 -> 0 | G75: ГИП | N75: =M75*J75*K75*L75 -> 0 | O75: =J75*K75*L75 -> 0
G76: Нач. отдела | N76: =M76*J76*K76*L76 -> 0 | O76: =J76*K76*L76 -> 0
G77: Гл. специалист | N77: =M77*J77*K77*L77 -> 0 | O77: =J77*K77*L77 -> 0
G78: Рук. Группы | N78: =M78*J78*K78*L78 -> 0 | O78: =J78*K78*L78 -> 0
G79: Вед. инженер | N79: =M79*J79*K79*L79 -> 0 | O79: =J79*K79*L79 -> 0
G80: Старший инженер | N80: =M80*J80*K80*L80 -> 0 | O80: =J80*K80*L80 -> 0
G81: Инженер | N81: =M81*J81*K81*L81 -> 0 | O81: =J81*K81*L81 -> 0
A82: 2.2. | B82: Раздел 2. Схема планировочной организации земельного участка. | C82: =SUM(N82:N88) -> 0 | D82: =SUM(O82:O88) -> 0 | E82: =D82/8 -> 0 | G82: ГИП | N82: =M82*J82*K82*L82 -> 0 | O82: =J82*K82*L82 -> 0
G83: Нач. отдела | N83: =M83*J83*K83*L83 -> 0 | O83: =J83*K83*L83 -> 0
G84: Гл. специалист | N84: =M84*J84*K84*L84 -> 0 | O84: =J84*K84*L84 -> 0
G85: Рук. Группы | N85: =M85*J85*K85*L85 -> 0 | O85: =J85*K85*L85 -> 0
G86: Вед. инженер | N86: =M86*J86*K86*L86 -> 0 | O86: =J86*K86*L86 -> 0
G87: Старший инженер | N87: =M87*J87*K87*L87 -> 0 | O87: =J87*K87*L87 -> 0
G88: Инженер | N88: =M88*J88*K88*L88 -> 0 | O88: =J88*K88*L88 -> 0
A89: 2.3. | B89: Раздел 3. Архитектурные решения. | C89: =SUM(N89:N95) -> 0 | D89: =SUM(O89:O95) -> 0 | E89: =D89/8 -> 0 | G89: ГИП | N89: =M89*J89*K89*L89 -> 0 | O89: =J89*K89*L89 -> 0
G90: Нач. отдела | N90: =M90*J90*K90*L90 -> 0 | O90: =J90*K90*L90 -> 0
G91: Гл. специалист | N91: =M91*J91*K91*L91 -> 0 | O91: =J91*K91*L91 -> 0
G92: Рук. Группы | N92: =M92*J92*K92*L92 -> 0 | O92: =J92*K92*L92 -> 0
G93: Вед. инженер | N93: =M93*J93*K93*L93 -> 0 | O93: =J93*K93*L93 -> 0
G94: Старший инженер | N94: =M94*J94*K94*L94 -> 0 | O94: =J94*K94*L94 -> 0
G95: Инженер | N95: =M95*J95*K95*L95 -> 0 | O95: =J95*K95*L95 -> 0
A96: 2.4. | B96: Раздел 4. Конструктивные и объемно-планировочные решения. | C96: =SUM(N96:N102) -> 0 | D96: =SUM(O96:O102) -> 0 | E96: =D96/8 -> 0 | G96: ГИП | N96: =M96*J96*K96*L96 -> 0 | O96: =J96*K96*L96 -> 0
G97: Нач. отдела | N97: =M97*J97*K97*L97 -> 0 | O97: =J97*K97*L97 -> 0
G98: Гл. специалист | N98: =M98*J98*K98*L98 -> 0 | O98: =J98*K98*L98 -> 0
G99: Рук. Группы | N99: =M99*J99*K99*L99 -> 0 | O99: =J99*K99*L99 -> 0
G100: Вед. инженер | N100: =M100*J100*K100*L100 -> 0 | O100: =J100*K100*L100 -> 0
G101: Старший инженер | N101: =M101*J101*K101*L101 -> 0 | O101: =J101*K101*L101 -> 0
G102: Инженер | N102: =M102*J102*K102*L102 -> 0 | O102: =J102*K102*L102 -> 0
...

Sheet Лист2

Sheet Лист3
