Workbook
Name \: Лист1!#REF!
Name \: Лист1!#REF!
Name \: Лист1!#REF!
Name \: [1]Лист1!#REF!
Name \: [2]Лист1!#REF!
Name \: Лист1!#REF!
Name KD: #REF!
Name KD: #REF!
Name KD: #REF!
Name KD: #REF!
Name KD: #REF!
Name KD: #REF!
Name KD: #REF!
Name KD: #REF!
Name KD: #REF!
Name Print_Area: '4.1 КД'!$A$1:$H$40
Name АВТОМОБИЛЬНЫЕ_ДОРОГИ: Лист1!$J$3:$J$4
Name город: #REF!
Name город: #REF!
Name город: #REF!
Name город: #REF!
Name город: #REF!
Name город: #REF!
Name город: #REF!
Name город: #REF!
Name город: #REF!
Name ЖЕЛЕЗНЫЕ_ДОРОГИ: Лист1!$AI$3:$AI$11
Name ЗАЩИТНЫЕ_СООРУЖЕНИЯ_ГРАЖДАНСКОЙ_ОБОРОНЫ: Лист1!$AO$3
Name ИСКУСТВЕННЫЕ: Лист1!$A$3:$A$12
Name ИСКУСТВЕННЫЕ_СООРУЖЕНИЯ: Лист1!$A$3:$A$12
Name ИССКУСТВЕННЫЕ: Лист1!$A$3:$A$12
Name ИССКУСТВЕННЫЕ_СООРУЖЕНИЯ_МОСТЫ_ПЕРЕХОДЫ_ПУТЕПРОВОДЫ: Лист1!$A$3:$A$12
Name КОММУНАЛЬНЫЕ_ИНЖЕНЕРНЫЕ_СЕТИ_И_СООРУЖЕНИЯ: Лист1!$S$3:$S$8
Name Конф: #REF!
Name Конф: #REF!
Name Конф: #REF!
Name Конф: #REF!
Name Конф: #REF!
Name Конф: #REF!
Name Конф: #REF!
Name Конф: #REF!
Name Конф: #REF!
Name конфл: #REF!
Name конфл: #REF!
Name конфл: #REF!
Name конфл: #REF!
Name конфл: #REF!
Name конфл: #REF!
Name конфл: #REF!
Name конфл: #REF!
Name конфл: #REF!
Name конфл2: #REF!
Name конфл2: #REF!
Name конфл2: #REF!
Name конфл2: #REF!
Name конфл2: #REF!
Name конфл2: #REF!
Name конфл2: #REF!
Name конфл2: #REF!
Name конфл2: #REF!

Sheet Форма сводной сметы 
B1: 1 | D1: 1 | G1: 1 | H1: 1 | I1: 1 | J1: 1
J2: Форма 1пс
B4: Приложение к
D5: (договору, дополнительному соглашению)
B7: СМЕТА на проектные и изыскательские работы
B9: Наименование строительства и стадии проектирования | F9: «Модернизация существующей инфраструктуры транспортировки и налива фракции С5, с целью обеспечения налива дополнительного объема фракции С5, в количестве 6 000 т/мес.» | N9: =F9 -> «Модернизация существующей инфраструктуры транспортировки и налива фракции С5, с целью обеспечения налива дополнительного объема фракции С5, в количестве 6 000 т/мес.»
B12: Наименование проектной организации - генерального проектировщика | F12: ОАО "СибНефтеТрансПроект"
B15: Наименование организации заказчика | F15: ПАО «Нижнекамскнефтехим»
B18: N п.п. | C18: Перечень выполняемых работ | E18: Характеристика проектируемого объекта | F18: Трудозатраты определенные участников, ч.ч. | G18: Ссылка на N смет по формам N 2п и 3п | H18: Стоимость работ
H19: изыскательских | I19: проектных | J19: всего, без НДС, руб. | K19: всего, с НДС, руб.
B20: =IF($B$1=1,SUBTOTAL(2,$B$1:B1),"") -> 1 | C20: =IF($B$1=1,SUBTOTAL(2,$B$1:D1),"") -> 2 | E20: =IF($B$1=1,SUBTOTAL(2,$B$1:E1),"") -> 2 | G20: =IF($B$1=1,SUBTOTAL(2,$B$1:G1),"") -> 3 | H20: =IF($B$1=1,SUBTOTAL(2,$B$1:H1),"") -> 4 | I20: =IF($B$1=1,SUBTOTAL(2,$B$1:I1),"") -> 5 | J20: =IF($B$1=1,SUBTOTAL(2,$B$1:J1),"") -> 6 | K20: 7
B21: 1 | C21: Сбор исходных данных и выполнение работ по обследованию существующих зданий и сооружений | G21: Сводная смета №1 | H21: 0 | I21: =СВОД!F18 -> 9272148.2 | J21: =SUM(H21:I21) -> 9272148.2 | K21: =J21*1.2 -> 11126578 | L21: 1.1 По калькуляции затрат по форме 3П 1.2 СБЦП 81-02-25-2001 «Справочник базовых цен на обмерные работы и обследования зданий и сооружений» (Приказ Минстроя России от 25.04.2016 № 270/пр).
B22: 2 | C22: Выполнение инженерных изысканий | G22: Сводная смета №1 | H22: =СВОД!F13 -> 20111633 | I22: 0 | J22: =SUM(H22:I22) -> 20111633 | K22: =J22*1.2 -> 24133960 | L22: СБЦ-ИИ-2006 "Инженерно-геодезические изыскания при строительстве и эксплуатации зданий и сооружений" (Рекомендован Росстроем Министерства регионального развития РФ письмом от 24.05.2006 г. N СК-1976/02). СБЦ-ИИ-1998 СБЦ на инженерно-геологические и инженерно-экологические изыскания для строительства (Одобрен письмом Госстроя от 22 июня 1998 г. N 9-4/84). СБЦ-ИИ-2000 "Инженерно-гидрографические работы. Инженерно-гидрометеорологические изыскания на реках" (Утвержден письмом Госстроя России от 26.09.2000 N 5-11/91). Приказ № 317, от 02.07.2010 г. Министерства регионального развития Российской Федерации. об утверждении методики определения стоимости работ по очистке местности от взрывоопасных предметов в сфере градостроительной деятельности. СЦНПР-91 Сборник цен на научно-проектные работы по памятникам истории и культуры.
B23: 3 | C23: Землеустроительная (градостроительная) документация (ППТ, ПМТ, градплан) | J23: =SUM(H23:I23) -> 0 | K23: =J23*1.2 -> 0 | L23: Сборник цен на проектные работы в строительстве "Территориальное планирование и планировка территории", утвержденный Приказом Министерства регионального развития Российской Федерации от 28.05.2010 г.№ 260. Сборник цен и общественно необходимых затрат труда (ОНЗТ) на изготовление проектной и изыскательской продукции землеустройства, земельного кадастра и мониторинга земель, утвержденный Приказом Роскомзема от 28.12.1995 г. № 70.
B24: 4 | C24: Корректировка проектной документации, в т.ч.: | J24: =SUM(H24:I24) -> 0 | K24: =J24*1.2 -> 0
B25: 4.1 | C25: - | D25: Формирование пакета исходно-разрешительной документации | J25: =SUM(H25:I25) -> 0 | K25: =J25*1.2 -> 0 | L25: По калькуляции затрат по форме 3П
B26: 4.2 | C26: - | D26: Подготовка проектов ТУ на подключение к инженерным сетям и на пересечение с инженерными сетями | J26: =SUM(H26:I26) -> 0 | K26: =J26*1.2 -> 0 | L26: По калькуляции затрат по форме 3П
B27: 4.3 | C27: - | D27: Разделы ПД по Постановлениюот 16.02.2008 №87 | J27: =SUM(H27:I27) -> 0 | K27: =J27*1.2 -> 0 | L27: Справочники базовых цен приведенные в «Федеральном реестре сметных нормативов, подлежащих применению при определении сметной стоимости объектов капитального строительства» размещенного на официальном сайте Минстроя России (www.minstroyrf.ru) методические указания по применению справочников базовых цен на проектные работы в строительстве, 2009 (Приказ Министерства регионального развития РФ от 29 декабря 2009 г. №620); разъяснения ОАО «ЦИНТРИНВЕСТпроект»; коэффициенты изменения сметной стоимости проектных работ публикуемые ежеквартально Минстроем РФ, за исключением случаев особо оговоренных в конкурсной документации | N27: ТЧ ПД
B28: 4.4 | C28: - | D28: Разработка КД, ОЛ и ИТТ на основное и вспомогательное энергетическое оборудование | J28: =SUM(H28:I28) -> 0 | K28: =J28*1.2 -> 0 | L28: СБЦ приведенные в «Федеральном реестре сметных нормативов, подлежащих применению при определении сметной стоимости объектов капитального строительства» размещенного на официальном сайте Минстроя России (www.minstroyrf.ru)
B29: 4.5 | C29: - | D29: Разработка ОВОС, проведение общественных слушаний, разработка ПМООС | J29: =SUM(H29:I29) -> 0 | K29: =J29*1.2 -> 0 | L29: 1. Ориентировочно стоимость разработки ОВОС может составлять дополнительно до 4% от общей стоимости разработки проектной и рабочей документации (П + Р). (Для объектов с привлечением средств ПАО "Газпром" - до 2%) 2. По калькуляции затрат по форме 3П, с предоставлением обоснования. 3. Затраты на разработку раздела ПД «Перечень мероприятий по охране окружающей среды» (ООС) учтены комплексными ценами, содержащимися в СБЦ изд. 1995-1999 гг., 2003 г., 2004 г., 2006-2008 гг., а также ценами, введенными в 2009 г. в статусе государственных стоимостных нормативов. Исключение составляют СБЦ в которых указан другой порядок определения этих затрат
B30: 4.6 | C30: - | D30: Разработка СЗЗ | J30: =SUM(H30:I30) -> 0 | K30: =J30*1.2 -> 0 | L30: СБЦ "Территориальное планирование и планировка территорий. 2010 г. Раздел 2, Таблица 5.
B31: 4.7 | C31: - | D31: Проведение процедур P&ID review, HAZOP/HAZID и SIL | J31: =SUM(H31:I31) -> 0 | K31: =J31*1.2 -> 0 | L31: По калькуляции затрат по форме 3П
B32: 5 | C32: Разработка рабочей документации, в т.ч.: | J32: =SUM(H32:I32) -> 0 | K32: =J32*1.2 -> 0
B33: 5.1 | C33: - | D33: Подготовка сводной заказной спецификации, разработка ведомости объемов работ по форме Заказчика, разработка спецификации аварийного запаса ЗИП | G33: Сводная смета №1 | H33: 0 | I33: =СВОД!H21*0.02 -> 819349.08 | J33: =SUM(H33:I33) -> 819349.08 | K33: =J33*1.2 -> 983218.89 | L33: Выполненнение отдельным томом (в том числе в формате Excel) в размере до 2% от стоимости проектирования соответствующих разделов. Затраты на разработку Разработка ведомости объемов работ учтены комплексными ценами, содержащимися в СБЦ. Затраты на разработку спецификации аварийного запаса ЗИП работ учтены комплексными ценами, содержащимися в СБЦ.
B34: 5.2 | C34: - | D34: Разработка комплектов по титулам | G34: Сводная смета №1 | H34: 0 | I34: =СВОД!E30-СВОД!E29 -> 44464376 | J34: =SUM(H34:I34) -> 44464376 | K34: =J34*1.2 -> 53357251 | L34: СБЦ приведенные в «Федеральном реестре сметных нормативов, подлежащих применению при определении сметной стоимости объектов капитального строительства» размещенного на официальном сайте Минстроя России (www.minstroyrf.ru)
B35: 6 | C35: Разработка эксплуатационной документации, в т.ч.: | J35: =SUM(H35:I35) -> 0 | K35: =J35*1.2 -> 0
B36: 6.1 | C36: - | D36: Разработка технологического регламента | J36: =SUM(H36:I36) -> 0 | K36: =J36*1.2 -> 0 | L36: По калькуляции затрат по форме 3П
B37: 6.2 | C37: - | D37: Разработка ПЛАС | J37: =SUM(H37:I37) -> 0 | K37: =J37*1.2 -> 0 | L37: Справочники базовых цен приведенные в «Федеральном реестре сметных нормативов, подлежащих применению при определении сметной стоимости объектов капитального строительства» размещенного на официальном сайте Минстроя России (www.minstroyrf.ru)
B38: 7 | C38: Прочие затраты, в т.ч.: | J38: =SUM(H38:I38) -> 0 | K38: =J38*1.2 -> 0
B39: 7.1 | C39: - | D39: Рассмотрение и согласование ТКП и РКД поставщиков оборудования и материалов | H39: 0 | I39: =СВОД!F36 -> 2009356.3 | J39: =SUM(H39:I39) -> 2009356.3 | K39: =J39*1.2 -> 2411227.6 | L39: По калькуляции затрат по форме 3П
B40: 8 | C40: Инжиниринговые услуги | J40: =SUM(H40:I40) -> 0 | K40: =J40*1.2 -> 0
B41: 8.1 | C41: - | D41: Авторский надзор Корректировка рабочей документации по результатам СМР.Стадия As build | H41: 0 | I41: =СВОД!E40 -> 6829577.3 | J41: =SUM(H41:I41) -> 6829577.3 | K41: =J41*1.2 -> 8195492.7
B42: 9 | C42: Эксплуатационная документация | J42: =SUM(H42:I42) -> 0 | K42: =J42*1.2 -> 0
B43: 9.1 | C43: - | D43: Корректировка технологического регламента,паспорта взрывобезопасности ОПО, декларации ПБ, план действий по предупреждению и ликвидации ЧС | H43: 0 | I43: =СВОД!E46 -> 3425610 | J43: =SUM(H43:I43) -> 3425610 | K43: =J43*1.2 -> 4110732
B44: 8 | C44: Итого: | H44: =ROUND(SUM(H21:H39),2) -> 20111633 | I44: =ROUND(SUM(I21:I43),2) -> 66820417 | J44: =SUM(H44:I44) -> 86932050
B45: 9 | C45: НДС 20 % | J45: =ROUND(J44*0.2,2) -> 17386410
B46: 10 | C46: Всего с учетом НДС: | J46: =J45+J44 -> 1.0431846e+08 | K46: =SUM(K21:K39) -> 92012236 | N46: =СВОД!F50 -> 1.0431846e+08
N47: =N46-K46 -> 12306225
D49: Итого по смете | F49: =K46 -> 92012236
E50: (сумма прописью)
D53: Главный инженер | G53: А.В. Крупников
G54: подпись (инициалы, фамилия)
D56: Главный инженер проекта | G56: М.В. Ефименко
G57: подпись (инициалы, фамилия)
B58: " 7 " ноября 2024 г.
B59: МП
B62: Согласована:
D64: Ответственный представитель заказчика
G65: подпись (инициалы, фамилия)
B66: Место печати "____" ________________ 20 г.

Sheet СВОД
A1: Сводная смета №1
A2: на проектные и изыскательские работы
A4: По объекту: | B4: ='Форма сводной сметы '!N9 -> «Модернизация существующей инфраструктуры транспортировки и налива фракции С5, с целью обеспечения налива дополнительного объема фракции С5, в количестве 6 000 т/мес.»
C6: Стадия проектирования: Рабочая документация
A7: № пп | B7: Перечень выполняемых работ | C7: Ссылка на № смет по формам 2П, 3П | D7: Полная стоимость работ, руб.
D8: изыскательских | E8: проектных | F8: Всего
A9: 1 | B9: 2 | C9: 4 | D9: 5 | E9: 6 | F9: 7
A10: 1 | B10: Инженерные изыскания
A11: 1.1 | B11: Инженерно-геодезические изыскания | C11: =CONCATENATE("Смета №",A11) -> Смета №1.1 | D11: ='1.1_ИГДИ'!O59 -> 5290473.2 | E11: 0 | F11: =ROUND(SUM(D11+E11),2) -> 5290473.2
A12: 1.2 | B12: Инженерно-геологические изыскания | C12: Смета №1.2.1 Смета №1.2.2 | D12: ='1.2.1 ИГИ'!G61+'1.2.2 ИГИ'!G60 -> 14821160 | E12: 0 | F12: =ROUND(SUM(D12+E12),2) -> 14821160
A13: 1.3 | B13: Итого : | D13: =ROUND(ROUND(SUM(D11:D12),2),2) -> 20111633 | E13: =ROUND(ROUND(SUM(E11:E12),2),2) -> 0 | F13: =E13+D13 -> 20111633
A15: 2 | B15: Обследование, СИД
A16: 2.1 | B16: Обследование существующих зданий и сооружений | C16: =CONCATENATE("Смета №",A16) -> Смета №2.1 | D16: 0 | E16: ='2.1 Обслед'!I53 -> 8939487 | F16: =ROUND(SUM(D16+E16),2) -> 8939487
A17: 2.2 | B17: Сбор исходных данных | C17: Смета №01 | D17: 0 | E17: ='РД_BOQ '!Q112 -> 332661.2 | F17: =ROUND(SUM(D17+E17),2) -> 332661.2
A18: 2.3 | B18: Итого : | D18: =ROUND(SUM(D16:D17),2) -> 0 | E18: =ROUND(SUM(E16:E17),2) -> 9272148.2 | F18: =E18+D18 -> 9272148.2
A20: 3 | B20: Рабочая документация | H20: ТЧ РД
A21: 3.1 | B21: Технология | C21: =CONCATENATE("Смета №",A21) -> Смета №3.1 | D21: 0 | E21: ='3.1 ТХ'!I56 -> 32951458 | F21: =ROUND(SUM(D21+E21),2) -> 32951458 | H21: =SUM(F21:F23) -> 40967454
A22: 3.2 | B22: Сети электроснабжения | C22: =CONCATENATE("Смета №",A22) -> Смета №3.2 | D22: 0 | E22: ='3.2 ЭС'!I52 -> 2711725.4 | F22: =ROUND(SUM(D22+E22),2) -> 2711725.4
A23: 3.3 | B23: Автоматизированная система управления технологическим процессом (АСУ ТП) | C23: =CONCATENATE("Смета №",A23) -> Смета №3.3 | D23: 0 | E23: ='3.3 АСУТП'!Y173 -> 5304270.9 | F23: =ROUND(SUM(D23+E23),2) -> 5304270.9
A24: 3.4 | B24: Промышленная безопасность | C24: =CONCATENATE("Смета №",A24) -> Смета №3.4 | D24: 0 | E24: =ПромБез!I23 -> 900000 | F24: =ROUND(SUM(D24+E24),2) -> 900000
A25: 3.5 | B25: Гидравлические расчеты | C25: =CONCATENATE("Смета №",A25) -> Смета №3.5 | D25: 0 | E25: =Расч!H36 -> 393032.72 | F25: =ROUND(SUM(D25+E25),2) -> 393032.72
A26: 3.6 | B26: Смежные работы | C26: =C17 -> Смета №01 | D26: 0 | E26: ='РД_BOQ '!Q157+'РД_BOQ '!Q178+'РД_BOQ '!Q199 -> 1213411.7 | F26: =ROUND(SUM(D26+E26),2) -> 1213411.7
A27: 3.7 | B27: Отчетная документация по проекту | C27: =C17 -> Смета №01 | D27: 0 | E27: ='РД_BOQ '!Q214 -> 240477.92 | F27: =ROUND(SUM(D27+E27),2) -> 240477.92
A28: 3.8 | B28: Оплата экспертизы Промышленной безопасности | C28: По факту | D28: 0 | E28: 750000 | F28: =ROUND(SUM(D28+E28),2) -> 750000
A29: 3.9 | B29: Подготовка сводной заказной спецификации, разработка ведомости объемов работ по форме Заказчика, разработка спецификации аварийного запаса ЗИП | C29: 2% от ТЧ РД | D29: 0 | E29: =(E21+E22+E23)*0.02 -> 819349.08 | F29: =ROUND(SUM(D29+E29),2) -> 819349.08
A30: 3.10 | B30: Итого : | D30: =SUM(D21:D29) -> 0 | E30: =ROUND(SUM(E21:E29),2) -> 45283725 | F30: =ROUND(SUM(D30+E30),2) -> 45283725
A32: 4 | B32: Прочие затраты
A33: 4.1 | B33: ='РД_BOQ '!B192 -> Формирование механических ОЛ | C33: =$C$27 -> Смета №01 | D33: 0 | E33: ='РД_BOQ '!C192 -> 1133002.4 | F33: =ROUND(SUM(D33+E33),2) -> 1133002.4
A34: 4.1 | B34: ='Форма сводной сметы '!D39 -> Рассмотрение и согласование ТКП и РКД поставщиков оборудования и материалов | C34: =CONCATENATE("Смета №",A34) -> Смета №4.1 | D34: 0 | E34: ='4.1 КД'!H36 -> 563231.44 | F34: =ROUND(SUM(D34+E34),2) -> 563231.44
A35: 4.2 | B35: Согласование с собственниками существующих сооружений пересечение с проектируемыми сооружениями | C35: =$C$27 -> Смета №01 | D35: 0 | E35: ='РД_BOQ '!C185 -> 313122.48 | F35: =ROUND(SUM(D35+E35),2) -> 313122.48
A36: 4.2 | B36: Итого : | D36: =ROUND(SUM(D34),2) -> 0 | E36: =ROUND(SUM(E33:E35),2) -> 2009356.3 | F36: =E36+D36 -> 2009356.3
A37: 5 | B37: Инжиниринговые услуги
A38: 5.1 | B38: Авторский надзор | C38: =$C$27 -> Смета №01 | D38: 0 | E38: ='РД_BOQ '!C224 -> 4236422.1 | F38: =ROUND(SUM(D38+E38),2) -> 4236422.1
A39: 5.2 | B39: Корректировка рабочей документации по результатам СМР.Стадия As build | C39: =$C$27 -> Смета №01 | D39: 0 | E39: ='РД_BOQ '!C231 -> 2593155.2 | F39: =ROUND(SUM(D39+E39),2) -> 2593155.2
A40: 5.3 | B40: Итого : | D40: =SUM(D30:D39) -> 0 | E40: =ROUND(SUM(E37:E39),2) -> 6829577.3 | F40: =ROUND(SUM(F37:F39),2) -> 6829577.3
A41: 6 | B41: Эксплуатационная документация
A42: 6.1 | B42: ='РД_BOQ '!B239 -> Корректировка технологического регламента (при необходимости) 5-ти регламентов (ЭП-616, ЭП-600, ИП-10, Т-8/2, Т-6) | C42: =$C$27 -> Смета №01 | D42: 0 | E42: ='РД_BOQ '!C239 -> 1283752.1 | F42: =ROUND(SUM(D42+E42),2) -> 1283752.1
A43: 6.2 | B43: ='РД_BOQ '!B246 -> Паспорт взрывобезопасности опасного производственного объекта (при необходимости) | C43: =$C$27 -> Смета №01 | D43: 0 | E43: ='РД_BOQ '!C246 -> 829849.7 | F43: =ROUND(SUM(D43+E43),2) -> 829849.7
A44: 6.3 | B44: ='РД_BOQ '!B253 -> Декларация пожарной безопасности (при необходимости) | C44: =$C$27 -> Смета №01 | D44: 0 | E44: ='РД_BOQ '!C253 -> 709610.66 | F44: =ROUND(SUM(D44+E44),2) -> 709610.66
A45: 6.4 | B45: ='РД_BOQ '!B260 -> План действий по предупреждению и ликвидации чрезвычайных ситуаций природного и техногенного характера (при необходимости) | C45: =$C$27 -> Смета №01 | D45: 0 | E45: ='РД_BOQ '!C260 -> 602397.54 | F45: =ROUND(SUM(D45+E45),2) -> 602397.54
A46: 6.4 | B46: Итого : | D46: =SUM(D37:D45) -> 0 | E46: =ROUND(SUM(E42:E45),2) -> 3425610 | F46: =ROUND(SUM(F42:F45),2) -> 3425610
A48: 3 | B48: Итого по сводной смете | D48: =ROUND(D30+D18+D13+D36,2) -> 20111633 | E48: =ROUND(E30+E18+E13+E36+E40+E46,2) -> 66820417 | F48: =E48+D48 -> 86932050
A49: 4 | B49: НДС | C49: 20% | D49: =ROUND(D48*0.2,2) -> 4022326.6 | E49: =E48*0.2 -> 13364083 | F49: =E49+D49 -> 17386410
A50: 5 | B50: Всего по сводной смете | D50: =D48+D49 -> 24133960 | E50: =E48+E49 -> 80184500 | F50: =E50+D50 -> 1.0431846e+08

Sheet 1.1_ИГДИ
A1: Смета № | F1: 1.1
A2: Инженерно - геодезические изыскания
B3: Наименование объекта: | D3: ='Форма сводной сметы '!N9 -> «Модернизация существующей инфраструктуры транспортировки и налива фракции С5, с целью обеспечения налива дополнительного объема фракции С5, в количестве 6 000 т/мес.»
B5: Наименование организации: | D5: ='Форма сводной сметы '!F12 -> ОАО "СибНефтеТрансПроект"
A7: № п/п | B7: Наименование работ и затрат | D7: Обоснование стоимости | E7: Ед. изм. | F7: Кол- во | G7: Расчет стоимости | O7: Стоимость, руб
A9: 1 | B9: 2 | D9: 3 | E9: 4 | F9: 5 | G9: 6 | O9: 7
B10: Сметный расчет составлен по Справочнику базовых цен на инженерные изыскания для строительства. Инженерно-геодезические изыскания. ПНИИИС, 2004 г.
A11: 1 | B11: Создание инженерно-топографического плана. Эстакада (3 яруса). | D11: Ч. I, гл.2, табл.9.
D12: 1,25п - территория со специальным режимом - ОУ, п.8, в);
B13: [ P ] = | C13: 19.58 | D13: 1,75пк - съемка подз. коммуникаций - Ч. I, гл.2, табл.9, прим.4.
B14: - масштаб: | C14: 1:500 | D14: 1,2к - применение комп. технологий - ОУ, п.15, д).
B15: - высота сеч. рельефа: | C15: 0.5м.
B16: - В. Территории действ. пром. предприятий.
D17: 1,3пк - детальное обследование колодцев подземных коммуникаций и надземных коммуникаций, с составлением эскизов и разрезов опор и узлов - Ч. I, гл.2, табл.9, прим.5;
B18: Категория сложности II | C18: полевые работы: | D18: Ч. I, гл.2, табл.9, § 5 | E18: 1 га. | F18: 19.58 | G18: 4632 | H18: 1.75 | J18: 1.3 | M18: 1.25 | N18: 19.58*4 632*1.75*1.3*1.25 | O18: 257912.66
C19: камеральные работы: | D19: Ч. I, гл.2, табл.9, § 5 | E19: 1 га. | F19: 19.58 | G19: 1938 | H19: 1.75 | I19: 1.2 | J19: 1.3 | N19: 19.58*1 938*1.75*1.2*1.3 | O19: 103592.69
A20: 2 | B20: Создание инженерно-топографического плана. Насосная. | D20: Ч. I, гл.2, табл.9.
D21: 1,25п - территория со специальным режимом - ОУ, п.8, в);
B22: [ P ] = | C22: 0.9 | D22: 1,75пк - съемка подз. коммуникаций - Ч. I, гл.2, табл.9, прим.4.
B23: - масштаб: | C23: 1:500 | D23: 1,2к - применение комп. технологий - ОУ, п.15, д).
B24: - высота сеч. рельефа: | C24: 0.5м.
B25: - В. Территории действ. пром. предприятий.
D26: 1,4п - съёмка участков 1:500 до 1 га. - Ч. I, гл.2, табл.10, § 1.
B27: Категория сложности II | C27: полевые работы: | D27: Ч. I, гл.2, табл.9, § 5 | E27: 1 га. | F27: 0.9 | G27: 4632 | H27: 1.75 | J27: 1.4 | M27: 1.25 | N27: 0.9*4 632*1.75*1.4*1.25 | O27: 12766.95
C28: камеральные работы: | D28: Ч. I, гл.2, табл.9, § 5 | E28: 1 га. | F28: 0.9 | G28: 1938 | H28: 1.75 | I28: 1.2 | N28: 0.9*1 938*1.75*1.2 | O28: 3662.82
A29: 3 | B29: Создание плановой опорной сети. | D29: Ч. I, гл.1, табл.8.
B30: с закладкой - | C30: 4
B31: - 2 разряд | D31: 1,3пк - использование спутниковых геодезических систем - Ч. I, гл.1, табл.8, прим.2.
B32: Категория И-II, З-II Категория II | C32: полевые работы: | D32: Ч. I, гл.1, табл.8, § 3 | E32: 1 пт. | F32: 4 | G32: 6426 | H32: 1.3 | N32: 4.0*6 426*1.3 | O32: 33415.2
C33: камеральные работы: | D33: Ч. I, гл.1, табл.8, § 3 | E33: 1 пт. | F33: 4 | G33: 2538 | H33: 1.3 | N33: 4.0*2 538*1.3 | O33: 13197.6
A34: 4 | B34: Создание высотной опорной сети. | D34: Ч. I, гл.1, табл.8.
B35: - IV класс
B36: Категория И-II, З-II Категория II | C36: полевые работы: | D36: Ч. I, гл.1, табл.8, § 4 | E36: 1 пт. | F36: 4 | G36: 1897 | N36: 4.0*1 897 | O36: 7588
C37: камеральные работы: | D37: Ч. I, гл.1, табл.8, § 4 | E37: 1 пт. | F37: 4 | G37: 428 | N37: 4.0*428 | O37: 1712
A38: 5 | B38: Плановая и высотная привязка геологических скважин, точек статического зондирования и пр. | D38: Ч. II, гл.7, табл.48.
B39: - скв. геологические | C39: 20
B40: [ ] = | C40: 20
B41: При расстоянии между точками:
B42: - св. 200 м. до 350 м. | D42: 0,5п - предварительная разбивка местоположения точек
B43: Категория сложности I | C43: полевые работы: | D43: Ч. II, гл.7, табл.48, § 4 | E43: 1 т. | F43: 20 | G43: 180 | H43: 0.5 | N43: 20.0*180*0.5 | O43: 1800
A44: 6 | B44: Плановая и высотная привязка геологических скважин, точек статического зондирования и пр. | D44: Ч. II, гл.7, табл.48.
B45: - скв. геологические | C45: 20
B46: [ ] = | C46: 20
B47: При расстоянии между точками:
B48: - св. 200 м. до 350 м.
B49: Категория сложности I | C49: полевые работы: | D49: Ч. II, гл.7, табл.48, § 4 | E49: 1 т. | F49: 20 | G49: 180 | N49: 20.0*180 | O49: 3600
A50: 7 | B50: Итого полевых работ - Неблагоприятный период (1/XI-1/V, 6мес.) | D50: 1,3п - неблагоприятный период года 6 - 7.5 мес. - ОУ, п.8, г), §2 | E50: 1 | F50: 1.3 | H50: 317082.81 | N50: 1.3*317 082.81 * 100.00% | O50: 412207.65
A51: 8 | B51: Итого камеральных работ | F51: 1 | N51: 1*122 165.11 | O51: 122165.11
A52: 9 | B52: Внутренний транспорт | D52: расст. от базы до уч. изысканий от 15 км до 20 км - ОУ, табл.4, §4 | F52: 0.125 | H52: 412207.65 | N52: 12.5%*412 207.65 | O52: 51525.96
A53: 10 | B53: Внешний транспорт | D53: расст. проезда и перевозки от 1000 км до 2000 км - ОУ, табл.5, §5 | F53: 0.364 | H53: 463733.61 | N53: 36.4%*(412 207.65 + 51 525.96) | O53: 168799.03
A54: 11 | B54: Организация и ликвидация работ | D54: ОУ, п.13 | F54: 0.06 | H54: 463733.61 | N54: 6%**(412 207.65+51 525.96) | O54: 27824.02
A55: 12 | B55: Итого с районным коэффициентом | C55: полевые работы: | D55: 1,08п - районный коэффициент 1,15 - ОУ, п.8, д), табл.3, §2 | F55: 1.08 | H55: 660356.66 | N55: 660 356.66*1.08 | O55: 713185.19
A56: 13 | B56: Итого с районным коэффициентом | C56: камеральные работы: | D56: 1,08к - районный коэффициент 1,15 - ОУ, п.8, д), табл.3, §2 | F56: 1.08 | H56: 122165.11 | N56: 122 165.11*1.08 | O56: 131938.32
A57: 14 | B57: итого: | O57: 845123.51
A58: 15 | B58: Итого с учетом индекса изменения стоимости к уровню базовых цен по состоянию на 1 января 2001 года | D58: Письмо Минстроя России N 61327-ИФ/09 от 18.10.2024 г (2024г. IV квартал) | F58: 6.26 | H58: 845123.51 | N58: 845 123.51*6.26 | O58: 5290473.2
A59: 16 | B59: Итого по смете | O59: 5290473.2

Sheet 1.2.1 ИГИ
A1: Смета №1.2.1
B2: на инженерно-геологические изыскания
A4: Наименование объекта: | C4: ='Форма сводной сметы '!N9 -> «Модернизация существующей инфраструктуры транспортировки и налива фракции С5, с целью обеспечения налива дополнительного объема фракции С5, в количестве 6 000 т/мес.»
C5: 56209 Нижнекамск. Насосная Т-8/2
A6: Наименование организации-подрядчика | C6: ОАО "Сибнефтетранспроект"
A8: № п/п | B8: Наименование видов работ | C8: Обоснование стоимости | D8: Единица измерения | E8: Объем | F8: Расценка | G8: Стоимость
A9: Справочник базовых цен на инженерно-геологические и инженерно-экологические изыскания для строительства, ГОССТРОЙ РФ, 1999г.
A10: Раздел I, БУРОВЫЕ И ГОРНОПРОХОДЧЕСКИЕ РАБОТЫ
A11: 1 | B11: Инженерно-геологическая рекогносцировка при удовлетворительной проходимости | C11: Таб.9 §2 | D11: 1км | E11: 0.4 | F11: =ROUND(E11,0)&"*27.0" -> 0*27.0 | G11: =ROUND(E11*27,1) -> 10.8
A12: 2 | B12: Колонковое бурение скважин диаметром до 160 мм глубиной до 15 м (8скв.х15п.м.) в породах | C12: Таб.17 §1
B13: I категории | D13: 1 м | E13: 15 | F13: =E13&"*36.0*0.9" -> 15*36.0*0.9 | G13: =ROUND(E13*36*0.9,0) -> 486
B14: II категории | D14: 1 м | E14: 45 | F14: =E14&"*38.4*0.9" -> 45*38.4*0.9 | G14: =ROUND(E14*38.4*0.9,1) -> 1555.2
B15: III категории | D15: 1 м | E15: 45 | F15: =E15&"*42.6*0.9" -> 45*42.6*0.9 | G15: =ROUND(E15*42.6*0.9,1) -> 1725.3
B16: IV категории | D16: 1 м | E16: 15 | F16: =E16&"*45.6*0.9" -> 15*45.6*0.9 | G16: =ROUND(E16*45.6*0.9,1) -> 615.6
B17: Итого по пункту 2 | E17: =SUM(E13:E16) -> 120 | G17: =SUM(G13:G16) -> 4382.1
A18: 3 | B18: Отбор монолитов | C18: Таб.57
B19: из скважин с глубины до 10м | C19: §1 | D19: 1 мон | E19: 40 | F19: =E19&"*22.9" -> 40*22.9 | G19: =ROUND(E19*22.9,1) -> 916
B20: из скважин с глубины св.10 до 20м | C20: §2 | D20: 1 мон | E20: 20 | F20: =E20&"*30.6" -> 20*30.6 | G20: =ROUND(E20*30.6,1) -> 612
A21: 4 | B21: Гидрогеологические наблюдения при бурении скважин диаметром до 160 мм | C21: Таб.18 §1 гл.4 п.8 | D21: 1 м | E21: =E17*0.6 -> 72 | F21: =E21&"*1.6*0.6" -> 72*1.6*0.6 | G21: =ROUND(E21*1.6*0.6,1) -> 69.1
A22: 5 | B22: Бурение скважин для штамповых испытаний площадью 600см2 до 10м в породах II категории | C22: глава 6 п.4 Таб.21 §4 | D22: 1 м | E22: 32 | F22: =E22&"*10.8*0.4" -> 32*10.8*0.4 | G22: =ROUND(E22*10.8*0.4,1) -> 138.2
A23: 6 | B23: Испытание грунтов в буровых скважинах на глубине до 10м вертикальной статической нагрузкой штампом площадью 600см2 удельным давлением до 0.3МПа-III категории сложности | C23: Таб.54 §15 | D23: 1 исп. | E23: 8 | F23: =E23&"*570" -> 8*570 | G23: =ROUND(E23*570,1) -> 4560
A24: 7 | B24: Статическое зондирование глубиной св.10 до 15 м | C24: Таб.45 §5 | D24: 1 испыт. | E24: 8 | F24: =E24&"*172.5" -> 8*172.5 | G24: =ROUND(E24*172.5,1) -> 1380
A25: 8 | B25: Плановая и высотная привязка выработок II категории сложности при расстоянии между выработками | C25: Таб.93
B26: до 50 м | C26: §1 | D26: 1т | E26: 8 | F26: =E26&"*8.5" -> 8*8.5 | G26: =ROUND(E26*8.5,1) -> 68
A27: 9 | B27: Предварительная разбивка II категории сложности при расстоянии между точками | C27: Таб.93
B28: до 50 м | C28: §1 | D28: 1т | E28: =E26 -> 8 | F28: =E28&"*8.5" -> 8*8.5 | G28: =ROUND(E28*8.5,1) -> 68
A29: 10 | B29: Итого по пунктам 1-9 с учетом неблагоприятного периода | C29: Таб.2 §3 | F29: =G11+ROUND(SUM(G17:G28),1)&"*1.3" -> 12204,2*1.3 | G29: =(G11+SUM(G17:G28))*1.3 -> 15865.46
A30: 11 | B30: Внутренний транспорт | C30: Таб.4 §5 | F30: =ROUND(G29,1)&"*0.1625" -> 15865,5*0.1625 | G30: =ROUND(G29*0.1625,1) -> 2578.1
A31: 12 | B31: Внешний транспорт | C31: Таб.5 §5 | F31: =ROUND((G29+G30),1)&"*0.364" -> 18443,6*0.364 | G31: =(G29+G30)*0.364 -> 6713.4558
A32: 13 | B32: Организация и ликвидация работ | C32: ОУ п.13 | F32: =ROUND((G29+G30),1)&"*0.06" -> 18443,6*0.06 | G32: =(G29+G30)*0.06 -> 1106.6136
A33: 14 | B33: ВСЕГО по разделу I с учетом спецрежима территории | C33: ОУ п.8в | F33: =ROUND((SUM(G29:G32)),1)&"*1.25" -> 26263,6*1.25 | G33: =ROUND(G29+G30+G31+G32,1)*1.25 -> 32829.5
A34: Раздел II, ЛАБОРАТОРНЫЕ РАБОТЫ
A35: =A33+1 -> 15 | B35: Полный комплекс определений физических свойств | C35: Таб.63 §8 | D35: 1обр | E35: =SUM(E19:E20)-SUM(E36:E38) -> 6 | F35: =E35&"*47.1" -> 6*47.1 | G35: =ROUND(E35*47.1,1) -> 282.6
A36: =A35+1 -> 16 | B36: Сокращенный комплекс физико-механических свойств грунтов при консолидированном срезе с нагрузкой до 0,6 МПа | C36: Таб.63 §11 | D36: 1обр | E36: 24 | F36: =E36&"*135.0" -> 24*135.0 | G36: =ROUND(E36*135,1) -> 3240
A37: =A36+1 -> 17 | B37: Сокращенный комплекс физико-механических свойств грунтов. Показатели сжимаемости и сопутствующие определения при компрессионных испытаниях с двумя ветвями нагрузки до 0,6 МПа | C37: Таб.63 §18 | D37: 1обр | E37: 6 | F37: =E37&"*147.5" -> 6*147.5 | G37: =ROUND(E37*147.5,1) -> 885
A38: =A37+1 -> 18 | B38: Определение характеристик прочности и деформируемости грунтов при трехосном сжатии. Дренированное испытание с предварительным уплотнением образца и отжатием воды из него только в процессе уплотнения) для определения характеристик прочности и деформируемости глинистых и биогенных грунтов в стабилизированном состоянии | C38: Таб.66 §4 | E38: 24 | F38: =E38&"*741.4" -> 24*741.4 | G38: =ROUND(E38*741.4,1) -> 17793.6
A39: =A38+1 -> 19 | B39: Относительная деформация пучения | C39: Табл.63 аналог §32 | D39: 1обр | E39: 12 | F39: =E39&"*186.4" -> 12*186.4 | G39: =ROUND(E39*186.4,1) -> 2236.8
A40: =A39+1 -> 20 | B40: Стандартный анализ воды | C40: Таб.73 §2 | D40: 1обр | E40: 3 | F40: =E40&"*67.3" -> 3*67.3 | G40: =ROUND(E40*67.3,1) -> 201.9
A41: =A40+1 -> 21 | B41: Коррозия грунтов к стали | C41: Таб.75 §4 | D41: 1обр | E41: 6 | F41: =E41&"*18.2" -> 6*18.2 | G41: =ROUND(E41*18.2,1) -> 109.2
A42: =A41+1 -> 22 | B42: Водная вытяжка | C42: Таб.71 §1 | D42: 1обр | E42: 6 | F42: =E42&"*48.8" -> 6*48.8 | G42: =ROUND(E42*48.8,1) -> 292.8
A43: =A42+1 -> 23 | B43: Итого по разделу II | G43: =SUM(G35:G42) -> 25041.9
A44: =A43+1 -> 24 | B44: ВСЕГО по разделу II с учетом районного коэффициента | C44: ОУ таб.3§2 | F44: =G43&"*1.08" -> 25041,9*1.08 | G44: =ROUND(G43*1.08,1) -> 27045.3
A45: Раздел III, КАМЕРАЛЬНЫЕ РАБОТЫ
A46: =A44+1 -> 25 | B46: Сбор, изучение и систематизация материалов изысканий прошлых лет:
B47: по горным выработкам | C47: Таб.78 §1 | D47: 1м | E47: 100 | F47: =ROUND(E47,1)&"*9.0" -> 100*9.0 | G47: =ROUND(E47*9,1) -> 900
B48: по цифровым показателям | C48: Таб.78 §2 | D48: 10 зн. | E48: 30 | F48: =E48&"*3.6" -> 30*3.6 | G48: =ROUND(E48*3.6,1) -> 108
A49: =A46+1 -> 26 | B49: Камеральная обработка результатов:
B50: буровых работ II кат. сложности | C50: Таб.82 §2 | D50: 1м | E50: =E17 -> 120 | F50: =E50&"*9.3" -> 120*9.3 | G50: =ROUND(E50*9.3,1) -> 1116
B51: штамповых испытаний | C51: Таб.83 §6 | D51: 1 исп | E51: =E23 -> 8 | F51: =ROUND(E51,1)&"*94.7" -> 8*94.7 | G51: =ROUND(E51*94.7,1) -> 757.6
B52: статического зондирования | C52: Таб.83 §3 | D52: 1исп | E52: =E24 -> 8 | F52: =E52&"*48.2" -> 8*48.2 | G52: =ROUND(E52*48.2,1) -> 385.6
B53: лабораторных работ | C53: Таб.86 §1 | E53: =SUM(G35:G37) -> 4407.6 | F53: =E53&"*0.2" -> 4407,6*0.2 | G53: =ROUND(E53*0.2,1) -> 881.5
B54: лабораторных работ (корр. активн. грунтов) | C54: Таб.86 §8 | E54: =SUM(G40:G42) -> 603.9 | F54: =E54&"*0.15" -> 603,9*0.15 | G54: =E54*0.15 -> 90.585
A55: =A49+1 -> 27 | B55: Итого камеральных работ | G55: =SUM(G47:G54) -> 4239.285
A56: =A55+1 -> 28 | B56: Составление программы работ при средней глубине исследования >10<15м, площади исследования <1 км2, II категории сложности | C56: Таб.81 §3 прим. 1 | D56: 1 прог. | E56: 1 | F56: 800*1.25 | G56: =800*1.25 -> 1000
A57: =A56+1 -> 29 | B57: Составление отчета II категории сложности, при стоимости камеральных работ до 5 тыс. руб. | C57: Таб.87§1 | D57: 1 отчет | E57: 1 | F57: =ROUND(G55,1)&"*0.21" -> 4239,3*0.21 | G57: =ROUND(G55*0.21,1) -> 890.2
A58: =A57+1 -> 30 | B58: ВСЕГО по разделу II с учетом районного коэффициента | C58: ОУ таб.3§2 | F58: =ROUND(G55+G56+G57,1)&"*1.08" -> 6129,5*1.08 | G58: =(G55+G56+G57)*1.08 -> 6619.8438
A59: =A58+1 -> 31 | B59: Итого: | G59: =G33+G44+G58 -> 66494.644
A60: =A59+1 -> 32 | B60: Итого с индексом инфляции 71.21 | G60: =G59*71.21 -> 4735083.6
A61: =A60+1 -> 33 | B61: ВСЕГО ПО СМЕТЕ: | G61: =G60 -> 4735083.6

Sheet 1.2.2 ИГИ
A1: Смета №1.2.2
B2: на инженерно-геологические изыскания
A4: Наименование объекта: | C4: ='Форма сводной сметы '!N9 -> «Модернизация существующей инфраструктуры транспортировки и налива фракции С5, с целью обеспечения налива дополнительного объема фракции С5, в количестве 6 000 т/мес.»
C5: 56209 Нижнекамск. Эстакада
A6: Наименование организации-подрядчика | C6: ОАО "Сибнефтетранспроект"
A8: № п/п | B8: Наименование видов работ | C8: Обоснование стоимости | D8: Единица измерения | E8: Объем | F8: Расценка | G8: Стоимость
A9: Справочник базовых цен на инженерно-геологические и инженерно-экологические изыскания для строительства, ГОССТРОЙ РФ, 1999г.
A10: Раздел I, БУРОВЫЕ И ГОРНОПРОХОДЧЕСКИЕ РАБОТЫ
A11: 1 | B11: Инженерно-геологическая рекогносцировка при удовлетворительной проходимости | C11: Таб.9 §2 | D11: 1км | E11: 4.9 | F11: =ROUND(E11,0)&"*27.0" -> 5*27.0 | G11: =ROUND(E11*27,1) -> 132.3
A12: 2 | B12: Колонковое бурение скважин диаметром до 160 мм глубиной до 15 м (8скв.х15п.м.) в породах | C12: Таб.17 §1
B13: I категории | D13: 1 м | E13: 70 | F13: =E13&"*36.0*0.9" -> 70*36.0*0.9 | G13: =ROUND(E13*36*0.9,0) -> 2268
B14: II категории | D14: 1 м | E14: 200 | F14: =E14&"*38.4*0.9" -> 200*38.4*0.9 | G14: =ROUND(E14*38.4*0.9,1) -> 6912
B15: III категории | D15: 1 м | E15: 200 | F15: =E15&"*42.6*0.9" -> 200*42.6*0.9 | G15: =ROUND(E15*42.6*0.9,1) -> 7668
B16: IV категории | D16: 1 м | E16: 40 | F16: =E16&"*45.6*0.9" -> 40*45.6*0.9 | G16: =ROUND(E16*45.6*0.9,1) -> 1641.6
B17: Итого по пункту 2 | E17: =SUM(E13:E16) -> 510 | G17: =SUM(G13:G16) -> 18489.6
A18: 3 | B18: Отбор монолитов | C18: Таб.57
B19: из скважин с глубины до 10м | C19: §1 | D19: 1 мон | E19: 90 | F19: =E19&"*22.9" -> 90*22.9 | G19: =ROUND(E19*22.9,1) -> 2061
B20: из скважин с глубины св.10 до 20м | C20: §2 | D20: 1 мон | E20: 60 | F20: =E20&"*30.6" -> 60*30.6 | G20: =ROUND(E20*30.6,1) -> 1836
A21: 4 | B21: Гидрогеологические наблюдения при бурении скважин диаметром до 160 мм | C21: Таб.18 §1 гл.4 п.8 | D21: 1 м | E21: =E17*0.6 -> 306 | F21: =E21&"*1.6*0.6" -> 306*1.6*0.6 | G21: =ROUND(E21*1.6*0.6,1) -> 293.8
A22: 5 | B22: Статическое зондирование глубиной св.10 до 15 м | C22: Таб.45 §5 | D22: 1 испыт. | E22: 34 | F22: =E22&"*172.5" -> 34*172.5 | G22: =ROUND(E22*172.5,1) -> 5865
A23: 6 | B23: Проходка шурфов сечением 1,25 м2 глубиной до 10 м в породах III категории | C23: Таб.27§2 прим.2, 3 | D23: 1 м | E23: 24 | F23: =E23&"*70.7*0.75*1.3" -> 24*70.7*0.75*1.3 | G23: =ROUND(E23*70.7*0.75*1.3,0) -> 1654
A24: 7 | B24: Крепление шурфов в неусточивых породах глубиной св. 2.5 до 5 м | C24: Таб.32§2 | D24: 1 шурф | E24: 6 | F24: =E24&"*102.6" -> 6*102.6 | G24: =ROUND(E24*102.6,0) -> 616
A25: =A24+1 -> 8 | B25: Плановая и высотная привязка выработок II категории сложности при расстоянии между выработками | C25: Таб.93
B26: св. 100 до 200 м | C26: §3 | D26: 1т | E26: 34 | F26: =E26&"*14.4" -> 34*14.4 | G26: =ROUND(E26*14.4,1) -> 489.6
A27: =A25+1 -> 9 | B27: Предварительная разбивка II категории сложности при расстоянии между точками | C27: Таб.93
B28: св. 100 до 200 м | C28: §3 | D28: 1т | E28: =E26 -> 34 | F28: =E28&"*14.4" -> 34*14.4 | G28: =ROUND(E28*14.4,1) -> 489.6
A29: =A27+1 -> 10 | B29: Итого по пунктам 1-9 с учетом неблагоприятного периода | C29: Таб.2 §3 | F29: =G11+ROUND(SUM(G17:G28),1)&"*1.3" -> 31926,9*1.3 | G29: =(G11+SUM(G17:G28))*1.3 -> 41504.97
A30: =A29+1 -> 11 | B30: Внутренний транспорт | C30: Таб.4 §5 | F30: =ROUND(G29,1)&"*0.15" -> 41505*0.15 | G30: =ROUND(G29*0.15,1) -> 6225.7
A31: =A30+1 -> 12 | B31: Внешний транспорт | C31: Таб.5 §5 | F31: =ROUND((G29+G30),1)&"*0.364" -> 47730,7*0.364 | G31: =(G29+G30)*0.364 -> 17373.964
A32: =A31+1 -> 13 | B32: Организация и ликвидация работ | C32: ОУ п.13 | F32: =ROUND((G29+G30),1)&"*0.06" -> 47730,7*0.06 | G32: =(G29+G30)*0.06 -> 2863.8402
A33: =A32+1 -> 14 | B33: ВСЕГО по разделу I с учетом спецрежима территории | C33: ОУ п.8в | F33: =ROUND((SUM(G29:G32)),1)&"*1.25" -> 67968,5*1.25 | G33: =ROUND(G29+G30+G31+G32,1)*1.25 -> 84960.625
A34: Раздел II, ЛАБОРАТОРНЫЕ РАБОТЫ
A35: =A33+1 -> 15 | B35: Полный комплекс определений физических свойств | C35: Таб.63 §8 | D35: 1обр | E35: =SUM(E19:E20)-SUM(E36:E38) -> 72 | F35: =E35&"*47.1" -> 72*47.1 | G35: =ROUND(E35*47.1,1) -> 3391.2
A36: =A35+1 -> 16 | B36: Сокращенный комплекс физико-механических свойств грунтов при консолидированном срезе с нагрузкой до 0,6 МПа | C36: Таб.63 §11 | D36: 1обр | E36: 36 | F36: =E36&"*135.0" -> 36*135.0 | G36: =ROUND(E36*135,1) -> 4860
A37: =A36+1 -> 17 | B37: Сокращенный комплекс физико-механических свойств грунтов. Показатели сжимаемости и сопутствующие определения при компрессионных испытаниях с двумя ветвями нагрузки до 0,6 МПа | C37: Таб.63 §18 | D37: 1обр | E37: 6 | F37: =E37&"*147.5" -> 6*147.5 | G37: =ROUND(E37*147.5,1) -> 885
A38: =A37+1 -> 18 | B38: Определение характеристик прочности и деформируемости грунтов при трехосном сжатии. Дренированное испытание с предварительным уплотнением образца и отжатием воды из него только в процессе уплотнения) для определения характеристик прочности и деформируемости глинистых и биогенных грунтов в стабилизированном состоянии | C38: Таб.66 §4 | E38: 36 | F38: =E38&"*741.4" -> 36*741.4 | G38: =ROUND(E38*741.4,1) -> 26690.4
A39: =A38+1 -> 19 | B39: Относительная деформация пучения | C39: Табл.63 аналог §32 | D39: 1обр | E39: 18 | F39: =E39&"*186.4" -> 18*186.4 | G39: =ROUND(E39*186.4,1) -> 3355.2
A40: =A39+1 -> 20 | B40: Стандартный анализ воды | C40: Таб.73 §2 | D40: 1обр | E40: 6 | F40: =E40&"*67.3" -> 6*67.3 | G40: =ROUND(E40*67.3,1) -> 403.8
A41: =A40+1 -> 21 | B41: Коррозия грунтов к стали | C41: Таб.75 §4 | D41: 1обр | E41: 12 | F41: =E41&"*18.2" -> 12*18.2 | G41: =ROUND(E41*18.2,1) -> 218.4
A42: =A41+1 -> 22 | B42: Водная вытяжка | C42: Таб.71 §1 | D42: 1обр | E42: 12 | F42: =E42&"*48.8" -> 12*48.8 | G42: =ROUND(E42*48.8,1) -> 585.6
A43: =A42+1 -> 23 | B43: Итого по разделу II | G43: =SUM(G35:G42) -> 40389.6
A44: =A43+1 -> 24 | B44: ВСЕГО по разделу II с учетом районного коэффициента | C44: ОУ таб.3§2 | F44: =G43&"*1.08" -> 40389,6*1.08 | G44: =ROUND(G43*1.08,1) -> 43620.8
A45: Раздел III, КАМЕРАЛЬНЫЕ РАБОТЫ
A46: =A44+1 -> 25 | B46: Сбор, изучение и систематизация материалов изысканий прошлых лет:
B47: по горным выработкам | C47: Таб.78 §1 | D47: 1м | E47: 100 | F47: =ROUND(E47,1)&"*9.0" -> 100*9.0 | G47: =ROUND(E47*9,1) -> 900
B48: по цифровым показателям | C48: Таб.78 §2 | D48: 10 зн. | E48: 30 | F48: =E48&"*3.6" -> 30*3.6 | G48: =ROUND(E48*3.6,1) -> 108
A49: =A46+1 -> 26 | B49: Камеральная обработка результатов:
B50: буровых работ II кат. сложности | C50: Таб.82 §2 | D50: 1м | E50: =E17 -> 510 | F50: =E50&"*9.3" -> 510*9.3 | G50: =ROUND(E50*9.3,1) -> 4743
B51: статического зондирования | C51: Таб.83 §3 | D51: 1исп | E51: =E22 -> 34 | F51: =E51&"*48.2" -> 34*48.2 | G51: =ROUND(E51*48.2,1) -> 1638.8
B52: лабораторных работ | C52: Таб.86 §1 | E52: =SUM(G35:G37) -> 9136.2 | F52: =E52&"*0.2" -> 9136,2*0.2 | G52: =ROUND(E52*0.2,1) -> 1827.2
B53: лабораторных работ (корр. активн. грунтов) | C53: Таб.86 §8 | E53: =SUM(G40:G42) -> 1207.8 | F53: =E53&"*0.15" -> 1207,8*0.15 | G53: =E53*0.15 -> 181.17
A54: =A49+1 -> 27 | B54: Итого камеральных работ | G54: =SUM(G47:G53) -> 9398.17
A55: =A54+1 -> 28 | B55: Составление программы работ при средней глубине исследования >10<15м, площади исследования <1 км2, II категории сложности | C55: Таб.81 §3 прим. 1 | D55: 1 прог. | E55: 1 | F55: 800*1.25 | G55: =800*1.25 -> 1000
A56: =A55+1 -> 29 | B56: Составление отчета II категории сложности, при стоимости камеральных работ св. 5 до 20 тыс. руб. | C56: Таб.87§1 | D56: 1 отчет | E56: 1 | F56: =ROUND(G54,1)&"*0.18" -> 9398,2*0.18 | G56: =ROUND(G54*0.18,1) -> 1691.7
A57: =A56+1 -> 30 | B57: ВСЕГО по разделу II с учетом районного коэффициента | C57: ОУ таб.3§2 | F57: =ROUND(G54+G55+G56,1)&"*1.08" -> 12089,9*1.08 | G57: =(G54+G55+G56)*1.08 -> 13057.06
A58: =A57+1 -> 31 | B58: Итого: | G58: =G33+G44+G57 -> 141638.48
A59: =A58+1 -> 32 | B59: Итого с индексом инфляции 71.21 | G59: =G58*71.21 -> 10086076
A60: =A59+1 -> 33 | B60: ВСЕГО ПО СМЕТЕ: | G60: =G59 -> 10086076

Sheet 2.1 Обслед
I1: Форма 2П
A3: =СВОД!C16 -> Смета №2.1
A4: на проектные работы
B6: Наименование объекта, стадии, | E6: ='Форма сводной сметы '!N9 -> «Модернизация существующей инфраструктуры транспортировки и налива фракции С5, с целью обеспечения налива дополнительного объема фракции С5, в количестве 6 000 т/мес.»
B7: этапа проектных работ
E8: =СВОД!B16 -> Обследование существующих зданий и сооружений
B10: Наименование проектной | E10: ='Форма сводной сметы '!F12 -> ОАО "СибНефтеТрансПроект"
B11: (изыскательской) организации
B13: Наименование организации | E13: ='Форма сводной сметы '!F15 -> ПАО «Нижнекамскнефтехим»
B14: заказчика
A16: № пп | B16: Характеристика предприятия, здания, сооружения или виды работ | D16: Номер частей, глав, таблиц, процентов, параграфов и пунктов указаний к разделу Справочника базовых цен на проектные и изыскательские работы для строительства | H16: Расчет стоимости: (a+bx)*Ki, или (объем строительно-монтажных работ) * проц./100 или количество x цена | I16: Стоимость, руб.
A17: 1 | B17: 2 | D17: 3 | H17: 4 | I17: 5
A18: Эстакады трубны
A19: 1 | B19: Выполнение инженерных обследований строительных конструкций каркасных одноэтажных зданий. II категория сложности работ. II категория сложности здания. Высота здания до 14 м. | D19: Справочник базовых цен на обмерные работы и обследования зданий и сооружений. 2016 г. Глава 3. Базовые цены на выполнение обмерных работ и обследований. Таблица 3. Базовые цены на выполнение инженерных обследований строительных конструкций одноэтажных зданий, п.12 B=0.4756 тыс.руб; Осн. показ. Х=916 (100 м3) Количество = 1 | H19: (A + B * Xзад) * Количество * Ктек * K1 (0 руб + 475.6 руб * 916) * 1 * 6.25 * 0.8 | I19: =ROUND((0 + 475.6 * 916) * 1 * 6.25 * 0.8,2) -> 2178248
B20: Коэффициенты
B21: инд.4кв.2024г.к 01.01.2001 на пр.раб. | D21: Ктек = 6.25 Письмо Минстроя России от 18.10.2024 №61327-ИФ/09
B22: Базовая цена для зданий и сооружений промышленного назначения (при пролетах более 12 м и высоте этажей более 6 м) определяется с применением коэффициента | D22: K1 = 0.8 Глава 2.1, п.2.1.2 (Ценообразующий)
A23: 2 | B23: Выполнение обмерных работ для каркасных одноэтажных зданий. II категория сложности работ. II категория сложности здания. Высота здания до 14 м. | D23: Справочник базовых цен на обмерные работы и обследования зданий и сооружений. 2016 г. Глава 3. Базовые цены на выполнение обмерных работ и обследований. Таблица 1. Базовые цены на выполнение обмерных работ для одноэтажных зданий, п.12 B=0.4136 тыс.руб; Осн. показ. Х=916 (100 м3) Количество = 1 | H23: (A + B * Xзад) * Количество * Ктек * K1 (0 руб + 413.6 руб * 916) * 1 * 6.25 * 0.8 | I23: =ROUND((0 + 413.6 * 916) * 1 * 6.25 * 0.8,2) -> 1894288
B24: Коэффициенты
B25: инд.4кв.2024г.к 01.01.2001 на пр.раб. | D25: Ктек = 6.25 Письмо Минстроя России от 18.10.2024 №61327-ИФ/09
B26: Базовая цена для зданий и сооружений промышленного назначения (при пролетах более 12 м и высоте этажей более 6 м) определяется с применением коэффициента | D26: K1 = 0.8 Глава 2.1, п.2.1.2 (Ценообразующий)
A27: 3 | B27: Выполнение инженерных обследований строительных конструкций каркасных одноэтажных зданий. II категория сложности работ. II категория сложности здания. Высота здания до 13 м. | D27: Справочник базовых цен на обмерные работы и обследования зданий и сооружений. 2016 г. Глава 3. Базовые цены на выполнение обмерных работ и обследований. Таблица 3. Базовые цены на выполнение инженерных обследований строительных конструкций одноэтажных зданий, п.11 B=0.4926 тыс.руб; Осн. показ. Х=455 (100 м3) Количество = 1 | H27: (A + B * Xзад) * Количество * Ктек * K1 (0 руб + 492.6 руб * 455) * 1 * 6.25 * 0.8 | I27: =ROUND((0 + 492.6 * 455) * 1 * 6.25 * 0.8,2) -> 1120665
B28: Коэффициенты
B29: инд.4кв.2024г.к 01.01.2001 на пр.раб. | D29: Ктек = 6.25 Письмо Минстроя России от 18.10.2024 №61327-ИФ/09
B30: Базовая цена для зданий и сооружений промышленного назначения (при пролетах более 12 м и высоте этажей более 6 м) определяется с применением коэффициента | D30: K1 = 0.8 Глава 2.1, п.2.1.2 (Ценообразующий)
A31: 4 | B31: Выполнение обмерных работ для каркасных одноэтажных зданий. II категория сложности работ. II категория сложности здания. Высота здания до 13 м. | D31: Справочник базовых цен на обмерные работы и обследования зданий и сооружений. 2016 г. Глава 3. Базовые цены на выполнение обмерных работ и обследований. Таблица 1. Базовые цены на выполнение обмерных работ для одноэтажных зданий, п.11 B=0.4444 тыс.руб; Осн. показ. Х=455 (100 м3) Количество = 1 | H31: (A + B * Xзад) * Количество * Ктек * K1 (0 руб + 444.4 руб * 455) * 1 * 6.25 * 0.8 | I31: =ROUND((0 + 444.4 * 455) * 1 * 6.25 * 0.8,2) -> 1011010
B32: Коэффициенты
B33: инд.4кв.2024г.к 01.01.2001 на пр.раб. | D33: Ктек = 6.25 Письмо Минстроя России от 18.10.2024 №61327-ИФ/09
B34: Базовая цена для зданий и сооружений промышленного назначения (при пролетах более 12 м и высоте этажей более 6 м) определяется с применением коэффициента | D34: K1 = 0.8 Глава 2.1, п.2.1.2 (Ценообразующий)
A35: 5 | B35: Выполнение инженерных обследований строительных конструкций каркасных одноэтажных зданий. II категория сложности работ. II категория сложности здания. Высота здания до 4 м. | D35: Справочник базовых цен на обмерные работы и обследования зданий и сооружений. 2016 г. Глава 3. Базовые цены на выполнение обмерных работ и обследований. Таблица 3. Базовые цены на выполнение инженерных обследований строительных конструкций одноэтажных зданий, п.2 B=0.6432 тыс.руб; Осн. показ. Х=307 (100 м3) Количество = 1 | H35: (A + B * Xзад) * Количество * Ктек * K1 (0 руб + 643.2 руб * 307) * 1 * 6.25 * 0.8 | I35: =ROUND((0 + 643.2 * 307) * 1 * 6.25 * 0.8,2) -> 987312
B36: Коэффициенты
B37: инд.4кв.2024г.к 01.01.2001 на пр.раб. | D37: Ктек = 6.25 Письмо Минстроя России от 18.10.2024 №61327-ИФ/09
B38: Базовая цена для зданий и сооружений промышленного назначения (при пролетах более 12 м и высоте этажей более 6 м) определяется с применением коэффициента | D38: K1 = 0.8 Глава 2.1, п.2.1.2 (Ценообразующий)
A39: 6 | B39: Выполнение обмерных работ для каркасных одноэтажных зданий. II категория сложности работ. II категория сложности здания. Высота здания до 4 м. | D39: Справочник базовых цен на обмерные работы и обследования зданий и сооружений. 2016 г. Глава 3. Базовые цены на выполнение обмерных работ и обследований. Таблица 1. Базовые цены на выполнение обмерных работ для одноэтажных зданий, п.2 B=0.7186 тыс.руб; Осн. показ. Х=307 (100 м3) Количество = 1 | H39: (A + B * Xзад) * Количество * Ктек * K1 (0 руб + 718.6 руб * 307) * 1 * 6.25 * 0.8 | I39: =ROUND((0 + 718.6 * 307) * 1 * 6.25 * 0.8,2) -> 1103051
B40: Коэффициенты
B41: инд.4кв.2024г.к 01.01.2001 на пр.раб. | D41: Ктек = 6.25 Письмо Минстроя России от 18.10.2024 №61327-ИФ/09
B42: Базовая цена для зданий и сооружений промышленного назначения (при пролетах более 12 м и высоте этажей более 6 м) определяется с применением коэффициента | D42: K1 = 0.8 Глава 2.1, п.2.1.2 (Ценообразующий)
A43: Насосная Т-8/2
A44: 7 | B44: Выполнение инженерных обследований строительных конструкций каркасных одноэтажных зданий. II категория сложности работ. II категория сложности здания. Высота здания до 12 м. | D44: Справочник базовых цен на обмерные работы и обследования зданий и сооружений. 2016 г. Глава 3. Базовые цены на выполнение обмерных работ и обследований. Таблица 3. Базовые цены на выполнение инженерных обследований строительных конструкций одноэтажных зданий, п.10 B=0.509 тыс.руб; Осн. показ. Х=131 (100 м3) Количество = 1 | H44: (A + B * Xзад) * Количество * Ктек * K1 (0 руб + 509 руб * 131) * 1 * 6.25 * 0.8 | I44: =ROUND((0 + 509 * 131) * 1 * 6.25 * 0.8,2) -> 333395
B45: Коэффициенты
B46: инд.4кв.2024г.к 01.01.2001 на пр.раб. | D46: Ктек = 6.25 Письмо Минстроя России от 18.10.2024 №61327-ИФ/09
B47: Базовая цена для зданий и сооружений промышленного назначения (при пролетах более 12 м и высоте этажей более 6 м) определяется с применением коэффициента | D47: K1 = 0.8 Глава 2.1, п.2.1.2 (Ценообразующий)
A48: 8 | B48: Выполнение обмерных работ для каркасных одноэтажных зданий. II категория сложности работ. II категория сложности здания. Высота здания до 12 м. | D48: Справочник базовых цен на обмерные работы и обследования зданий и сооружений. 2016 г. Глава 3. Базовые цены на выполнение обмерных работ и обследований. Таблица 1. Базовые цены на выполнение обмерных работ для одноэтажных зданий, п.10 B=0.4756 тыс.руб; Осн. показ. Х=131 (100 м3) Количество = 1 | H48: (A + B * Xзад) * Количество * Ктек * K1 (0 руб + 475.6 руб * 131) * 1 * 6.25 * 0.8 | I48: =ROUND((0 + 475.6 * 131) * 1 * 6.25 * 0.8,2) -> 311518
B49: Коэффициенты
B50: инд.4кв.2024г.к 01.01.2001 на пр.раб. | D50: Ктек = 6.25 Письмо Минстроя России от 18.10.2024 №61327-ИФ/09
B51: Базовая цена для зданий и сооружений промышленного назначения (при пролетах более 12 м и высоте этажей более 6 м) определяется с применением коэффициента | D51: K1 = 0.8 Глава 2.1, п.2.1.2 (Ценообразующий)
A52: 9 | B52: Итого по смете: | I52: =ROUND((SUM($I$19:$I$48)),2) -> 8939487
B53: Всего по смете: | I53: =I52 -> 8939487

Sheet 3.1 ТХ
I1: Форма 2П
A3: =СВОД!C21 -> Смета №3.1
A4: на проектные работы
B6: Наименование объекта, стадии, | E6: ='Форма сводной сметы '!N9 -> «Модернизация существующей инфраструктуры транспортировки и налива фракции С5, с целью обеспечения налива дополнительного объема фракции С5, в количестве 6 000 т/мес.»
B7: этапа проектных работ
E8: =СВОД!B21 -> Технология
B10: Наименование проектной | E10: ='Форма сводной сметы '!F12 -> ОАО "СибНефтеТрансПроект"
B11: (изыскательской) организации
B13: Наименование организации | E13: ='Форма сводной сметы '!F15 -> ПАО «Нижнекамскнефтехим»
B14: заказчика
A16: № пп | B16: Характеристика предприятия, здания, сооружения или виды работ | D16: Номер частей, глав, таблиц, процентов, параграфов и пунктов указаний к разделу Справочника базовых цен на проектные и изыскательские работы для строительства | H16: Расчет стоимости: (a+bx)*Ki, или (объем строительно-монтажных работ) * проц./100 или количество x цена | I16: Стоимость, руб.
A17: 1 | B17: 2 | D17: 3 | H17: 4 | I17: 5
A18: Замена запорной арматуры - узел из 2 ед. для насосов Н-5, Н-6 в насосной ЭП-616
A19: 1 | B19: Здания и сооружения. Электрифицированные задвижки на сетях МЦК, сосредоточенные в одном месте | D19: Объекты нефтеперерабатывающей и нефтехимической промышленности. 2015 г. Таблица 8. Объекты подсобно-производственного, вспомогательного и общезаводского назначения, внутриплощадочные инженерные сети, схема планировочной организации земельного участка, п.1.93 A=16.5 тыс.руб.; B=7.7 тыс.руб.; Осн. показ. Х=2 (задвижка) Количество = 1 | H19: (A + B * Xзад) * Количество * Кст * Ктек * K1 (16500 руб + 7700 руб * 2) * 1 * 0.6 * 6.25 * 1.2 | I19: 143550
B20: Коэффициенты
B21: Стадия: Рабочая документация | D21: Кст = 0.6
B22: инд.4кв.2024г.к 01.01.2001 на пр.раб. | D22: Ктек = 6.25 Письмо Минстроя России от 18.10.2024 №61327-ИФ/09
B23: Цена разработки проектной и рабочей документации на реконструкцию действующих предприятий, цехов, зданий и сооружений определяется по ценам Справочников базовых цен на проектные работы для строительства. При этом при определении стоимости проектных работ от стоимости реконструкции применяется коэффициент | D23: K1 = 1.2 МУ 2009 г. Часть III п.3.4 (Ценообразующий)
A24: Замена участка трубопровода рег. № 2112х длиной 352 м. от ЭП-616 до ИП-10
A25: 2 | B25: Внутриплощадочные инженерные сети. Тепло-, газо-, материалопроводы на эстакадах. Длина трассы свыше 0.3 до 0.5 км. | D25: Объекты нефтеперерабатывающей и нефтехимической промышленности. 2015 г. Таблица 8. Объекты подсобно-производственного, вспомогательного и общезаводского назначения, внутриплощадочные инженерные сети, схема планировочной организации земельного участка, п.2.5 A=1712.5 тыс.руб.; B=1007.8 тыс.руб.; Осн. показ. Х=0.352 (км) Количество = 1 | H25: (A + B * Xзад) * Количество * Кст * Ктек * K1 (1712500 руб + 1007800 руб * 0.352) * 1 * 0.6 * 6.25 * 1.2 | I25: =9302605.2*0.8 -> 7442084.2
B26: Коэффициенты
B27: Стадия: Рабочая документация | D27: Кст = 0.6
B28: инд.4кв.2024г.к 01.01.2001 на пр.раб. | D28: Ктек = 6.25 Письмо Минстроя России от 18.10.2024 №61327-ИФ/09
B29: Цена разработки проектной и рабочей документации на реконструкцию действующих предприятий, цехов, зданий и сооружений определяется по ценам Справочников базовых цен на проектные работы для строительства. При этом при определении стоимости проектных работ от стоимости реконструкции применяется коэффициент | D29: K1 = 1.2 МУ 2009 г. Часть III п.3.4 (Ценообразующий)
A30: Замена расходомера с обвязкой на ИП-10
A31: 3 | B31: Здания и сооружения. Узлы коммерческого учета | D31: Объекты нефтеперерабатывающей и нефтехимической промышленности. 2015 г. Таблица 8. Объекты подсобно-производственного, вспомогательного и общезаводского назначения, внутриплощадочные инженерные сети, схема планировочной организации земельного участка, п.1.95 A=385 тыс.руб.; Количество = 1 (узел) | H31: A * Количество * Кст * Ктек * K1 385000 руб * 1 * 0.6 * 6.25 * 1.2 | I31: =1732500*0.3 -> 519750
B32: Коэффициенты
B33: Стадия: Рабочая документация | D33: Кст = 0.6
B34: инд.4кв.2024г.к 01.01.2001 на пр.раб. | D34: Ктек = 6.25 Письмо Минстроя России от 18.10.2024 №61327-ИФ/09
B35: Цена разработки проектной и рабочей документации на реконструкцию действующих предприятий, цехов, зданий и сооружений определяется по ценам Справочников базовых цен на проектные работы для строительства. При этом при определении стоимости проектных работ от стоимости реконструкции применяется коэффициент | D35: K1 = 1.2 МУ 2009 г. Часть III п.3.4 (Ценообразующий)
A36: Замена насосов - 2 ед. в насосной Т-8/2
A37: 4 | B37: Здания и сооружения. Насосная перекачки нефтепродуктов. Производительность свыше 100 до 1000 м3/час. | D37: Объекты нефтеперерабатывающей и нефтехимической промышленности. 2015 г. Таблица 8. Объекты подсобно-производственного, вспомогательного и общезаводского назначения, внутриплощадочные инженерные сети, схема планировочной организации земельного участка, п.1.45 A=609.6 тыс.руб.; B=0.54 тыс.руб.; Осн. показ. Х=280 (м3/час) Количество = 1 | H37: (A + B * Xзад) * Количество * Кст * Ктек * K1 (609600 руб + 540 руб * 280) * 1 * 0.6 * 6.25 * 1.2 | I37: =3423600 -> 3423600
B38: Коэффициенты
B39: Стадия: Рабочая документация | D39: Кст = 0.6
B40: инд.4кв.2024г.к 01.01.2001 на пр.раб. | D40: Ктек = 6.25 Письмо Минстроя России от 18.10.2024 №61327-ИФ/09
B41: Цена разработки проектной и рабочей документации на реконструкцию действующих предприятий, цехов, зданий и сооружений определяется по ценам Справочников базовых цен на проектные работы для строительства. При этом при определении стоимости проектных работ от стоимости реконструкции применяется коэффициент | D41: K1 = 1.2 МУ 2009 г. Часть III п.3.4 (Ценообразующий)
A42: Трубопроводы подключения к емкостям Е-16/1,2, емкости Е-2/1 длиной 409 м.
A43: 5 | B43: Внутриплощадочные инженерные сети. Тепло-, газо-, материалопроводы на эстакадах. Длина трассы свыше 0.3 до 0.5 км. | D43: Объекты нефтеперерабатывающей и нефтехимической промышленности. 2015 г. Таблица 8. Объекты подсобно-производственного, вспомогательного и общезаводского назначения, внутриплощадочные инженерные сети, схема планировочной организации земельного участка, п.2.5 A=1712.5 тыс.руб.; B=1007.8 тыс.руб.; Осн. показ. Х=0.409 (км) Количество = 1 | H43: (A + B * Xзад) * Количество * Кст * Ктек * K1 (1712500 руб + 1007800 руб * 0.409) * 1 * 0.6 * 6.25 * 1.2 | I43: =9561105.9*0.8 -> 7648884.7
B44: Коэффициенты
B45: Стадия: Рабочая документация | D45: Кст = 0.6
B46: инд.4кв.2024г.к 01.01.2001 на пр.раб. | D46: Ктек = 6.25 Письмо Минстроя России от 18.10.2024 №61327-ИФ/09
B47: Цена разработки проектной и рабочей документации на реконструкцию действующих предприятий, цехов, зданий и сооружений определяется по ценам Справочников базовых цен на проектные работы для строительства. При этом при определении стоимости проектных работ от стоимости реконструкции применяется коэффициент | D47: K1 = 1.2 МУ 2009 г. Часть III п.3.4 (Ценообразующий)
A49: Замена трубопровода от Т-8/2 до Т-6 длиной 4788 м.
A50: 6 | B50: Внутриплощадочные инженерные сети. Тепло-, газо-, материалопроводы на эстакадах. Длина трассы свыше 4 до 14 км. | D50: Объекты нефтеперерабатывающей и нефтехимической промышленности. 2015 г. Таблица 8. Объекты подсобно-производственного, вспомогательного и общезаводского назначения, внутриплощадочные инженерные сети, схема планировочной организации земельного участка, п.2.8 A=2371.02 тыс.руб.; B=570.24 тыс.руб.; Осн. показ. Х=4.788 (км) Количество = 1 | H50: (A + B * Xзад) * Количество * Кст * Ктек * K1 (2371020 руб + 570240 руб * 4.788) * 1 * 0.6 * 6.25 * 1.2 | I50: =22955981.04*0.6 -> 13773589
B51: Коэффициенты
B52: Стадия: Рабочая документация | D52: Кст = 0.6
B53: инд.4кв.2024г.к 01.01.2001 на пр.раб. | D53: Ктек = 6.25 Письмо Минстроя России от 18.10.2024 №61327-ИФ/09
B54: Цена разработки проектной и рабочей документации на реконструкцию действующих предприятий, цехов, зданий и сооружений определяется по ценам Справочников базовых цен на проектные работы для строительства. При этом при определении стоимости проектных работ от стоимости реконструкции применяется коэффициент | D54: K1 = 1.2 МУ 2009 г. Часть III п.3.4 (Ценообразующий)
A55: 7 | B55: Итого по смете: | I55: =I50+I43+I37+I31+I25+I19 -> 32951458
B56: Всего по смете: | I56: =I55 -> 32951458

Sheet 3.2 ЭС
I1: Форма 2П
A3: =СВОД!C22 -> Смета №3.2
A4: на проектные работы
B6: Наименование объекта, стадии, | E6: ='Форма сводной сметы '!N9 -> «Модернизация существующей инфраструктуры транспортировки и налива фракции С5, с целью обеспечения налива дополнительного объема фракции С5, в количестве 6 000 т/мес.»
B7: этапа проектных работ
E8: =СВОД!B22 -> Сети электроснабжения
B10: Наименование проектной | E10: ='Форма сводной сметы '!F12 -> ОАО "СибНефтеТрансПроект"
B11: (изыскательской) организации
B13: Наименование организации | E13: ='Форма сводной сметы '!F15 -> ПАО «Нижнекамскнефтехим»
B14: заказчика
A16: № пп | B16: Характеристика предприятия, здания, сооружения или виды работ | D16: Номер частей, глав, таблиц, процентов, параграфов и пунктов указаний к разделу Справочника базовых цен на проектные и изыскательские работы для строительства | H16: Расчет стоимости: (a+bx)*Ki, или (объем строительно-монтажных работ) * проц./100 или количество x цена | I16: Стоимость, руб.
A17: 1 | B17: 2 | D17: 3 | H17: 4 | I17: 5
A18: Проектирование системы бесперебойного питания
A19: 1 | B19: Электропитание приборов в газовых объектах | D19: Газооборудование и газоснабжение промышленных предприятий, зданий и сооружений. 2015 г. Таблица 19. Электроснабжение и молниезащита, п.1 A=11.083 тыс.руб; Количество = 6 (панель) | H19: A * Количество * Кст * Ктек 11083 руб * 6 * 0.6 * 6.25 | I19: =ROUND(11083 * 6 * 0.6 * 6.25,2) -> 249367.5
B20: Коэффициенты
B21: Стадия: Рабочая документация | D21: Кст = 0.6
B22: инд.4кв.2024г.к 01.01.2001 на пр.раб. | D22: Ктек = 6.25 Письмо Минстроя России от 18.10.2024 №61327-ИФ/09
A23: Установка низковольтных щитов управления (НКУ-0,4 кВ)
A24: 2 | B24: Установка щитов станции управления в здании. Размер свыше 25 до 30 м2. | D24: Объекты магистрального трубопроводного транспорта нефти. 2012 г. Таблица 4. Отдельные сооружения объектов магистрального трубопроводного транспорта нефти, п.24.4 A=42.24 тыс.руб; Количество = 1 (1 установка) | H24: A * Количество * Кст * Ктек 42240 руб * 1 * 0.6 * 6.25 | I24: =ROUND(42240 * 1 * 0.6 * 6.25,2) -> 158400
B25: Коэффициенты
B26: Стадия: Рабочая документация | D26: Кст = 0.6
B27: инд.4кв.2024г.к 01.01.2001 на пр.раб. | D27: Ктек = 6.25 Письмо Минстроя России от 18.10.2024 №61327-ИФ/09
A28: ЧРП
A29: 3 | B29: Частотно-регулируемый привод, расположенный в отдельном здании | D29: Объекты магистрального трубопроводного транспорта нефти. 2012 г. Таблица 4. Отдельные сооружения объектов магистрального трубопроводного транспорта нефти п.47 A=400.91 тыс.руб; Количество = 2 (1 сооружение) | H29: A * Количество * Кст * Ктек * K1 400910 руб * 2 * 0.6 * 6.25 * 0.5 | I29: =ROUND(400910 * 2 * 0.6 * 6.25 * 0.5,2) -> 1503412.5
B30: Коэффициенты
B31: Стадия: Рабочая документация | D31: Кст = 0.6
B32: инд.4кв.2024г.к 01.01.2001 на пр.раб. | D32: Ктек = 6.25 Письмо Минстроя России от 18.10.2024 №61327-ИФ/09
B33: Цена привязки типовой или повторно применяемой проектной документации с внесением в нее изменений в подземную и надземную часть определяется по ценам Справочников с применением коэффициента | D33: K1 = 0.5 МУ 2009 г. Часть III п.3.2 (Ценообразующий)
A34: Прокладка кабельных линий 0,4/0,23 кВ до потребителей
A35: 4 | B35: Внутриплощадочные инженерные сети. Электрокабельные сети, сети КиА, сети связи. В том числе: по непроходным кабельным эстакадам. | D35: Объекты нефтеперерабатывающей и нефтехимической промышленности. 2015 г. Таблица 8. Объекты подсобно-производственного, вспомогательного и общезаводского назначения, внутриплощадочные инженерные сети, схема планировочной организации земельного участка, п.2.10 B=433.69 тыс.руб.; Осн. показ. Х=0.5 (км) Количество = 1 | H35: (A + B * Xзад) * Количество * Кст * Ктек (0 руб + 433690 руб * 0.5) * 1 * 0.6 * 6.25 * 0.666 | I35: =ROUND((0 + 433690 * 0.5) * 1 * 0.6 * 6.25 * 0.666,2) -> 541570.39
B36: Коэффициенты
B37: Стадия: Рабочая документация | D37: Кст = 0.6
B38: инд.4кв.2024г.к 01.01.2001 на пр.раб. | D38: Ктек = 6.25 Письмо Минстроя России от 18.10.2024 №61327-ИФ/09
B39: Разделы документации
B40: 1. Инженерное оборудование. Технологические решения: система электроснабжения | D40: 0.666
A41: Проектирование заземляющего устройства зданий и сооружений
A42: 5 | B42: Объединенные заземляющие устройства нефтеперекачивающей станции и подстанции напряжением 110 кВ и выше с установкой выравнивающих и защитных контуров. Значения удельных сопротивлений грунта от 1 до 50000 Ом/см. | D42: Объекты магистрального трубопроводного транспорта нефти. 2012 г. Таблица 4. Отдельные сооружения объектов магистрального трубопроводного транспорта нефти, п.22.1 A=8.87 тыс.руб; Количество = 6 (1 объект) | H42: A * Количество * Кст * Ктек 8870 руб * 6 * 0.6 * 6.25 | I42: =ROUND(8870 * 6 * 0.6 * 6.25,2) -> 199575
B43: Коэффициенты
B44: Стадия: Рабочая документация | D44: Кст = 0.6
B45: инд.4кв.2024г.к 01.01.2001 на пр.раб. | D45: Ктек = 6.25 Письмо Минстроя России от 18.10.2024 №61327-ИФ/09
A46: Расчеты
A47: 6 | B47: Расчет токов короткого замыкания электрических сетей напряжением до 20 кВ. Радиальная секционированная электрическая сеть простой конфигурации с количеством выключателей до 5 шт. | D47: Объекты нефтеперерабатывающей и нефтехимической промышленности. 2015 г. Таблица 11. Трансформаторные подстанции и распределительные устройства, размещаемые на площадках взрывопожароопасных производств, п.17 A=2.64 тыс.руб.; Количество = 6 (линия) | H47: A * Количество * Кст * Ктек 2640 руб * 6 * 0.6 * 6.25 | I47: =ROUND(2640 * 6 * 0.6 * 6.25,2) -> 59400
B48: Коэффициенты
B49: Стадия: Рабочая документация | D49: Кст = 0.6
B50: инд.4кв.2024г.к 01.01.2001 на пр.раб. | D50: Ктек = 6.25 Письмо Минстроя России от 18.10.2024 №61327-ИФ/09
A51: 7 | B51: Итого по смете: | I51: =ROUND((SUM($I$19:$I$47)),2) -> 2711725.4
B52: Всего по смете: | I52: =I51 -> 2711725.4

Sheet 3.3 АСУТП
B1: 5
B4: =СВОД!C23 -> Смета №3.3
B5: =СВОД!B23 -> Автоматизированная система управления технологическим процессом (АСУ ТП)
B6: Наименование объекта | G6: ='Форма сводной сметы '!N9 -> «Модернизация существующей инфраструктуры транспортировки и налива фракции С5, с целью обеспечения налива дополнительного объема фракции С5, в количестве 6 000 т/мес.»
B8: Стадия | G8: Рабочая документация
B10: Наименование организации Заказчика | G10: ='Форма сводной сметы '!F15 -> ПАО «Нижнекамскнефтехим»
B11: Наименование проектной организации | G11: ='Форма сводной сметы '!F12 -> ОАО "СибНефтеТрансПроект"
B13: Смета составлена на основании "СБЦ на проектные работы в строительстве "Автоматизированные системы управления технологическими процессами (АСУТП)" (2016г.)
B15: 1. Краткая характеристика объекта автоматизации:
B16: Новое строительство
B17: Новое строительство
B18: Реконструкция, модернизация, тех. перевооружение
B19: Требование на разработку ТЗ к созданию АСУ ТП: | H19: Нет
H20: Да
H21: Нет
B22: Требуемые части документации АСУ ТП:
D23: ОР | E23: ОО | F23: ИО | G23: ТО | H23: МО | I23: ПО
D24: Да | E24: Нет | F24: Да | G24: Да | H24: Да | I24: Да
D25: Да | E25: Да | F25: Да | G25: Да | H25: Да | I25: Да
D26: Нет | E26: Нет | F26: Нет | G26: Нет | H26: Нет | I26: Нет
B27: 2. Исходные данные:
B28: Трудоемкость разработки ТЗ на создание АСУ ТП
B29: Основные факторы, определяющие трудоемкость разработки | M29: Количество баллов
B30: № пп | C30: Фактор | E30: Наименование | H30: Определение | M30: ТЗ
B31: 1 | C31: Ф1 | E31: Степень научно-технической новизны (ТОУ) | H31: I степень - ТОУ имеет действующие аналоги в России и, возможно за рубежом | M31: =IF(H19="Да",SUMIF($H32:$L35,$H31,M32:N35),0) -> 0
B32: 1.1 | H32: I степень - ТОУ имеет действующие аналоги в России и, возможно за рубежом | M32: 1
B33: 1.2 | H33: II степень - ТОУ имеет действующие аналоги только за рубежом | M33: 2
B34: 1.3 | H34: III степень - ни с конструкторской, ни с технологической точек зрения ТОУ не является принципиально новым объектом, но действующих аналогов не имеет | M34: 4
B35: 1.4 | H35: IV степень - с конструкторской и (или) технологической точек зрения ТОУ является принципиально новым объектом | M35: 8
B36: 2 | C36: Ф2 | E36: Характер протекания управляемого технологического процесса во времени | H36: Непрерывный (с длительным поддержанием режимов, близких к установившимся, и практически безостановочной подачей сырья и реагентов) | M36: =IF(H19="Да",SUMIF($H37:$L42,$H36,M37:N42),0) -> 0
B37: 2.1 | H37: Непрерывный (с длительным поддержанием режимов, близких к установившимся, и практически безостановочной подачей сырья и реагентов) | M37: 1
B38: 2.2 | H38: Полунепрерывный (непрерывный, с существенными для управления переходными режимами, вызванными либо добавками (заменами) сырья или реагентов, либо выдачей продукции) | M38: 2
B39: 2.3 | H39: Непрерывно-дискретный - I (сочетающий непрерывные и прерывистые режимы на различных стадиях процесса) | M39: 4
B40: 2.4 | H40: Непрерывно-дискретный - II (сочетающий непрерывные и прерывистые режимы с малой длительностью непрерывных режимов в аварийных условиях) | M40: 5
B41: 2.5 | H41: Циклический (прерывистый, с существенной для управления длительностью интервалов непрерывного функционирования и циклическим следованием интервалов с различными режимами) | M41: 4
B42: 2.6 | H42: Дискретный (прерывистый, с малой, несущественной для управления, длительностью непрерывных технологических операций) | M42: 3
B43: 3 | C43: Ф3 | E43: Количество технологических операций, выполняемых на ТОУ | H43: свыше 5 до 10 | M43: =IF(H19="Да",SUMIF($H44:$L51,$H43,M44:N51),0) -> 0
B44: 3.1 | H44: до 5 | M44: 1
B45: 3.2 | H45: свыше 5 до 10 | M45: 2
B46: 3.3 | H46: свыше 10 до 20 | M46: 4
B47: 3.4 | H47: свыше 20 до 35 | M47: 5
B48: 3.5 | H48: свыше 35 до 50 | M48: 7
B49: 3.6 | H49: свыше 50 до 70 | M49: 9
B50: 3.7 | H50: свыше 70 до 100 | M50: 10
B51: 3.8 | H51: за каждые 50 свыше 100 | M51: 11
B52: 4 | C52: Ф4 | E52: Количество переменных, характеризующих ТОУ | H52: свыше 20 до 50 | M52: =IF(H19="Да",SUMIF($H53:$L66,$H52,M53:N66),0) -> 0
B53: 4.1 | H53: до 20 | M53: 1
B54: 4.2 | H54: свыше 20 до 50 | M54: 2
B55: 4.3 | H55: свыше 50 до 100 | M55: 3
B56: 4.4 | H56: свыше 100 до 170 | M56: 4
B57: 4.5 | H57: свыше 170 до 250 | M57: 5
B58: 4.6 | H58: свыше 250 до 350 | M58: 6
B59: 4.7 | H59: свыше 350 до 470 | M59: 7
B60: 4.8 | H60: свыше 470 до 600 | M60: 8
B61: 4.9 | H61: свыше 600 до 800 | M61: 9
B62: 4.10 | H62: свыше 800 до 1000 | M62: 10
B63: 4.11 | H63: свыше 1000 до 1300 | M63: 11
B64: 4.12 | H64: свыше 1300 до 1600 | M64: 12
... B66: 4.14 | H66: за каждые 500 свыше 2000 | M66: 14
B67: 5 | L67: ИТОГО (ƩБч): | M67: =M31+M36+M43+M52 -> 0
B68: Трудоемкость разработки документации на АСУ ТП
B69: Основные факторы, определяющие трудоемкость разработки | M69: Количество баллов для частей проектной документации (Бч)
B70: № пп | C70: Фактор | E70: Наименование | H70: Определение | M70: ОР | N70: ОО | O70: ИО | P70: ТО | Q70: МО | R70: ПО
B71: 1 | C71: Ф2 | E71: Характер протекания управляемого технологического процесса во времени | H71: Непрерывный (с длительным поддержанием режимов, близких к установившимся, и практически безостановочной подачей сырья и реагентов) | M71: =IF(D24="Да",SUMIF($H72:$L77,$H71,M72:M77),0) -> 1 | N71: =IF(E24="Да",SUMIF($H72:$L77,$H71,N72:N77),0) -> 0 | O71: =IF(F24="Да",SUMIF($H72:$L77,$H71,O72:O77),0) -> 1 | P71: =IF(G24="Да",SUMIF($H72:$L77,$H71,P72:P77),0) -> 1 | Q71: =IF(H24="Да",SUMIF($H72:$L77,$H71,Q72:Q77),0) -> 1 | R71: =IF(I24="Да",SUMIF($H72:$L77,$H71,R72:R77),0) -> 1
B72: 1.1 | H72: Непрерывный (с длительным поддержанием режимов, близких к установившимся, и практически безостановочной подачей сырья и реагентов) | M72: 1 | N72: 1 | O72: 1 | P72: 1 | Q72: 1 | R72: 1
B73: 1.2 | H73: Полунепрерывный (непрерывный, с существенными для управления переходными режимами, вызванными либо добавками (заменами) сырья или реагентов, либо выдачей продукции) | M73: 2 | N73: 1 | O73: 2 | P73: 1 | Q73: 2 | R73: 2
B74: 1.3 | H74: Непрерывно-дискретный - I (сочетающий непрерывные и прерывистые режимы на различных стадиях процесса) | M74: 3 | N74: 3 | O74: 3 | P74: 3 | Q74: 3 | R74: 3
B75: 1.4 | H75: Непрерывно-дискретный - II (сочетающий непрерывные и прерывистые режимы с малой длительностью непрерывных режимов в аварийных условиях) | M75: 4 | N75: 3 | O75: 4 | P75: 3 | Q75: 4 | R75: 4
B76: 1.5 | H76: Циклический (прерывистый, с существенной для управления длительностью интервалов непрерывного функционирования и циклическим следованием интервалов с различными режимами) | M76: 3 | N76: 2 | O76: 3 | P76: 2 | Q76: 3 | R76: 3
B77: 1.6 | H77: Дискретный (прерывистый, с малой, несущественной для управления, длительностью непрерывных технологических операций) | M77: 2 | N77: 2 | O77: 2 | P77: 2 | Q77: 3 | R77: 3
B78: 2 | C78: Ф5 | E78: Количество технологических операций, контролируемых или управляемых АСУ ТП | H78: свыше 5 до 10 | M78: =IF(D24="Да",SUMIF($H79:$L85,$H78,M79:M85),0) -> 2 | N78: =IF(E24="Да",SUMIF($H79:$L85,$H78,N79:N85),0) -> 0 | O78: =IF(F24="Да",SUMIF($H79:$L85,$H78,O79:O85),0) -> 2 | P78: =IF(G24="Да",SUMIF($H79:$L85,$H78,P79:P85),0) -> 2 | Q78: =IF(H24="Да",SUMIF($H79:$L85,$H78,Q79:Q85),0) -> 2 | R78: =IF(I24="Да",SUMIF($H79:$L85,$H78,R79:R85),0) -> 2
B79: 2.1 | E79: За каждые 50 свыше 100 начисляется еще по баллу | H79: до 5 | M79: 1 | N79: 1 | O79: 1 | P79: 1 | Q79: 1 | R79: 1
B80: 2.2 | H80: свыше 5 до 10 | M80: 2 | N80: 2 | O80: 2 | P80: 2 | Q80: 2 | R80: 2
B81: 2.3 | H81: свыше 10 до 20 | M81: 3 | N81: 2 | O81: 3 | P81: 2 | Q81: 3 | R81: 3
B82: 2.4 | H82: свыше 20 до 35 | M82: 4 | N82: 3 | O82: 4 | P82: 3 | Q82: 4 | R82: 4
B83: 2.5 | H83: свыше 35 до 50 | M83: 5 | N83: 3 | O83: 5 | P83: 3 | Q83: 5 | R83: 5
B84: 2.6 | H84: свыше 50 до 70 | M84: 6 | N84: 4 | O84: 6 | P84: 4 | Q84: 6 | R84: 6
B85: 2.7 | H85: свыше 70 до 100 | M85: 7 | N85: 5 | O85: 7 | P85: 5 | Q85: 7 | R85: 7
B86: 3 | C86: Ф6 | E86: Степень развитости информационных функций АСУ ТП | H86: II степень - централизованный контроль и измерение параметров состояния ТОУ | M86: =IF(D24="Да",SUMIF($H87:$L90,$H86,M87:M90),0) -> 3 | N86: =IF(E24="Да",SUMIF($H87:$L90,$H86,N87:N90),0) -> 0 | O86: =IF(F24="Да",SUMIF($H87:$L90,$H86,O87:O90),0) -> 3 | P86: =IF(G24="Да",SUMIF($H87:$L90,$H86,P87:P90),0) -> 3 | Q86: =IF(H24="Да",SUMIF($H87:$L90,$H86,Q87:Q90),0) -> 3 | R86: =IF(I24="Да",SUMIF($H87:$L90,$H86,R87:R90),0) -> 3
B87: 3.1 | H87: I степень - параллельные контроль и измерение параметров состояния ТОУ | M87: 1 | N87: 1 | O87: 1 | P87: 1 | Q87: 1 | R87: 1
B88: 3.2 | H88: II степень - централизованный контроль и измерение параметров состояния ТОУ | M88: 3 | N88: 2 | O88: 3 | P88: 3 | Q88: 3 | R88: 3
B89: 3.3 | H89: III степень - косвенное измерение (вычисление) отдельных комплексных показателей функционирования ТОУ | M89: 6 | N89: 2 | O89: 6 | P89: 5 | Q89: 6 | R89: 6
B90: 3.4 | H90: IV степень - анализ и обобщенная оценка состояния процесса в целом по его модели (распознавание ситуаций, диагностика аварийных состояний, поиск "узкого места", прогноз хода процесса) | M90: 9 | N90: 3 | O90: 9 | P90: 8 | Q90: 9 | R90: 9
B91: 4 | C91: Ф7 | E91: Степень развитости управляющих функций АСУ ТП | H91: II степень - каскадное и (или) программное автоматическое регулирование или автоматическое программное логическое управление по "жесткому" циклу | M91: =IF(D24="Да",SUMIF($H92:$L98,$H91,M92:M98),0) -> 3 | N91: =IF(E24="Да",SUMIF($H92:$L98,$H91,N92:N98),0) -> 0 | O91: =IF(F24="Да",SUMIF($H92:$L98,$H91,O92:O98),0) -> 3 | P91: =IF(G24="Да",SUMIF($H92:$L98,$H91,P92:P98),0) -> 3 | Q91: =IF(H24="Да",SUMIF($H92:$L98,$H91,Q92:Q98),0) -> 3 | R91: =IF(I24="Да",SUMIF($H92:$L98,$H91,R92:R98),0) -> 3
B92: 7.1 | H92: I степень - одноконтурное автоматическое регулирование или автоматическое однотактное логическое управление (переключения, блокировки и тому подобное) | M92: 1 | N92: 1 | O92: 1 | P92: 1 | Q92: 1 | R92: 1
B93: 7.2 | H93: II степень - каскадное и (или) программное автоматическое регулирование или автоматическое программное логическое управление по "жесткому" циклу | M93: 3 | N93: 2 | O93: 3 | P93: 3 | Q93: 3 | R93: 3
B94: 7.3 | H94: III степень - многосвязное автоматическое регулирование или автоматическое программное логическое управление по циклу с разветвлениями | M94: 5 | N94: 2 | O94: 5 | P94: 5 | Q94: 5 | R94: 5
B95: 7.4 | H95: IV степень - оптимальное управление установившимися режимами (в статике) | M95: 6 | N95: 3 | O95: 7 | P95: 7 | Q95: 7 | R95: 7
B96: 7.5 | H96: V степень - оптимальное управление переходными процессами или процессом в целом (оптимизация в динамике) | M96: 8 | N96: 4 | O96: 10 | P96: 9 | Q96: 11 | R96: 11
B97: 7.6 | H97: VI степень - оптимальное управление быстропротекающими переходными процессами в аварийных условиях | M97: 9 | N97: 4 | O97: 11 | P97: 10 | Q97: 13 | R97: 13
B98: 7.7 | H98: VII степень - оптимальное управление с адаптацией (самообучением и изменением алгоритмов и параметров системы) | M98: 10 | N98: 5 | O98: 12 | P98: 11 | Q98: 14 | R98: 14
B99: 5 | C99: Ф8 | E99: Режим выполнения управляющих фукций АСУ ТП | H99: Автоматизированный диалоговый режим | M99: =IF(D24="Да",SUMIF($H100:$L104,$H99,M100:M104),0) -> 2 | N99: =IF(E24="Да",SUMIF($H100:$L104,$H99,N100:N104),0) -> 0 | O99: =IF(F24="Да",SUMIF($H100:$L104,$H99,O100:O104),0) -> 2 | P99: =IF(G24="Да",SUMIF($H100:$L104,$H99,P100:P104),0) -> 2 | Q99: =IF(H24="Да",SUMIF($H100:$L104,$H99,Q100:Q104),0) -> 3 | R99: =IF(I24="Да",SUMIF($H100:$L104,$H99,R100:R104),0) -> 3
B100: 5.1 | H100: Автоматизированный "ручной" режим | M100: 1 | N100: 1 | O100: 1 | P100: 1 | Q100: 1 | R100: 1
B101: 5.2 | H101: Автоматизированный режим "советчика" | M101: 1 | N101: 1 | O101: 2 | P101: 1 | Q101: 2 | R101: 2
B102: 5.3 | H102: Автоматизированный диалоговый режим | M102: 2 | N102: 2 | O102: 2 | P102: 2 | Q102: 3 | R102: 3
B103: 5.4 | H103: Автоматический режим косвенного управления | M103: 3 | N103: 2 | O103: 3 | P103: 4 | Q103: 4 | R103: 4
B104: 5.5 | H104: Автоматический режим прямого (непосредственного) цифрового (или аналого-цифрового) управления | M104: 5 | N104: 3 | O104: 5 | P104: 7 | Q104: 7 | R104: 7
B105: 6 | C105: Ф9 | E105: Количество переменных, измеряемых, контролируемых и регистрируемых АСУ ТП | H105: свыше 20 до 50 | M105: =IF(D24="Да",SUMIF($H106:$L119,$H105,M106:M119),0) -> 2 | N105: =IF(E24="Да",SUMIF($H106:$L119,$H105,N106:N119),0) -> 0 | O105: =IF(F24="Да",SUMIF($H106:$L119,$H105,O106:O119),0) -> 2 | P105: =IF(G24="Да",SUMIF($H106:$L119,$H105,P106:P119),0) -> 2 | Q105: =IF(H24="Да",SUMIF($H106:$L119,$H105,Q106:Q119),0) -> 2 | R105: =IF(I24="Да",SUMIF($H106:$L119,$H105,R106:R119),0) -> 2
B106: 6.1 | H106: до 20 | M106: 1 | N106: 1 | O106: 1 | P106: 1 | Q106: 1 | R106: 1
B107: 6.2 | H107: свыше 20 до 50 | M107: 2 | N107: 1 | O107: 2 | P107: 2 | Q107: 2 | R107: 2
...

Sheet ПромБез
I1: Форма 2П
A3: =СВОД!C24 -> Смета №3.4
A4: на проектные работы
B6: Наименование объекта, стадии, | E6: ='Форма сводной сметы '!N9 -> «Модернизация существующей инфраструктуры транспортировки и налива фракции С5, с целью обеспечения налива дополнительного объема фракции С5, в количестве 6 000 т/мес.»
B7: этапа проектных работ
E8: =СВОД!B24 -> Промышленная безопасность
B10: Наименование проектной | E10: ='Форма сводной сметы '!F12 -> ОАО "СибНефтеТрансПроект"
B11: (изыскательской) организации
B13: Наименование организации | E13: ='Форма сводной сметы '!F15 -> ПАО «Нижнекамскнефтехим»
B14: заказчика
A16: № пп | B16: Характеристика предприятия, здания, сооружения или виды работ | D16: Номер частей, глав, таблиц, процентов, параграфов и пунктов указаний к разделу Справочника базовых цен на проектные и изыскательские работы для строительства | H16: Расчет стоимости: (a+bx)*Ki, или (объем строительно-монтажных работ) * проц./100 или количество x цена | I16: Стоимость, руб.
A17: 1 | B17: 2 | D17: 3 | H17: 4 | I17: 5
A18: 1 | B18: Подраздел «Промышленная безопасность» | D18: Объекты магистрального трубопроводного транспорта нефти. 2012 г. Таблица 5. Раздел "Промышленная безопасность". Раздел "Мероприятия по гражданской обороне. Мероприятия по предупреждению чрезвычайных ситуаций природного и техногенного характера" (стадия "Проектная документация") п.3 A=144 тыс.руб; Количество = 1 (декларируемый объект) | H18: Полный комплекс работ (100%): A * Количество * Кст * Ктек 144000 руб * 1 * 1 * 6.25 | I18: =ROUND(144000 * 1 * 1 * 6.25,2) -> 900000
B19: Коэффициенты
B20: Стадия: Проектная документация | D20: Кст = 1
B21: инд.4кв.2024г.к 01.01.2001 на пр.раб. | D21: Ктек = 6.25 Письмо Минстроя России от 18.10.2024 №61327-ИФ/09
A22: 2 | B22: Итого по смете: | I22: =ROUND(($I$18),2) -> 900000
B23: Всего по смете: | I23: =I22 -> 900000

Sheet Расч
H1: Форма 3П
H2: Приложение № ___
H3: к договору №______________________
C4: СМЕТА на проектные работы № | D4: =СВОД!A25 -> 3.5
B6: Наименование предприятия, здания, сооружения:
B9: Стадия: | C9: этап:
B10: Проектная документация | C10: =СВОД!B25 -> Гидравлические расчеты
B11: Наименование организации исполнителя:
B12: ='Форма сводной сметы '!F12 -> ОАО "СибНефтеТрансПроект"
B13: Наименование организации заказчика:
B14: ='Форма сводной сметы '!F15 -> ПАО «Нижнекамскнефтехим»
B16: Раздел 1. Определение трудоемкости (трудозатрат) выполняемой работы
A18: № п/п | B18: Перечень выполняемых работ | C18: Исполнители | F18: Количество человеко-дней (гр.4 * гр.5) | G18: Средняя зарплата за 1 день | H18: Оплата труда (всего) (гр.6 * гр.7)
C19: должность | D19: Количество
D20: чел | E20: дн
A21: 1 | B21: 2 | C21: 3 | D21: 4 | E21: 5 | F21: 6 | G21: 7 | H21: 8
A22: Разработка документации (вид работ/сооружение) | K22: среднечасов. ЗП
A23: 1 | B23: =C10 -> Гидравлические расчеты | C23: Начальник отдела | D23: 1 | E23: 1 | F23: =E23*D23 -> 1 | G23: =K23*8 -> 40079.68 | H23: =F23*G23 -> 40079.68 | J23: Начальник отдела | K23: 5009.96
C24: Главный специалист | D24: 1 | E24: 1 | F24: =E24*D24 -> 1 | G24: =K24*8 -> 30059.76 | H24: =F24*G24 -> 30059.76 | J24: Главный специалист | K24: 3757.47
C25: Руководитель группы | D25: 1 | E25: 0 | F25: =E25*D25 -> 0 | G25: =K25*8 -> 27053.76 | H25: =F25*G25 -> 0 | J25: Руководитель группы | K25: 3381.72
C26: Ведущий инженер | D26: 1 | E26: 8 | F26: =E26*D26 -> 8 | G26: =K26*8 -> 20039.84 | H26: =F26*G26 -> 160318.72 | J26: Ведущий инженер | K26: 2504.98
C27: Инженер 1-й категории | D27: 1 | E27: 9 | F27: =E27*D27 -> 9 | G27: =K27*8 -> 18063.84 | H27: =F27*G27 -> 162574.56 | J27: Инженер 1-й категории | K27: 2257.98
C28: Инженер 2-й категории | D28: 1 | E28: 0 | F28: =E28*D28 -> 0 | G28: =K28*8 -> 17033.84 | H28: =F28*G28 -> 0 | J28: Инженер 2-й категории | K28: 2129.23
C29: Инженер 3-й категории | D29: 1 | E29: 0 | F29: =E29*D29 -> 0 | G29: =K29*8 -> 16031.84 | H29: =F29*G29 -> 0 | J29: Инженер 3-й категории | K29: 2003.98
C30: Инженер | D30: 1 | E30: 0 | F30: =E30*D30 -> 0 | G30: =K30*8 -> 14528.84 | H30: =F30*G30 -> 0 | J30: Инженер | K30: 1816.105
B31: Итого з/п непосредственных исполнителей | H31: =SUM(H23:H30) -> 393032.72
B32: Раздел 2. Определение стоимости работ, перечисленных в разделе 1
A33: № п/п | B33: Наименование показателей | G33: Единица измерения | H33: Сумма
A34: 1 | B34: 2 | G34: 3 | H34: 4
A35: .1 | B35: Итого заработная плата непосредственных исполнителей (итог по гр.8 раздела 1) | G35: руб. | H35: =H31 -> 393032.72
A36: .2 | B36: Общая стоимость работы (стр.1) | G36: руб. | H36: =H35 -> 393032.72
A37: .3 | B37: НДС 20% | G37: руб. | H37: =H36*0.2 -> 78606.544
A38: .4 | B38: Всего с НДС | G38: руб. | H38: =H36+H37 -> 471639.26
B39: Средняя стоимость ч.ч. | G39: руб. | H39: =H31/SUM(F23:F30)/8 -> 2585.7416

Sheet РД_BOQ 
C1: Форма для заполнения по тендерной процедуре №ТП №2089458
A2: Смета №01 объекту
A3: ='Форма сводной сметы '!N9 -> «Модернизация существующей инфраструктуры транспортировки и налива фракции С5, с целью обеспечения налива дополнительного объема фракции С5, в количестве 6 000 т/мес.»
C5: (заполняется участником)
A6: № п/п | B6: Наименование показателей | C6: Стоимость, руб. без НДС | D6: Трудозатраты чел.час | E6: Трудозатраты чел.дни | F6: Наименование подрядчика | G6: Обоснование расчета*
G8: Должность | H8: Оценка количества листов документации | J8: чел. | K8: Дней | L8: Дней | M8: Часов | N8: Ст-ть чел. часа (руб.) без НДС | O8: Итого Ст-ть (руб.) без НДС | P8: Итого кол. чел.час
H9: (текст.) ф.А4 | I9: (граф.) ф.А1
A10: Соответствие техническому заданию стадии ПД | R10: K= | S10: 1
A11: 1. | B11: Смета на строительство объектов капитального строительства | C11: =SUM(C12:C67) -> 7166243.6 | D11: =SUM(D12:D67) -> 2098 | E11: =SUM(E12:E67) -> 262.25
A12: 1.1. | B12: Выполнить мониторинг рынка поставщиков и предоставить данные с учетом доставки до г. Нижнекамск: - по основным (ценообразующим) материалам - по вспомогательному оборудованию | C12: =SUM(O12:O18) -> 586165.04 | D12: =SUM(P12:P18) -> 164 | E12: =D12/8 -> 20.5 | G12: ГИП | H12: =ROUND(C12/(4*3200),0) -> 46 | J12: 1 | K12: =L12*$S$10 -> 0.5 | L12: 0.5 | M12: 8 | N12: 5009.96 | O12: =N12*J12*K12*M12 -> 20039.84 | P12: =J12*K12*M12 -> 4
G13: Нач. отдела | J13: 5 | K13: =L13*$S$10 -> 1 | L13: 1 | M13: 8 | N13: 4508.96 | O13: =N13*J13*K13*M13 -> 180358.4 | P13: =J13*K13*M13 -> 40
G14: Гл. специалист | J14: 5 | K14: =L14*$S$10 -> 1 | L14: 1 | M14: 8 | N14: 3757.47 | O14: =N14*J14*K14*M14 -> 150298.8 | P14: =J14*K14*M14 -> 40
G15: Рук. Группы | J15: 5 | K15: =L15*$S$10 -> 1 | L15: 1 | M15: 8 | N15: 3381.72 | O15: =N15*J15*K15*M15 -> 135268.8 | P15: =J15*K15*M15 -> 40
G16: Вед. инженер | J16: 5 | K16: =L16*$S$10 -> 1 | L16: 1 | M16: 8 | N16: 2504.98 | O16: =N16*J16*K16*M16 -> 100199.2 | P16: =J16*K16*M16 -> 40
G17: Старший инженер | K17: =L17*$S$10 -> 0 | M17: 8 | N17: 2254.48 | O17: =N17*J17*K17*M17 -> 0 | P17: =J17*K17*M17 -> 0
G18: Инженер | K18: =L18*$S$10 -> 0 | M18: 8 | N18: 2129.23 | O18: =N18*J18*K18*M18 -> 0 | P18: =J18*K18*M18 -> 0
A19: 1.2. | B19: Предоставить ведомости объемов работ в формате BOQ (Описание выполняемых работ/объемы) | C19: =SUM(O19:O25) -> 893776.4 | D19: =SUM(P19:P25) -> 276 | E19: =D19/8 -> 34.5 | G19: ГИП | H19: =ROUND(C19/(4*3200),0) -> 70 | J19: 1 | K19: =L19*$S$10 -> 0.5 | L19: 0.5 | M19: 8 | N19: 5009.96 | O19: =N19*J19*K19*M19 -> 20039.84 | P19: =J19*K19*M19 -> 4
G20: Нач. отдела | J20: 5 | K20: =L20*$S$10 -> 1 | L20: 1 | M20: 8 | N20: 4508.96 | O20: =N20*J20*K20*M20 -> 180358.4 | P20: =J20*K20*M20 -> 40
G21: Гл. специалист | J21: 5 | K21: =L21*$S$10 -> 1 | L21: 1 | M21: 8 | N21: 3757.47 | O21: =N21*J21*K21*M21 -> 150298.8 | P21: =J21*K21*M21 -> 40
G22: Рук. Группы | J22: 5 | K22: =L22*$S$10 -> 2 | L22: 2 | M22: 8 | N22: 3381.72 | O22: =N22*J22*K22*M22 -> 270537.6 | P22: =J22*K22*M22 -> 80
G23: Вед. инженер | J23: 5 | K23: =L23*$S$10 -> 2 | L23: 2 | M23: 8 | N23: 2504.98 | O23: =N23*J23*K23*M23 -> 200398.4 | P23: =J23*K23*M23 -> 80
G24: Старший инженер | J24: 4 | K24: =L24*$S$10 -> 1 | L24: 1 | M24: 8 | N24: 2254.48 | O24: =N24*J24*K24*M24 -> 72143.36 | P24: =J24*K24*M24 -> 32
G25: Инженер | K25: =L25*$S$10 -> 0 | M25: 8 | N25: 2129.23 | O25: =N25*J25*K25*M25 -> 0 | P25: =J25*K25*M25 -> 0
A26: 1.3. | B26: Предоставить таблицу физических объемов сводную / по титульно | C26: =SUM(O26:O32) -> 677346.4 | D26: =SUM(P26:P32) -> 200 | E26: =D26/8 -> 25 | G26: ГИП | H26: =ROUND(C26/(4*3200),0) -> 53 | J26: 1 | K26: =L26*$S$10 -> 1 | L26: 1 | M26: 8 | N26: 5009.96 | O26: =N26*J26*K26*M26 -> 40079.68 | P26: =J26*K26*M26 -> 8
G27: Нач. отдела | J27: 6 | K27: =L27*$S$10 -> 1 | L27: 1 | M27: 8 | N27: 4508.96 | O27: =N27*J27*K27*M27 -> 216430.08 | P27: =J27*K27*M27 -> 48
G28: Гл. специалист | J28: 6 | K28: =L28*$S$10 -> 1 | L28: 1 | M28: 8 | N28: 3757.47 | O28: =N28*J28*K28*M28 -> 180358.56 | P28: =J28*K28*M28 -> 48
G29: Рук. Группы | K29: =L29*$S$10 -> 0 | M29: 8 | N29: 3381.72 | O29: =N29*J29*K29*M29 -> 0 | P29: =J29*K29*M29 -> 0
G30: Вед. инженер | J30: 6 | K30: =L30*$S$10 -> 2 | L30: 2 | M30: 8 | N30: 2504.98 | O30: =N30*J30*K30*M30 -> 240478.08 | P30: =J30*K30*M30 -> 96
G31: Старший инженер | K31: =L31*$S$10 -> 0 | M31: 8 | N31: 2254.48 | O31: =N31*J31*K31*M31 -> 0 | P31: =J31*K31*M31 -> 0
G32: Инженер | K32: =L32*$S$10 -> 0 | M32: 8 | N32: 2129.23 | O32: =N32*J32*K32*M32 -> 0 | P32: =J32*K32*M32 -> 0
A33: 1.4. | B33: Предоставить ведомости материалов с построчной стоимостью ресурсов (BOM) | C33: =SUM(O33:O39) -> 1913804.2 | D33: =SUM(P33:P39) -> 524 | E33: =D33/8 -> 65.5 | G33: ГИП | H33: =ROUND(C33/(4*3200),0) -> 150 | J33: 1 | K33: =L33*$S$10 -> 0.5 | L33: 0.5 | M33: 8 | N33: 5009.96 | O33: =N33*J33*K33*M33 -> 20039.84 | P33: =J33*K33*M33 -> 4
G34: Нач. отдела | J34: 5 | K34: =L34*$S$10 -> 2 | L34: 2 | M34: 8 | N34: 4508.96 | O34: =N34*J34*K34*M34 -> 360716.8 | P34: =J34*K34*M34 -> 80
G35: Гл. специалист | J35: 5 | K35: =L35*$S$10 -> 9 | L35: 9 | M35: 8 | N35: 3757.47 | O35: =N35*J35*K35*M35 -> 1352689.2 | P35: =J35*K35*M35 -> 360
G36: Рук. Группы | K36: =L36*$S$10 -> 0 | M36: 8 | N36: 3381.72 | O36: =N36*J36*K36*M36 -> 0 | P36: =J36*K36*M36 -> 0
G37: Вед. инженер | K37: =L37*$S$10 -> 0 | M37: 8 | N37: 2504.98 | O37: =N37*J37*K37*M37 -> 0 | P37: =J37*K37*M37 -> 0
G38: Старший инженер | J38: 5 | K38: =L38*$S$10 -> 2 | L38: 2 | M38: 8 | N38: 2254.48 | O38: =N38*J38*K38*M38 -> 180358.4 | P38: =J38*K38*M38 -> 80
G39: Инженер | K39: =L39*$S$10 -> 0 | M39: 8 | N39: 2129.23 | O39: =N39*J39*K39*M39 -> 0 | P39: =J39*K39*M39 -> 0
A40: 1.5. | B40: Предоставить ведомости оборудования с построчной стоимостью ресурсов (BOE) | C40: =SUM(O40:O46) -> 1068123.3 | D40: =SUM(P40:P46) -> 272 | E40: =D40/8 -> 34 | G40: ГИП | H40: =ROUND(C40/(4*3200),0) -> 83 | J40: 1 | K40: =L40*$S$10 -> 1 | L40: 1 | M40: 8 | N40: 5009.96 | O40: =N40*J40*K40*M40 -> 40079.68 | P40: =J40*K40*M40 -> 8
G41: Нач. отдела | J41: 3 | K41: =L41*$S$10 -> 2 | L41: 2 | M41: 8 | N41: 4508.96 | O41: =N41*J41*K41*M41 -> 216430.08 | P41: =J41*K41*M41 -> 48
G42: Гл. специалист | J42: 3 | K42: =L42*$S$10 -> 9 | L42: 9 | M42: 8 | N42: 3757.47 | O42: =N42*J42*K42*M42 -> 811613.52 | P42: =J42*K42*M42 -> 216
G43: Рук. Группы | K43: =L43*$S$10 -> 0 | M43: 8 | N43: 3381.72 | O43: =N43*J43*K43*M43 -> 0 | P43: =J43*K43*M43 -> 0
G44: Вед. инженер | K44: =L44*$S$10 -> 0 | M44: 8 | N44: 2504.98 | O44: =N44*J44*K44*M44 -> 0 | P44: =J44*K44*M44 -> 0
G45: Старший инженер | K45: =L45*$S$10 -> 0 | M45: 8 | N45: 2254.48 | O45: =N45*J45*K45*M45 -> 0 | P45: =J45*K45*M45 -> 0
G46: Инженер | K46: =L46*$S$10 -> 0 | M46: 8 | N46: 2129.23 | O46: =N46*J46*K46*M46 -> 0 | P46: =J46*K46*M46 -> 0
A47: 1.6. | B47: Расчитать количество стыков / дюйм диаметров по проекту (с приведением методики и пояснения расчетов) | C47: =SUM(O47:O53) -> 608208.96 | D47: =SUM(P47:P53) -> 198 | E47: =D47/8 -> 24.75 | G47: ГИП | H47: =ROUND(C47/(4*3200),0) -> 48 | J47: 1 | K47: 0.25 | L47: 0.25 | M47: 8 | N47: 5009.96 | O47: =N47*J47*K47*M47 -> 10019.92 | P47: =J47*K47*M47 -> 2
G48: Нач. отдела | J48: 1 | K48: =L48*$S$10 -> 0.5 | L48: 0.5 | M48: 8 | N48: 4508.96 | O48: =N48*J48*K48*M48 -> 18035.84 | P48: =J48*K48*M48 -> 4
G49: Гл. специалист | J49: 1 | K49: =L49*$S$10 -> 5 | L49: 5 | M49: 8 | N49: 3757.47 | O49: =N49*J49*K49*M49 -> 150298.8 | P49: =J49*K49*M49 -> 40
G50: Рук. Группы | J50: 1 | K50: =L50*$S$10 -> 7 | L50: 7 | M50: 8 | N50: 3381.72 | O50: =N50*J50*K50*M50 -> 189376.32 | P50: =J50*K50*M50 -> 56
G51: Вед. инженер | J51: 1 | K51: =L51*$S$10 -> 12 | L51: 12 | M51: 8 | N51: 2504.98 | O51: =N51*J51*K51*M51 -> 240478.08 | P51: =J51*K51*M51 -> 96
G52: Старший инженер | K52: 0 | M52: 8 | N52: 2254.48 | O52: =N52*J52*K52*M52 -> 0 | P52: =J52*K52*M52 -> 0
G53: Инженер | K53: 0 | M53: 8 | N53: 2129.23 | O53: =N53*J53*K53*M53 -> 0 | P53: =J53*K53*M53 -> 0
A54: 1.7. | B54: Предоставить пусконаладочные работы (ПНР, ППНР) | C54: =SUM(O54:O60) -> 977943.2 | D54: =SUM(P54:P60) -> 324 | E54: =D54/8 -> 40.5 | G54: ГИП | H54: =ROUND(C54/(4*3200),0) -> 76 | J54: 1 | K54: =L54*$S$10 -> 0.5 | L54: 0.5 | M54: 8 | N54: 5009.96 | O54: =N54*J54*K54*M54 -> 20039.84 | P54: =J54*K54*M54 -> 4
G55: Нач. отдела | J55: 2 | K55: =L55*$S$10 -> 2 | L55: 2 | M55: 8 | N55: 4508.96 | O55: =N55*J55*K55*M55 -> 144286.72 | P55: =J55*K55*M55 -> 32
G56: Гл. специалист | K56: =L56*$S$10 -> 0 | M56: 8 | N56: 3757.47 | O56: =N56*J56*K56*M56 -> 0 | P56: =J56*K56*M56 -> 0
G57: Рук. Группы | J57: 2 | K57: =L57*$S$10 -> 10 | L57: 10 | M57: 8 | N57: 3381.72 | O57: =N57*J57*K57*M57 -> 541075.2 | P57: =J57*K57*M57 -> 160
G58: Вед. инженер | K58: =L58*$S$10 -> 0 | M58: 8 | N58: 2504.98 | O58: =N58*J58*K58*M58 -> 0 | P58: =J58*K58*M58 -> 0
G59: Старший инженер | K59: =L59*$S$10 -> 0 | M59: 8 | N59: 2254.48 | O59: =N59*J59*K59*M59 -> 0 | P59: =J59*K59*M59 -> 0
G60: Инженер | J60: 4 | K60: =L60*$S$10 -> 4 | L60: 4 | M60: 8 | N60: 2129.23 | O60: =N60*J60*K60*M60 -> 272541.44 | P60: =J60*K60*M60 -> 128
A61: 1.8. | B61: Предоставить пояснительную записку | C61: =SUM(O61:O67) -> 440876.08 | D61: =SUM(P61:P67) -> 140 | E61: =D61/8 -> 17.5 | G61: ГИП | H61: =ROUND(C61/(4*3200),0) -> 34 | J61: 1 | K61: =L61*$S$10 -> 1.5 | L61: 1.5 | M61: 8 | N61: 5009.96 | O61: =N61*J61*K61*M61 -> 60119.52 | P61: =J61*K61*M61 -> 12
G62: Нач. отдела | J62: 1 | K62: =L62*$S$10 -> 2 | L62: 2 | M62: 8 | N62: 4508.96 | O62: =N62*J62*K62*M62 -> 72143.36 | P62: =J62*K62*M62 -> 16
G63: Гл. специалист | K63: =L63*$S$10 -> 0 | M63: 8 | N63: 3757.47 | O63: =N63*J63*K63*M63 -> 0 | P63: =J63*K63*M63 -> 0
G64: Рук. Группы | J64: 1 | K64: =L64*$S$10 -> 7 | L64: 7 | M64: 8 | N64: 3381.72 | O64: =N64*J64*K64*M64 -> 189376.32 | P64: =J64*K64*M64 -> 56
G65: Вед. инженер | K65: =L65*$S$10 -> 0 | M65: 8 | N65: 2504.98 | O65: =N65*J65*K65*M65 -> 0 | P65: =J65*K65*M65 -> 0
G66: Старший инженер | K66: =L66*$S$10 -> 0 | M66: 8 | N66: 2254.48 | O66: =N66*J66*K66*M66 -> 0 | P66: =J66*K66*M66 -> 0
G67: Инженер | J67: 1 | K67: =L67*$S$10 -> 7 | L67: 7 | M67: 8 | N67: 2129.23 | O67: =N67*J67*K67*M67 -> 119236.88 | P67: =J67*K67*M67 -> 56
A68: 2. | B68: Документация РД | C68: =SUM(C69:C110) -> 46264445 | D68: =SUM(D69:D110) -> 17448 | E68: =SUM(E69:E110) -> 2181
A69: 2.1. | B69: Пояснительная записка | C69: =SUM(O69:O75) -> 6969851.8 | D69: =SUM(P69:P75) -> 2704 | E69: =D69/8 -> 338 | G69: ГИП | H69: 85 | J69: 1 | K69: =L69*$S$10 -> 2 | L69: 2 | M69: 8 | N69: 5009.96 | O69: =N69*J69*K69*M69 -> 80159.36 | P69: =J69*K69*M69 -> 16
G70: Нач. отдела | J70: 6 | K70: =L70*$S$10 -> 1 | L70: 1 | M70: 8 | N70: 4508.96 | O70: =N70*J70*K70*M70 -> 216430.08 | P70: =J70*K70*M70 -> 48
G71: Гл. специалист | J71: 6 | K71: =L71*$S$10 -> 5 | L71: 5 | M71: 8 | N71: 3757.47 | O71: =N71*J71*K71*M71 -> 901792.8 | P71: =J71*K71*M71 -> 240
G72: Рук. Группы | J72: 6 | K72: =L72*$S$10 -> 5 | L72: 5 | M72: 8 | N72: 3381.72 | O72: =N72*J72*K72*M72 -> 811612.8 | P72: =J72*K72*M72 -> 240
G73: Вед. инженер | J73: 6 | K73: =L73*$S$10 -> 15 | L73: 15 | M73: 8 | N73: 2504.98 | O73: =N73*J73*K73*M73 -> 1803585.6 | P73: =J73*K73*M73 -> 720
G74: Старший инженер | J74: 6 | K74: =L74*$S$10 -> 15 | L74: 15 | M74: 8 | N74: 2254.48 | O74: =N74*J74*K74*M74 -> 1623225.6 | P74: =J74*K74*M74 -> 720
G75: Инженер | J75: 6 | K75: =L75*$S$10 -> 15 | L75: 15 | M75: 8 | N75: 2129.23 | O75: =N75*J75*K75*M75 -> 1533045.6 | P75: =J75*K75*M75 -> 720
A76: 2.2 | B76: Техническое перевооружение насосной склада производства №2111 (ЭП-616) : GP-Генеральный план, ER - Электротехнические решения, KJ1 - Конструкции железобетонные, AK - Автоматизация комплексная, KM1 - Конструкции металлические, TH - Технология производства | C76: =SUM(O76:O82) -> 10396663 | D76: =SUM(P76:P82) -> 3664 | E76: =D76/8 -> 458 | G76: ГИП | H76: 85 | J76: 1 | K76: =L76*$S$10 -> 2 | L76: 2 | M76: 8 | N76: 5009.96 | O76: =N76*J76*K76*M76 -> 80159.36 | P76: =J76*K76*M76 -> 16
G77: Нач. отдела | J77: 6 | K77: =L77*$S$10 -> 1 | L77: 1 | M77: 8 | N77: 4508.96 | O77: =N77*J77*K77*M77 -> 216430.08 | P77: =J77*K77*M77 -> 48
G78: Гл. специалист | J78: 6 | K78: =L78*$S$10 -> 15 | L78: 15 | M78: 8 | N78: 3757.47 | O78: =N78*J78*K78*M78 -> 2705378.4 | P78: =J78*K78*M78 -> 720
G79: Рук. Группы | J79: 6 | K79: =L79*$S$10 -> 15 | L79: 15 | M79: 8 | N79: 3381.72 | O79: =N79*J79*K79*M79 -> 2434838.4 | P79: =J79*K79*M79 -> 720
G80: Вед. инженер | J80: 6 | K80: =L80*$S$10 -> 15 | L80: 15 | M80: 8 | N80: 2504.98 | O80: =N80*J80*K80*M80 -> 1803585.6 | P80: =J80*K80*M80 -> 720
G81: Старший инженер | J81: 6 | K81: =L81*$S$10 -> 15 | L81: 15 | M81: 8 | N81: 2254.48 | O81: =N81*J81*K81*M81 -> 1623225.6 | P81: =J81*K81*M81 -> 720
G82: Инженер | J82: 6 | K82: =L82*$S$10 -> 15 | L82: 15 | M82: 8 | N82: 2129.23 | O82: =N82*J82*K82*M82 -> 1533045.6 | P82: =J82*K82*M82 -> 720
A83: 2.3. | B83: Техническое перевооружение участка эстакады от ИП-10 до Т-8/2 (тр-д рег№ 345: ER - Электротехнические решения, KJ1 - Конструкции железобетонные, AK - Автоматизация комплексная, KM1 - Конструкции металлические, TH - Технология производства | C83: =SUM(O83:O89) -> 11402664 | D83: =SUM(P83:P89) -> 4292 | E83: =D83/8 -> 536.5 | G83: ГИП | H83: 80 | I83: 13 | J83: 1 | K83: =L83*$S$10 -> 1.5 | L83: 1.5 | M83: 8 | N83: 5009.96 | O83: =N83*J83*K83*M83 -> 60119.52 | P83: =J83*K83*M83 -> 12
G84: Нач. отдела | J84: 5 | K84: =L84*$S$10 -> 4 | L84: 4 | M84: 8 | N84: 4508.96 | O84: =N84*J84*K84*M84 -> 721433.6 | P84: =J84*K84*M84 -> 160
G85: Гл. специалист | J85: 5 | K85: =L85*$S$10 -> 8 | L85: 8 | M85: 8 | N85: 3757.47 | O85: =N85*J85*K85*M85 -> 1202390.4 | P85: =J85*K85*M85 -> 320
G86: Рук. Группы | J86: 5 | K86: =L86*$S$10 -> 10 | L86: 10 | M86: 8 | N86: 3381.72 | O86: =N86*J86*K86*M86 -> 1352688 | P86: =J86*K86*M86 -> 400
G87: Вед. инженер | J87: 5 | K87: =L87*$S$10 -> 45 | L87: 45 | M87: 8 | N87: 2504.98 | O87: =N87*J87*K87*M87 -> 4508964 | P87: =J87*K87*M87 -> 1800
G88: Старший инженер | J88: 5 | K88: =L88*$S$10 -> 30 | L88: 30 | M88: 8 | N88: 2254.48 | O88: =N88*J88*K88*M88 -> 2705376 | P88: =J88*K88*M88 -> 1200
G89: Инженер | J89: 5 | K89: =L89*$S$10 -> 10 | L89: 10 | M89: 8 | N89: 2129.23 | O89: =N89*J89*K89*M89 -> 851692 | P89: =J89*K89*M89 -> 400
A90: 2.2. | B90: Техническое перевооружение участка эстакады от Т-8/2 до Т-6/1: ER - Электротехнические решения, KJ1 - Конструкции железобетонные, AK - Автоматизация комплексная, KM1 - Конструкции металлические, TH - Технология производства | C90: =SUM(O90:O96) -> 10846555 | D90: =SUM(P90:P96) -> 4172 | E90: =D90/8 -> 521.5 | G90: ГИП | H90: 80 | I90: 13 | J90: 1 | K90: =L90*$S$10 -> 1.5 | L90: 1.5 | M90: 8 | N90: 5009.96 | O90: =N90*J90*K90*M90 -> 60119.52 | P90: =J90*K90*M90 -> 12
G91: Нач. отдела | J91: 5 | K91: =L91*$S$10 -> 4 | L91: 4 | M91: 8 | N91: 4508.96 | O91: =N91*J91*K91*M91 -> 721433.6 | P91: =J91*K91*M91 -> 160
G92: Гл. специалист | J92: 5 | K92: =L92*$S$10 -> 8 | L92: 8 | M92: 8 | N92: 3757.47 | O92: =N92*J92*K92*M92 -> 1202390.4 | P92: =J92*K92*M92 -> 320
G93: Рук. Группы | J93: 5 | K93: =L93*$S$10 -> 12 | L93: 12 | M93: 8 | N93: 3381.72 | O93: =N93*J93*K93*M93 -> 1623225.6 | P93: =J93*K93*M93 -> 480
G94: Вед. инженер | J94: 5 | K94: =L94*$S$10 -> 20 | L94: 20 | M94: 8 | N94: 2504.98 | O94: =N94*J94*K94*M94 -> 2003984 | P94: =J94*K94*M94 -> 800
G95: Старший инженер | J95: 5 | K95: =L95*$S$10 -> 25 | L95: 25 | M95: 8 | N95: 2254.48 | O95: =N95*J95*K95*M95 -> 2254480 | P95: =J95*K95*M95 -> 1000
G96: Инженер | J96: 5 | K96: =L96*$S$10 -> 35 | L96: 35 | M96: 8 | N96: 2129.23 | O96: =N96*J96*K96*M96 -> 2980922 | P96: =J96*K96*M96 -> 1400
A97: 2.3. | B97: Техническое перевооружение насосной резервуарного парка производства №8801 (Т-8/2): ER - Электротехнические решения, KJ1 - Конструкции железобетонные, AK - Автоматизация комплексная, KM1 - Конструкции металлические, TH - Технология производства | C97: =SUM(O97:O103) -> 5475881 | D97: =SUM(P97:P103) -> 2164 | E97: =D97/8 -> 270.5 | G97: ГИП | H97: 50 | I97: 8 | J97: 1 | K97: =L97*$S$10 -> 0.5 | L97: 0.5 | M97: 8 | N97: 5009.96 | O97: =N97*J97*K97*M97 -> 20039.84 | P97: =J97*K97*M97 -> 4
G98: Нач. отдела | J98: 5 | K98: =L98*$S$10 -> 2 | L98: 2 | M98: 8 | N98: 4508.96 | O98: =N98*J98*K98*M98 -> 360716.8 | P98: =J98*K98*M98 -> 80
G99: Гл. специалист | J99: 5 | K99: =L99*$S$10 -> 4 | L99: 4 | M99: 8 | N99: 3757.47 | O99: =N99*J99*K99*M99 -> 601195.2 | P99: =J99*K99*M99 -> 160
G100: Рук. Группы | J100: 5 | K100: =L100*$S$10 -> 6 | L100: 6 | M100: 8 | N100: 3381.72 | O100: =N100*J100*K100*M100 -> 811612.8 | P100: =J100*K100*M100 -> 240
G101: Вед. инженер | J101: 5 | K101: =L101*$S$10 -> 2 | L101: 2 | M101: 8 | N101: 2504.98 | O101: =N101*J101*K101*M101 -> 200398.4 | P101: =J101*K101*M101 -> 80
G102: Старший инженер | J102: 5 | K102: =L102*$S$10 -> 15 | L102: 15 | M102: 8 | N102: 2254.48 | O102: =N102*J102*K102*M102 -> 1352688 | P102: =J102*K102*M102 -> 600
...

Sheet 4.1 КД
H1: Форма 3П
H2: Приложение № ___
H3: к договору №______________________
C4: СМЕТА на проектные работы № | D4: =СВОД!A34 -> 4.1
B6: Наименование предприятия, здания, сооружения:
B9: Стадия: | C9: этап:
B10: Рабочая документация | C10: =СВОД!B34 -> Рассмотрение и согласование ТКП и РКД поставщиков оборудования и материалов
B11: Наименование организации исполнителя:
B12: ='Форма сводной сметы '!F12 -> ОАО "СибНефтеТрансПроект"
B13: Наименование организации заказчика:
B14: ='Форма сводной сметы '!F15 -> ПАО «Нижнекамскнефтехим»
B16: Раздел 1. Определение трудоемкости (трудозатрат) выполняемой работы
A18: № п/п | B18: Перечень выполняемых работ | C18: Исполнители | F18: Количество человеко-дней (гр.4 * гр.5) | G18: Средняя зарплата за 1 день | H18: Оплата труда (всего) (гр.6 * гр.7)
C19: должность | D19: Количество
D20: чел | E20: дн
A21: 1 | B21: 2 | C21: 3 | D21: 4 | E21: 5 | F21: 6 | G21: 7 | H21: 8
A22: Разработка документации (вид работ/сооружение) | K22: среднечасов. ЗП
A23: 1 | B23: =C10 -> Рассмотрение и согласование ТКП и РКД поставщиков оборудования и материалов | C23: Начальник отдела | D23: 3 | E23: 1 | F23: =E23*D23 -> 3 | G23: =K23*8 -> 40079.68 | H23: =F23*G23 -> 120239.04 | J23: Начальник отдела | K23: 5009.96
C24: Главный специалист | D24: 3 | E24: 1 | F24: =E24*D24 -> 3 | G24: =K24*8 -> 30059.76 | H24: =F24*G24 -> 90179.28 | J24: Главный специалист | K24: 3757.47
C25: Руководитель группы | D25: 1 | E25: 0 | F25: =E25*D25 -> 0 | G25: =K25*8 -> 27053.76 | H25: =F25*G25 -> 0 | J25: Руководитель группы | K25: 3381.72
C26: Ведущий инженер | D26: 2 | E26: 7 | F26: =E26*D26 -> 14 | G26: =K26*8 -> 20039.84 | H26: =F26*G26 -> 280557.76 | J26: Ведущий инженер | K26: 2504.98
C27: Инженер 1-й категории | D27: 1 | E27: 4 | F27: =E27*D27 -> 4 | G27: =K27*8 -> 18063.84 | H27: =F27*G27 -> 72255.36 | J27: Инженер 1-й категории | K27: 2257.98
C28: Инженер 2-й категории | D28: 0 | E28: 0 | F28: =E28*D28 -> 0 | G28: =K28*8 -> 17033.84 | H28: =F28*G28 -> 0 | J28: Инженер 2-й категории | K28: 2129.23
C29: Инженер 3-й категории | D29: 0 | E29: 0 | F29: =E29*D29 -> 0 | G29: =K29*8 -> 16031.84 | H29: =F29*G29 -> 0 | J29: Инженер 3-й категории | K29: 2003.98
C30: Инженер | D30: 0 | E30: 0 | F30: =E30*D30 -> 0 | G30: =K30*8 -> 14528.84 | H30: =F30*G30 -> 0 | J30: Инженер | K30: 1816.105
B31: Итого з/п непосредственных исполнителей | H31: =SUM(H23:H30) -> 563231.44
B32: Раздел 2. Определение стоимости работ, перечисленных в разделе 1
A33: № п/п | B33: Наименование показателей | G33: Единица измерения | H33: Сумма
A34: 1 | B34: 2 | G34: 3 | H34: 4
A35: .1 | B35: Итого заработная плата непосредственных исполнителей (итог по гр.8 раздела 1) | G35: руб. | H35: =H31 -> 563231.44
A36: .2 | B36: Общая стоимость работы (стр.1) | G36: руб. | H36: =ROUND(H35,2) -> 563231.44
A37: .3 | B37: НДС 20% | G37: руб. | H37: =H36*0.2 -> 112646.29
A38: .4 | B38: Всего с НДС | G38: руб. | H38: =H36+H37 -> 675877.73
B39: Средняя стоимость ч.ч. | G39: руб. | H39: =H31/SUM(F23:F30)/8 -> 2933.4971

Sheet ИД для составления смет
C1: «Наименование объекта»
B2: Форма сбора исходных данных для составления смет на проектные работы
B3: № | C3: Номер и наименование титульного сооружения (заполняется в случае наличия присвоенного номера) | D3: Наименование сооружения/работ | E3: Ед.изм. | F3: Кол-во | G3: Усложняющие факторы (сейсмичность, в подтапливаемых районах и т.д.), разделы, к разработке которых установлены особые требования | H3: Дополнительные исходные данные, влияющие на цену; ценообразующие коэффициенты | I3: Применение повторно-применяемых проектных решений (указать % переработки, относительно какого титульного сооружения) | J3: Разделы документации включаемые в объектно-ориентированную параметрическую трехмерную модель для видов документации: - Проектная документация (П) - Рабочая документация (Р) | K3: Пункт ЗП/ТЗ, к которому относится сооружение и работа или ссылка на том документации
B4: 1 | C4: 2 | D4: 3 | E4: 4 | F4: 5 | G4: 6 | H4: 7 | I4: 8 | J4: 9 | K4: 10
B5: 1 | C5: Титул 1.3.1.00.106 Подъездная автомобильная дорога №11; | G5: Сейсмичность - 7 | J5: П
B6: =MAX($B$5:B5)+1 -> 2 | C6: Титул 1.3.1.00.112 Устройство примыкания проектируемой ПАД №11. | G6: Сейсмичность - 7 | J6: П

Sheet Лист2
A1: Наименование | B1: Показатель
A2: Железнодорожные мосты с пролетами до 42 м. | B2: Полная длина | C2: м | E2: РД
A3: Железнодорожные мосты с пролетами свыше 42 м. | E3: ПД
A4: Автодорожные мосты | B4: Полная длина | C4: м | E4: вне стадийная
A5: Пешеходные мосты | B5: Полная длина | C5: м | E5: ПД+РД
A6: Городские мосты | B6: Полная длина | C6: м
A7: Пешеходный переход (технологическая эстакада) шириной до 3 м | B7: Полная длина | C7: м
A8: Пешеходный переход (технологическая эстакада) шириной до 5 м | B8: Полная длина | C8: м
A9: Путепроводы, эстакады однопутные железнодорожные | B9: Полная длина | C9: м
A10: Путепроводы, эстакады автодорожные | B10: Полная длина | C10: м
A11: Водопропускные трубы на железных и автомобильных дорогах | B11: Материал Диаметр Количество проходов Протяженность | C11: _ мм шт м
A12: Газопровод диаметром до 500 мм | B12: Протяженность | C12: км
A13: Газопровод диаметром более 500 мм | B13: Протяженность | C13: км
A14: Переходы газопроводом (трубопроводом) через водные преграды и препятствия | B14: Протяженность между отключающими кранами | C14: м
A15: Подвесные переходы | B15: Пролеты между крайними опорами | C15: м
A16: Балочные переходы | B16: Длина надземной части | C16: м
A17: Установка компримирования газа | B17: Суммарная установленная мощность | C17: кВт
... A57: Автомобильные дороги | B57: Категория Протяженность | C57: км
A58: Транспортные развязки | B58: Тип развязки Уровней развязки
A59: Котельные | B59: стоимость строительства на 2001 год | C59: млн. руб
A60: ДЭС | B60: стоимость строительства на 2001 год | C60: млн. руб
A61: Газотурбинные ЭС | B61: стоимость строительства на 2001 год | C61: млн. руб
A62: Открытые и закрытые электрические подстанции напряжением 35 - 1150 кВ | B62: стоимость строительства на 2001 год | C62: млн. руб
A63: Воздушные линии (ВЛ) электропередачи напряжением 35 - 1150 кВ | B63: стоимость строительства на 2001 год | C63: млн. руб
A64: Кабельные линии напряжением 110 - 500 кВ | B64: стоимость строительства на 2001 год | C64: млн. руб
A65: Ремонтно-производственные базы (РПБ) и ремонтно-эксплуатационные пункты (РЭП) электросетей | B65: стоимость строительства на 2001 год | C65: млн. руб
A66: ВЛ (Воздушные линии) электропередачи 20 кВ | B66: Длина | C66: км
A67: ВЛ (Воздушные линии) электропередачи 35 кВ | B67: Длина | C67: км
A68: ВЛ (Воздушные линии) электропередачи 110-750 кВ | B68: Длина | C68: км
A69: Трансформаторные подстанции | B69: Мощность | C69: кВ*А
A70: Центральный тепловой пункт | B70: Нагрузка | C70: Гкал/ч
... A90: Ремонтные службы | B90: Площадь (количество) | C90: м2(объектов)
A91: Объекты подсобно-производственного, вспомогательного и общезаводского назначения, внутриплощадочные инженерные сети, генплан
A92: Очистные сооружения и водоблоки | B92: Производительность | C92: м3/сут
A93: Трансформаторные подстанции и распределительные устройства, размещаемые на площадках взрывопожароопасных производств | B93: Напряжение Мощность | C93: кВ кВА
A94: Производство полиамидных смол | B94: Производительность | C94: тыс. т/год
A95: Производство поликорбанатов | B95: Производительность | C95: тыс. т/год
A96: Производство полибутилентерефталата | B96: Производительность | C96: тыс. т/год
A97: Производство карбамидных смол | B97: Производительность | C97: тыс. т/год
A98: Производство полиэфирмалеинатов | B98: Производительность | C98: тыс. т/год
A99: Производство полиформальдегида | B99: Производительность | C99: тыс. т/год
A100: Производство полистирола | B100: Производительность | C100: тыс. т/год
A101: Производство полиэтилена высокого давления | B101: Производительность | C101: тыс. т/год
A102: Производство полиэтилена низкого давления | B102: Производительность | C102: тыс. т/год
A103: Производство полиэтилентерефталата | B103: Производительность | C103: тыс. т/год
... A130: Лаборатория | B130: площадь | C130: м2

Sheet Справочник СБЦ
C1: Столбец1 | D1: Сооружения | E1: Где искать | F1: Фильтр
C2: =IF(ISNUMBER(SEARCH($J$4,Сооруж[[#This Row],[Сооружения]])),MAX(Сооруж[[#Headers],[Столбец1]]:OFFSET(Сооруж[[#This Row],[Столбец1]],-1,0))+1,0) -> 0 | D2: Железнодорожные мосты с пролетами до 42 м. | E2: ИСКУССТВЕННЫЕ_СООРУЖЕНИЯ_МОСТЫ_ПЕРЕХОДЫ_ПУТЕПРОВОДЫ | F2: =IFERROR(VLOOKUP(ROW(Фильтр[[#This Row],[Фильтр]])-ROW(Фильтр[[#Headers],[Фильтр]]),Сооруж[],2,FALSE),"") -> Железнодорожные мосты с пролетами свыше 42 м.
C3: =IF(ISNUMBER(SEARCH($J$4,Сооруж[[#This Row],[Сооружения]])),MAX(Сооруж[[#Headers],[Столбец1]]:OFFSET(Сооруж[[#This Row],[Столбец1]],-1,0))+1,0) -> 1 | D3: Железнодорожные мосты с пролетами свыше 42 м. | E3: ИСКУССТВЕННЫЕ_СООРУЖЕНИЯ_МОСТЫ_ПЕРЕХОДЫ_ПУТЕПРОВОДЫ | F3: =IFERROR(VLOOKUP(ROW(Фильтр[[#This Row],[Фильтр]])-ROW(Фильтр[[#Headers],[Фильтр]]),Сооруж[],2,FALSE),"") | J3: ВВЕДИТЕ НАЗВАНИЕ СООРУЖЕНИЯ
C4: =IF(ISNUMBER(SEARCH($J$4,Сооруж[[#This Row],[Сооружения]])),MAX(Сооруж[[#Headers],[Столбец1]]:OFFSET(Сооруж[[#This Row],[Столбец1]],-1,0))+1,0) -> 0 | D4: Автодорожные мосты | E4: ИСКУССТВЕННЫЕ_СООРУЖЕНИЯ_МОСТЫ_ПЕРЕХОДЫ_ПУТЕПРОВОДЫ | F4: =IFERROR(VLOOKUP(ROW(Фильтр[[#This Row],[Фильтр]])-ROW(Фильтр[[#Headers],[Фильтр]]),Сооруж[],2,FALSE),"") | J4: Железнодорожные мосты с пролетами свыше 42 м. | K4: Возможно ввести часть названия и далее выбрать из предложенного выпадающего списка*
C5: =IF(ISNUMBER(SEARCH($J$4,Сооруж[[#This Row],[Сооружения]])),MAX(Сооруж[[#Headers],[Столбец1]]:OFFSET(Сооруж[[#This Row],[Столбец1]],-1,0))+1,0) -> 0 | D5: Пешеходные мосты | E5: ИСКУССТВЕННЫЕ_СООРУЖЕНИЯ_МОСТЫ_ПЕРЕХОДЫ_ПУТЕПРОВОДЫ | F5: =IFERROR(VLOOKUP(ROW(Фильтр[[#This Row],[Фильтр]])-ROW(Фильтр[[#Headers],[Фильтр]]),Сооруж[],2,FALSE),"") | J5: Возможно указать СБЦ
C6: =IF(ISNUMBER(SEARCH($J$4,Сооруж[[#This Row],[Сооружения]])),MAX(Сооруж[[#Headers],[Столбец1]]:OFFSET(Сооруж[[#This Row],[Столбец1]],-1,0))+1,0) -> 0 | D6: Городские мосты | E6: ИСКУССТВЕННЫЕ_СООРУЖЕНИЯ_МОСТЫ_ПЕРЕХОДЫ_ПУТЕПРОВОДЫ | F6: =IFERROR(VLOOKUP(ROW(Фильтр[[#This Row],[Фильтр]])-ROW(Фильтр[[#Headers],[Фильтр]]),Сооруж[],2,FALSE),"") | J6: =VLOOKUP(J4,$D$2:$E$140,2,0) -> ИСКУССТВЕННЫЕ_СООРУЖЕНИЯ_МОСТЫ_ПЕРЕХОДЫ_ПУТЕПРОВОДЫ
C7: =IF(ISNUMBER(SEARCH($J$4,Сооруж[[#This Row],[Сооружения]])),MAX(Сооруж[[#Headers],[Столбец1]]:OFFSET(Сооруж[[#This Row],[Столбец1]],-1,0))+1,0) -> 0 | D7: Пешеходный переход (технологическая эстакада) шириной до 3 м | E7: ИСКУССТВЕННЫЕ_СООРУЖЕНИЯ_МОСТЫ_ПЕРЕХОДЫ_ПУТЕПРОВОДЫ | F7: =IFERROR(VLOOKUP(ROW(Фильтр[[#This Row],[Фильтр]])-ROW(Фильтр[[#Headers],[Фильтр]]),Сооруж[],2,FALSE),"")
C8: =IF(ISNUMBER(SEARCH($J$4,Сооруж[[#This Row],[Сооружения]])),MAX(Сооруж[[#Headers],[Столбец1]]:OFFSET(Сооруж[[#This Row],[Столбец1]],-1,0))+1,0) -> 0 | D8: Пешеходный переход (технологическая эстакада) шириной до 5 м | E8: ИСКУССТВЕННЫЕ_СООРУЖЕНИЯ_МОСТЫ_ПЕРЕХОДЫ_ПУТЕПРОВОДЫ | F8: =IFERROR(VLOOKUP(ROW(Фильтр[[#This Row],[Фильтр]])-ROW(Фильтр[[#Headers],[Фильтр]]),Сооруж[],2,FALSE),"")
C9: =IF(ISNUMBER(SEARCH($J$4,Сооруж[[#This Row],[Сооружения]])),MAX(Сооруж[[#Headers],[Столбец1]]:OFFSET(Сооруж[[#This Row],[Столбец1]],-1,0))+1,0) -> 0 | D9: Путепроводы, эстакады однопутные железнодорожные | E9: ИСКУССТВЕННЫЕ_СООРУЖЕНИЯ_МОСТЫ_ПЕРЕХОДЫ_ПУТЕПРОВОДЫ | F9: =IFERROR(VLOOKUP(ROW(Фильтр[[#This Row],[Фильтр]])-ROW(Фильтр[[#Headers],[Фильтр]]),Сооруж[],2,FALSE),"") | J9: * Поиск находит сочетание букв заданные в запросе. При совпадении, указывает возможные варианты в выпадающем списке.
C10: =IF(ISNUMBER(SEARCH($J$4,Сооруж[[#This Row],[Сооружения]])),MAX(Сооруж[[#Headers],[Столбец1]]:OFFSET(Сооруж[[#This Row],[Столбец1]],-1,0))+1,0) -> 0 | D10: Путепроводы, эстакады автодорожные | E10: ИСКУССТВЕННЫЕ_СООРУЖЕНИЯ_МОСТЫ_ПЕРЕХОДЫ_ПУТЕПРОВОДЫ | F10: =IFERROR(VLOOKUP(ROW(Фильтр[[#This Row],[Фильтр]])-ROW(Фильтр[[#Headers],[Фильтр]]),Сооруж[],2,FALSE),"")
C11: =IF(ISNUMBER(SEARCH($J$4,Сооруж[[#This Row],[Сооружения]])),MAX(Сооруж[[#Headers],[Столбец1]]:OFFSET(Сооруж[[#This Row],[Столбец1]],-1,0))+1,0) -> 0 | D11: Водопропускные трубы на железных и автомобильных дорогах | E11: ИСКУССТВЕННЫЕ_СООРУЖЕНИЯ_МОСТЫ_ПЕРЕХОДЫ_ПУТЕПРОВОДЫ | F11: =IFERROR(VLOOKUP(ROW(Фильтр[[#This Row],[Фильтр]])-ROW(Фильтр[[#Headers],[Фильтр]]),Сооруж[],2,FALSE),"")
C12: =IF(ISNUMBER(SEARCH($J$4,Сооруж[[#This Row],[Сооружения]])),MAX(Сооруж[[#Headers],[Столбец1]]:OFFSET(Сооруж[[#This Row],[Столбец1]],-1,0))+1,0) -> 0 | D12: Газопровод диаметром до 500 мм | E12: ОБЪЕКТЫ_ГАЗОВОЙ_ПРОМЫШЛЕННОСТИ | F12: =IFERROR(VLOOKUP(ROW(Фильтр[[#This Row],[Фильтр]])-ROW(Фильтр[[#Headers],[Фильтр]]),Сооруж[],2,FALSE),"")
C13: =IF(ISNUMBER(SEARCH($J$4,Сооруж[[#This Row],[Сооружения]])),MAX(Сооруж[[#Headers],[Столбец1]]:OFFSET(Сооруж[[#This Row],[Столбец1]],-1,0))+1,0) -> 0 | D13: Газопровод диаметром более 500 мм | E13: ОБЪЕКТЫ_ГАЗОВОЙ_ПРОМЫШЛЕННОСТИ | F13: =IFERROR(VLOOKUP(ROW(Фильтр[[#This Row],[Фильтр]])-ROW(Фильтр[[#Headers],[Фильтр]]),Сооруж[],2,FALSE),"")
C14: =IF(ISNUMBER(SEARCH($J$4,Сооруж[[#This Row],[Сооружения]])),MAX(Сооруж[[#Headers],[Столбец1]]:OFFSET(Сооруж[[#This Row],[Столбец1]],-1,0))+1,0) -> 0 | D14: Переходы газопроводом (трубопроводом) через водные преграды и препятствия | E14: ОБЪЕКТЫ_ГАЗОВОЙ_ПРОМЫШЛЕННОСТИ | F14: =IFERROR(VLOOKUP(ROW(Фильтр[[#This Row],[Фильтр]])-ROW(Фильтр[[#Headers],[Фильтр]]),Сооруж[],2,FALSE),"")
C15: =IF(ISNUMBER(SEARCH($J$4,Сооруж[[#This Row],[Сооружения]])),MAX(Сооруж[[#Headers],[Столбец1]]:OFFSET(Сооруж[[#This Row],[Столбец1]],-1,0))+1,0) -> 0 | D15: Подвесные переходы | E15: ОБЪЕКТЫ_ГАЗОВОЙ_ПРОМЫШЛЕННОСТИ | F15: =IFERROR(VLOOKUP(ROW(Фильтр[[#This Row],[Фильтр]])-ROW(Фильтр[[#Headers],[Фильтр]]),Сооруж[],2,FALSE),"")
C16: =IF(ISNUMBER(SEARCH($J$4,Сооруж[[#This Row],[Сооружения]])),MAX(Сооруж[[#Headers],[Столбец1]]:OFFSET(Сооруж[[#This Row],[Столбец1]],-1,0))+1,0) -> 0 | D16: Балочные переходы | E16: ОБЪЕКТЫ_ГАЗОВОЙ_ПРОМЫШЛЕННОСТИ | F16: =IFERROR(VLOOKUP(ROW(Фильтр[[#This Row],[Фильтр]])-ROW(Фильтр[[#Headers],[Фильтр]]),Сооруж[],2,FALSE),"")
C17: =IF(ISNUMBER(SEARCH($J$4,Сооруж[[#This Row],[Сооружения]])),MAX(Сооруж[[#Headers],[Столбец1]]:OFFSET(Сооруж[[#This Row],[Столбец1]],-1,0))+1,0) -> 0 | D17: Установка компримирования газа | E17: ОБЪЕКТЫ_ГАЗОВОЙ_ПРОМЫШЛЕННОСТИ | F17: =IFERROR(VLOOKUP(ROW(Фильтр[[#This Row],[Фильтр]])-ROW(Фильтр[[#Headers],[Фильтр]]),Сооруж[],2,FALSE),"")
C18: =IF(ISNUMBER(SEARCH($J$4,Сооруж[[#This Row],[Сооружения]])),MAX(Сооруж[[#Headers],[Столбец1]]:OFFSET(Сооруж[[#This Row],[Столбец1]],-1,0))+1,0) -> 0 | D18: Установка осушки газа | E18: ОБЪЕКТЫ_ГАЗОВОЙ_ПРОМЫШЛЕННОСТИ | F18: =IFERROR(VLOOKUP(ROW(Фильтр[[#This Row],[Фильтр]])-ROW(Фильтр[[#Headers],[Фильтр]]),Сооруж[],2,FALSE),"")
C19: =IF(ISNUMBER(SEARCH($J$4,Сооруж[[#This Row],[Сооружения]])),MAX(Сооруж[[#Headers],[Столбец1]]:OFFSET(Сооруж[[#This Row],[Столбец1]],-1,0))+1,0) -> 0 | D19: Установка очистки газа от пыли | E19: ОБЪЕКТЫ_ГАЗОВОЙ_ПРОМЫШЛЕННОСТИ | F19: =IFERROR(VLOOKUP(ROW(Фильтр[[#This Row],[Фильтр]])-ROW(Фильтр[[#Headers],[Фильтр]]),Сооруж[],2,FALSE),"")
C20: =IF(ISNUMBER(SEARCH($J$4,Сооруж[[#This Row],[Сооружения]])),MAX(Сооруж[[#Headers],[Столбец1]]:OFFSET(Сооруж[[#This Row],[Столбец1]],-1,0))+1,0) -> 0 | D20: Установка второй ступени очистки с фильтросепараторами | E20: ОБЪЕКТЫ_ГАЗОВОЙ_ПРОМЫШЛЕННОСТИ | F20: =IFERROR(VLOOKUP(ROW(Фильтр[[#This Row],[Фильтр]])-ROW(Фильтр[[#Headers],[Фильтр]]),Сооруж[],2,FALSE),"")
C21: =IF(ISNUMBER(SEARCH($J$4,Сооруж[[#This Row],[Сооружения]])),MAX(Сооруж[[#Headers],[Столбец1]]:OFFSET(Сооруж[[#This Row],[Столбец1]],-1,0))+1,0) -> 0 | D21: Установка воздушного охлаждения газа | E21: ОБЪЕКТЫ_ГАЗОВОЙ_ПРОМЫШЛЕННОСТИ | F21: =IFERROR(VLOOKUP(ROW(Фильтр[[#This Row],[Фильтр]])-ROW(Фильтр[[#Headers],[Фильтр]]),Сооруж[],2,FALSE),"")
... C143: =IF(ISNUMBER(SEARCH($J$4,Сооруж[[#This Row],[Сооружения]])),MAX(Сооруж[[#Headers],[Столбец1]]:OFFSET(Сооруж[[#This Row],[Столбец1]],-1,0))+1,0) -> 0 | D143: Защитные сооружения гражданской обороны (убежища) | E143: ЗАЩИТНЫЕ_СООРУЖЕНИЯ_ГРАЖДАНСКОЙ_ОБОРОНЫ | F143: =IFERROR(VLOOKUP(ROW(Фильтр[[#This Row],[Фильтр]])-ROW(Фильтр[[#Headers],[Фильтр]]),Сооруж[],2,FALSE),"")

Sheet Лист1
A2: ИСКУССТВЕННЫЕ_СООРУЖЕНИЯ_МОСТЫ_ПЕРЕХОДЫ_ПУТЕПРОВОДЫ | D2: ОБЪЕКТЫ_ГАЗОВОЙ_ПРОМЫШЛЕННОСТИ | G2: ОБЪЕКТЫ_ЖИЛИЩНО_ГРАЖДАНСКОГО_СТРОИТЕЛЬСТВА | J2: АВТОМОБИЛЬНЫЕ_ДОРОГИ | M2: ОБЪЕКТЫ_ЭНЕРГЕТИКИ_ГЕНЕРАЦИЯ_ЭНЕРГИИ | P2: ОБЪЕКТЫ_ЭНЕРГЕТИКИ_ЭЛЕКТРОСЕТЕВЫЕ_ОБЪЕКТЫ | S2: КОММУНАЛЬНЫЕ_ИНЖЕНЕРНЫЕ_СЕТИ_И_СООРУЖЕНИЯ | V2: ОБЪЕКТЫ_ВОДОСНАБЖЕНИЯ_И_КАНАЛИЗАЦИИ | Y2: ОБЪЕКТЫ_МАГИСТРАЛЬНОГО_ТРУБОПРОВОДНОГО_ТРАНСПОРТА_НЕФТИ | AB2: ОБЪЕКТЫ_НЕФТЕПЕРЕРАБАТЫВАЮЩЕЙ_И_НЕФТЕХИМИЧЕСКОЙ_ПРОМЫШЛЕННОСТИ | AE2: Другое (Указать вручную) | AF2: ОБЪЕКТЫ_СИНТЕТИЧЕСКИХ_СМОЛ_ПЛАСТИЧЕСКИХ_МАСС_СТЕКЛОВОЛОКНА_СТЕКЛОПЛАСТИК_ПЛАСТМАССОВЫХ_ИЗДЕЛИЙ | AI2: ЖЕЛЕЗНЫЕ_ДОРОГИ | AL2: СИСТЕМЫ_ПРОТИВОПОЖАРНОЙ_И_ОХРАННОЙ_ЗАЩИТЫ | AO2: ЗАЩИТНЫЕ_СООРУЖЕНИЯ_ГРАЖДАНСКОЙ_ОБОРОНЫ | AR2: ПРЕДПРИЯТИЯ_АГРОПРОМЫШЛЕННОГО_КОМПЛЕКСА,ТОРГОВЛИ_И_ОБЩЕСТВЕННОГО_ПИТАНИЯ
A3: Железнодорожные мосты с пролетами до 42 м. | B3: Полная длина | C3: м | D3: Газопровод диаметром до 500 мм | E3: Протяженность | F3: км | G3: Гостиницы, общежития | H3: количество мест | I3: мест | J3: Автомобильные дороги | K3: Категория Протяженность | L3: км | M3: Котельные | N3: стоимость строительства на 2001 год | O3: млн. руб | P3: Открытые и закрытые электрические подстанции напряжением 35 - 110 кВ | Q3: стоимость строительства на 2001 год | R3: млн. руб | S3: ВЛ (Воздушные линии) электропередачи 20 кВ | T3: Длина | U3: км | V3: Водозаборные сооружения из поверхностных источников с насосной станцией 1-го подъема | W3: Производительность | X3: тыс.м3/ч | Y3: Линейная часть магистральных нефтепроводов | Z3: Диаметр Протяженность | AA3: мм км | AB3: Технологические установки и отдельные производства нефтеперерабатывающей промышленности | AC3: Производительность (количество) | AD3: тыс.т/год(объектов) | AE3: _ | AF3: Производство полиамидных смол | AG3: Производительность | AH3: тыс. т/год | AI3: Железная дорога | AJ3: Категория Протяженность Вид тяги | AK3: _ км - | AL3: Спринклерные установки | AM3: Площадь объекта | AN3: м2 | AO3: Защитные сооружения гражданской обороны (убежища) | AP3: Количество укрываемых людей | AQ3: чел.
A4: Железнодорожные мосты с пролетами свыше 42 м. | D4: Газопровод диаметром более 500 мм | E4: Протяженность | F4: км | G4: Объекты здравоохранения | H4: площадь | I4: м2 | J4: Транспортные развязки | K4: Уровней развязки | L4: шт | M4: ДЭС | N4: стоимость строительства на 2001 год | O4: млн. руб | P4: Воздушные линии (ВЛ) электропередачи напряжением 35 - 110 кВ | Q4: стоимость строительства на 2001 год | R4: млн. руб | S4: ВЛ (Воздушные линии) электропередачи 35 кВ | T4: Длина | U4: км | V4: Водозаборы из подземных источников | W4: Производительность | X4: м3/ч | Y4: Переходы нефтепроводов | Z4: Протяженность | AA4: км | AB4: Технологические установки и отдельные производства нефтеперерабатывающей промышленности | AC4: Производительность (количество) | AD4: тыс.т/год(объектов) | AF4: Производство поликорбанатов | AG4: Производительность | AH4: тыс. т/год | AI4: Платформы низкие | AJ4: Площадь | AK4: м2 | AL4: Дренчерные установки | AM4: Площадь объекта | AN4: м2
A5: Автодорожные мосты | B5: Полная длина | C5: м | D5: Переходы газопроводом (трубопроводом) через водные преграды и препятствия | E5: Протяженность между отключающими кранами | F5: м | G5: Объекты отдыха | H5: площадь | I5: м2 | M5: Газотурбинные ЭС | N5: стоимость строительства на 2001 год | O5: млн. руб | P5: Кабельные линии напряжением 110 - 500 кВ | Q5: стоимость строительства на 2001 год | R5: млн. руб | S5: ВЛ (Воздушные линии) электропередачи 110-750 кВ | T5: Длина | U5: км | V5: Водовод в одну линию с сооружениями на нем | W5: Длина Диаметр Расход | X5: м мм м3/ч | Y5: Здание магистральной насосной станции | Z5: Производительность | AA5: млн. т/год | AB5: Ремонтные службы | AC5: Площадь (количество) | AD5: м2(объектов) | AF5: Производство полибутилентерефталата | AG5: Производительность | AH5: тыс. т/год | AI5: Платформы | AJ5: Площадь | AK5: м2 | AL5: Автоматические установки пожарной сигнализации | AM5: Площадь объекта | AN5: м2
A6: Пешеходные мосты | B6: Полная длина | C6: м | D6: Подвесные переходы | E6: Пролеты между крайними опорами | F6: м | G6: Специализированные здания для физической культуры и спорта | H6: количество мест | I6: мест | P6: Ремонтно-производственные базы (РПБ) и ремонтно-эксплуатационные пункты (РЭП) электросетей | Q6: стоимость строительства на 2001 год | R6: млн. руб | S6: Трансформаторные подстанции | T6: Мощность | U6: кВ*А | V6: Водопроводные очистные сооружения | W6: Производительность | X6: тыс.м3/ч | Y6: Подпорные насосные станции | Z6: Производительность | AA6: млн. т/год | AB6: Объекты подсобно-производственного, вспомогательного и общезаводского назначения, внутриплощадочные инженерные сети, генплан | AF6: Производство карбамидных смол | AG6: Производительность | AH6: тыс. т/год | AI6: Подпорные и ограждающие стенки в грунте | AJ6: Полная длина | AK6: п.м. | AL6: Системы оповещения людей о пожаре | AM6: Площадь объекта | AN6: м2
A7: Городские мосты | B7: Полная длина | C7: м | D7: Балочные переходы | E7: Длина надземной части | F7: м | G7: Плоскостные сооружения | H7: габаритные размеры | I7: м х м | S7: Центральный тепловой пункт | T7: Нагрузка | U7: Гкал/ч | V7: Насосная станция II-го подъема, подкачки или систем оборотного водоснабжения | W7: Производительность | X7: тыс.м3/ч | Y7: Системы измерений количества и показателей качества нефти | Z7: Производительность | AA7: млн. т/год | AB7: Очистные сооружения и водоблоки | AC7: Производительность | AD7: м3/сут | AF7: Производство полиэфирмалеинатов | AG7: Производительность | AH7: тыс. т/год | AI7: Железнодорожный переезд | AJ7: Количество путей | AK7: шт | AL7: Установки охранной сигнализации | AM7: Площадь объекта | AN7: м2
A8: Пешеходный переход (технологическая эстакада) шириной до 3 м | B8: Полная длина | C8: м | D8: Установка компримирования газа | E8: Суммарная установленная мощность | F8: кВт | G8: Библиотеки, архивы | H8: количество томов | I8: тыс. томов | S8: Котельные | T8: теплопроизводительность | U8: Гкал/ч | V8: Канализационные коллекторы с сооружениями на них | W8: Пропускная способность | X8: м3/ч | Y8: Пункт подогрева нефти | Z8: Число печей | AA8: шт | AB8: Трансформаторные подстанции и распределительные устройства, размещаемые на площадках взрывопожароопасных производств | AC8: Напряжение Мощность | AD8: кВ кВА | AF8: Производство полиформальдегида | AG8: Производительность | AH8: тыс. т/год | AI8: Диспетчерское управление энергетическими объектами (электростанциями, подстанциями) | AJ8: Количество | AK8: шт | AL8: Установки периметральной охранной сигнализации | AM8: Протяженность | AN8: км
A9: Пешеходный переход (технологическая эстакада) шириной до 5 м | B9: Полная длина | C9: м | D9: Установка осушки газа | E9: Производительность | F9: млн. м3/сут | G9: Научно-исследовательские учреждения, проектные и конструкторские организации | H9: Площадь | I9: м2 | V9: Станции перекачки сточных вод | W9: Производительность | X9: тыс.м3/ч | Y9: Наружное освещение территории нефтеперекачивающей станции | Z9: Площадь | AA9: га | AB9: Пожарное депо | AC9: Количество машин | AD9: шт | AF9: Производство полистирола | AG9: Производительность | AH9: тыс. т/год | AI9: Ремонтно-механические мастерские | AJ9: Площадь | AK9: м2 | AL9: Системы управления установками дымоудаления | AM9: Площадь объекта | AN9: м2
A10: Путепроводы, эстакады однопутные железнодорожные | B10: Полная длина | C10: м | D10: Установка очистки газа от пыли | E10: Производительность | F10: млн. м3/сут | G10: Проектные, конструкторские организации | H10: Число рабочих мест | I10: мест | V10: Сооружения для очистки сточных вод | W10: Производительность | X10: тыс.м3/ч | Y10: Переходы траншейным методом | Z10: Диаметр трубы Протяженность | AA10: мм м | AF10: Производство полиэтилена высокого давления | AG10: Производительность | AH10: тыс. т/год | AI10: Гараж-стоянка | AJ10: Количество автомобилей | AK10: шт
A11: Путепроводы, эстакады автодорожные | B11: Полная длина | C11: м | D11: Установка второй ступени очистки с фильтросепараторами | E11: Производительность | F11: млн. м3/сут | G11: Здания предприятий общественного питания | H11: Число посадочных мест | I11: мест | V11: Водоподготовки и очистки сточных вод | W11: Производительность | X11: м3/ч | Y11: Переходы наклонно-направленного бурения | Z11: Диаметр трубы Протяженность | AA11: мм м | AF11: Производство полиэтилена низкого давления | AG11: Производительность | AH11: тыс. т/год | AI11: Туалет | AJ11: Количество мест | AK11: мест
A12: Водопропускные трубы на железных и автомобильных дорогах | B12: Протяженность | C12: м | D12: Установка воздушного охлаждения газа | E12: Производительность | F12: млн. м3/сут | G12: Административные здания | H12: Площадь | I12: м2 | Y12: Переходы методом микротоннелирования | Z12: Диаметр трубы Протяженность | AA12: мм м | AF12: Производство полиэтилентерефталата | AG12: Производительность | AH12: тыс. т/год
D13: Установка замера газа (отдельная площадка вне территории КС) | E13: на газопроводе диаметром | F13: мм | G13: Предприятия по стирке белья и химической чистке одежды | H13: мощность | I13: кг/смена | Y13: Переходы методом тоннелирования | Z13: Диаметр трубы Протяженность | AA13: мм м | AF13: Производство поливинилбутираля | AG13: Производительность | AH13: тыс. т/год
D14: Установка запуска и приема очистных устройств с узлом подключения КС | E14: на газопроводе диаметром | F14: мм | G14: Заводы по переработке твердых бытовых отходов, полигон для захоронения твердых бытовых отходов, станции по сортировке, перегрузке твердых бытовых отходов | H14: Производительность | I14: тыс. т/год или т для полигонов | Y14: Переходы подвесные | Z14: Диаметр трубы Протяженность | AA14: мм м | AF14: Производство простых полиэфиров | AG14: Производительность | AH14: тыс. т/год
D15: Автомобильные газонаполнительные компрессорные станции (АГНКС) | E15: Количество заправок в сутки | F15: заправок | G15: Эксплуатационные базы газового хозяйства | H15: количество жителей | I15: тыс. чел. | Y15: Балочные пролеты | Z15: Диаметр трубы Протяженность | AA15: мм м | AF15: Производство конфекционированных систем | AG15: Производительность | AH15: тыс. т/год
D16: Установка переключающей арматуры | E16: Производительность | F16: млн. м3/сут | G16: Инженерная подготовка территории, набережные | H16: объем намыва грунта | I16: тыс. м3 | AF16: Производство блочного │пенополиуретана | AG16: Производительность | AH16: тыс. т/год
D17: Установка первичной сепарации газа | E17: Производительность | F17: млн. м3/сут | G17: Уникальные здания и сооружения | H17: стоимость строительства на 2001 год | I17: млн. руб | AF17: Производство кабельного пластиката | AG17: Производительность | AH17: тыс. т/год
D18: Установка первичной обработки конденсата газа | E18: Производительность | F18: т/час | G18: Столовая | H18: посадочных мест | I18: посадочных мест | AF18: Производство пластификаторов | AG18: Производительность | AH18: тыс. т/год
A19: ОБЪЕКТЫ_СИНТЕТИЧЕСКИХ_СМОЛ_ПЛАСТИЧЕСКИХ_МАСС_СТЕКЛОВОЛОКНА_СТЕКЛОПЛАСТИК_ПЛАСТМАССОВЫХ_ИЗДЕЛИЙ | D19: Установка низкотемпературной сепарации газа | E19: Производительность | F19: млн. м3/сут | G19: Лаборатория | H19: площадь | I19: м2 | AF19: Производство пентаэритрита | AG19: Производительность | AH19: тыс. т/год
A20: ИСКУССТВЕННЫЕ_СООРУЖЕНИЯ_МОСТЫ_ПЕРЕХОДЫ_ПУТЕПРОВОДЫ | D20: Установка низкотемпературной абсорбции газа | E20: Производительность | F20: млн. м3/сут | AF20: Производство фенолоформальдегидных смол | AG20: Производительность | AH20: тыс. т/год
A21: ОБЪЕКТЫ_ГАЗОВОЙ_ПРОМЫШЛЕННОСТИ | D21: Установка абсорбции газа | E21: Производительность | F21: млн. м3/сут | AF21: Производство формалина | AG21: Производительность | AH21: тыс. т/год
A22: ОБЪЕКТЫ_ЖИЛИЩНО_ГРАЖДАНСКОГО_СТРОИТЕЛЬСТВА | D22: Установка осушки газа | E22: Производительность | F22: млн. м3/сут | AF22: Производства стекловолокна и стеклотканей | AG22: Производительность | AH22: тыс. т/год
A23: АВТОМОБИЛЬНЫЕ_ДОРОГИ | D23: Установка регенерации метанола (огневая регенерация) | E23: Производительность | F23: млн. м3/сут | AF23: Производство стеклопластиковых изделий | AG23: Производительность | AH23: тыс. т/год
A24: ОБЪЕКТЫ_ЭНЕРГЕТИКИ_ГЕНЕРАЦИЯ_ЭНЕРГИИ | D24: Установка факельного сепаратора и сборника жидкости | E24: Производительность | F24: млн. м3/сут | AF24: Производство пластмассовых изделий | AG24: Производительность | AH24: тыс. т/год
A25: ОБЪЕКТЫ_ЭНЕРГЕТИКИ_ЭЛЕКТРОСЕТЕВЫЕ_ОБЪЕКТЫ | D25: Установка факела | E25: Производительность | F25: млн. м3/сут | AF25: Производство дренажных гофрированных труб из ПВХ и композиции ПВХ | AG25: Производительность | AH25: тыс. т/год
A26: КОММУНАЛЬНЫЕ_ИНЖЕНЕРНЫЕ_СЕТИ_И_СООРУЖЕНИЯ | D26: Электрокабельные сети | E26: Протяженность | F26: км | AF26: Производство пленки полиэтиленовой | AG26: Производительность | AH26: тыс. т/год
A27: ОБЪЕКТЫ_ВОДОСНАБЖЕНИЯ_И_КАНАЛИЗАЦИИ | D27: Насосная перекачки ГЖ и ЛВЖ | E27: Производительность | F27: м3/час
A28: ОБЪЕКТЫ_МАГИСТРАЛЬНОГО_ТРУБОПРОВОДНОГО_ТРАНСПОРТА_НЕФТИ | D28: Товарно-сырьевой склад ГЖ и ЛВЖ из вертикальных стальных резервуаров | E28: Объём | F28: тыс. м3
A29: ОБЪЕКТЫ_НЕФТЕПЕРЕРАБАТЫВАЮЩЕЙ_И_НЕФТЕХИМИЧЕСКОЙ_ПРОМЫШЛЕННОСТИ | D29: Сливно-наливные установки ГЖ и ЛВЖ, неавтоматизированные для налива в автоцистерны | E29: Количество стояков | F29: шт
A30: ЖЕЛЕЗНЫЕ_ДОРОГИ | D30: Установка приготовления и подачи ингибиторов коррозии ПАВ | E30: Производительность | F30: м3/сут
A31: СИСТЕМЫ_ПРОТИВОПОЖАРНОЙ_И_ОХРАННОЙ_ЗАЩИТЫ | D31: Центральный пункт управления, диспетчерская, операторная, СЭБ, СЭРБ | E31: Площадь | F31: м2
A32: ЗАЩИТНЫЕ_СООРУЖЕНИЯ_ГРАЖДАНСКОЙ_ОБОРОНЫ | D32: Установка компримирования газа на дожимной компрессорной станции | E32: мощность | F32: тыс. кВт
A33: Другое (Указать вручную)

Sheet Форма сметы ПИР (2П)
I1: Форма 2П
A3: СМЕТА №
A4: на проектные работы
B6: Наименование объекта, стадии,
B7: этапа проектных работ
B10: Наименование проектной
B11: (изыскательской) организации
B13: Наименование организации
B14: заказчика
A17: № пп | B17: Характеристика предприятия, здания, сооружения или виды работ | D17: Номер частей, глав, таблиц, процентов, параграфов и пунктов указаний к разделу Справочника базовых цен на проектные и изыскательские работы для строительства | H17: Расчет стоимости: (a+bx)*Ki, или (объем строительно-монтажных работ) * проц./100 или количество x цена | I17: Стоимость, руб.
A18: 1 | B18: 2 | D18: 3 | H18: 4 | I18: 5
B20: Всего по смете:
B22: ВСЕГО текущих ценах в рублях
B24: кроме того НДС 20%
B26: Всего с НДС

Sheet Форма расчета трудозатрат (3П)
H1: Форма 3П
H2: Приложение № ___
H3: к договору №______________________
C4: СМЕТА на проектные работы №
B6: Наименование предприятия, здания, сооружения:
B9: Стадия: | C9: этап:
B11: Наименование организации исполнителя:
B13: Наименование организации заказчика:
B16: Раздел 1. Определение трудоемкости (трудозатрат) выполняемой работы
A18: № п/п | B18: Перечень выполняемых работ | C18: Исполнители | F18: Количество человеко-дней (гр.4 * гр.5) | G18: Средняя зарплата за 1 день | H18: Оплата труда (всего) (гр.6 * гр.7)
C19: должность | D19: Количество
D20: чел | E20: дн
A21: 1 | B21: 2 | C21: 3 | D21: 4 | E21: 5 | F21: 6 | G21: 7 | H21: 8
A22: Разработка документации (вид работ/сооружение)
A23: 1 | B23: Указать сооружение/Вид работ (Указать раздел ТХ, ЭМ, ТК и т.д.) | C23: Начальник отдела | D23: 1 | F23: =E23*D23 -> 0 | H23: =F23*G23 -> 0
C24: Главный специалист | D24: 1 | F24: =E24*D24 -> 0 | H24: =F24*G24 -> 0
C25: Руководитель группы | D25: 1 | F25: =E25*D25 -> 0 | H25: =F25*G25 -> 0
C26: Ведущий инженер | D26: 1 | F26: =E26*D26 -> 0 | H26: =F26*G26 -> 0
C27: Инженер 1-й категории | D27: 1 | F27: =E27*D27 -> 0 | H27: =F27*G27 -> 0
C28: Инженер 2-й категории | D28: 1 | F28: =E28*D28 -> 0 | H28: =F28*G28 -> 0
C29: Инженер 3-й категории | D29: 1 | F29: =E29*D29 -> 0 | H29: =F29*G29 -> 0
C30: Инженер | D30: 1 | F30: =E30*D30 -> 0 | H30: =F30*G30 -> 0
A31: 1 | B31: Указать сооружение/Вид работ (Указать раздел ТХ, ЭМ, ТК и т.д.) | C31: Начальник отдела | D31: 1 | F31: =E31*D31 -> 0 | H31: =F31*G31 -> 0
C32: Главный специалист | D32: 1 | F32: =E32*D32 -> 0 | H32: =F32*G32 -> 0
C33: Руководитель группы | D33: 1 | F33: =E33*D33 -> 0 | H33: =F33*G33 -> 0
C34: Ведущий инженер | D34: 1 | F34: =E34*D34 -> 0 | H34: =F34*G34 -> 0
C35: Инженер 1-й категории | D35: 1 | F35: =E35*D35 -> 0 | H35: =F35*G35 -> 0
C36: Инженер 2-й категории | D36: 1 | F36: =E36*D36 -> 0 | H36: =F36*G36 -> 0
C37: Инженер 3-й категории | D37: 1 | F37: =E37*D37 -> 0 | H37: =F37*G37 -> 0
C38: Инженер | D38: 1 | F38: =E38*D38 -> 0 | H38: =F38*G38 -> 0
B39: Итого з/п непосредственных исполнителей | H39: =SUM(H31:H38) -> 0
B40: Раздел 2. Определение стоимости работ, перечисленных в разделе 1
A41: № п/п | B41: Наименование показателей | G41: Единица измерения | H41: Сумма
A42: 1 | B42: 2 | G42: 3 | H42: 4
A43: .1 | B43: Итого заработная плата непосредственных исполнителей (итог по гр.8 раздела 1) | G43: руб. | H43: =H39 -> 0
A44: .2 | B44: Общая стоимость работы (стр.1) | G44: руб. | H44: =H43 -> 0
A45: .3 | B45: НДС 20% | G45: руб. | H45: =H44*0.2 -> 0
A46: .4 | B46: Всего с НДС | G46: руб. | H46: =H44+H45 -> 0
B47: Средняя стоимость ч.ч. | G47: руб. | H47: =H39/SUM(F23:F38)/8 -> #DIV/0!
B48: Итого по смете:
B51: Главный инженер проекта__________________________________

Sheet Форма расчета трудозатрат Дизай
H1: Форма 3П
H2: Приложение № ___
H3: к договору №______________________
C4: СМЕТА на проектные работы №
B6: Наименование предприятия, здания, сооружения:
B9: Стадия: | C9: этап:
B11: Наименование организации исполнителя:
B13: Наименование организации заказчика:
B16: Раздел 1. Определение трудоемкости (трудозатрат) выполняемой работы
A18: № п/п | B18: Перечень выполняемых работ | C18: Исполнители | F18: Количество человеко-часов (гр.4 * гр.5) | G18: Средняя зарплата за 1 час | H18: Оплата труда (всего) (гр.6 * гр.7)
C19: должность | D19: Количество
D20: чел | E20: час
A21: 1 | B21: 2 | C21: 3 | D21: 4 | E21: 5 | F21: 6 | G21: 7 | H21: 8
A22: 1.1 | B22: Разработка дизайн-проекта интерьера Титул № Общей площадью м2 (вид работ, номер титула/сооружения, площадь м2) | C22: Начальник отдела | D22: 1 | F22: =E22*D22 -> 0 | H22: =F22*G22 -> 0
C23: Главный специалист | D23: 1 | F23: =E23*D23 -> 0 | H23: =F23*G23 -> 0
C24: Руководитель группы | D24: 1 | F24: =E24*D24 -> 0 | H24: =F24*G24 -> 0
C25: Ведущий инженер | D25: 1 | F25: =E25*D25 -> 0 | H25: =F25*G25 -> 0
C26: Инженер 1-й категории | D26: 1 | F26: =E26*D26 -> 0 | H26: =F26*G26 -> 0
C27: Инженер 2-й категории | D27: 1 | F27: =E27*D27 -> 0 | H27: =F27*G27 -> 0
C28: Инженер 3-й категории | D28: 1 | F28: =E28*D28 -> 0 | H28: =F28*G28 -> 0
C29: Инженер | D29: 1 | F29: =E29*D29 -> 0 | H29: =F29*G29 -> 0
C30: Итого з/п непосредственных исполнителей | H30: =SUM(H22:H29) -> 0
C31: Уточняющий коэффициент, при наличии в ТЗ дополнительных требований к детализации (указать № пункта согласно ТЗ ) | H31: 0
B32: Итого з/п непосредственных исполнителей, с учетом уточняющего коэффициента | H32: =-H31*H30 -> 0
B33: Итого стоимость за м2
A35: 1.2 | B35: Разработка дизайн-проекта интерьера Титул № Общей площадью м2 (вид работ, номер титула/сооружения, площадь м2) | C35: Начальник отдела | D35: 1 | F35: =E35*D35 -> 0 | H35: =F35*G35 -> 0
C36: Главный специалист | D36: 1 | F36: =E36*D36 -> 0 | H36: =F36*G36 -> 0
C37: Руководитель группы | D37: 1 | F37: =E37*D37 -> 0 | H37: =F37*G37 -> 0
C38: Ведущий инженер | D38: 1 | F38: =E38*D38 -> 0 | H38: =F38*G38 -> 0
C39: Инженер 1-й категории | D39: 1 | F39: =E39*D39 -> 0 | H39: =F39*G39 -> 0
C40: Инженер 2-й категории | D40: 1 | F40: =E40*D40 -> 0 | H40: =F40*G40 -> 0
C41: Инженер 3-й категории | D41: 1 | F41: =E41*D41 -> 0 | H41: =F41*G41 -> 0
C42: Инженер | D42: 1 | F42: =E42*D42 -> 0 | H42: =F42*G42 -> 0
C43: Итого з/п непосредственных исполнителей | H43: =SUM(H35:H42) -> 0
C44: Уточняющий коэффициент, при наличии в ТЗ дополнительных требований к детализации (указать № пункта согласно ТЗ ) | H44: 0
B45: Итого з/п непосредственных исполнителей, с учетом уточняющего коэффициента | H45: =-H44*H43 -> 0
B46: Итого стоимость за м2
A48: 1.3 | B48: Разработка дизайн-проекта экстерьера Титул № Общей площадью м2 (вид работ, номер титула/сооружения, площадь м2) | C48: Начальник отдела | D48: 1 | F48: =E48*D48 -> 0 | H48: =F48*G48 -> 0
C49: Главный специалист | D49: 1 | F49: =E49*D49 -> 0 | H49: =F49*G49 -> 0
C50: Руководитель группы | D50: 1 | F50: =E50*D50 -> 0 | H50: =F50*G50 -> 0
C51: Ведущий инженер | D51: 1 | F51: =E51*D51 -> 0 | H51: =F51*G51 -> 0
C52: Инженер 1-й категории | D52: 1 | F52: =E52*D52 -> 0 | H52: =F52*G52 -> 0
C53: Инженер 2-й категории | D53: 1 | F53: =E53*D53 -> 0 | H53: =F53*G53 -> 0
C54: Инженер 3-й категории | D54: 1 | F54: =E54*D54 -> 0 | H54: =F54*G54 -> 0
C55: Инженер | D55: 1 | F55: =E55*D55 -> 0 | H55: =F55*G55 -> 0
C56: Итого з/п непосредственных исполнителей | H56: =SUM(H48:H55) -> 0
C57: Уточняющий коэффициент, при наличии в ТЗ дополнительных требований к детализации (указать № пункта согласно ТЗ ) | H57: 0
B58: Итого з/п непосредственных исполнителей, с учетом уточняющего коэффициента | H58: =-H57*H56 -> 0
B59: Итого стоимость за м2
B60: Раздел 2. Определение стоимости работ, перечисленных в разделе 1
A61: № п/п | B61: Наименование показателей | G61: Единица измерения | H61: Сумма
A62: 1 | B62: 2 | G62: 3 | H62: 4
A63: .1 | B63: Итого заработная плата непосредственных исполнителей (итог по гр.8 раздела 1) | G63: руб. | H63: =H58+H32+H45 -> 0
A64: .2 | B64: Коэффициент отношения заработной платы основного производственного персонала (непосредственных исполнителей) организации к себестоимости работ (услуг) | G64: ед. | H64: 0
A65: .3 | B65: Себестоимость исходя из установленного коэффициента (стр.1:стр.2) | G65: руб. | H65: =ROUND(H63/H64,3) -> #DIV/0!
A66: .4 | B66: Прибыль (%) | G66: руб. | H66: =H65*0.08 -> #DIV/0!
A67: .5 | B67: Стоимость работы (стр.3 +стр.4) | G67: руб. | H67: =H66+H65 -> #DIV/0!
A68: .6 | B68: Общая стоимость работы (стр.5) | G68: руб. | H68: =H67 -> #DIV/0!
A69: .7 | B69: НДС 20% | G69: руб. | H69: =H68*0.2 -> #DIV/0!
A70: .8 | B70: Всего с НДС | G70: руб. | H70: =H68+H69 -> #DIV/0!
B72: Итого по смете:
B75: Главный инженер проекта__________________________________

Sheet Форма расчета трудозатрат НТС
H1: Форма 3П
H2: Приложение № ___
H3: к договору №______________________
C4: СМЕТА на проектные работы №
B6: Наименование предприятия, здания, сооружения:
B9: Стадия: | C9: этап:
B11: Наименование организации исполнителя:
B13: Наименование организации заказчика:
B16: Раздел 1. Определение трудоемкости (трудозатрат) выполняемой работы
A18: № п/п | B18: Перечень выполняемых работ | C18: Исполнители | F18: Количество человеко-часов (гр.4 * гр.5) | G18: Средняя зарплата за 1 час | H18: Оплата труда (всего) (гр.6 * гр.7)
C19: должность | D19: Количество
D20: чел | E20: час
A21: 1 | B21: 2 | C21: 3 | D21: 4 | E21: 5 | F21: 6 | G21: 7 | H21: 8
A22: 1.1 | B22: Научно-технического сопровождения для зданий и сооружений повышенного уровня ответственности (КС-3), Титул № (вид работ, № титула/наименование сооружения, для каждого титула/сооружения) | C22: Начальник отдела | D22: 1 | F22: =E22*D22 -> 0 | H22: =F22*G22 -> 0
C23: Главный специалист | D23: 1 | F23: =E23*D23 -> 0 | H23: =F23*G23 -> 0
C24: Руководитель группы | D24: 1 | F24: =E24*D24 -> 0 | H24: =F24*G24 -> 0
C25: Ведущий инженер | D25: 1 | F25: =E25*D25 -> 0 | H25: =F25*G25 -> 0
C26: Инженер 1-й категории | D26: 1 | F26: =E26*D26 -> 0 | H26: =F26*G26 -> 0
C27: Инженер 2-й категории | D27: 1 | F27: =E27*D27 -> 0 | H27: =F27*G27 -> 0
C28: Инженер 3-й категории | D28: 1 | F28: =E28*D28 -> 0 | H28: =F28*G28 -> 0
C29: Инженер | D29: 1 | F29: =E29*D29 -> 0 | H29: =F29*G29 -> 0
C30: Итого з/п непосредственных исполнителей | H30: =SUM(H22:H29) -> 0
C31: Уточняющий коэффициент, в связи с наличием однотипных задний и сооружений, наличием уникальных задний сооружений (указать при их наличии) | H31: 0
B32: Итого з/п непосредственных исполнителей, с учетом уточняющего коэффициента | H32: =H30*H31 -> 0
B33: Итого стоимость за Титул №
A35: 1.2 | B35: Научно-технического сопровождения для зданий и сооружений повышенного уровня ответственности (КС-3), Титул № (вид работ, № титула/наименование сооружения, для каждого титула/сооружения) | C35: Начальник отдела | D35: 1 | F35: =E35*D35 -> 0 | H35: =F35*G35 -> 0
C36: Главный специалист | D36: 1 | F36: =E36*D36 -> 0 | H36: =F36*G36 -> 0
C37: Руководитель группы | D37: 1 | F37: =E37*D37 -> 0 | H37: =F37*G37 -> 0
C38: Ведущий инженер | D38: 1 | F38: =E38*D38 -> 0 | H38: =F38*G38 -> 0
C39: Инженер 1-й категории | D39: 1 | F39: =E39*D39 -> 0 | H39: =F39*G39 -> 0
C40: Инженер 2-й категории | D40: 1 | F40: =E40*D40 -> 0 | H40: =F40*G40 -> 0
C41: Инженер 3-й категории | D41: 1 | F41: =E41*D41 -> 0 | H41: =F41*G41 -> 0
C42: Инженер | D42: 1 | F42: =E42*D42 -> 0 | H42: =F42*G42 -> 0
C43: Итого з/п непосредственных исполнителей | H43: =SUM(H35:H42) -> 0
C44: Уточняющий коэффициент, в связи с наличием однотипных задний и сооружений, наличием уникальных задний сооружений (указать при их наличии) | H44: 0
B45: Итого з/п непосредственных исполнителей, с учетом уточняющего коэффициента | H45: =H43*H44 -> 0
B46: Итого стоимость за Титул №
A48: 1.3 | B48: Дополнительные виды работ согласно ТЗ (указать № пункта согласно ТЗ ) | C48: Начальник отдела | D48: 1 | F48: =E48*D48 -> 0 | H48: =F48*G48 -> 0
C49: Главный специалист | D49: 1 | F49: =E49*D49 -> 0 | H49: =F49*G49 -> 0
C50: Руководитель группы | D50: 1 | F50: =E50*D50 -> 0 | H50: =F50*G50 -> 0
C51: Ведущий инженер | D51: 1 | F51: =E51*D51 -> 0 | H51: =F51*G51 -> 0
C52: Инженер 1-й категории | D52: 1 | F52: =E52*D52 -> 0 | H52: =F52*G52 -> 0
C53: Инженер 2-й категории | D53: 1 | F53: =E53*D53 -> 0 | H53: =F53*G53 -> 0
C54: Инженер 3-й категории | D54: 1 | F54: =E54*D54 -> 0 | H54: =F54*G54 -> 0
C55: Инженер | D55: 1 | F55: =E55*D55 -> 0 | H55: =F55*G55 -> 0
B56: Итого з/п непосредственных исполнителей | H56: =SUM(H48:H55) -> 0
B58: Раздел 2. Определение стоимости работ, перечисленных в разделе 1
A59: № п/п | B59: Наименование показателей | G59: Единица измерения | H59: Сумма
A60: 1 | B60: 2 | G60: 3 | H60: 4
A61: .1 | B61: Итого заработная плата непосредственных исполнителей (итог по гр.8 раздела 1) | G61: руб. | H61: =H56+H32+H45 -> 0
A62: .2 | B62: Коэффициент отношения заработной платы основного производственного персонала (непосредственных исполнителей) организации к себестоимости работ (услуг) | G62: ед.
A63: .3 | B63: Себестоимость исходя из установленного коэффициента (стр.1:стр.2) | G63: руб. | H63: =IFERROR(ROUND(H61/H62,3),H61) -> 0
A64: .4 | B64: % рентабельности | G64: руб.
A65: .4 | B65: Прибыль | G65: руб. | H65: =H63*H64 -> 0
A66: .5 | B66: Стоимость работы (стр.3 +стр.4) | G66: руб. | H66: =H65+H63 -> 0
A67: .6 | B67: Общая стоимость работы (стр.5) | G67: руб. | H67: =H66 -> 0
A68: .7 | B68: НДС 20% | G68: руб. | H68: =H67*0.2 -> 0
A69: .8 | B69: Всего с НДС | G69: руб. | H69: =H67+H68 -> 0
B71: Итого по смете:
B74: Главный инженер проекта__________________________________
