Workbook

Sheet Лист1
C1: Форма для заполнения по тендерной процедуре №ТП.....
A2: Разработка проектной и рабочей документации объекта "Перевод установки получения масляных альдегидов методом оксосинтеза на Rh катализатор с наращением мощности по 2-ЭГ и 2-ЭГК на АО «Сибур-Химпром»
A4: № п/п | B4: Наименование показателей | C4: Претендент
A6: Соответствие техническому заданию.
A7: п. 4.10 Смета на строительство объектов капитального строительства
A8: 1. | B8: Разработка сметной документации в 2-х форматах: - ресурсным методом -базисно индексным методом
A9: 2. | B9: Базисно-индексный метод:
A10: 2.1 | B10: По основным (ценообразующим) материалам и вспомогательному оборудованию провести мониторинг рынка поставщиков
A11: 2.2 | B11: Предоставить ведомости объемов работ к каждому расчету за подписью разработчика марки проекта.
A12: 2.3 | B12: Предоставить ведомости материалов с построчной стоимостью ресурсов
A13: 2.4 | B13: Предоставить ведомости оборудования с построчной стоимостью ресурсов
A14: 2.5 | B14: В локальных сметных расчетах учесть разделение ТМЦ поставки Заказчик / Подрядчик.
A15: 2.6 | B15: Базисно-индексным методом: локальные сметные расчеты выполнить в сметно-нормативной базе ФЕР-2001 в ред.2017 (с изм.1-4) в программном комплексе «Гранд-Смета» с применением индексов пересчета по статьям затрат Пермского Регионального Центра Ценообразования (ПРЦЦС).
A16: 2.7 | B16: Сметную документацию (для БИМ) сформировать в составе: - сводный сметный расчет; - объектные сметные расчеты; - локальные сметные расчеты ; - ведомости объемов работ; - ведомости ресурсов; - ведомости оборудования
A17: 3. | B17: Ресурсный метод:
A18: 3.1 | B18: Ресурсные ведомости под каждую единичную расценку (ЕР) и титул
A19: 3.2 | B19: Для определения стоимости ресурсов использовать текущие цены на ресурсы, согласованные с Заказчиком.
... A26: 6. | B26: Предоставить пояснительную записку по формированию стоимости с указанием перечня затрат, возможных к реализации, но не учтенных в стоимости строительства

Sheet СВОД
C1: Форма для заполнения по тендерной процедуре № __________
A3: Разработка рабочей документации по проекту «Техническое перевооружение узла очистки, осушки и регазификации этилена на площадке Казанской компрессорной станции магистрального продуктопровода (этилен) Нижнекамск-Казань Татарстанского линейно-производственного управления ООО «УЭТП-НКНХ»
A5: № п/п | B5: Наименование показателей | C5: Стоимость, руб. без НДС
A7: 1 | B7: Итого стоимость предложения | C7: =КП!G20 -> 82828575
B8: Итого стоимость предложения | C8: =C7 -> 82828575
B11: ОАО "Сибнефтетранспроект"
B13: Главный инженер
B14: Крупников Антон Владимирович
B15: 45825 | D15: ( подпись, M.П.)

Sheet КП
G1: Форма для заполнения по тендерной процедуре №…….
A3: Разработка рабочей документации по проекту «Техническое перевооружение узла очистки, осушки и регазификации этилена на площадке Казанской компрессорной станции магистрального продуктопровода (этилен) Нижнекамск-Казань Татарстанского линейно-производственного управления ООО «УЭТП-НКНХ». Календарный план.
A5: Этапы № п/п | B5: Наименование Этапа | C5: Отчетная документация | D5: Дата начала | E5: Дата окончания* | F5: Перечень пунктов из формы ТКП входящих в этап | G5: Стоимость, руб. без НДС
D6: Перечень пунктов из | E6: Перечень пунктов из | F6: Перечень пунктов из
A7: 1 | B7: =РД!B182 -> Сбор исходных данных. | C7: Отчеты | D7: 45839 | E7: =E9 -> 45912 | F7: 4.1. | G7: =РД!C182 -> 2466021.5
A8: 2 | B8: =РД!B160 -> Инженерные Изыскания | C8: Отчеты | D8: =D7+14 -> 45853 | E8: =E7 -> 45912 | F8: 3.1.-3.3. | G8: =РД!C160 -> 8533475.6
A9: 3 | B9: =РД!B190 -> Обследование существующих строительных конструкций | C9: Отчеты | D9: =D7+14 -> 45853 | E9: =D9+45+14 -> 45912 | F9: 5.1.-5.3. | G9: =РД!C190 -> 6258438.2
A10: 4 | B10: =РД!B212 -> Проектное технологическое обследование объекта | C10: Отчеты | D10: =D9 -> 45853 | E10: =E9 -> 45912 | F10: 6.1.-6.2. | G10: =РД!C212 -> 5138011.9
A11: 5 | B11: =РД!B220 -> Разработка рабочей документации | C11: Документация | D11: =E8-18 -> 45894 | E11: =D11+46+14 -> 45954 | F11: 7.1.-7.8. | G11: =РД!C220 -> 25983500
A12: 6 | B12: =РД!B53 -> Пояснительная записка для ЭПБ на техническое перевооружение | C12: Документация | D12: =D11 -> 45894 | E12: =E11 -> 45954 | F12: 2.1.-2.9 | G12: =РД!C53 -> 6422003.9
A13: 7 | B13: =РД!B373 -> Выполнение проектных расчетов. Оформление передача заказчику. | C13: Расчеты | D13: =D14 -> 45894 | E13: =E14 -> 45954 | F13: 13.1.-13.7. | G13: =РД!C373 -> 5919023.3
A14: 8 | B14: =РД!B329 -> Смежные работы | C14: Отчеты | D14: =D11 -> 45894 | E14: =E11 -> 45954 | F14: 11.1.-11.5. | G14: =РД!C329 -> 12971781
A15: 9 | B15: =РД!B10 -> Расчет ключевых физических объемов | C15: Отчеты | D15: =D14+14 -> 45908 | E15: =E14-14+7 -> 45947 | F15: 1.1.-1.6. | G15: =РД!C10 -> 4567418.2
A16: 10 | B16: =РД!B292 -> Сессии VE (Value Engineering) | C16: Отчеты | D16: =D11+30 -> 45924 | E16: =D16+14 -> 45938 | F16: 9.1.-9.2. | G16: =РД!C292 -> 224446.08
A17: 11 | B17: =РД!B284 -> Отчетная документация по проекту | C17: Отчеты | D17: =D8 -> 45853 | E17: =E18 -> 45978 | F17: 8.1. | G17: =РД!C284 -> 565123.2
A18: 12 | B18: =РД!B307 -> Эксплуатационная документация | C18: Документация | D18: =E16+7 -> 45945 | E18: =D18+19+14 -> 45978 | F18: 10.1.-10.5. | G18: =РД!C307 -> 3052887.5
A19: 13 | B19: =РД!B365 -> Электронный документооборот | C19: Акт | D19: =D18 -> 45945 | E19: =E18 -> 45978 | F19: 12.1 | G19: =РД!C365 -> 726443.76
B20: Итого стоимость предложения | G20: =SUM(G7:H19) -> 82828575
B21: * - Датой окончания является дата подписания Заказчиком акта приемки выполненных работ
B23: Наименование организации
B25: ОАО "Сибнефтетранспроект"
B26: Главный инженер
B27: Крупников Антон Владимирович
B28: 45825 | G28: ( подпись, M.П.)

Sheet РД
C1: Форма для заполнения по тендерной процедуре №ТП.....
A2: Разработка рабочей документации по проекту «Техническое перевооружение узла очистки, осушки и регазификации этилена на площадке Казанской компрессорной станции магистрального продуктопровода (этилен) Нижнекамск-Казань Татарстанского линейно-производственного управления ООО «УЭТП-НКНХ»
C4: (заполняется участником)
A5: № п/п | B5: Наименование показателей | C5: Стоимость, руб. без НДС | D5: Трудозатраты чел.час | E5: Трудозатраты чел.дни | F5: Наименование подрядчика | G5: Обоснование расчета*
G7: Должность | H7: Оценка количества листов документации | J7: чел. | K7: Дней | L7: Дней | M7: Часов | N7: Ст-ть чел. часа (руб.) без НДС | O7: Итого Ст-ть (руб.) без НДС | P7: Итого кол. чел.час
H8: (текст.) ф.А4 | I8: (граф.) ф.А1 | R8: K= | S8: 1
A9: Соответствие техническому заданию стадии ОТР
A10: 1. | B10: Расчет ключевых физических объемов | C10: =SUBTOTAL(9,C11:C52) -> 4567418.2 | D10: =SUBTOTAL(9,D11:D52) -> 1653.28 | E10: =SUBTOTAL(9,E11:E52) -> 206.66
A11: 1.1. | B11: Формирование перечня Ключевых физических объемов изделий, материалов, работ | C11: =SUM(,O11:O17) -> 2064002.6 | D11: =SUM(,P11:P17) -> 780.16 | E11: =D11/8 -> 97.52 | G11: ГИП | J11: 1 | K11: =L11*$S$8 -> 0.42 | L11: 0.42 | M11: 8 | N11: =DATA!$D$2 -> 5009.96 | O11: =N11*J11*K11*M11 -> 16833.466 | P11: =J11*K11*M11 -> 3.36
G12: Нач. отдела | J12: 5 | K12: =L12*$S$8 -> 0.42 | L12: 0.42 | M12: 8 | N12: =DATA!$D$3 -> 4508.96 | O12: =N12*J12*K12*M12 -> 75750.528 | P12: =J12*K12*M12 -> 16.8
G13: Гл. специалист | J13: 5 | K13: =L13*$S$8 -> 1.5 | L13: 1.5 | M13: 8 | N13: =DATA!$D$4 -> 3757.47 | O13: =N13*J13*K13*M13 -> 225448.2 | P13: =J13*K13*M13 -> 60
G14: Рук. Группы | J14: 5 | K14: =L14*$S$8 -> 1.5 | L14: 1.5 | M14: 8 | N14: =DATA!$D$5 -> 3381.72 | O14: =N14*J14*K14*M14 -> 202903.2 | P14: =J14*K14*M14 -> 60
G15: Вед. инженер | J15: 5 | K15: =L15*$S$8 -> 10 | L15: 10 | M15: 8 | N15: =DATA!$D$6 -> 2504.98 | O15: =N15*J15*K15*M15 -> 1001992 | P15: =J15*K15*M15 -> 400
G16: Старший инженер | J16: 3 | K16: =L16*$S$8 -> 10 | L16: 10 | M16: 8 | N16: =DATA!$D$7 -> 2254.48 | O16: =N16*J16*K16*M16 -> 541075.2 | P16: =J16*K16*M16 -> 240
G17: Инженер
A18: 1.2. | B18: Предоставить ведомости объемов работ в формате BOQ (Описание выполняемых работ/объемы) | C18: =SUM(,O18:O24) -> 929748.03 | D18: =SUM(,P18:P24) -> 308.16 | E18: =D18/8 -> 38.52 | G18: ГИП | J18: 1 | K18: =L18*$S$8 -> 0.42 | L18: 0.42 | M18: 8 | N18: =DATA!$D$2 -> 5009.96 | O18: =N18*J18*K18*M18 -> 16833.466 | P18: =J18*K18*M18 -> 3.36
G19: Нач. отдела | J19: 5 | K19: =L19*$S$8 -> 0.42 | L19: 0.42 | M19: 8 | N19: =DATA!$D$3 -> 4508.96 | O19: =N19*J19*K19*M19 -> 75750.528 | P19: =J19*K19*M19 -> 16.8
G20: Гл. специалист | J20: 5 | K20: =L20*$S$8 -> 1.5 | L20: 1.5 | M20: 8 | N20: =DATA!$D$4 -> 3757.47 | O20: =N20*J20*K20*M20 -> 225448.2 | P20: =J20*K20*M20 -> 60
G21: Рук. Группы | J21: 5 | K21: =L21*$S$8 -> 1.5 | L21: 1.5 | M21: 8 | N21: =DATA!$D$5 -> 3381.72 | O21: =N21*J21*K21*M21 -> 202903.2 | P21: =J21*K21*M21 -> 60
G22: Вед. инженер | J22: 5 | K22: =L22*$S$8 -> 3 | L22: 3 | M22: 8 | N22: =DATA!$D$6 -> 2504.98 | O22: =N22*J22*K22*M22 -> 300597.6 | P22: =J22*K22*M22 -> 120
G23: Старший инженер | J23: 2 | K23: =L23*$S$8 -> 3 | L23: 3 | M23: 8 | N23: =DATA!$D$7 -> 2254.48 | O23: =N23*J23*K23*M23 -> 108215.04 | P23: =J23*K23*M23 -> 48
G24: Инженер
A25: 1.3. | B25: Предоставление ведомостей материалов с построчной стоимостью ресурсов (BOM) | C25: =SUM(,O25:O31) -> 604240.88 | D25: =SUM(,P25:P31) -> 226.08 | E25: =D25/8 -> 28.26 | G25: ГИП | J25: 1 | K25: =L25*$S$8 -> 0.42 | L25: 0.42 | M25: 8 | N25: =DATA!$D$2 -> 5009.96 | O25: =N25*J25*K25*M25 -> 16833.466 | P25: =J25*K25*M25 -> 3.36
G26: Нач. отдела | J26: 2 | K26: =L26*$S$8 -> 0.42 | L26: 0.42 | M26: 8 | N26: =DATA!$D$3 -> 4508.96 | O26: =N26*J26*K26*M26 -> 30300.211 | P26: =J26*K26*M26 -> 6.72
G27: Гл. специалист | J27: 2 | K27: =L27*$S$8 -> 1.5 | L27: 1.5 | M27: 8 | N27: =DATA!$D$4 -> 3757.47 | O27: =N27*J27*K27*M27 -> 90179.28 | P27: =J27*K27*M27 -> 24
G28: Рук. Группы | J28: 2 | K28: =L28*$S$8 -> 1.5 | L28: 1.5 | M28: 8 | N28: =DATA!$D$5 -> 3381.72 | O28: =N28*J28*K28*M28 -> 81161.28 | P28: =J28*K28*M28 -> 24
G29: Вед. инженер | J29: 1 | K29: =L29*$S$8 -> 7 | L29: 7 | M29: 8 | N29: =DATA!$D$6 -> 2504.98 | O29: =N29*J29*K29*M29 -> 140278.88 | P29: =J29*K29*M29 -> 56
G30: Старший инженер | J30: 1 | K30: =L30*$S$8 -> 7 | L30: 7 | M30: 8 | N30: =DATA!$D$7 -> 2254.48 | O30: =N30*J30*K30*M30 -> 126250.88 | P30: =J30*K30*M30 -> 56
G31: Инженер | J31: 1 | K31: =L31*$S$8 -> 7 | L31: 7 | M31: 8 | N31: =DATA!$D$8 -> 2129.23 | O31: =N31*J31*K31*M31 -> 119236.88 | P31: =J31*K31*M31 -> 56
A32: 1.4. | B32: Предоставление ведомостей оборудования с построчной стоимостью ресурсов (BOE) | C32: =SUM(,O32:O38) -> 343222.16 | D32: =SUM(,P32:P38) -> 118.08 | E32: =D32/8 -> 14.76 | G32: ГИП | J32: 1 | K32: =L32*$S$8 -> 0.42 | L32: 0.42 | M32: 8 | N32: =DATA!$D$2 -> 5009.96 | O32: =N32*J32*K32*M32 -> 16833.466 | P32: =J32*K32*M32 -> 3.36
G33: Нач. отдела | J33: 2 | K33: =L33*$S$8 -> 0.42 | L33: 0.42 | M33: 8 | N33: =DATA!$D$3 -> 4508.96 | O33: =N33*J33*K33*M33 -> 30300.211 | P33: =J33*K33*M33 -> 6.72
G34: Гл. специалист | J34: 2 | K34: =L34*$S$8 -> 1.5 | L34: 1.5 | M34: 8 | N34: =DATA!$D$4 -> 3757.47 | O34: =N34*J34*K34*M34 -> 90179.28 | P34: =J34*K34*M34 -> 24
G35: Рук. Группы | J35: 1 | K35: =L35*$S$8 -> 1.5 | L35: 1.5 | M35: 8 | N35: =DATA!$D$5 -> 3381.72 | O35: =N35*J35*K35*M35 -> 40580.64 | P35: =J35*K35*M35 -> 12
G36: Вед. инженер | J36: 1 | K36: =L36*$S$8 -> 3 | L36: 3 | M36: 8 | N36: =DATA!$D$6 -> 2504.98 | O36: =N36*J36*K36*M36 -> 60119.52 | P36: =J36*K36*M36 -> 24
G37: Старший инженер | J37: 1 | K37: =L37*$S$8 -> 3 | L37: 3 | M37: 8 | N37: =DATA!$D$7 -> 2254.48 | O37: =N37*J37*K37*M37 -> 54107.52 | P37: =J37*K37*M37 -> 24
G38: Инженер | J38: 1 | K38: =L38*$S$8 -> 3 | L38: 3 | M38: 8 | N38: =DATA!$D$8 -> 2129.23 | O38: =N38*J38*K38*M38 -> 51101.52 | P38: =J38*K38*M38 -> 24
A39: 1.5. | B39: Предоставление ведомостей дефектов (BOD) | C39: =SUM(,O39:O45) -> 343222.16 | D39: =SUM(,P39:P45) -> 118.08 | E39: =D39/8 -> 14.76 | G39: ГИП | J39: 1 | K39: =L39*$S$8 -> 0.42 | L39: 0.42 | M39: 8 | N39: =DATA!$D$2 -> 5009.96 | O39: =N39*J39*K39*M39 -> 16833.466 | P39: =J39*K39*M39 -> 3.36
G40: Нач. отдела | J40: 2 | K40: =L40*$S$8 -> 0.42 | L40: 0.42 | M40: 8 | N40: =DATA!$D$3 -> 4508.96 | O40: =N40*J40*K40*M40 -> 30300.211 | P40: =J40*K40*M40 -> 6.72
G41: Гл. специалист | J41: 2 | K41: =L41*$S$8 -> 1.5 | L41: 1.5 | M41: 8 | N41: =DATA!$D$4 -> 3757.47 | O41: =N41*J41*K41*M41 -> 90179.28 | P41: =J41*K41*M41 -> 24
G42: Рук. Группы | J42: 1 | K42: =L42*$S$8 -> 1.5 | L42: 1.5 | M42: 8 | N42: =DATA!$D$5 -> 3381.72 | O42: =N42*J42*K42*M42 -> 40580.64 | P42: =J42*K42*M42 -> 12
G43: Вед. инженер | J43: 1 | K43: =L43*$S$8 -> 3 | L43: 3 | M43: 8 | N43: =DATA!$D$6 -> 2504.98 | O43: =N43*J43*K43*M43 -> 60119.52 | P43: =J43*K43*M43 -> 24
G44: Старший инженер | J44: 1 | K44: =L44*$S$8 -> 3 | L44: 3 | M44: 8 | N44: =DATA!$D$7 -> 2254.48 | O44: =N44*J44*K44*M44 -> 54107.52 | P44: =J44*K44*M44 -> 24
G45: Инженер | J45: 1 | K45: =L45*$S$8 -> 3 | L45: 3 | M45: 8 | N45: =DATA!$D$8 -> 2129.23 | O45: =N45*J45*K45*M45 -> 51101.52 | P45: =J45*K45*M45 -> 24
A46: 1.6. | B46: Перечень основного и вспомогательного оборудования | C46: =SUM(,O46:O52) -> 282982.41 | D46: =SUM(,P46:P52) -> 102.72 | E46: =D46/8 -> 12.84 | G46: ГИП | J46: 1 | K46: =L46*$S$8 -> 0.42 | L46: 0.42 | M46: 8 | N46: =DATA!$D$2 -> 5009.96 | O46: =N46*J46*K46*M46 -> 16833.466 | P46: =J46*K46*M46 -> 3.36
G47: Нач. отдела | J47: 1 | K47: =L47*$S$8 -> 0.42 | L47: 0.42 | M47: 8 | N47: =DATA!$D$3 -> 4508.96 | O47: =N47*J47*K47*M47 -> 15150.106 | P47: =J47*K47*M47 -> 3.36
G48: Гл. специалист | J48: 1 | K48: =L48*$S$8 -> 1.5 | L48: 1.5 | M48: 8 | N48: =DATA!$D$4 -> 3757.47 | O48: =N48*J48*K48*M48 -> 45089.64 | P48: =J48*K48*M48 -> 12
G49: Рук. Группы | J49: 1 | K49: =L49*$S$8 -> 1.5 | L49: 1.5 | M49: 8 | N49: =DATA!$D$5 -> 3381.72 | O49: =N49*J49*K49*M49 -> 40580.64 | P49: =J49*K49*M49 -> 12
G50: Вед. инженер | J50: 1 | K50: =L50*$S$8 -> 3 | L50: 3 | M50: 8 | N50: =DATA!$D$6 -> 2504.98 | O50: =N50*J50*K50*M50 -> 60119.52 | P50: =J50*K50*M50 -> 24
G51: Старший инженер | J51: 1 | K51: =L51*$S$8 -> 3 | L51: 3 | M51: 8 | N51: =DATA!$D$7 -> 2254.48 | O51: =N51*J51*K51*M51 -> 54107.52 | P51: =J51*K51*M51 -> 24
G52: Инженер | J52: 1 | K52: =L52*$S$8 -> 3 | L52: 3 | M52: 8 | N52: =DATA!$D$8 -> 2129.23 | O52: =N52*J52*K52*M52 -> 51101.52 | P52: =J52*K52*M52 -> 24
A53: 2. | B53: Пояснительная записка для ЭПБ на техническое перевооружение | C53: =SUBTOTAL(9,C54:C159) -> 6422003.9 | D53: =SUBTOTAL(9,D54:D159) -> 2315.84 | E53: =SUBTOTAL(9,E54:E159) -> 199.6
A54: 2.1. | B54: Раздел 1. Пояснительная записка. | C54: =SUM(,O54:O60) -> 282982.41 | D54: =SUM(,P54:P60) -> 102.72 | E54: =D54/8 -> 12.84 | G54: ГИП | J54: 1 | K54: =L54*$S$8 -> 0.42 | L54: 0.42 | M54: 8 | N54: =DATA!$D$2 -> 5009.96 | O54: =N54*J54*K54*M54 -> 16833.466 | P54: =J54*K54*M54 -> 3.36
G55: Нач. отдела | J55: 1 | K55: =L55*$S$8 -> 0.42 | L55: 0.42 | M55: 8 | N55: =DATA!$D$3 -> 4508.96 | O55: =N55*J55*K55*M55 -> 15150.106 | P55: =J55*K55*M55 -> 3.36
G56: Гл. специалист | J56: 1 | K56: =L56*$S$8 -> 1.5 | L56: 1.5 | M56: 8 | N56: =DATA!$D$4 -> 3757.47 | O56: =N56*J56*K56*M56 -> 45089.64 | P56: =J56*K56*M56 -> 12
G57: Рук. Группы | J57: 1 | K57: =L57*$S$8 -> 1.5 | L57: 1.5 | M57: 8 | N57: =DATA!$D$5 -> 3381.72 | O57: =N57*J57*K57*M57 -> 40580.64 | P57: =J57*K57*M57 -> 12
G58: Вед. инженер | J58: 1 | K58: =L58*$S$8 -> 3 | L58: 3 | M58: 8 | N58: =DATA!$D$6 -> 2504.98 | O58: =N58*J58*K58*M58 -> 60119.52 | P58: =J58*K58*M58 -> 24
G59: Старший инженер | J59: 1 | K59: =L59*$S$8 -> 3 | L59: 3 | M59: 8 | N59: =DATA!$D$7 -> 2254.48 | O59: =N59*J59*K59*M59 -> 54107.52 | P59: =J59*K59*M59 -> 24
G60: Инженер | J60: 1 | K60: =L60*$S$8 -> 3 | L60: 3 | M60: 8 | N60: =DATA!$D$8 -> 2129.23 | O60: =N60*J60*K60*M60 -> 51101.52 | P60: =J60*K60*M60 -> 24
A61: 2.2. | B61: Раздел 2. Схема планировочной организации земельного участка. | C61: =SUM(,O61:O67) -> 323062.09 | D61: =SUM(,P61:P67) -> 118.72 | E61: =D61/8 -> 14.84 | G61: ГИП | J61: 1 | K61: =L61*$S$8 -> 0.42 | L61: 0.42 | M61: 8 | N61: =DATA!$D$2 -> 5009.96 | O61: =N61*J61*K61*M61 -> 16833.466 | P61: =J61*K61*M61 -> 3.36
G62: Нач. отдела | J62: 1 | K62: =L62*$S$8 -> 0.42 | L62: 0.42 | M62: 8 | N62: =DATA!$D$3 -> 4508.96 | O62: =N62*J62*K62*M62 -> 15150.106 | P62: =J62*K62*M62 -> 3.36
G63: Гл. специалист | J63: 1 | K63: =L63*$S$8 -> 1.5 | L63: 1.5 | M63: 8 | N63: =DATA!$D$4 -> 3757.47 | O63: =N63*J63*K63*M63 -> 45089.64 | P63: =J63*K63*M63 -> 12
G64: Рук. Группы | J64: 1 | K64: =L64*$S$8 -> 1.5 | L64: 1.5 | M64: 8 | N64: =DATA!$D$5 -> 3381.72 | O64: =N64*J64*K64*M64 -> 40580.64 | P64: =J64*K64*M64 -> 12
G65: Вед. инженер | J65: 1 | K65: =L65*$S$8 -> 5 | L65: 5 | M65: 8 | N65: =DATA!$D$6 -> 2504.98 | O65: =N65*J65*K65*M65 -> 100199.2 | P65: =J65*K65*M65 -> 40
G66: Старший инженер | J66: 1 | K66: =L66*$S$8 -> 3 | L66: 3 | M66: 8 | N66: =DATA!$D$7 -> 2254.48 | O66: =N66*J66*K66*M66 -> 54107.52 | P66: =J66*K66*M66 -> 24
G67: Инженер | J67: 1 | K67: =L67*$S$8 -> 3 | L67: 3 | M67: 8 | N67: =DATA!$D$8 -> 2129.23 | O67: =N67*J67*K67*M67 -> 51101.52 | P67: =J67*K67*M67 -> 24
A68: 2.3. | B68: Раздел 3. Архитектурные решения. | C68: =SUM(,O68:O74) -> 247912.73 | D68: =SUM(,P68:P74) -> 86.72 | E68: =D68/8 -> 10.84 | G68: ГИП | J68: 1 | K68: =L68*$S$8 -> 0.42 | L68: 0.42 | M68: 8 | N68: =DATA!$D$2 -> 5009.96 | O68: =N68*J68*K68*M68 -> 16833.466 | P68: =J68*K68*M68 -> 3.36
G69: Нач. отдела | J69: 1 | K69: =L69*$S$8 -> 0.42 | L69: 0.42 | M69: 8 | N69: =DATA!$D$3 -> 4508.96 | O69: =N69*J69*K69*M69 -> 15150.106 | P69: =J69*K69*M69 -> 3.36
G70: Гл. специалист | J70: 1 | K70: =L70*$S$8 -> 1.5 | L70: 1.5 | M70: 8 | N70: =DATA!$D$4 -> 3757.47 | O70: =N70*J70*K70*M70 -> 45089.64 | P70: =J70*K70*M70 -> 12
G71: Рук. Группы | J71: 1 | K71: =L71*$S$8 -> 1.5 | L71: 1.5 | M71: 8 | N71: =DATA!$D$5 -> 3381.72 | O71: =N71*J71*K71*M71 -> 40580.64 | P71: =J71*K71*M71 -> 12
G72: Вед. инженер | J72: 1 | K72: =L72*$S$8 -> 3 | L72: 3 | M72: 8 | N72: =DATA!$D$6 -> 2504.98 | O72: =N72*J72*K72*M72 -> 60119.52 | P72: =J72*K72*M72 -> 24
G73: Старший инженер | J73: 1 | K73: =L73*$S$8 -> 2 | L73: 2 | M73: 8 | N73: =DATA!$D$7 -> 2254.48 | O73: =N73*J73*K73*M73 -> 36071.68 | P73: =J73*K73*M73 -> 16
G74: Инженер | J74: 1 | K74: =L74*$S$8 -> 2 | L74: 2 | M74: 8 | N74: =DATA!$D$8 -> 2129.23 | O74: =N74*J74*K74*M74 -> 34067.68 | P74: =J74*K74*M74 -> 16
A75: 2.4. | B75: Раздел 4. Конструктивные и объемно-планировочные решения. | C75: =SUM(,O75:O81) -> 418251.29 | D75: =SUM(,P75:P81) -> 158.72 | E75: =D75/8 -> 19.84 | G75: ГИП | J75: 1 | K75: =L75*$S$8 -> 0.42 | L75: 0.42 | M75: 8 | N75: =DATA!$D$2 -> 5009.96 | O75: =N75*J75*K75*M75 -> 16833.466 | P75: =J75*K75*M75 -> 3.36
G76: Нач. отдела | J76: 1 | K76: =L76*$S$8 -> 0.42 | L76: 0.42 | M76: 8 | N76: =DATA!$D$3 -> 4508.96 | O76: =N76*J76*K76*M76 -> 15150.106 | P76: =J76*K76*M76 -> 3.36
G77: Гл. специалист | J77: 1 | K77: =L77*$S$8 -> 1.5 | L77: 1.5 | M77: 8 | N77: =DATA!$D$4 -> 3757.47 | O77: =N77*J77*K77*M77 -> 45089.64 | P77: =J77*K77*M77 -> 12
G78: Рук. Группы | J78: 1 | K78: =L78*$S$8 -> 1.5 | L78: 1.5 | M78: 8 | N78: =DATA!$D$5 -> 3381.72 | O78: =N78*J78*K78*M78 -> 40580.64 | P78: =J78*K78*M78 -> 12
G79: Вед. инженер | J79: 1 | K79: =L79*$S$8 -> 7 | L79: 7 | M79: 8 | N79: =DATA!$D$6 -> 2504.98 | O79: =N79*J79*K79*M79 -> 140278.88 | P79: =J79*K79*M79 -> 56
G80: Старший инженер | J80: 1 | K80: =L80*$S$8 -> 7 | L80: 7 | M80: 8 | N80: =DATA!$D$7 -> 2254.48 | O80: =N80*J80*K80*M80 -> 126250.88 | P80: =J80*K80*M80 -> 56
G81: Инженер | J81: 1 | K81: =L81*$S$8 -> 2 | L81: 2 | M81: 8 | N81: =DATA!$D$8 -> 2129.23 | O81: =N81*J81*K81*M81 -> 34067.68 | P81: =J81*K81*M81 -> 16
A82: 2.5. | B82: Раздел 5. Сведения об инженерном оборудовании, сетях инженерно-технического обеспечения, перечень инженерно-технических мероприятий, содержание технологических решений. | C82: =SUM(,C83:C131) -> 2003922.9 | D82: =SUM(,D83:D131) -> 719.04 | E82: =SUBTOTAL(9,E83:E131) -> 89.88
A83: 2.5.1. | B83: подраздел 5.1 Система электроснабжения | C83: =SUM(,O83:O89) -> 382179.61 | D83: =SUM(,P83:P89) -> 142.72 | E83: =D83/8 -> 17.84 | G83: ГИП | J83: 1 | K83: =L83*$S$8 -> 0.42 | L83: 0.42 | M83: 8 | N83: =DATA!$D$2 -> 5009.96 | O83: =N83*J83*K83*M83 -> 16833.466 | P83: =J83*K83*M83 -> 3.36
G84: Нач. отдела | J84: 1 | K84: =L84*$S$8 -> 0.42 | L84: 0.42 | M84: 8 | N84: =DATA!$D$3 -> 4508.96 | O84: =N84*J84*K84*M84 -> 15150.106 | P84: =J84*K84*M84 -> 3.36
G85: Гл. специалист | J85: 1 | K85: =L85*$S$8 -> 1.5 | L85: 1.5 | M85: 8 | N85: =DATA!$D$4 -> 3757.47 | O85: =N85*J85*K85*M85 -> 45089.64 | P85: =J85*K85*M85 -> 12
G86: Рук. Группы | J86: 1 | K86: =L86*$S$8 -> 1.5 | L86: 1.5 | M86: 8 | N86: =DATA!$D$5 -> 3381.72 | O86: =N86*J86*K86*M86 -> 40580.64 | P86: =J86*K86*M86 -> 12
G87: Вед. инженер | J87: 1 | K87: =L87*$S$8 -> 7 | L87: 7 | M87: 8 | N87: =DATA!$D$6 -> 2504.98 | O87: =N87*J87*K87*M87 -> 140278.88 | P87: =J87*K87*M87 -> 56
G88: Старший инженер | J88: 1 | K88: =L88*$S$8 -> 5 | L88: 5 | M88: 8 | N88: =DATA!$D$7 -> 2254.48 | O88: =N88*J88*K88*M88 -> 90179.2 | P88: =J88*K88*M88 -> 40
G89: Инженер | J89: 1 | K89: =L89*$S$8 -> 2 | L89: 2 | M89: 8 | N89: =DATA!$D$8 -> 2129.23 | O89: =N89*J89*K89*M89 -> 34067.68 | P89: =J89*K89*M89 -> 16
A90: 2.5.2. | B90: подраздел 5.2 Система водоснабжения | C90: =SUM(,O90:O96) -> 137693.69 | D90: =SUM(,P90:P96) -> 38.72 | E90: =D90/8 -> 4.84 | G90: ГИП | J90: 1 | K90: =L90*$S$8 -> 0.42 | L90: 0.42 | M90: 8 | N90: =DATA!$D$2 -> 5009.96 | O90: =N90*J90*K90*M90 -> 16833.466 | P90: =J90*K90*M90 -> 3.36
G91: Нач. отдела | J91: 1 | K91: =L91*$S$8 -> 0.42 | L91: 0.42 | M91: 8 | N91: =DATA!$D$3 -> 4508.96 | O91: =N91*J91*K91*M91 -> 15150.106 | P91: =J91*K91*M91 -> 3.36
G92: Гл. специалист | J92: 1 | K92: =L92*$S$8 -> 1.5 | L92: 1.5 | M92: 8 | N92: =DATA!$D$4 -> 3757.47 | O92: =N92*J92*K92*M92 -> 45089.64 | P92: =J92*K92*M92 -> 12
G93: Рук. Группы | J93: 1 | K93: =L93*$S$8 -> 1.5 | L93: 1.5 | M93: 8 | N93: =DATA!$D$5 -> 3381.72 | O93: =N93*J93*K93*M93 -> 40580.64 | P93: =J93*K93*M93 -> 12
G94: Вед. инженер | J94: 1 | K94: =L94*$S$8 -> 1 | L94: 1 | M94: 8 | N94: =DATA!$D$6 -> 2504.98 | O94: =N94*J94*K94*M94 -> 20039.84 | P94: =J94*K94*M94 -> 8
G95: Старший инженер | J95: 1 | K95: =L95*$S$8 -> 0 | L95: 0 | M95: 8 | N95: =DATA!$D$7 -> 2254.48 | O95: =N95*J95*K95*M95 -> 0 | P95: =J95*K95*M95 -> 0
G96: Инженер | J96: 1 | K96: =L96*$S$8 -> 0 | L96: 0 | M96: 8 | N96: =DATA!$D$8 -> 2129.23 | O96: =N96*J96*K96*M96 -> 0 | P96: =J96*K96*M96 -> 0
A97: 2.5.3. | B97: подраздел 5.3 Система водоотведения | C97: =SUM(,O97:O103) -> 137693.69 | D97: =SUM(,P97:P103) -> 38.72 | E97: =D97/8 -> 4.84 | G97: ГИП | J97: 1 | K97: =L97*$S$8 -> 0.42 | L97: 0.42 | M97: 8 | N97: =DATA!$D$2 -> 5009.96 | O97: =N97*J97*K97*M97 -> 16833.466 | P97: =J97*K97*M97 -> 3.36
G98: Нач. отдела | J98: 1 | K98: =L98*$S$8 -> 0.42 | L98: 0.42 | M98: 8 | N98: =DATA!$D$3 -> 4508.96 | O98: =N98*J98*K98*M98 -> 15150.106 | P98: =J98*K98*M98 -> 3.36
G99: Гл. специалист | J99: 1 | K99: =L99*$S$8 -> 1.5 | L99: 1.5 | M99: 8 | N99: =DATA!$D$4 -> 3757.47 | O99: =N99*J99*K99*M99 -> 45089.64 | P99: =J99*K99*M99 -> 12
G100: Рук. Группы | J100: 1 | K100: =L100*$S$8 -> 1.5 | L100: 1.5 | M100: 8 | N100: =DATA!$D$5 -> 3381.72 | O100: =N100*J100*K100*M100 -> 40580.64 | P100: =J100*K100*M100 -> 12
G101: Вед. инженер | J101: 1 | K101: =L101*$S$8 -> 1 | L101: 1 | M101: 8 | N101: =DATA!$D$6 -> 2504.98 | O101: =N101*J101*K101*M101 -> 20039.84 | P101: =J101*K101*M101 -> 8
G102: Старший инженер | J102: 1 | K102: =L102*$S$8 -> 0 | L102: 0 | M102: 8 | N102: =DATA!$D$7 -> 2254.48 | O102: =N102*J102*K102*M102 -> 0 | P102: =J102*K102*M102 -> 0
...

Sheet DATA
D1: ПД, РД | E1: АН | F1: ИИ
C2: ГИП | D2: =P4 -> 5009.96 | F2: =D2/0.6 -> 8349.9333 | H2: 20454 | I2: =H2*(30-4) -> 531804 | J2: =I2*0.25 -> 132951 | M2: Среднеотраслевая шкала индексов средневзвешенных ставок непосредственных исполнителей устанавливается с учетом положений п. 5.3 МУ о разработке СБЦ (приказ Минстроя России от 04.06.2015) | Q2: Рамка Сибур ЭТО | R2: Рамка НИПИГАЗ | S2: ГПП ставки для формы 3П (0,45; 8%) | T2: ГПП | U2: С5 | V2: Сибур Рамка ЭТО | W2: ГПП | X2: Рамка НИПИГАЗ
C3: Нач. отдела | D3: =P5 -> 4508.96 | F3: =D3/0.6 -> 7514.9333 | H3: 20454 | I3: =H3*(30-4) -> 531804 | J3: =I3*0.25 -> 132951 | M3: наименование должностей | O3: Индекс ср. взв.ставок
C4: Гл. специалист | D4: =P7 -> 3757.47 | F4: =D4/0.6 -> 6262.45 | H4: 16290 | I4: =H4*(30-4) -> 423540 | J4: =I4*0.25 -> 105885 | M4: Главный инженер проекта | O4: 2 | P4: 5009.96 | Q4: =$Q$9*O4 -> 5000 | R4: =$R$9*O4 -> 3242 | S4: =20454 -> 20454 | T4: =S4*1.08/0.45/8 -> 6136.2 | U4: =P4*160*0.25 -> 200398.4 | V4: =Q4*160*0.25 -> 200000 | W4: =T4*160*0.25 -> 245448 | X4: =R4*160*0.25 -> 129680 | Y4: =T4/Q4 -> 1.22724
C5: Рук. Группы | D5: =P8 -> 3381.72 | F5: =D5/0.6 -> 5636.2 | M5: Начальник отдела | O5: 1.8 | P5: 4508.96 | Q5: =$Q$9*O5 -> 4500 | R5: =$R$9*O5 -> 2917.8 | S5: =20454 -> 20454 | T5: =S5/0.45*1.08/8 -> 6136.2 | U5: =P5*160*0.25 -> 180358.4 | V5: =Q5*160*0.25 -> 180000 | W5: =T5*160*0.25 -> 245448 | X5: =R5*160*0.25 -> 116712 | Y5: =T5/Q5 -> 1.3636
C6: Вед. инженер | D6: =P9 -> 2504.98 | F6: =D6/0.6 -> 4174.9667 | M6: Заместитель нач. отдела | O6: 1.7 | P6: 4258.47 | Q6: =$Q$9*O6 -> 4250 | R6: =$R$9*O6 -> 2755.7 | S6: 18278 | T6: =S6/0.45*1.08/8 -> 5483.4 | U6: =P6*160*0.25 -> 170338.8 | V6: =Q6*160*0.25 -> 170000 | W6: =T6*160*0.25 -> 219336 | X6: =R6*160*0.25 -> 110228 | Y6: =T6/Q6 -> 1.2902118
C7: Старший инженер | D7: =P10 -> 2254.48 | F7: =D7/0.6 -> 3757.4667 | M7: Главный специалист | O7: 1.5 | P7: 3757.47 | Q7: =$Q$9*O7 -> 3750 | R7: =$R$9*O7 -> 2431.5 | S7: 16290 | T7: =S7/0.45*1.08/8 -> 4887 | U7: =P7*160*0.25 -> 150298.8 | V7: =Q7*160*0.25 -> 150000 | W7: =T7*160*0.25 -> 195480 | X7: =R7*160*0.25 -> 97260 | Y7: =T7/Q7 -> 1.3032
C8: Инженер | D8: =P11 -> 2129.23 | F8: =D8/0.6 -> 3548.7167 | M8: Руководитель группы | O8: 1.35 | P8: 3381.72 | Q8: =$Q$9*O8 -> 3375 | R8: =$R$9*O8 -> 2188.35 | S8: 14574 | T8: =S8/0.45*1.08/8 -> 4372.2 | U8: =P8*160*0.25 -> 135268.8 | V8: =Q8*160*0.25 -> 135000 | W8: =T8*160*0.25 -> 174888 | X8: =R8*160*0.25 -> 87534 | Y8: =T8/Q8 -> 1.2954667
D9: =SUM(D2:D8)*160*5 -> 18837440 | M9: Ведущий специалист | O9: 1 | P9: 2504.98 | Q9: 2500 | R9: 1621 | S9: 12984 | T9: =S9/0.45*1.08/8 -> 3895.2 | U9: =P9*160*0.25 -> 100199.2 | V9: =Q9*160*0.25 -> 100000 | W9: =T9*160*0.25 -> 155808 | X9: =R9*160*0.25 -> 64840 | Y9: =T9/Q9 -> 1.55808 | Z9: =Q9/R9 -> 1.5422579
M10: Инженер 1 категории | O10: 0.9 | P10: 2254.48 | Q10: =$Q$9*O10 -> 2250 | R10: =$R$9*O10 -> 1458.9 | S10: 10605 | T10: =S10/0.45*1.08/8 -> 3181.5 | U10: =P10*160*0.25 -> 90179.2 | V10: =Q10*160*0.25 -> 90000 | W10: =T10*160*0.25 -> 127260 | X10: =R10*160*0.25 -> 58356 | Y10: =T10/Q10 -> 1.414
M11: Инженер 2 категории | O11: 0.85 | P11: 2129.23 | Q11: =$Q$9*O11 -> 2125 | R11: =$R$9*O11 -> 1377.85 | S11: 9784 | T11: =S11/0.45*1.08/8 -> 2935.2 | U11: =P11*160*0.25 -> 85169.2 | V11: =Q11*160*0.25 -> 85000 | W11: =T11*160*0.25 -> 117408 | X11: =R11*160*0.25 -> 55114 | Y11: =T11/Q11 -> 1.3812706
M12: Инженер 3 категории | O12: 0.8 | P12: 2003.98 | Q12: =$Q$9*O12 -> 2000 | R12: =$R$9*O12 -> 1296.8 | S12: 8300 | T12: =S12/0.45*1.08/8 -> 2490 | U12: =P12*160*0.25 -> 80159.2 | V12: =Q12*160*0.25 -> 80000 | W12: =T12*160*0.25 -> 99600 | X12: =R12*160*0.25 -> 51872 | Y12: =T12/Q12 -> 1.245
C13: Офис в нижнекамске, средняя | D13: =(D7*4+D2)*1.5/5 -> 4208.364 | M13: Техник 1 категории | O13: 0.6 | P13: 1502.99 | Q13: =$Q$9*O13 -> 1500 | R13: =$R$9*O13 -> 972.6 | S13: 8300 | T13: =S13/0.45*1.08/8 -> 2490 | U13: =P13*160*0.25 -> 60119.6 | V13: =Q13*160*0.25 -> 60000 | W13: =T13*160*0.25 -> 99600 | X13: =R13*160*0.25 -> 38904 | Y13: =T13/Q13 -> 1.66
C14: Стоимость 5 чел | D14: =D13*260*5*2 -> 10941746 | M14: Техник 2 категории | O14: 0.55 | P14: 1377.74 | Q14: =$Q$9*O14 -> 1375 | R14: =$R$9*O14 -> 891.55 | S14: 7406 | T14: =S14/0.45*1.08/8 -> 2221.8 | U14: =P14*160*0.25 -> 55109.6 | V14: =Q14*160*0.25 -> 55000 | W14: =T14*160*0.25 -> 88872 | X14: =R14*160*0.25 -> 35662 | Y14: =T14/Q14 -> 1.6158545
C15: Билеты | D15: =18000*5*2*2 -> 360000 | M15: Техник 3 категории | O15: 0.5 | P15: 1252.49 | Q15: =$Q$9*O15 -> 1250 | R15: =$R$9*O15 -> 810.5 | S15: 6689 | T15: =S15/0.45*1.08/8 -> 2006.7 | U15: =P15*160*0.25 -> 50099.6 | V15: =Q15*160*0.25 -> 50000 | W15: =T15*160*0.25 -> 80268 | X15: =R15*160*0.25 -> 32420 | Y15: =T15/Q15 -> 1.60536
C16: Суточные/питание | D16: =700*5*60 -> 210000
C17: Проживание | D17: =3500*5*60 -> 1050000
C18: Ежедневный проезд до места работы | D18: =500*5*60 -> 150000
C19: Аренда офиса | D19: =90000*2 -> 180000
C20: Аттестация специалистов/обучение | D20: =50000/6*5 -> 41666.667
C21: Лицензии для ПО | D21: =69000*5 -> 345000
C22: Медосмотры | D22: =7000*5 -> 35000
C23: Covid - мероприятия/прививочный сертификат | D23: =3000*5 -> 15000
C24: ИТОГО | D24: =SUM(D13:D23)*0.5 -> 6666310.7

Sheet  ТРУДОЕМКОСТЬ
E1: Приложение №1.1 к Форме КП
B2: ФИКСИРОВАННАЯ ТРУДОЕМКОСТЬ НА ГРАФИЧЕСКИЙ И ТЕКСТОВОЙ ЛИСТ (единица измерения) ПРОЕКТНОЙ И РАБОЧЕЙ ДОКУМЕНТАЦИИ.
B4: № п/п | C4: Наименование | D4: Марка чертежа | E4: Формат листа | F4: Норматив трудозатрат, (чел./час). ПД | G4: Норматив трудозатрат, (чел./час). РД.
B5: 1. | C5: МОНТАЖНО - ТЕХНОЛОГИЧЕСКИЙ ОТДЕЛ
B6: 1.1 | C6: Технология производства. Текстовая часть | D6: ТХ | E6: А4 | F6: 4 | G6: 4
B7: 1.2 | C7: Технология производства. Графическая часть | D7: ТХ | E7: А1 | F7: 36 | G7: 36
B8: 1.3 | C8: Технологические коммуникации. Текстовая часть | D8: ТК | E8: А4 | F8: 4 | G8: 4
B9: 1.4 | C9: Технологические коммуникации. Графическая часть. | D9: ТК | E9: А1 | F9: 28 | G9: 28
B10: 1.5 | C10: Тепловая изоляция. Текстовая часть | D10: ТИ | E10: А4 | F10: 4 | G10: 4
B11: 1.6 | C11: Антикоррозионная защита. Текстовая часть. | D11: АЗ, АЗО | E11: А4 | F11: 4 | G11: 4
B12: 1.7 | C12: Антикоррозионная защита. Графическая часть. | D12: АЗ, АЗО | E12: А1 | F12: 18 | G12: 18
B13: 1.8 | C13: Расчет Материального баланса. Тестовая чать. | D13: РР | E13: А4 | F13: 12 | G13: 12
B14: 1.9 | C14: Расчет Материального баланса. Графическая чать. | D14: РР | E14: А1 | F14: 36 | G14: 36
B15: 1.10 | C15: Тепловая изоляция. Графическая часть | D15: ТИ | E15: А1 | F15: 28 | G15: 28
B16: 1.11 | C16: Сборочные и монтажны чертежи | D16: СБ | E16: А4 | F16: 4 | G16: 4
B17: 1.12 | C17: Сборочные и монтажные чертежи | D17: СБ | E17: А1 | F17: 36 | G17: 36
B18: 2. | C18: КИПиА
B19: 2.1 | C19: Автоматизация технологически процессов. Текстовая часть. | D19: АК, АТХ | E19: А4 | F19: а | G19: 4
B20: 2.2 | C20: Автоматизация технологически процессов. Графическая часть. | D20: АК, АТХ | E20: А1 | F20: 28 | G20: 28
B21: 2.3 | C21: Разработка ТЗ на ВУ АСУТП. Текстовая часть. | D21: ТЗ | E21: А4 | F21: 5 | G21: 5
B22: 2.4 | C22: Разработка ТЗ на ВУ АСУТП. Графическая часть. | D22: ТЗ | E22: А1 | F22: 16 | G22: 16
B23: 3. | C23: ЭЛЕКТРОТЕХНИЧЕСКИЙ ОТДЕЛ
B24: 3.1 | C24: Силовое электрооборудование. Текстовая часть. | D24: ЭМ | E24: А4 | F24: 4 | G24: 4
B25: 3.2 | C25: Силовое электрооборудование. Графическая часть. | D25: ЭМ | E25: А1 | F25: 25 | G25: 25
B26: 3.3 | C26: Электрическое освещение. Текстовая часть. | D26: ЭО, ЭН | E26: А4 | F26: 4 | G26: 4
B27: 3.4 | C27: Электрическое освещение. Графическая часть. | D27: ЭО, ЭН | E27: А1 | F27: 18 | G27: 18
B28: 3.5 | C28: Электроснабжение. Текстовая часть | D28: ЭС | E28: А4 | F28: 4 | G28: 4
B29: 3.6 | C29: Электроснабжение. Графическая часть | D29: ЭС | E29: А1 | F29: 25 | G29: 25
B30: 3.7 | C30: Воздушние, кабельные линии электро передач. Текстовая часть. | D30: ЭВ, ЭК | E30: А4 | F30: 4 | G30: 4
B31: 3.8 | C31: Воздушние, кабельные линии электро передач. Графическая часть. | D31: ЭВ, ЭК | E31: А1 | F31: 18 | G31: 18
B32: 3.9 | C32: Электрообогрев. Текстовая часть. | D32: ЭОГ | E32: А4 | F32: 4 | G32: 4
B33: 3.10 | C33: Электрообогрев. Графическая часть. | D33: ЭОГ | E33: А1 | F33: 18 | G33: 18
B34: 3.11 | C34: Молниезащита, Заземление. Тестовая часть | D34: ЭГ | E34: А4 | F34: 4 | G34: 4
B35: 3.12 | C35: Молниезащита, Заземление. Графическая часть | D35: МЗ, ЗЗ, ЭГ | E35: А1 | F35: 18 | G35: 18
B36: 4. | C36: СЕТИ СВЯЗИ
B37: 4.1 | C37: Сети связи. Охранная и пожарная сигнализации. Текстовая часть | D37: СС, ОС, ПС, СОУЭ, | E37: А4 | F37: 4 | G37: 4
B38: 4.2 | C38: Сети связи. Охранная и пожарная сигнализации. Графическая часть | D38: СС, ОС, ПС,СОУЭ, | E38: А1 | F38: 19 | G38: 19
B39: 4.3 | C39: Радиосвязь, радиовещание и телевидение. Текстовая часть | D39: РТ | E39: А4 | F39: 4 | G39: 4
B40: 4.4 | C40: Радиосвязь, радиовещание и телевидение. Графическая часть | D40: РТ | E40: А1 | F40: 20 | G40: 20
B41: 5. | C41: СТРОИТЕЛЬНО - КОНСТРУКТОРСКИЙ ОТДЕЛ
B42: 5.1 | C42: Конструкции железобетонные, металлические, деревянные. Текстовая часть. | D42: КЖ, КМ, КД | E42: А4 | F42: 4 | G42: 4
B43: 5.2 | C43: Конструкции железобетонные, металлические, деревянные. Графическая часть. | D43: КЖ, КМ, КД | E43: А1 | F43: 31 | G43: 31
B44: 5.3 | C44: Архитектурно-строительные решения. Текстовая часть | D44: АС | E44: А4 | F44: 4 | G44: 4
B45: 5.4 | C45: Архитектурно-строительные решения. Графическая часть. | D45: АС | E45: А1 | F45: 31 | G45: 31
B46: 5.5 | C46: Архитектурные решения. Текстовая часть | D46: АР | E46: А4 | F46: 4 | G46: 4
B47: 5.6 | C47: Архитектурные решения. Графическая часть. | D47: АР | E47: А1 | F47: 24 | G47: 24
B48: 5.7 | C48: Архитектурные решения интерьера. Текстовая часть | D48: АИ | E48: А4 | F48: 4 | G48: 4
B49: 5.8 | C49: Архитектурные решения интерьера. Графическая часть | D49: АИ | E49: А1 | F49: 24 | G49: 24
B50: 6. | C50: СЕКТОР ИНЖЕНЕРНЫХ СЕТЕЙ
B51: 6.1 | C51: Наружные сети водоснабжения и канализации. Текстовая часть | D51: НВК | E51: А4 | F51: 4 | G51: 4
B52: 6.2 | C52: Наружные сети водоснабжения и канализации. Графическая часть | D52: НВК | E52: А1 | F52: 28 | G52: 28
B53: 6.3 | C53: Водоснабжение и канализация. Текстовая часть | D53: ВК | E53: А4 | F53: 3 | G53: 3
B54: 6.4 | C54: Водоснабжение и канализация. Графическая часть. | D54: ВК | E54: А1 | F54: 28 | G54: 28
B55: 6.5 | C55: Тепловые сети. Текстовая часть | D55: ТС | E55: А4 | F55: 4 | G55: 4
B56: 6.6 | C56: Тепловые сети. Графическая часть. | D56: ТС | E56: А1 | F56: 28 | G56: 28
B57: 6.7 | C57: Наружные газопроводы и газоснабжение. Текстовая часть. | D57: ГСН, ГСВ | E57: А4 | F57: 4 | G57: 4
B58: 6.8 | C58: Наружные газопроводы и газоснабжение. Графическая часть. | D58: ГСН, ГСВ | E58: А1 | F58: 28 | G58: 28
B59: 6.9 | C59: Отопление и вентиляция, кондиционирование. Текстовая часть | D59: ОВ | E59: А4 | F59: 4 | G59: 4
B60: 6.10 | C60: Отопление и вентиляция, кондиционирование. Графическая часть. | D60: ОВ | E60: А1 | F60: 36 | G60: 36
B61: 6.11 | C61: Сети и системы пожаротушения. Текстовая часть. | D61: ПТ | E61: А4 | F61: 4 | G61: 4
B62: 6.12 | C62: Сети и системы пожаротушения. Графическая часть. | D62: ПТ | E62: А1 | F62: 26 | G62: 26
B63: 7. | C63: ПОЯСНИТЕЛЬНАЯ ЗАПИСКА
B64: 7.1 | C64: Общая Пояснительная записка. Текстовая часть | D64: ПЗ | E64: А4 | F64: 4 | G64: 4
B65: 8. | C65: ПРОЕКТ ОРГАНИЗАЦИИ СТРОИТЕЛЬСТВА ОБЪЕКТОВ КАП. СТРОИТЕЛЬСТВА
B66: 8.1. | C66: ПОС. Текстовая часть | D66: ПОС | E66: А4 | F66: 3 | G66: 3
B67: 8.2. | C67: ПОС. Графическая часть | D67: ПОС | E67: А1 | F67: 20 | G67: 20
B68: 9. | C68: ПРОЕКТ ОРГАНИЗАЦИИ ПО СНОСУ И ДЕМОНТАЖУ, КОНСЕРВАЦИЯ
B69: 9.1. | C69: ПОД. Текстовая часть | D69: ПОД | E69: А4 | F69: 3 | G69: 3
B70: 9.2. | C70: ПОД. Графическая часть | D70: ПОД | E70: А1 | F70: 20 | G70: 20
B71: 9,3 | C71: Консервация. Текстовая часть. | E71: А4 | F71: 3 | G71: 3
B72: 9.4 | C72: Консервация. Графическая часть. | E72: А1 | F72: 20 | G72: 20
B73: 10. | C73: ПЕРЕЧЕНЬ МЕРОПРИЯТИЙ ПО ОХРАНЕ ОКРУЖАЮЩЕЙ СРЕДЫ
B74: 10.1. | C74: ООС, ОВОС. Текстовая часть | D74: ООС, ОВОС | E74: А4 | F74: 3 | G74: 3
B75: 10.2. | C75: ООС, ОВОС. .Графическая часть | D75: ООС, ОВОС | E75: А1 | F75: 20 | G75: 20
B76: 11. | C76: МЕРОПРИЯТИЯ ПО ОБЕСПЕЧЕНИЮ ПОЖАРНОЙ БЕЗОПАСНОСТИ
B77: 11.1. | C77: Мероприятия по обеспечению пожарной безопасности. Текстовая часть | D77: МОПБ | E77: А4 | F77: 3 | G77: 3
B78: 11.2. | C78: Мероприятия по обеспечению пожарной безопасности. Графическая часть | D78: МОПБ | E78: А1 | F78: 20 | G78: 20
B79: 12. | C79: МЕРОПРИЯТИЯ ПО ОБЕСПЕЧЕНИЮ СОБЛЮДЕНИЯ ТРЕБОВАНИЙ ЭНЕРГЕТИЧЕСКОЙ ЭФФЕКТИВНОСТИ
B80: 12.1. | C80: ЭЭ. Текстовая часть | D80: ЭЭ | E80: А4 | F80: 3 | G80: 3
B81: 12.2. | C81: ЭЭ. Графическая часть | D81: ЭЭ | E81: А1 | F81: 20 | G81: 20
B82: 13. | C82: СМЕТНАЯ ДОКУМЕНТАЦИЯ
B83: 13.1 | C83: Сметная документация. | D83: ЛСР, ОСР, ССРСС, ПЗ | E83: А4 | F83: 2 | G83: 2
B84: 13.2 | C84: Таблица Конъюктурного анализа | D84: КА | E84: А4 | F84: 3 | G84: 3
B85: 14. | C85: ИНАЯ ДОКУМЕНТАЦИЯ В СЛУЧАЯХ, ПРЕДУСМОТРЕННЫХ ФЕДЕРАЛЬНЫМ ЗАКОНОМ
B86: 14.1 | C86: ПМЛА, ПЛА. План мероприятий по локализации и ликвидации последствий аварий на ОПО. Тестовая часть. | D86: ПМЛА, ПЛА | E86: А4 | F86: 3 | G86: 3
B87: 14.2 | C87: ПМЛА, ПЛА. План мероприятий по локализации и ликвидации последствий аварий на ОПО. Графическая час | D87: ПМЛА, ПЛА | E87: А1 | F87: 20 | G87: 20
B88: 14.3 | C88: Промышленная безопасность. Тестовая часть. | D88: ПБ | E88: А4 | F88: 3 | G88: 3
B89: 14.4 | C89: Промышленная безопасность. Графическая часть. | D89: ПБ | E89: А1 | F89: 20 | G89: 20
B90: 14.5 | C90: ГОЧС. Текстовая часть | D90: ГОЧС | E90: А4 | F90: 3 | G90: 3
B91: 14.6 | C91: ГОЧС. Графическая часть | D91: ГОЧС | E91: А1 | F91: 20 | G91: 20
B92: 14.7 | C92: ТБЭ.Текстовая часть | D92: ТБЭ | E92: А4 | F92: 3 | G92: 3
B93: 14.8 | C93: ТБЭ. Графическая часть | D93: ТБЭ | E93: А1 | F93: 20 | G93: 20
B94: 15. | C94: ГЕНЕРАЛЬНЫЙ ПЛАН
B95: 15.1 | C95: Генплан. Текстовая часть | D95: ГП | E95: А4 | F95: 4 | G95: 4
B96: 15.2 | C96: Генплан. Графическая часть | D96: ГП | E96: А1 | F96: 28 | G96: 28
B97: 16. | C97: ПОДГОТОВКА ТЕХНИЧЕСКИХ ЗАДАНИЙ
B98: 16.1 | C98: Техническое задание. Текстовая часть. | D98: ТЗ | E98: А4 | F98: 5 | G98: 5
B99: 16.2 | C99: Техническое задание. Графическая часть. | D99: ТЗ | E99: А1 | F99: 16 | G99: 16
B100: 17. | C100: РАЗРАБОТКА ОПРОСНЫХ ЛИСТОВ
B101: 17.1 | C101: Опросные листы, текстовая часть | D101: ОЛ | E101: А4 | F101: 5 | G101: 5
...

Sheet Лист2

Sheet Лист3
