Workbook
Name Print_Titles: '1.1.4 ИГДИ+'!$6:$6
Name Print_Titles: '3.15.1 Бурение+ '!$16:$16
Name Print_Titles: '3.15.2 ПроектБур+ '!$16:$16

Sheet РНМЦ
A1: Расчет начальной максимальной цены
A2: на выполнение работ по объекту:
A3: Реконструкция газопромысловых сооружений Степновской станции подземного хранения газа
A5: Наименование предприятия, здания, сооружения, стадии проектирования, этапа, вида проектных или изыскательских работ | C5: Выполнение работ по корректировке рабочей и сметной документации объекта «Реконструкция газопромысловых сооружений Степновской СПХГ» , Выполнение диагностического обследования существующих зданий и сооружений, Выполнение комплексных инженерных изысканий.
C6: Рабочая документация
A7: Наименование проектной (изыскательской) организации | C7: Определяется по итогам конкурентных процедур
A8: Наименование организации заказчика | C8: ООО "Газпром проектирование"
A10: № п/п | B10: Наименование видов работ | C10: Ссылка на номер локального расчета | D10: Стоимость, руб.
A11: 1 | B11: 2 | C11: 3 | D11: 4
A12: =СВОД!A21 -> 1 | B12: =СВОД!B21 -> Инженерные изыскания
A13: =СВОД!A22 -> 1.1 | B13: =СВОД!B22 -> Инженерно-геодезические изыскания | C13: =СВОД!E22 -> Сметы №1.1.1-№1.1.4 | D13: =СВОД!H22 -> 13435089
A14: =СВОД!A23 -> 1.2 | B14: =СВОД!B23 -> Инженерно-геологические изыскания | C14: =СВОД!E23 -> Сметы №1.2.1-№1.2.2 | D14: =СВОД!H23 -> 21969334
A15: =СВОД!A24 -> 1.3 | B15: =СВОД!B24 -> Мобильное лазерное сканирование (МЛС) | C15: =СВОД!E24 -> Смета №1.3 | D15: =СВОД!H24 -> 0
A16: =СВОД!A25 -> 1.4 | B16: =СВОД!B25 -> Итого Инженерные изыскания: | D16: =СВОД!H25 -> 39964618
A18: =СВОД!A27 -> 2 | B18: =СВОД!B27 -> Обследование, сбор исходных данных
A19: =СВОД!A28 -> 2.1 | B19: =СВОД!B28 -> Обследование и оценка технического состяния строительных конструкций | C19: =СВОД!E28 -> Смета №2.1 | D19: =СВОД!H28 -> 13673881
A20: =СВОД!A29 -> 2.2 | B20: =СВОД!B29 -> Внесение изменений в техническую документацию | C20: =СВОД!E29 -> Смета №2.2 | D20: =СВОД!H29 -> 5079636
A21: =СВОД!A30 -> 2.3 | B21: =СВОД!B30 -> Сбор исходных данных | C21: =СВОД!E30 -> Смета №2.3 | D21: =СВОД!H30 -> 5721868.2
A22: =СВОД!A31 -> 2.4 | B22: =СВОД!B31 -> Итого Обследование, сбор исходных данных: | D22: =СВОД!H31 -> 24475386
A24: =СВОД!A33 -> 3 | B24: =СВОД!B33 -> Рабочая документация
A25: =СВОД!A34 -> 3.1 | B25: =СВОД!B34 -> Генеральный план | C25: =СВОД!E34 -> Смета №3.1 | D25: =СВОД!H34 -> 3276535.2
A26: =СВОД!A35 -> 3.2 | B26: =СВОД!B35 -> Автомобильные дороги | C26: =СВОД!E35 -> Смета №3.2 | D26: =СВОД!H35 -> 4828808.6
A27: =СВОД!A36 -> 3.3 | B27: =СВОД!B36 -> Технология производства | C27: =СВОД!E36 -> Смета №3.3 | D27: =СВОД!H36 -> 58732646
A28: =СВОД!A37 -> 3.4 | B28: =СВОД!B37 -> Отопление, вентиляция и кондиционирование | C28: =СВОД!E37 -> Смета №3.4 | D28: =СВОД!H37 -> 30320631
A29: =СВОД!A38 -> 3.5 | B29: =СВОД!B38 -> Автоматизированная система управления технологическим процессом (АСУ ТП) | C29: =СВОД!E38 -> Сметы №3.5.1-№3.5.6 | D29: =СВОД!H38 -> 14529311
A30: =СВОД!A39 -> 3.6 | B30: =СВОД!B39 -> Автоматизированная система управления энергоснабжением (АСУ Э) | C30: =СВОД!E39 -> Сметы №3.6.1-№3.6.5 | D30: =СВОД!H39 -> 5811572
A31: =СВОД!A40 -> 3.7 | B31: =СВОД!B40 -> Автоматизация электрического освещения (АЭО) | C31: =СВОД!E40 -> Сметы №3.7.1-№3.7.3 | D31: =СВОД!H40 -> 1690386
A32: =СВОД!A41 -> 3.8 | B32: =СВОД!B41 -> Система противопожарной безопасности и автоматики (СПБА) | C32: =СВОД!E41 -> Сметы №3.8.1-№3.8.6 | D32: =СВОД!H41 -> 11368057
A33: =СВОД!A42 -> 3.9 | B33: =СВОД!B42 -> Сети связи и сигнализации | C33: =СВОД!E42 -> Сметы №3.9.1-№3.9.7 | D33: =СВОД!H42 -> 14311185
A34: =СВОД!A43 -> 3.10 | B34: =СВОД!B43 -> Электроснабжение | C34: =СВОД!E43 -> Смета №3.10 | D34: =СВОД!H43 -> 45652932
A35: =СВОД!A44 -> 3.11 | B35: =СВОД!B44 -> Электрохимическая защита | C35: =СВОД!E44 -> Смета №3.11 | D35: =СВОД!H44 -> 18342242
A36: =СВОД!A45 -> 3.12 | B36: =СВОД!B45 -> Сети водоснабжения и канализации | C36: =СВОД!E45 -> Смета №3.12 | D36: =СВОД!H45 -> 7763728.1
... A39: =СВОД!A48 -> 3.15 | B39: =СВОД!B48 -> Проект бурения скважин | C39: =СВОД!E48 -> Сметы №3.15.1-№3.15.2 | D39: =СВОД!H48 -> 1309609.4
A40: =СВОД!A49 -> 3.16 | B40: =СВОД!B49 -> Итого Рабочая документация: | D40: =СВОД!H49 -> 2.1926073e+08
A42: =СВОД!A51 -> 4 | B42: Итого | D42: =СВОД!H51 -> 2.8370073e+08
A43: =СВОД!A52 -> 5 | B43: Кроме того, НДС 22% | C43: 22% от п.4 | D43: =СВОД!H52 -> 62414161
A44: =СВОД!A53 -> 6 | B44: Всего с НДС | C44: Сумма от п.4-5 | D44: =СВОД!H53 -> 3.4611489e+08
A47: Главный инженер проекта
A48: ООО «Газпром проектирование»
A49: Саратовский филиал | C49: ___________________ | D49: А.Г. Гордеев

Sheet СВОД
D1: Форма 1пс
A3: СВОДНАЯ СМЕТА
A4: на проектные работы и инженерные изыскания
A6: По объекту: | D6: Реконструкция газопромысловых сооружений Степновской станции подземного хранения газа
A9: Наименование строительства и стадии проектирования | D9: Рабочая документация
A14: Наименование проектной организации-генерального проектировщика | D14: Определяется по итогам конкурентных процедур
A16: Наименование организации заказчика | D16: ООО «Газпром проектирование»
A18: №пп | B18: Перечень выполняемых работ | E18: Ссылка на № смет по формам 2П, 3П | F18: Полная стоимость работ, руб.
F19: изыскательских | G19: проектных | H19: Всего
A20: 1 | B20: 2 | E20: 4 | F20: 5 | G20: 6 | H20: 7
A21: 1 | B21: Инженерные изыскания
A22: 1.1 | B22: Инженерно-геодезические изыскания | E22: =CONCATENATE("Сметы №",A22,".1","-№",A22,".4") -> Сметы №1.1.1-№1.1.4 | F22: ='1.1.1 ИГДИ'!G102+'1.1.2 ИГДИ'!O21+'1.1.3 ИГДИ'!G102+'1.1.4 ИГДИ+'!G105 -> 13435089 | H22: =G22+F22 -> 13435089
A23: 1.2 | B23: Инженерно-геологические изыскания | E23: =CONCATENATE("Сметы №",A23,".1","-№",A23,".2") -> Сметы №1.2.1-№1.2.2 | F23: ='1.2.1 ИГИ'!E87+'1.2.2 ИГИ+'!E86 -> 21969334 | H23: =G23+F23 -> 21969334
A24: 1.3 | B24: Мобильное лазерное сканирование (МЛС) | E24: =CONCATENATE("Смета №",A24) -> Смета №1.3 | F24: ='1.3 МЛС'!G96 -> 4560194.1
A25: 1.4 | B25: =CONCATENATE("Итого ",B21,":") -> Итого Инженерные изыскания: | F25: =ROUND(SUM(F22:F24),2) -> 39964618 | G25: =ROUND(SUM(G22:G23),2) -> 0 | H25: =G25+F25 -> 39964618
A27: 2 | B27: Обследование, сбор исходных данных
A28: 2.1 | B28: Обследование и оценка технического состяния строительных конструкций | E28: =CONCATENATE("Смета №",A28) -> Смета №2.1 | G28: =Смета_№2.1_Обслед!R239 -> 13673881 | H28: =G28+F28 -> 13673881
A29: 2.2 | B29: Внесение изменений в техническую документацию | E29: =CONCATENATE("Смета №",A29) -> Смета №2.2 | G29: ='2.2 ТехДок+ '!K32 -> 5079636 | H29: =G29+F29 -> 5079636
A30: 2.3 | B30: Сбор исходных данных | E30: =CONCATENATE("Смета №",A30) -> Смета №2.3 | G30: ='2.3 СИД '!G58 -> 5721868.2 | H30: =G30+F30 -> 5721868.2
A31: 2.4 | B31: =CONCATENATE("Итого ",B27,":") -> Итого Обследование, сбор исходных данных: | F31: =ROUND(SUM(F26:F28),2) -> 0 | G31: =ROUND(SUM(G28:G30),2) -> 24475386 | H31: =G31+F31 -> 24475386
A33: 3 | B33: Рабочая документация
A34: 3.1 | B34: Генеральный план | E34: =CONCATENATE("Смета №",A34) -> Смета №3.1 | G34: ='РД 3.1 ГП++'!R70 -> 3276535.2 | H34: =G34+F34 -> 3276535.2
A35: 3.2 | B35: Автомобильные дороги | E35: =CONCATENATE("Смета №",A35) -> Смета №3.2 | G35: ='3.2 Автодороги++'!R96 -> 4828808.6 | H35: =G35+F35 -> 4828808.6
A36: 3.3 | B36: Технология производства | E36: =CONCATENATE("Смета №",A36) -> Смета №3.3 | G36: ='3.3 ТХ++'!R478 -> 58732646 | H36: =G36+F36 -> 58732646
A37: 3.4 | B37: Отопление, вентиляция и кондиционирование | E37: =CONCATENATE("Смета №",A37) -> Смета №3.4 | G37: ='3.4 ОВ++'!R185 -> 30320631 | H37: =G37+F37 -> 30320631
A38: 3.5 | B38: Автоматизированная система управления технологическим процессом (АСУ ТП) | E38: =CONCATENATE("Сметы №",A38,".1","-№",A38,".6") -> Сметы №3.5.1-№3.5.6 | G38: ='3.5.1 АСУТП этап12'!Y173+'3.5.2 АСУТП этап15'!Y173+'3.5.3 АСУТП этап16'!Y173+'3.5.4 АСУТП этап27'!Y173+'3.5.5 АСУТП этап2+'!Y173+'3.5.6 АСУТП этап3++'!Y173 -> 14529311 | H38: =G38+F38 -> 14529311
A39: 3.6 | B39: Автоматизированная система управления энергоснабжением (АСУ Э) | E39: =CONCATENATE("Сметы №",A39,".1","-№",A39,".5") -> Сметы №3.6.1-№3.6.5 | G39: ='3.6.1 АСУЭ этап2'!Y173+'3.6.2 АСУЭ этап15'!Y173+'3.6.3 АСУЭ этап16'!Y173+'3.6.4 АСУЭ этап27'!Y173+'3.6.5 АСУЭ этап3++'!Y173 -> 5811572 | H39: =G39+F39 -> 5811572
A40: 3.7 | B40: Автоматизация электрического освещения (АЭО) | E40: =CONCATENATE("Сметы №",A40,".1","-№",A40,".3") -> Сметы №3.7.1-№3.7.3 | G40: ='3.7.1 АЭО этап15'!Y173+'3.7.2 АЭО этап16'!Y173+'3.7.3 АЭО этап3++'!Y173 -> 1690386 | H40: =G40+F40 -> 1690386
A41: 3.8 | B41: Система противопожарной безопасности и автоматики (СПБА) | E41: =CONCATENATE("Сметы №",A41,".1","-№",A41,".6") -> Сметы №3.8.1-№3.8.6 | G41: ='3.8.1 СПБА этап12'!Y173+'3.8.2 СПБА этап15'!Y173+'3.8.3 СПБА этап16'!Y173+'3.8.4 СПБА этап27'!Y173+'3.8.5 СПБА этап2+'!Y173+'3.8.6 СПБА этап3++'!Y173 -> 11368057 | H41: =G41+F41 -> 11368057
A42: 3.9 | B42: Сети связи и сигнализации | E42: =CONCATENATE("Сметы №",A42,".1","-№",A42,".7") -> Сметы №3.9.1-№3.9.7 | G42: ='3.9.1 этап12 СС'!E116+'3.9.2 этап13 СС'!E25+'3.9.3 этап 15 СС'!E121+'3.9.4 этап16 СС'!E48+'3.9.5 этап17 СС'!E34+'3.9.6 этап27 СС'!E162+'3.9.7 СС ЭТАП3++'!E244 -> 14311185 | H42: =G42+F42 -> 14311185
A43: 3.10 | B43: Электроснабжение | E43: =CONCATENATE("Смета №",A43) -> Смета №3.10 | G43: ='3.10 ЭС++'!E915 -> 45652932 | H43: =G43+F43 -> 45652932
A44: 3.11 | B44: Электрохимическая защита | E44: =CONCATENATE("Смета №",A44) -> Смета №3.11 | G44: ='3.11 ЭХЗ+'!E384 -> 18342242 | H44: =G44+F44 -> 18342242
A45: 3.12 | B45: Сети водоснабжения и канализации | E45: =CONCATENATE("Смета №",A45) -> Смета №3.12 | G45: ='3.12 ВК++'!E213 -> 7763728.1 | H45: =G45+F45 -> 7763728.1
A46: 3.13 | B46: Архитектурно-строительные решения | E46: =CONCATENATE("Смета №",A46) -> Смета №3.13 | G46: ='3.13 АС'!R29 -> 606480 | H46: =G46+F46 -> 606480
A47: 3.14 | B47: Линейная часть | E47: =CONCATENATE("Смета №",A47) -> Смета №3.14 | G47: ='3.14 ЛЧ++'!R94 -> 716607.12 | H47: =G47+F47 -> 716607.12
A48: 3.15 | B48: Проект бурения скважин | E48: =CONCATENATE("Сметы №",A48,".1","-№",A48,".2") -> Сметы №3.15.1-№3.15.2 | G48: ='3.15.1 Бурение+ '!G38+'3.15.2 ПроектБур+ '!G38 -> 1309609.4 | H48: =G48+F48 -> 1309609.4
A49: 3.16 | B49: =CONCATENATE("Итого ",B33,":") -> Итого Рабочая документация: | F49: =ROUND(SUM(F44:F46),2) -> 0 | G49: =ROUND(SUM(G34:G48),2) -> 2.1926073e+08 | H49: =G49+F49 -> 2.1926073e+08
A51: 4 | B51: Итого по сводной смете: | F51: =F49+F31+F25 -> 39964618 | G51: =G49+G31+G25 -> 2.4373611e+08 | H51: =G51+F51 -> 2.8370073e+08
A52: 5 | B52: Кроме того, НДС | E52: 0.22 | F52: =ROUND(($F$51) * (22/100),2) -> 8792215.9 | G52: =ROUND(G51*0.22,2) -> 53621945 | H52: =G52+F52 -> 62414161
A53: 6 | B53: Всего по сводной смете: | F53: =ROUND((SUM($F$51:$F$52)) * 1,2) -> 48756834 | G53: =ROUND((SUM($G$51:$G$52)) * 1,2) -> 2.9735806e+08 | H53: =G53+F53 -> 3.4611489e+08

Sheet 1.1.1 ИГДИ
B2: Смета №1.1.1
B3: =СВОД!B22 -> Инженерно-геодезические изыскания
A5: № пп | B5: Наименование работ и затрат | C5: Единица измерения | D5: Кол-во | E5: Обоснование стоимости | F5: Расчет стоимости, руб. | G5: Стоимость, руб.
A6: 1 | B6: 2 | C6: 3 | D6: 4 | E6: 5 | F6: 6 | G6: 7
A7: Раздел 1. Полевые работы
A8: III. Работы по созданию опорной геодезической сети (ПИИ Таблица 4.1.1)
A9: 1 | B9: Создание пунктов плановой опорной геодезической сети без закладки центров методом спутниковых геодезических определений, 2-го разряда в условиях выполнения полевых работ: II категории | C9: 1 пункт | D9: 4 | E9: НЗ_ИГДИ-7-8 | F9: 35837*4 A** | G9: 143348
E10: Кинф = 1.2700 (1) Письмо Минстроя России N 45358-ИФ/09 от 22.07.2026г (2026г. III квартал)
A11: 2 | B11: Создание пунктов плановой опорной геодезической сети без закладки центров методом спутниковых геодезических определений, 2-го разряда в условиях выполнения полевых работ: II категории | C11: 1 пункт | D11: 4 | E11: НЗ_ИГДИ-7-8 | F11: (35837*4)*0.5 (A**)*К1 | G11: 71674
E12: К1 = 0.5 (ТЧ_п.44_т.7_прим._п.1) При выполнении полевых работ по созданию пунктов плановой опорной геодезической сети без закладки центров методом спутниковых геодезических определений, совмещённых с пунктами высотной опорной сети IV класса, созданных без закладки центров методом спутниковых геодезических определений, (К3)
E13: Кинф = 1.2700 (1) Письмо Минстроя России N 45358-ИФ/09 от 22.07.2026г (2026г. III квартал)
A14: IV. Работы по топографической съёмке в масштабах 1:500 - 1:2000 (ПИИ Таблица 4.1.2)
A15: Незастроенная территория
A16: Застроенная территория (ПИИ Таблица 4.1.2)
A17: 3 | B17: Топографическая съемка тахеометрическим методом и сочетанием тахеометрического метода с методом спутниковых геодезических определений с высотой сечения рельефа через 0,5 метров, застроенной территории в масштабе 1:1000 в условиях выполнения полевых работ: IV категории | C17: 1 гектар | D17: 2 | E17: НЗ_ИГДИ-18-17 | F17: 57593*2 A** | G17: 115186
E18: Кинф = 1.2700 (1) Письмо Минстроя России N 45358-ИФ/09 от 22.07.2026г (2026г. III квартал)
A19: V. Работы по съёмке подземных инженерных коммуникаций и сооружений (ПИИ Таблица 4.1.2)
A20: 4 | B20: Полевые работы по поиску и съемке подземных инженерных коммуникаций при помощи трубокабелеискателя при количестве точек подземных инженерных коммуникаций на 1 гектар снимаемого участка: от 7 до 14 включительно | C20: 1 гектар | D20: 2 | E20: НЗ_ИГДИ-46-2 | F20: 24772*2 A** | G20: 49544
E21: Кинф = 1.2700 (1) Письмо Минстроя России N 45358-ИФ/09 от 22.07.2026г (2026г. III квартал)
A22: VII. Работы по привязке инженерно-геологических выработок, геофизических и гидрогеологических точек наблюдения (ПИИ Таблица 4.1.3)
A23: Работы по перенесению в натуру проектного положения инженерно-геологических, геофизических, гидрогеологических точек наблюдения (ПИИ Таблица 4.1.3).
A24: 5 | B24: Привязка инженерно-геологических выработок, геофизических и гидрогеологических точек наблюдения при расстоянии между точками от 200 (двухсот) до 350 (трехсот пятидесяти) метров включительно, в условиях выполнения полевых работ: III категории | C24: 1 точка | D24: 31 | E24: НЗ_ИГДИ-55-12 | F24: (13975*31)*0.5 (A**)*К1 | G24: 216612.5
E25: К1 = 0.5 (ТЧ_п.126_т.55_прим._п.1) При работах по перенесению в натуру инженерно-геологических выработок, геофизических, гидрогеологических точек наблюдений, (К8)
E26: Кинф = 1.2700 (1) Письмо Минстроя России N 45358-ИФ/09 от 22.07.2026г (2026г. III квартал)
A27: Работы по привязке фактического положения инженерно-геологических, геофизических, гидрогеологических точек наблюдения после завершения работ (ПИИ Таблица 4.1.3).
A28: 6 | B28: Привязка инженерно-геологических выработок, геофизических и гидрогеологических точек наблюдения при расстоянии между точками от 200 (двухсот) до 350 (трехсот пятидесяти) метров включительно, в условиях выполнения полевых работ: III категории | C28: 1 точка | D28: 31 | E28: НЗ_ИГДИ-55-12 | F28: 13975*31 A** | G28: 433225
E29: Кинф = 1.2700 (1) Письмо Минстроя России N 45358-ИФ/09 от 22.07.2026г (2026г. III квартал)
B30: Итоги по разделу 1 Полевые работы:
B31: Итого Поз. 1-6 | G31: 1 029 589.50
B32: Всего c учетом "Письмо Минстроя России N 45358-ИФ/09 от 22.07.2026г (2026г. III квартал) 1.2700" | G32: 1 286 986.88
B33: Итого по разделу 1 Полевые работы | G33: 1 286 986.88
A34: Раздел 2. Дополнительные затраты на производство полевых работ
A35: 7 | B35: Дополнительные затраты на неизбежные перерывы - 25% | C35: руб. | D35: 1029589.6 | E35: НЗ_ИГДИ п.25 | F35: 0.25*1029589.63 B** | G35: 257397.41
E36: Кинф = 1.2700 (1) Письмо Минстроя России N 45358-ИФ/09 от 22.07.2026г (2026г. III квартал)
A37: 8 | B37: Показатели дополнительных затрат на внешний транспорт (ПДЗвнеш) автомобильного транспорта, расстояние от места постоянной работы работников до участка проведения полевых работ от 2000 до 4000 км включительно при стоимости полевых работ от 1000 до 3000 тыс. руб. | C37: руб. | D37: 1029589.6 | E37: НЗ_ИГДИ-3-4-4 | F37: 0.2343*1029589.63 B** | G37: 241232.85
E38: Кинф = 1.2700 (1) Письмо Минстроя России N 45358-ИФ/09 от 22.07.2026г (2026г. III квартал)
A39: 9 | B39: Показатели дополнительных затрат на организацию полевых работ (ПДЗорг), расстояние от места постоянной работы работников до участка проведения полевых работ от 1000 до 2000 км включительно: при стоимости полевых работ свыше/до 3000 тыс. руб. - 7,7 % | C39: руб. | D39: 1029589.6 | E39: НЗ_ИГДИ-4-4-4 | F39: 0.3038*1029589.63 B** | G39: 312789.33
E40: Кинф = 1.2700 (1) Письмо Минстроя России N 45358-ИФ/09 от 22.07.2026г (2026г. III квартал)
B41: Итоги по разделу 2 Дополнительные затраты на производство полевых работ:
B42: Итого Поз. 7-9 | G42: 811 419.59
B43: Всего c учетом "Письмо Минстроя России N 45358-ИФ/09 от 22.07.2026г (2026г. III квартал) 1.2700" | G43: 1 014 274.49
B44: Итого по разделу 2 Дополнительные затраты на производство полевых работ | G44: 1 014 274.49
A45: Раздел 3. Камеральные работы
A46: III. Работы по созданию опорной геодезической сети (ПИИ Таблица 4.1.1)
A47: 10 | B47: Камеральная обработка результатов измерений, выполненных при создании пунктов плановой опорной геодезической сети 4-го класса, 1-го и 2-го разрядов | C47: 1 пункт | D47: 4 | E47: НЗ_ИГДИ-16-1 | F47: 1714*4 A** | G47: 6856
E48: Кинф = 1.2700 (1) Письмо Минстроя России N 45358-ИФ/09 от 22.07.2026г (2026г. III квартал)
A49: 11 | B49: Камеральная обработка результатов измерений, выполненных при создании нивелирных пунктов высотной опорной геодезической сети III и IV классов | C49: 1 пункт | D49: 4 | E49: НЗ_ИГДИ-16-3 | F49: 1844*4 A** | G49: 7376
E50: Кинф = 1.2700 (1) Письмо Минстроя России N 45358-ИФ/09 от 22.07.2026г (2026г. III квартал)
A51: VI. Работы по созданию и обновлению инженерно-топографических планов в масштабах 1:500 - 1:5000 (ПИИ Таблица 4.1.2)
A52: Незастроенная территория
A53: Застроенная территория (ПИИ Таблица 4.1.2)
A54: 12 | B54: Камеральные работы по созданию инженерно-топографических планов в масштабе 1:1000 застроенной территории для условий выполнения полевых работ категории IV при площади участка: до 10 гектар включительно | C54: 1 гектар | D54: 2 | E54: НЗ_ИГДИ-48-25 | F54: 2912+5181*2 A+B** | G54: 13274
E55: Кинф = 1.2700 (1) Письмо Минстроя России N 45358-ИФ/09 от 22.07.2026г (2026г. III квартал)
A56: Подземные коммуникации (ПИИ Таблица 4.1.2)
A57: 13 | B57: Камеральные работы по нанесению подземных инженерных коммуникаций с их техническими характеристиками на инженерно-топографический план в масштабе 1:1000 при количестве подземных инженерных коммуникаций по назначению на участке, подлежащем топографической съемке от 3 (трех) до 8 (восьми) включительно: до 10 гектар включительно | C57: 1 гектар | D57: 2.000001 | E57: НЗ_ИГДИ-52-7 | F57: 326+515*2.000001 A+B** | G57: 1356
E58: Кинф = 1.2700 (1) Письмо Минстроя России N 45358-ИФ/09 от 22.07.2026г (2026г. III квартал)
A59: VIII. Работы по трассированию сетей
A60: *I. Прочие работы по ИГДИ
B61: Итоги по разделу 3 Камеральные работы:
B62: Итого Поз. 10-13 | G62: 28 862.00
B63: Всего c учетом "Письмо Минстроя России N 45358-ИФ/09 от 22.07.2026г (2026г. III квартал) 1.2700" | G63: 36 077.50
B64: Итого по разделу 3 Камеральные работы | G64: 36 077.50
A65: Раздел 4. Дополнительные затраты на производство камеральных работ
A66: 14 | B66: Дополнительные затраты на районные выплаты - 1.15 | C66: руб. | D66: 28862.05 | E66: НЗ_ИГДИ п.40 | F66: 0.1095*28862.05 A** | G66: 3160.39
E67: Кинф = 1.2700 (1) Письмо Минстроя России N 45358-ИФ/09 от 22.07.2026г (2026г. III квартал)
B68: Итоги по разделу 4 Дополнительные затраты на производство камеральных работ:
B69: Итого Поз. 14 | G69: 3 160.39
B70: Всего c учетом "Письмо Минстроя России N 45358-ИФ/09 от 22.07.2026г (2026г. III квартал) 1.2700" | G70: 3 950.49
B71: Итого по разделу 4 Дополнительные затраты на производство камеральных работ | G71: 3 950.49
A72: Раздел 5. Составление программы инженерно-геодезических изысканий и технического отчёта по результам ИГДИ (ПИИ Таблица 4.1.5; ПИИ Таблица 4.1.6)
A73: 15 | B73: Камеральные работы по составлению программы инженерно-геодезических изысканий при общей стоимости полевых и камеральных работ, определенной по показателям затрат, приведенным в НЗ: 10000 тысяч рублей | C73: 1 программа | D73: 1058451.7 | E73: НЗ_ИГДИ-80-6 | F73: 36839+(127949-36839)/(5000000-1000000)*(1058451.68-1000000) A1+(A2-A1)/(*2-*1)*(*-*1) | G73: 38170.38
E74: Кинф = 1.2700 (1) Письмо Минстроя России N 45358-ИФ/09 от 22.07.2026г (2026г. III квартал)
A75: 16 | B75: Камеральные работы по составлению технического отчета по результатам выполнения работ по ИГДИ при общей стоимости полевых и камеральных работ, определенной по показателям затрат, приведенным в НЗ: 10000 тысяч рублей | C75: 1 отчет | D75: 1058451.7 | E75: НЗ_ИГДИ-81-6 | F75: 76000+(204000-76000)/(5000000-1000000)*(1058451.68-1000000) A1+(A2-A1)/(*2-*1)*(*-*1) | G75: 77870.45
E76: Кинф = 1.2700 (1) Письмо Минстроя России N 45358-ИФ/09 от 22.07.2026г (2026г. III квартал)
B77: Итоги по разделу 5 Составление программы инженерно-геодезических изысканий и технического отчёта по результам ИГДИ (ПИИ Таблица 4.1.5; ПИИ Таблица 4.1.6):
B78: Итого Поз. 15-16 | G78: 116 040.83
B79: Всего c учетом "Письмо Минстроя России N 45358-ИФ/09 от 22.07.2026г (2026г. III квартал) 1.2700" | G79: 145 051.04
B80: Итого по разделу 5 Составление программы инженерно-геодезических изысканий и технического отчёта по результам ИГДИ (ПИИ Таблица 4.1.5; ПИИ Таблица 4.1.6) | G80: 145 051.04
B81: Итоги по смете:
B82: Итого по разделу 1 Полевые работы
B83: Итого Поз. 1-6 | G83: 1 029 589.50
B84: Всего c учетом "Письмо Минстроя России N 45358-ИФ/09 от 22.07.2026г (2026г. III квартал) 1.2700" | G84: 1 286 986.88
B85: Итого по разделу 1 Полевые работы | G85: 1 286 986.88
B86: Итого по разделу 2 Дополнительные затраты на производство полевых работ
B87: Итого Поз. 7-9 | G87: 811 419.59
B88: Всего c учетом "Письмо Минстроя России N 45358-ИФ/09 от 22.07.2026г (2026г. III квартал) 1.2700" | G88: 1 014 274.49
B89: Итого по разделу 2 Дополнительные затраты на производство полевых работ | G89: 1 014 274.49
B90: Итого по разделу 3 Камеральные работы
B91: Итого Поз. 10-13 | G91: 28 862.00
B92: Всего c учетом "Письмо Минстроя России N 45358-ИФ/09 от 22.07.2026г (2026г. III квартал) 1.2700" | G92: 36 077.50
B93: Итого по разделу 3 Камеральные работы | G93: 36 077.50
B94: Итого по разделу 4 Дополнительные затраты на производство камеральных работ
B95: Итого Поз. 14 | G95: 3 160.39
B96: Всего c учетом "Письмо Минстроя России N 45358-ИФ/09 от 22.07.2026г (2026г. III квартал) 1.2700" | G96: 3 950.49
B97: Итого по разделу 4 Дополнительные затраты на производство камеральных работ | G97: 3 950.49
B98: Итого по разделу 5 Составление программы инженерно-геодезических изысканий и технического отчёта по результам ИГДИ (ПИИ Таблица 4.1.5; ПИИ Таблица 4.1.6)
B99: Итого Поз. 15-16 | G99: 116 040.83
B100: Всего c учетом "Письмо Минстроя России N 45358-ИФ/09 от 22.07.2026г (2026г. III квартал) 1.2700" | G100: 145 051.04
B101: Итого по разделу 5 Составление программы инженерно-геодезических изысканий и технического отчёта по результам ИГДИ (ПИИ Таблица 4.1.5; ПИИ Таблица 4.1.6) | G101: 145 051.04
B102: Итого | G102: 2526121.8

Sheet 1.1.2 ИГДИ
A1: Смета №1.1.2
A2: Инженерно - геодезические изыскания
A4: № п/п | B4: Наименование работ и затрат | D4: Обоснование стоимости | E4: Ед. изм. | F4: Кол- во | G4: Расчет стоимости | O4: Стоимость, руб
A5: 1 | B5: 2 | D5: 3 | E5: 4 | F5: 5 | G5: 6 | O5: 7
B6: Сметный расчет составлен по Справочнику базовых цен на инженерные изыскания для строительства. Инженерно-геодезические изыскания. ПНИИИС, 2004 г.
A7: 1 | B7: Картографическое вычерчивание топографических планов и карт. Создание ситуационного плана. | D7: Ч. II, гл.8, табл.65.
D8: 1,2к - применение комп. технологий - ОУ, п.15, д).
B9: Категория К-II, Р-II Категория II | C9: 1:5000 0,5м
C11: камеральные работы: | D11: Ч. II, гл.8, табл.65, § 10 | E11: 1 дм2 | F11: 40 | G11: 110 | H11: 1.2 | N11: 40.0*110*1.2 | O11: 5280
B12: Категория К-II, Р-II Категория II | C12: 1:10000 0,5м
C14: камеральные работы: | D14: Ч. II, гл.8, табл.65, § 14 | E14: 1 дм2 | F14: 10 | G14: 154 | H14: 1.2 | N14: 10.0*154*1.2 | O14: 1848
A15: 2 | B15: Итого камеральных работ | F15: 1 | N15: 1*7 128.00 | O15: 7128
A16: 3 | B16: Итого с районным коэффициентом | C16: камеральные работы: | D16: 1,08к - районный коэффициент 1,15 - ОУ, п.8, д), табл.3, §2 | F16: 1.08 | H16: 7128 | N16: 7 128.00*1.08 | O16: 7698.24
A17: 4 | B17: итого: | O17: 7698.24
A18: 5 | B18: Итого с учетом индекса изменения стоимости к уровню базовых цен по состоянию на 1 января 2001 года | D18: Письмо Минстроя России N 45358-ИФ/09 от 22.07.2026г (2026г. III квартал) | F18: 7.229 | H18: 7698.24 | N18: 7 698.24*7.07 | O18: =(54426.56/7.07)*7.229 -> 55650.58
A19: 6 | B19: Итого | O19: =O18 -> 55650.58
A20: 7 | B20: Итого с коэффициентом оптимизации ПАО Газпром | O20: =O19*0.8 -> 44520.464
A21: 8 | B21: Всего по смете | O21: =O20 -> 44520.464

Sheet 1.1.3 ИГДИ
G2: Форма 2п
B3: СМЕТА №1.1.3
B4: Реконструкция ГПС - Объёмы к изм ТЗ (ИГДИ.2)
B5: =СВОД!B22 -> Инженерно-геодезические изыскания
A7: № пп | B7: Наименование работ и затрат | C7: Единица измерения | D7: Кол-во | E7: Обоснование стоимости | F7: Расчет стоимости, руб. | G7: Стоимость, руб.
A8: 1 | B8: 2 | C8: 3 | D8: 4 | E8: 5 | F8: 6 | G8: 7
A9: Раздел 1. Полевые работы
A10: III. Работы по созданию опорной геодезической сети
A11: Этап 16; 4212.012.Р.16/0.0004.Г3.001.40203.000-ГСН; Межпоселковый газопровод высокого давления II категории от ПППГ до коллектора КС3-ГРП5; ПОГС - 1шт; 4212.012.Р.3/0.0004.КЛС.02А.41403.001-КЛС; Трассы кабельных линий связи; ГРП-2А Операторная - КС-3 СЭБ (поз. 225); ПОГС - 2шт; Этап 3; 4212.00.Р.04.МПВ.2.000.НВ.000; Водовод межплощадочный КС3-ГРП2А подземной прокладки; ПОГС – 1шт; Этап 16; 4212.00.Р.04.КК.10.000.НК.000; Коллектор межплощадочный канализационный ПППГ-КОС; ПОГС – 1шт; Этап 16; 4212.00.Р.04.МПВ.9.000.НВ.000; Водовод межплощадочный ПППГ-КОС; ПОГС – 1шт; Этап 27; 4212.00.Р.04.МПВ.8.000.НВ.000; Водовод межплощадочный КОС-КС5; ПОГС – 1шт; Этап 27; 4212.СРТ.00.Р.04.МПВ.5.1.НВ.000; Водовод межплощадочный к точке подключения ГРП.5; ПОГС – 2шт; Этап 27; 4212.00.Р.04.МПВ.5.000.НВ.000; Водовод межплощадочный от КС5 до РЛВЖ; ПОГС – 1шт; 4212.012.Р.3/0.0004.ВЭЛ.000.41501.000-ЭВ - ВЛЗ 6 кВ (в габаритах 35 кВ) от ПС 110/35/6 кВ «Степная-газовая» до КСПХГ №5; ПОГС – 3шт; 4212.012.Р.3/0.0004.ВЭЛ.000.41501.000-ЭВ1 - ВЛЗ 6 кВ к ГРП 2А 253м; ПОГС – 1шт; 4212.012.Р.3/0.0004.ВЭЛ.000.41501.000-ЭВ2 - ВЛЗ 6 кВ к ГРП 1А 920м ПОГС – 1шт.
A12: 1 | B12: Создание пунктов плановой опорной геодезической сети без закладки центров методом спутниковых геодезических определений, 2-го разряда в условиях выполнения полевых работ: II категории | C12: 1 пункт | D12: 15 | E12: НЗ_ИГДИ-7-8 | F12: (35837*15)*1.27 (A**)*К1 | G12: 671943.75
E13: К1 = 1.27 Письмо Минстроя России N 45358-ИФ/09 от 22.07.2026г (2026г. III квартал)
E14: Кинф = 1.2700 (1) Письмо Минстроя России N 45358-ИФ/09 от 22.07.2026г (2026г. III квартал)
A15: 2 | B15: Создание пунктов плановой опорной геодезической сети без закладки центров методом спутниковых геодезических определений, 2-го разряда в условиях выполнения полевых работ: II категории | C15: 1 пункт | D15: 15 | E15: НЗ_ИГДИ-7-8 | F15: (35837*15)*0.5*1.27 (A**)*К1*К2 | G15: 335971.88
E16: К1 = 0.5 (ТЧ_п.44_т.7_прим._п.1) При выполнении полевых работ по созданию пунктов плановой опорной геодезической сети без закладки центров методом спутниковых геодезических определений, совмещённых с пунктами высотной опорной сети IV класса, созданных без закладки центров методом спутниковых геодезических определений, (К3)
E17: К2 = 1.27 Письмо Минстроя России N 45358-ИФ/09 от 22.07.2026г (2026г. III квартал)
E18: Кинф = 1.2700 (1) Письмо Минстроя России N 45358-ИФ/09 от 22.07.2026г (2026г. III квартал)
A19: IV. Работы по топографической съёмке в масштабах 1:500 - 1:2000
A20: Незастроенная территория
A21: Застроенная территория
A22: Этап 16; 4212.012.Р.16/0.0004.Г3.001.40203.000-ГСН; Межпоселковый газопровод высокого давления II категории от ПППГ до коллектора КС3-ГРП5; P=154,55м*6м=0.08га; 4212.012.Р.3/0.0004.КЛС.02А.41403.001-КЛС; Трассы кабельных линий связи; ГРП-2А Операторная - КС-3 СЭБ (поз. 225); P=4500м*6м=2.7га; Этап 3; 4212.00.Р.04.МПВ.2.000.НВ.000; Водовод межплощадочный КС3-ГРП2А подземной прокладки; P=1900м*6м=1.14а; Этап 16; 4212.00.Р.04.КК.10.000.НК.000; Коллектор межплощадочный канализационный ПППГ-КОС; P=214м*6м=0.13га; Этап 16; 4212.00.Р.04.МПВ.9.000.НВ.000; Водовод межплощадочный ПППГ-КОС; P=257м*6м=0.15га; Этап 27; 4212.00.Р.04.МПВ.8.000.НВ.000; Водовод межплощадочный КОС-КС5; P=665м*6м=0.40га; Этап 27; 4212.СРТ.00.Р.04.МПВ.5.1.НВ.000; Водовод межплощадочный к точке подключения ГРП.5; P=1370м*6м=0.82га; Этап 27; 4212.00.Р.04.МПВ.5.000.НВ.000; Водовод межплощадочный от КС5 до РЛВЖ; P=210м*6м=0.13га; 4212.012.Р.3/0.0004.ВЭЛ.000.41501.000-ЭВ - ВЛЗ 6 кВ (в габаритах 35 кВ) от ПС 110/35/6 кВ «Степная-газовая» до КСПХГ №5; P=3927м*6м=2.36га; 4212.012.Р.3/0.0004.ВЭЛ.000.41501.000-ЭВ1 - ВЛЗ 6 кВ к ГРП 2А; P=253м*6м=0.15га; 4212.012.Р.3/0.0004.ВЭЛ.000.41501.000-ЭВ2 - ВЛЗ 6 кВ к ГРП 1А; P=920м*6м=0.55га
A23: 3 | B23: Топографическая съемка тахеометрическим методом и сочетанием тахеометрического метода с методом спутниковых геодезических определений с высотой сечения рельефа через 0,5 метров, застроенной территории в масштабе 1:500 в условиях выполнения полевых работ: II категории | C23: 1 гектар | D23: 8.62233 | E23: НЗ_ИГДИ-18-11 | F23: (38848*8.62233)*1.27*0.5 (A**)*К2*К3 | G23: 209350.17
E24: К2 = 1.27 Письмо Минстроя России N 45358-ИФ/09 от 22.07.2026г (2026г. III квартал)
E25: К3 = 0.5 Обновление ИИ
E26: Кинф = 1.2700 (1) Письмо Минстроя России N 45358-ИФ/09 от 22.07.2026г (2026г. III квартал)
A27: V. Работы по съёмке подземных инженерных коммуникаций и сооружений
A28: 4 | B28: Полевые работы по поиску и съемке подземных инженерных коммуникаций при помощи трубокабелеискателя при количестве точек подземных инженерных коммуникаций на 1 гектар снимаемого участка: от 7 до 14 включительно | C28: 1 гектар | D28: 8.622335 | E28: НЗ_ИГДИ-46-2 | F28: (24772*8.622335)*1.27*0.5 (A**)*К1*К2 | G28: 133495.3
E29: К1 = 1.27 Письмо Минстроя России N 45358-ИФ/09 от 22.07.2026г (2026г. III квартал)
E30: К2 = 0.5 Обновление ИИ
E31: Кинф = 1.2700 (1) Письмо Минстроя России N 45358-ИФ/09 от 22.07.2026г (2026г. III квартал)
A32: VII. Работы по привязке инженерно-геологических выработок, геофизических и гидрогеологических точек наблюдения
A33: Работы по перенесению в натуру проектного положения инженерно-геологических, геофизических, гидрогеологических точек наблюдения.
A34: Работы по привязке фактического положения инженерно-геологических, геофизических, гидрогеологических точек наблюдения после завершения работ.
B35: Итоги по разделу 1 Полевые работы:
B36: Итого Поз. 1-4 | G36: 1 350 761.10
B37: Итого по разделу 1 Полевые работы | G37: 1 350 761.10
A38: Раздел 2. Дополнительные затраты на производство полевых работ
A39: 5 | B39: Показатели дополнительных затрат на внешний транспорт (ПДЗвнеш) автомобильного транспорта, расстояние от места постоянной работы работников до участка проведения полевых работ от 1000 до 2000 км включительно при стоимости полевых работ свыше/до 3000 тыс. руб. - 8,2 % | C39: руб. | D39: 1350761.2 | E39: НЗ_ИГДИ-3-4-4 | F39: (0.1175*1350761.24)*1.27 (B**)*Кинф | G39: 198393.06
E40: Кинф = 1.2700 (1) Письмо Минстроя России N 45358-ИФ/09 от 22.07.2026г (2026г. III квартал)
A41: 6 | B41: Показатели дополнительных затрат на организацию полевых работ (ПДЗорг), расстояние от места постоянной работы работников до участка проведения полевых работ от 1000 до 2000 км включительно: при стоимости полевых работ свыше/до 3000 тыс. руб. - 7,7 % | C41: руб. | D41: 1350761.2 | E41: НЗ_ИГДИ-4-4-4 | F41: (0.2345*1350761.24)*1.27 (B**)*Кинф | G41: 395941.89
E42: Кинф = 1.2700 (1) Письмо Минстроя России N 45358-ИФ/09 от 22.07.2026г (2026г. III квартал)
A43: 7 | B43: Дополнительные затраты на районные выплаты - 1.75 | C43: руб. | D43: 1746703.1 | E43: НЗ_ИГДИ п.33 | F43: (0*1746703.13)*1.27 (A**)*Кинф
E44: Кинф = 1.2700 (1) Письмо Минстроя России N 45358-ИФ/09 от 22.07.2026г (2026г. III квартал)
B45: Итоги по разделу 2 Дополнительные затраты на производство полевых работ:
B46: Итого Поз. 5-7 | G46: 594 334.95
B47: Итого по разделу 2 Дополнительные затраты на производство полевых работ | G47: 594 334.95
A48: Раздел 3. Камеральные работы
A49: III. Работы по созданию опорной геодезической сети
A50: 8 | B50: Камеральная обработка результатов измерений, выполненных при создании пунктов плановой опорной геодезической сети 4-го класса, 1-го и 2-го разрядов | C50: 1 пункт | D50: 15 | E50: НЗ_ИГДИ-16-1 | F50: (1714*15)*1.27 (A**)*Кинф | G50: 32137.5
E51: Кинф = 1.2700 (1) Письмо Минстроя России N 45358-ИФ/09 от 22.07.2026г (2026г. III квартал)
A52: 9 | B52: Камеральная обработка результатов измерений, выполненных при создании нивелирных пунктов высотной опорной геодезической сети III и IV классов | C52: 1 пункт | D52: 15 | E52: НЗ_ИГДИ-16-3 | F52: (1844*15)*1.27 (A**)*Кинф | G52: 34575
E53: Кинф = 1.2700 (1) Письмо Минстроя России N 45358-ИФ/09 от 22.07.2026г (2026г. III квартал)
A54: VI. Работы по созданию и обновлению инженерно-топографических планов в масштабах 1:500 - 1:5000
A55: Незастроенная территория
A56: Застроенная территория
A57: 10 | B57: Камеральные работы по созданию инженерно-топографических планов в масштабе 1:500 застроенной территории для условий выполнения полевых работ категории II при площади участка: от 10 до 50 гектар включительно | C57: 1 гектар | D57: 8.62233 | E57: НЗ_ИГДИ-47-18 | F57: (2556+4071*8.62233)*1.27 (A+B**)*Кинф | G57: 47071.88
E58: Кинф = 1.2700 (1) Письмо Минстроя России N 45358-ИФ/09 от 22.07.2026г (2026г. III квартал)
A59: Подземные коммуникации
A60: 11 | B60: Камеральные работы по нанесению подземных инженерных коммуникаций с их техническими характеристиками на инженерно-топографический план в масштабе 1:500 при количестве подземных инженерных коммуникаций по назначению на участке, подлежащем топографической съемке от 3 (трех) до 8 (восьми) включительно: от 10 до 50 гектар включительно | C60: 1 гектар | D60: 8.622331 | E60: НЗ_ИГДИ-51-8 | F60: (643+1018*8.622331)*1.27 (A+B**)*Кинф | G60: 11775.67
E61: Кинф = 1.2700 (1) Письмо Минстроя России N 45358-ИФ/09 от 22.07.2026г (2026г. III квартал)
A62: VIII. Работы по трассированию сетей
A63: *I. Прочие работы по ИГДИ
A64: 12 | B64: Камеральные работы по согласованию нанесения на инженерно-топографический план подземных инженерных коммуникаций и их технических характеристик с собственниками (эксплуатирующими организациями): известными | C64: 1 собственник (эксплуатирующая организация) | D64: 20 | E64: НЗ_ИГДИ-82-1 | F64: (21451*20)*1.27 (A**)*Кинф | G64: 536275
E65: Кинф = 1.2700 (1) Письмо Минстроя России N 45358-ИФ/09 от 22.07.2026г (2026г. III квартал)
A66: 13 | B66: Камеральные работы по согласованию нанесения на инженерно-топографический план подземных инженерных коммуникаций и их технических характеристик с собственниками (эксплуатирующими организациями): неизвестными | C66: 1 собственник (эксплуатирующая организация) | D66: 20 | E66: НЗ_ИГДИ-82-2 | F66: (29854*20)*1.27 (A**)*Кинф | G66: 746350
E67: Кинф = 1.2700 (1) Письмо Минстроя России N 45358-ИФ/09 от 22.07.2026г (2026г. III квартал)
B68: Итоги по разделу 3 Камеральные работы:
B69: Итого Поз. 8-13 | G69: 1 408 185.05
B70: Итого по разделу 3 Камеральные работы | G70: 1 408 185.05
A71: Раздел 4. Дополнительные затраты на производство камеральных работ
A72: 14 | B72: Дополнительные затраты на районные выплаты - 1.15 | C72: руб. | D72: 1408185.1 | E72: НЗ_ИГДИ п.40 | F72: (0.1095*1408185.05)*1.27 (A**)*Кинф | G72: 192745.33
E73: Кинф = 1.2700 (1) Письмо Минстроя России N 45358-ИФ/09 от 22.07.2026г (2026г. III квартал)
B74: Итоги по разделу 4 Дополнительные затраты на производство камеральных работ:
B75: Итого Поз. 14 | G75: 192 745.33
B76: Итого по разделу 4 Дополнительные затраты на производство камеральных работ | G76: 192 745.33
A77: Раздел 5. Составление программы инженерно-геодезических изысканий и технического отчёта по результам ИГДИ
A78: 15 | B78: Камеральные работы по составлению программы инженерно-геодезических изысканий при общей стоимости полевых и камеральных работ, определенной по показателям затрат, приведенным в НЗ: 10000 тысяч рублей | C78: 1 программа | D78: 2758946.3 | E78: НЗ_ИГДИ-80-6 | F78: (36839+(127949-36839)/(5000000-1000000)*(2758946.29-1000000))*1.27 (A1+(A2-A1)/(*2-*1)*(*-*1))*Кинф | G78: 96129.25
E79: Кинф = 1.2700 (1) Письмо Минстроя России N 45358-ИФ/09 от 22.07.2026г (2026г. III квартал)
A80: 16 | B80: Камеральные работы по составлению технического отчета по результатам выполнения работ по ИГДИ при общей стоимости полевых и камеральных работ, определенной по показателям затрат, приведенным в НЗ: 10000 тысяч рублей | C80: 1 отчет | D80: 2758946.3 | E80: НЗ_ИГДИ-81-6 | F80: (76000+(204000-76000)/(5000000-1000000)*(2758946.29-1000000))*1.27 (A1+(A2-A1)/(*2-*1)*(*-*1))*Кинф | G80: 165357.85
E81: Кинф = 1.2700 (1) Письмо Минстроя России N 45358-ИФ/09 от 22.07.2026г (2026г. III квартал)
B82: Итоги по разделу 5 Составление программы инженерно-геодезических изысканий и технического отчёта по результам ИГДИ:
B83: Итого Поз. 15-16 | G83: 261 487,220
B84: Итого по разделу 5 Составление программы инженерно-геодезических изысканий и технического отчёта по результам ИГДИ | G84: 261 487,220
B85: Итоги по смете:
B86: Итого по разделу 1 Полевые работы
B87: Итого Поз. 1-4 | G87: 1 350 761.10
B88: Итого по разделу 1 Полевые работы | G88: 1 350 761.10
B89: Итого по разделу 2 Дополнительные затраты на производство полевых работ
B90: Итого Поз. 5-7 | G90: 594 334.95
B91: Итого по разделу 2 Дополнительные затраты на производство полевых работ | G91: 594 334.95
B92: Итого по разделу 3 Камеральные работы
B93: Итого Поз. 8-13 | G93: 1 408 185.05
B94: Итого по разделу 3 Камеральные работы | G94: 1 408 185.05
B95: Итого по разделу 4 Дополнительные затраты на производство камеральных работ
B96: Итого Поз. 14 | G96: 192 745.33
B97: Итого по разделу 4 Дополнительные затраты на производство камеральных работ | G97: 192 745.33
B98: Итого по разделу 5 Составление программы инженерно-геодезических изысканий и технического отчёта по результам ИГДИ
B99: Итого Поз. 15-16 | G99: 261 487,220
B100: Итого по разделу 5 Составление программы инженерно-геодезических изысканий и технического отчёта по результам ИГДИ | G100: 261 487,220
B101: Итого | G101: 3868433.7
B102: ВСЕГО по смете | G102: 3807513.5

Sheet 1.1.4 ИГДИ+
G2: Форма 2п
B3: СМЕТА № 1.1.4 2026-07-29 Реконструкция ГПС - Убежище + ГС ГРП-2А
A5: № пп | B5: Наименование работ и затрат | C5: Единица измерения | D5: Кол-во | E5: Обоснование стоимости | F5: Расчет стоимости, руб. | G5: Стоимость, руб.
A6: 1 | B6: 2 | C6: 3 | D6: 4 | E6: 5 | F6: 6 | G6: 7
A7: Раздел 1. Полевые работы
A8: III. Работы по созданию опорной геодезической сети
A9: 1 | B9: Создание пунктов плановой опорной геодезической сети без закладки центров методом спутниковых геодезических определений, 2-го разряда в условиях выполнения полевых работ: II категории | C9: 1 пункт | D9: 10 | E9: НЗ_ИГДИ-7-8 | F9: (35837*10)*1.27 (A**)*К1 | G9: 447962.5
E10: К1 = 1.27 Письмо Минстроя России N 45358-ИФ/09 от 22.07.2026г (2026г. III квартал)
E11: Кинф = 1.2700 (1) Письмо Минстроя России N 45358-ИФ/09 от 22.07.2026г (2026г. III квартал)
A12: 2 | B12: Создание пунктов плановой опорной геодезической сети без закладки центров методом спутниковых геодезических определений, 2-го разряда в условиях выполнения полевых работ: II категории | C12: 1 пункт | D12: 10 | E12: НЗ_ИГДИ-7-8 | F12: (35837*10)*0.5*1.27 (A**)*К1*К2 | G12: 223981.25
E13: К1 = 0.5 (ТЧ_п.44_т.7_прим._п.1) При выполнении полевых работ по созданию пунктов плановой опорной геодезической сети без закладки центров методом спутниковых геодезических определений, совмещённых с пунктами высотной опорной сети IV класса, созданных без закладки центров методом спутниковых геодезических определений, (К3)
E14: К2 = 1.27 Письмо Минстроя России N 45358-ИФ/09 от 22.07.2026г (2026г. III квартал)
E15: Кинф = 1.2700 (1) Письмо Минстроя России N 45358-ИФ/09 от 22.07.2026г (2026г. III квартал)
A16: IV. Работы по топографической съёмке в масштабах 1:500 - 1:2000
A17: Незастроенная территория
A18: Застроенная территория
A19: 3 | B19: Топографическая съемка тахеометрическим методом и сочетанием тахеометрического метода с методом спутниковых геодезических определений с высотой сечения рельефа через 0,5 метров, застроенной территории в масштабе 1:1000 в условиях выполнения полевых работ: II категории | C19: 1 гектар | D19: 52 | E19: НЗ_ИГДИ-18-15 | F19: (25899*52)*1.27 (A**)*К2 | G19: 1683435
E20: К2 = 1.27 Письмо Минстроя России N 45358-ИФ/09 от 22.07.2026г (2026г. III квартал)
E21: Кинф = 1.2700 (1) Письмо Минстроя России N 45358-ИФ/09 от 22.07.2026г (2026г. III квартал)
A22: V. Работы по съёмке подземных инженерных коммуникаций и сооружений
A23: 4 | B23: Полевые работы по поиску и съемке подземных инженерных коммуникаций при помощи трубокабелеискателя при количестве точек подземных инженерных коммуникаций на 1 гектар снимаемого участка: от 7 до 14 включительно | C23: 1 гектар | D23: 52 | E23: НЗ_ИГДИ-46-2 | F23: (24772*52)*1.27 (A**)*К1 | G23: 1610180
E24: К1 = 1.27 Письмо Минстроя России N 45358-ИФ/09 от 22.07.2026г (2026г. III квартал)
E25: Кинф = 1.2700 (1) Письмо Минстроя России N 45358-ИФ/09 от 22.07.2026г (2026г. III квартал)
A26: VII. Работы по привязке инженерно-геологических выработок, геофизических и гидрогеологических точек наблюдения
A27: Работы по перенесению в натуру проектного положения инженерно-геологических, геофизических, гидрогеологических точек наблюдения.
A28: Работы по привязке фактического положения инженерно-геологических, геофизических, гидрогеологических точек наблюдения после завершения работ.
B29: Итоги по разделу 1 Полевые работы:
B30: Итого Поз. 1-4 | G30: 3 965 558.75
B31: Итого по разделу 1 Полевые работы | G31: 3 965 558.75
A32: Раздел 2. Дополнительные затраты на производство полевых работ
A33: 5 | B33: Дополнительные затраты на неизбежные перерывы - 25% | C33: руб. | D33: 3965558.9 | E33: НЗ_ИГДИ п.25 | F33: (0.25*3965558.86)*1.27 (B**)*Кинф | G33: 1239237.2
E34: Кинф = 1.2700 (1) Письмо Минстроя России N 45358-ИФ/09 от 22.07.2026г (2026г. III квартал)
A35: 6 | B35: Показатели дополнительных затрат на внешний транспорт (ПДЗвнеш) автомобильного транспорта, расстояние от места постоянной работы работников до участка проведения полевых работ от 1000 до 2000 км включительно при стоимости полевых работ свыше/до 3000 тыс. руб. - 8,2 % | C35: руб. | D35: 3965558.9 | E35: НЗ_ИГДИ-3-4-4 | F35: (0.119*3965558.86)*1.27 (B**)*Кинф | G35: 589876.88
E36: Кинф = 1.2700 (1) Письмо Минстроя России N 45358-ИФ/09 от 22.07.2026г (2026г. III квартал)
A37: 7 | B37: Показатели дополнительных затрат на организацию полевых работ (ПДЗорг), расстояние от места постоянной работы работников до участка проведения полевых работ от 1000 до 2000 км включительно: при стоимости полевых работ свыше/до 3000 тыс. руб. - 7,7 % | C37: руб. | D37: 3965558.9 | E37: НЗ_ИГДИ-4-4-4 | F37: (0.088*3965558.86)*1.27 (B**)*Кинф | G37: 436211.47
E38: Кинф = 1.2700 (1) Письмо Минстроя России N 45358-ИФ/09 от 22.07.2026г (2026г. III квартал)
B39: Итоги по разделу 2 Дополнительные затраты на производство полевых работ:
B40: Итого Поз. 5-7 | G40: 2 265 325.49
B41: Итого по разделу 2 Дополнительные затраты на производство полевых работ | G41: 2 265 325.49
A42: Раздел 3. Камеральные работы
A43: III. Работы по созданию опорной геодезической сети
A44: 8 | B44: Камеральная обработка результатов измерений, выполненных при создании пунктов плановой опорной геодезической сети 4-го класса, 1-го и 2-го разрядов | C44: 1 пункт | D44: 10 | E44: НЗ_ИГДИ-16-1 | F44: (1714*10)*1.27 (A**)*Кинф | G44: 21425
E45: Кинф = 1.2700 (1) Письмо Минстроя России N 45358-ИФ/09 от 22.07.2026г (2026г. III квартал)
A46: 9 | B46: Камеральная обработка результатов измерений, выполненных при создании нивелирных пунктов высотной опорной геодезической сети III и IV классов | C46: 1 пункт | D46: 10 | E46: НЗ_ИГДИ-16-3 | F46: (1844*10)*1.27 (A**)*Кинф | G46: 23050
E47: Кинф = 1.2700 (1) Письмо Минстроя России N 45358-ИФ/09 от 22.07.2026г (2026г. III квартал)
A48: VI. Работы по созданию и обновлению инженерно-топографических планов в масштабах 1:500 - 1:5000
A49: Незастроенная территория
A50: Застроенная территория
A51: 10 | B51: Камеральные работы по созданию инженерно-топографических планов в масштабе 1:1000 застроенной территории для условий выполнения полевых работ категории II при площади участка: от 10 до 50 гектар включительно | C51: 1 гектар | D51: 52 | E51: НЗ_ИГДИ-48-18 | F51: (15559+1017*52)*1.27 (A+B**)*Кинф | G51: 85553.75
E52: Кинф = 1.2700 (1) Письмо Минстроя России N 45358-ИФ/09 от 22.07.2026г (2026г. III квартал)
A53: Подземные коммуникации
A54: 11 | B54: Камеральные работы по нанесению подземных инженерных коммуникаций с их техническими характеристиками на инженерно-топографический план в масштабе 1:1000 при количестве подземных инженерных коммуникаций по назначению на участке, подлежащем топографической съемке от 3 (трех) до 8 (восьми) включительно: от 10 до 50 гектар включительно | C54: 1 гектар | D54: 52 | E54: НЗ_ИГДИ-52-8 | F54: (4904+308*52)*1.27 (A+B**)*Кинф | G54: 26150
E55: Кинф = 1.2700 (1) Письмо Минстроя России N 45358-ИФ/09 от 22.07.2026г (2026г. III квартал)
A56: VIII. Работы по трассированию сетей
A57: 12 | B57: Камеральные работы при подготовке ситуационного плана прохождения проектируемой трассы (ее вариантов) при условиях выполнения полевых работ: III категории | C57: 1 км | D57: 33.9 | E57: НЗ_ИГДИ-64-3 | F57: (310*33.9)*1.27 (A**)*Кинф | G57: 13136.25
E58: Кинф = 1.2700 (1) Письмо Минстроя России N 45358-ИФ/09 от 22.07.2026г (2026г. III квартал)
A59: 13 | B59: Камеральные работы при подготовке продольного профиля местности, по которому проходит проектируемая трасса в масштабах (горизонтальном 1:5000, вертикальном 1:500), при условиях производства полевых работ: II категории | C59: 1 км | D59: 33.9 | E59: НЗ_ИГДИ-64-5 | F59: (1289*33.9)*1.27*1.27 (A**)*К1*Кинф | G59: 68276.72
E60: К1 = 1.27 (ТЧ_п.138_т.64_прим._п.2) При работах по подготовке продольного профиля местности, по которому проходит проектируемая трасса в масштабах горизонтальном 1:2000, вертикальном 1:200, (К10)
E61: Кинф = 1.2700 (1) Письмо Минстроя России N 45358-ИФ/09 от 22.07.2026г (2026г. III квартал)
A62: 14 | B62: Подготовка схемы установки реперов и закрепления оси трассы закрепительными и выносными знаками | C62: 1 км | D62: 33.9 | E62: НЗ_ИГДИ-64-7 | F62: (212*33.9)*1.27 (A**)*Кинф | G62: 8983.5
E63: Кинф = 1.2700 (1) Письмо Минстроя России N 45358-ИФ/09 от 22.07.2026г (2026г. III квартал)
A64: 15 | B64: Подготовка ведомостей углов поворота, прямых и кривых (прямых и углов) | C64: 1 угол | D64: 169.5 | E64: НЗ_ИГДИ-64-8 | F64: (49*169.5)*1.27 (A**)*Кинф | G64: 10381.88
E65: Кинф = 1.2700 (1) Письмо Минстроя России N 45358-ИФ/09 от 22.07.2026г (2026г. III квартал)
A66: 16 | B66: Подготовка ведомостей координат закрепительных знаков и реперов | C66: 1 закрепительный знак | D66: 678 | E66: НЗ_ИГДИ-64-9 | F66: (49*678)*1.27 (A**)*Кинф | G66: 41527.5
E67: Кинф = 1.2700 (1) Письмо Минстроя России N 45358-ИФ/09 от 22.07.2026г (2026г. III квартал)
A68: 17 | B68: Подготовка ведомости пересекаемых угодий и лесов, водотоков, автомобильных и железных дорог, надземных и подземных сооружений, заболоченных и косогорных участков | C68: 1 пересечение | D68: 135.6 | E68: НЗ_ИГДИ-64-10 | F68: (54*135.6)*1.27 (A**)*Кинф | G68: 9153
E69: Кинф = 1.2700 (1) Письмо Минстроя России N 45358-ИФ/09 от 22.07.2026г (2026г. III квартал)
A70: *I. Прочие работы по ИГДИ
B71: Итоги по разделу 3 Камеральные работы:
B72: Итого Поз. 8-17 | G72: 307 637.60
B73: Итого по разделу 3 Камеральные работы | G73: 307 637.60
A74: Раздел 4. Дополнительные затраты на производство камеральных работ
A75: 18 | B75: Дополнительные затраты на районные выплаты - 1.15 | C75: руб. | D75: 307637.67 | E75: НЗ_ИГДИ п.40 | F75: (0.1095*307637.67)*1.27 (A**)*Кинф | G75: 42107.91
E76: Кинф = 1.2700 (1) Письмо Минстроя России N 45358-ИФ/09 от 22.07.2026г (2026г. III квартал)
B77: Итоги по разделу 4 Дополнительные затраты на производство камеральных работ:
B78: Итого Поз. 18 | G78: 42 107.91
B79: Итого по разделу 4 Дополнительные затраты на производство камеральных работ | G79: 42 107.91
A80: Раздел 5. Составление программы инженерно-геодезических изысканий и технического отчёта по результам ИГДИ
A81: 19 | B81: Камеральные работы по составлению программы инженерно-геодезических изысканий при общей стоимости полевых и камеральных работ, определенной по показателям затрат, приведенным в НЗ:1000 тысяч рублей | C81: 1 программа | D81: 4273196.5 | E81: НЗ_ИГДИ-80-4 | F81: (36839+(127949-36839)/(5000000-1000000)*(4273196.53-1000000))*1.27 (A1+(A2-A1)/(*2-*1)*(*-*1))*Кинф | G81: 139242.79
E82: Кинф = 1.2700 (1) Письмо Минстроя России N 45358-ИФ/09 от 22.07.2026г (2026г. III квартал)
A83: 20 | B83: Камеральные работы по составлению технического отчета по результатам выполнения работ по ИГДИ при общей стоимости полевых и камеральных работ, определенной по показателям затрат, приведенным в НЗ:1000 тысяч рублей | C83: 1 отчет | D83: 4273196.5 | E83: НЗ_ИГДИ-81-4 | F83: (76000+(204000-76000)/(5000000-1000000)*(4273196.53-1000000))*1.27 (A1+(A2-A1)/(*2-*1)*(*-*1))*Кинф | G83: 225927.86
E84: Кинф = 1.2700 (1) Письмо Минстроя России N 45358-ИФ/09 от 22.07.2026г (2026г. III квартал)
B85: Итоги по разделу 5 Составление программы инженерно-геодезических изысканий и технического отчёта по результам ИГДИ:
B86: Итого Поз. 19-20 | G86: 365 170.65
B87: Итого по разделу 5 Составление программы инженерно-геодезических изысканий и технического отчёта по результам ИГДИ | G87: 365 170.65
B88: Итоги по смете:
B89: Итого по разделу 1 Полевые работы
B90: Итого Поз. 1-4 | G90: 3 965 558.75
B91: Итого по разделу 1 Полевые работы | G91: 3 965 558.75
B92: Итого по разделу 2 Дополнительные затраты на производство полевых работ
B93: Итого Поз. 5-7 | G93: 2 265 325.49
B94: Итого по разделу 2 Дополнительные затраты на производство полевых работ | G94: 2 265 325.49
B95: Итого по разделу 3 Камеральные работы
B96: Итого Поз. 8-17 | G96: 307 637.60
B97: Итого по разделу 3 Камеральные работы | G97: 307 637.60
B98: Итого по разделу 4 Дополнительные затраты на производство камеральных работ
B99: Итого Поз. 18 | G99: 42 107.91
B100: Итого по разделу 4 Дополнительные затраты на производство камеральных работ | G100: 42 107.91
B101: Итого по разделу 5 Составление программы инженерно-геодезических изысканий и технического отчёта по результам ИГДИ
B102: Итого Поз. 19-20 | G102: 365 170.65
...

Sheet 1.2.1 ИГИ
A1: Смета №1.2.1
A2: на работы по инженерным изысканиям
A4: инженерно-геологические
A5: (наименование вида инженерных изысканий)
A6: Реконструкция газопромысловых сооружений Степновской СПХГ
A7: (наименование объекта капитального строительства)
A10: № | B10: Наименование работ или затрат | C10: Обоснование | D10: Расчет стоимости | E10: Сметная стоимость в уровне цен, сложившемся на день составления сметной документации, рублей | F10: объем
A11: 1 | B11: 2 | C11: 3 | D11: 4 | E11: 5
B12: I. Полевые работы
A13: 1 | B13: Рекогносцировочное обследование II категории сложности | C13: Нормативные затраты на работы по инженерно-геологическим изысканиям Табл.12, п.7 | D13: ="(15264+3608*"&F13&"га)*1.27" -> (15264+3608*13га)*1.27 | E13: =(15264+(3608*F13))*1.27 -> 78953.36 | F13: 13
A14: =A13+1 -> 2 | B14: Проходка инженерно-геологических скважин колонковым способом бурения: | C14: Нормативные затраты на работы по инженерно-геологическим изысканиям
B15: диаметром до 160 (ста шестидесяти) миллиметров включительно при глубине скважины до 15 (пятнадцати) метров включительно в грунтах категории:
B16: I | C16: Табл.14, п.1; Табл.2, п.1 | D16: ="2858*"&F16&"п.м.*1.04*1.27" -> 2858*57п.м.*1.04*1.27 | E16: =2858*F16*1.04*1.27 -> 215166.24 | F16: 57
B17: II | C17: Табл.14, п.2; Табл.2, п.1 | D17: ="3237*"&F17&"п.м.*1.04*1.27" -> 3237*204п.м.*1.04*1.27 | E17: =3237*F17*1.04*1.27 -> 872187.64 | F17: 204
B18: III | C18: Табл.14, п.3; Табл.2, п.1 | D18: ="3300*"&F18&"п.м.*1.04*1.27" -> 3300*74п.м.*1.04*1.27 | E18: =3300*F18*1.04*1.27 -> 322539.36 | F18: 74
B19: IV | C19: Табл.14, п.4; Табл.2, п.1 | D19: ="4125*"&F19&"п.м.*1.04*1.27" -> 4125*0п.м.*1.04*1.27 | E19: =4125*F19*1.04*1.27 -> 0 | F19: 0
A20: =A14+1 -> 3 | B20: Крепление инженерно-геологических скважин обсадными трубами | C20: Нормативные затраты на работы по инженерно-геологическим изысканиям Табл.25, п.1 | D20: ="1536*"&F20&"п.м.*1.27" -> 1536*67п.м.*1.27 | E20: =1536*F20*1.27 -> 130698.24 | F20: 67
A21: =A20+1 -> 4 | B21: Проведение гидрогеологических исследований первого от поверхности земли подземного водоносного горизонта в инженерно-геологических скважинах | C21: Нормативные затраты на работы по инженерно-геологическим изысканиям Табл.26, п.1 | D21: ="983*"&F21&"скв*1.27" -> 983*31скв*1.27 | E21: =983*F21*1.27 -> 38700.71 | F21: 31
A22: =A21+1 -> 5 | B22: Проходка шурфов при глубине шурфа, метров: | C22: Нормативные затраты на работы по инженерно-геологическим изысканиям
B23: от 2,5 до 5 включительно в грунтах категории:
B24: III | C24: Табл.30, п.7 | D24: ="23558*"&F24&"м3*1.27" -> 23558*60м3*1.27 | E24: =23558*F24*1.02*1.27 -> 1831022 | F24: =24*2.5 -> 60
B25: IV | C25: Табл.30, п.8 | D25: ="37562*"&F25&"м3*1.27" -> 37562*60м3*1.27 | E25: =37562*F25*1.02*1.27 -> 2919468.9 | F25: =24*2.5 -> 60
A26: =A22+1 -> 6 | B26: Предварительная проходка методом разбуривания асфальта, бетона, древесины, крупнообломочных грунтов, техногенных грунтов с поверхности земли для последующего проведения полевых испытаний грунтов методом статического зондирования | C26: Нормативные затраты на работы по инженерно-геологическим изысканиям Табл.43, п.1; Табл.2, п.5 | D26: ="902*"&F26&"п.м.*1.02*1.27" -> 902*10п.м.*1.02*1.27 | E26: =902*F26*1.02*1.27 -> 11684.508 | F26: 10
A27: =A26+1 -> 7 | B27: Полевые испытания грунтов методом статического зондирования непрерывным вдавливанием на глубину, метров: | C27: Нормативные затраты на работы по инженерно-геологическим изысканиям
B28: от 10 до 15 включительно | C28: Табл.43, п.3; Табл.2, п.5 | D28: ="3138*"&F28&"п.м.*1.1*1.27" -> 3138*150п.м.*1.1*1.27 | E28: =3138*F28*1.1*1.27 -> 657567.9 | F28: 150
A29: =A27+1 -> 8 | B29: Дополнительные затраты на производство полевых работ в неблагоприятный период года | C29: Нормативные затраты на работы по инженерно-геологическим изысканиям Табл.3, п.3 | D29: =ROUND(SUM(E13:E28),0)&"*0.19" -> 7077989*0.19 | E29: =SUM(E13:E28)*0.19 -> 1344817.9
A30: =A29+1 -> 9 | B30: Дополнительных затрат на неизбежные перерывы | C30: Нормативные затраты на работы по инженерно-геологическим изысканиям п.27 | D30: =ROUND(SUM(E13:E28),0)&"*0.25" -> 7077989*0.25 | E30: =SUM(E13:E28)*0.25 -> 1769497.2
A31: =A30+1 -> 10 | B31: Дополнительные затраты на проезд | C31: Нормативные затраты на работы по инженерно-геологическим изысканиям Табл.5, п.5 | D31: =ROUND(SUM(E13:E28),0)&"*(28.1%+(48.2%-28.1%)/(10млн.руб-5млн.руб)*(10млн.руб-"&ROUND(SUM(E13:E28),0)&"))" -> 7077989*(28.1%+(48.2%-28.1%)/(10млн.руб-5млн.руб)*(10млн.руб-7077989)) | E31: =SUM(E13:E28)*(28.1%+(48.2%-28.1%)/(10000000-5000000)*(10000000-SUM(E13:E28))) -> 2820329.8
A32: =A31+1 -> 11 | B32: Дополнительные затраты на организацию полевых работ | C32: Нормативные затраты на работы по инженерно-геологическим изысканиям Табл.8, п.5. | D32: =ROUND(SUM(E13:E28),0)&"*7.4%" -> 7077989*7.4% | E32: =SUM(E13:E28)*7.4% -> 523771.17
A33: =A32+1 -> 12 | B33: Дополнительные затраты на районные выплаты | C33: Нормативные затраты на работы по инженерно-геологическим изысканиям п.40 | D33: ="("&ROUND(SUM(E13:E28),0)&"+"&ROUND(E29,0)&"+"&ROUND(E30,0)&"+"&ROUND(E32,0)&")*(0.41*"&ROUND(F33,2)&"+0.59-1)" -> (7077989+1344818+1769497+523771)*(0.41*1+0.59-1) | E33: =(SUM(E13:E30)+E32)*(0.41*F33+0.59-1) -> 0 | F33: 1
B34: Итого по разделу I | E34: =SUM(E13:E33) -> 13536405
B35: II. Лабораторные работы
A36: =A33+1 -> 13 | B36: Определение влажности грунта методом высушивания до постоянной массы | C36: Нормативные затраты на работы по инженерно-геологическим изысканиям Табл.56, п.1-3; Табл.57, п.1 | D36: ="((459+335+141)*"&F36&"обр+229*"&F36&"опр)*1.27" -> ((459+335+141)*167обр+229*167опр)*1.27 | E36: =((459+335+141)*F36+229*F36)*1.27 -> 246872.76 | F36: 167
A37: =A36+1 -> 14 | B37: Определение плотности частиц грунта пикнометрическим методом | C37: Нормативные затраты на работы по инженерно-геологическим изысканиям Табл.56, п.1-3; Табл.57, п.4 | D37: ="((459+335+141)*"&F37&"обр+600*"&F37&"опр)*1.27" -> ((459+335+141)*122обр+600*122опр)*1.27 | E37: =((459+335+141)*F37+600*F37)*1.27 -> 237832.9 | F37: =90+32 -> 122
A38: =A37+1 -> 15 | B38: Определение содержания органических веществ в грунте методом прокаливания до постоянной массы | C38: Нормативные затраты на работы по инженерно-геологическим изысканиям Табл.56, п.1-3; Табл.57, п.8 | D38: ="((459+335+141)*"&F38&"обр+370*"&F38&"опр)*1.27" -> ((459+335+141)*18обр+370*18опр)*1.27 | E38: =((459+335+141)*F38+370*F38)*1.27 -> 29832.3 | F38: 18
A39: =A38+1 -> 16 | B39: Определение гранулометрического (зернового) состава грунта ситовым методом с промывкой водой с разделением грунта по фракциям размерами: свыше 0,5 миллиметра, от 0,25 до 0,5 миллиметра, от 0,1 до 0,25 миллиметра и до 0,1 миллиметра | C39: Нормативные затраты на работы по инженерно-геологическим изысканиям Табл.56, п.1-3; Табл.57, п.10 | D39: ="((459+335+141)*"&F39&"обр+917*"&F39&"опр)*1.27" -> ((459+335+141)*60обр+917*60опр)*1.27 | E39: =((459+335+141)*F39+917*F39)*1.27 -> 141122.4 | F39: 60
A40: =A39+1 -> 17 | B40: Определение гранулометрического (микроагрегатного) состава грунта ареометрическим методом с разделением грунта на фракции размерами: от 0,05 до 0,1 миллиметра, от 0,01 до 0,05 миллиметра, от 0,005 до 0,01 миллиметра, от 0,001 до 0,002 миллиметра и до 0,001 миллиметра | C40: Нормативные затраты на работы по инженерно-геологическим изысканиям Табл.56, п.1-3; Табл.57, п.14 | D40: ="((459+335+141)*"&F40&"обр+1852*"&F40&"опр)*1.27" -> ((459+335+141)*60обр+1852*60опр)*1.27 | E40: =((459+335+141)*F40+1852*F40)*1.27 -> 212369.4 | F40: 60
A41: =A40+1 -> 18 | B41: Определение относительной деформации морозного пучения | C41: Нормативные затраты на работы по инженерно-геологическим изысканиям Табл.56, п.1-3; Табл.57, п.16 | D41: ="((459+335+141)*"&F41&"обр+4546*"&F41&"опр)*1.27" -> ((459+335+141)*6обр+4546*6опр)*1.27 | E41: =((459+335+141)*F41+4546*F41)*1.27 -> 41765.22 | F41: 6
A42: =A41+1 -> 19 | B42: Определение плотности глинистого грунта методом режущего кольца | C42: Нормативные затраты на работы по инженерно-геологическим изысканиям Табл.56, п.1-3; Табл.57, п.17 | D42: ="((459+335+141)*"&F42&"обр+529*"&F42&"опр)*1.27" -> ((459+335+141)*122обр+529*122опр)*1.27 | E42: =((459+335+141)*F42+529*F42)*1.27 -> 226832.16 | F42: =90+32 -> 122
A43: =A42+1 -> 20 | B43: Определение верхнего предела пластичности глинистого грунта - влажности грунта на границе текучести и нижнего предела пластичности глинистого грунта - влажности грунта на границе раскатывания при проведении испытания с использованием образца грунта природной влажности | C43: Нормативные затраты на работы по инженерно-геологическим изысканиям Табл.56, п.1-3; Табл.57, п.18 | D43: ="((459+335+141)*"&F43&"обр+1676*"&F43&"опр)*1.27" -> ((459+335+141)*139обр+1676*139опр)*1.27 | E43: =((459+335+141)*F43+1676*F43)*1.27 -> 460919.83 | F43: =107+32 -> 139
A44: =A43+1 -> 21 | B44: Определение характеристик набухания глинистого грунта методом свободного набухания | C44: Нормативные затраты на работы по инженерно-геологическим изысканиям Табл.56, п.1-3; Табл.57, п.20 | D44: ="((459+335+141)*"&F44&"обр+723*"&F44&"опр)*1.27" -> ((459+335+141)*12обр+723*12опр)*1.27 | E44: =((459+335+141)*F44+723*F44)*1.27 -> 25267.92 | F44: 12
A45: =A44+1 -> 22 | B45: Определение характеристик свободной усадки глинистого грунта | C45: Нормативные затраты на работы по инженерно-геологическим изысканиям Табл.56, п.1-3; Табл.57, п.21 | D45: ="((459+335+141)*"&F45&"обр+388*"&F45&"опр)*1.27" -> ((459+335+141)*6обр+388*6опр)*1.27 | E45: =((459+335+141)*F45+388*F45)*1.27 -> 10081.26 | F45: 6
A46: =A45+1 -> 23 | B46: Определение максимальной плотности сухого глинистого грунта и соответствующей ей влажности с увеличением влажности грунта на 1 (один) - 2 (два) процента не менее шести раз | C46: Нормативные затраты на работы по инженерно-геологическим изысканиям Табл.56, п.1-3; Табл.57, п.24 | D46: ="((459+335+141)*"&F46&"обр+13759*"&F46&"опр)*1.27" -> ((459+335+141)*6обр+13759*6опр)*1.27 | E46: =((459+335+141)*F46+13759*F46)*1.27 -> 111968.28 | F46: 6
A47: =A46+1 -> 24 | B47: Определение коэффициента фильтрации песчаных грунтов при постоянном градиенте напора (стационарный режим фильтрации) с содержанием частиц диаметром менее 0,1 миллиметра до 5 (пяти) процентов включительно | C47: Нормативные затраты на работы по инженерно-геологическим изысканиям Табл.56, п.1-3; Табл.57, п.28 | D47: ="((459+335+141)*"&F47&"обр+2203*"&F47&"опр)*1.27" -> ((459+335+141)*10обр+2203*10опр)*1.27 | E47: =((459+335+141)*F47+2203*F47)*1.27 -> 39852.6 | F47: 10
A48: =A47+1 -> 25 | B48: Определение характеристик деформируемости песчаного грунта методом компрессионного сжатия при нагружении одного образца грунта не менее чем пятью ступенями статической нагрузки | C48: Нормативные затраты на работы по инженерно-геологическим изысканиям Табл.56, п.1-3; Табл.58, п.1 | D48: ="((459+335+141)*"&F48&"обр+5452*"&F48&"опр)*1.27" -> ((459+335+141)*12обр+5452*12опр)*1.27 | E48: =((459+335+141)*F48+5452*F48)*1.27 -> 97337.88 | F48: 12
A49: =A48+1 -> 26 | B49: Определение характеристик деформируемости глинистого грунта с показателем текучести менее 0,25 для образцов ненарушенного сложения методом компрессионного сжатия с предварительным водонасыщением образца грунта (при необходимости) и при нагружении одного образца грунта не менее чем пятью ступенями статической нагрузки | C49: Нормативные затраты на работы по инженерно-геологическим изысканиям Табл.56, п.1-3; Табл.58, п.2 | D49: ="((459+335+141)*"&F49&"обр+7357*"&F49&"опр)*1.27" -> ((459+335+141)*50обр+7357*50опр)*1.27 | E49: =((459+335+141)*F49+7357*F49)*1.27 -> 526542 | F49: =18+32 -> 50
A50: =A49+1 -> 27 | B50: Определение характеристик просадочности грунта при замачивании водой в компрессионных приборах по схеме "двух кривых" для определения относительной просадочности грунта при различных давлениях начального просадочного давления | C50: Нормативные затраты на работы по инженерно-геологическим изысканиям Табл.56, п.1-3; Табл.58, п.8 | D50: ="((459+335+141)*"&F50&"обр+7266*"&F50&"опр)*1.27" -> ((459+335+141)*12обр+7266*12опр)*1.27 | E50: =((459+335+141)*F50+7266*F50)*1.27 -> 124983.24 | F50: 12
A51: =A50+1 -> 28 | B51: Определение характеристик набухания и усадки грунта под нагрузкой | C51: Нормативные затраты на работы по инженерно-геологическим изысканиям Табл.56, п.1-3; Табл.58, п.12 | D51: ="((459+335+141)*"&F51&"обр+29931*"&F51&"опр)*1.27" -> ((459+335+141)*6обр+29931*6опр)*1.27 | E51: =((459+335+141)*F51+29931*F51)*1.27 -> 235198.92 | F51: 6
A52: =A51+1 -> 29 | B52: Определение характеристик прочности песчаного грунта консолидированно-дренированными испытаниями методом одноплоскостного среза при проведении не менее трех испытаний идентичных образцов при различных значениях нормального напряжения | C52: Нормативные затраты на работы по инженерно-геологическим изысканиям Табл.56, п.1-3; Табл.59, п.1 | D52: ="((459+335+141)*"&F52&"обр+8520*"&F52&"опр)*1.27" -> ((459+335+141)*12обр+8520*12опр)*1.27 | E52: =((459+335+141)*F52+8520*F52)*1.27 -> 144094.2 | F52: 12
A53: =A52+1 -> 30 | B53: Определение характеристик прочности глины с числом пластичности от 17 (семнадцати) до 30 (тридцати) процентов включительно консолидированно-дренированными испытаниями методом одноплоскостного среза при проведении не менее трех испытаний идентичных образцов при различных значениях нормального напряжения | C53: Нормативные затраты на работы по инженерно-геологическим изысканиям Табл.56, п.1-3; Табл.59, п.5 | D53: ="((459+335+141)*"&F53&"обр+9293*"&F53&"опр)*1.27" -> ((459+335+141)*50обр+9293*50опр)*1.27 | E53: =((459+335+141)*F53+9293*F53)*1.27 -> 649478 | F53: =18+32 -> 50
A54: =A53+1 -> 31 | B54: Определение характеристик деформируемости методом трехосного сжатия песчаного грунта Консолидированно-дренированным испытанием (КД) | C54: Нормативные затраты на работы по инженерно-геологическим изысканиям Табл.56, п.1-3; Табл.60, п.22 | D54: ="((459+335+141)*"&F54&"обр+4593*"&F54&"опр)*1.27" -> ((459+335+141)*44обр+4593*44опр)*1.27 | E54: =((459+335+141)*F54+4593*F54)*1.27 -> 308904.64 | F54: =12+32 -> 44
A55: =A54+1 -> 32 | B55: Определение характеристик деформируемости методом трехосного сжатия глины с показателем текучести до 0,25 Консолидированно-дренированным испытанием (КД) | C55: Нормативные затраты на работы по инженерно-геологическим изысканиям Табл.56, п.1-3; Табл.60, п.28 | D55: ="((459+335+141)*"&F55&"обр+6470*"&F55&"опр)*1.27" -> ((459+335+141)*18обр+6470*18опр)*1.27 | E55: =((459+335+141)*F55+6470*F55)*1.27 -> 169278.3 | F55: 18
A56: =A55+1 -> 33 | B56: Определение физических свойств, химического состава и агрессивности подземных вод состава | C56: Нормативные затраты на работы по инженерно-геологическим изысканиям Табл.63, п.1 | D56: ="11731*"&F56&"опр*1.27" -> 11731*9опр*1.27 | E56: =11731*F56*1.27 -> 134085.33 | F56: 9
A57: =A56+1 -> 34 | B57: Определение физических свойств, химического состава и агрессивности водной вытяжки из грунтов | C57: Нормативные затраты на работы по инженерно-геологическим изысканиям Табл.63, п.3 | D57: ="9786*"&F57&"опр*1.27" -> 9786*22опр*1.27 | E57: =9786*F57*1.27 -> 273420.84 | F57: 22
A58: =A57+1 -> 35 | B58: Определение удельного электрического сопротивления и средней плотности катодного тока грунта | C58: Нормативные затраты на работы по инженерно-геологическим изысканиям Табл.63, п.5 | D58: ="2726*"&F58&"опр*1.27" -> 2726*18опр*1.27 | E58: =2726*F58*1.27 -> 62316.36 | F58: 18
A59: =A58+1 -> 36 | B59: Дополнительные затраты на районные выплаты | C59: Нормативные затраты на работы по инженерно-геологическим изысканиям п.47; Табл.10, п.1 | D59: =ROUND(SUM(E36:F58),0)&"*("&0.65&"*"&F59&"+"&0.35&"-"&1&")" -> 4511338*(0,65*1,15+0,35-1) | E59: =SUM(E36:E58)*(0.65*F59+0.35-1) -> 439759.78 | F59: 1.15
B60: Итого по разделу II | E60: =SUM(E36:E59) -> 4950116.5
B61: III. Камеральные работы
A62: =A59+1 -> 37 | B62: Камеральная обработка результатов полевых работ по проходке следующих инженерно-геологических выработок: | C62: Нормативные затраты на работы по инженерно-геологическим изысканиям
B63: инженерно-геологических скважин в условиях категории сложности инженерно-геологических условий:
B64: II (архив) | C64: Табл.33, п.2 | D64: ="342*"&F64&"п.м.*1.27" -> 342*297п.м.*1.27 | E64: =342*F64*1.27 -> 128998.98 | F64: 297
B65: II | C65: Табл.33, п.2 | D65: ="342*"&SUM(F16:F19)&"п.м.*1.27" -> 342*335п.м.*1.27 | E65: =342*SUM(F16:F19)*1.27 -> 145503.9
A66: =A62+1 -> 38 | B66: Камеральная обработка результатов полевых работ по проходке шурфов глубиной, метров: | C66: Нормативные затраты на работы по инженерно-геологическим изысканиям
B67: до 5 включительно | C67: Табл.33, п.5 | D67: ="2504*"&F67&"шурфов*1.27" -> 2504*16шурфов*1.27 | E67: =2504*F67*1.2 -> 48076.8 | F67: 16
A68: =A62+1 -> 38 | B68: Камеральная обработка результатов полевых испытаний грунтов методом статического зондирования непрерывным вдавливанием зонда | C68: Нормативные затраты на работы по инженерно-геологическим изысканиям Табл.45, п.1 | D68: ="173*"&SUM(F28)&"п.м.*1.27" -> 173*150п.м.*1.27 | E68: =173*SUM(F28)*1.27 -> 32956.5
A69: =A68+1 -> 39 | B69: Камеральная обработка результатов лабораторных определений физических свойств грунтов: | C69: Нормативные затраты на работы по инженерно-геологическим изысканиям
B70: песчаных | C70: Табл.62, п.1 | D70: ="320*"&F39&"обр*1.27" -> 320*60обр*1.27 | E70: =320*F39*1.27 -> 24384
B71: глинистых | C71: Табл.62, п.2 | D71: ="381*"&F43&"обр*1.27" -> 381*139обр*1.27 | E71: =381*F43*1.27 -> 67257.93
B72: органических | C72: Табл.62, п.4 | D72: ="358*"&F38&"обр*1.27" -> 358*18обр*1.27 | E72: =358*F38*1.27 -> 8183.88
A73: =A69+1 -> 40 | B73: Камеральная обработка результатов лабораторных исследований механических свойств грунтов (методом компрессионного сжатия, методом одноплоскостного среза, методом трехосного сжатия): | C73: Нормативные затраты на работы по инженерно-геологическим изысканиям
B74: песчаных | C74: Табл.62, п.5 | D74: ="693*"&SUM(F48,F52,F54)&"обр*1.27" -> 693*68обр*1.27 | E74: =693*(SUM(F48,F52,F54))*1.27 -> 59847.48
B75: глинистых | C75: Табл.62, п.6 | D75: ="730*"&SUM(F41,F49,F50,F51,F53,F55)&"обр*1.27" -> 730*142обр*1.27 | E75: =730*SUM(F41,F49,F50,F51,F53,F55)*1.27 -> 131648.2
A76: =A73+1 -> 41 | B76: Камеральная обработка результатов лабораторных исследований физических свойств, химического состава и агрессивности подземных вод | C76: Нормативные затраты на работы по инженерно-геологическим изысканиям Табл.64, п.1 | D76: ="385*"&F57&"обр*1.27" -> 385*22обр*1.27 | E76: =385*F56*1.27 -> 4400.55
A77: =A76+1 -> 42 | B77: Камеральная обработка результатов лабораторных исследований физических свойств, химического состава и агрессивности водной вытяжки из грунтов и удельного электрического сопротивления и средней плотности катодного тока грунта | C77: Нормативные затраты на работы по инженерно-геологическим изысканиям Табл.64, п.2 | D77: ="352*"&SUM(F57:F58)&"обр*1.27" -> 352*40обр*1.27 | E77: =352*SUM(F57:F58)*1.27 -> 17881.6
A78: =A77+1 -> 43 | B78: Составление технического отчета по результатам выполнения работ по ИГИ при общей стоимости камеральных работ в уровне цен по состоянию на 1 января 2024 г. (без учета дополнительных затрат), определенной по показателям затрат, приведенным в НЗ, в условиях инженерно-геологических условий категории сложности, тысяч рублей: | C78: Нормативные затраты на работы по инженерно-геологическим изысканиям
B79: II
B80: 250-500 | C80: Табл.65, п.12-13, прим.3 | D80: =(789323&"-(789323-577018)/(1млн.руб-500тыс.руб)*("&"1млн.руб-"&ROUND(SUM(E62:E75),0)&"))*1.1*1.27") -> 789323-(789323-577018)/(1млн.руб-500тыс.руб)*(1млн.руб-646858))*1.1*1.27 | E80: =(789323-(789323-577018)/(1000000-500000)*(1000000-SUM(E62:E75)))*1.1*1.27 -> 893207.2
A81: =A78+1 -> 44 | B81: Составление программы инженерно-геологических изысканий для II категории сложности инженерно-геологических условий: | C81: Нормативные затраты на работы по инженерно-геологическим изысканиям
B82: при площади земельного участка (участка для строительства) от 10 (десяти) до 100 (ста) гектаров и максимальной глубине исследования, метров:
B83: от 10 до 15 включительно | C83: Табл.66, п.17 | D83: ="200982*1.27" -> 200982*1.27 | E83: =200982*1.27 -> 255247.14
A84: =A81+1 -> 45 | B84: Дополнительные затраты на районные выплаты | C84: Нормативные затраты на работы по инженерно-геологическим изысканиям п.45; Табл.10, п.2 | D84: =ROUND(SUM(E62:E83),0)&"*("&0.73&"*"&F84&"+"&0.27&"-"&1&")" -> 1817594*(0,73*1,15+0,27-1) | E84: =SUM(E62:E83)*(0.73*F84+0.27-1) -> 199026.56 | F84: 1.15
A85: 46 | B85: Итого по разделу III | E85: =SUM(E62:E84) -> 2016620.7
A86: 47 | B86: Всего по смете в уровне цен, сложившемся на день составления сметной документации: | E86: =SUM(E34,E60,E85) -> 20503142
A87: 48 | B87: Всего по смете | E87: =E86 -> 20503142

Sheet 1.2.2 ИГИ+
A1: Смета №1.2.2
A2: на работы по инженерным изысканиям
A4: инженерно-геологические
A5: (наименование вида инженерных изысканий)
A6: Реконструкция газопромысловых сооружений Степновской СПХГ
A7: (наименование объекта капитального строительства)
A10: № | B10: Наименование работ или затрат | C10: Обоснование | D10: Расчет стоимости | E10: Сметная стоимость в уровне цен, сложившемся на день составления сметной документации, рублей | F10: объем
A11: 1 | B11: 2 | C11: 3 | D11: 4 | E11: 5
B12: I. Полевые работы
A13: 1 | B13: Рекогносцировочное обследование II категории сложности | C13: Нормативные затраты на работы по инженерно-геологическим изысканиям Табл.12, п.7 | D13: ="(15264+3608*"&F13&"га)*1,27" -> (15264+3608*0,3га)*1,27 | E13: =(15264+(3608*F13))*1.27 -> 20759.928 | F13: 0.3
A14: =A13+1 -> 2 | B14: Проходка инженерно-геологических скважин колонковым способом бурения: | C14: Нормативные затраты на работы по инженерно-геологическим изысканиям
B15: диаметром до 160 (ста шестидесяти) миллиметров включительно при глубине скважины до 15 (пятнадцати) метров включительно в грунтах категории:
B16: I | C16: Табл.14, п.1; Табл.2, п.1 | D16: ="2858*"&F16&"п.м.*1.04*1,27" -> 2858*7п.м.*1.04*1,27 | E16: =2858*F16*1.04*1.27 -> 26423.925 | F16: 7
B17: II | C17: Табл.14, п.2; Табл.2, п.1 | D17: ="3237*"&F17&"п.м.*1.04*1,27" -> 3237*7п.м.*1.04*1,27 | E17: =3237*F17*1.04*1.27 -> 29928.007 | F17: 7
B18: III | C18: Табл.14, п.3; Табл.2, п.1 | D18: ="3300*"&F18&"п.м.*1.04*1,27" -> 3300*8п.м.*1.04*1,27 | E18: =3300*F18*1.04*1.27 -> 34869.12 | F18: 8
B19: IV | C19: Табл.14, п.4; Табл.2, п.1 | D19: ="4125*"&F19&"п.м.*1.04*1,27" -> 4125*0п.м.*1.04*1,27 | E19: =4125*F19*1.04*1.27 -> 0 | F19: 0
A20: =A14+1 -> 3 | B20: Крепление инженерно-геологических скважин обсадными трубами | C20: Нормативные затраты на работы по инженерно-геологическим изысканиям Табл.25, п.1 | D20: ="1536*"&F20&"п.м.*1,27" -> 1536*6п.м.*1,27 | E20: =1536*F20*1.27 -> 11704.32 | F20: 6
A21: =A20+1 -> 4 | B21: Проведение гидрогеологических исследований первого от поверхности земли подземного водоносного горизонта в инженерно-геологических скважинах | C21: Нормативные затраты на работы по инженерно-геологическим изысканиям Табл.26, п.1 | D21: ="983*"&F21&"скв*1,27" -> 983*2скв*1,27 | E21: =983*F21*1.27 -> 2496.82 | F21: 2
A22: =A21+1 -> 5 | B22: Проходка шурфов при глубине шурфа, метров: | C22: Нормативные затраты на работы по инженерно-геологическим изысканиям
B23: от 2,5 до 5 включительно в грунтах категории:
B24: III | C24: Табл.30, п.7 | D24: ="23558*"&F24&"м3*1,27" -> 23558*0м3*1,27 | E24: =23558*F24*1.02*1.27 -> 0 | F24: 0
B25: IV | C25: Табл.30, п.8 | D25: ="37562*"&F25&"м3*1,27" -> 37562*0м3*1,27 | E25: =37562*F25*1.02*1.27 -> 0 | F25: 0
A26: =A22+1 -> 6 | B26: Предварительная проходка методом разбуривания асфальта, бетона, древесины, крупнообломочных грунтов, техногенных грунтов с поверхности земли для последующего проведения полевых испытаний грунтов методом статического зондирования | C26: Нормативные затраты на работы по инженерно-геологическим изысканиям Табл.43, п.1; Табл.2, п.5 | D26: ="902*"&F26&"п.м.*1.02*1,27" -> 902*0п.м.*1.02*1,27 | E26: =902*F26*1.02*1.27 -> 0 | F26: 0
A27: =A26+1 -> 7 | B27: Полевые испытания грунтов методом статического зондирования непрерывным вдавливанием на глубину, метров: | C27: Нормативные затраты на работы по инженерно-геологическим изысканиям
B28: от 10 до 15 включительно | C28: Табл.43, п.3; Табл.2, п.5 | D28: ="3138*"&F28&"п.м.*1.1*1,27" -> 3138*0п.м.*1.1*1,27 | E28: =3138*F28*1.1*1.27 -> 0 | F28: 0
A29: =A27+1 -> 8 | B29: Дополнительные затраты на производство полевых работ в неблагоприятный период года | C29: Нормативные затраты на работы по инженерно-геологическим изысканиям Табл.3, п.3 | D29: =ROUND(SUM(E13:E28),0)&"*0.19" -> 126182*0.19 | E29: =SUM(E13:E28)*0.19 -> 23974.603
A30: =A29+1 -> 9 | B30: Дополнительных затрат на неизбежные перерывы | C30: Нормативные затраты на работы по инженерно-геологическим изысканиям п.27 | D30: =ROUND(SUM(E13:E28),0)&"*0.25" -> 126182*0.25 | E30: =SUM(E13:E28)*0.25 -> 31545.53
A31: =A30+1 -> 10 | B31: Дополнительные затраты на проезд | C31: Нормативные затраты на работы по инженерно-геологическим изысканиям Табл.5, п.5 | D31: =ROUND(SUM(E13:E28),0)&"*(28.1%+(48.2%-28.1%)/(10млн.руб-5млн.руб)*(10млн.руб-"&ROUND(SUM(E13:E28),0)&"))" -> 126182*(28.1%+(48.2%-28.1%)/(10млн.руб-5млн.руб)*(10млн.руб-126182)) | E31: =SUM(E13:E28)*(28.1%+(48.2%-28.1%)/(10000000-5000000)*(10000000-SUM(E13:E28))) -> 85542.326
A32: =A31+1 -> 11 | B32: Дополнительные затраты на организацию полевых работ | C32: Нормативные затраты на работы по инженерно-геологическим изысканиям Табл.8, п.5. | D32: =ROUND(SUM(E13:E28),0)&"*7.4%" -> 126182*7.4% | E32: =SUM(E13:E28)*7.4% -> 9337.4769
A33: =A32+1 -> 12 | B33: Дополнительные затраты на районные выплаты | C33: Нормативные затраты на работы по инженерно-геологическим изысканиям п.40 | D33: ="("&ROUND(SUM(E13:E28),0)&"+"&ROUND(E29,0)&"+"&ROUND(E30,0)&"+"&ROUND(E32,0)&")*(0.41*"&ROUND(F33,2)&"+0.59-1)" -> (126182+23975+31546+9337)*(0.41*1+0.59-1) | E33: =(SUM(E13:E30)+E32)*(0.41*F33+0.59-1) -> 0 | F33: 1
B34: Итого по разделу I | E34: =SUM(E13:E33) -> 276582.06
B35: II. Лабораторные работы
A36: =A33+1 -> 13 | B36: Определение влажности грунта методом высушивания до постоянной массы | C36: Нормативные затраты на работы по инженерно-геологическим изысканиям Табл.56, п.1-3; Табл.57, п.1 | D36: ="((459+335+141)*"&F36&"обр+229*"&F36&"опр)*1,27" -> ((459+335+141)*12обр+229*12опр)*1,27 | E36: =((459+335+141)*F36+229*F36)*1.27 -> 17739.36 | F36: 12
A37: =A36+1 -> 14 | B37: Определение плотности частиц грунта пикнометрическим методом | C37: Нормативные затраты на работы по инженерно-геологическим изысканиям Табл.56, п.1-3; Табл.57, п.4 | D37: ="((459+335+141)*"&F37&"обр+600*"&F37&"опр)*1,27" -> ((459+335+141)*6обр+600*6опр)*1,27 | E37: =((459+335+141)*F37+600*F37)*1.27 -> 11696.7 | F37: 6
A38: =A37+1 -> 15 | B38: Определение содержания органических веществ в грунте методом прокаливания до постоянной массы | C38: Нормативные затраты на работы по инженерно-геологическим изысканиям Табл.56, п.1-3; Табл.57, п.8 | D38: ="((459+335+141)*"&F38&"обр+370*"&F38&"опр)*1,27" -> ((459+335+141)*3обр+370*3опр)*1,27 | E38: =((459+335+141)*F38+370*F38)*1.27 -> 4972.05 | F38: 3
A39: =A38+1 -> 16 | B39: Определение гранулометрического (зернового) состава грунта ситовым методом с промывкой водой с разделением грунта по фракциям размерами: свыше 0,5 миллиметра, от 0,25 до 0,5 миллиметра, от 0,1 до 0,25 миллиметра и до 0,1 миллиметра | C39: Нормативные затраты на работы по инженерно-геологическим изысканиям Табл.56, п.1-3; Табл.57, п.10 | D39: ="((459+335+141)*"&F39&"обр+917*"&F39&"опр)*1,27" -> ((459+335+141)*3обр+917*3опр)*1,27 | E39: =((459+335+141)*F39+917*F39)*1.27 -> 7056.12 | F39: 3
A40: =A39+1 -> 17 | B40: Определение гранулометрического (микроагрегатного) состава грунта ареометрическим методом с разделением грунта на фракции размерами: от 0,05 до 0,1 миллиметра, от 0,01 до 0,05 миллиметра, от 0,005 до 0,01 миллиметра, от 0,001 до 0,002 миллиметра и до 0,001 миллиметра | C40: Нормативные затраты на работы по инженерно-геологическим изысканиям Табл.56, п.1-3; Табл.57, п.14 | D40: ="((459+335+141)*"&F40&"обр+1852*"&F40&"опр)*1,27" -> ((459+335+141)*2обр+1852*2опр)*1,27 | E40: =((459+335+141)*F40+1852*F40)*1.27 -> 7078.98 | F40: 2
A41: =A40+1 -> 18 | B41: Определение относительной деформации морозного пучения | C41: Нормативные затраты на работы по инженерно-геологическим изысканиям Табл.56, п.1-3; Табл.57, п.16 | D41: ="((459+335+141)*"&F41&"обр+4546*"&F41&"опр)*1,27" -> ((459+335+141)*1обр+4546*1опр)*1,27 | E41: =((459+335+141)*F41+4546*F41)*1.27 -> 6960.87 | F41: 1
A42: =A41+1 -> 19 | B42: Определение плотности глинистого грунта методом режущего кольца | C42: Нормативные затраты на работы по инженерно-геологическим изысканиям Табл.56, п.1-3; Табл.57, п.17 | D42: ="((459+335+141)*"&F42&"обр+529*"&F42&"опр)*1,27" -> ((459+335+141)*3обр+529*3опр)*1,27 | E42: =((459+335+141)*F42+529*F42)*1.27 -> 5577.84 | F42: 3
A43: =A42+1 -> 20 | B43: Определение верхнего предела пластичности глинистого грунта - влажности грунта на границе текучести и нижнего предела пластичности глинистого грунта - влажности грунта на границе раскатывания при проведении испытания с использованием образца грунта природной влажности | C43: Нормативные затраты на работы по инженерно-геологическим изысканиям Табл.56, п.1-3; Табл.57, п.18 | D43: ="((459+335+141)*"&F43&"обр+1676*"&F43&"опр)*1,27" -> ((459+335+141)*6обр+1676*6опр)*1,27 | E43: =((459+335+141)*F43+1676*F43)*1.27 -> 19895.82 | F43: 6
A44: =A43+1 -> 21 | B44: Определение характеристик набухания глинистого грунта методом свободного набухания | C44: Нормативные затраты на работы по инженерно-геологическим изысканиям Табл.56, п.1-3; Табл.57, п.20 | D44: ="((459+335+141)*"&F44&"обр+723*"&F44&"опр)*1,27" -> ((459+335+141)*2обр+723*2опр)*1,27 | E44: =((459+335+141)*F44+723*F44)*1.27 -> 4211.32 | F44: 2
A45: =A44+1 -> 22 | B45: Определение характеристик свободной усадки глинистого грунта | C45: Нормативные затраты на работы по инженерно-геологическим изысканиям Табл.56, п.1-3; Табл.57, п.21 | D45: ="((459+335+141)*"&F45&"обр+388*"&F45&"опр)*1,27" -> ((459+335+141)*0обр+388*0опр)*1,27 | E45: =((459+335+141)*F45+388*F45)*1.27 -> 0 | F45: 0
A46: =A45+1 -> 23 | B46: Определение максимальной плотности сухого глинистого грунта и соответствующей ей влажности с увеличением влажности грунта на 1 (один) - 2 (два) процента не менее шести раз | C46: Нормативные затраты на работы по инженерно-геологическим изысканиям Табл.56, п.1-3; Табл.57, п.24 | D46: ="((459+335+141)*"&F46&"обр+13759*"&F46&"опр)*1,27" -> ((459+335+141)*0обр+13759*0опр)*1,27 | E46: =((459+335+141)*F46+13759*F46)*1.27 -> 0 | F46: 0
A47: =A46+1 -> 24 | B47: Определение коэффициента фильтрации песчаных грунтов при постоянном градиенте напора (стационарный режим фильтрации) с содержанием частиц диаметром менее 0,1 миллиметра до 5 (пяти) процентов включительно | C47: Нормативные затраты на работы по инженерно-геологическим изысканиям Табл.56, п.1-3; Табл.57, п.28 | D47: ="((459+335+141)*"&F47&"обр+2203*"&F47&"опр)*1,27" -> ((459+335+141)*0обр+2203*0опр)*1,27 | E47: =((459+335+141)*F47+2203*F47)*1.27 -> 0 | F47: 0
A48: =A47+1 -> 25 | B48: Определение характеристик деформируемости песчаного грунта методом компрессионного сжатия при нагружении одного образца грунта не менее чем пятью ступенями статической нагрузки | C48: Нормативные затраты на работы по инженерно-геологическим изысканиям Табл.56, п.1-3; Табл.58, п.1 | D48: ="((459+335+141)*"&F48&"обр+5452*"&F48&"опр)*1,27" -> ((459+335+141)*3обр+5452*3опр)*1,27 | E48: =((459+335+141)*F48+5452*F48)*1.27 -> 24334.47 | F48: 3
A49: =A48+1 -> 26 | B49: Определение характеристик деформируемости глинистого грунта с показателем текучести менее 0,25 для образцов ненарушенного сложения методом компрессионного сжатия с предварительным водонасыщением образца грунта (при необходимости) и при нагружении одного образца грунта не менее чем пятью ступенями статической нагрузки | C49: Нормативные затраты на работы по инженерно-геологическим изысканиям Табл.56, п.1-3; Табл.58, п.2 | D49: ="((459+335+141)*"&F49&"обр+7357*"&F49&"опр)*1,27" -> ((459+335+141)*3обр+7357*3опр)*1,27 | E49: =((459+335+141)*F49+7357*F49)*1.27 -> 31592.52 | F49: 3
A50: =A49+1 -> 27 | B50: Определение характеристик просадочности грунта при замачивании водой в компрессионных приборах по схеме "двух кривых" для определения относительной просадочности грунта при различных давлениях начального просадочного давления | C50: Нормативные затраты на работы по инженерно-геологическим изысканиям Табл.56, п.1-3; Табл.58, п.8 | D50: ="((459+335+141)*"&F50&"обр+7266*"&F50&"опр)*1,27" -> ((459+335+141)*0обр+7266*0опр)*1,27 | E50: =((459+335+141)*F50+7266*F50)*1.27 -> 0 | F50: 0
A51: =A50+1 -> 28 | B51: Определение характеристик набухания и усадки грунта под нагрузкой | C51: Нормативные затраты на работы по инженерно-геологическим изысканиям Табл.56, п.1-3; Табл.58, п.12 | D51: ="((459+335+141)*"&F51&"обр+29931*"&F51&"опр)*1,27" -> ((459+335+141)*0обр+29931*0опр)*1,27 | E51: =((459+335+141)*F51+29931*F51)*1.27 -> 0 | F51: 0
A52: =A51+1 -> 29 | B52: Определение характеристик прочности песчаного грунта консолидированно-дренированными испытаниями методом одноплоскостного среза при проведении не менее трех испытаний идентичных образцов при различных значениях нормального напряжения | C52: Нормативные затраты на работы по инженерно-геологическим изысканиям Табл.56, п.1-3; Табл.59, п.1 | D52: ="((459+335+141)*"&F52&"обр+8520*"&F52&"опр)*1,27" -> ((459+335+141)*3обр+8520*3опр)*1,27 | E52: =((459+335+141)*F52+8520*F52)*1.27 -> 36023.55 | F52: 3
A53: =A52+1 -> 30 | B53: Определение характеристик прочности глины с числом пластичности от 17 (семнадцати) до 30 (тридцати) процентов включительно консолидированно-дренированными испытаниями методом одноплоскостного среза при проведении не менее трех испытаний идентичных образцов при различных значениях нормального напряжения | C53: Нормативные затраты на работы по инженерно-геологическим изысканиям Табл.56, п.1-3; Табл.59, п.5 | D53: ="((459+335+141)*"&F53&"обр+9293*"&F53&"опр)*1,27" -> ((459+335+141)*3обр+9293*3опр)*1,27 | E53: =((459+335+141)*F53+9293*F53)*1.27 -> 38968.68 | F53: 3
A54: =A53+1 -> 31 | B54: Определение характеристик деформируемости методом трехосного сжатия песчаного грунта Консолидированно-дренированным испытанием (КД) | C54: Нормативные затраты на работы по инженерно-геологическим изысканиям Табл.56, п.1-3; Табл.60, п.22 | D54: ="((459+335+141)*"&F54&"обр+4593*"&F54&"опр)*1,27" -> ((459+335+141)*1обр+4593*1опр)*1,27 | E54: =((459+335+141)*F54+4593*F54)*1.27 -> 7020.56 | F54: 1
A55: =A54+1 -> 32 | B55: Определение характеристик деформируемости методом трехосного сжатия глины с показателем текучести до 0,25 Консолидированно-дренированным испытанием (КД) | C55: Нормативные затраты на работы по инженерно-геологическим изысканиям Табл.56, п.1-3; Табл.60, п.28 | D55: ="((459+335+141)*"&F55&"обр+6470*"&F55&"опр)*1,27" -> ((459+335+141)*1обр+6470*1опр)*1,27 | E55: =((459+335+141)*F55+6470*F55)*1.27 -> 9404.35 | F55: 1
A56: =A55+1 -> 33 | B56: Определение физических свойств, химического состава и агрессивности подземных вод состава | C56: Нормативные затраты на работы по инженерно-геологическим изысканиям Табл.63, п.1 | D56: ="11731*"&F56&"опр*1,27" -> 11731*1опр*1,27 | E56: =11731*F56*1.27 -> 14898.37 | F56: 1
A57: =A56+1 -> 34 | B57: Определение физических свойств, химического состава и агрессивности водной вытяжки из грунтов | C57: Нормативные затраты на работы по инженерно-геологическим изысканиям Табл.63, п.3 | D57: ="9786*"&F57&"опр*1,27" -> 9786*1опр*1,27 | E57: =9786*F57*1.27 -> 12428.22 | F57: 1
A58: =A57+1 -> 35 | B58: Определение удельного электрического сопротивления и средней плотности катодного тока грунта | C58: Нормативные затраты на работы по инженерно-геологическим изысканиям Табл.63, п.5 | D58: ="2726*"&F58&"опр*1,27" -> 2726*1опр*1,27 | E58: =2726*F58*1.27 -> 3462.02 | F58: 1
A59: =A58+1 -> 36 | B59: Дополнительные затраты на районные выплаты | C59: Нормативные затраты на работы по инженерно-геологическим изысканиям п.47; Табл.10, п.1 | D59: =ROUND(SUM(E36:F58),0)&"*("&0.65&"*"&F59&"+"&0.35&"-"&1&")" -> 263377*(0,65*1,15+0,35-1) | E59: =SUM(E36:E58)*(0.65*F59+0.35-1) -> 25673.875 | F59: 1.15
B60: Итого по разделу II | E60: =SUM(E36:E59) -> 288995.68
B61: III. Камеральные работы
A62: =A59+1 -> 37 | B62: Камеральная обработка результатов полевых работ по проходке следующих инженерно-геологических выработок: | C62: Нормативные затраты на работы по инженерно-геологическим изысканиям
B63: инженерно-геологических скважин в условиях категории сложности инженерно-геологических условий:
B64: II (архив) | C64: Табл.33, п.2 | D64: ="342*"&F64&"п.м.*1,27" -> 342*0п.м.*1,27 | E64: =342*F64*1.27 -> 0 | F64: 0
B65: II | C65: Табл.33, п.2 | D65: ="342*"&SUM(F16:F19)&"п.м.*1,27" -> 342*22п.м.*1,27 | E65: =342*SUM(F16:F19)*1.27 -> 9555.48
A66: =A62+1 -> 38 | B66: Камеральная обработка результатов полевых работ по проходке шурфов глубиной, метров: | C66: Нормативные затраты на работы по инженерно-геологическим изысканиям
B67: до 5 включительно | C67: Табл.33, п.5 | D67: ="2504*"&F67&"шурфов*1,27" -> 2504*0шурфов*1,27 | E67: =2504*F67*1.2 -> 0 | F67: 0
A68: =A62+1 -> 38 | B68: Камеральная обработка результатов полевых испытаний грунтов методом статического зондирования непрерывным вдавливанием зонда | C68: Нормативные затраты на работы по инженерно-геологическим изысканиям Табл.45, п.1 | D68: ="173*"&SUM(F28)&"п.м.*1,27" -> 173*0п.м.*1,27 | E68: =173*SUM(F28)*1.27 -> 0
A69: =A68+1 -> 39 | B69: Камеральная обработка результатов лабораторных определений физических свойств грунтов: | C69: Нормативные затраты на работы по инженерно-геологическим изысканиям
B70: песчаных | C70: Табл.62, п.1 | D70: ="320*"&F39&"обр*1,27" -> 320*3обр*1,27 | E70: =320*F39*1.27 -> 1219.2
B71: глинистых | C71: Табл.62, п.2 | D71: ="381*"&F43&"обр*1,27" -> 381*6обр*1,27 | E71: =381*F43*1.27 -> 2903.22
B72: органических | C72: Табл.62, п.4 | D72: ="358*"&F38&"обр*1,27" -> 358*3обр*1,27 | E72: =358*F38*1.27 -> 1363.98
A73: =A69+1 -> 40 | B73: Камеральная обработка результатов лабораторных исследований механических свойств грунтов (методом компрессионного сжатия, методом одноплоскостного среза, методом трехосного сжатия): | C73: Нормативные затраты на работы по инженерно-геологическим изысканиям
B74: песчаных | C74: Табл.62, п.5 | D74: ="693*"&SUM(F48,F52,F54)&"обр*1,27" -> 693*7обр*1,27 | E74: =693*(SUM(F48,F52,F54))*1.27 -> 6160.77
B75: глинистых | C75: Табл.62, п.6 | D75: ="730*"&SUM(F41,F49,F50,F51,F53,F55)&"обр*1,27" -> 730*8обр*1,27 | E75: =730*SUM(F41,F49,F50,F51,F53,F55)*1.27 -> 7416.8
A76: =A73+1 -> 41 | B76: Камеральная обработка результатов лабораторных исследований физических свойств, химического состава и агрессивности подземных вод | C76: Нормативные затраты на работы по инженерно-геологическим изысканиям Табл.64, п.1 | D76: ="385*"&F57&"обр*1,27" -> 385*1обр*1,27 | E76: =385*F56*1.27 -> 488.95
A77: =A76+1 -> 42 | B77: Камеральная обработка результатов лабораторных исследований физических свойств, химического состава и агрессивности водной вытяжки из грунтов и удельного электрического сопротивления и средней плотности катодного тока грунта | C77: Нормативные затраты на работы по инженерно-геологическим изысканиям Табл.64, п.2 | D77: ="352*"&SUM(F57:F58)&"обр*1,27" -> 352*2обр*1,27 | E77: =352*SUM(F57:F58)*1.27 -> 894.08
A78: =A77+1 -> 43 | B78: Составление технического отчета по результатам выполнения работ по ИГИ при общей стоимости камеральных работ в уровне цен по состоянию на 1 января 2024 г. (без учета дополнительных затрат), определенной по показателям затрат, приведенным в НЗ, в условиях инженерно-геологических условий категории сложности, тысяч рублей: | C78: Нормативные затраты на работы по инженерно-геологическим изысканиям
B79: II
B80: 250-500 | C80: Табл.65, п.12-13, прим.3 | D80: =(789323&"-(789323-577018)/(1млн.руб-500тыс.руб)*("&"1млн.руб-"&ROUND(SUM(E62:E75),0)&"))*1.1*1,27") -> 789323-(789323-577018)/(1млн.руб-500тыс.руб)*(1млн.руб-28619))*1.1*1,27 | E80: =(789323-(789323-577018)/(1000000-500000)*(1000000-SUM(E62:E75)))*1.1*1.27 -> 526480.55
A81: =A78+1 -> 44 | B81: Составление программы инженерно-геологических изысканий для II категории сложности инженерно-геологических условий: | C81: Нормативные затраты на работы по инженерно-геологическим изысканиям
B82: при площади земельного участка (участка для строительства) от 10 (десяти) до 100 (ста) гектаров и максимальной глубине исследования, метров:
B83: от 10 до 15 включительно | C83: Табл.66, п.17 | D83: ="200982*1,27" -> 200982*1,27 | E83: =200982*1.27 -> 255247.14
A84: =A81+1 -> 45 | B84: Дополнительные затраты на районные выплаты | C84: Нормативные затраты на работы по инженерно-геологическим изысканиям п.45; Табл.10, п.2 | D84: =ROUND(SUM(E62:E83),0)&"*("&0.73&"*"&F84&"+"&0.27&"-"&1&")" -> 811730*(0,73*1,15+0,27-1) | E84: =SUM(E62:E83)*(0.73*F84+0.27-1) -> 88884.454 | F84: 1.15
B85: Итого по разделу III | E85: =SUM(E62:E84) -> 900614.62
B86: Всего по смете в уровне цен, сложившемся на день составления сметной документации: | E86: =SUM(E34,E60,E85) -> 1466192.4

Sheet 1.3 МЛС
G2: Форма 2п
B3: =СВОД!E24 -> Смета №1.3
B4: Реконструкция ГПС - Объёмы к изм ТЗ (МЛС)
B5: =СВОД!B24 -> Мобильное лазерное сканирование (МЛС)
A7: № пп | B7: Наименование работ и затрат | C7: Единица измерения | D7: Кол-во | E7: Обоснование стоимости | F7: Расчет стоимости, руб. | G7: Стоимость, руб.
A8: 1 | B8: 2 | C8: 3 | D8: 4 | E8: 5 | F8: 6 | G8: 7
A9: Раздел 1. Полевые работы
A10: III. Работы по созданию опорной геодезической сети
A11: 1 | B11: Создание пунктов плановой опорной геодезической сети без закладки центров методом спутниковых геодезических определений, 2-го разряда в условиях выполнения полевых работ: II категории | C11: 1 пункт | D11: 6 | E11: НЗ_ИГДИ-7-8 | F11: (35837*6)*1,27 (A**)*Кинф | G11: 268777.5
E12: Кинф = 1,2700 (1) Письмо Минстроя России N 45358-ИФ/09 от 22.07.2026г (2026г. III квартал)
A13: 2 | B13: Создание пунктов плановой опорной геодезической сети без закладки центров методом спутниковых геодезических определений, 2-го разряда в условиях выполнения полевых работ: II категории | C13: 1 пункт | D13: 6 | E13: НЗ_ИГДИ-7-8 | F13: (35837*6)*0.5*1,27 (A**)*К1*Кинф | G13: 134388.75
E14: К1 = 0.5 (ТЧ_п.44_т.7_прим._п.1) При выполнении полевых работ по созданию пунктов плановой опорной геодезической сети без закладки центров методом спутниковых геодезических определений, совмещённых с пунктами высотной опорной сети IV класса, созданных без закладки центров методом спутниковых геодезических определений, (К3)
E15: Кинф = 1,2700 (1) Письмо Минстроя России N 45358-ИФ/09 от 22.07.2026г (2026г. III квартал)
A16: IV. Работы по топографической съёмке в масштабах 1:500 - 1:2000
A17: Топографическая съёмка методом МЛС ПППГ - КС-3 СЭБ (поз. 225) КС-3 СЭБ (поз. 225) - РЛВЖ КПП КС-3 СЭБ (поз. 225) - КС-5 ПЭБ
A18: 3 | B18: Создание пунктов съемочной геодезической сети для топографической съемки методами ВЛС ЦАФС, ЦАФС, МЛС и НЛС в условиях выполнения полевых работ: II категории | C18: 1 пункт | D18: 90 | E18: НЗ_ИГДИ-19-2 | F18: (16439*90)*1,27 (A**)*Кинф | G18: 1849387.5
E19: Кинф = 1,2700 (1) Письмо Минстроя России N 45358-ИФ/09 от 22.07.2026г (2026г. III квартал)
A20: В границах нас пункта
A21: 4 | B21: Топографическая съемка полосы местности вдоль оси (участка оси) линейного объекта шириной до 100 (ста) метров методом МЛС в масштабах 1:500 - 1:2000 расположенного в границах населенных пунктов в условиях выполнения полевых работ при протяженности участка:до 20 км включительно | C21: 1 км | D21: 9 | E21: НЗ_ИГДИ-41-1 | F21: (92160+21504*9)*1,27 (A+B**)*Кинф | G21: 357120
E22: Кинф = 1,2700 (1) Письмо Минстроя России N 45358-ИФ/09 от 22.07.2026г (2026г. III квартал)
A23: За границами населенного пункта
A24: V. Работы по съёмке подземных инженерных коммуникаций и сооружений
A25: VII. Работы по привязке инженерно-геологических выработок, геофизических и гидрогеологических точек наблюдения
A26: Работы по перенесению в натуру проектного положения инженерно-геологических, геофизических, гидрогеологических точек наблюдения.
A27: Работы по привязке фактического положения инженерно-геологических, геофизических, гидрогеологических точек наблюдения после завершения работ.
B28: Итоги по разделу 1 Полевые работы:
B29: Итого Поз. 1-4 | G29: 2 609 673.75
B30: Итого по разделу 1 Полевые работы | G30: 2 609 673.75
A31: Раздел 2. Дополнительные затраты на производство полевых работ
A32: 5 | B32: Дополнительные затраты на неизбежные перерывы - 25% | C32: руб. | D32: 2609674 | E32: НЗ_ИГДИ п.25 | F32: (0.25*2609674.02)*1,27 (B**)*Кинф | G32: 815523.13
E33: Кинф = 1,2700 (1) Письмо Минстроя России N 45358-ИФ/09 от 22.07.2026г (2026г. III квартал)
A34: 6 | B34: Показатели дополнительных затрат на внешний транспорт (ПДЗвнеш) автомобильного транспорта, расстояние от места постоянной работы работников до участка проведения полевых работ от 1000 до 2000 км включительно при стоимости полевых работ свыше/до 3000 тыс. руб. - 8,2 % | C34: руб. | D34: 2609674 | E34: НЗ_ИГДИ-3-4-4 | F34: (0.082*2609674.02)*1,27 (B**)*Кинф | G34: 267491.59
E35: Кинф = 1,2700 (1) Письмо Минстроя России N 45358-ИФ/09 от 22.07.2026г (2026г. III квартал)
A36: 7 | B36: Показатели дополнительных затрат на организацию полевых работ (ПДЗорг), расстояние от места постоянной работы работников до участка проведения полевых работ от 1000 до 2000 км включительно: при стоимости полевых работ свыше/до 3000 тыс. руб. - 7,7 % | C36: руб. | D36: 2609674 | E36: НЗ_ИГДИ-4-4-4 | F36: (0.077*2609674.02)*1,27 (B**)*Кинф | G36: 251181.12
E37: Кинф = 1,2700 (1) Письмо Минстроя России N 45358-ИФ/09 от 22.07.2026г (2026г. III квартал)
B38: Итоги по разделу 2 Дополнительные затраты на производство полевых работ:
B39: Итого Поз. 5-7 | G39: 1 334 195.84
B40: Итого по разделу 2 Дополнительные затраты на производство полевых работ | G40: 1 334 195.84
A41: Раздел 3. Камеральные работы
A42: III. Работы по созданию опорной геодезической сети
A43: 8 | B43: Камеральная обработка результатов измерений, выполненных при создании пунктов плановой опорной геодезической сети 4-го класса, 1-го и 2-го разрядов | C43: 1 пункт | D43: 6 | E43: НЗ_ИГДИ-16-1 | F43: (1714*6)*1,27 (A**)*Кинф | G43: 12855
E44: Кинф = 1,2700 (1) Письмо Минстроя России N 45358-ИФ/09 от 22.07.2026г (2026г. III квартал)
A45: 9 | B45: Камеральная обработка результатов измерений, выполненных при создании нивелирных пунктов высотной опорной геодезической сети III и IV классов | C45: 1 пункт | D45: 6 | E45: НЗ_ИГДИ-16-3 | F45: (1844*6)*1,27 (A**)*Кинф | G45: 13830
E46: Кинф = 1,2700 (1) Письмо Минстроя России N 45358-ИФ/09 от 22.07.2026г (2026г. III квартал)
A47: IV. Работы по топографической съёмке в масштабах 1:500 - 1:2000
A48: Камеральная обраьотка измерений МЛС
A49: 10 | B49: Камеральная обработка результатов измерений, выполненных при создании пунктов съемочной геодезической сети и пунктов геодезической основы, выполненной в виде опознаков и (или) контрольных точек, для топографической съемки методами ВЛС ЦАФС, ЦАФС, МЛС и HЛC | C49: 1 пункт | D49: 90 | E49: НЗ_ИГДИ-27-1 | F49: (392*90)*1,27 (A**)*Кинф | G49: 44100
E50: Кинф = 1,2700 (1) Письмо Минстроя России N 45358-ИФ/09 от 22.07.2026г (2026г. III квартал)
A51: 11 | B51: Камеральная обработка результатов МЛС в масштабах 1:500 - 1:2000:до 20 км включительно | C51: 1 км | D51: 9 | E51: НЗ_ИГДИ-42-1 | F51: (12935+1979*9)*1,27 (A+B**)*Кинф | G51: 38432.5
E52: Кинф = 1,2700 (1) Письмо Минстроя России N 45358-ИФ/09 от 22.07.2026г (2026г. III квартал)
A53: VI. Работы по созданию и обновлению инженерно-топографических планов в масштабах 1:500 - 1:5000
A54: Незастроенная территория
A55: Застроенная территория
A56: Подземные коммуникации
A57: VIII. Работы по трассированию сетей
A58: I*. Специальные геодезические работы при строительстве и реконструкции зданий и сооружений
A59: *I. Прочие работы по ИГДИ
A60: 12 | B60: Камеральные работы по согласованию нанесения на инженерно-топографический план подземных инженерных коммуникаций и их технических характеристик с собственниками (эксплуатирующими организациями): известными | C60: 1 собственник (эксплуатирующая организация) | D60: 5 | E60: НЗ_ИГДИ-82-1 | F60: (21451*5)*1,27 (A**)*Кинф | G60: 134068.75
E61: Кинф = 1,2700 (1) Письмо Минстроя России N 45358-ИФ/09 от 22.07.2026г (2026г. III квартал)
B62: Итоги по разделу 3 Камеральные работы:
B63: Итого Поз. 8-12 | G63: 243 286.25
B64: Итого по разделу 3 Камеральные работы | G64: 243 286.25
A65: Раздел 4. Дополнительные затраты на производство камеральных работ
A66: 13 | B66: Дополнительные затраты на районные выплаты - 1.15 | C66: руб. | D66: 243286.3 | E66: НЗ_ИГДИ п.40 | F66: (0.1095*243286.3)*1,27 (A**)*Кинф | G66: 33299.81
E67: Кинф = 1,2700 (1) Письмо Минстроя России N 45358-ИФ/09 от 22.07.2026г (2026г. III квартал)
B68: Итоги по разделу 4 Дополнительные затраты на производство камеральных работ:
B69: Итого Поз. 13 | G69: 33 299.81
B70: Итого по разделу 4 Дополнительные затраты на производство камеральных работ | G70: 33 299.81
A71: Раздел 5. Составление программы инженерно-геодезических изысканий и технического отчёта по результам ИГДИ
A72: 14 | B72: Камеральные работы по составлению программы инженерно-геодезических изысканий при общей стоимости полевых и камеральных работ, определенной по показателям затрат, приведенным в НЗ:5000 тысяч рублей | C72: 1 программа | D72: 2852960.3 | E72: НЗ_ИГДИ-80-5 | F72: (36839+(127949-36839)/(5000000-1000000)*(2852960.32-1000000))*1,27 (A1+(A2-A1)/(*2-*1)*(*-*1))*Кинф | G72: 98806
E73: Кинф = 1,2700 (1) Письмо Минстроя России N 45358-ИФ/09 от 22.07.2026г (2026г. III квартал)
A74: 15 | B74: Камеральные работы по составлению технического отчета по результатам выполнения работ по ИГДИ при общей стоимости полевых и камеральных работ, определенной по показателям затрат, приведенным в НЗ:5000 тысяч рублей | C74: 1 отчет | D74: 2852960.3 | E74: НЗ_ИГДИ-81-5 | F74: (76000+(204000-76000)/(5000000-1000000)*(2852960.32-1000000))*1,27 (A1+(A2-A1)/(*2-*1)*(*-*1))*Кинф | G74: 169118.41
E75: Кинф = 1,2700 (1) Письмо Минстроя России N 45358-ИФ/09 от 22.07.2026г (2026г. III квартал)
A76: 16 | B76: Итоги по разделу 5 Составление программы инженерно-геодезических изысканий и технического отчёта по результам ИГДИ:
A77: 17 | B77: Итого Поз. 14-15 | G77: 267 924.41
A78: 18 | B78: Итого по разделу 5 Составление программы инженерно-геодезических изысканий и технического отчёта по результам ИГДИ | G78: 267 924.41
A79: 19 | B79: Итоги по смете:
A80: 20 | B80: Итого по разделу 1 Полевые работы
A81: 21 | B81: Итого Поз. 1-4 | G81: 2 609 673.75
A82: 22 | B82: Итого по разделу 1 Полевые работы | G82: 2 609 673.75
A83: 23 | B83: Итого по разделу 2 Дополнительные затраты на производство полевых работ
A84: 24 | B84: Итого Поз. 5-7 | G84: 1 334 195.84
A85: 25 | B85: Итого по разделу 2 Дополнительные затраты на производство полевых работ | G85: 1 334 195.84
A86: 26 | B86: Итого по разделу 3 Камеральные работы
A87: 27 | B87: Итого Поз. 8-12 | G87: 243 286.25
A88: 28 | B88: Итого по разделу 3 Камеральные работы | G88: 243 286.25
A89: 29 | B89: Итого по разделу 4 Дополнительные затраты на производство камеральных работ
A90: 30 | B90: Итого Поз. 13 | G90: 33 299.81
A91: 31 | B91: Итого по разделу 4 Дополнительные затраты на производство камеральных работ | G91: 33 299.81
A92: 32 | B92: Итого по разделу 5 Составление программы инженерно-геодезических изысканий и технического отчёта по результам ИГДИ
A93: 33 | B93: Итого Поз. 14-15 | G93: 267 924.41
A94: 34 | B94: Итого по разделу 5 Составление программы инженерно-геодезических изысканий и технического отчёта по результам ИГДИ | G94: 267 924.41
A95: 35 | B95: Итого | G95: 4560194.1
A96: 36 | B96: ВСЕГО по смете | G96: 4560194.1

Sheet Смета_№2.1_Обслед
A1: Адепт: Проект v 2026.4.2 © ООО"Адепт" | E1: форма 2П, 707/пр
A3: Смета №2.1
A4: на проектные (изыскательские) работы
A6: Наименование предприятия, здания, сооружения, стадии проектирования, этапа, вида проектных или изыскательских работ | F6: Степн.ПХГ - Обследование
A8: Наименование проектной (изыскательской) организации
A10: Наименование организации заказчика
A12: № пп | B12: Наименование объекта проектирования или вида проектных работ | G12: Наименование, номера глав, таблиц, параграфов и пунктов МНЗ на проектные работы | K12: Расчет стоимости | O12: Стоимость, руб.
A13: 1 | B13: 2 | G13: 3 | K13: 4 | O13: 5
A14: Выполнение обмерных работ и обследований
A15: 1. КС-3. Производственно-энергетический блок (поз. 103)
A16: 1 | B16: Выполнение обмерных работ для каркасных многоэтажных зданий. III категория сложности работ. III категория сложности здания. Высота здания до 7 м. | G16: Справочник базовых цен на обмерные работы и обследования зданий и сооружений. 2016 г. Глава 3. Базовые цены на выполнение обмерных работ и обследований. Таблица 2. Базовые цены на выполнение обмерных работ для многоэтажных зданий, п.5 A = 0.9296 тыс.руб; Xзад = 45.97 (100 м3); Количество = 1 (100 м3) | K16: A * Xзад * Количество * Ктек * K1 * K2 * K3 * K4 929.6 руб. * 45.97 * 1 * 7.22 * 1.2 * 1.15 * 1.15 * 1.3 | O16: =ROUND(929.6 * 45.97 * 1 * 7.22 * 1.2 * 1.15 * 1.15 * 1.3, 2) -> 636543.51
B17: Коэффициенты
B18: инд.3кв.2026г.к 01.01.2001 на пр.раб. | G18: Ктек = 7.22 Письмо Минстроя России от 23.07.2026 №45358-ИФ/09
B19: Здания, возведенные на просадочных, набухающих грунтах, над горными выработками, в подтапливаемых районах с карстовыми и оползневыми явлениями | G19: K1 = 1.2 Таблица 10, п.1 (Ценообразующий)
B20: Насыщенность оборудованием более 50% площади помещений, затрудняющая производство обмерных и обследовательских работ или выполнение обмеров и обследований в затрудненных условиях (захламленность, стесненность, частично разобраны полы и др.) | G20: K2 = 1.15 Таблица 10, п.2 (Ценообразующий)
B21: Выполнение работ в условиях, требующих обеспечение безопасности (использование дополнительных лестниц и различных приспособлений) | G21: K3 = 1.15 Таблица 10, п.6 (Ценообразующий)
B22: Корректирующий коэффициент, учитывающий строительный объем зданий и сооружений до 5000 м3 | G22: K4 = 1.3 Таблица 11, п.5 (Ценообразующий)
A23: 2 | B23: Выполнение инженерных обследований строительных конструкций каркасных многоэтажных зданий. III категория сложности работ. III категория сложности здания. Высота здания до 7 м. | G23: Справочник базовых цен на обмерные работы и обследования зданий и сооружений. 2016 г. Глава 3. Базовые цены на выполнение обмерных работ и обследований. Таблица 4. Цены на выполнение инженерных обследований строительных конструкций многоэтажных зданий, п.5 A = 0.9044 тыс.руб; Xзад = 45.97 (100 м3); Количество = 1 (100 м3) | K23: A * Xзад * Количество * Ктек * K1 * K2 * K3 * K4 904.4 руб. * 45.97 * 1 * 7.22 * 1.2 * 1.15 * 1.15 * 1.3 | O23: =ROUND(904.4 * 45.97 * 1 * 7.22 * 1.2 * 1.15 * 1.15 * 1.3, 2) -> 619287.81
B24: Коэффициенты
B25: инд.3кв.2026г.к 01.01.2001 на пр.раб. | G25: Ктек = 7.22 Письмо Минстроя России от 23.07.2026 №45358-ИФ/09
B26: Здания, возведенные на просадочных, набухающих грунтах, над горными выработками, в подтапливаемых районах с карстовыми и оползневыми явлениями | G26: K1 = 1.2 Таблица 10, п.1 (Ценообразующий)
B27: Насыщенность оборудованием более 50% площади помещений, затрудняющая производство обмерных и обследовательских работ или выполнение обмеров и обследований в затрудненных условиях (захламленность, стесненность, частично разобраны полы и др.) | G27: K2 = 1.15 Таблица 10, п.2 (Ценообразующий)
B28: Выполнение работ в условиях, требующих обеспечение безопасности (использование дополнительных лестниц и различных приспособлений) | G28: K3 = 1.15 Таблица 10, п.6 (Ценообразующий)
B29: Корректирующий коэффициент, учитывающий строительный объем зданий и сооружений до 5000 м3 | G29: K4 = 1.3 Таблица 11, п.5 (Ценообразующий)
A30: 2. КС-3. Здание закрытого распределительного устройства 6кВ (поз.104)
A31: 3 | B31: Выполнение обмерных работ для каркасных одноэтажных зданий. III категория сложности работ. III категория сложности здания. Высота здания до 4 м. | G31: Справочник базовых цен на обмерные работы и обследования зданий и сооружений. 2016 г. Глава 3. Базовые цены на выполнение обмерных работ и обследований. Таблица 1. Базовые цены на выполнение обмерных работ для одноэтажных зданий, п.2 A = 0.9468 тыс.руб; Xзад = 8.045 (100 м3); Количество = 1 (100 м3) | K31: A * Xзад * Количество * Ктек * K1 * K2 * K3 * K4 946.8 руб. * 8.045 * 1 * 7.22 * 1.2 * 1.15 * 1.15 * 2.2 | O31: =ROUND(946.8 * 8.045 * 1 * 7.22 * 1.2 * 1.15 * 1.15 * 2.2, 2) -> 192008.79
B32: Коэффициенты
B33: инд.3кв.2026г.к 01.01.2001 на пр.раб. | G33: Ктек = 7.22 Письмо Минстроя России от 23.07.2026 №45358-ИФ/09
B34: Здания, возведенные на просадочных, набухающих грунтах, над горными выработками, в подтапливаемых районах с карстовыми и оползневыми явлениями | G34: K1 = 1.2 Таблица 10, п.1 (Ценообразующий)
B35: Насыщенность оборудованием более 50% площади помещений, затрудняющая производство обмерных и обследовательских работ или выполнение обмеров и обследований в затрудненных условиях (захламленность, стесненность, частично разобраны полы и др.) | G35: K2 = 1.15 Таблица 10, п.2 (Ценообразующий)
B36: Выполнение работ в условиях, требующих обеспечение безопасности (использование дополнительных лестниц и различных приспособлений) | G36: K3 = 1.15 Таблица 10, п.6 (Ценообразующий)
B37: Корректирующий коэффициент, учитывающий строительный объем зданий и сооружений до 3000 м3 | G37: K4 = 2.2 Таблица 11, п.3 (Ценообразующий)
A38: 4 | B38: Выполнение инженерных обследований строительных конструкций каркасных одноэтажных зданий. III категория сложности работ. III категория сложности здания. Высота здания до 4 м. | G38: Справочник базовых цен на обмерные работы и обследования зданий и сооружений. 2016 г. Глава 3. Базовые цены на выполнение обмерных работ и обследований. Таблица 3. Базовые цены на выполнение инженерных обследований строительных конструкций одноэтажных зданий, п.2 A = 0.9102 тыс.руб; Xзад = 8.045 (100 м3); Количество = 1 (100 м3) | K38: A * Xзад * Количество * Ктек * K1 * K2 * K3 * K4 910.2 руб. * 8.045 * 1 * 7.22 * 1.2 * 1.15 * 1.15 * 2.2 | O38: =ROUND(910.2 * 8.045 * 1 * 7.22 * 1.2 * 1.15 * 1.15 * 2.2, 2) -> 184586.39
B39: Коэффициенты
B40: инд.3кв.2026г.к 01.01.2001 на пр.раб. | G40: Ктек = 7.22 Письмо Минстроя России от 23.07.2026 №45358-ИФ/09
B41: Здания, возведенные на просадочных, набухающих грунтах, над горными выработками, в подтапливаемых районах с карстовыми и оползневыми явлениями | G41: K1 = 1.2 Таблица 10, п.1 (Ценообразующий)
B42: Насыщенность оборудованием более 50% площади помещений, затрудняющая производство обмерных и обследовательских работ или выполнение обмеров и обследований в затрудненных условиях (захламленность, стесненность, частично разобраны полы и др.) | G42: K2 = 1.15 Таблица 10, п.2 (Ценообразующий)
B43: Выполнение работ в условиях, требующих обеспечение безопасности (использование дополнительных лестниц и различных приспособлений) | G43: K3 = 1.15 Таблица 10, п.6 (Ценообразующий)
B44: Корректирующий коэффициент, учитывающий строительный объем зданий и сооружений до 3000 м3 | G44: K4 = 2.2 Таблица 11, п.3 (Ценообразующий)
A45: 3. КС-3. Здание операторной (поз. 152)
A46: 5 | B46: Выполнение обмерных работ для каркасных многоэтажных зданий. III категория сложности работ. III категория сложности здания. Высота здания до 7 м. | G46: Справочник базовых цен на обмерные работы и обследования зданий и сооружений. 2016 г. Глава 3. Базовые цены на выполнение обмерных работ и обследований. Таблица 2. Базовые цены на выполнение обмерных работ для многоэтажных зданий, п.5 A = 0.9296 тыс.руб; Xзад = 37.25 (100 м3); Количество = 1 (100 м3) | K46: A * Xзад * Количество * Ктек * K1 * K2 * K3 * K4 929.6 руб. * 37.25 * 1 * 7.22 * 1.2 * 1.15 * 1.15 * 2.2 | O46: =ROUND(929.6 * 37.25 * 1 * 7.22 * 1.2 * 1.15 * 1.15 * 2.2, 2) -> 872889.36
B47: Коэффициенты
B48: инд.3кв.2026г.к 01.01.2001 на пр.раб. | G48: Ктек = 7.22 Письмо Минстроя России от 23.07.2026 №45358-ИФ/09
B49: Здания, возведенные на просадочных, набухающих грунтах, над горными выработками, в подтапливаемых районах с карстовыми и оползневыми явлениями | G49: K1 = 1.2 Таблица 10, п.1 (Ценообразующий)
B50: Насыщенность оборудованием более 50% площади помещений, затрудняющая производство обмерных и обследовательских работ или выполнение обмеров и обследований в затрудненных условиях (захламленность, стесненность, частично разобраны полы и др.) | G50: K2 = 1.15 Таблица 10, п.2 (Ценообразующий)
B51: Выполнение работ в условиях, требующих обеспечение безопасности (использование дополнительных лестниц и различных приспособлений) | G51: K3 = 1.15 Таблица 10, п.6 (Ценообразующий)
B52: Корректирующий коэффициент, учитывающий строительный объем зданий и сооружений до 3000 м3 | G52: K4 = 2.2 Таблица 11, п.3 (Ценообразующий)
A53: 6 | B53: Выполнение инженерных обследований строительных конструкций каркасных многоэтажных зданий. III категория сложности работ. III категория сложности здания. Высота здания до 7 м. | G53: Справочник базовых цен на обмерные работы и обследования зданий и сооружений. 2016 г. Глава 3. Базовые цены на выполнение обмерных работ и обследований. Таблица 4. Цены на выполнение инженерных обследований строительных конструкций многоэтажных зданий, п.5 A = 0.9044 тыс.руб; Xзад = 37.25 (100 м3); Количество = 1 (100 м3) | K53: A * Xзад * Количество * Ктек * K1 * K2 * K3 * K4 904.4 руб. * 37.25 * 1 * 7.22 * 1.2 * 1.15 * 1.15 * 2.2 | O53: =ROUND(904.4 * 37.25 * 1 * 7.22 * 1.2 * 1.15 * 1.15 * 2.2, 2) -> 849226.69
B54: Коэффициенты
B55: инд.3кв.2026г.к 01.01.2001 на пр.раб. | G55: Ктек = 7.22 Письмо Минстроя России от 23.07.2026 №45358-ИФ/09
B56: Здания, возведенные на просадочных, набухающих грунтах, над горными выработками, в подтапливаемых районах с карстовыми и оползневыми явлениями | G56: K1 = 1.2 Таблица 10, п.1 (Ценообразующий)
B57: Насыщенность оборудованием более 50% площади помещений, затрудняющая производство обмерных и обследовательских работ или выполнение обмеров и обследований в затрудненных условиях (захламленность, стесненность, частично разобраны полы и др.) | G57: K2 = 1.15 Таблица 10, п.2 (Ценообразующий)
B58: Выполнение работ в условиях, требующих обеспечение безопасности (использование дополнительных лестниц и различных приспособлений) | G58: K3 = 1.15 Таблица 10, п.6 (Ценообразующий)
B59: Корректирующий коэффициент, учитывающий строительный объем зданий и сооружений до 3000 м3 | G59: K4 = 2.2 Таблица 11, п.3 (Ценообразующий)
A60: 4. КС-3. Установка регенерации метанола (поз. 201)
A61: 7 | B61: Выполнение обмерных работ для каркасных одноэтажных зданий. III категория сложности работ. III категория сложности здания. Высота здания до 6 м. | G61: Справочник базовых цен на обмерные работы и обследования зданий и сооружений. 2016 г. Глава 3. Базовые цены на выполнение обмерных работ и обследований. Таблица 1. Базовые цены на выполнение обмерных работ для одноэтажных зданий, п.4 A = 0.8732 тыс.руб; Xзад = 24.21 (100 м3); Количество = 1 (100 м3) | K61: A * Xзад * Количество * Ктек * K1 * K2 * K3 * K4 873.2 руб. * 24.21 * 1 * 7.22 * 1.2 * 1.15 * 1.15 * 2.2 | O61: =ROUND(873.2 * 24.21 * 1 * 7.22 * 1.2 * 1.15 * 1.15 * 2.2, 2) -> 532899.51
B62: Коэффициенты
B63: инд.3кв.2026г.к 01.01.2001 на пр.раб. | G63: Ктек = 7.22 Письмо Минстроя России от 23.07.2026 №45358-ИФ/09
B64: Здания, возведенные на просадочных, набухающих грунтах, над горными выработками, в подтапливаемых районах с карстовыми и оползневыми явлениями | G64: K1 = 1.2 Таблица 10, п.1 (Ценообразующий)
B65: Насыщенность оборудованием более 50% площади помещений, затрудняющая производство обмерных и обследовательских работ или выполнение обмеров и обследований в затрудненных условиях (захламленность, стесненность, частично разобраны полы и др.) | G65: K2 = 1.15 Таблица 10, п.2 (Ценообразующий)
B66: Выполнение работ в условиях, требующих обеспечение безопасности (использование дополнительных лестниц и различных приспособлений) | G66: K3 = 1.15 Таблица 10, п.6 (Ценообразующий)
B67: Корректирующий коэффициент, учитывающий строительный объем зданий и сооружений до 3000 м3 | G67: K4 = 2.2 Таблица 11, п.3 (Ценообразующий)
A68: 8 | B68: Выполнение инженерных обследований строительных конструкций каркасных одноэтажных зданий. III категория сложности работ. III категория сложности здания. Высота здания до 6 м. | G68: Справочник базовых цен на обмерные работы и обследования зданий и сооружений. 2016 г. Глава 3. Базовые цены на выполнение обмерных работ и обследований. Таблица 3. Базовые цены на выполнение инженерных обследований строительных конструкций одноэтажных зданий, п.4 A = 0.8558 тыс.руб; Xзад = 24.21 (100 м3); Количество = 1 (100 м3) | K68: A * Xзад * Количество * Ктек * K1 * K2 * K3 * K4 855.8 руб. * 24.21 * 1 * 7.22 * 1.2 * 1.15 * 1.15 * 2.2 | O68: =ROUND(855.8 * 24.21 * 1 * 7.22 * 1.2 * 1.15 * 1.15 * 2.2, 2) -> 522280.58
B69: Коэффициенты
B70: инд.3кв.2026г.к 01.01.2001 на пр.раб. | G70: Ктек = 7.22 Письмо Минстроя России от 23.07.2026 №45358-ИФ/09
B71: Здания, возведенные на просадочных, набухающих грунтах, над горными выработками, в подтапливаемых районах с карстовыми и оползневыми явлениями | G71: K1 = 1.2 Таблица 10, п.1 (Ценообразующий)
B72: Насыщенность оборудованием более 50% площади помещений, затрудняющая производство обмерных и обследовательских работ или выполнение обмеров и обследований в затрудненных условиях (захламленность, стесненность, частично разобраны полы и др.) | G72: K2 = 1.15 Таблица 10, п.2 (Ценообразующий)
B73: Выполнение работ в условиях, требующих обеспечение безопасности (использование дополнительных лестниц и различных приспособлений) | G73: K3 = 1.15 Таблица 10, п.6 (Ценообразующий)
B74: Корректирующий коэффициент, учитывающий строительный объем зданий и сооружений до 3000 м3 | G74: K4 = 2.2 Таблица 11, п.3 (Ценообразующий)
A75: 5. КС-3. Установка осушки газа (поз. 202)
A76: 9 | B76: Выполнение инженерных обследований строительных конструкций каркасных одноэтажных зданий. III категория сложности работ. III категория сложности здания. Высота здания до 6 м. | G76: Справочник базовых цен на обмерные работы и обследования зданий и сооружений. 2016 г. Глава 3. Базовые цены на выполнение обмерных работ и обследований. Таблица 3. Базовые цены на выполнение инженерных обследований строительных конструкций одноэтажных зданий, п.4 A = 0.8558 тыс.руб; Xзад = 47.47 (100 м3); Количество = 1 (100 м3) | K76: A * Xзад * Количество * Ктек * K1 * K2 * K3 * K4 855.8 руб. * 47.47 * 1 * 7.22 * 1.2 * 1.15 * 1.15 * 2.2 | O76: =ROUND(855.8 * 47.47 * 1 * 7.22 * 1.2 * 1.15 * 1.15 * 2.2, 2) -> 1024066.9
B77: Коэффициенты
B78: инд.3кв.2026г.к 01.01.2001 на пр.раб. | G78: Ктек = 7.22 Письмо Минстроя России от 23.07.2026 №45358-ИФ/09
B79: Здания, возведенные на просадочных, набухающих грунтах, над горными выработками, в подтапливаемых районах с карстовыми и оползневыми явлениями | G79: K1 = 1.2 Таблица 10, п.1 (Ценообразующий)
B80: Насыщенность оборудованием более 50% площади помещений, затрудняющая производство обмерных и обследовательских работ или выполнение обмеров и обследований в затрудненных условиях (захламленность, стесненность, частично разобраны полы и др.) | G80: K2 = 1.15 Таблица 10, п.2 (Ценообразующий)
B81: Выполнение работ в условиях, требующих обеспечение безопасности (использование дополнительных лестниц и различных приспособлений) | G81: K3 = 1.15 Таблица 10, п.6 (Ценообразующий)
B82: Корректирующий коэффициент, учитывающий строительный объем зданий и сооружений до 3000 м3 | G82: K4 = 2.2 Таблица 11, п.3 (Ценообразующий)
A83: 10 | B83: Выполнение обмерных работ для каркасных одноэтажных зданий. III категория сложности работ. III категория сложности здания. Высота здания до 6 м. | G83: Справочник базовых цен на обмерные работы и обследования зданий и сооружений. 2016 г. Глава 3. Базовые цены на выполнение обмерных работ и обследований. Таблица 1. Базовые цены на выполнение обмерных работ для одноэтажных зданий, п.4 A = 0.8732 тыс.руб; Xзад = 47.47 (100 м3); Количество = 1 (100 м3) | K83: A * Xзад * Количество * Ктек * K1 * K2 * K3 * K4 873.2 руб. * 47.47 * 1 * 7.22 * 1.2 * 1.15 * 1.15 * 2.2 | O83: =ROUND(873.2 * 47.47 * 1 * 7.22 * 1.2 * 1.15 * 1.15 * 2.2, 2) -> 1044888.1
B84: Коэффициенты
B85: инд.3кв.2026г.к 01.01.2001 на пр.раб. | G85: Ктек = 7.22 Письмо Минстроя России от 23.07.2026 №45358-ИФ/09
B86: Здания, возведенные на просадочных, набухающих грунтах, над горными выработками, в подтапливаемых районах с карстовыми и оползневыми явлениями | G86: K1 = 1.2 Таблица 10, п.1 (Ценообразующий)
B87: Насыщенность оборудованием более 50% площади помещений, затрудняющая производство обмерных и обследовательских работ или выполнение обмеров и обследований в затрудненных условиях (захламленность, стесненность, частично разобраны полы и др.) | G87: K2 = 1.15 Таблица 10, п.2 (Ценообразующий)
B88: Выполнение работ в условиях, требующих обеспечение безопасности (использование дополнительных лестниц и различных приспособлений) | G88: K3 = 1.15 Таблица 10, п.6 (Ценообразующий)
B89: Корректирующий коэффициент, учитывающий строительный объем зданий и сооружений до 3000 м3 | G89: K4 = 2.2 Таблица 11, п.3 (Ценообразующий)
A90: 6. КС-3. Здание насосной метанола и ДЭГ (поз. 203)
A91: 11 | B91: Выполнение инженерных обследований строительных конструкций каркасных одноэтажных зданий. III категория сложности работ. III категория сложности здания. Высота здания до 7 м. | G91: Справочник базовых цен на обмерные работы и обследования зданий и сооружений. 2016 г. Глава 3. Базовые цены на выполнение обмерных работ и обследований. Таблица 3. Базовые цены на выполнение инженерных обследований строительных конструкций одноэтажных зданий, п.5 A = 0.829 тыс.руб; Xзад = 51.85 (100 м3); Количество = 1 (100 м3) | K91: A * Xзад * Количество * Ктек * K1 * K2 * K3 * K4 829 руб. * 51.85 * 1 * 7.22 * 1.2 * 1.15 * 1.15 * 2.2 | O91: =ROUND(829 * 51.85 * 1 * 7.22 * 1.2 * 1.15 * 1.15 * 2.2, 2) -> 1083527.9
B92: Коэффициенты
B93: инд.3кв.2026г.к 01.01.2001 на пр.раб. | G93: Ктек = 7.22 Письмо Минстроя России от 23.07.2026 №45358-ИФ/09
B94: Здания, возведенные на просадочных, набухающих грунтах, над горными выработками, в подтапливаемых районах с карстовыми и оползневыми явлениями | G94: K1 = 1.2 Таблица 10, п.1 (Ценообразующий)
B95: Насыщенность оборудованием более 50% площади помещений, затрудняющая производство обмерных и обследовательских работ или выполнение обмеров и обследований в затрудненных условиях (захламленность, стесненность, частично разобраны полы и др.) | G95: K2 = 1.15 Таблица 10, п.2 (Ценообразующий)
B96: Выполнение работ в условиях, требующих обеспечение безопасности (использование дополнительных лестниц и различных приспособлений) | G96: K3 = 1.15 Таблица 10, п.6 (Ценообразующий)
B97: Корректирующий коэффициент, учитывающий строительный объем зданий и сооружений до 3000 м3 | G97: K4 = 2.2 Таблица 11, п.3 (Ценообразующий)
A98: 12 | B98: Выполнение обмерных работ для каркасных одноэтажных зданий. III категория сложности работ. III категория сложности здания. Высота здания до 7 м. | G98: Справочник базовых цен на обмерные работы и обследования зданий и сооружений. 2016 г. Глава 3. Базовые цены на выполнение обмерных работ и обследований. Таблица 1. Базовые цены на выполнение обмерных работ для одноэтажных зданий, п.5 A = 0.8378 тыс.руб; Xзад = 51.85 (100 м3); Количество = 1 (100 м3) | K98: A * Xзад * Количество * Ктек * K1 * K2 * K3 * K4 837.8 руб. * 51.85 * 1 * 7.22 * 1.2 * 1.15 * 1.15 * 2.2 | O98: =ROUND(837.8 * 51.85 * 1 * 7.22 * 1.2 * 1.15 * 1.15 * 2.2, 2) -> 1095029.8
B99: Коэффициенты
B100: инд.3кв.2026г.к 01.01.2001 на пр.раб. | G100: Ктек = 7.22 Письмо Минстроя России от 23.07.2026 №45358-ИФ/09
B101: Здания, возведенные на просадочных, набухающих грунтах, над горными выработками, в подтапливаемых районах с карстовыми и оползневыми явлениями | G101: K1 = 1.2 Таблица 10, п.1 (Ценообразующий)
B102: Насыщенность оборудованием более 50% площади помещений, затрудняющая производство обмерных и обследовательских работ или выполнение обмеров и обследований в затрудненных условиях (захламленность, стесненность, частично разобраны полы и др.) | G102: K2 = 1.15 Таблица 10, п.2 (Ценообразующий)
B103: Выполнение работ в условиях, требующих обеспечение безопасности (использование дополнительных лестниц и различных приспособлений) | G103: K3 = 1.15 Таблица 10, п.6 (Ценообразующий)
B104: Корректирующий коэффициент, учитывающий строительный объем зданий и сооружений до 3000 м3 | G104: K4 = 2.2 Таблица 11, п.3 (Ценообразующий)
A105: 7. КС-3. Площадка емкостей и АВО (поз. 211)
...

Sheet Расчет КР
A3: Командировочные расходы
A5: 1) Расчет командировочных расходов
A6: Маршрут | B6: Кол-во поездок | C6: Кол-во человек | D6: Кол-во дней ком-ки, дн. | E6: Проживание, сутки | F6: Ст-ть проживания в сутки, руб./день | G6: Ст-ть проезда туда, руб. | H6: Ст-ть проезда обратно, руб. | I6: Суточные, руб./день. | J6: Итого
A7: 1 | B7: 2 | C7: 3 | D7: 4 | E7: 5 | F7: 6 | G7: 7 | H7: 8 | I7: 9 | J7: 10
A8: Омск - Саратовская обл. - Омск | B8: 1 | C8: 3 | D8: 10 | E8: 9 | F8: 6000 | G8: 10000 | H8: 10000 | I8: 500 | J8: =$B$8 * $C$8 * ($D$8 * $I$8 + $E$8 * $F$8 + $G$8 + $H$8) -> 237000
A10: Стоимость проезда | D10: =$B$8 * $C$8 -> 3 | E10: чел-поездок * | G10: =$G$8 + $H$8 -> 20000 | H10: руб. = | I10: =$D$10*$G$10 -> 60000 | J10: руб.
A11: Стоимость проживания | D11: =$B$8 * $C$8 * $E$8 -> 27 | E11: чел.-дн. * | G11: =$F$8 -> 6000 | H11: руб. = | I11: =$D$11*$G$11 -> 162000 | J11: руб.
A12: Суточные всего | D12: =$B$8 * $C$8 * $D$8 -> 30 | E12: чел.-дн. * | G12: =$I$8 -> 500 | H12: руб. = | I12: =$D$12*$G$12 -> 15000 | J12: руб.
A15: Всего: | C15: =$J$8 -> 237000 | J15: руб.

Sheet 2.2 ТехДок+ 
D1: форма №3П
A3: Смета №2.2
A4: на проектные (изыскательские) работы
A6: Наименование предприятия, здания, сооружения, стадии проектирования, этапа, вида проектных или изыскательских работ | E6: Внесение изменений в техническую документацию
A8: Наименование проектной (изыскательской) организации | E8: Определяется по итогам конкурентных процедур
A10: Наименование организации заказчика | E10: ООО "Газпром проектирование"
A12: № пп | B12: Перечень выполняемых работ | E12: Исполнители | G12: Количество человеко-дней | H12: Средняя оплата труда за 1 день | I12: Оплата труда (всего), руб.
E13: количество | F13: должность
A14: 1 | B14: 2 | E14: 3 | F14: 4 | G14: 5 | H14: 6 | I14: 7
A15: 1 | B15: Внесение изменений в техническую документацию: - КС-3. Здание ПЭБ (поз. 103)- - КС-3. ЗРУ (поз. 104) - КС-3. Установка регенерации метанола (поз. 201) - КС-3. Установка осушки газа (поз. 202) - КС-3. Здание насосной метанола и ДЭГ (поз. 203) - КС-3. Площадка емкостей и АВО (поз. 211) - КС-3. ПЭБ (поз. 215) - ВС-3. Здание установки мехочистки и осушки газа (поз. 180) - КС-3. Здание закрытого распределительного устройства 6кВ - Блок-бокс дизельной электростанции "БКАЭ-0,4-630-К" (поз. 250, поз. 250а) • Определение теплотехнических показателей наружных ограждающих конструкций с выполнением расчетов. • Оценка пожарной безопасности на соответствие требованиям действующих нормативных документов в области пожарной безопасности. • Рекомендации по восстановлению конструкций. • Разработка комплектов рабочей документации по восстановлению строительных конструкций. | E15: 1 | F15: Главный инженер проекта | G15: 2 | H15: 22082 | I15: =ROUND((E15 * G15 * H15+E16 * G16 * H16+E17 * G17 * H17+E18 *G18 * H18+E19 * G19 * H19+E20* G20 * H20),2) -> 2116515
E16: 2 | F16: Главный специалист | G16: 5 | H16: 17599
E17: 1 | F17: Начальник отдела | G17: 4 | H17: 22082
E18: 2 | F18: Руководитель группы в составе отдела | G18: 7 | H18: 15758
E19: 3 | F19: Ведущий инженер | G19: 29 | H19: 14027
E20: 2 | F20: Инженер 1 категории | G20: 16 | H20: 11471
A21: 2 | B21: Итого по смете: | I21: =ROUND($I$15,2) -> 2116515
A24: Итого оплата труда (руб.) 1 920 615.00
A27: 3 | B27: Итого оплата труда Сумма от п.2 | I27: =I21 -> 2116515
A28: 4 | B28: Коэффициент отношения заработной платы исполнителей к себестоимости работ Коэф-т-делитель 0.45 от п.3 1 920 615.00 руб. / 0.45 | I28: =ROUND((($I$27) / 0.45),2) -> 4703366.7
A29: 5 | B29: Прибыль 8% от п.4 4 268 033.33 руб. * 8/100 | I29: =ROUND(($I$28) * (8/100),2) -> 376269.33
A30: 6 | B30: Стоимость работы Сумма от п.4-5 | I30: =ROUND(($I$28+$I$29),2) -> 5079636
A31: 7 | B31: Итого за вычетом кураторских затрат Разделить на коэф-т 1,02 от п. 6 | I31: =ROUND(($I$30),2) -> 5079636
A32: 8 | B32: Всего по смете: | I32: =I31 -> 5079636 | K32: =I32 -> 5079636

Sheet 2.3 СИД 
C1: форма №3П
B4: =СВОД!E30 -> Смета №2.3
B5: на проектные (изыскательские) работы | C5: Приложение к ______________________________________ | D5: Приложение к ______________________________________
A7: Наименование предприятия, здания, сооружения, стадии проектирования, этапа, вида проектных или изыскательских работ | E7: =СВОД!B30 -> Сбор исходных данных
A9: Наименование проектной (изыскательской) организации | E9: =СВОД!D14 -> Определяется по итогам конкурентных процедур
A11: Наименование организации заказчика | E11: =СВОД!D16 -> ООО «Газпром проектирование»
B13: Раздел 1. Определение трудоемкости (трудозатрат) выполняемой работы
A15: № пп | B15: Перечень выполняемых работ | C15: Исполнители | E15: Количество человеко-дней | F15: Средняя оплата труда за 1 день | G15: Оплата труда (всего),руб.
C16: количество | D16: должность
A17: 1 | B17: 2 | C17: 3 | D17: 4 | E17: 5 | F17: 6 | G17: 7
A18: 1 | B18: Раздел 1 «Исходно-разрешительная документация» | C18: 1 | D18: ГИП | E18: 1 | F18: 20337 | G18: =E18*F18+E19*F19+E21*F21*2+E22*F22+E20*F20 -> 499694
C19: 1 | D19: Начальник отдела | E19: 3 | F19: 20337
C20: 1 | D20: Главный специалист | E20: 5 | F20: 16222
C21: 2 | D21: Ведущий инженер | E21: 8 | F21: 13116
C22: 1 | D22: Инженер 1 категории | E22: 12 | F22: 10615
A23: 2 | B23: Раздел 2 «Согласование места размещения объекта» | C23: 1 | D23: ГИП | E23: 2 | F23: 20337 | G23: =E23*F23+E24*F24+E26*F26+E27*F27+E25*F25*2 -> 726232
C24: 1 | D24: Начальник отдела | E24: 4 | F24: 20337
C25: 2 | D25: Главный специалист | E25: 10 | F25: 16222
C26: 1 | D26: Ведущий инженер | E26: 10 | F26: 13116
C27: 1 | D27: Инженер 1 категории | E27: 14 | F27: 10615
A28: 3 | B28: Раздел 3 «Градостроительная документация» | C28: 1 | D28: ГИП | E28: 2 | F28: 20337 | G28: =E28*F28+E29*F29+E31*F31+E32*F32+E30*F30*2 -> 714125
C29: 1 | D29: Начальник отдела | E29: 5 | F29: 20337
C30: 2 | D30: Главный специалист | E30: 9 | F30: 16222
C31: 1 | D31: Ведущий инженер | E31: 10 | F31: 13116
C32: 1 | D32: Инженер 1 категории | E32: 14 | F32: 10615
A33: 4 | B33: Раздел 4 «Технические условия на подключение» | C33: 1 | D33: ГИП | E33: 1 | F33: 20337 | G33: =E33*F33+E34*F34+E36*F36+E37*F37+E35*F35 -> 159934
C34: 1 | D34: Начальник отдела | E34: 1 | F34: 20337
C35: 1 | D35: Главный специалист | E35: 1 | F35: 16222
C36: 1 | D36: Ведущий инженер | E36: 3 | F36: 13116
C37: 1 | D37: Инженер 1 категории | E37: 6 | F37: 10615
A38: 5 | B38: Раздел 5 «Технические требования на пересечения» | C38: 1 | D38: ГИП | E38: 1 | F38: 20337 | G38: =E38*F38+E39*F39+E41*F41+E42*F42+E40*F40 -> 186771
C39: 1 | D39: Начальник отдела | E39: 1 | F39: 20337
C40: 1 | D40: Главный специалист | E40: 2 | F40: 16222
C41: 1 | D41: Ведущий инженер | E41: 3 | F41: 13116
C42: 1 | D42: Инженер 1 категории | E42: 7 | F42: 10615
A43: 6 | B43: Составление пояснительной записки. | C43: 1 | D43: ГИП | E43: 1 | F43: 20337 | G43: =F43*E43+F44*E44+E45*F45 -> 145038
C44: 1 | D44: Начальник отдела | E44: 3 | F44: 20337
C45: 1 | D45: Инженер 1 категории | E45: 6 | F45: 10615
A46: 7 | B46: Итого по смете: | G46: =SUM(G18:G45) -> 2431794
B48: Раздел 2. Определение стоимости работы
A50: № п/п | B50: Наименование показателей | F50: Единица измерения | G50: Значение показателей
A51: 1 | B51: Общая з/п непосредственных исполнителей | F51: руб. | G51: =G46 -> 2431794
B52: Коэффициент отношения з/п непосредственных исполнителей к себестоимости | G52: 0.45
A53: 2 | B53: Себестоимость исходя из установленного коэффициента Разделить на коэф-т 0.45 от п.1 | F53: руб. | G53: =G51/G52 -> 5403986.7
B54: Уровень рентабельности (по отношению к себестоимости) | F54: % | G54: 8
A55: 3 | B55: Прибыль 8% от п.2 | F55: руб. | G55: =G53*0.08 -> 432318.93
A56: 4 | B56: Стоимость работы Сумма от п.2-3 | F56: руб. | G56: =G55+G53 -> 5836305.6
A57: 5 | B57: Итого за вычетом кураторских затрат Разделить на коэф-т 1,02 от п. 4 | F57: руб. | G57: =ROUND(G56/1.02,2) -> 5721868.2
A58: 6 | B58: Всего стоимость по смете | F58: руб. | G58: =G57 -> 5721868.2 | H58: 5700396

Sheet РД 3.1 ГП++
E1: форма 2П, 707/пр
A3: =СВОД!E34 -> Смета №3.1
A4: на проектные (изыскательские) работы
A6: Наименование предприятия, здания, сооружения, стадии проектирования, этапа, вида проектных или изыскательских работ | F6: =СВОД!B34 -> Генеральный план
A8: Наименование проектной (изыскательской) организации | F8: =СВОД!D14 -> Определяется по итогам конкурентных процедур
A10: Наименование организации заказчика | F10: =СВОД!D16 -> ООО «Газпром проектирование»
A12: № пп | B12: Наименование объекта проектирования или вида проектных работ | G12: Наименование, номера глав, таблиц, параграфов и пунктов МНЗ на проектные работы | K12: Расчет стоимости | O12: Стоимость, руб.
A13: 1 | B13: 2 | G13: 3 | K13: 4 | O13: 5
A14: Этап 12 (Площадка РЛВЖ) Разработка комплекта 4212.012.Р.12/0.0004.ПРЛВЖ.000.00000.000-ГП
A15: 1 | B15: Генеральный план и транспорт в составе: вертикальная планировка, благоустройство и озеленение, внутриплощадочные автодороги, сводный план коммуникаций и сетей, участка. Площадь от 0.5 га до 10 га включительно. | G15: НЗ №849/пр Объекты газовой промышленности. 2023 г. Таблица 3.8. Объекты общетехнического назначения, п.10 A = 31.1 тыс.руб; B = 122.993 тыс.руб; Xзад = 4.9 (га); Количество = 1 | K15: Полный комплекс работ (100%): (A + B * Xзад) * Количество * Ктек * Кст (31 100 руб. + 122 993 руб. * 4.9) * 1 * 1.56 * 0.6 | O15: =ROUND((31100 + 122993 * 4.9) * 1 * 1.56 * 0.6, 2) -> 593204.7
B16: Коэффициенты
B17: Стадия: Рабочая документация | G17: Кст = 0.6
B18: инд.3кв.2026г.к 01.01.2022 на пр.раб. | G18: Ктек = 1.56 Письмо Минстроя России от 23.07.2026 №45358-ИФ/09
A19: Этап 12 (Площадка РЛВЖ) Разработка комплекта 4212.012.Р.12/0.0004.ПРЛВЖ.000.00000.000-ГП
A20: 2 | B20: Инженерная подготовка территории. Объем отсыпки (намыва) грунта от 20 до 50 тыс.куб.м. включительно. | G20: НЗ №912/пр Инженерная защита территорий, зданий и сооружений от опасных геологических процессов. 2023 г. Таблица 3.2. Объекты регулирования стока поверхностных вод, водопонижения, п.1 A = 87.1 тыс.руб; B = 24.266 тыс.руб; Xзад = 45 (тыс.куб.м.); Количество = 1 | K20: (A + B * Xзад) * Количество * Ктек * Кст (87 100 руб. + 24 266 руб. * 45) * 1 * 1.56 * 0.6 | O20: =ROUND((87100 + 24266 * 45) * 1 * 1.56 * 0.6, 2) -> 1103609.5
B21: Коэффициенты
B22: Стадия: Рабочая документация | G22: Кст = 0.6
B23: инд.3кв.2026г.к 01.01.2022 на пр.раб. | G23: Ктек = 1.56 Письмо Минстроя России от 23.07.2026 №45358-ИФ/09
A24: Этап 16 (Площадка печей подогревателей газа Степновской СПХГ) Разработка комплекта 4212.012.Р.16/0.0004.ПлППГ.000.00000.000-ГП
A25: 3 | B25: Генеральный план и транспорт в составе: вертикальная планировка, благоустройство и озеленение, внутриплощадочные автодороги, сводный план коммуникаций и сетей, участка. Площадь от 0.5 га до 10 га включительно. | G25: НЗ №849/пр Объекты газовой промышленности. 2023 г. Таблица 3.8. Объекты общетехнического назначения, п.10 A = 31.1 тыс.руб; B = 122.993 тыс.руб; Xзад = 2 (га); Количество = 1 | K25: Полный комплекс работ (100%): (A + B * Xзад) * Количество * Ктек * Кст (31 100 руб. + 122 993 руб. * 2) * 1 * 1.56 * 0.6 | O25: =ROUND((31100 + 122993 * 2) * 1 * 1.56 * 0.6, 2) -> 259352.5
B26: Коэффициенты
B27: Стадия: Рабочая документация | G27: Кст = 0.6
B28: инд.3кв.2026г.к 01.01.2022 на пр.раб. | G28: Ктек = 1.56 Письмо Минстроя России от 23.07.2026 №45358-ИФ/09
A29: Этап 16 (Площадка печей подогревателей газа Степновской СПХГ) Разработка комплекта 4212.012.Р.16/0.0004.ПлППГ.000.00000.000-ГП
A30: 4 | B30: Инженерная подготовка территории. Объем отсыпки (намыва) грунта от 6 до 20 тыс.куб.м. включительно. | G30: НЗ №912/пр Инженерная защита территорий, зданий и сооружений от опасных геологических процессов. 2023 г. Таблица 3.2. Объекты регулирования стока поверхностных вод, водопонижения, п.1 A = 85.7 тыс.руб; B = 24.336 тыс.руб; Xзад = 20 (тыс.куб.м.); Количество = 1 | K30: (A + B * Xзад) * Количество * Ктек * Кст (85 700 руб. + 24 336 руб. * 20) * 1 * 1.56 * 0.6 | O30: =ROUND((85700 + 24336 * 20) * 1 * 1.56 * 0.6, 2) -> 535785.12
B31: Коэффициенты
B32: Стадия: Рабочая документация | G32: Кст = 0.6
B33: инд.3кв.2026г.к 01.01.2022 на пр.раб. | G33: Ктек = 1.56 Письмо Минстроя России от 23.07.2026 №45358-ИФ/09
A34: Этап 17 (УЗРГ.000-Узел замера расхода газа)
A35: 5 | B35: Генеральный план и транспорт в составе: вертикальная планировка, благоустройство и озеленение, внутриплощадочные автодороги, сводный план коммуникаций и сетей, участка. Площадь от 0.5 га до 10 га включительно. | G35: НЗ №849/пр Объекты газовой промышленности. 2023 г. Таблица 3.8. Объекты общетехнического назначения, п.10 A = 31.1 тыс.руб; B = 122.993 тыс.руб; Xзад = 1 (га); Количество = 1 | K35: Полный комплекс работ (100%): (A + B * Xзад) * Количество * Ктек * Кст (31 100 руб. + 122 993 руб. * 1) * 1 * 1.56 * 0.6 | O35: =ROUND((31100 + 122993 * 1) * 1 * 1.56 * 0.6, 2) -> 144231.05
B36: Коэффициенты
B37: Стадия: Рабочая документация | G37: Кст = 0.6
B38: инд.3кв.2026г.к 01.01.2022 на пр.раб. | G38: Ктек = 1.56 Письмо Минстроя России от 23.07.2026 №45358-ИФ/09
A39: 6 | B39: Инженерная подготовка территории. Объем отсыпки (намыва) грунта от 6 до 20 тыс.куб.м. включительно. | G39: НЗ №912/пр Инженерная защита территорий, зданий и сооружений от опасных геологических процессов. 2023 г. Таблица 3.2. Объекты регулирования стока поверхностных вод, водопонижения, п.1 A = 85.7 тыс.руб; B = 24.336 тыс.руб; Xзад = 15 (тыс.куб.м.); Количество = 1 | K39: (A + B * Xзад) * Количество * Ктек * Кст (85 700 руб. + 24 336 руб. * 15) * 1 * 1.56 * 0.6 | O39: =ROUND((85700 + 24336 * 15) * 1 * 1.56 * 0.6, 2) -> 421892.64
B40: Коэффициенты
B41: Стадия: Рабочая документация | G41: Кст = 0.6
B42: инд.3кв.2026г.к 01.01.2022 на пр.раб. | G42: Ктек = 1.56 Письмо Минстроя России от 23.07.2026 №45358-ИФ/09
A43: Этап 27 (Объекты на площадке КС-5 (частично)) Разработка комплекта 4212.00.Р.04.КСПХГ.5.000.ГП.000
A44: 7 | B44: Генеральный план и транспорт в составе: вертикальная планировка, благоустройство и озеленение, внутриплощадочные автодороги, сводный план коммуникаций и сетей, участка. Площадь от 10 га до 20 га включительно. | G44: НЗ №849/пр Объекты газовой промышленности. 2023 г. Таблица 3.8. Объекты общетехнического назначения, п.10 A = 258.9 тыс.руб; B = 100.213 тыс.руб; Xзад = 13 (га); Количество = 1 | K44: Полный комплекс работ (100%): (A + B * Xзад) * Количество * Ктек * Кст (258 900 руб. + 100 213 руб. * 13) * 1 * 1.56 * 0.6 | O44: =ROUND((258900 + 100213 * 13) * 1 * 1.56 * 0.6, 2) -> 1461722.2
B45: Коэффициенты
B46: Стадия: Рабочая документация | G46: Кст = 0.6
B47: инд.3кв.2026г.к 01.01.2022 на пр.раб. | G47: Ктек = 1.56 Письмо Минстроя России от 23.07.2026 №45358-ИФ/09
A48: Этап 3
A49: Этап 3 (Объекты на площадке ГРП 2А) Разработка комплекта "4212.012.Р.3/0.0004.ГРП.02А.00000.000-ГП"
A50: 8 | B50: Генеральный план и транспорт в составе: вертикальная планировка, благоустройство и озеленение, внутриплощадочные автодороги, сводный план коммуникаций и сетей, участка. Площадь от 0.5 га до 10 га включительно. | G50: НЗ №849/пр Объекты газовой промышленности. 2023 г. Таблица 3.8. Объекты общетехнического назначения, п.10 A = 31.1 тыс.руб; B = 122.993 тыс.руб; Xзад = 5 (га); Количество = 1 | K50: Полный комплекс работ (100%): (A + B * Xзад) * Количество * Ктек * Кст (31 100 руб. + 122 993 руб. * 5) * 1 * 1.56 * 0.6*0,7 | O50: =ROUND((31100+122993*5)*1*1.56*0.6*0.7,2) -> 423301.79
B51: Коэффициенты
B52: Стадия: Рабочая документация | G52: Кст = 0.6
B53: Объем работ | G53: Кобъем = 0.7
B54: инд.3кв.2026г.к 01.01.2022 на пр.раб. | G54: Ктек = 1.56 Письмо Минстроя России от 23.07.2026 №45358-ИФ/09
A55: Этап 3 (Объекты на площадке ГРП 2А) Разработка комплекта "4212.012.Р.3/0.0004.ГРП.02А.00000.000-ГП"
A56: 9 | B56: Инженерная подготовка территории. Объем отсыпки (намыва) грунта от 20 до 50 тыс.куб.м. включительно. | G56: НЗ №912/пр Инженерная защита территорий, зданий и сооружений от опасных геологических процессов. 2023 г. Таблица 3.2. Объекты регулирования стока поверхностных вод, водопонижения, п.1 A = 87.1 тыс.руб; B = 24.266 тыс.руб; Xзад = 50 (тыс.куб.м.); Количество = 1 | K56: (A + B * Xзад) * Количество * Ктек * Кст (87 100 руб. + 24 266 руб. * 50) * 1 * 1.56 * 0.6*0,7 | O56: =ROUND((87100+24266*50)*1*1.56*0.6*0.7,2) -> 852022.08
B57: Коэффициенты
B58: Стадия: Рабочая документация | G58: Кст = 0.6
B59: Объем работ | G59: Кобъем = 0.7
B60: инд.3кв.2026г.к 01.01.2022 на пр.раб. | G60: Ктек = 1.56 Письмо Минстроя России от 23.07.2026 №45358-ИФ/09
A61: Этап 3 (Шг.2А - Сеть газосборная ГРП 2А). Площадки БКЭС.
A62: 10 | B62: Генеральный план и транспорт в составе: вертикальная планировка, благоустройство и озеленение, внутриплощадочные автодороги, сводный план коммуникаций и сетей, участка. Площадь от 0.5 га до 10 га включительно. | G62: НЗ №849/пр Объекты газовой промышленности. 2023 г. Таблица 3.8. Объекты общетехнического назначения, п.10 A = 31.1 тыс.руб; B = 122.993 тыс.руб; Xмин = 0.5; Xзад = 0.4 (га); Количество = 1 | K62: Полный комплекс работ (100%): (A + B * (0.4 * Xмин + 0.6 * Xзад)) * Количество * Ктек * Кст (31 100 руб. + 122 993 руб. * (0.4 * 0.5 + 0.6 * 0.4)) * 1 * 1.56 * 0.6*0,7 | O62: =ROUND((31100+122993*(0.4*0.5+0.6*0.4))*1*1.56*0.6*0.7,2) -> 55834.13
B63: Коэффициенты
B64: Стадия: Рабочая документация | G64: Кст = 0.6
B65: Объем работ | G65: Кобъем = 0.7
B66: инд.3кв.2026г.к 01.01.2022 на пр.раб. | G66: Ктек = 1.56 Письмо Минстроя России от 23.07.2026 №45358-ИФ/09
A67: 11 | B67: Итого по смете: | O67: =ROUND(SUM($O$15:$O$62),2) -> 5850955.7
A68: 12 | B68: Новое начисление | G68: К1 = 0.8 Коэффициент оптимизации ПАО "Газпром" («Порядок формирования стоимости проектно-изыскательских работ для строительства и реконструкции объектов ПАО «Газпром» от 28.12.2017г. п.5.41) (Ценообразующий) | K68: Коэф-т 1 от п.11 * 0.8 6 421 451.99 руб. * 1 * 0.8 | O68: =ROUND(($O$67)*1*0.8,2) -> 4680764.6
A69: 13 | B69: Новое начисление | G69: Коэффициент на объем работ по Этапам 2, 3, 12, 15, 16, 27 | K69: Коэф-т 0.7 от п.22 43 315 187.26 руб. * 0.7 | O69: =O68*0.7 -> 3276535.2
A70: 14 | B70: Всего по смете: | O70: =O69 -> 3276535.2 | R70: =O70 -> 3276535.2

Sheet 3.2 Автодороги++
E1: форма 2П, 707/пр
A3: =СВОД!E35 -> Смета №3.2
A4: на проектные (изыскательские) работы
A6: Наименование предприятия, здания, сооружения, стадии проектирования, этапа, вида проектных или изыскательских работ | F6: =СВОД!B35 -> Автомобильные дороги
A8: Наименование проектной (изыскательской) организации | F8: =СВОД!D14 -> Определяется по итогам конкурентных процедур
A10: Наименование организации заказчика | F10: =СВОД!D16 -> ООО «Газпром проектирование»
A12: № пп | B12: Наименование объекта проектирования или вида проектных работ | G12: Наименование, номера глав, таблиц, параграфов и пунктов МНЗ на проектные работы | K12: Расчет стоимости | O12: Стоимость, руб.
A13: 1 | B13: 2 | G13: 3 | K13: 4 | O13: 5
A14: Этап 16 (Площадка печей подогревателей газа Степновской СПХГ) ПАД.011 - Подъездная автомобильная дорога к ПППГ Разработка комплекта 4212.012.Р.16/0.0004.ПАД.011.40712.000-АД
A15: 1 | B15: Автомобильные дороги технической категории IV. Категория сложности проектирования: 3. Протяженность от 0.2 до 0.5 километра включительно. | G15: НЗ №51/пр Строительство, реконструкция и капитальный ремонт автомобильных дорог, их конструктивных элементов и сооружений на них. 2025 г. Таблица 3.5. Автомобильные дороги технической категории IV, п.2.3 A = 290.1 тыс.руб; B = 1 856.633 тыс.руб; Протяженность дороги L = 0.23229 км; Количество = 1; | K15: (A + B * L) * Количество * Ктек * Кст (290 100 руб. + 1 856 633 руб. * 0.23229) * 1 * 1.4 * 0.6 | O15: =ROUND((290100 + 1856633 * 0.23229) * 1 * 1.4 * 0.6, 2) -> 605956.91
B16: Коэффициенты
B17: Стадия: Рабочая документация | G17: Кст = 0.6
B18: инд.3кв.2026г.к 01.01.2023 на пр.раб. | G18: Ктек = 1.4 Письмо Минстроя России от 23.07.2026 №45358-ИФ/09
A19: Этап 16 (Площадка печей подогревателей газа Степновской СПХГ) ПАД.011 - Подъездная автомобильная дорога к ПППГ Разработка комплекта 4212.012.Р.16/0.0004.ПАД.011.40712.000-АД
A20: 2 | B20: Примыкание автомобильных дорог в одном уровне с устройством переходно-скоростных полос движения, островков безопасности. Категория сложности проектирования: 3. | G20: НЗ №51/пр Строительство, реконструкция и капитальный ремонт автомобильных дорог, их конструктивных элементов и сооружений на них. 2025 г. Таблица 3.7. Развязки, п.2.3 A = 1 622.6 тыс.руб; Количество = 1 (объект) | K20: A * Количество * Ктек * Кст * K1 1 622 600 руб. * 1 * 1.4 * 0.6 * 0.47 | O20: =ROUND(1622600 * 1 * 1.4 * 0.6 * 0.47, 2) -> 640602.48
B21: Коэффициенты
B22: Стадия: Рабочая документация | G22: Кст = 0.6
B23: инд.3кв.2026г.к 01.01.2023 на пр.раб. | G23: Ктек = 1.4 Письмо Минстроя России от 23.07.2026 №45358-ИФ/09
B24: Пересечение (примыкание) автомобильных дорог в одном уровне определяется с корректирующим коэффициентом для примыканий без устройства переходно-скоростных полос | G24: K1 = 0.47 Табл.4, п.9 (Ценообразующий)
A25: Этап 16 (Площадка печей подогревателей газа Степновской СПХГ) ПАД.010 - Подъездная автомобильная дорога к УЗРГ Разработка комплекта 4212.012.Р.16/0.0004.ПАД.010.40712.000-АД
A26: 3 | B26: Автомобильные дороги технической категории IV. Категория сложности проектирования: 3. Протяженность от 0.2 до 0.5 километра включительно. | G26: НЗ №51/пр Строительство, реконструкция и капитальный ремонт автомобильных дорог, их конструктивных элементов и сооружений на них. 2025 г. Таблица 3.5. Автомобильные дороги технической категории IV, п.2.3 A = 290.1 тыс.руб; B = 1 856.633 тыс.руб; Протяженность дороги L = 0.29304 км; Количество = 1; | K26: (A + B * L) * Количество * Ктек * Кст (290 100 руб. + 1 856 633 руб. * 0.29304) * 1 * 1.4 * 0.6 | O26: =ROUND((290100 + 1856633 * 0.29304) * 1 * 1.4 * 0.6, 2) -> 700700.9
B27: Коэффициенты
B28: Стадия: Рабочая документация | G28: Кст = 0.6
B29: инд.3кв.2026г.к 01.01.2023 на пр.раб. | G29: Ктек = 1.4 Письмо Минстроя России от 23.07.2026 №45358-ИФ/09
A30: Этап 16 (Площадка печей подогревателей газа Степновской СПХГ) ПАД.010 - Подъездная автомобильная дорога к УЗРГ Разработка комплекта 4212.012.Р.16/0.0004.ПАД.010.40712.000-АД
A31: 4 | B31: Примыкание автомобильных дорог в одном уровне с устройством переходно-скоростных полос движения, островков безопасности. Категория сложности проектирования: 3. | G31: НЗ №51/пр Строительство, реконструкция и капитальный ремонт автомобильных дорог, их конструктивных элементов и сооружений на них. 2025 г. Таблица 3.7. Развязки, п.2.3 A = 1 622.6 тыс.руб; Количество = 1 (объект) | K31: A * Количество * Ктек * Кст * K1 1 622 600 руб. * 1 * 1.4 * 0.6 * 0.47 | O31: =ROUND(1622600 * 1 * 1.4 * 0.6 * 0.47, 2) -> 640602.48
B32: Коэффициенты
B33: Стадия: Рабочая документация | G33: Кст = 0.6
B34: инд.3кв.2026г.к 01.01.2023 на пр.раб. | G34: Ктек = 1.4 Письмо Минстроя России от 23.07.2026 №45358-ИФ/09
B35: Пересечение (примыкание) автомобильных дорог в одном уровне определяется с корректирующим коэффициентом для примыканий без устройства переходно-скоростных полос | G35: K1 = 0.47 Табл.4, п.9 (Ценообразующий)
A36: Этап 16 (Площадка печей подогревателей газа Степновской СПХГ) ПАД.010 - Подъездная автомобильная дорога к УЗРГ Разработка комплекта 4212.012.Р.16/0.0004.ПАД.010.40712.000-АД
A37: 5 | B37: Водопропускные трубы на автомобильных дорогах протяженностью, м. Круглые и прямоугольные железобетонные трубы отверстием до 2000 мм. | G37: Искусственные сооружения. 2015 г. Таблица 2. Водопропускные трубы на железных и автомобильных дорогах, п.2.4 A = 5.61 тыс.руб; B = 0.24 тыс.руб; Xзад = 13 (м); Количество = 1 | K37: (A + B * Xзад) * Количество * Ктек * Кст (5 610 руб. + 240 руб. * 13) * 1 * 7.22 * 0.66 | O37: =ROUND((5610 + 240 * 13) * 1 * 7.22 * 0.66, 2) -> 41600.2
B38: Коэффициенты
B39: Стадия: Рабочая документация | G39: Кст = 0.66
B40: инд.3кв.2026г.к 01.01.2001 на пр.раб. | G40: Ктек = 7.22 Письмо Минстроя России от 23.07.2026 №45358-ИФ/09
A41: Этап 27 (Объекты на площадке КС-5 (частично)) ПАД.009 - Подъездная автомобильная дорога к РЛВЖ Разработка комплекта 4212.012.Р.12/0.0004.ПАД.009.40712.000-АД
A42: 6 | B42: Автомобильные дороги технической категории IV. Категория сложности проектирования: 3. Протяженность от 0.2 до 0.5 километра включительно. | G42: НЗ №51/пр Строительство, реконструкция и капитальный ремонт автомобильных дорог, их конструктивных элементов и сооружений на них. 2025 г. Таблица 3.5. Автомобильные дороги технической категории IV, п.2.3 A = 290.1 тыс.руб; B = 1 856.633 тыс.руб; Протяженность дороги L = 0.28839 км; Количество = 1; | K42: (A + B * L) * Количество * Ктек * Кст (290 100 руб. + 1 856 633 руб. * 0.28839) * 1 * 1.4 * 0.6 | O42: =ROUND((290100 + 1856633 * 0.28839) * 1 * 1.4 * 0.6, 2) -> 693448.89
B43: Коэффициенты
B44: Стадия: Рабочая документация | G44: Кст = 0.6
B45: инд.3кв.2026г.к 01.01.2023 на пр.раб. | G45: Ктек = 1.4 Письмо Минстроя России от 23.07.2026 №45358-ИФ/09
A46: Этап 27 (Объекты на площадке КС-5 (частично)) ПАД.009 - Подъездная автомобильная дорога к РЛВЖ Разработка комплекта 4212.012.Р.12/0.0004.ПАД.009.40712.000-АД
A47: 7 | B47: Примыкание автомобильных дорог в одном уровне с устройством переходно-скоростных полос движения, островков безопасности. Категория сложности проектирования: 3. | G47: НЗ №51/пр Строительство, реконструкция и капитальный ремонт автомобильных дорог, их конструктивных элементов и сооружений на них. 2025 г. Таблица 3.7. Развязки, п.2.3 A = 1 622.6 тыс.руб; Количество = 1 (объект) | K47: A * Количество * Ктек * Кст * K1 1 622 600 руб. * 1 * 1.4 * 0.6 * 0.47 | O47: =ROUND(1622600 * 1 * 1.4 * 0.6 * 0.47, 2) -> 640602.48
B48: Коэффициенты
B49: Стадия: Рабочая документация | G49: Кст = 0.6
B50: инд.3кв.2026г.к 01.01.2023 на пр.раб. | G50: Ктек = 1.4 Письмо Минстроя России от 23.07.2026 №45358-ИФ/09
B51: Пересечение (примыкание) автомобильных дорог в одном уровне определяется с корректирующим коэффициентом для примыканий без устройства переходно-скоростных полос | G51: K1 = 0.47 Табл.4, п.9 (Ценообразующий)
A52: Этап 27 (Объекты на площадке КС-5 (частично)) ПАД.051 - Подъездная автомобильная дорога №1 к КС 5 Разработка комплекта 4212.012.Р.12/0.0004.ПАД.051.40712.000-АД
A53: 8 | B53: Автомобильные дороги технической категории IV. Категория сложности проектирования: 3. Протяженность от 0.2 до 0.5 километра включительно. | G53: НЗ №51/пр Строительство, реконструкция и капитальный ремонт автомобильных дорог, их конструктивных элементов и сооружений на них. 2025 г. Таблица 3.5. Автомобильные дороги технической категории IV, п.2.3 A = 290.1 тыс.руб; B = 1 856.633 тыс.руб; Протяженность дороги L = 0.43480 км; Количество = 1; | K53: (A + B * L) * Количество * Ктек * Кст (290 100 руб. + 1 856 633 руб. * 0.43480) * 1 * 1.4 * 0.6 | O53: =ROUND((290100 + 1856633 * 0.4348) * 1 * 1.4 * 0.6, 2) -> 921785.78
B54: Коэффициенты
B55: Стадия: Рабочая документация | G55: Кст = 0.6
B56: инд.3кв.2026г.к 01.01.2023 на пр.раб. | G56: Ктек = 1.4 Письмо Минстроя России от 23.07.2026 №45358-ИФ/09
A57: Этап 27 (Объекты на площадке КС-5 (частично)) ПАД.051 - Подъездная автомобильная дорога №1 к КС 5 Разработка комплекта 4212.012.Р.12/0.0004.ПАД.051.40712.000-АД
A58: 9 | B58: Примыкание автомобильных дорог в одном уровне с устройством переходно-скоростных полос движения, островков безопасности. Категория сложности проектирования: 3. | G58: НЗ №51/пр Строительство, реконструкция и капитальный ремонт автомобильных дорог, их конструктивных элементов и сооружений на них. 2025 г. Таблица 3.7. Развязки, п.2.3 A = 1 622.6 тыс.руб; Количество = 1 (объект) | K58: A * Количество * Ктек * Кст * K1 1 622 600 руб. * 1 * 1.4 * 0.6 * 0.47 | O58: =ROUND(1622600 * 1 * 1.4 * 0.6 * 0.47, 2) -> 640602.48
B59: Коэффициенты
B60: Стадия: Рабочая документация | G60: Кст = 0.6
B61: инд.3кв.2026г.к 01.01.2023 на пр.раб. | G61: Ктек = 1.4 Письмо Минстроя России от 23.07.2026 №45358-ИФ/09
B62: Пересечение (примыкание) автомобильных дорог в одном уровне определяется с корректирующим коэффициентом для примыканий без устройства переходно-скоростных полос | G62: K1 = 0.47 Табл.4, п.9 (Ценообразующий)
A63: Этап 27 (Объекты на площадке КС-5 (частично)) ПАД.051 - Подъездная автомобильная дорога №1 к КС 5 Разработка комплекта 4212.012.Р.12/0.0004.ПАД.051.40712.000-АД
A64: 10 | B64: Водопропускные трубы на автомобильных дорогах протяженностью, м. Круглые и прямоугольные железобетонные трубы отверстием до 2000 мм. | G64: Искусственные сооружения. 2015 г. Таблица 2. Водопропускные трубы на железных и автомобильных дорогах, п.2.4 A = 5.61 тыс.руб; B = 0.24 тыс.руб; Xзад = 14 (м); Количество = 1 | K64: (A + B * Xзад) * Количество * Ктек * Кст (5 610 руб. + 240 руб. * 14) * 1 * 7.22 * 0.66 | O64: =ROUND((5610 + 240 * 14) * 1 * 7.22 * 0.66, 2) -> 42743.84
B65: Коэффициенты
B66: Стадия: Рабочая документация | G66: Кст = 0.66
B67: инд.3кв.2026г.к 01.01.2001 на пр.раб. | G67: Ктек = 7.22 Письмо Минстроя России от 23.07.2026 №45358-ИФ/09
A68: Этап 27 (Объекты на площадке КС-5 (частично)) ПАД.052 - Подъездная автомобильная дорога №2 к КС5 Разработка комплекта 4212.012.Р.12/0.0004.ПАД.052.40712.000-АД
A69: 11 | B69: Автомобильные дороги технической категории IV. Категория сложности проектирования: 3. Протяженность от 0.5 до 1 километра включительно. | G69: НЗ №51/пр Строительство, реконструкция и капитальный ремонт автомобильных дорог, их конструктивных элементов и сооружений на них. 2025 г. Таблица 3.5. Автомобильные дороги технической категории IV, п.3.3 A = 652.3 тыс.руб; B = 1 132.306 тыс.руб; Протяженность дороги L = 0.94891 км; Количество = 1; | K69: (A + B * L) * Количество * Ктек * Кст (652 300 руб. + 1 132 306 руб. * 0.94891) * 1 * 1.4 * 0.6 | O69: =ROUND((652300 + 1132306 * 0.94891) * 1 * 1.4 * 0.6, 2) -> 1450475.4
B70: Коэффициенты
B71: Стадия: Рабочая документация | G71: Кст = 0.6
B72: инд.3кв.2026г.к 01.01.2023 на пр.раб. | G72: Ктек = 1.4 Письмо Минстроя России от 23.07.2026 №45358-ИФ/09
A73: Этап 27 (Объекты на площадке КС-5 (частично)) ПАД.052 - Подъездная автомобильная дорога №2 к КС5 Разработка комплекта 4212.012.Р.12/0.0004.ПАД.052.40712.000-АД
A74: 12 | B74: Примыкание автомобильных дорог в одном уровне с устройством переходно-скоростных полос движения, островков безопасности. Категория сложности проектирования: 3. | G74: НЗ №51/пр Строительство, реконструкция и капитальный ремонт автомобильных дорог, их конструктивных элементов и сооружений на них. 2025 г. Таблица 3.7. Развязки, п.2.3 A = 1 622.6 тыс.руб; Количество = 1 (объект) | K74: A * Количество * Ктек * Кст * K1 1 622 600 руб. * 1 * 1.4 * 0.6 * 0.47 | O74: =ROUND(1622600 * 1 * 1.4 * 0.6 * 0.47, 2) -> 640602.48
B75: Коэффициенты
B76: Стадия: Рабочая документация | G76: Кст = 0.6
B77: инд.3кв.2026г.к 01.01.2023 на пр.раб. | G77: Ктек = 1.4 Письмо Минстроя России от 23.07.2026 №45358-ИФ/09
B78: Пересечение (примыкание) автомобильных дорог в одном уровне определяется с корректирующим коэффициентом для примыканий без устройства переходно-скоростных полос | G78: K1 = 0.47 Табл.4, п.9 (Ценообразующий)
A79: Этап 3
A80: Этап 3 (Объекты на площадке ГРП 2А) ПАД.02А - Подъездная автомобильная дорога к ГРП 2А Разработка комплекта 4212.012.Р.3/0.0004.ПАД.02А.40712.000-АД
A81: 13 | B81: Автомобильные дороги технической категории IV. Категория сложности проектирования: 3. Протяженность от 0.2 до 0.5 километра включительно. | G81: НЗ №51/пр Строительство, реконструкция и капитальный ремонт автомобильных дорог, их конструктивных элементов и сооружений на них. 2025 г. Таблица 3.5. Автомобильные дороги технической категории IV, п.2.3 A = 290.1 тыс.руб; B = 1 856.633 тыс.руб; Протяженность дороги L = 0.31524 км; Количество = 1; | K81: (A + B * L) * Количество * Ктек * Кст (290 100 руб. + 1 856 633 руб. * 0.31524) * 1 * 1.4 * 0.6*0,7 | O81: =ROUND((290100+1856633*0.31524)*1*1.4*0.6*0.7,2) -> 514726.37
B82: Коэффициенты
B83: Стадия: Рабочая документация | G83: Кст = 0.6
B84: Объем работ | G84: Кобъем = 0.7
B85: инд.3кв.2026г.к 01.01.2023 на пр.раб. | G85: Ктек = 1.4 Письмо Минстроя России от 23.07.2026 №45358-ИФ/09
A86: Этап 3 (Объекты на площадке ГРП 2А) ПАД.02А - Подъездная автомобильная дорога к ГРП 2А Разработка комплекта 4212.012.Р.3/0.0004.ПАД.02А.40712.000-АД
A87: 14 | B87: Примыкание автомобильных дорог в одном уровне с устройством переходно-скоростных полос движения, островков безопасности. Категория сложности проектирования: 3. | G87: НЗ №51/пр Строительство, реконструкция и капитальный ремонт автомобильных дорог, их конструктивных элементов и сооружений на них. 2025 г. Таблица 3.7. Развязки, п.2.3 A = 1 622.6 тыс.руб; Количество = 1 (объект) | K87: A * Количество * Ктек * Кст * K1 1 622 600 руб. * 1 * 1.4 * 0.6 * 0.47*0,7 | O87: =ROUND(1622600*1*1.4*0.6*0.47*0.7,2) -> 448421.74
B88: Коэффициенты
B89: Стадия: Рабочая документация | G89: Кст = 0.6
B90: Объем работ | G90: Кобъем = 0.7
B91: инд.3кв.2026г.к 01.01.2023 на пр.раб. | G91: Ктек = 1.4 Письмо Минстроя России от 23.07.2026 №45358-ИФ/09
B92: Пересечение (примыкание) автомобильных дорог в одном уровне определяется с корректирующим коэффициентом для примыканий без устройства переходно-скоростных полос | G92: K1 = 0.47 Табл.4, п.9 (Ценообразующий)
A93: 15 | B93: Итого по смете: | O93: =ROUND(SUM($O$15:$O$87),2) -> 8622872.5
A94: 16 | B94: Новое начисление | G94: К1 = 0.8 Коэффициент оптимизации ПАО "Газпром" («Порядок формирования стоимости проектно-изыскательских работ для строительства и реконструкции объектов ПАО «Газпром» от 28.12.2017г. п.5.41) (Ценообразующий) | K94: Коэф-т 1 от п.15 * 0.8 9 035 650.24 руб. * 1 * 0.8 | O94: =ROUND(($O$93)*1*0.8,2) -> 6898298
A95: 17 | B95: Новое начисление | G95: Коэффициент на объем работ по Этапам 2, 3, 12, 15, 16, 27 | K95: Коэф-т 0.7 от п.22 43 315 187.26 руб. * 0.7 | O95: =O94*0.7 -> 4828808.6
A96: 18 | B96: Всего по смете: | O96: =O95 -> 4828808.6 | R96: =O96 -> 4828808.6

Sheet 3.3 ТХ++
E1: форма 2П, 707/пр
A3: =СВОД!E36 -> Смета №3.3
A4: на проектные (изыскательские) работы
A6: Наименование предприятия, здания, сооружения, стадии проектирования, этапа, вида проектных или изыскательских работ | F6: =СВОД!B36 -> Технология производства
A8: Наименование проектной (изыскательской) организации | F8: =СВОД!D14 -> Определяется по итогам конкурентных процедур
A10: Наименование организации заказчика | F10: =СВОД!D16 -> ООО «Газпром проектирование»
A12: № пп | B12: Наименование объекта проектирования или вида проектных работ | G12: Наименование, номера глав, таблиц, параграфов и пунктов МНЗ на проектные работы | K12: Расчет стоимости | O12: Стоимость, руб.
A13: 1 | B13: 2 | G13: 3 | K13: 4 | O13: 5
A14: Этап 2 (Объекты на площадке КС 3)
A15: 201 - Установка регенерации метанола
A16: 1 | B16: Установка регенерации метанола (огневая регенерация) производительностью от 1 куб.м/час до 5 куб.м/час включительно | G16: НЗ №849/пр Объекты газовой промышленности. 2023 г. Таблица 3.7. Объекты подготовки газа, газового конденсата (УКПГ, УППГ, УПТГ, ГС), п.8 A = 1 202.4 тыс. руб.B = 412.925 тыс. руб.; Xмакс = 5; Хзад = 20 (куб.м/час); Количество = 1 | K16: (A + B * (0.4 * Xмакс + 0.6 * Xзад)) * Количество * Ктек * Кст * K1 * K2 (1 202 400 руб. + 412 925 руб. * (0.4 * 5 + 0.6 * 20)) * 1 * 1.56 * 0.6 * 0.2 * 0.7 | O16: =ROUND((1202400 + 412925 * (0.4 * 5 + 0.6 * 20)) * 1 * 1.56 * 0.6 * 0.2 * 0.7, 2) -> 915098.18
B17: Коэффициенты
B18: Стадия: Рабочая документация | G18: Кст = 0.6
B19: инд.3кв.2026г.к 01.01.2022 на пр.раб. | G19: Ктек = 1.56 Письмо Минстроя России от 23.07.2026 №45358-ИФ/09
B20: Стоимость проектных работ для зданий и сооружений блочного (модульного) типа высокой заводской готовности определяется на основании параметров цены проектных работ с применением корректирующего коэффициента | G20: K1 = 0.2 Глава 2, п.15 (Ценообразующий)
B21: Коэффициент на объём работ | G21: K2 = 0.7 (Ценообразующий)
A22: 211 - Площадка емкостей и АВО
A23: 2 | B23: Установка регенерации метанола (огневая регенерация) производительностью от 1 куб.м/час до 5 куб.м/час включительно | G23: НЗ №849/пр Объекты газовой промышленности. 2023 г. Таблица 3.7. Объекты подготовки газа, газового конденсата (УКПГ, УППГ, УПТГ, ГС), п.8 A = 1 202.4 тыс. руб.B = 412.925 тыс. руб.; Xмакс = 5; Хзад = 20 (куб.м/час); Количество = 1 | K23: (A + B * (0.4 * Xмакс + 0.6 * Xзад)) * Количество * Ктек * Кст * K1 * K2 (1 202 400 руб. + 412 925 руб. * (0.4 * 5 + 0.6 * 20)) * 1 * 1.56 * 0.6 * 0.2 * 0.7 | O23: =ROUND((1202400 + 412925 * (0.4 * 5 + 0.6 * 20)) * 1 * 1.56 * 0.6 * 0.2 * 0.7, 2) -> 915098.18
B24: Коэффициенты
B25: Стадия: Рабочая документация | G25: Кст = 0.6
B26: инд.3кв.2026г.к 01.01.2022 на пр.раб. | G26: Ктек = 1.56 Письмо Минстроя России от 23.07.2026 №45358-ИФ/09
B27: Стоимость проектных работ для зданий и сооружений блочного (модульного) типа высокой заводской готовности определяется на основании параметров цены проектных работ с применением корректирующего коэффициента | G27: K1 = 0.2 Глава 2, п.15 (Ценообразующий)
B28: Коэффициент на объём работ | G28: K2 = 0.7 (Ценообразующий)
A29: 230 - Узел подключения ГРП
A30: 3 | B30: Установка переключающей арматуры производительностью от 10 млн.куб.м/сут до 60 млн.куб.м/сут включительно | G30: НЗ №849/пр Объекты газовой промышленности. 2023 г. Таблица 3.7. Объекты подготовки газа, газового конденсата (УКПГ, УППГ, УПТГ, ГС), п.1 A = 1 087.3 тыс. руб.B = 47.464 тыс. руб.; Xмакс = 60; Хзад = 80 (млн.куб.м/сут); Количество = 1 | K30: (A + B * (0.4 * Xмакс + 0.6 * Xзад)) * Количество * Ктек * Кст * K1 (1 087 300 руб. + 47 464 руб. * (0.4 * 60 + 0.6 * 80)) * 1 * 1.56 * 0.6 * 0.7 | O30: =ROUND((1087300 + 47464 * (0.4 * 60 + 0.6 * 80)) * 1 * 1.56 * 0.6 * 0.7, 2) -> 2951484.7
B31: Коэффициенты
B32: Стадия: Рабочая документация | G32: Кст = 0.6
B33: инд.3кв.2026г.к 01.01.2022 на пр.раб. | G33: Ктек = 1.56 Письмо Минстроя России от 23.07.2026 №45358-ИФ/09
B34: Коэффициент на объём работ | G34: K1 = 0.7 (Ценообразующий)
A35: Этап 12 (Площадка РЛВЖ)
A36: 001 - Резервуарный парк метанола V=2х700 м3
A37: 4 | B37: Товарно-сырьевой склад ГЖ и ЛВЖ из вертикальных стальных резервуаров объемом от 1 тыс.куб.м до 5 тыс.куб.м включительно | G37: НЗ №849/пр Объекты газовой промышленности. 2023 г. Таблица 3.7. Объекты подготовки газа, газового конденсата (УКПГ, УППГ, УПТГ, ГС), п.29 A = 532 тыс. руб.B = 618.795 тыс. руб.; Хзад = 1.4 (тыс.куб.м); Количество = 1 | K37: (A + B * Xзад) * Количество * Ктек * Кст * K1 (532 000 руб. + 618 795 руб. * 1.4) * 1 * 1.56 * 0.6 * 0.7 | O37: =ROUND((532000 + 618795 * 1.4) * 1 * 1.56 * 0.6 * 0.7, 2) -> 916174.68
B38: Коэффициенты
B39: Стадия: Рабочая документация | G39: Кст = 0.6
B40: инд.3кв.2026г.к 01.01.2022 на пр.раб. | G40: Ктек = 1.56 Письмо Минстроя России от 23.07.2026 №45358-ИФ/09
B41: Коэффициент на объём работ | G41: K1 = 0.7 (Ценообразующий)
A42: 002 - Здание насосной парков метанола и ДЭГа (ТЭГа)
A43: 5 | B43: Насосная перекачки ГЖ и ЛВЖ с общей установленной производительностью насосов от 80 куб.м/час до 150 куб.м/час включительно | G43: НЗ №849/пр Объекты газовой промышленности. 2023 г. Таблица 3.7. Объекты подготовки газа, газового конденсата (УКПГ, УППГ, УПТГ, ГС), п.27 A = 471.8 тыс. руб.B = 10.314 тыс. руб.; Xмакс = 150; Хзад = 306 (куб.м/час); Количество = 1 | K43: (A + B * (0.4 * Xмакс + 0.6 * Xзад)) * Количество * Ктек * Кст * K1 (471 800 руб. + 10 314 руб. * (0.4 * 150 + 0.6 * 306)) * 1 * 1.56 * 0.6 * 0.7 | O43: =ROUND((471800 + 10314 * (0.4 * 150 + 0.6 * 306)) * 1 * 1.56 * 0.6 * 0.7, 2) -> 1955307.1
B44: Коэффициенты
B45: Стадия: Рабочая документация | G45: Кст = 0.6
B46: инд.3кв.2026г.к 01.01.2022 на пр.раб. | G46: Ктек = 1.56 Письмо Минстроя России от 23.07.2026 №45358-ИФ/09
B47: Коэффициент на объём работ | G47: K1 = 0.7 (Ценообразующий)
A48: 003 - Емкость приемно-дренажная для метанола V=40 м3
A49: 6 | B49: Установка дренажной емкости с погружным насосом объемом до 50 куб.м | G49: НЗ №849/пр Объекты газовой промышленности. 2023 г. Таблица 3.7. Объекты подготовки газа, газового конденсата (УКПГ, УППГ, УПТГ, ГС), п.39 A = 990.6 тыс. руб. Количество = 1 (объект) | K49: A * Количество * Ктек * Кст * K1 990 600 руб. * 1 * 1.56 * 0.6 * 0.7 | O49: =ROUND(990600 * 1 * 1.56 * 0.6 * 0.7, 2) -> 649041.12
B50: Коэффициенты
B51: Стадия: Рабочая документация | G51: Кст = 0.6
B52: инд.3кв.2026г.к 01.01.2022 на пр.раб. | G52: Ктек = 1.56 Письмо Минстроя России от 23.07.2026 №45358-ИФ/09
B53: Коэффициент на объём работ | G53: K1 = 0.7 (Ценообразующий)
A54: 005 - Резервуарный парк конденсата V=2х200м3
A55: 7 | B55: Товарно-сырьевой склад ГЖ и ЛВЖ из вертикальных стальных резервуаров объемом от 1 тыс.куб.м до 5 тыс.куб.м включительно | G55: НЗ №849/пр Объекты газовой промышленности. 2023 г. Таблица 3.7. Объекты подготовки газа, газового конденсата (УКПГ, УППГ, УПТГ, ГС), п.29 A = 532 тыс. руб.B = 618.795 тыс. руб.; Хзад = 1.4 (тыс.куб.м); Количество = 1 | K55: (A + B * Xзад) * Количество * Ктек * Кст * K1 (532 000 руб. + 618 795 руб. * 1.4) * 1 * 1.56 * 0.6 * 0.7 | O55: =ROUND((532000 + 618795 * 1.4) * 1 * 1.56 * 0.6 * 0.7, 2) -> 916174.68
B56: Коэффициенты
B57: Стадия: Рабочая документация | G57: Кст = 0.6
B58: инд.3кв.2026г.к 01.01.2022 на пр.раб. | G58: Ктек = 1.56 Письмо Минстроя России от 23.07.2026 №45358-ИФ/09
B59: Коэффициент на объём работ | G59: K1 = 0.7 (Ценообразующий)
A60: 006 - Ёмкость приёмно-дренажная для ДЭГа (ТЭГа) V=25м3
A61: 8 | B61: Установка дренажной емкости с погружным насосом объемом до 50 куб.м | G61: НЗ №849/пр Объекты газовой промышленности. 2023 г. Таблица 3.7. Объекты подготовки газа, газового конденсата (УКПГ, УППГ, УПТГ, ГС), п.39 A = 990.6 тыс. руб. Количество = 1 (объект) | K61: A * Количество * Ктек * Кст * K1 990 600 руб. * 1 * 1.56 * 0.6 * 0.7 | O61: =ROUND(990600 * 1 * 1.56 * 0.6 * 0.7, 2) -> 649041.12
B62: Коэффициенты
B63: Стадия: Рабочая документация | G63: Кст = 0.6
B64: инд.3кв.2026г.к 01.01.2022 на пр.раб. | G64: Ктек = 1.56 Письмо Минстроя России от 23.07.2026 №45358-ИФ/09
B65: Коэффициент на объём работ | G65: K1 = 0.7 (Ценообразующий)
A66: 007 - Автомобильная эстакада стояков налива конденсата
A67: 9 | B67: Сливно-наливные установки ГЖ и ЛВЖ, неавтоматизированные для налива в автоцистерны, количество стояков от 2 до 10 включительно | G67: НЗ №849/пр Объекты газовой промышленности. 2023 г. Таблица 3.7. Объекты подготовки газа, газового конденсата (УКПГ, УППГ, УПТГ, ГС), п.33 A = 952.6 тыс. руб.B = 21.23 тыс. руб.; Хзад = 2 (стояк); Количество = 1 | K67: (A + B * Xзад) * Количество * Ктек * Кст * K1 (952 600 руб. + 21 230 руб. * 2) * 1 * 1.56 * 0.6 * 0.7 | O67: =ROUND((952600 + 21230 * 2) * 1 * 1.56 * 0.6 * 0.7, 2) -> 651963.31
B68: Коэффициенты
B69: Стадия: Рабочая документация | G69: Кст = 0.6
B70: инд.3кв.2026г.к 01.01.2022 на пр.раб. | G70: Ктек = 1.56 Письмо Минстроя России от 23.07.2026 №45358-ИФ/09
B71: Коэффициент на объём работ | G71: K1 = 0.7 (Ценообразующий)
A72: 008 - Площадка манифольдной парка метанола
A73: 10 | B73: Установка переключающей арматуры производительностью от 10 млн.куб.м/сут до 60 млн.куб.м/сут включительно | G73: НЗ №849/пр Объекты газовой промышленности. 2023 г. Таблица 3.7. Объекты подготовки газа, газового конденсата (УКПГ, УППГ, УПТГ, ГС), п.1 A = 1 087.3 тыс. руб.B = 47.464 тыс. руб.; Xмин = 10; Хзад = 0.0007 (млн.куб.м/сут); Количество = 1 | K73: (A + B * (0.4 * Xмин + 0.6 * (Xмин / 2))) * Количество * Кпон * Ктек * Кст * K1 (1 087 300 руб. + 47 464 руб. * (0.4 * 10 + 0.6 * (10 / 2))) * 1 * 0.1 * 1.56 * 0.6 * 0.7 | O73: =ROUND((1087300 + 47464 * (0.4 * 10 + 0.6 * (10 / 2))) * 1 * 0.1 * 1.56 * 0.6 * 0.7, 2) -> 93008.78
B74: Коэффициенты
B75: Стадия: Рабочая документация | G75: Кст = 0.6
B76: инд.3кв.2026г.к 01.01.2022 на пр.раб. | G76: Ктек = 1.56 Письмо Минстроя России от 23.07.2026 №45358-ИФ/09
B77: К'пон = Xзад / (0.5 * Xмин) | G77: К'пон = 0.1 понижающий коэффициент, учитывающий разницу в трудоемкости работ по проектируемому объекту и объекту аналогу. (Методика 707/пр п.131(3)) (Ценообразующий)
B78: Коэффициент на объём работ | G78: K1 = 0.7 (Ценообразующий)
A79: 009 - Ёмкость приёмно-дренажная для конденсата V=40м3
A80: 11 | B80: Установка дренажной емкости с погружным насосом объемом до 50 куб.м | G80: НЗ №849/пр Объекты газовой промышленности. 2023 г. Таблица 3.7. Объекты подготовки газа, газового конденсата (УКПГ, УППГ, УПТГ, ГС), п.39 A = 990.6 тыс. руб. Количество = 1 (объект) | K80: A * Количество * Ктек * Кст * K1 990 600 руб. * 1 * 1.56 * 0.6 * 0.7 | O80: =ROUND(990600 * 1 * 1.56 * 0.6 * 0.7, 2) -> 649041.12
B81: Коэффициенты
B82: Стадия: Рабочая документация | G82: Кст = 0.6
B83: инд.3кв.2026г.к 01.01.2022 на пр.раб. | G83: Ктек = 1.56 Письмо Минстроя России от 23.07.2026 №45358-ИФ/09
B84: Коэффициент на объём работ | G84: K1 = 0.7 (Ценообразующий)
A85: 010 - Площадка свечи с гидрозатвором (метанол)
A86: 12 | B86: Установка факела вертикального производительностью от 7.5 млн.куб.м/сут до 25 млн.куб.м/сут включительно | G86: НЗ №849/пр Объекты газовой промышленности. 2023 г. Таблица 3.7. Объекты подготовки газа, газового конденсата (УКПГ, УППГ, УПТГ, ГС), п.23 A = 1 320.8 тыс. руб.B = 9.459 тыс. руб.; Xмин = 7.5; Хзад = 0.00528 (млн.куб.м/сут); Количество = 1 | K86: (A + B * (0.4 * Xмин + 0.6 * (Xмин / 2))) * Количество * Кпон * Ктек * Кст * K1 (1 320 800 руб. + 9 459 руб. * (0.4 * 7.5 + 0.6 * (7.5 / 2))) * 1 * 0.1 * 1.56 * 0.6 * 0.7 | O86: =ROUND((1320800 + 9459 * (0.4 * 7.5 + 0.6 * (7.5 / 2))) * 1 * 0.1 * 1.56 * 0.6 * 0.7, 2) -> 89792.52
B87: Коэффициенты
B88: Стадия: Рабочая документация | G88: Кст = 0.6
B89: инд.3кв.2026г.к 01.01.2022 на пр.раб. | G89: Ктек = 1.56 Письмо Минстроя России от 23.07.2026 №45358-ИФ/09
B90: К'пон = Xзад / (0.5 * Xмин) | G90: К'пон = 0.1 понижающий коэффициент, учитывающий разницу в трудоемкости работ по проектируемому объекту и объекту аналогу. (Методика 707/пр п.131(3)) (Ценообразующий)
B91: Коэффициент на объём работ | G91: K1 = 0.7 (Ценообразующий)
A92: 011 - Площадка свечи с гидрозатвором (конденсат)
A93: 13 | B93: Установка факельного сепаратора и сборника жидкости производительностью по сбрасываемому газу от 7.5 млн.куб.м/сут до 25 млн.куб.м/сут включительно | G93: НЗ №849/пр Объекты газовой промышленности. 2023 г. Таблица 3.7. Объекты подготовки газа, газового конденсата (УКПГ, УППГ, УПТГ, ГС), п.22 A = 415.6 тыс. руб.B = 32.687 тыс. руб.; Xмин = 7.5; Хзад = 0.005280 (млн.куб.м/сут); Количество = 1 | K93: (A + B * (0.4 * Xмин + 0.6 * (Xмин / 2))) * Количество * Кпон * Ктек * Кст * K1 (415 600 руб. + 32 687 руб. * (0.4 * 7.5 + 0.6 * (7.5 / 2))) * 1 * 0.1 * 1.56 * 0.6 * 0.7 | O93: =ROUND((415600 + 32687 * (0.4 * 7.5 + 0.6 * (7.5 / 2))) * 1 * 0.1 * 1.56 * 0.6 * 0.7, 2) -> 38473.79
B94: Коэффициенты
B95: Стадия: Рабочая документация | G95: Кст = 0.6
B96: инд.3кв.2026г.к 01.01.2022 на пр.раб. | G96: Ктек = 1.56 Письмо Минстроя России от 23.07.2026 №45358-ИФ/09
B97: К'пон = Xзад / (0.5 * Xмин) | G97: К'пон = 0.1 понижающий коэффициент, учитывающий разницу в трудоемкости работ по проектируемому объекту и объекту аналогу. (Методика 707/пр п.131(3)) (Ценообразующий)
B98: Коэффициент на объём работ | G98: K1 = 0.7 (Ценообразующий)
A99: 012 - Площадка манифольдной резервуарного парка конденсата
A100: 14 | B100: Установка по приему, травлению, крашению и перемешиванию метанола производительностью от 25 куб.м до 100 куб.м включительно | G100: НЗ №849/пр Объекты газовой промышленности. 2023 г. Таблица 3.7. Объекты подготовки газа, газового конденсата (УКПГ, УППГ, УПТГ, ГС), п.28 A = 51.6 тыс. руб.B = 33.004 тыс. руб.; Xмакс = 100; Хзад = 220 (куб.м); Количество = 1 | K100: (A + B * (0.4 * Xмакс + 0.6 * Xзад)) * Количество * Ктек * Кст * K1 (51 600 руб. + 33 004 руб. * (0.4 * 100 + 0.6 * 220)) * 1 * 1.56 * 0.6 * 0.7 | O100: =ROUND((51600 + 33004 * (0.4 * 100 + 0.6 * 220)) * 1 * 1.56 * 0.6 * 0.7, 2) -> 3753174.3
B101: Коэффициенты
B102: Стадия: Рабочая документация | G102: Кст = 0.6
B103: инд.3кв.2026г.к 01.01.2022 на пр.раб. | G103: Ктек = 1.56 Письмо Минстроя России от 23.07.2026 №45358-ИФ/09
B104: Коэффициент на объём работ | G104: K1 = 0.7 (Ценообразующий)
A105: 015 - Установка по производству азота
...

Sheet 3.4 ОВ++
E1: форма 2П, 707/пр
A3: Смета №3
A4: на проектные (изыскательские) работы
A6: Наименование предприятия, здания, сооружения, стадии проектирования, этапа, вида проектных или изыскательских работ | F6: =СВОД!B37 -> Отопление, вентиляция и кондиционирование
A8: Наименование проектной (изыскательской) организации | F8: =СВОД!D14 -> Определяется по итогам конкурентных процедур
A10: Наименование организации заказчика | F10: =СВОД!D16 -> ООО «Газпром проектирование»
A12: № пп | B12: Наименование объекта проектирования или вида проектных работ | G12: Наименование, номера глав, таблиц, параграфов и пунктов МНЗ на проектные работы | K12: Расчет стоимости | O12: Стоимость, руб.
A13: 1 | B13: 2 | G13: 3 | K13: 4 | O13: 5
A14: Этап 2 (Объекты на площадке КС 3)
A15: Поз. 220 Здание котельной
A16: 1 | B16: Автономные источники теплоснабжения (АИТ). Теплопроизводительность свыше 10 до 20 МВт. | G16: Газооборудование и газоснабжение промышленных предприятий, зданий и сооружений. 2015 г. Таблица 2. Автономные источники теплоснабжения (АИТ), п.4 A = 770.111 тыс.руб; B = 14.84 тыс.руб; Xзад = 20 (МВт); Количество = 1 | K16: (A + B * Xзад) * Количество * Ктек * Кст (770 111 руб. + 14 840 руб. * 20) * 1 * 7.22 * 0.6 | O16: =ROUND((770111 + 14840 * 20) * 1 * 7.22 * 0.6, 2) -> 4621858.5
B17: Коэффициенты
B18: Стадия: Рабочая документация | G18: Кст = 0.6
B19: инд.3кв.2026г.к 01.01.2001 на пр.раб. | G19: Ктек = 7.22 Письмо Минстроя России от 23.07.2026 №45358-ИФ/09
A20: 224 Механическая мастерская
A21: 2 | B21: Ремонтно-механическая мастерская (РММ) со складом оборудования, материалов и другие, аналогичные здания и сооружения объемом 5000 куб.м | G21: НЗ №849/пр Объекты газовой промышленности. 2023 г. Таблица 3.8. Объекты общетехнического назначения, п.4 A = 556.1 тыс. руб. Количество = 1 (объект) | K21: A * Количество * Ктек * Кст 556 100 руб. * 1 * 1.56 * 0.6 | O21: =ROUND(556100 * 1 * 1.56 * 0.6, 2) -> 520509.6
B22: Коэффициенты
B23: Стадия: Рабочая документация | G23: Кст = 0.6
B24: инд.3кв.2026г.к 01.01.2022 на пр.раб. | G24: Ктек = 1.56 Письмо Минстроя России от 23.07.2026 №45358-ИФ/09
A25: Поз. 226 Здание установки разделения и выветривания конденсата
A26: 3 | B26: Установка стабилизации конденсата по схеме выветривания с прямым огневым нагревом производительностью от 50 т/час до 200 т/час включительно по сырью | G26: НЗ №849/пр Объекты газовой промышленности. 2023 г. Таблица 3.7. Объекты подготовки газа, газового конденсата (УКПГ, УППГ, УПТГ, ГС), п.13 A = 4 367 тыс. руб.B = 13.577 тыс. руб.; Хзад = 50 (т/час по сырью); Количество = 1 | K26: (A + B * Xзад) * Количество * Ктек * Кст (4 367 000 руб. + 13 577 руб. * 50) * 1 * 1.56 * 0.6 | O26: =ROUND((4367000 + 13577 * 50) * 1 * 1.56 * 0.6, 2) -> 4722915.6
B27: Коэффициенты
B28: Стадия: Рабочая документация | G28: Кст = 0.6
B29: инд.3кв.2026г.к 01.01.2022 на пр.раб. | G29: Ктек = 1.56 Письмо Минстроя России от 23.07.2026 №45358-ИФ/09
A30: Этап 12 (Площадка РЛВЖ)
A31: 4212.012.Р.12/0.0004.ПРЛВЖ.000.31194.004-ТС
A32: 4 | B32: Внутриплощадочные инженерные сети. Тепло-, газо-, материалопроводы на эстакадах. Длина трассы до 0.1 км. | G32: Объекты нефтеперерабатывающей и нефтехимической промышленности. 2015 г. Таблица 8. Объекты подсобно-производственного, вспомогательного и общезаводского назначения, внутриплощадочные инженерные сети, схема планировочной организации земельного участка, п.2.3 A = 1 695.18 тыс.руб; B = 1 100.96 тыс.руб; Xмин = 0.1; Xзад = 0.015 (км); Количество = 1 | K32: (A + B * (0.4 * Xмин + 0.6 * (Xмин / 2))) * Количество * Кпон * Ктек * Кст * K1 (1 695 180 руб. + 1 100 960 руб. * (0.4 * 0.1 + 0.6 * (0.1 / 2))) * 1 * 0.3 * 7.22 * 0.6 * 0.5 * 0.7 | O32: =ROUND((1695180 + 1100960 * (0.4 * 0.1 + 0.6 * (0.1 / 2))) * 1 * 0.3 * 7.22 * 0.6 * 0.5 * 0.7, 2) -> 806124.36
B33: Коэффициенты
B34: Стадия: Рабочая документация | G34: Кст = 0.6
B35: инд.3кв.2026г.к 01.01.2001 на пр.раб. | G35: Ктек = 7.22 Письмо Минстроя России от 23.07.2026 №45358-ИФ/09
B36: К'пон = Xзад / (0.5 * Xмин) | G36: К'пон = 0.3 понижающий коэффициент, учитывающий разницу в трудоемкости работ по проектируемому объекту и объекту аналогу. (Методика 707/пр п.131(3)) (Ценообразующий)
B37: При проектировании трассы с 1-5 трубопроводами вводится коэффициент | G37: K1 = 0.5 Глава 2.5, п.2.5.6 (Ценообразующий)
B38: Исключенные разделы документации
B39: 1. Схема планировочной организации земельного участка | G39: 5%
B40: 2. Архитектурные решения. Конструктивные и объемно-планировочные решения | G40: 25%
A41: 4212.012.Р.12/0.0004.ПРЛВЖ.000.31122.006-ТС
A42: 5 | B42: Внутриплощадочные инженерные сети. Тепло-, газо-, материалопроводы на эстакадах. Длина трассы до 0.1 км. | G42: Объекты нефтеперерабатывающей и нефтехимической промышленности. 2015 г. Таблица 8. Объекты подсобно-производственного, вспомогательного и общезаводского назначения, внутриплощадочные инженерные сети, схема планировочной организации земельного участка, п.2.3 A = 1 695.18 тыс.руб; B = 1 100.96 тыс.руб; Xмин = 0.1; Xзад = 0.015 (км); Количество = 1 | K42: (A + B * (0.4 * Xмин + 0.6 * (Xмин / 2))) * Количество * Кпон * Ктек * Кст * K1 (1 695 180 руб. + 1 100 960 руб. * (0.4 * 0.1 + 0.6 * (0.1 / 2))) * 1 * 0.3 * 7.22 * 0.6 * 0.5 * 0.7 | O42: =ROUND((1695180 + 1100960 * (0.4 * 0.1 + 0.6 * (0.1 / 2))) * 1 * 0.3 * 7.22 * 0.6 * 0.5 * 0.7, 2) -> 806124.36
B43: Коэффициенты
B44: Стадия: Рабочая документация | G44: Кст = 0.6
B45: инд.3кв.2026г.к 01.01.2001 на пр.раб. | G45: Ктек = 7.22 Письмо Минстроя России от 23.07.2026 №45358-ИФ/09
B46: К'пон = Xзад / (0.5 * Xмин) | G46: К'пон = 0.3 понижающий коэффициент, учитывающий разницу в трудоемкости работ по проектируемому объекту и объекту аналогу. (Методика 707/пр п.131(3)) (Ценообразующий)
B47: При проектировании трассы с 1-5 трубопроводами вводится коэффициент | G47: K1 = 0.5 Глава 2.5, п.2.5.6 (Ценообразующий)
B48: Исключенные разделы документации
B49: 1. Схема планировочной организации земельного участка | G49: 5%
B50: 2. Архитектурные решения. Конструктивные и объемно-планировочные решения | G50: 25%
A51: 4212.00.Р.04.РЛВЖ.000.000.ТК.000
A52: 6 | B52: Внутриплощадочные инженерные сети. Тепло-, газо-, материалопроводы на эстакадах. Длина трассы свыше 0.1 до 0.3 км. | G52: Объекты нефтеперерабатывающей и нефтехимической промышленности. 2015 г. Таблица 8. Объекты подсобно-производственного, вспомогательного и общезаводского назначения, внутриплощадочные инженерные сети, схема планировочной организации земельного участка, п.2.4 A = 1 700.5 тыс.руб; B = 1 047.8 тыс.руб; Xзад = 0.3 (км); Количество = 1 | K52: (A + B * Xзад) * Количество * Ктек * Кст * K1 (1 700 500 руб. + 1 047 800 руб. * 0.3) * 1 * 7.22 * 0.6 * 0.5 * 0.7 | O52: =ROUND((1700500 + 1047800 * 0.3) * 1 * 7.22 * 0.6 * 0.5 * 0.7, 2) -> 3054900.4
B53: Коэффициенты
B54: Стадия: Рабочая документация | G54: Кст = 0.6
B55: инд.3кв.2026г.к 01.01.2001 на пр.раб. | G55: Ктек = 7.22 Письмо Минстроя России от 23.07.2026 №45358-ИФ/09
B56: При проектировании трассы с 1-5 трубопроводами вводится коэффициент | G56: K1 = 0.5 Глава 2.5, п.2.5.6 (Ценообразующий)
B57: Исключенные разделы документации
B58: 1. Схема планировочной организации земельного участка | G58: 5%
B59: 2. Архитектурные решения. Конструктивные и объемно-планировочные решения | G59: 25%
A60: Этап 15 (Установка огневой регенерации ДЭГа КС-3 Степновской СПХГ. 2 пусковой комплекс)
A61: 4212.008.Р.0/0.0004.КСПХГ.003.0211.200-ТС
A62: 7 | B62: Внутриплощадочные инженерные сети. Тепло-, газо-, материалопроводы на эстакадах. Длина трассы до 0.1 км. | G62: Объекты нефтеперерабатывающей и нефтехимической промышленности. 2015 г. Таблица 8. Объекты подсобно-производственного, вспомогательного и общезаводского назначения, внутриплощадочные инженерные сети, схема планировочной организации земельного участка, п.2.3 A = 1 695.18 тыс.руб; B = 1 100.96 тыс.руб; Xмин = 0.1; Xзад = 0.07 (км); Количество = 1 | K62: (A + B * (0.4 * Xмин + 0.6 * Xзад)) * Количество * Ктек * Кст * K1 (1 695 180 руб. + 1 100 960 руб. * (0.4 * 0.1 + 0.6 * 0.07)) * 1 * 7.22 * 0.6 * 0.5 * 0.7 | O62: =ROUND((1695180 + 1100960 * (0.4 * 0.1 + 0.6 * 0.07)) * 1 * 7.22 * 0.6 * 0.5 * 0.7, 2) -> 2707112.5
B63: Коэффициенты
B64: Стадия: Рабочая документация | G64: Кст = 0.6
B65: инд.3кв.2026г.к 01.01.2001 на пр.раб. | G65: Ктек = 7.22 Письмо Минстроя России от 23.07.2026 №45358-ИФ/09
B66: При проектировании трассы с 1-5 трубопроводами вводится коэффициент | G66: K1 = 0.5 Глава 2.5, п.2.5.6 (Ценообразующий)
B67: Исключенные разделы документации
B68: 1. Схема планировочной организации земельного участка | G68: 5%
B69: 2. Архитектурные решения. Конструктивные и объемно-планировочные решения | G69: 25%
A70: 4212.00.Р.04.КС.3.000.ТК.000
A71: 8 | B71: Внутриплощадочные инженерные сети. Тепло-, газо-, материалопроводы на эстакадах. Длина трассы свыше 0.5 до 0.85 км. | G71: Объекты нефтеперерабатывающей и нефтехимической промышленности. 2015 г. Таблица 8. Объекты подсобно-производственного, вспомогательного и общезаводского назначения, внутриплощадочные инженерные сети, схема планировочной организации земельного участка, п.2.6 A = 1 765.51 тыс.руб; B = 901.79 тыс.руб; Xзад = 0.55 (км); Количество = 1 | K71: (A + B * Xзад) * Количество * Ктек * Кст * K1 (1 765 510 руб. + 901 790 руб. * 0.55) * 1 * 7.22 * 0.6 * 0.5 * 0.7 | O71: =ROUND((1765510 + 901790 * 0.55) * 1 * 7.22 * 0.6 * 0.5 * 0.7, 2) -> 3428878
B72: Коэффициенты
B73: Стадия: Рабочая документация | G73: Кст = 0.6
B74: инд.3кв.2026г.к 01.01.2001 на пр.раб. | G74: Ктек = 7.22 Письмо Минстроя России от 23.07.2026 №45358-ИФ/09
B75: При проектировании трассы с 1-5 трубопроводами вводится коэффициент | G75: K1 = 0.5 Глава 2.5, п.2.5.6 (Ценообразующий)
B76: Исключенные разделы документации
B77: 1. Схема планировочной организации земельного участка | G77: 5%
B78: 2. Архитектурные решения. Конструктивные и объемно-планировочные решения | G78: 25%
A79: 4212.00.Р.04.КС.3.000.ТК1.000
A80: 9 | B80: Внутриплощадочные инженерные сети. Тепло-, газо-, материалопроводы на эстакадах. Длина трассы свыше 0.3 до 0.5 км. | G80: Объекты нефтеперерабатывающей и нефтехимической промышленности. 2015 г. Таблица 8. Объекты подсобно-производственного, вспомогательного и общезаводского назначения, внутриплощадочные инженерные сети, схема планировочной организации земельного участка, п.2.5 A = 1 712.5 тыс.руб; B = 1 007.8 тыс.руб; Xзад = 0.36 (км); Количество = 1 | K80: (A + B * Xзад) * Количество * Ктек * Кст * K1 (1 712 500 руб. + 1 007 800 руб. * 0.36) * 1 * 7.22 * 0.6 * 0.5 * 0.7 | O80: =ROUND((1712500 + 1007800 * 0.36) * 1 * 7.22 * 0.6 * 0.5 * 0.7, 2) -> 3146582
B81: Коэффициенты
B82: Стадия: Рабочая документация | G82: Кст = 0.6
B83: инд.3кв.2026г.к 01.01.2001 на пр.раб. | G83: Ктек = 7.22 Письмо Минстроя России от 23.07.2026 №45358-ИФ/09
B84: При проектировании трассы с 1-5 трубопроводами вводится коэффициент | G84: K1 = 0.5 Глава 2.5, п.2.5.6 (Ценообразующий)
B85: Исключенные разделы документации
B86: 1. Схема планировочной организации земельного участка | G86: 5%
B87: 2. Архитектурные решения. Конструктивные и объемно-планировочные решения | G87: 25%
A88: 4212.00.Р.04.КС.3.000.ТК3.000
A89: 10 | B89: Внутриплощадочные инженерные сети. Тепло-, газо-, материалопроводы на эстакадах. Длина трассы свыше 0.85 до 4 км. | G89: Объекты нефтеперерабатывающей и нефтехимической промышленности. 2015 г. Таблица 8. Объекты подсобно-производственного, вспомогательного и общезаводского назначения, внутриплощадочные инженерные сети, схема планировочной организации земельного участка, п.2.7 A = 1 959.98 тыс.руб; B = 673 тыс.руб; Xзад = 2.2 (км); Количество = 1 | K89: (A + B * Xзад) * Количество * Ктек * Кст * K1 (1 959 980 руб. + 673 000 руб. * 2.2) * 1 * 7.22 * 0.6 * 0.5 * 0.7 | O89: =ROUND((1959980 + 673000 * 2.2) * 1 * 7.22 * 0.6 * 0.5 * 0.7, 2) -> 5216607.4
B90: Коэффициенты
B91: Стадия: Рабочая документация | G91: Кст = 0.6
B92: инд.3кв.2026г.к 01.01.2001 на пр.раб. | G92: Ктек = 7.22 Письмо Минстроя России от 23.07.2026 №45358-ИФ/09
B93: При проектировании трассы с 1-5 трубопроводами вводится коэффициент | G93: K1 = 0.5 Глава 2.5, п.2.5.6 (Ценообразующий)
B94: Исключенные разделы документации
B95: 1. Схема планировочной организации земельного участка | G95: 5%
B96: 2. Архитектурные решения. Конструктивные и объемно-планировочные решения | G96: 25%
A97: Этап 16 (Площадка печей подогревателей газа Степновской СПХГ)
A98: 4212.012.Р.16/0.0004.ПлППГ.000.35704.001-ТС
A99: 11 | B99: Внутриплощадочные инженерные сети. Тепло-, газо-, материалопроводы на эстакадах. Длина трассы свыше 0.5 до 0.85 км. | G99: Объекты нефтеперерабатывающей и нефтехимической промышленности. 2015 г. Таблица 8. Объекты подсобно-производственного, вспомогательного и общезаводского назначения, внутриплощадочные инженерные сети, схема планировочной организации земельного участка, п.2.6 A = 1 765.51 тыс.руб; B = 901.79 тыс.руб; Xзад = 0.6 (км); Количество = 1 | K99: (A + B * Xзад) * Количество * Ктек * Кст * K1 (1 765 510 руб. + 901 790 руб. * 0.6) * 1 * 7.22 * 0.6 * 0.8 * 0.7 | O99: =ROUND((1765510 + 901790 * 0.6) * 1 * 7.22 * 0.6 * 0.8 * 0.7, 2) -> 5595588.3
B100: Коэффициенты
B101: Стадия: Рабочая документация | G101: Кст = 0.6
B102: инд.3кв.2026г.к 01.01.2001 на пр.раб. | G102: Ктек = 7.22 Письмо Минстроя России от 23.07.2026 №45358-ИФ/09
B103: При проектировании трассы с трубопроводами от 6 до 25 вводится коэффициент | G103: K1 = 0.8 Глава 2.5, п.2.5.6 (Ценообразующий)
B104: Исключенные разделы документации
B105: 1. Схема планировочной организации земельного участка | G105: 5%
...

Sheet 3.5.1 АСУТП этап12
B1: 5
B4: Смета №3.5.1
B5: Этап 12 (Площадка РЛВЖ) АСУ ТП
B6: Наименование объекта | G6: Сети внутриплощадочные 001 - Резервуарный парк метанола V=2х700 м3 002 - Здание насосной парков метанола и ДЭГа (ТЭГа) 003 - Емкость приемно-дренажная для метанола V=40 м3 004 - Площадка расходных ёмкостей ДЭГа (ТЭГа) V=2х50м3 005 - Резервуарный парк конденсата V=2х200м3 006 - Ёмкость приёмно-дренажная для ДЭГа (ТЭГа) V=25м3 008 - Площадка манифольдной парка метанола 009 - Ёмкость приёмно-дренажная для конденсата V=40м3 010 - Площадка свечи с гидрозатвором (метанол) 011 - Площадка свечи с гидрозатвором (конденсат) 012 - Площадка манифольдной резервуарного парка конденсата 021 - Резервуар, емкость расходная дизельного топлива
B8: Стадия | G8: Рабочая документация
B10: Наименование организации Заказчика
B11: Наименование проектной организации | G11: Определяется по итогам конкурентных процедур
B13: Смета составлена на основании "СБЦ на проектные работы в строительстве "Автоматизированные системы управления технологическими процессами (АСУТП)" (2016г.)
B15: 1. Краткая характеристика объекта автоматизации:
B16: Новое строительство
B17: Новое строительство
B18: Реконструкция, модернизация, тех. перевооружение
B19: Требование на разработку ТЗ к созданию АСУ ТП: | H19: Нет
H20: Да
H21: Нет
B22: Требуемые части документации АСУ ТП:
D23: ОР | E23: ОО | F23: ИО | G23: ТО | H23: МО | I23: ПО
D24: Да | E24: Нет | F24: Нет | G24: Да | H24: Нет | I24: Нет
D25: Да | E25: Да | F25: Да | G25: Да | H25: Да | I25: Да
D26: Нет | E26: Нет | F26: Нет | G26: Нет | H26: Нет | I26: Нет
B27: 2. Исходные данные:
B28: Трудоемкость разработки ТЗ на создание АСУ ТП
B29: Основные факторы, определяющие трудоемкость разработки | M29: Количество баллов
B30: № пп | C30: Фактор | E30: Наименование | H30: Определение | M30: ТЗ
B31: 1 | C31: Ф1 | E31: Степень научно-технической новизны (ТОУ) | H31: I степень - ТОУ имеет действующие аналоги в России и, возможно за рубежом | M31: =IF(H19="Да",SUMIF($H32:$L35,$H31,M32:N35),0) -> 0
B32: 1.1 | H32: I степень - ТОУ имеет действующие аналоги в России и, возможно за рубежом | M32: 1
B33: 1.2 | H33: II степень - ТОУ имеет действующие аналоги только за рубежом | M33: 2
B34: 1.3 | H34: III степень - ни с конструкторской, ни с технологической точек зрения ТОУ не является принципиально новым объектом, но действующих аналогов не имеет | M34: 4
B35: 1.4 | H35: IV степень - с конструкторской и (или) технологической точек зрения ТОУ является принципиально новым объектом | M35: 8
B36: 2 | C36: Ф2 | E36: Характер протекания управляемого технологического процесса во времени | H36: Непрерывный (с длительным поддержанием режимов, близких к установившимся, и практически безостановочной подачей сырья и реагентов) | M36: =IF(H19="Да",SUMIF($H37:$L42,$H36,M37:N42),0) -> 0
B37: 2.1 | H37: Непрерывный (с длительным поддержанием режимов, близких к установившимся, и практически безостановочной подачей сырья и реагентов) | M37: 1
B38: 2.2 | H38: Полунепрерывный (непрерывный, с существенными для управления переходными режимами, вызванными либо добавками (заменами) сырья или реагентов, либо выдачей продукции) | M38: 2
B39: 2.3 | H39: Непрерывно-дискретный - I (сочетающий непрерывные и прерывистые режимы на различных стадиях процесса) | M39: 4
B40: 2.4 | H40: Непрерывно-дискретный - II (сочетающий непрерывные и прерывистые режимы с малой длительностью непрерывных режимов в аварийных условиях) | M40: 5
B41: 2.5 | H41: Циклический (прерывистый, с существенной для управления длительностью интервалов непрерывного функционирования и циклическим следованием интервалов с различными режимами) | M41: 4
B42: 2.6 | H42: Дискретный (прерывистый, с малой, несущественной для управления, длительностью непрерывных технологических операций) | M42: 3
B43: 3 | C43: Ф3 | E43: Количество технологических операций, выполняемых на ТОУ | H43: свыше 10 до 20 | M43: =IF(H19="Да",SUMIF($H44:$L51,$H43,M44:N51),0) -> 0
B44: 3.1 | H44: до 5 | M44: 1
B45: 3.2 | H45: свыше 5 до 10 | M45: 2
B46: 3.3 | H46: свыше 10 до 20 | M46: 4
B47: 3.4 | H47: свыше 20 до 35 | M47: 5
B48: 3.5 | H48: свыше 35 до 50 | M48: 7
B49: 3.6 | H49: свыше 50 до 70 | M49: 9
B50: 3.7 | H50: свыше 70 до 100 | M50: 10
B51: 3.8 | H51: за каждые 50 свыше 100 | M51: 11
B52: 4 | C52: Ф4 | E52: Количество переменных, характеризующих ТОУ | H52: свыше 470 до 600 | M52: =IF(H19="Да",SUMIF($H53:$L66,$H52,M53:N66),0) -> 0
B53: 4.1 | H53: до 20 | M53: 1
B54: 4.2 | H54: свыше 20 до 50 | M54: 2
B55: 4.3 | H55: свыше 50 до 100 | M55: 3
B56: 4.4 | H56: свыше 100 до 170 | M56: 4
B57: 4.5 | H57: свыше 170 до 250 | M57: 5
B58: 4.6 | H58: свыше 250 до 350 | M58: 6
B59: 4.7 | H59: свыше 350 до 470 | M59: 7
B60: 4.8 | H60: свыше 470 до 600 | M60: 8
B61: 4.9 | H61: свыше 600 до 800 | M61: 9
B62: 4.10 | H62: свыше 800 до 1000 | M62: 10
B63: 4.11 | H63: свыше 1000 до 1300 | M63: 11
B64: 4.12 | H64: свыше 1300 до 1600 | M64: 12
... B66: 4.14 | H66: за каждые 500 свыше 2000 | M66: 14
B67: 5 | L67: ИТОГО (ƩБч): | M67: =M31+M36+M43+M52 -> 0
B68: Трудоемкость разработки документации на АСУ ТП
B69: Основные факторы, определяющие трудоемкость разработки | M69: Количество баллов для частей проектной документации (Бч)
B70: № пп | C70: Фактор | E70: Наименование | H70: Определение | M70: ОР | N70: ОО | O70: ИО | P70: ТО | Q70: МО | R70: ПО
B71: 1 | C71: Ф2 | E71: Характер протекания управляемого технологического процесса во времени | H71: Непрерывный (с длительным поддержанием режимов, близких к установившимся, и практически безостановочной подачей сырья и реагентов) | M71: =IF(D24="Да",SUMIF($H72:$L77,$H71,M72:M77),0) -> 1 | N71: =IF(E24="Да",SUMIF($H72:$L77,$H71,N72:N77),0) -> 0 | O71: =IF(F24="Да",SUMIF($H72:$L77,$H71,O72:O77),0) -> 0 | P71: =IF(G24="Да",SUMIF($H72:$L77,$H71,P72:P77),0) -> 1 | Q71: =IF(H24="Да",SUMIF($H72:$L77,$H71,Q72:Q77),0) -> 0 | R71: =IF(I24="Да",SUMIF($H72:$L77,$H71,R72:R77),0) -> 0
B72: 1.1 | H72: Непрерывный (с длительным поддержанием режимов, близких к установившимся, и практически безостановочной подачей сырья и реагентов) | M72: 1 | N72: 1 | O72: 1 | P72: 1 | Q72: 1 | R72: 1
B73: 1.2 | H73: Полунепрерывный (непрерывный, с существенными для управления переходными режимами, вызванными либо добавками (заменами) сырья или реагентов, либо выдачей продукции) | M73: 2 | N73: 1 | O73: 2 | P73: 1 | Q73: 2 | R73: 2
B74: 1.3 | H74: Непрерывно-дискретный - I (сочетающий непрерывные и прерывистые режимы на различных стадиях процесса) | M74: 3 | N74: 3 | O74: 3 | P74: 3 | Q74: 3 | R74: 3
B75: 1.4 | H75: Непрерывно-дискретный - II (сочетающий непрерывные и прерывистые режимы с малой длительностью непрерывных режимов в аварийных условиях) | M75: 4 | N75: 3 | O75: 4 | P75: 3 | Q75: 4 | R75: 4
B76: 1.5 | H76: Циклический (прерывистый, с существенной для управления длительностью интервалов непрерывного функционирования и циклическим следованием интервалов с различными режимами) | M76: 3 | N76: 2 | O76: 3 | P76: 2 | Q76: 3 | R76: 3
B77: 1.6 | H77: Дискретный (прерывистый, с малой, несущественной для управления, длительностью непрерывных технологических операций) | M77: 2 | N77: 2 | O77: 2 | P77: 2 | Q77: 3 | R77: 3
B78: 2 | C78: Ф5 | E78: Количество технологических операций, контролируемых или управляемых АСУ ТП | H78: свыше 10 до 20 | M78: =IF(D24="Да",SUMIF($H79:$L85,$H78,M79:M85),0) -> 3 | N78: =IF(E24="Да",SUMIF($H79:$L85,$H78,N79:N85),0) -> 0 | O78: =IF(F24="Да",SUMIF($H79:$L85,$H78,O79:O85),0) -> 0 | P78: =IF(G24="Да",SUMIF($H79:$L85,$H78,P79:P85),0) -> 2 | Q78: =IF(H24="Да",SUMIF($H79:$L85,$H78,Q79:Q85),0) -> 0 | R78: =IF(I24="Да",SUMIF($H79:$L85,$H78,R79:R85),0) -> 0
B79: 2.1 | E79: За каждые 50 свыше 100 начисляется еще по баллу | H79: до 5 | M79: 1 | N79: 1 | O79: 1 | P79: 1 | Q79: 1 | R79: 1
B80: 2.2 | H80: свыше 5 до 10 | M80: 2 | N80: 2 | O80: 2 | P80: 2 | Q80: 2 | R80: 2
B81: 2.3 | H81: свыше 10 до 20 | M81: 3 | N81: 2 | O81: 3 | P81: 2 | Q81: 3 | R81: 3
B82: 2.4 | H82: свыше 20 до 35 | M82: 4 | N82: 3 | O82: 4 | P82: 3 | Q82: 4 | R82: 4
B83: 2.5 | H83: свыше 35 до 50 | M83: 5 | N83: 3 | O83: 5 | P83: 3 | Q83: 5 | R83: 5
B84: 2.6 | H84: свыше 50 до 70 | M84: 6 | N84: 4 | O84: 6 | P84: 4 | Q84: 6 | R84: 6
B85: 2.7 | H85: свыше 70 до 100 | M85: 7 | N85: 5 | O85: 7 | P85: 5 | Q85: 7 | R85: 7
B86: 3 | C86: Ф6 | E86: Степень развитости информационных функций АСУ ТП | H86: III степень - косвенное измерение (вычисление) отдельных комплексных показателей функционирования ТОУ | M86: =IF(D24="Да",SUMIF($H87:$L90,$H86,M87:M90),0) -> 6 | N86: =IF(E24="Да",SUMIF($H87:$L90,$H86,N87:N90),0) -> 0 | O86: =IF(F24="Да",SUMIF($H87:$L90,$H86,O87:O90),0) -> 0 | P86: =IF(G24="Да",SUMIF($H87:$L90,$H86,P87:P90),0) -> 5 | Q86: =IF(H24="Да",SUMIF($H87:$L90,$H86,Q87:Q90),0) -> 0 | R86: =IF(I24="Да",SUMIF($H87:$L90,$H86,R87:R90),0) -> 0
B87: 3.1 | H87: I степень - параллельные контроль и измерение параметров состояния ТОУ | M87: 1 | N87: 1 | O87: 1 | P87: 1 | Q87: 1 | R87: 1
B88: 3.2 | H88: II степень - централизованный контроль и измерение параметров состояния ТОУ | M88: 3 | N88: 2 | O88: 3 | P88: 3 | Q88: 3 | R88: 3
B89: 3.3 | H89: III степень - косвенное измерение (вычисление) отдельных комплексных показателей функционирования ТОУ | M89: 6 | N89: 2 | O89: 6 | P89: 5 | Q89: 6 | R89: 6
B90: 3.4 | H90: IV степень - анализ и обобщенная оценка состояния процесса в целом по его модели (распознавание ситуаций, диагностика аварийных состояний, поиск "узкого места", прогноз хода процесса) | M90: 9 | N90: 3 | O90: 9 | P90: 8 | Q90: 9 | R90: 9
B91: 4 | C91: Ф7 | E91: Степень развитости управляющих функций АСУ ТП | H91: III степень - многосвязное автоматическое регулирование или автоматическое программное логическое управление по циклу с разветвлениями | M91: =IF(D24="Да",SUMIF($H92:$L98,$H91,M92:M98),0) -> 5 | N91: =IF(E24="Да",SUMIF($H92:$L98,$H91,N92:N98),0) -> 0 | O91: =IF(F24="Да",SUMIF($H92:$L98,$H91,O92:O98),0) -> 0 | P91: =IF(G24="Да",SUMIF($H92:$L98,$H91,P92:P98),0) -> 5 | Q91: =IF(H24="Да",SUMIF($H92:$L98,$H91,Q92:Q98),0) -> 0 | R91: =IF(I24="Да",SUMIF($H92:$L98,$H91,R92:R98),0) -> 0
B92: 7.22 | H92: I степень - одноконтурное автоматическое регулирование или автоматическое однотактное логическое управление (переключения, блокировки и тому подобное) | M92: 1 | N92: 1 | O92: 1 | P92: 1 | Q92: 1 | R92: 1
B93: 7.2 | H93: II степень - каскадное и (или) программное автоматическое регулирование или автоматическое программное логическое управление по "жесткому" циклу | M93: 3 | N93: 2 | O93: 3 | P93: 3 | Q93: 3 | R93: 3
B94: 7.3 | H94: III степень - многосвязное автоматическое регулирование или автоматическое программное логическое управление по циклу с разветвлениями | M94: 5 | N94: 2 | O94: 5 | P94: 5 | Q94: 5 | R94: 5
B95: 7.4 | H95: IV степень - оптимальное управление установившимися режимами (в статике) | M95: 6 | N95: 3 | O95: 7 | P95: 7 | Q95: 7 | R95: 7
B96: 7.5 | H96: V степень - оптимальное управление переходными процессами или процессом в целом (оптимизация в динамике) | M96: 8 | N96: 4 | O96: 10 | P96: 9 | Q96: 11 | R96: 11
B97: 7.6 | H97: VI степень - оптимальное управление быстропротекающими переходными процессами в аварийных условиях | M97: 9 | N97: 4 | O97: 11 | P97: 10 | Q97: 13 | R97: 13
B98: 7.7 | H98: VII степень - оптимальное управление с адаптацией (самообучением и изменением алгоритмов и параметров системы) | M98: 10 | N98: 5 | O98: 12 | P98: 11 | Q98: 14 | R98: 14
B99: 5 | C99: Ф8 | E99: Режим выполнения управляющих фукций АСУ ТП | H99: Автоматический режим прямого (непосредственного) цифрового (или аналого-цифрового) управления | M99: =IF(D24="Да",SUMIF($H100:$L104,$H99,M100:M104),0) -> 5 | N99: =IF(E24="Да",SUMIF($H100:$L104,$H99,N100:N104),0) -> 0 | O99: =IF(F24="Да",SUMIF($H100:$L104,$H99,O100:O104),0) -> 0 | P99: =IF(G24="Да",SUMIF($H100:$L104,$H99,P100:P104),0) -> 7 | Q99: =IF(H24="Да",SUMIF($H100:$L104,$H99,Q100:Q104),0) -> 0 | R99: =IF(I24="Да",SUMIF($H100:$L104,$H99,R100:R104),0) -> 0
B100: 5.1 | H100: Автоматизированный "ручной" режим | M100: 1 | N100: 1 | O100: 1 | P100: 1 | Q100: 1 | R100: 1
B101: 5.2 | H101: Автоматизированный режим "советчика" | M101: 1 | N101: 1 | O101: 2 | P101: 1 | Q101: 2 | R101: 2
B102: 5.3 | H102: Автоматизированный диалоговый режим | M102: 2 | N102: 2 | O102: 2 | P102: 2 | Q102: 3 | R102: 3
B103: 5.4 | H103: Автоматический режим косвенного управления | M103: 3 | N103: 2 | O103: 3 | P103: 4 | Q103: 4 | R103: 4
B104: 5.5 | H104: Автоматический режим прямого (непосредственного) цифрового (или аналого-цифрового) управления | M104: 5 | N104: 3 | O104: 5 | P104: 7 | Q104: 7 | R104: 7
B105: 6 | C105: Ф9 | E105: Количество переменных, измеряемых, контролируемых и регистрируемых АСУ ТП | H105: свыше 250 до 350 | M105: =IF(D24="Да",SUMIF($H106:$L119,$H105,M106:M119),0) -> 4 | N105: =IF(E24="Да",SUMIF($H106:$L119,$H105,N106:N119),0) -> 0 | O105: =IF(F24="Да",SUMIF($H106:$L119,$H105,O106:O119),0) -> 0 | P105: =IF(G24="Да",SUMIF($H106:$L119,$H105,P106:P119),0) -> 6 | Q105: =IF(H24="Да",SUMIF($H106:$L119,$H105,Q106:Q119),0) -> 0 | R105: =IF(I24="Да",SUMIF($H106:$L119,$H105,R106:R119),0) -> 0
B106: 6.1 | H106: до 20 | M106: 1 | N106: 1 | O106: 1 | P106: 1 | Q106: 1 | R106: 1
B107: 6.2 | H107: свыше 20 до 50 | M107: 2 | N107: 1 | O107: 2 | P107: 2 | Q107: 2 | R107: 2
...

Sheet 3.5.2 АСУТП этап15
B1: 5
B4: Смета №3.5.2
B5: Этап 15 (Установка огневой регенерации ДЭГа КС-3 Степновской СПХГ. 2 пусковой комплекс) АСУ ТП
B6: Наименование объекта | G6: Сети внутриплощадочные 234 - Емкость аварийная дренажная для ДЭГа (ТЭГа) V=40м3
B8: Стадия | G8: Рабочая документация
B10: Наименование организации Заказчика
B11: Наименование проектной организации | G11: =СВОД!D14 -> Определяется по итогам конкурентных процедур
B13: Смета составлена на основании "СБЦ на проектные работы в строительстве "Автоматизированные системы управления технологическими процессами (АСУТП)" (2016г.)
B15: 1. Краткая характеристика объекта автоматизации:
B16: Новое строительство
B17: Новое строительство
B18: Реконструкция, модернизация, тех. перевооружение
B19: Требование на разработку ТЗ к созданию АСУ ТП: | H19: Нет
H20: Да
H21: Нет
B22: Требуемые части документации АСУ ТП:
D23: ОР | E23: ОО | F23: ИО | G23: ТО | H23: МО | I23: ПО
D24: Да | E24: Нет | F24: Нет | G24: Да | H24: Нет | I24: Нет
D25: Да | E25: Да | F25: Да | G25: Да | H25: Да | I25: Да
D26: Нет | E26: Нет | F26: Нет | G26: Нет | H26: Нет | I26: Нет
B27: 2. Исходные данные:
B28: Трудоемкость разработки ТЗ на создание АСУ ТП
B29: Основные факторы, определяющие трудоемкость разработки | M29: Количество баллов
B30: № пп | C30: Фактор | E30: Наименование | H30: Определение | M30: ТЗ
B31: 1 | C31: Ф1 | E31: Степень научно-технической новизны (ТОУ) | H31: I степень - ТОУ имеет действующие аналоги в России и, возможно за рубежом | M31: =IF(H19="Да",SUMIF($H32:$L35,$H31,M32:N35),0) -> 0
B32: 1.1 | H32: I степень - ТОУ имеет действующие аналоги в России и, возможно за рубежом | M32: 1
B33: 1.2 | H33: II степень - ТОУ имеет действующие аналоги только за рубежом | M33: 2
B34: 1.3 | H34: III степень - ни с конструкторской, ни с технологической точек зрения ТОУ не является принципиально новым объектом, но действующих аналогов не имеет | M34: 4
B35: 1.4 | H35: IV степень - с конструкторской и (или) технологической точек зрения ТОУ является принципиально новым объектом | M35: 8
